Workbook
Name Asservissement: PARAM!$A$44:$A$46
Name CODE_SANDRE_3: PARAM!$I$4:$I$19
Name CODE_SANDRE_SCL: PARAM!$F$4:$F$7
Name CODE_SANDRE_STEU: PARAM!$E$4:$E$19
Name conditions_meteo: PARAM!$F$44:$F$46
Name Conformité: PARAM!$B$44:$B$48
Name Eq_h_controle: PARAM!$C$30:$C$32
Name EQUIPEMENT_PREL: PARAM!$B$4:$B$6
Name EQUIPEMENT_Q: PARAM!$A$4:$A$15
Name Frequence: PARAM!$E$44:$E$51
Name LISTE_1: PARAM!$A$21:$A$23
Name LISTE_2: PARAM!$B$21:$B$24
Name LISTE_3: PARAM!$C$21:$C$25
Name LISTE_4: PARAM!$D$21:$D$27
Name LISTE_5: PARAM!$F$21:$F$25
Name LISTE_6: PARAM!$G$21
Name LISTE_7: PARAM!$H$21:$H$23
Name listeDebimetres: INDIRECT("Descriptif!"&ADDRESS(Descriptif!$AD$2,COLUMN(Descriptif!$AF$1))):INDEX(INDIRECT("Descriptif!AF"&Descriptif!$AD$2&":AF101"),COUNTIF(INDIRECT("Descriptif!AF"&Descriptif!$AD$2&":AF101"),"?*"))
Name listePluviometres: INDIRECT("Descriptif!"&ADDRESS(Descriptif!$AD$2,COLUMN(Descriptif!$AJ$1))):INDEX(INDIRECT("Descriptif!AJ"&Descriptif!$AD$2&":AJ101"),COUNTIF(INDIRECT("Descriptif!AJ"&Descriptif!$AD$2&":AJ101"),"?*"))
Name listePreleveurs: INDIRECT("Descriptif!"&ADDRESS(Descriptif!$AD$2,COLUMN(Descriptif!$AD$1))):INDEX(INDIRECT("Descriptif!AD"&Descriptif!$AD$2&":AD101"),COUNTIF(INDIRECT("Descriptif!AD"&Descriptif!$AD$2&":AD101"),"?*"))
Name listeSondeTemp: INDIRECT("Descriptif!"&ADDRESS(Descriptif!$AD$2,COLUMN(Descriptif!$AH$1))):INDEX(INDIRECT("Descriptif!AH"&Descriptif!$AD$2&":AH101"),COUNTIF(INDIRECT("Descriptif!AH"&Descriptif!$AD$2&":AH101"),"?*"))
Name Méthode: PARAM!$A$55:$A$57
Name Montage_sonde: PARAM!$G$44:$G$47
Name PLUVIO_SCL: Descriptif!$E$24:$E$24
Name Print_Area: LimitequantificationSDE!$A$1:$F$21
Name Print_Area: 'SeuilsComparaison-EMT'!$A$1:$K$29
Name Q_en_charge: PARAM!$A$30:$A$33
Name Q_en_charge_boues: PARAM!$E$30
Name Q_Gravitaire: PARAM!$B$30:$B$39
Name Satisfaction: PARAM!$D$44:$D$46
Name Type_capteur: PARAM!$C$44:$C$48
Name Type_equipement: PARAM!$C$4:$C$7
Name Type_reseau: PARAM!$D$30:$D$32
Name TypeDeMesure: PARAM!$B$55:$B$56

Sheet Descriptif
AC1: Ne rien mettre dans cette colonne | AD1: Ne rien mettre dans cette colonne | AE1: Ne rien mettre dans cette colonne | AF1: Ne rien mettre dans cette colonne | AG1: Ne rien mettre dans cette colonne | AH1: Ne rien mettre dans cette colonne | AI1: Ne rien mettre dans cette colonne | AJ1: Ne rien mettre dans cette colonne
C2: CONTRÔLE ANNUEL DES DISPOSITIFS D'AUTOSURVEILLANCE DES SYSTÈMES D'ASSAINISSEMENT COLLECTIF | AC2: début données sys collect | AD2: =ROW(E13)+1 -> 14 | AE2: fin données sys collect | AF2: =ROW(D15)-1 -> 14 | AG2: pluvio SCL | AH2: =ROW(E22)+1 -> 23 | AI2: =ROW(D24)-1 -> 23
C3: NOM DU SYSTÈME D'ASSAINISSEMENT : | I3: NOM DU SYSTÈME DE TRAITEMENT : | N3: NOM DU SYSTÈME DE COLLECTE : | S3: NOM DE L'ORGANISME DE CONTRÔLE : | AC3: début données station | AD3: =ROW(E33)+1 -> 34 | AE3: fin données station | AF3: =ROW(D35)-1 -> 34 | AG3: pluvio STEU | AH3: =ROW(E42)+1 -> 43 | AI3: =ROW(D44)-1 -> 43
C4: CODE SANDRE DE L'AGGLOMÉRATION : | I4: CODE SANDRE DE LA STATION : | N4: CODE SANDRE DU RÉSEAU : | S4: NOM(S) DU(ES) CONTROLEUR(S) :
C5: MAITRE D'OUVRAGE DE LA STATION : | I5: TYPE DE TRAITEMENT : | N5: TYPE DE RÉSEAU : | S5: DATE(S) D'INTERVENTION :
C6: EXPLOITANT DE LA STATION : | I6: CAPACITÉ DE LA STATION : | N6: EXPLOITANT DU RÉSEAU : | S6: CONDITION(S) MÉTÉO :
C8: SYSTÈME DE COLLECTE
D9: Remarques: | E9: Les estimations et les apports par camion ne rentrent pas dans le CDA
D10: Liste des équipements du système de collecte pour chaque point d’autosurveillance
H12: Les informations de codification sont à reprendre du MAS
E13: Actif | F13: Lien vers l'onglet de l'équipement | H13: Point réglementaire | I13: Localisation (cf. MAS) | J13: Code du point (cf MAS) | K13: Libellé de l'équipement | M13: Type d'équipement | O13: Type de matériel | Q13: Pluviométre de référence | S13: Certaines informations d'un équipement ne sont pas modifiables. Au besoin il est préférable de supprimer et de recréer l'équipement. | AC13: Liste préleveurs | AE13: Liste débimètres | AG13: Liste thermo | AI13: Liste pluvio
AB14: =ROW(A14)- $AD$2 +1 -> 1 | AC14: =IF(AND($E14="Oui",$M14="Préleveur"),$F14,"") | AD14: {=IFERROR(INDEX($AC$14:$AC$99,SMALL(IF($AC$14:$AC$99<>"",ROW($AC$14:$AC$99)-ROW(INDIRECT("$AC$14"))+1),ROW(INDIRECT("A" & AB14 ) ))),"")} | AE14: =IF(AND($E14="Oui",LEFT($M14,10) ="Débitmètre"),$F14,"") | AF14: {=IFERROR(INDEX($AE$14:$AE$99,SMALL(IF($AE$14:$AE$99<>"",ROW($AE$14:$AE$99)-ROW(INDIRECT("$AE$14"))+1),ROW(INDIRECT("A" & AB14 ) ))),"")} | AG14: =IF(AND($E14="Oui",LEFT($M14,5) ="Sonde"),$F14,"") | AH14: {=IFERROR(INDEX($AG$14:$AG$99,SMALL(IF($AG$14:$AG$99<>"",ROW($AG$14:$AG$99)-ROW(INDIRECT("$AG$14"))+1),ROW(INDIRECT("A" & AB14 ) ))),"")} | AI14: =IF(AND($E14="Oui", $F14 <> "", $M14 = ""),$F14,"") | AJ14: {=IFERROR(INDEX($AI$14:$AI$99,SMALL(IF($AI$14:$AI$99<>"",ROW($AI$14:$AI$99)-ROW(INDIRECT("$AI$14"))+1),ROW(INDIRECT("A" & AB14 ) ))),"")}
E15: Ajouter un équipement réseau | K15: Si certains points ne sont pas équipés, veuillez les indiquer en commentaire : | AB15: =ROW(A15)- $AD$2 +1 -> 2 | AC15: =IF(AND($E15="Oui",$M15="Préleveur"),$F15,"") | AD15: {=IFERROR(INDEX($AC$14:$AC$99,SMALL(IF($AC$14:$AC$99<>"",ROW($AC$14:$AC$99)-ROW(INDIRECT("$AC$14"))+1),ROW(INDIRECT("A" & AB15 ) ))),"")} | AE15: =IF(AND($E15="Oui",LEFT($M15,10) ="Débitmètre"),$F15,"") | AF15: {=IFERROR(INDEX($AE$14:$AE$99,SMALL(IF($AE$14:$AE$99<>"",ROW($AE$14:$AE$99)-ROW(INDIRECT("$AE$14"))+1),ROW(INDIRECT("A" & AB15 ) ))),"")} | AG15: =IF(AND($E15="Oui",LEFT($M15,5) ="Sonde"),$F15,"") | AH15: {=IFERROR(INDEX($AG$14:$AG$99,SMALL(IF($AG$14:$AG$99<>"",ROW($AG$14:$AG$99)-ROW(INDIRECT("$AG$14"))+1),ROW(INDIRECT("A" & AB15 ) ))),"")} | AI15: =IF(AND($E15="Oui", $F15 <> "", $M15 = ""),$F15,"") | AJ15: {=IFERROR(INDEX($AI$14:$AI$99,SMALL(IF($AI$14:$AI$99<>"",ROW($AI$14:$AI$99)-ROW(INDIRECT("$AI$14"))+1),ROW(INDIRECT("A" & AB15 ) ))),"")}
AB16: =ROW(A16)- $AD$2 +1 -> 3 | AC16: =IF(AND($E16="Oui",$M16="Préleveur"),$F16,"") | AD16: {=IFERROR(INDEX($AC$14:$AC$99,SMALL(IF($AC$14:$AC$99<>"",ROW($AC$14:$AC$99)-ROW(INDIRECT("$AC$14"))+1),ROW(INDIRECT("A" & AB16 ) ))),"")} | AE16: =IF(AND($E16="Oui",LEFT($M16,10) ="Débitmètre"),$F16,"") | AF16: {=IFERROR(INDEX($AE$14:$AE$99,SMALL(IF($AE$14:$AE$99<>"",ROW($AE$14:$AE$99)-ROW(INDIRECT("$AE$14"))+1),ROW(INDIRECT("A" & AB16 ) ))),"")} | AG16: =IF(AND($E16="Oui",LEFT($M16,5) ="Sonde"),$F16,"") | AH16: {=IFERROR(INDEX($AG$14:$AG$99,SMALL(IF($AG$14:$AG$99<>"",ROW($AG$14:$AG$99)-ROW(INDIRECT("$AG$14"))+1),ROW(INDIRECT("A" & AB16 ) ))),"")} | AI16: =IF(AND($E16="Oui", $F16 <> "", $M16 = ""),$F16,"") | AJ16: {=IFERROR(INDEX($AI$14:$AI$99,SMALL(IF($AI$14:$AI$99<>"",ROW($AI$14:$AI$99)-ROW(INDIRECT("$AI$14"))+1),ROW(INDIRECT("A" & AB16 ) ))),"")}
AB17: =ROW(A17)- $AD$2 +1 -> 4 | AC17: =IF(AND($E17="Oui",$M17="Préleveur"),$F17,"") | AD17: {=IFERROR(INDEX($AC$14:$AC$99,SMALL(IF($AC$14:$AC$99<>"",ROW($AC$14:$AC$99)-ROW(INDIRECT("$AC$14"))+1),ROW(INDIRECT("A" & AB17 ) ))),"")} | AE17: =IF(AND($E17="Oui",LEFT($M17,10) ="Débitmètre"),$F17,"") | AF17: {=IFERROR(INDEX($AE$14:$AE$99,SMALL(IF($AE$14:$AE$99<>"",ROW($AE$14:$AE$99)-ROW(INDIRECT("$AE$14"))+1),ROW(INDIRECT("A" & AB17 ) ))),"")} | AG17: =IF(AND($E17="Oui",LEFT($M17,5) ="Sonde"),$F17,"") | AH17: {=IFERROR(INDEX($AG$14:$AG$99,SMALL(IF($AG$14:$AG$99<>"",ROW($AG$14:$AG$99)-ROW(INDIRECT("$AG$14"))+1),ROW(INDIRECT("A" & AB17 ) ))),"")} | AI17: =IF(AND($E17="Oui", $F17 <> "", $M17 = ""),$F17,"") | AJ17: {=IFERROR(INDEX($AI$14:$AI$99,SMALL(IF($AI$14:$AI$99<>"",ROW($AI$14:$AI$99)-ROW(INDIRECT("$AI$14"))+1),ROW(INDIRECT("A" & AB17 ) ))),"")}
AB18: =ROW(A18)- $AD$2 +1 -> 5 | AC18: =IF(AND($E18="Oui",$M18="Préleveur"),$F18,"") | AD18: {=IFERROR(INDEX($AC$14:$AC$99,SMALL(IF($AC$14:$AC$99<>"",ROW($AC$14:$AC$99)-ROW(INDIRECT("$AC$14"))+1),ROW(INDIRECT("A" & AB18 ) ))),"")} | AE18: =IF(AND($E18="Oui",LEFT($M18,10) ="Débitmètre"),$F18,"") | AF18: {=IFERROR(INDEX($AE$14:$AE$99,SMALL(IF($AE$14:$AE$99<>"",ROW($AE$14:$AE$99)-ROW(INDIRECT("$AE$14"))+1),ROW(INDIRECT("A" & AB18 ) ))),"")} | AG18: =IF(AND($E18="Oui",LEFT($M18,5) ="Sonde"),$F18,"") | AH18: {=IFERROR(INDEX($AG$14:$AG$99,SMALL(IF($AG$14:$AG$99<>"",ROW($AG$14:$AG$99)-ROW(INDIRECT("$AG$14"))+1),ROW(INDIRECT("A" & AB18 ) ))),"")} | AI18: =IF(AND($E18="Oui", $F18 <> "", $M18 = ""),$F18,"") | AJ18: {=IFERROR(INDEX($AI$14:$AI$99,SMALL(IF($AI$14:$AI$99<>"",ROW($AI$14:$AI$99)-ROW(INDIRECT("$AI$14"))+1),ROW(INDIRECT("A" & AB18 ) ))),"")}
AB19: =ROW(A19)- $AD$2 +1 -> 6 | AC19: =IF(AND($E19="Oui",$M19="Préleveur"),$F19,"") | AD19: {=IFERROR(INDEX($AC$14:$AC$99,SMALL(IF($AC$14:$AC$99<>"",ROW($AC$14:$AC$99)-ROW(INDIRECT("$AC$14"))+1),ROW(INDIRECT("A" & AB19 ) ))),"")} | AE19: =IF(AND($E19="Oui",LEFT($M19,10) ="Débitmètre"),$F19,"") | AF19: {=IFERROR(INDEX($AE$14:$AE$99,SMALL(IF($AE$14:$AE$99<>"",ROW($AE$14:$AE$99)-ROW(INDIRECT("$AE$14"))+1),ROW(INDIRECT("A" & AB19 ) ))),"")} | AG19: =IF(AND($E19="Oui",LEFT($M19,5) ="Sonde"),$F19,"") | AH19: {=IFERROR(INDEX($AG$14:$AG$99,SMALL(IF($AG$14:$AG$99<>"",ROW($AG$14:$AG$99)-ROW(INDIRECT("$AG$14"))+1),ROW(INDIRECT("A" & AB19 ) ))),"")} | AI19: =IF(AND($E19="Oui", $F19 <> "", $M19 = ""),$F19,"") | AJ19: {=IFERROR(INDEX($AI$14:$AI$99,SMALL(IF($AI$14:$AI$99<>"",ROW($AI$14:$AI$99)-ROW(INDIRECT("$AI$14"))+1),ROW(INDIRECT("A" & AB19 ) ))),"")}
D20: Liste des pluviomètres de référence du réseau | AB20: =ROW(A20)- $AD$2 +1 -> 7 | AC20: =IF(AND($E20="Oui",$M20="Préleveur"),$F20,"") | AD20: {=IFERROR(INDEX($AC$14:$AC$99,SMALL(IF($AC$14:$AC$99<>"",ROW($AC$14:$AC$99)-ROW(INDIRECT("$AC$14"))+1),ROW(INDIRECT("A" & AB20 ) ))),"")} | AE20: =IF(AND($E20="Oui",LEFT($M20,10) ="Débitmètre"),$F20,"") | AF20: {=IFERROR(INDEX($AE$14:$AE$99,SMALL(IF($AE$14:$AE$99<>"",ROW($AE$14:$AE$99)-ROW(INDIRECT("$AE$14"))+1),ROW(INDIRECT("A" & AB20 ) ))),"")} | AG20: =IF(AND($E20="Oui",LEFT($M20,5) ="Sonde"),$F20,"") | AH20: {=IFERROR(INDEX($AG$14:$AG$99,SMALL(IF($AG$14:$AG$99<>"",ROW($AG$14:$AG$99)-ROW(INDIRECT("$AG$14"))+1),ROW(INDIRECT("A" & AB20 ) ))),"")} | AI20: =IF(AND($E20="Oui", $F20 <> "", $M20 = ""),$F20,"") | AJ20: {=IFERROR(INDEX($AI$14:$AI$99,SMALL(IF($AI$14:$AI$99<>"",ROW($AI$14:$AI$99)-ROW(INDIRECT("$AI$14"))+1),ROW(INDIRECT("A" & AB20 ) ))),"")}
AB21: =ROW(A21)- $AD$2 +1 -> 8 | AC21: =IF(AND($E21="Oui",$M21="Préleveur"),$F21,"") | AD21: {=IFERROR(INDEX($AC$14:$AC$99,SMALL(IF($AC$14:$AC$99<>"",ROW($AC$14:$AC$99)-ROW(INDIRECT("$AC$14"))+1),ROW(INDIRECT("A" & AB21 ) ))),"")} | AE21: =IF(AND($E21="Oui",LEFT($M21,10) ="Débitmètre"),$F21,"") | AF21: {=IFERROR(INDEX($AE$14:$AE$99,SMALL(IF($AE$14:$AE$99<>"",ROW($AE$14:$AE$99)-ROW(INDIRECT("$AE$14"))+1),ROW(INDIRECT("A" & AB21 ) ))),"")} | AG21: =IF(AND($E21="Oui",LEFT($M21,5) ="Sonde"),$F21,"") | AH21: {=IFERROR(INDEX($AG$14:$AG$99,SMALL(IF($AG$14:$AG$99<>"",ROW($AG$14:$AG$99)-ROW(INDIRECT("$AG$14"))+1),ROW(INDIRECT("A" & AB21 ) ))),"")} | AI21: =IF(AND($E21="Oui", $F21 <> "", $M21 = ""),$F21,"") | AJ21: {=IFERROR(INDEX($AI$14:$AI$99,SMALL(IF($AI$14:$AI$99<>"",ROW($AI$14:$AI$99)-ROW(INDIRECT("$AI$14"))+1),ROW(INDIRECT("A" & AB21 ) ))),"")}
E22: Actif | F22: Lien vers l'onglet de l'équipement | AB22: =ROW(A22)- $AD$2 +1 -> 9 | AC22: =IF(AND($E22="Oui",$M22="Préleveur"),$F22,"") | AD22: {=IFERROR(INDEX($AC$14:$AC$99,SMALL(IF($AC$14:$AC$99<>"",ROW($AC$14:$AC$99)-ROW(INDIRECT("$AC$14"))+1),ROW(INDIRECT("A" & AB22 ) ))),"")} | AE22: =IF(AND($E22="Oui",LEFT($M22,10) ="Débitmètre"),$F22,"") | AF22: {=IFERROR(INDEX($AE$14:$AE$99,SMALL(IF($AE$14:$AE$99<>"",ROW($AE$14:$AE$99)-ROW(INDIRECT("$AE$14"))+1),ROW(INDIRECT("A" & AB22 ) ))),"")} | AG22: =IF(AND($E22="Oui",LEFT($M22,5) ="Sonde"),$F22,"") | AH22: {=IFERROR(INDEX($AG$14:$AG$99,SMALL(IF($AG$14:$AG$99<>"",ROW($AG$14:$AG$99)-ROW(INDIRECT("$AG$14"))+1),ROW(INDIRECT("A" & AB22 ) ))),"")} | AI22: =IF(AND($E22="Oui", $F22 <> "", $M22 = ""),$F22,"") | AJ22: {=IFERROR(INDEX($AI$14:$AI$99,SMALL(IF($AI$14:$AI$99<>"",ROW($AI$14:$AI$99)-ROW(INDIRECT("$AI$14"))+1),ROW(INDIRECT("A" & AB22 ) ))),"")}
AB23: =ROW(A23)- $AD$2 +1 -> 10 | AC23: =IF(AND($E23="Oui",$M23="Préleveur"),$F23,"") | AD23: {=IFERROR(INDEX($AC$14:$AC$99,SMALL(IF($AC$14:$AC$99<>"",ROW($AC$14:$AC$99)-ROW(INDIRECT("$AC$14"))+1),ROW(INDIRECT("A" & AB23 ) ))),"")} | AE23: =IF(AND($E23="Oui",LEFT($M23,10) ="Débitmètre"),$F23,"") | AF23: {=IFERROR(INDEX($AE$14:$AE$99,SMALL(IF($AE$14:$AE$99<>"",ROW($AE$14:$AE$99)-ROW(INDIRECT("$AE$14"))+1),ROW(INDIRECT("A" & AB23 ) ))),"")} | AG23: =IF(AND($E23="Oui",LEFT($M23,5) ="Sonde"),$F23,"") | AH23: {=IFERROR(INDEX($AG$14:$AG$99,SMALL(IF($AG$14:$AG$99<>"",ROW($AG$14:$AG$99)-ROW(INDIRECT("$AG$14"))+1),ROW(INDIRECT("A" & AB23 ) ))),"")} | AI23: =IF(AND($E23="Oui", $F23 <> "", $M23 = ""),$F23,"") | AJ23: {=IFERROR(INDEX($AI$14:$AI$99,SMALL(IF($AI$14:$AI$99<>"",ROW($AI$14:$AI$99)-ROW(INDIRECT("$AI$14"))+1),ROW(INDIRECT("A" & AB23 ) ))),"")}
E24: Ajouter un pluviomètre réseau | K24: Si pas de pluviomètre, veuillez ajouter en commentaire la provenance des données : | AB24: =ROW(A24)- $AD$2 +1 -> 11 | AC24: =IF(AND($E24="Oui",$M24="Préleveur"),$F24,"") | AD24: {=IFERROR(INDEX($AC$14:$AC$99,SMALL(IF($AC$14:$AC$99<>"",ROW($AC$14:$AC$99)-ROW(INDIRECT("$AC$14"))+1),ROW(INDIRECT("A" & AB24 ) ))),"")} | AE24: =IF(AND($E24="Oui",LEFT($M24,10) ="Débitmètre"),$F24,"") | AF24: {=IFERROR(INDEX($AE$14:$AE$99,SMALL(IF($AE$14:$AE$99<>"",ROW($AE$14:$AE$99)-ROW(INDIRECT("$AE$14"))+1),ROW(INDIRECT("A" & AB24 ) ))),"")} | AG24: =IF(AND($E24="Oui",LEFT($M24,5) ="Sonde"),$F24,"") | AH24: {=IFERROR(INDEX($AG$14:$AG$99,SMALL(IF($AG$14:$AG$99<>"",ROW($AG$14:$AG$99)-ROW(INDIRECT("$AG$14"))+1),ROW(INDIRECT("A" & AB24 ) ))),"")} | AI24: =IF(AND($E24="Oui", $F24 <> "", $M24 = ""),$F24,"") | AJ24: {=IFERROR(INDEX($AI$14:$AI$99,SMALL(IF($AI$14:$AI$99<>"",ROW($AI$14:$AI$99)-ROW(INDIRECT("$AI$14"))+1),ROW(INDIRECT("A" & AB24 ) ))),"")}
AB25: =ROW(A25)- $AD$2 +1 -> 12 | AC25: =IF(AND($E25="Oui",$M25="Préleveur"),$F25,"") | AD25: {=IFERROR(INDEX($AC$14:$AC$99,SMALL(IF($AC$14:$AC$99<>"",ROW($AC$14:$AC$99)-ROW(INDIRECT("$AC$14"))+1),ROW(INDIRECT("A" & AB25 ) ))),"")} | AE25: =IF(AND($E25="Oui",LEFT($M25,10) ="Débitmètre"),$F25,"") | AF25: {=IFERROR(INDEX($AE$14:$AE$99,SMALL(IF($AE$14:$AE$99<>"",ROW($AE$14:$AE$99)-ROW(INDIRECT("$AE$14"))+1),ROW(INDIRECT("A" & AB25 ) ))),"")} | AG25: =IF(AND($E25="Oui",LEFT($M25,5) ="Sonde"),$F25,"") | AH25: {=IFERROR(INDEX($AG$14:$AG$99,SMALL(IF($AG$14:$AG$99<>"",ROW($AG$14:$AG$99)-ROW(INDIRECT("$AG$14"))+1),ROW(INDIRECT("A" & AB25 ) ))),"")} | AI25: =IF(AND($E25="Oui", $F25 <> "", $M25 = ""),$F25,"") | AJ25: {=IFERROR(INDEX($AI$14:$AI$99,SMALL(IF($AI$14:$AI$99<>"",ROW($AI$14:$AI$99)-ROW(INDIRECT("$AI$14"))+1),ROW(INDIRECT("A" & AB25 ) ))),"")}
AB26: =ROW(A26)- $AD$2 +1 -> 13 | AC26: =IF(AND($E26="Oui",$M26="Préleveur"),$F26,"") | AD26: {=IFERROR(INDEX($AC$14:$AC$99,SMALL(IF($AC$14:$AC$99<>"",ROW($AC$14:$AC$99)-ROW(INDIRECT("$AC$14"))+1),ROW(INDIRECT("A" & AB26 ) ))),"")} | AE26: =IF(AND($E26="Oui",LEFT($M26,10) ="Débitmètre"),$F26,"") | AF26: {=IFERROR(INDEX($AE$14:$AE$99,SMALL(IF($AE$14:$AE$99<>"",ROW($AE$14:$AE$99)-ROW(INDIRECT("$AE$14"))+1),ROW(INDIRECT("A" & AB26 ) ))),"")} | AG26: =IF(AND($E26="Oui",LEFT($M26,5) ="Sonde"),$F26,"") | AH26: {=IFERROR(INDEX($AG$14:$AG$99,SMALL(IF($AG$14:$AG$99<>"",ROW($AG$14:$AG$99)-ROW(INDIRECT("$AG$14"))+1),ROW(INDIRECT("A" & AB26 ) ))),"")} | AI26: =IF(AND($E26="Oui", $F26 <> "", $M26 = ""),$F26,"") | AJ26: {=IFERROR(INDEX($AI$14:$AI$99,SMALL(IF($AI$14:$AI$99<>"",ROW($AI$14:$AI$99)-ROW(INDIRECT("$AI$14"))+1),ROW(INDIRECT("A" & AB26 ) ))),"")}
AB27: =ROW(A27)- $AD$2 +1 -> 14 | AC27: =IF(AND($E27="Oui",$M27="Préleveur"),$F27,"") | AD27: {=IFERROR(INDEX($AC$14:$AC$99,SMALL(IF($AC$14:$AC$99<>"",ROW($AC$14:$AC$99)-ROW(INDIRECT("$AC$14"))+1),ROW(INDIRECT("A" & AB27 ) ))),"")} | AE27: =IF(AND($E27="Oui",LEFT($M27,10) ="Débitmètre"),$F27,"") | AF27: {=IFERROR(INDEX($AE$14:$AE$99,SMALL(IF($AE$14:$AE$99<>"",ROW($AE$14:$AE$99)-ROW(INDIRECT("$AE$14"))+1),ROW(INDIRECT("A" & AB27 ) ))),"")} | AG27: =IF(AND($E27="Oui",LEFT($M27,5) ="Sonde"),$F27,"") | AH27: {=IFERROR(INDEX($AG$14:$AG$99,SMALL(IF($AG$14:$AG$99<>"",ROW($AG$14:$AG$99)-ROW(INDIRECT("$AG$14"))+1),ROW(INDIRECT("A" & AB27 ) ))),"")} | AI27: =IF(AND($E27="Oui", $F27 <> "", $M27 = ""),$F27,"") | AJ27: {=IFERROR(INDEX($AI$14:$AI$99,SMALL(IF($AI$14:$AI$99<>"",ROW($AI$14:$AI$99)-ROW(INDIRECT("$AI$14"))+1),ROW(INDIRECT("A" & AB27 ) ))),"")}
AB28: =ROW(A28)- $AD$2 +1 -> 15 | AC28: =IF(AND($E28="Oui",$M28="Préleveur"),$F28,"") | AD28: {=IFERROR(INDEX($AC$14:$AC$99,SMALL(IF($AC$14:$AC$99<>"",ROW($AC$14:$AC$99)-ROW(INDIRECT("$AC$14"))+1),ROW(INDIRECT("A" & AB28 ) ))),"")} | AE28: =IF(AND($E28="Oui",LEFT($M28,10) ="Débitmètre"),$F28,"") | AF28: {=IFERROR(INDEX($AE$14:$AE$99,SMALL(IF($AE$14:$AE$99<>"",ROW($AE$14:$AE$99)-ROW(INDIRECT("$AE$14"))+1),ROW(INDIRECT("A" & AB28 ) ))),"")} | AG28: =IF(AND($E28="Oui",LEFT($M28,5) ="Sonde"),$F28,"") | AH28: {=IFERROR(INDEX($AG$14:$AG$99,SMALL(IF($AG$14:$AG$99<>"",ROW($AG$14:$AG$99)-ROW(INDIRECT("$AG$14"))+1),ROW(INDIRECT("A" & AB28 ) ))),"")} | AI28: =IF(AND($E28="Oui", $F28 <> "", $M28 = ""),$F28,"") | AJ28: {=IFERROR(INDEX($AI$14:$AI$99,SMALL(IF($AI$14:$AI$99<>"",ROW($AI$14:$AI$99)-ROW(INDIRECT("$AI$14"))+1),ROW(INDIRECT("A" & AB28 ) ))),"")}
C29: SYSTÈME DE TRAITEMENT | AB29: =ROW(A29)- $AD$2 +1 -> 16 | AC29: =IF(AND($E29="Oui",$M29="Préleveur"),$F29,"") | AD29: {=IFERROR(INDEX($AC$14:$AC$99,SMALL(IF($AC$14:$AC$99<>"",ROW($AC$14:$AC$99)-ROW(INDIRECT("$AC$14"))+1),ROW(INDIRECT("A" & AB29 ) ))),"")} | AE29: =IF(AND($E29="Oui",LEFT($M29,10) ="Débitmètre"),$F29,"") | AF29: {=IFERROR(INDEX($AE$14:$AE$99,SMALL(IF($AE$14:$AE$99<>"",ROW($AE$14:$AE$99)-ROW(INDIRECT("$AE$14"))+1),ROW(INDIRECT("A" & AB29 ) ))),"")} | AG29: =IF(AND($E29="Oui",LEFT($M29,5) ="Sonde"),$F29,"") | AH29: {=IFERROR(INDEX($AG$14:$AG$99,SMALL(IF($AG$14:$AG$99<>"",ROW($AG$14:$AG$99)-ROW(INDIRECT("$AG$14"))+1),ROW(INDIRECT("A" & AB29 ) ))),"")} | AI29: =IF(AND($E29="Oui", $F29 <> "", $M29 = ""),$F29,"") | AJ29: {=IFERROR(INDEX($AI$14:$AI$99,SMALL(IF($AI$14:$AI$99<>"",ROW($AI$14:$AI$99)-ROW(INDIRECT("$AI$14"))+1),ROW(INDIRECT("A" & AB29 ) ))),"")}
D30: Remarques: | E30: Les estimations et les apports par camion ne rentrent pas dans le CDA | AB30: =ROW(A30)- $AD$2 +1 -> 17 | AC30: =IF(AND($E30="Oui",$M30="Préleveur"),$F30,"") | AD30: {=IFERROR(INDEX($AC$14:$AC$99,SMALL(IF($AC$14:$AC$99<>"",ROW($AC$14:$AC$99)-ROW(INDIRECT("$AC$14"))+1),ROW(INDIRECT("A" & AB30 ) ))),"")} | AE30: =IF(AND($E30="Oui",LEFT($M30,10) ="Débitmètre"),$F30,"") | AF30: {=IFERROR(INDEX($AE$14:$AE$99,SMALL(IF($AE$14:$AE$99<>"",ROW($AE$14:$AE$99)-ROW(INDIRECT("$AE$14"))+1),ROW(INDIRECT("A" & AB30 ) ))),"")} | AG30: =IF(AND($E30="Oui",LEFT($M30,5) ="Sonde"),$F30,"") | AH30: {=IFERROR(INDEX($AG$14:$AG$99,SMALL(IF($AG$14:$AG$99<>"",ROW($AG$14:$AG$99)-ROW(INDIRECT("$AG$14"))+1),ROW(INDIRECT("A" & AB30 ) ))),"")} | AI30: =IF(AND($E30="Oui", $F30 <> "", $M30 = ""),$F30,"") | AJ30: {=IFERROR(INDEX($AI$14:$AI$99,SMALL(IF($AI$14:$AI$99<>"",ROW($AI$14:$AI$99)-ROW(INDIRECT("$AI$14"))+1),ROW(INDIRECT("A" & AB30 ) ))),"")}
D31: Liste des équipements du système de traitement pour chaque point d’autosurveillance | AB31: =ROW(A31)- $AD$2 +1 -> 18 | AC31: =IF(AND($E31="Oui",$M31="Préleveur"),$F31,"") | AD31: {=IFERROR(INDEX($AC$14:$AC$99,SMALL(IF($AC$14:$AC$99<>"",ROW($AC$14:$AC$99)-ROW(INDIRECT("$AC$14"))+1),ROW(INDIRECT("A" & AB31 ) ))),"")} | AE31: =IF(AND($E31="Oui",LEFT($M31,10) ="Débitmètre"),$F31,"") | AF31: {=IFERROR(INDEX($AE$14:$AE$99,SMALL(IF($AE$14:$AE$99<>"",ROW($AE$14:$AE$99)-ROW(INDIRECT("$AE$14"))+1),ROW(INDIRECT("A" & AB31 ) ))),"")} | AG31: =IF(AND($E31="Oui",LEFT($M31,5) ="Sonde"),$F31,"") | AH31: {=IFERROR(INDEX($AG$14:$AG$99,SMALL(IF($AG$14:$AG$99<>"",ROW($AG$14:$AG$99)-ROW(INDIRECT("$AG$14"))+1),ROW(INDIRECT("A" & AB31 ) ))),"")} | AI31: =IF(AND($E31="Oui", $F31 <> "", $M31 = ""),$F31,"") | AJ31: {=IFERROR(INDEX($AI$14:$AI$99,SMALL(IF($AI$14:$AI$99<>"",ROW($AI$14:$AI$99)-ROW(INDIRECT("$AI$14"))+1),ROW(INDIRECT("A" & AB31 ) ))),"")}
AB32: =ROW(A32)- $AD$2 +1 -> 19 | AC32: =IF(AND($E32="Oui",$M32="Préleveur"),$F32,"") | AD32: {=IFERROR(INDEX($AC$14:$AC$99,SMALL(IF($AC$14:$AC$99<>"",ROW($AC$14:$AC$99)-ROW(INDIRECT("$AC$14"))+1),ROW(INDIRECT("A" & AB32 ) ))),"")} | AE32: =IF(AND($E32="Oui",LEFT($M32,10) ="Débitmètre"),$F32,"") | AF32: {=IFERROR(INDEX($AE$14:$AE$99,SMALL(IF($AE$14:$AE$99<>"",ROW($AE$14:$AE$99)-ROW(INDIRECT("$AE$14"))+1),ROW(INDIRECT("A" & AB32 ) ))),"")} | AG32: =IF(AND($E32="Oui",LEFT($M32,5) ="Sonde"),$F32,"") | AH32: {=IFERROR(INDEX($AG$14:$AG$99,SMALL(IF($AG$14:$AG$99<>"",ROW($AG$14:$AG$99)-ROW(INDIRECT("$AG$14"))+1),ROW(INDIRECT("A" & AB32 ) ))),"")} | AI32: =IF(AND($E32="Oui", $F32 <> "", $M32 = ""),$F32,"") | AJ32: {=IFERROR(INDEX($AI$14:$AI$99,SMALL(IF($AI$14:$AI$99<>"",ROW($AI$14:$AI$99)-ROW(INDIRECT("$AI$14"))+1),ROW(INDIRECT("A" & AB32 ) ))),"")}
E33: Actif | F33: Lien vers l'onglet de l'équipement | H33: Point réglementaire | I33: Localisation (cf. MAS) | J33: Code du point (cf MAS) | K33: Libellé de l'équipement | M33: Type d'équipement | O33: Type de matériel | R33: Certaines informations d'un équipement ne sont pas modifiables. Au besoin il est préférable de supprimer et de recréer l'équipement. | AB33: =ROW(A33)- $AD$2 +1 -> 20 | AC33: =IF(AND($E33="Oui",$M33="Préleveur"),$F33,"") | AD33: {=IFERROR(INDEX($AC$14:$AC$99,SMALL(IF($AC$14:$AC$99<>"",ROW($AC$14:$AC$99)-ROW(INDIRECT("$AC$14"))+1),ROW(INDIRECT("A" & AB33 ) ))),"")} | AE33: =IF(AND($E33="Oui",LEFT($M33,10) ="Débitmètre"),$F33,"") | AF33: {=IFERROR(INDEX($AE$14:$AE$99,SMALL(IF($AE$14:$AE$99<>"",ROW($AE$14:$AE$99)-ROW(INDIRECT("$AE$14"))+1),ROW(INDIRECT("A" & AB33 ) ))),"")} | AG33: =IF(AND($E33="Oui",LEFT($M33,5) ="Sonde"),$F33,"") | AH33: {=IFERROR(INDEX($AG$14:$AG$99,SMALL(IF($AG$14:$AG$99<>"",ROW($AG$14:$AG$99)-ROW(INDIRECT("$AG$14"))+1),ROW(INDIRECT("A" & AB33 ) ))),"")} | AI33: =IF(AND($E33="Oui", $F33 <> "", $M33 = ""),$F33,"") | AJ33: {=IFERROR(INDEX($AI$14:$AI$99,SMALL(IF($AI$14:$AI$99<>"",ROW($AI$14:$AI$99)-ROW(INDIRECT("$AI$14"))+1),ROW(INDIRECT("A" & AB33 ) ))),"")}
AB34: =ROW(A34)- $AD$2 +1 -> 21 | AC34: =IF(AND($E34="Oui",$M34="Préleveur"),$F34,"") | AD34: {=IFERROR(INDEX($AC$14:$AC$99,SMALL(IF($AC$14:$AC$99<>"",ROW($AC$14:$AC$99)-ROW(INDIRECT("$AC$14"))+1),ROW(INDIRECT("A" & AB34 ) ))),"")} | AE34: =IF(AND($E34="Oui",LEFT($M34,10) ="Débitmètre"),$F34,"") | AF34: {=IFERROR(INDEX($AE$14:$AE$99,SMALL(IF($AE$14:$AE$99<>"",ROW($AE$14:$AE$99)-ROW(INDIRECT("$AE$14"))+1),ROW(INDIRECT("A" & AB34 ) ))),"")} | AG34: =IF(AND($E34="Oui",LEFT($M34,5) ="Sonde"),$F34,"") | AH34: {=IFERROR(INDEX($AG$14:$AG$99,SMALL(IF($AG$14:$AG$99<>"",ROW($AG$14:$AG$99)-ROW(INDIRECT("$AG$14"))+1),ROW(INDIRECT("A" & AB34 ) ))),"")} | AI34: =IF(AND($E34="Oui", $F34 <> "", $M34 = ""),$F34,"") | AJ34: {=IFERROR(INDEX($AI$14:$AI$99,SMALL(IF($AI$14:$AI$99<>"",ROW($AI$14:$AI$99)-ROW(INDIRECT("$AI$14"))+1),ROW(INDIRECT("A" & AB34 ) ))),"")}
E35: Ajouter un équipement station | K35: Si certains points ne sont pas équipés, veuillez les indiquer en commentaire : | AB35: =ROW(A35)- $AD$2 +1 -> 22 | AC35: =IF(AND($E35="Oui",$M35="Préleveur"),$F35,"") | AD35: {=IFERROR(INDEX($AC$14:$AC$99,SMALL(IF($AC$14:$AC$99<>"",ROW($AC$14:$AC$99)-ROW(INDIRECT("$AC$14"))+1),ROW(INDIRECT("A" & AB35 ) ))),"")} | AE35: =IF(AND($E35="Oui",LEFT($M35,10) ="Débitmètre"),$F35,"") | AF35: {=IFERROR(INDEX($AE$14:$AE$99,SMALL(IF($AE$14:$AE$99<>"",ROW($AE$14:$AE$99)-ROW(INDIRECT("$AE$14"))+1),ROW(INDIRECT("A" & AB35 ) ))),"")} | AG35: =IF(AND($E35="Oui",LEFT($M35,5) ="Sonde"),$F35,"") | AH35: {=IFERROR(INDEX($AG$14:$AG$99,SMALL(IF($AG$14:$AG$99<>"",ROW($AG$14:$AG$99)-ROW(INDIRECT("$AG$14"))+1),ROW(INDIRECT("A" & AB35 ) ))),"")} | AI35: =IF(AND($E35="Oui", $F35 <> "", $M35 = ""),$F35,"") | AJ35: {=IFERROR(INDEX($AI$14:$AI$99,SMALL(IF($AI$14:$AI$99<>"",ROW($AI$14:$AI$99)-ROW(INDIRECT("$AI$14"))+1),ROW(INDIRECT("A" & AB35 ) ))),"")}
AB36: =ROW(A36)- $AD$2 +1 -> 23 | AC36: =IF(AND($E36="Oui",$M36="Préleveur"),$F36,"") | AD36: {=IFERROR(INDEX($AC$14:$AC$99,SMALL(IF($AC$14:$AC$99<>"",ROW($AC$14:$AC$99)-ROW(INDIRECT("$AC$14"))+1),ROW(INDIRECT("A" & AB36 ) ))),"")} | AE36: =IF(AND($E36="Oui",LEFT($M36,10) ="Débitmètre"),$F36,"") | AF36: {=IFERROR(INDEX($AE$14:$AE$99,SMALL(IF($AE$14:$AE$99<>"",ROW($AE$14:$AE$99)-ROW(INDIRECT("$AE$14"))+1),ROW(INDIRECT("A" & AB36 ) ))),"")} | AG36: =IF(AND($E36="Oui",LEFT($M36,5) ="Sonde"),$F36,"") | AH36: {=IFERROR(INDEX($AG$14:$AG$99,SMALL(IF($AG$14:$AG$99<>"",ROW($AG$14:$AG$99)-ROW(INDIRECT("$AG$14"))+1),ROW(INDIRECT("A" & AB36 ) ))),"")} | AI36: =IF(AND($E36="Oui", $F36 <> "", $M36 = ""),$F36,"") | AJ36: {=IFERROR(INDEX($AI$14:$AI$99,SMALL(IF($AI$14:$AI$99<>"",ROW($AI$14:$AI$99)-ROW(INDIRECT("$AI$14"))+1),ROW(INDIRECT("A" & AB36 ) ))),"")}
AB37: =ROW(A37)- $AD$2 +1 -> 24 | AC37: =IF(AND($E37="Oui",$M37="Préleveur"),$F37,"") | AD37: {=IFERROR(INDEX($AC$14:$AC$99,SMALL(IF($AC$14:$AC$99<>"",ROW($AC$14:$AC$99)-ROW(INDIRECT("$AC$14"))+1),ROW(INDIRECT("A" & AB37 ) ))),"")} | AE37: =IF(AND($E37="Oui",LEFT($M37,10) ="Débitmètre"),$F37,"") | AF37: {=IFERROR(INDEX($AE$14:$AE$99,SMALL(IF($AE$14:$AE$99<>"",ROW($AE$14:$AE$99)-ROW(INDIRECT("$AE$14"))+1),ROW(INDIRECT("A" & AB37 ) ))),"")} | AG37: =IF(AND($E37="Oui",LEFT($M37,5) ="Sonde"),$F37,"") | AH37: {=IFERROR(INDEX($AG$14:$AG$99,SMALL(IF($AG$14:$AG$99<>"",ROW($AG$14:$AG$99)-ROW(INDIRECT("$AG$14"))+1),ROW(INDIRECT("A" & AB37 ) ))),"")} | AI37: =IF(AND($E37="Oui", $F37 <> "", $M37 = ""),$F37,"") | AJ37: {=IFERROR(INDEX($AI$14:$AI$99,SMALL(IF($AI$14:$AI$99<>"",ROW($AI$14:$AI$99)-ROW(INDIRECT("$AI$14"))+1),ROW(INDIRECT("A" & AB37 ) ))),"")}
AB38: =ROW(A38)- $AD$2 +1 -> 25 | AC38: =IF(AND($E38="Oui",$M38="Préleveur"),$F38,"") | AD38: {=IFERROR(INDEX($AC$14:$AC$99,SMALL(IF($AC$14:$AC$99<>"",ROW($AC$14:$AC$99)-ROW(INDIRECT("$AC$14"))+1),ROW(INDIRECT("A" & AB38 ) ))),"")} | AE38: =IF(AND($E38="Oui",LEFT($M38,10) ="Débitmètre"),$F38,"") | AF38: {=IFERROR(INDEX($AE$14:$AE$99,SMALL(IF($AE$14:$AE$99<>"",ROW($AE$14:$AE$99)-ROW(INDIRECT("$AE$14"))+1),ROW(INDIRECT("A" & AB38 ) ))),"")} | AG38: =IF(AND($E38="Oui",LEFT($M38,5) ="Sonde"),$F38,"") | AH38: {=IFERROR(INDEX($AG$14:$AG$99,SMALL(IF($AG$14:$AG$99<>"",ROW($AG$14:$AG$99)-ROW(INDIRECT("$AG$14"))+1),ROW(INDIRECT("A" & AB38 ) ))),"")} | AI38: =IF(AND($E38="Oui", $F38 <> "", $M38 = ""),$F38,"") | AJ38: {=IFERROR(INDEX($AI$14:$AI$99,SMALL(IF($AI$14:$AI$99<>"",ROW($AI$14:$AI$99)-ROW(INDIRECT("$AI$14"))+1),ROW(INDIRECT("A" & AB38 ) ))),"")}
AB39: =ROW(A39)- $AD$2 +1 -> 26 | AC39: =IF(AND($E39="Oui",$M39="Préleveur"),$F39,"") | AD39: {=IFERROR(INDEX($AC$14:$AC$99,SMALL(IF($AC$14:$AC$99<>"",ROW($AC$14:$AC$99)-ROW(INDIRECT("$AC$14"))+1),ROW(INDIRECT("A" & AB39 ) ))),"")} | AE39: =IF(AND($E39="Oui",LEFT($M39,10) ="Débitmètre"),$F39,"") | AF39: {=IFERROR(INDEX($AE$14:$AE$99,SMALL(IF($AE$14:$AE$99<>"",ROW($AE$14:$AE$99)-ROW(INDIRECT("$AE$14"))+1),ROW(INDIRECT("A" & AB39 ) ))),"")} | AG39: =IF(AND($E39="Oui",LEFT($M39,5) ="Sonde"),$F39,"") | AH39: {=IFERROR(INDEX($AG$14:$AG$99,SMALL(IF($AG$14:$AG$99<>"",ROW($AG$14:$AG$99)-ROW(INDIRECT("$AG$14"))+1),ROW(INDIRECT("A" & AB39 ) ))),"")} | AI39: =IF(AND($E39="Oui", $F39 <> "", $M39 = ""),$F39,"") | AJ39: {=IFERROR(INDEX($AI$14:$AI$99,SMALL(IF($AI$14:$AI$99<>"",ROW($AI$14:$AI$99)-ROW(INDIRECT("$AI$14"))+1),ROW(INDIRECT("A" & AB39 ) ))),"")}
D40: Liste des pluviomètres de référence de la station | AB40: =ROW(A40)- $AD$2 +1 -> 27 | AC40: =IF(AND($E40="Oui",$M40="Préleveur"),$F40,"") | AD40: {=IFERROR(INDEX($AC$14:$AC$99,SMALL(IF($AC$14:$AC$99<>"",ROW($AC$14:$AC$99)-ROW(INDIRECT("$AC$14"))+1),ROW(INDIRECT("A" & AB40 ) ))),"")} | AE40: =IF(AND($E40="Oui",LEFT($M40,10) ="Débitmètre"),$F40,"") | AF40: {=IFERROR(INDEX($AE$14:$AE$99,SMALL(IF($AE$14:$AE$99<>"",ROW($AE$14:$AE$99)-ROW(INDIRECT("$AE$14"))+1),ROW(INDIRECT("A" & AB40 ) ))),"")} | AG40: =IF(AND($E40="Oui",LEFT($M40,5) ="Sonde"),$F40,"") | AH40: {=IFERROR(INDEX($AG$14:$AG$99,SMALL(IF($AG$14:$AG$99<>"",ROW($AG$14:$AG$99)-ROW(INDIRECT("$AG$14"))+1),ROW(INDIRECT("A" & AB40 ) ))),"")} | AI40: =IF(AND($E40="Oui", $F40 <> "", $M40 = ""),$F40,"") | AJ40: {=IFERROR(INDEX($AI$14:$AI$99,SMALL(IF($AI$14:$AI$99<>"",ROW($AI$14:$AI$99)-ROW(INDIRECT("$AI$14"))+1),ROW(INDIRECT("A" & AB40 ) ))),"")}
AB41: =ROW(A41)- $AD$2 +1 -> 28 | AC41: =IF(AND($E41="Oui",$M41="Préleveur"),$F41,"") | AD41: {=IFERROR(INDEX($AC$14:$AC$99,SMALL(IF($AC$14:$AC$99<>"",ROW($AC$14:$AC$99)-ROW(INDIRECT("$AC$14"))+1),ROW(INDIRECT("A" & AB41 ) ))),"")} | AE41: =IF(AND($E41="Oui",LEFT($M41,10) ="Débitmètre"),$F41,"") | AF41: {=IFERROR(INDEX($AE$14:$AE$99,SMALL(IF($AE$14:$AE$99<>"",ROW($AE$14:$AE$99)-ROW(INDIRECT("$AE$14"))+1),ROW(INDIRECT("A" & AB41 ) ))),"")} | AG41: =IF(AND($E41="Oui",LEFT($M41,5) ="Sonde"),$F41,"") | AH41: {=IFERROR(INDEX($AG$14:$AG$99,SMALL(IF($AG$14:$AG$99<>"",ROW($AG$14:$AG$99)-ROW(INDIRECT("$AG$14"))+1),ROW(INDIRECT("A" & AB41 ) ))),"")} | AI41: =IF(AND($E41="Oui", $F41 <> "", $M41 = ""),$F41,"") | AJ41: {=IFERROR(INDEX($AI$14:$AI$99,SMALL(IF($AI$14:$AI$99<>"",ROW($AI$14:$AI$99)-ROW(INDIRECT("$AI$14"))+1),ROW(INDIRECT("A" & AB41 ) ))),"")}
E42: Actif | F42: Lien vers l'onglet de l'équipement | AB42: =ROW(A42)- $AD$2 +1 -> 29 | AC42: =IF(AND($E42="Oui",$M42="Préleveur"),$F42,"") | AD42: {=IFERROR(INDEX($AC$14:$AC$99,SMALL(IF($AC$14:$AC$99<>"",ROW($AC$14:$AC$99)-ROW(INDIRECT("$AC$14"))+1),ROW(INDIRECT("A" & AB42 ) ))),"")} | AE42: =IF(AND($E42="Oui",LEFT($M42,10) ="Débitmètre"),$F42,"") | AF42: {=IFERROR(INDEX($AE$14:$AE$99,SMALL(IF($AE$14:$AE$99<>"",ROW($AE$14:$AE$99)-ROW(INDIRECT("$AE$14"))+1),ROW(INDIRECT("A" & AB42 ) ))),"")} | AG42: =IF(AND($E42="Oui",LEFT($M42,5) ="Sonde"),$F42,"") | AH42: {=IFERROR(INDEX($AG$14:$AG$99,SMALL(IF($AG$14:$AG$99<>"",ROW($AG$14:$AG$99)-ROW(INDIRECT("$AG$14"))+1),ROW(INDIRECT("A" & AB42 ) ))),"")} | AI42: =IF(AND($E42="Oui", $F42 <> "", $M42 = ""),$F42,"") | AJ42: {=IFERROR(INDEX($AI$14:$AI$99,SMALL(IF($AI$14:$AI$99<>"",ROW($AI$14:$AI$99)-ROW(INDIRECT("$AI$14"))+1),ROW(INDIRECT("A" & AB42 ) ))),"")}
AB43: =ROW(A43)- $AD$2 +1 -> 30 | AC43: =IF(AND($E43="Oui",$M43="Préleveur"),$F43,"") | AD43: {=IFERROR(INDEX($AC$14:$AC$99,SMALL(IF($AC$14:$AC$99<>"",ROW($AC$14:$AC$99)-ROW(INDIRECT("$AC$14"))+1),ROW(INDIRECT("A" & AB43 ) ))),"")} | AE43: =IF(AND($E43="Oui",LEFT($M43,10) ="Débitmètre"),$F43,"") | AF43: {=IFERROR(INDEX($AE$14:$AE$99,SMALL(IF($AE$14:$AE$99<>"",ROW($AE$14:$AE$99)-ROW(INDIRECT("$AE$14"))+1),ROW(INDIRECT("A" & AB43 ) ))),"")} | AG43: =IF(AND($E43="Oui",LEFT($M43,5) ="Sonde"),$F43,"") | AH43: {=IFERROR(INDEX($AG$14:$AG$99,SMALL(IF($AG$14:$AG$99<>"",ROW($AG$14:$AG$99)-ROW(INDIRECT("$AG$14"))+1),ROW(INDIRECT("A" & AB43 ) ))),"")} | AI43: =IF(AND($E43="Oui", $F43 <> "", $M43 = ""),$F43,"") | AJ43: {=IFERROR(INDEX($AI$14:$AI$99,SMALL(IF($AI$14:$AI$99<>"",ROW($AI$14:$AI$99)-ROW(INDIRECT("$AI$14"))+1),ROW(INDIRECT("A" & AB43 ) ))),"")}
E44: Ajouter un pluviomètre station | K44: Si pas de pluviomètre, veuillez ajouter en commentaire la provenance des données : | AB44: =ROW(A44)- $AD$2 +1 -> 31 | AC44: =IF(AND($E44="Oui",$M44="Préleveur"),$F44,"") | AD44: {=IFERROR(INDEX($AC$14:$AC$99,SMALL(IF($AC$14:$AC$99<>"",ROW($AC$14:$AC$99)-ROW(INDIRECT("$AC$13"))+1),ROW(INDIRECT("A" & AB44 ) ))),"")} | AE44: =IF(AND($E44="Oui",LEFT($M44,10) ="Débitmètre"),$F44,"") | AF44: {=IFERROR(INDEX($AE$14:$AE$99,SMALL(IF($AE$14:$AE$99<>"",ROW($AE$14:$AE$99)-ROW(INDIRECT("$AE$13"))+1),ROW(INDIRECT("A" & AB44 ) ))),"")} | AG44: =IF(AND($E44="Oui",LEFT($M44,5) ="Sonde"),$F44,"") | AH44: {=IFERROR(INDEX($AG$14:$AG$99,SMALL(IF($AG$14:$AG$99<>"",ROW($AG$14:$AG$99)-ROW(INDIRECT("$AG$13"))+1),ROW(INDIRECT("A" & AB44 ) ))),"")} | AI44: =IF(AND($E44="Oui", $F44 <> "", $M44 = ""),$F44,"") | AJ44: {=IFERROR(INDEX($AI$14:$AI$99,SMALL(IF($AI$14:$AI$99<>"",ROW($AI$14:$AI$99)-ROW(INDIRECT("$AI$13"))+1),ROW(INDIRECT("A" & AB44 ) ))),"")}
AB45: =ROW(A45)- $AD$2 +1 -> 32 | AC45: =IF(AND($E45="Oui",$M45="Préleveur"),$F45,"") | AD45: {=IFERROR(INDEX($AC$14:$AC$99,SMALL(IF($AC$14:$AC$99<>"",ROW($AC$14:$AC$99)-ROW(INDIRECT("$AC$13"))+1),ROW(INDIRECT("A" & AB45 ) ))),"")} | AE45: =IF(AND($E45="Oui",LEFT($M45,10) ="Débitmètre"),$F45,"") | AF45: {=IFERROR(INDEX($AE$14:$AE$99,SMALL(IF($AE$14:$AE$99<>"",ROW($AE$14:$AE$99)-ROW(INDIRECT("$AE$13"))+1),ROW(INDIRECT("A" & AB45 ) ))),"")} | AG45: =IF(AND($E45="Oui",LEFT($M45,5) ="Sonde"),$F45,"") | AH45: {=IFERROR(INDEX($AG$14:$AG$99,SMALL(IF($AG$14:$AG$99<>"",ROW($AG$14:$AG$99)-ROW(INDIRECT("$AG$13"))+1),ROW(INDIRECT("A" & AB45 ) ))),"")} | AI45: =IF(AND($E45="Oui", $F45 <> "", $M45 = ""),$F45,"") | AJ45: {=IFERROR(INDEX($AI$14:$AI$99,SMALL(IF($AI$14:$AI$99<>"",ROW($AI$14:$AI$99)-ROW(INDIRECT("$AI$13"))+1),ROW(INDIRECT("A" & AB45 ) ))),"")}
AB46: =ROW(A46)- $AD$2 +1 -> 33 | AC46: =IF(AND($E46="Oui",$M46="Préleveur"),$F46,"") | AD46: {=IFERROR(INDEX($AC$14:$AC$99,SMALL(IF($AC$14:$AC$99<>"",ROW($AC$14:$AC$99)-ROW(INDIRECT("$AC$13"))+1),ROW(INDIRECT("A" & AB46 ) ))),"")} | AE46: =IF(AND($E46="Oui",LEFT($M46,10) ="Débitmètre"),$F46,"") | AF46: {=IFERROR(INDEX($AE$14:$AE$99,SMALL(IF($AE$14:$AE$99<>"",ROW($AE$14:$AE$99)-ROW(INDIRECT("$AE$13"))+1),ROW(INDIRECT("A" & AB46 ) ))),"")} | AG46: =IF(AND($E46="Oui",LEFT($M46,5) ="Sonde"),$F46,"") | AH46: {=IFERROR(INDEX($AG$14:$AG$99,SMALL(IF($AG$14:$AG$99<>"",ROW($AG$14:$AG$99)-ROW(INDIRECT("$AG$13"))+1),ROW(INDIRECT("A" & AB46 ) ))),"")} | AI46: =IF(AND($E46="Oui", $F46 <> "", $M46 = ""),$F46,"") | AJ46: {=IFERROR(INDEX($AI$14:$AI$99,SMALL(IF($AI$14:$AI$99<>"",ROW($AI$14:$AI$99)-ROW(INDIRECT("$AI$13"))+1),ROW(INDIRECT("A" & AB46 ) ))),"")}
AB47: =ROW(A47)- $AD$2 +1 -> 34 | AC47: =IF(AND($E47="Oui",$M47="Préleveur"),$F47,"") | AD47: {=IFERROR(INDEX($AC$14:$AC$99,SMALL(IF($AC$14:$AC$99<>"",ROW($AC$14:$AC$99)-ROW(INDIRECT("$AC$13"))+1),ROW(INDIRECT("A" & AB47 ) ))),"")} | AE47: =IF(AND($E47="Oui",LEFT($M47,10) ="Débitmètre"),$F47,"") | AF47: {=IFERROR(INDEX($AE$14:$AE$99,SMALL(IF($AE$14:$AE$99<>"",ROW($AE$14:$AE$99)-ROW(INDIRECT("$AE$13"))+1),ROW(INDIRECT("A" & AB47 ) ))),"")} | AG47: =IF(AND($E47="Oui",LEFT($M47,5) ="Sonde"),$F47,"") | AH47: {=IFERROR(INDEX($AG$14:$AG$99,SMALL(IF($AG$14:$AG$99<>"",ROW($AG$14:$AG$99)-ROW(INDIRECT("$AG$13"))+1),ROW(INDIRECT("A" & AB47 ) ))),"")} | AI47: =IF(AND($E47="Oui", $F47 <> "", $M47 = ""),$F47,"") | AJ47: {=IFERROR(INDEX($AI$14:$AI$99,SMALL(IF($AI$14:$AI$99<>"",ROW($AI$14:$AI$99)-ROW(INDIRECT("$AI$13"))+1),ROW(INDIRECT("A" & AB47 ) ))),"")}
AB48: =ROW(A48)- $AD$2 +1 -> 35 | AC48: =IF(AND($E48="Oui",$M48="Préleveur"),$F48,"") | AD48: {=IFERROR(INDEX($AC$14:$AC$99,SMALL(IF($AC$14:$AC$99<>"",ROW($AC$14:$AC$99)-ROW(INDIRECT("$AC$13"))+1),ROW(INDIRECT("A" & AB48 ) ))),"")} | AE48: =IF(AND($E48="Oui",LEFT($M48,10) ="Débitmètre"),$F48,"") | AF48: {=IFERROR(INDEX($AE$14:$AE$99,SMALL(IF($AE$14:$AE$99<>"",ROW($AE$14:$AE$99)-ROW(INDIRECT("$AE$13"))+1),ROW(INDIRECT("A" & AB48 ) ))),"")} | AG48: =IF(AND($E48="Oui",LEFT($M48,5) ="Sonde"),$F48,"") | AH48: {=IFERROR(INDEX($AG$14:$AG$99,SMALL(IF($AG$14:$AG$99<>"",ROW($AG$14:$AG$99)-ROW(INDIRECT("$AG$13"))+1),ROW(INDIRECT("A" & AB48 ) ))),"")} | AI48: =IF(AND($E48="Oui", $F48 <> "", $M48 = ""),$F48,"") | AJ48: {=IFERROR(INDEX($AI$14:$AI$99,SMALL(IF($AI$14:$AI$99<>"",ROW($AI$14:$AI$99)-ROW(INDIRECT("$AI$13"))+1),ROW(INDIRECT("A" & AB48 ) ))),"")}
AB49: =ROW(A49)- $AD$2 +1 -> 36 | AC49: =IF(AND($E49="Oui",$M49="Préleveur"),$F49,"") | AD49: {=IFERROR(INDEX($AC$14:$AC$99,SMALL(IF($AC$14:$AC$99<>"",ROW($AC$14:$AC$99)-ROW(INDIRECT("$AC$13"))+1),ROW(INDIRECT("A" & AB49 ) ))),"")} | AE49: =IF(AND($E49="Oui",LEFT($M49,10) ="Débitmètre"),$F49,"") | AF49: {=IFERROR(INDEX($AE$14:$AE$99,SMALL(IF($AE$14:$AE$99<>"",ROW($AE$14:$AE$99)-ROW(INDIRECT("$AE$13"))+1),ROW(INDIRECT("A" & AB49 ) ))),"")} | AG49: =IF(AND($E49="Oui",LEFT($M49,5) ="Sonde"),$F49,"") | AH49: {=IFERROR(INDEX($AG$14:$AG$99,SMALL(IF($AG$14:$AG$99<>"",ROW($AG$14:$AG$99)-ROW(INDIRECT("$AG$13"))+1),ROW(INDIRECT("A" & AB49 ) ))),"")} | AI49: =IF(AND($E49="Oui", $F49 <> "", $M49 = ""),$F49,"") | AJ49: {=IFERROR(INDEX($AI$14:$AI$99,SMALL(IF($AI$14:$AI$99<>"",ROW($AI$14:$AI$99)-ROW(INDIRECT("$AI$13"))+1),ROW(INDIRECT("A" & AB49 ) ))),"")}
AB50: =ROW(A50)- $AD$2 +1 -> 37 | AC50: =IF(AND($E50="Oui",$M50="Préleveur"),$F50,"") | AD50: {=IFERROR(INDEX($AC$14:$AC$99,SMALL(IF($AC$14:$AC$99<>"",ROW($AC$14:$AC$99)-ROW(INDIRECT("$AC$13"))+1),ROW(INDIRECT("A" & AB50 ) ))),"")} | AE50: =IF(AND($E50="Oui",LEFT($M50,10) ="Débitmètre"),$F50,"") | AF50: {=IFERROR(INDEX($AE$14:$AE$99,SMALL(IF($AE$14:$AE$99<>"",ROW($AE$14:$AE$99)-ROW(INDIRECT("$AE$13"))+1),ROW(INDIRECT("A" & AB50 ) ))),"")} | AG50: =IF(AND($E50="Oui",LEFT($M50,5) ="Sonde"),$F50,"") | AH50: {=IFERROR(INDEX($AG$14:$AG$99,SMALL(IF($AG$14:$AG$99<>"",ROW($AG$14:$AG$99)-ROW(INDIRECT("$AG$13"))+1),ROW(INDIRECT("A" & AB50 ) ))),"")} | AI50: =IF(AND($E50="Oui", $F50 <> "", $M50 = ""),$F50,"") | AJ50: {=IFERROR(INDEX($AI$14:$AI$99,SMALL(IF($AI$14:$AI$99<>"",ROW($AI$14:$AI$99)-ROW(INDIRECT("$AI$13"))+1),ROW(INDIRECT("A" & AB50 ) ))),"")}
AB51: =ROW(A51)- $AD$2 +1 -> 38 | AC51: =IF(AND($E51="Oui",$M51="Préleveur"),$F51,"") | AD51: {=IFERROR(INDEX($AC$14:$AC$99,SMALL(IF($AC$14:$AC$99<>"",ROW($AC$14:$AC$99)-ROW(INDIRECT("$AC$13"))+1),ROW(INDIRECT("A" & AB51 ) ))),"")} | AE51: =IF(AND($E51="Oui",LEFT($M51,10) ="Débitmètre"),$F51,"") | AF51: {=IFERROR(INDEX($AE$14:$AE$99,SMALL(IF($AE$14:$AE$99<>"",ROW($AE$14:$AE$99)-ROW(INDIRECT("$AE$13"))+1),ROW(INDIRECT("A" & AB51 ) ))),"")} | AG51: =IF(AND($E51="Oui",LEFT($M51,5) ="Sonde"),$F51,"") | AH51: {=IFERROR(INDEX($AG$14:$AG$99,SMALL(IF($AG$14:$AG$99<>"",ROW($AG$14:$AG$99)-ROW(INDIRECT("$AG$13"))+1),ROW(INDIRECT("A" & AB51 ) ))),"")} | AI51: =IF(AND($E51="Oui", $F51 <> "", $M51 = ""),$F51,"") | AJ51: {=IFERROR(INDEX($AI$14:$AI$99,SMALL(IF($AI$14:$AI$99<>"",ROW($AI$14:$AI$99)-ROW(INDIRECT("$AI$13"))+1),ROW(INDIRECT("A" & AB51 ) ))),"")}
AB52: =ROW(A52)- $AD$2 +1 -> 39 | AC52: =IF(AND($E52="Oui",$M52="Préleveur"),$F52,"") | AD52: {=IFERROR(INDEX($AC$14:$AC$99,SMALL(IF($AC$14:$AC$99<>"",ROW($AC$14:$AC$99)-ROW(INDIRECT("$AC$13"))+1),ROW(INDIRECT("A" & AB52 ) ))),"")} | AE52: =IF(AND($E52="Oui",LEFT($M52,10) ="Débitmètre"),$F52,"") | AF52: {=IFERROR(INDEX($AE$14:$AE$99,SMALL(IF($AE$14:$AE$99<>"",ROW($AE$14:$AE$99)-ROW(INDIRECT("$AE$13"))+1),ROW(INDIRECT("A" & AB52 ) ))),"")} | AG52: =IF(AND($E52="Oui",LEFT($M52,5) ="Sonde"),$F52,"") | AH52: {=IFERROR(INDEX($AG$14:$AG$99,SMALL(IF($AG$14:$AG$99<>"",ROW($AG$14:$AG$99)-ROW(INDIRECT("$AG$13"))+1),ROW(INDIRECT("A" & AB52 ) ))),"")} | AI52: =IF(AND($E52="Oui", $F52 <> "", $M52 = ""),$F52,"") | AJ52: {=IFERROR(INDEX($AI$14:$AI$99,SMALL(IF($AI$14:$AI$99<>"",ROW($AI$14:$AI$99)-ROW(INDIRECT("$AI$13"))+1),ROW(INDIRECT("A" & AB52 ) ))),"")}
AB53: =ROW(A53)- $AD$2 +1 -> 40 | AC53: =IF(AND($E53="Oui",$M53="Préleveur"),$F53,"") | AD53: {=IFERROR(INDEX($AC$14:$AC$99,SMALL(IF($AC$14:$AC$99<>"",ROW($AC$14:$AC$99)-ROW(INDIRECT("$AC$13"))+1),ROW(INDIRECT("A" & AB53 ) ))),"")} | AE53: =IF(AND($E53="Oui",LEFT($M53,10) ="Débitmètre"),$F53,"") | AF53: {=IFERROR(INDEX($AE$14:$AE$99,SMALL(IF($AE$14:$AE$99<>"",ROW($AE$14:$AE$99)-ROW(INDIRECT("$AE$13"))+1),ROW(INDIRECT("A" & AB53 ) ))),"")} | AG53: =IF(AND($E53="Oui",LEFT($M53,5) ="Sonde"),$F53,"") | AH53: {=IFERROR(INDEX($AG$14:$AG$99,SMALL(IF($AG$14:$AG$99<>"",ROW($AG$14:$AG$99)-ROW(INDIRECT("$AG$13"))+1),ROW(INDIRECT("A" & AB53 ) ))),"")} | AI53: =IF(AND($E53="Oui", $F53 <> "", $M53 = ""),$F53,"") | AJ53: {=IFERROR(INDEX($AI$14:$AI$99,SMALL(IF($AI$14:$AI$99<>"",ROW($AI$14:$AI$99)-ROW(INDIRECT("$AI$13"))+1),ROW(INDIRECT("A" & AB53 ) ))),"")}
AB54: =ROW(A54)- $AD$2 +1 -> 41 | AC54: =IF(AND($E54="Oui",$M54="Préleveur"),$F54,"") | AD54: {=IFERROR(INDEX($AC$14:$AC$99,SMALL(IF($AC$14:$AC$99<>"",ROW($AC$14:$AC$99)-ROW(INDIRECT("$AC$13"))+1),ROW(INDIRECT("A" & AB54 ) ))),"")} | AE54: =IF(AND($E54="Oui",LEFT($M54,10) ="Débitmètre"),$F54,"") | AF54: {=IFERROR(INDEX($AE$14:$AE$99,SMALL(IF($AE$14:$AE$99<>"",ROW($AE$14:$AE$99)-ROW(INDIRECT("$AE$13"))+1),ROW(INDIRECT("A" & AB54 ) ))),"")} | AG54: =IF(AND($E54="Oui",LEFT($M54,5) ="Sonde"),$F54,"") | AH54: {=IFERROR(INDEX($AG$14:$AG$99,SMALL(IF($AG$14:$AG$99<>"",ROW($AG$14:$AG$99)-ROW(INDIRECT("$AG$13"))+1),ROW(INDIRECT("A" & AB54 ) ))),"")} | AI54: =IF(AND($E54="Oui", $F54 <> "", $M54 = ""),$F54,"") | AJ54: {=IFERROR(INDEX($AI$14:$AI$99,SMALL(IF($AI$14:$AI$99<>"",ROW($AI$14:$AI$99)-ROW(INDIRECT("$AI$13"))+1),ROW(INDIRECT("A" & AB54 ) ))),"")}
AB55: =ROW(A55)- $AD$2 +1 -> 42 | AC55: =IF(AND($E55="Oui",$M55="Préleveur"),$F55,"") | AD55: {=IFERROR(INDEX($AC$14:$AC$99,SMALL(IF($AC$14:$AC$99<>"",ROW($AC$14:$AC$99)-ROW(INDIRECT("$AC$13"))+1),ROW(INDIRECT("A" & AB55 ) ))),"")} | AE55: =IF(AND($E55="Oui",LEFT($M55,10) ="Débitmètre"),$F55,"") | AF55: {=IFERROR(INDEX($AE$14:$AE$99,SMALL(IF($AE$14:$AE$99<>"",ROW($AE$14:$AE$99)-ROW(INDIRECT("$AE$13"))+1),ROW(INDIRECT("A" & AB55 ) ))),"")} | AG55: =IF(AND($E55="Oui",LEFT($M55,5) ="Sonde"),$F55,"") | AH55: {=IFERROR(INDEX($AG$14:$AG$99,SMALL(IF($AG$14:$AG$99<>"",ROW($AG$14:$AG$99)-ROW(INDIRECT("$AG$13"))+1),ROW(INDIRECT("A" & AB55 ) ))),"")} | AI55: =IF(AND($E55="Oui", $F55 <> "", $M55 = ""),$F55,"") | AJ55: {=IFERROR(INDEX($AI$14:$AI$99,SMALL(IF($AI$14:$AI$99<>"",ROW($AI$14:$AI$99)-ROW(INDIRECT("$AI$13"))+1),ROW(INDIRECT("A" & AB55 ) ))),"")}
AB56: =ROW(A56)- $AD$2 +1 -> 43 | AC56: =IF(AND($E56="Oui",$M56="Préleveur"),$F56,"") | AD56: {=IFERROR(INDEX($AC$14:$AC$99,SMALL(IF($AC$14:$AC$99<>"",ROW($AC$14:$AC$99)-ROW(INDIRECT("$AC$13"))+1),ROW(INDIRECT("A" & AB56 ) ))),"")} | AE56: =IF(AND($E56="Oui",LEFT($M56,10) ="Débitmètre"),$F56,"") | AF56: {=IFERROR(INDEX($AE$14:$AE$99,SMALL(IF($AE$14:$AE$99<>"",ROW($AE$14:$AE$99)-ROW(INDIRECT("$AE$13"))+1),ROW(INDIRECT("A" & AB56 ) ))),"")} | AG56: =IF(AND($E56="Oui",LEFT($M56,5) ="Sonde"),$F56,"") | AH56: {=IFERROR(INDEX($AG$14:$AG$99,SMALL(IF($AG$14:$AG$99<>"",ROW($AG$14:$AG$99)-ROW(INDIRECT("$AG$13"))+1),ROW(INDIRECT("A" & AB56 ) ))),"")} | AI56: =IF(AND($E56="Oui", $F56 <> "", $M56 = ""),$F56,"") | AJ56: {=IFERROR(INDEX($AI$14:$AI$99,SMALL(IF($AI$14:$AI$99<>"",ROW($AI$14:$AI$99)-ROW(INDIRECT("$AI$13"))+1),ROW(INDIRECT("A" & AB56 ) ))),"")}
... AB91: =ROW(A91)- $AD$2 +1 -> 78 | AC91: =IF(AND($E91="Oui",$M91="Préleveur"),$F91,"") | AD91: {=IFERROR(INDEX($AC$14:$AC$99,SMALL(IF($AC$14:$AC$99<>"",ROW($AC$14:$AC$99)-ROW(INDIRECT("$AC$13"))+1),ROW(INDIRECT("A" & AB91 ) ))),"")} | AE91: =IF(AND($E91="Oui",LEFT($M91,10) ="Débitmètre"),$F91,"") | AF91: {=IFERROR(INDEX($AE$14:$AE$99,SMALL(IF($AE$14:$AE$99<>"",ROW($AE$14:$AE$99)-ROW(INDIRECT("$AE$13"))+1),ROW(INDIRECT("A" & AB91 ) ))),"")} | AG91: =IF(AND($E91="Oui",LEFT($M91,5) ="Sonde"),$F91,"") | AH91: {=IFERROR(INDEX($AG$14:$AG$99,SMALL(IF($AG$14:$AG$99<>"",ROW($AG$14:$AG$99)-ROW(INDIRECT("$AG$13"))+1),ROW(INDIRECT("A" & AB91 ) ))),"")} | AI91: =IF(AND($E91="Oui", $F91 <> "", $M91 = ""),$F91,"") | AJ91: {=IFERROR(INDEX($AI$14:$AI$99,SMALL(IF($AI$14:$AI$99<>"",ROW($AI$14:$AI$99)-ROW(INDIRECT("$AI$13"))+1),ROW(INDIRECT("A" & AB91 ) ))),"")}
AI92: =IF(AND($E92="Oui", $M92 <> "", $M92 = ""),$F92,"") | AJ92: {=IFERROR(INDEX($AI$14:$AI$99,SMALL(IF($AI$14:$AI$99<>"",ROW($AI$14:$AI$99)-ROW(INDIRECT("$AI$13"))+1),ROW(INDIRECT("A" & AB92 ) ))),"")}

Sheet SYNTHESE_SCL
C2: CONTRÔLE ANNUEL DES DISPOSITIFS D'AUTOSURVEILLANCE DES SYSTÈMES D'ASSAINISSEMENT COLLECTIF | Y2: Exporter en Word
C3: NOM DU SYSTÈME D'ASSAINISSEMENT : | G3: =IF(ISBLANK(Descriptif!F3),"",Descriptif!F3) | J3: NOM DU SYSTÈME DE TRAITEMENT : | M3: =IF(ISBLANK(Descriptif!L3),"",Descriptif!L3) | P3: NOM DU SYSTÈME DE COLLECTE : | S3: =IF(ISBLANK(Descriptif!Q3),"",Descriptif!Q3) | V3: NOM DE L'ORGANISME DE CONTRÔLE : | Y3: =IF(ISBLANK(Descriptif!U3),"",Descriptif!U3)
C4: CODE SANDRE DE L'AGGLOMÉRATION : | G4: =IF(ISBLANK(Descriptif!F4),"",Descriptif!F4) | J4: CODE SANDRE DE LA STATION : | M4: =IF(ISBLANK(Descriptif!L4),"",Descriptif!L4) | P4: CODE SANDRE DU RÉSEAU : | S4: =IF(ISBLANK(Descriptif!Q4),"",Descriptif!Q4) | V4: NOM(S) DU(ES) CONTROLEUR(S) : | Y4: =IF(ISBLANK(Descriptif!U4),"",Descriptif!U4)
C5: MAITRE D'OUVRAGE DE LA STATION : | G5: =IF(ISBLANK(Descriptif!F5),"",Descriptif!F5) | J5: TYPE DE TRAITEMENT : | M5: =IF(ISBLANK(Descriptif!L5),"",Descriptif!L5) | P5: TYPE DE RÉSEAU : | S5: =IF(ISBLANK(Descriptif!Q5),"",Descriptif!Q5) | V5: DATE(S) D'INTERVENTION : | Y5: =IF(ISBLANK(Descriptif!U5),"",Descriptif!U5)
C6: EXPLOITANT DE LA STATION : | G6: =IF(ISBLANK(Descriptif!F6),"",Descriptif!F6) | J6: CAPACITÉ DE LA STATION : | M6: =IF(ISBLANK(Descriptif!L6),"",Descriptif!L6) | P6: EXPLOITANT DU RÉSEAU : | S6: =IF(ISBLANK(Descriptif!Q6),"",Descriptif!Q6) | V6: CONDITION(S) MÉTÉO : | Y6: =IF(ISBLANK(Descriptif!U6),"",Descriptif!U6)
C8: SYNTHÈSE DES CONTRÔLES RÉALISÉS SUR LES DISPOSITIFS AUTOSURVEILLANCE
D11: Évaluation des pratiques de fractionnement et de transport des échantillons
K12: Penalité | N12: Commentaires sur l'évaluation :
G13: SDE | I13: Aquaref | K13: =IF(Analytique!N11<>"",Analytique!N11,"") | N13: =IF(Analytique!D17<>"",Analytique!D17,"")
G14: Eaux résiduaires | I14: Fractionnement | K14: =IF(Analytique!N12<>"",Analytique!N12,"")
I15: Température | K15: =IF(Analytique!N13<>"",Analytique!N13,"")
I16: Transport | K16: =IF(Analytique!N14<>"",Analytique!N14,"")
D19: Autres évaluations
K20: Score | N20: Commentaires sur l'évaluation :
G21: Sonde température | I21: {=IFERROR(INDEX(Equipements_SCL!$L$16:$L$72,SMALL(IF(Equipements_SCL!$J$16:$J$72="Sonde de température",ROW(Equipements_SCL!$J$16:$J$72)-ROW(Equipements_SCL!$J$16)+1),ROW(1:1))),"")} | K21: {=IFERROR(INDEX(Equipements_SCL!$P$16:$P$72,SMALL(IF(Equipements_SCL!$J$16:$J$72="Sonde de température",ROW(Equipements_SCL!$J$16:$J$72)-ROW(Equipements_SCL!$J$16)+1),ROW(1:1))),"")} | N21: {=IFERROR(INDEX(Equipements_SCL!$T$16:$T$72,SMALL(IF(Equipements_SCL!$J$16:$J$72="Sonde de température",ROW(Equipements_SCL!$J$16:$J$72)-ROW(Equipements_SCL!$J$16)+1),ROW(1:1))),"")}
I22: {=IFERROR(INDEX(Equipements_SCL!$L$16:$L$72,SMALL(IF(Equipements_SCL!$J$16:$J$72="Sonde de température",ROW(Equipements_SCL!$J$16:$J$72)-ROW(Equipements_SCL!$J$16)+1),ROW(2:2))),"")} | K22: {=IFERROR(INDEX(Equipements_SCL!$R$16:$R$72,SMALL(IF(Equipements_SCL!$J$16:$J$72="Sonde de température",ROW(Equipements_SCL!$J$16:$J$72)-ROW(Equipements_SCL!$J$16)+1),ROW(2:2))),"")} | N22: {=IFERROR(INDEX(Equipements_SCL!$T$16:$T$72,SMALL(IF(Equipements_SCL!$J$16:$J$72="Sonde de température",ROW(Equipements_SCL!$J$16:$J$72)-ROW(Equipements_SCL!$J$16)+1),ROW(2:2))),"")}
I23: {=IFERROR(INDEX(Equipements_SCL!$L$16:$L$72,SMALL(IF(Equipements_SCL!$J$16:$J$72="Sonde de température",ROW(Equipements_SCL!$J$16:$J$72)-ROW(Equipements_SCL!$J$16)+1),ROW(3:3))),"")} | K23: {=IFERROR(INDEX(Equipements_SCL!$R$16:$R$72,SMALL(IF(Equipements_SCL!$J$16:$J$72="Sonde de température",ROW(Equipements_SCL!$J$16:$J$72)-ROW(Equipements_SCL!$J$16)+1),ROW(3:3))),"")} | N23: {=IFERROR(INDEX(Equipements_SCL!$T$16:$T$72,SMALL(IF(Equipements_SCL!$J$16:$J$72="Sonde de température",ROW(Equipements_SCL!$J$16:$J$72)-ROW(Equipements_SCL!$J$16)+1),ROW(3:3))),"")}
K25: Score | N25: Commentaires sur l'évaluation :
G26: Pluviomètre | I26: {=IFERROR(INDEX(Equipements_SCL!$L$16:$L$72,SMALL(IF(Equipements_SCL!$J$16:$J$72="Pluviomètre",ROW(Equipements_SCL!$J$16:$J$72)-ROW(Equipements_SCL!$J$16)+1),ROW(1:1))),"")} | K26: {=IFERROR(INDEX(Equipements_SCL!$P$16:$P$72,SMALL(IF(Equipements_SCL!$J$16:$J$72="Pluviomètre",ROW(Equipements_SCL!$J$16:$J$72)-ROW(Equipements_SCL!$J$16)+1),ROW(1:1))),"")} | N26: {=IFERROR(INDEX(Equipements_SCL!$T$16:$T$72,SMALL(IF(Equipements_SCL!$J$16:$J$72="Pluviomètre",ROW(Equipements_SCL!$J$16:$J$72)-ROW(Equipements_SCL!$J$16)+1),ROW(1:1))),"")}
I27: {=IFERROR(INDEX(Equipements_SCL!$L$16:$L$72,SMALL(IF(Equipements_SCL!$J$16:$J$72="Pluviomètre",ROW(Equipements_SCL!$J$16:$J$72)-ROW(Equipements_SCL!$J$16)+1),ROW(2:2))),"")} | K27: {=IFERROR(INDEX(Equipements_SCL!$P$16:$P$72,SMALL(IF(Equipements_SCL!$J$16:$J$72="Pluviomètre",ROW(Equipements_SCL!$J$16:$J$72)-ROW(Equipements_SCL!$J$16)+1),ROW(2:2))),"")} | N27: {=IFERROR(INDEX(Equipements_SCL!$T$16:$T$72,SMALL(IF(Equipements_SCL!$J$16:$J$72="Pluviomètre",ROW(Equipements_SCL!$J$16:$J$72)-ROW(Equipements_SCL!$J$16)+1),ROW(2:2))),"")}
I28: {=IFERROR(INDEX(Equipements_SCL!$L$16:$L$72,SMALL(IF(Equipements_SCL!$J$16:$J$72="Pluviomètre",ROW(Equipements_SCL!$J$16:$J$72)-ROW(Equipements_SCL!$J$16)+1),ROW(3:3))),"")} | K28: {=IFERROR(INDEX(Equipements_SCL!$P$16:$P$72,SMALL(IF(Equipements_SCL!$J$16:$J$72="Pluviomètre",ROW(Equipements_SCL!$J$16:$J$72)-ROW(Equipements_SCL!$J$16)+1),ROW(3:3))),"")} | N28: {=IFERROR(INDEX(Equipements_SCL!$T$16:$T$72,SMALL(IF(Equipements_SCL!$J$16:$J$72="Pluviomètre",ROW(Equipements_SCL!$J$16:$J$72)-ROW(Equipements_SCL!$J$16)+1),ROW(3:3))),"")}
D31: Évaluation des points règlementaires du réseau
G32: Point | H32: Score | I32: Débitmètre | J32: Débitmètre gravitaire | K32: Débitmètre en charge | L32: Préleveur | M32: Analytique
G33: {=_xlfn._xlws.SORT(_xlfn.UNIQUE(_xlfn._xlws.FILTER(Equipements_SCL!$M$16:M100, Equipements_SCL!$M$16:M100<>"", "")))} | H33: =IF(AND($G33<>"",OR($I33<>"",$L33<>"",$M33<>"")),AVERAGE($I33,$L33,$M33),"") | I33: =IF(AND($G33<>"",OR($J33<>"",$K33<>"")),MAX($J33,$K33),"") | J33: =IF($G33="", "", IF(SUMIFS(Equipements_SCL!$P$16:$P$100, Equipements_SCL!$M$16:$M$100, $G33, Equipements_SCL!$J$16:$J$100, J$32)=0, "", SUMIFS(Equipements_SCL!$P$16:$P$100, Equipements_SCL!$M$16:$M$100, $G33, Equipements_SCL!$J$16:$J$100, J$32))) | K33: =IF($G33="", "", IF(SUMIFS(Equipements_SCL!$P$16:$P$100, Equipements_SCL!$M$16:$M$100, $G33, Equipements_SCL!$J$16:$J$100, K$32)=0, "", SUMIFS(Equipements_SCL!$P$16:$P$100, Equipements_SCL!$M$16:$M$100, $G33, Equipements_SCL!$J$16:$J$100, K$32))) | L33: =IF($G33="", "", IF(SUMIFS(Equipements_SCL!$P$16:$P$100, Equipements_SCL!$M$16:$M$100, $G33, Equipements_SCL!$J$16:$J$100, L$32)=0, "", SUMIFS(Equipements_SCL!$P$16:$P$100, Equipements_SCL!$M$16:$M$100, $G33, Equipements_SCL!$J$16:$J$100, L$32))) | M33: =IF( $G33="", "", IF( SUMIFS(Analytique!$AD$3:$AD$20, Analytique!$Z$3:$Z$20, $G33, Analytique!$Y$3:$Y$20, "A1")=0, "", SUMIFS(Analytique!$AD$3:$AD$20, Analytique!$Z$3:$Z$20, $G33, Analytique!$Y$3:$Y$20, "A1") ) )
G34: {=_xlfn._xlws.SORT(_xlfn.UNIQUE(_xlfn._xlws.FILTER(Equipements_SCL!$M$16:M101, Equipements_SCL!$M$16:M101<>"", "")))} | H34: =IF(AND($G34<>"",OR($I34<>"",$L34<>"",$M34<>"")),AVERAGE($I34,$L34,$M34),"") | I34: =IF(AND($G34<>"",OR($J34<>"",$K34<>"")),MAX($J34,$K34),"") | J34: =IF($G34="", "", IF(SUMIFS(Equipements_SCL!$P$16:$P$100, Equipements_SCL!$M$16:$M$100, $G34, Equipements_SCL!$J$16:$J$100, J$32)=0, "", SUMIFS(Equipements_SCL!$P$16:$P$100, Equipements_SCL!$M$16:$M$100, $G34, Equipements_SCL!$J$16:$J$100, J$32))) | K34: =IF($G34="", "", IF(SUMIFS(Equipements_SCL!$P$16:$P$100, Equipements_SCL!$M$16:$M$100, $G34, Equipements_SCL!$J$16:$J$100, K$32)=0, "", SUMIFS(Equipements_SCL!$P$16:$P$100, Equipements_SCL!$M$16:$M$100, $G34, Equipements_SCL!$J$16:$J$100, K$32))) | L34: =IF($G34="", "", IF(SUMIFS(Equipements_SCL!$P$16:$P$100, Equipements_SCL!$M$16:$M$100, $G34, Equipements_SCL!$J$16:$J$100, L$32)=0, "", SUMIFS(Equipements_SCL!$P$16:$P$100, Equipements_SCL!$M$16:$M$100, $G34, Equipements_SCL!$J$16:$J$100, L$32))) | M34: =IF( $G34="", "", IF( SUMIFS(Analytique!$AD$3:$AD$20, Analytique!$Z$3:$Z$20, $G34, Analytique!$Y$3:$Y$20, "A1")=0, "", SUMIFS(Analytique!$AD$3:$AD$20, Analytique!$Z$3:$Z$20, $G34, Analytique!$Y$3:$Y$20, "A1") ) )
G35: {=_xlfn._xlws.SORT(_xlfn.UNIQUE(_xlfn._xlws.FILTER(Equipements_SCL!$M$16:M102, Equipements_SCL!$M$16:M102<>"", "")))} | H35: =IF(AND($G35<>"",OR($I35<>"",$L35<>"",$M35<>"")),AVERAGE($I35,$L35,$M35),"") | I35: =IF(AND($G35<>"",OR($J35<>"",$K35<>"")),MAX($J35,$K35),"") | J35: =IF($G35="", "", IF(SUMIFS(Equipements_SCL!$P$16:$P$100, Equipements_SCL!$M$16:$M$100, $G35, Equipements_SCL!$J$16:$J$100, J$32)=0, "", SUMIFS(Equipements_SCL!$P$16:$P$100, Equipements_SCL!$M$16:$M$100, $G35, Equipements_SCL!$J$16:$J$100, J$32))) | K35: =IF($G35="", "", IF(SUMIFS(Equipements_SCL!$P$16:$P$100, Equipements_SCL!$M$16:$M$100, $G35, Equipements_SCL!$J$16:$J$100, K$32)=0, "", SUMIFS(Equipements_SCL!$P$16:$P$100, Equipements_SCL!$M$16:$M$100, $G35, Equipements_SCL!$J$16:$J$100, K$32))) | L35: =IF($G35="", "", IF(SUMIFS(Equipements_SCL!$P$16:$P$100, Equipements_SCL!$M$16:$M$100, $G35, Equipements_SCL!$J$16:$J$100, L$32)=0, "", SUMIFS(Equipements_SCL!$P$16:$P$100, Equipements_SCL!$M$16:$M$100, $G35, Equipements_SCL!$J$16:$J$100, L$32))) | M35: =IF( $G35="", "", IF( SUMIFS(Analytique!$AD$3:$AD$20, Analytique!$Z$3:$Z$20, $G35, Analytique!$Y$3:$Y$20, "A1")=0, "", SUMIFS(Analytique!$AD$3:$AD$20, Analytique!$Z$3:$Z$20, $G35, Analytique!$Y$3:$Y$20, "A1") ) )
G36: {=_xlfn._xlws.SORT(_xlfn.UNIQUE(_xlfn._xlws.FILTER(Equipements_SCL!$M$16:M103, Equipements_SCL!$M$16:M103<>"", "")))} | H36: =IF(AND($G36<>"",OR($I36<>"",$L36<>"",$M36<>"")),AVERAGE($I36,$L36,$M36),"") | I36: =IF(AND($G36<>"",OR($J36<>"",$K36<>"")),MAX($J36,$K36),"") | J36: =IF($G36="", "", IF(SUMIFS(Equipements_SCL!$P$16:$P$100, Equipements_SCL!$M$16:$M$100, $G36, Equipements_SCL!$J$16:$J$100, J$32)=0, "", SUMIFS(Equipements_SCL!$P$16:$P$100, Equipements_SCL!$M$16:$M$100, $G36, Equipements_SCL!$J$16:$J$100, J$32))) | K36: =IF($G36="", "", IF(SUMIFS(Equipements_SCL!$P$16:$P$100, Equipements_SCL!$M$16:$M$100, $G36, Equipements_SCL!$J$16:$J$100, K$32)=0, "", SUMIFS(Equipements_SCL!$P$16:$P$100, Equipements_SCL!$M$16:$M$100, $G36, Equipements_SCL!$J$16:$J$100, K$32))) | L36: =IF($G36="", "", IF(SUMIFS(Equipements_SCL!$P$16:$P$100, Equipements_SCL!$M$16:$M$100, $G36, Equipements_SCL!$J$16:$J$100, L$32)=0, "", SUMIFS(Equipements_SCL!$P$16:$P$100, Equipements_SCL!$M$16:$M$100, $G36, Equipements_SCL!$J$16:$J$100, L$32))) | M36: =IF( $G36="", "", IF( SUMIFS(Analytique!$AD$3:$AD$20, Analytique!$Z$3:$Z$20, $G36, Analytique!$Y$3:$Y$20, "A1")=0, "", SUMIFS(Analytique!$AD$3:$AD$20, Analytique!$Z$3:$Z$20, $G36, Analytique!$Y$3:$Y$20, "A1") ) )
G37: {=_xlfn._xlws.SORT(_xlfn.UNIQUE(_xlfn._xlws.FILTER(Equipements_SCL!$M$16:M104, Equipements_SCL!$M$16:M104<>"", "")))} | H37: =IF(AND($G37<>"",OR($I37<>"",$L37<>"",$M37<>"")),AVERAGE($I37,$L37,$M37),"") | I37: =IF(AND($G37<>"",OR($J37<>"",$K37<>"")),MAX($J37,$K37),"") | J37: =IF($G37="", "", IF(SUMIFS(Equipements_SCL!$P$16:$P$100, Equipements_SCL!$M$16:$M$100, $G37, Equipements_SCL!$J$16:$J$100, J$32)=0, "", SUMIFS(Equipements_SCL!$P$16:$P$100, Equipements_SCL!$M$16:$M$100, $G37, Equipements_SCL!$J$16:$J$100, J$32))) | K37: =IF($G37="", "", IF(SUMIFS(Equipements_SCL!$P$16:$P$100, Equipements_SCL!$M$16:$M$100, $G37, Equipements_SCL!$J$16:$J$100, K$32)=0, "", SUMIFS(Equipements_SCL!$P$16:$P$100, Equipements_SCL!$M$16:$M$100, $G37, Equipements_SCL!$J$16:$J$100, K$32))) | L37: =IF($G37="", "", IF(SUMIFS(Equipements_SCL!$P$16:$P$100, Equipements_SCL!$M$16:$M$100, $G37, Equipements_SCL!$J$16:$J$100, L$32)=0, "", SUMIFS(Equipements_SCL!$P$16:$P$100, Equipements_SCL!$M$16:$M$100, $G37, Equipements_SCL!$J$16:$J$100, L$32))) | M37: =IF( $G37="", "", IF( SUMIFS(Analytique!$AD$3:$AD$20, Analytique!$Z$3:$Z$20, $G37, Analytique!$Y$3:$Y$20, "A1")=0, "", SUMIFS(Analytique!$AD$3:$AD$20, Analytique!$Z$3:$Z$20, $G37, Analytique!$Y$3:$Y$20, "A1") ) )
G38: {=_xlfn._xlws.SORT(_xlfn.UNIQUE(_xlfn._xlws.FILTER(Equipements_SCL!$M$16:M105, Equipements_SCL!$M$16:M105<>"", "")))} | H38: =IF(AND($G38<>"",OR($I38<>"",$L38<>"",$M38<>"")),AVERAGE($I38,$L38,$M38),"") | I38: =IF(AND($G38<>"",OR($J38<>"",$K38<>"")),MAX($J38,$K38),"") | J38: =IF($G38="", "", IF(SUMIFS(Equipements_SCL!$P$16:$P$100, Equipements_SCL!$M$16:$M$100, $G38, Equipements_SCL!$J$16:$J$100, J$32)=0, "", SUMIFS(Equipements_SCL!$P$16:$P$100, Equipements_SCL!$M$16:$M$100, $G38, Equipements_SCL!$J$16:$J$100, J$32))) | K38: =IF($G38="", "", IF(SUMIFS(Equipements_SCL!$P$16:$P$100, Equipements_SCL!$M$16:$M$100, $G38, Equipements_SCL!$J$16:$J$100, K$32)=0, "", SUMIFS(Equipements_SCL!$P$16:$P$100, Equipements_SCL!$M$16:$M$100, $G38, Equipements_SCL!$J$16:$J$100, K$32))) | L38: =IF($G38="", "", IF(SUMIFS(Equipements_SCL!$P$16:$P$100, Equipements_SCL!$M$16:$M$100, $G38, Equipements_SCL!$J$16:$J$100, L$32)=0, "", SUMIFS(Equipements_SCL!$P$16:$P$100, Equipements_SCL!$M$16:$M$100, $G38, Equipements_SCL!$J$16:$J$100, L$32))) | M38: =IF( $G38="", "", IF( SUMIFS(Analytique!$AD$3:$AD$20, Analytique!$Z$3:$Z$20, $G38, Analytique!$Y$3:$Y$20, "A1")=0, "", SUMIFS(Analytique!$AD$3:$AD$20, Analytique!$Z$3:$Z$20, $G38, Analytique!$Y$3:$Y$20, "A1") ) )
G39: {=_xlfn._xlws.SORT(_xlfn.UNIQUE(_xlfn._xlws.FILTER(Equipements_SCL!$M$16:M106, Equipements_SCL!$M$16:M106<>"", "")))} | H39: =IF(AND($G39<>"",OR($I39<>"",$L39<>"",$M39<>"")),AVERAGE($I39,$L39,$M39),"") | I39: =IF(AND($G39<>"",OR($J39<>"",$K39<>"")),MAX($J39,$K39),"") | J39: =IF($G39="", "", IF(SUMIFS(Equipements_SCL!$P$16:$P$100, Equipements_SCL!$M$16:$M$100, $G39, Equipements_SCL!$J$16:$J$100, J$32)=0, "", SUMIFS(Equipements_SCL!$P$16:$P$100, Equipements_SCL!$M$16:$M$100, $G39, Equipements_SCL!$J$16:$J$100, J$32))) | K39: =IF($G39="", "", IF(SUMIFS(Equipements_SCL!$P$16:$P$100, Equipements_SCL!$M$16:$M$100, $G39, Equipements_SCL!$J$16:$J$100, K$32)=0, "", SUMIFS(Equipements_SCL!$P$16:$P$100, Equipements_SCL!$M$16:$M$100, $G39, Equipements_SCL!$J$16:$J$100, K$32))) | L39: =IF($G39="", "", IF(SUMIFS(Equipements_SCL!$P$16:$P$100, Equipements_SCL!$M$16:$M$100, $G39, Equipements_SCL!$J$16:$J$100, L$32)=0, "", SUMIFS(Equipements_SCL!$P$16:$P$100, Equipements_SCL!$M$16:$M$100, $G39, Equipements_SCL!$J$16:$J$100, L$32))) | M39: =IF( $G39="", "", IF( SUMIFS(Analytique!$AD$3:$AD$20, Analytique!$Z$3:$Z$20, $G39, Analytique!$Y$3:$Y$20, "A1")=0, "", SUMIFS(Analytique!$AD$3:$AD$20, Analytique!$Z$3:$Z$20, $G39, Analytique!$Y$3:$Y$20, "A1") ) )
G40: {=_xlfn._xlws.SORT(_xlfn.UNIQUE(_xlfn._xlws.FILTER(Equipements_SCL!$M$16:M107, Equipements_SCL!$M$16:M107<>"", "")))} | H40: =IF(AND($G40<>"",OR($I40<>"",$L40<>"",$M40<>"")),AVERAGE($I40,$L40,$M40),"") | I40: =IF(AND($G40<>"",OR($J40<>"",$K40<>"")),MAX($J40,$K40),"") | J40: =IF($G40="", "", IF(SUMIFS(Equipements_SCL!$P$16:$P$100, Equipements_SCL!$M$16:$M$100, $G40, Equipements_SCL!$J$16:$J$100, J$32)=0, "", SUMIFS(Equipements_SCL!$P$16:$P$100, Equipements_SCL!$M$16:$M$100, $G40, Equipements_SCL!$J$16:$J$100, J$32))) | K40: =IF($G40="", "", IF(SUMIFS(Equipements_SCL!$P$16:$P$100, Equipements_SCL!$M$16:$M$100, $G40, Equipements_SCL!$J$16:$J$100, K$32)=0, "", SUMIFS(Equipements_SCL!$P$16:$P$100, Equipements_SCL!$M$16:$M$100, $G40, Equipements_SCL!$J$16:$J$100, K$32))) | L40: =IF($G40="", "", IF(SUMIFS(Equipements_SCL!$P$16:$P$100, Equipements_SCL!$M$16:$M$100, $G40, Equipements_SCL!$J$16:$J$100, L$32)=0, "", SUMIFS(Equipements_SCL!$P$16:$P$100, Equipements_SCL!$M$16:$M$100, $G40, Equipements_SCL!$J$16:$J$100, L$32))) | M40: =IF( $G40="", "", IF( SUMIFS(Analytique!$AD$3:$AD$20, Analytique!$Z$3:$Z$20, $G40, Analytique!$Y$3:$Y$20, "A1")=0, "", SUMIFS(Analytique!$AD$3:$AD$20, Analytique!$Z$3:$Z$20, $G40, Analytique!$Y$3:$Y$20, "A1") ) )
G41: {=_xlfn._xlws.SORT(_xlfn.UNIQUE(_xlfn._xlws.FILTER(Equipements_SCL!$M$16:M108, Equipements_SCL!$M$16:M108<>"", "")))} | H41: =IF(AND($G41<>"",OR($I41<>"",$L41<>"",$M41<>"")),AVERAGE($I41,$L41,$M41),"") | I41: =IF(AND($G41<>"",OR($J41<>"",$K41<>"")),MAX($J41,$K41),"") | J41: =IF($G41="", "", IF(SUMIFS(Equipements_SCL!$P$16:$P$100, Equipements_SCL!$M$16:$M$100, $G41, Equipements_SCL!$J$16:$J$100, J$32)=0, "", SUMIFS(Equipements_SCL!$P$16:$P$100, Equipements_SCL!$M$16:$M$100, $G41, Equipements_SCL!$J$16:$J$100, J$32))) | K41: =IF($G41="", "", IF(SUMIFS(Equipements_SCL!$P$16:$P$100, Equipements_SCL!$M$16:$M$100, $G41, Equipements_SCL!$J$16:$J$100, K$32)=0, "", SUMIFS(Equipements_SCL!$P$16:$P$100, Equipements_SCL!$M$16:$M$100, $G41, Equipements_SCL!$J$16:$J$100, K$32))) | L41: =IF($G41="", "", IF(SUMIFS(Equipements_SCL!$P$16:$P$100, Equipements_SCL!$M$16:$M$100, $G41, Equipements_SCL!$J$16:$J$100, L$32)=0, "", SUMIFS(Equipements_SCL!$P$16:$P$100, Equipements_SCL!$M$16:$M$100, $G41, Equipements_SCL!$J$16:$J$100, L$32))) | M41: =IF( $G41="", "", IF( SUMIFS(Analytique!$AD$3:$AD$20, Analytique!$Z$3:$Z$20, $G41, Analytique!$Y$3:$Y$20, "A1")=0, "", SUMIFS(Analytique!$AD$3:$AD$20, Analytique!$Z$3:$Z$20, $G41, Analytique!$Y$3:$Y$20, "A1") ) )
G42: {=_xlfn._xlws.SORT(_xlfn.UNIQUE(_xlfn._xlws.FILTER(Equipements_SCL!$M$16:M109, Equipements_SCL!$M$16:M109<>"", "")))} | H42: =IF(AND($G42<>"",OR($I42<>"",$L42<>"",$M42<>"")),AVERAGE($I42,$L42,$M42),"") | I42: =IF(AND($G42<>"",OR($J42<>"",$K42<>"")),MAX($J42,$K42),"") | J42: =IF($G42="", "", IF(SUMIFS(Equipements_SCL!$P$16:$P$100, Equipements_SCL!$M$16:$M$100, $G42, Equipements_SCL!$J$16:$J$100, J$32)=0, "", SUMIFS(Equipements_SCL!$P$16:$P$100, Equipements_SCL!$M$16:$M$100, $G42, Equipements_SCL!$J$16:$J$100, J$32))) | K42: =IF($G42="", "", IF(SUMIFS(Equipements_SCL!$P$16:$P$100, Equipements_SCL!$M$16:$M$100, $G42, Equipements_SCL!$J$16:$J$100, K$32)=0, "", SUMIFS(Equipements_SCL!$P$16:$P$100, Equipements_SCL!$M$16:$M$100, $G42, Equipements_SCL!$J$16:$J$100, K$32))) | L42: =IF($G42="", "", IF(SUMIFS(Equipements_SCL!$P$16:$P$100, Equipements_SCL!$M$16:$M$100, $G42, Equipements_SCL!$J$16:$J$100, L$32)=0, "", SUMIFS(Equipements_SCL!$P$16:$P$100, Equipements_SCL!$M$16:$M$100, $G42, Equipements_SCL!$J$16:$J$100, L$32))) | M42: =IF( $G42="", "", IF( SUMIFS(Analytique!$AD$3:$AD$20, Analytique!$Z$3:$Z$20, $G42, Analytique!$Y$3:$Y$20, "A1")=0, "", SUMIFS(Analytique!$AD$3:$AD$20, Analytique!$Z$3:$Z$20, $G42, Analytique!$Y$3:$Y$20, "A1") ) )
G43: {=_xlfn._xlws.SORT(_xlfn.UNIQUE(_xlfn._xlws.FILTER(Equipements_SCL!$M$16:M110, Equipements_SCL!$M$16:M110<>"", "")))} | H43: =IF(AND($G43<>"",OR($I43<>"",$L43<>"",$M43<>"")),AVERAGE($I43,$L43,$M43),"") | I43: =IF(AND($G43<>"",OR($J43<>"",$K43<>"")),MAX($J43,$K43),"") | J43: =IF($G43="", "", IF(SUMIFS(Equipements_SCL!$P$16:$P$100, Equipements_SCL!$M$16:$M$100, $G43, Equipements_SCL!$J$16:$J$100, J$32)=0, "", SUMIFS(Equipements_SCL!$P$16:$P$100, Equipements_SCL!$M$16:$M$100, $G43, Equipements_SCL!$J$16:$J$100, J$32))) | K43: =IF($G43="", "", IF(SUMIFS(Equipements_SCL!$P$16:$P$100, Equipements_SCL!$M$16:$M$100, $G43, Equipements_SCL!$J$16:$J$100, K$32)=0, "", SUMIFS(Equipements_SCL!$P$16:$P$100, Equipements_SCL!$M$16:$M$100, $G43, Equipements_SCL!$J$16:$J$100, K$32))) | L43: =IF($G43="", "", IF(SUMIFS(Equipements_SCL!$P$16:$P$100, Equipements_SCL!$M$16:$M$100, $G43, Equipements_SCL!$J$16:$J$100, L$32)=0, "", SUMIFS(Equipements_SCL!$P$16:$P$100, Equipements_SCL!$M$16:$M$100, $G43, Equipements_SCL!$J$16:$J$100, L$32))) | M43: =IF( $G43="", "", IF( SUMIFS(Analytique!$AD$3:$AD$20, Analytique!$Z$3:$Z$20, $G43, Analytique!$Y$3:$Y$20, "A1")=0, "", SUMIFS(Analytique!$AD$3:$AD$20, Analytique!$Z$3:$Z$20, $G43, Analytique!$Y$3:$Y$20, "A1") ) )
G44: {=_xlfn._xlws.SORT(_xlfn.UNIQUE(_xlfn._xlws.FILTER(Equipements_SCL!$M$16:M111, Equipements_SCL!$M$16:M111<>"", "")))} | H44: =IF(AND($G44<>"",OR($I44<>"",$L44<>"",$M44<>"")),AVERAGE($I44,$L44,$M44),"") | I44: =IF(AND($G44<>"",OR($J44<>"",$K44<>"")),MAX($J44,$K44),"") | J44: =IF($G44="", "", IF(SUMIFS(Equipements_SCL!$P$16:$P$100, Equipements_SCL!$M$16:$M$100, $G44, Equipements_SCL!$J$16:$J$100, J$32)=0, "", SUMIFS(Equipements_SCL!$P$16:$P$100, Equipements_SCL!$M$16:$M$100, $G44, Equipements_SCL!$J$16:$J$100, J$32))) | K44: =IF($G44="", "", IF(SUMIFS(Equipements_SCL!$P$16:$P$100, Equipements_SCL!$M$16:$M$100, $G44, Equipements_SCL!$J$16:$J$100, K$32)=0, "", SUMIFS(Equipements_SCL!$P$16:$P$100, Equipements_SCL!$M$16:$M$100, $G44, Equipements_SCL!$J$16:$J$100, K$32))) | L44: =IF($G44="", "", IF(SUMIFS(Equipements_SCL!$P$16:$P$100, Equipements_SCL!$M$16:$M$100, $G44, Equipements_SCL!$J$16:$J$100, L$32)=0, "", SUMIFS(Equipements_SCL!$P$16:$P$100, Equipements_SCL!$M$16:$M$100, $G44, Equipements_SCL!$J$16:$J$100, L$32))) | M44: =IF( $G44="", "", IF( SUMIFS(Analytique!$AD$3:$AD$20, Analytique!$Z$3:$Z$20, $G44, Analytique!$Y$3:$Y$20, "A1")=0, "", SUMIFS(Analytique!$AD$3:$AD$20, Analytique!$Z$3:$Z$20, $G44, Analytique!$Y$3:$Y$20, "A1") ) )
... G57: {=_xlfn._xlws.SORT(_xlfn.UNIQUE(_xlfn._xlws.FILTER(Equipements_SCL!$M$16:M124, Equipements_SCL!$M$16:M124<>"", "")))} | H57: =IF(AND($G57<>"",OR($I57<>"",$L57<>"",$M57<>"")),AVERAGE($I57,$L57,$M57),"") | I57: =IF(AND($G57<>"",OR($J57<>"",$K57<>"")),MAX($J57,$K57),"") | J57: =IF($G57="", "", IF(SUMIFS(Equipements_SCL!$P$16:$P$100, Equipements_SCL!$M$16:$M$100, $G57, Equipements_SCL!$J$16:$J$100, J$32)=0, "", SUMIFS(Equipements_SCL!$P$16:$P$100, Equipements_SCL!$M$16:$M$100, $G57, Equipements_SCL!$J$16:$J$100, J$32))) | K57: =IF($G57="", "", IF(SUMIFS(Equipements_SCL!$P$16:$P$100, Equipements_SCL!$M$16:$M$100, $G57, Equipements_SCL!$J$16:$J$100, K$32)=0, "", SUMIFS(Equipements_SCL!$P$16:$P$100, Equipements_SCL!$M$16:$M$100, $G57, Equipements_SCL!$J$16:$J$100, K$32))) | L57: =IF($G57="", "", IF(SUMIFS(Equipements_SCL!$P$16:$P$100, Equipements_SCL!$M$16:$M$100, $G57, Equipements_SCL!$J$16:$J$100, L$32)=0, "", SUMIFS(Equipements_SCL!$P$16:$P$100, Equipements_SCL!$M$16:$M$100, $G57, Equipements_SCL!$J$16:$J$100, L$32))) | M57: =IF( $G57="", "", IF( SUMIFS(Analytique!$AD$3:$AD$20, Analytique!$Z$3:$Z$20, $G57, Analytique!$Y$3:$Y$20, "A1")=0, "", SUMIFS(Analytique!$AD$3:$AD$20, Analytique!$Z$3:$Z$20, $G57, Analytique!$Y$3:$Y$20, "A1") ) )
G58: Veuillez étendre le tableau si tous vos points réseau n'apparaissent pas
D62: Commentaire général
C68: DÉTAIL DES CONTRÔLES RÉALISÉS PAR ÉQUIPEMENT D'AUTOSURVEILLANCE
D70: Détails des équipements contrôlés | N70: Score sur 100 | O70: Critères d'évaluation
D71: Libellé | F71: Localisation | G71: Code Point | H71: Type d'équipement | J71: Type de matériel | O71: 1 | P71: 2 | Q71: 3 | R71: 4 | S71: 5 | T71: 6 | U71: 7 | V71: 8 | W71: 9 | X71: 10
D72: =Equipements_SCL!H16 | F72: =Equipements_SCL!I16 | G72: =Equipements_SCL!M16 | H72: =Equipements_SCL!J16 | J72: =Equipements_SCL!K16 | N72: =Equipements_SCL!P16 | O72: =IF(Equipements_SCL!Y16<>"",Equipements_SCL!AK16,"") | P72: =IF(Equipements_SCL!Z16<>"",Equipements_SCL!AL16,"") | Q72: =IF(Equipements_SCL!AA16<>"",Equipements_SCL!AM16,"") | R72: =IF(Equipements_SCL!AB16<>"",Equipements_SCL!AN16,"") | S72: =IF(Equipements_SCL!AC16<>"",Equipements_SCL!AO16,"") | T72: =IF(Equipements_SCL!AD16<>"",Equipements_SCL!AP16,"") | U72: =IF(Equipements_SCL!AE16<>"",Equipements_SCL!AQ16,"") | V72: =IF(Equipements_SCL!AF16<>"",Equipements_SCL!AR16,"") | ... X72: =IF(Equipements_SCL!AH16<>"",Equipements_SCL!AT16,"")
D73: =Equipements_SCL!H17 | F73: =Equipements_SCL!I17 | G73: =Equipements_SCL!M17 | H73: =Equipements_SCL!J17 | J73: =Equipements_SCL!K17 | N73: =Equipements_SCL!P17 | O73: =IF(Equipements_SCL!Y17<>"",Equipements_SCL!AK17,"") | P73: =IF(Equipements_SCL!Z17<>"",Equipements_SCL!AL17,"") | Q73: =IF(Equipements_SCL!AA17<>"",Equipements_SCL!AM17,"") | R73: =IF(Equipements_SCL!AB17<>"",Equipements_SCL!AN17,"") | S73: =IF(Equipements_SCL!AC17<>"",Equipements_SCL!AO17,"") | T73: =IF(Equipements_SCL!AD17<>"",Equipements_SCL!AP17,"") | U73: =IF(Equipements_SCL!AE17<>"",Equipements_SCL!AQ17,"") | V73: =IF(Equipements_SCL!AF17<>"",Equipements_SCL!AR17,"") | ... X73: =IF(Equipements_SCL!AH17<>"",Equipements_SCL!AT17,"")
D74: =Equipements_SCL!H18 | F74: =Equipements_SCL!I18 | G74: =Equipements_SCL!M18 | H74: =Equipements_SCL!J18 | J74: =Equipements_SCL!K18 | N74: =Equipements_SCL!P18 | O74: =IF(Equipements_SCL!Y18<>"",Equipements_SCL!AK18,"") | P74: =IF(Equipements_SCL!Z18<>"",Equipements_SCL!AL18,"") | Q74: =IF(Equipements_SCL!AA18<>"",Equipements_SCL!AM18,"") | R74: =IF(Equipements_SCL!AB18<>"",Equipements_SCL!AN18,"") | S74: =IF(Equipements_SCL!AC18<>"",Equipements_SCL!AO18,"") | T74: =IF(Equipements_SCL!AD18<>"",Equipements_SCL!AP18,"") | U74: =IF(Equipements_SCL!AE18<>"",Equipements_SCL!AQ18,"") | V74: =IF(Equipements_SCL!AF18<>"",Equipements_SCL!AR18,"") | ... X74: =IF(Equipements_SCL!AH18<>"",Equipements_SCL!AT18,"")
D75: =Equipements_SCL!H19 | F75: =Equipements_SCL!I19 | G75: =Equipements_SCL!M19 | H75: =Equipements_SCL!J19 | J75: =Equipements_SCL!K19 | N75: =Equipements_SCL!P19 | O75: =IF(Equipements_SCL!Y19<>"",Equipements_SCL!AK19,"") | P75: =IF(Equipements_SCL!Z19<>"",Equipements_SCL!AL19,"") | Q75: =IF(Equipements_SCL!AA19<>"",Equipements_SCL!AM19,"") | R75: =IF(Equipements_SCL!AB19<>"",Equipements_SCL!AN19,"") | S75: =IF(Equipements_SCL!AC19<>"",Equipements_SCL!AO19,"") | T75: =IF(Equipements_SCL!AD19<>"",Equipements_SCL!AP19,"") | U75: =IF(Equipements_SCL!AE19<>"",Equipements_SCL!AQ19,"") | V75: =IF(Equipements_SCL!AF19<>"",Equipements_SCL!AR19,"") | ... X75: =IF(Equipements_SCL!AH19<>"",Equipements_SCL!AT19,"")
D76: =Equipements_SCL!H20 | F76: =Equipements_SCL!I20 | G76: =Equipements_SCL!M20 | H76: =Equipements_SCL!J20 | J76: =Equipements_SCL!K20 | N76: =Equipements_SCL!P20 | O76: =IF(Equipements_SCL!Y20<>"",Equipements_SCL!AK20,"") | P76: =IF(Equipements_SCL!Z20<>"",Equipements_SCL!AL20,"") | Q76: =IF(Equipements_SCL!AA20<>"",Equipements_SCL!AM20,"") | R76: =IF(Equipements_SCL!AB20<>"",Equipements_SCL!AN20,"") | S76: =IF(Equipements_SCL!AC20<>"",Equipements_SCL!AO20,"") | T76: =IF(Equipements_SCL!AD20<>"",Equipements_SCL!AP20,"") | U76: =IF(Equipements_SCL!AE20<>"",Equipements_SCL!AQ20,"") | V76: =IF(Equipements_SCL!AF20<>"",Equipements_SCL!AR20,"") | ... X76: =IF(Equipements_SCL!AH20<>"",Equipements_SCL!AT20,"")
D77: =Equipements_SCL!H21 | F77: =Equipements_SCL!I21 | G77: =Equipements_SCL!M21 | H77: =Equipements_SCL!J21 | J77: =Equipements_SCL!K21 | N77: =Equipements_SCL!P21 | O77: =IF(Equipements_SCL!Y21<>"",Equipements_SCL!AK21,"") | P77: =IF(Equipements_SCL!Z21<>"",Equipements_SCL!AL21,"") | Q77: =IF(Equipements_SCL!AA21<>"",Equipements_SCL!AM21,"") | R77: =IF(Equipements_SCL!AB21<>"",Equipements_SCL!AN21,"") | S77: =IF(Equipements_SCL!AC21<>"",Equipements_SCL!AO21,"") | T77: =IF(Equipements_SCL!AD21<>"",Equipements_SCL!AP21,"") | U77: =IF(Equipements_SCL!AE21<>"",Equipements_SCL!AQ21,"") | V77: =IF(Equipements_SCL!AF21<>"",Equipements_SCL!AR21,"") | ... X77: =IF(Equipements_SCL!AH21<>"",Equipements_SCL!AT21,"")
D78: =Equipements_SCL!H22 | F78: =Equipements_SCL!I22 | G78: =Equipements_SCL!M22 | H78: =Equipements_SCL!J22 | J78: =Equipements_SCL!K22 | N78: =Equipements_SCL!P22 | O78: =IF(Equipements_SCL!Y22<>"",Equipements_SCL!AK22,"") | P78: =IF(Equipements_SCL!Z22<>"",Equipements_SCL!AL22,"") | Q78: =IF(Equipements_SCL!AA22<>"",Equipements_SCL!AM22,"") | R78: =IF(Equipements_SCL!AB22<>"",Equipements_SCL!AN22,"") | S78: =IF(Equipements_SCL!AC22<>"",Equipements_SCL!AO22,"") | T78: =IF(Equipements_SCL!AD22<>"",Equipements_SCL!AP22,"") | U78: =IF(Equipements_SCL!AE22<>"",Equipements_SCL!AQ22,"") | V78: =IF(Equipements_SCL!AF22<>"",Equipements_SCL!AR22,"") | ... X78: =IF(Equipements_SCL!AH22<>"",Equipements_SCL!AT22,"")
D79: =Equipements_SCL!H23 | F79: =Equipements_SCL!I23 | G79: =Equipements_SCL!M23 | H79: =Equipements_SCL!J23 | J79: =Equipements_SCL!K23 | N79: =Equipements_SCL!P23 | O79: =IF(Equipements_SCL!Y23<>"",Equipements_SCL!AK23,"") | P79: =IF(Equipements_SCL!Z23<>"",Equipements_SCL!AL23,"") | Q79: =IF(Equipements_SCL!AA23<>"",Equipements_SCL!AM23,"") | R79: =IF(Equipements_SCL!AB23<>"",Equipements_SCL!AN23,"") | S79: =IF(Equipements_SCL!AC23<>"",Equipements_SCL!AO23,"") | T79: =IF(Equipements_SCL!AD23<>"",Equipements_SCL!AP23,"") | U79: =IF(Equipements_SCL!AE23<>"",Equipements_SCL!AQ23,"") | V79: =IF(Equipements_SCL!AF23<>"",Equipements_SCL!AR23,"") | ... X79: =IF(Equipements_SCL!AH23<>"",Equipements_SCL!AT23,"")
D80: =Equipements_SCL!H24 | F80: =Equipements_SCL!I24 | G80: =Equipements_SCL!M24 | H80: =Equipements_SCL!J24 | J80: =Equipements_SCL!K24 | N80: =Equipements_SCL!P24 | O80: =IF(Equipements_SCL!Y24<>"",Equipements_SCL!AK24,"") | P80: =IF(Equipements_SCL!Z24<>"",Equipements_SCL!AL24,"") | Q80: =IF(Equipements_SCL!AA24<>"",Equipements_SCL!AM24,"") | R80: =IF(Equipements_SCL!AB24<>"",Equipements_SCL!AN24,"") | S80: =IF(Equipements_SCL!AC24<>"",Equipements_SCL!AO24,"") | T80: =IF(Equipements_SCL!AD24<>"",Equipements_SCL!AP24,"") | U80: =IF(Equipements_SCL!AE24<>"",Equipements_SCL!AQ24,"") | V80: =IF(Equipements_SCL!AF24<>"",Equipements_SCL!AR24,"") | ... X80: =IF(Equipements_SCL!AH24<>"",Equipements_SCL!AT24,"")
D81: =Equipements_SCL!H25 | F81: =Equipements_SCL!I25 | G81: =Equipements_SCL!M25 | H81: =Equipements_SCL!J25 | J81: =Equipements_SCL!K25 | N81: =Equipements_SCL!P25 | O81: =IF(Equipements_SCL!Y25<>"",Equipements_SCL!AK25,"") | P81: =IF(Equipements_SCL!Z25<>"",Equipements_SCL!AL25,"") | Q81: =IF(Equipements_SCL!AA25<>"",Equipements_SCL!AM25,"") | R81: =IF(Equipements_SCL!AB25<>"",Equipements_SCL!AN25,"") | S81: =IF(Equipements_SCL!AC25<>"",Equipements_SCL!AO25,"") | T81: =IF(Equipements_SCL!AD25<>"",Equipements_SCL!AP25,"") | U81: =IF(Equipements_SCL!AE25<>"",Equipements_SCL!AQ25,"") | V81: =IF(Equipements_SCL!AF25<>"",Equipements_SCL!AR25,"") | ... X81: =IF(Equipements_SCL!AH25<>"",Equipements_SCL!AT25,"")
D82: =Equipements_SCL!H26 | F82: =Equipements_SCL!I26 | G82: =Equipements_SCL!M26 | H82: =Equipements_SCL!J26 | J82: =Equipements_SCL!K26 | N82: =Equipements_SCL!P26 | O82: =IF(Equipements_SCL!Y26<>"",Equipements_SCL!AK26,"") | P82: =IF(Equipements_SCL!Z26<>"",Equipements_SCL!AL26,"") | Q82: =IF(Equipements_SCL!AA26<>"",Equipements_SCL!AM26,"") | R82: =IF(Equipements_SCL!AB26<>"",Equipements_SCL!AN26,"") | S82: =IF(Equipements_SCL!AC26<>"",Equipements_SCL!AO26,"") | T82: =IF(Equipements_SCL!AD26<>"",Equipements_SCL!AP26,"") | U82: =IF(Equipements_SCL!AE26<>"",Equipements_SCL!AQ26,"") | V82: =IF(Equipements_SCL!AF26<>"",Equipements_SCL!AR26,"") | ... X82: =IF(Equipements_SCL!AH26<>"",Equipements_SCL!AT26,"")
D83: =Equipements_SCL!H27 | F83: =Equipements_SCL!I27 | G83: =Equipements_SCL!M27 | H83: =Equipements_SCL!J27 | J83: =Equipements_SCL!K27 | N83: =Equipements_SCL!P27 | O83: =IF(Equipements_SCL!Y27<>"",Equipements_SCL!AK27,"") | P83: =IF(Equipements_SCL!Z27<>"",Equipements_SCL!AL27,"") | Q83: =IF(Equipements_SCL!AA27<>"",Equipements_SCL!AM27,"") | R83: =IF(Equipements_SCL!AB27<>"",Equipements_SCL!AN27,"") | S83: =IF(Equipements_SCL!AC27<>"",Equipements_SCL!AO27,"") | T83: =IF(Equipements_SCL!AD27<>"",Equipements_SCL!AP27,"") | U83: =IF(Equipements_SCL!AE27<>"",Equipements_SCL!AQ27,"") | V83: =IF(Equipements_SCL!AF27<>"",Equipements_SCL!AR27,"") | ... X83: =IF(Equipements_SCL!AH27<>"",Equipements_SCL!AT27,"")
... D121: =Equipements_SCL!H65 | F121: =Equipements_SCL!I65 | G121: =Equipements_SCL!M65 | H121: =Equipements_SCL!J65 | J121: =Equipements_SCL!K65 | N121: =Equipements_SCL!P65 | O121: =IF(Equipements_SCL!Y65<>"",Equipements_SCL!AK65,"") | P121: =IF(Equipements_SCL!Z65<>"",Equipements_SCL!AL65,"") | Q121: =IF(Equipements_SCL!AA65<>"",Equipements_SCL!AM65,"") | R121: =IF(Equipements_SCL!AB65<>"",Equipements_SCL!AN65,"") | S121: =IF(Equipements_SCL!AC65<>"",Equipements_SCL!AO65,"") | T121: =IF(Equipements_SCL!AD65<>"",Equipements_SCL!AP65,"") | U121: =IF(Equipements_SCL!AE65<>"",Equipements_SCL!AQ65,"") | V121: =IF(Equipements_SCL!AF65<>"",Equipements_SCL!AR65,"") | ... X121: =IF(Equipements_SCL!AH65<>"",Equipements_SCL!AT65,"")
D122: Veuillez étendre le tableau si tous vos équipements réseau n'apparaissent pas

Sheet SYNTHESE_STEU
C2: CONTRÔLE ANNUEL DES DISPOSITIFS D'AUTOSURVEILLANCE DES SYSTÈMES D'ASSAINISSEMENT COLLECTIF | Y2: Exporter en Word
C3: NOM DU SYSTÈME D'ASSAINISSEMENT : | G3: =IF(ISBLANK(Descriptif!F3),"",Descriptif!F3) | J3: NOM DU SYSTÈME DE TRAITEMENT : | M3: =IF(ISBLANK(Descriptif!L3),"",Descriptif!L3) | P3: NOM DU SYSTÈME DE COLLECTE : | S3: =IF(ISBLANK(Descriptif!Q3),"",Descriptif!Q3) | V3: NOM DE L'ORGANISME DE CONTRÔLE : | Y3: =IF(ISBLANK(Descriptif!U3),"",Descriptif!U3)
C4: CODE SANDRE DE L'AGGLOMÉRATION : | G4: =IF(ISBLANK(Descriptif!F4),"",Descriptif!F4) | J4: CODE SANDRE DE LA STATION : | M4: =IF(ISBLANK(Descriptif!L4),"",Descriptif!L4) | P4: CODE SANDRE DU RÉSEAU : | S4: =IF(ISBLANK(Descriptif!Q4),"",Descriptif!Q4) | V4: NOM(S) DU(ES) CONTROLEUR(S) : | Y4: =IF(ISBLANK(Descriptif!U4),"",Descriptif!U4)
C5: MAITRE D'OUVRAGE DE LA STATION : | G5: =IF(ISBLANK(Descriptif!F5),"",Descriptif!F5) | J5: TYPE DE TRAITEMENT : | M5: =IF(ISBLANK(Descriptif!L5),"",Descriptif!L5) | P5: TYPE DE RÉSEAU : | S5: =IF(ISBLANK(Descriptif!Q5),"",Descriptif!Q5) | V5: DATE(S) D'INTERVENTION : | Y5: =IF(ISBLANK(Descriptif!U5),"",Descriptif!U5)
C6: EXPLOITANT DE LA STATION : | G6: =IF(ISBLANK(Descriptif!F6),"",Descriptif!F6) | J6: CAPACITÉ DE LA STATION : | M6: =IF(ISBLANK(Descriptif!L6),"",Descriptif!L6) | P6: EXPLOITANT DU RÉSEAU : | S6: =IF(ISBLANK(Descriptif!Q6),"",Descriptif!Q6) | V6: CONDITION(S) MÉTÉO : | Y6: =IF(ISBLANK(Descriptif!U6),"",Descriptif!U6)
C8: SYNTHÈSE DES CONTRÔLES RÉALISÉS SUR LES DISPOSITIFS AUTOSURVEILLANCE
D10: Évaluation des points règlementaires
G11: ENTRÉE et SORTIE | J11: Score | L11: DTS ET BY-PASS | O11: Score | Q11: BOUES ET APPORTS EXTÉRIEURS | T11: Score | V11: RÉUTILISATION DES EAUX TRAITÉES | Y11: Score
G12: Point A3 | J12: =Recap_equipements!E63 | L12: Point A2 | O12: =Recap_equipements!E75 | Q12: Point A6 | T12: =Recap_equipements!E87 | V12: Point A8 | Y12: =Recap_equipements!E105
G13: Débitmètre | J13: =IF(Recap_equipements!F65<>"",Recap_equipements!F65,"") | L13: Débitmètre | O13: =IF(Recap_equipements!F77<>"",Recap_equipements!F77,"") | Q13: Débitmètre | T13: =IF(Recap_equipements!F89<>"",Recap_equipements!F89,"") | V13: Débitmètre | Y13: =IF(Recap_equipements!F107<>"",Recap_equipements!F107,"")
G14: Préleveur | J14: =IF(Recap_equipements!F66<>"",Recap_equipements!F66,"") | L14: Préleveur | O14: =IF(Recap_equipements!F78<>"",Recap_equipements!F78,"") | Q14: Préleveur | T14: =IF(Recap_equipements!F90<>"",Recap_equipements!F90,"") | V14: Préleveur | Y14: =IF(Recap_equipements!F108<>"",Recap_equipements!F108,"")
G15: Analytique | J15: =IF(Recap_equipements!F67<>"",Recap_equipements!F67,"") | L15: Analytique | O15: =IF(Recap_equipements!F79<>"",Recap_equipements!F79,"") | Q15: Analytique | T15: =IF(Recap_equipements!F91<>"",Recap_equipements!F91,"") | V15: Analytique | Y15: =IF(Recap_equipements!F109<>"",Recap_equipements!F109,"")
G16: Point A4 | J16: =Recap_equipements!E69 | L16: Point A5 | O16: =Recap_equipements!E81 | Q16: Point A7 | T16: =Recap_equipements!E93
G17: Débitmètre | J17: =IF(Recap_equipements!F71<>"",Recap_equipements!F71,"") | L17: Débitmètre | O17: =IF(Recap_equipements!F83<>"",Recap_equipements!F83,"") | Q17: Débitmètre | T17: =IF(Recap_equipements!F95<>"",Recap_equipements!F95,"") | V17: Validé
G18: Préleveur | J18: =IF(Recap_equipements!F72<>"",Recap_equipements!F72,"") | L18: Préleveur | O18: =IF(Recap_equipements!F84<>"",Recap_equipements!F84,"") | Q18: Préleveur | T18: =IF(Recap_equipements!F96<>"",Recap_equipements!F96,"") | V18: Réserve
G19: Analytique | J19: =IF(Recap_equipements!F73<>"",Recap_equipements!F73,"") | L19: Analytique | O19: =IF(Recap_equipements!F85<>"",Recap_equipements!F85,"") | Q19: Analytique | T19: =IF(Recap_equipements!F97<>"",Recap_equipements!F97,"") | V19: Non validé
D22: Évaluation documentaire
M23: Coefficient Qualité | N23: Commentaires sur l'évaluation :
G24: Manuel autosurveillance à jour, validé ou en cours d'expertise ? | L24: =IF(Qualité!L10<>"",Qualité!L10,"Non contrôlé") -> Non contrôlé | N24: =IF(Qualité!M10<>"",Qualité!M10,"")
G25: Existe-t-il un système Qualité performant ? | L25: =IF(Qualité!L29<>"",Qualité!L29,"Non contrôlé") -> Non contrôlé | M25: =IF(Qualité!L29="Oui",1,0.9) -> 0.9 | N25: =IF(Qualité!D32<>"",Qualité!D32,"")
D28: Évaluation des pratiques de fractionnement et de transport des échantillons
K29: Penalité | N29: Commentaires sur l'évaluation :
G30: SDE | I30: Aquaref | K30: =IF(Analytique!N11<>"",Analytique!N11,"") | N30: =IF(Analytique!D17<>"",Analytique!D17,"")
G31: Eaux résiduaires | I31: Fractionnement | K31: =IF(Analytique!N12<>"",Analytique!N12,"")
I32: Température | K32: =IF(Analytique!N13<>"",Analytique!N13,"")
I33: Transport | K33: =IF(Analytique!N14<>"",Analytique!N14,"")
D36: Autres évaluations
K37: Score | N37: Commentaires sur l'évaluation :
G38: Sonde température | I38: {=IFERROR(INDEX(Equipements_STEU!$L$16:$L$72,SMALL(IF(Equipements_STEU!$J$16:$J$72="Sonde de température",ROW(Equipements_STEU!$J$16:$J$72)-ROW(Equipements_STEU!$J$16)+1),ROW(1:1))),"")} | K38: {=IFERROR(INDEX(Equipements_STEU!$P$16:$P$72,SMALL(IF(Equipements_STEU!$J$16:$J$72="Sonde de température",ROW(Equipements_STEU!$J$16:$J$72)-ROW(Equipements_STEU!$J$16)+1),ROW(1:1))),"")} | N38: {=IFERROR(INDEX(Equipements_STEU!$T$16:$T$72,SMALL(IF(Equipements_STEU!$J$16:$J$72="Sonde de température",ROW(Equipements_STEU!$J$16:$J$72)-ROW(Equipements_STEU!$J$16)+1),ROW(1:1))),"")}
I39: {=IFERROR(INDEX(Equipements_STEU!$L$16:$L$72,SMALL(IF(Equipements_STEU!$J$16:$J$72="Sonde de température",ROW(Equipements_STEU!$J$16:$J$72)-ROW(Equipements_STEU!$J$16)+1),ROW(2:2))),"")} | K39: {=IFERROR(INDEX(Equipements_STEU!$R$16:$R$72,SMALL(IF(Equipements_STEU!$J$16:$J$72="Sonde de température",ROW(Equipements_STEU!$J$16:$J$72)-ROW(Equipements_STEU!$J$16)+1),ROW(2:2))),"")} | N39: {=IFERROR(INDEX(Equipements_STEU!$T$16:$T$72,SMALL(IF(Equipements_STEU!$J$16:$J$72="Sonde de température",ROW(Equipements_STEU!$J$16:$J$72)-ROW(Equipements_STEU!$J$16)+1),ROW(2:2))),"")}
I40: {=IFERROR(INDEX(Equipements_STEU!$L$16:$L$72,SMALL(IF(Equipements_STEU!$J$16:$J$72="Sonde de température",ROW(Equipements_STEU!$J$16:$J$72)-ROW(Equipements_STEU!$J$16)+1),ROW(3:3))),"")} | K40: {=IFERROR(INDEX(Equipements_STEU!$R$16:$R$72,SMALL(IF(Equipements_STEU!$J$16:$J$72="Sonde de température",ROW(Equipements_STEU!$J$16:$J$72)-ROW(Equipements_STEU!$J$16)+1),ROW(3:3))),"")} | N40: {=IFERROR(INDEX(Equipements_STEU!$T$16:$T$72,SMALL(IF(Equipements_STEU!$J$16:$J$72="Sonde de température",ROW(Equipements_STEU!$J$16:$J$72)-ROW(Equipements_STEU!$J$16)+1),ROW(3:3))),"")}
K42: Score | N42: Commentaires sur l'évaluation :
G43: Pluviomètre | I43: {=IFERROR(INDEX(Equipements_STEU!$L$16:$L$72,SMALL(IF(Equipements_STEU!$J$16:$J$72="Pluviomètre",ROW(Equipements_STEU!$J$16:$J$72)-ROW(Equipements_STEU!$J$16)+1),ROW(1:1))),"")} | K43: {=IFERROR(INDEX(Equipements_STEU!$P$16:$P$72,SMALL(IF(Equipements_STEU!$J$16:$J$72="Pluviomètre",ROW(Equipements_STEU!$J$16:$J$72)-ROW(Equipements_STEU!$J$16)+1),ROW(1:1))),"")} | N43: {=IFERROR(INDEX(Equipements_STEU!$T$16:$T$72,SMALL(IF(Equipements_STEU!$J$16:$J$72="Pluviomètre",ROW(Equipements_STEU!$J$16:$J$72)-ROW(Equipements_STEU!$J$16)+1),ROW(1:1))),"")}
I44: {=IFERROR(INDEX(Equipements_STEU!$L$16:$L$72,SMALL(IF(Equipements_STEU!$J$16:$J$72="Pluviomètre",ROW(Equipements_STEU!$J$16:$J$72)-ROW(Equipements_STEU!$J$16)+1),ROW(2:2))),"")} | K44: {=IFERROR(INDEX(Equipements_STEU!$P$16:$P$72,SMALL(IF(Equipements_STEU!$J$16:$J$72="Pluviomètre",ROW(Equipements_STEU!$J$16:$J$72)-ROW(Equipements_STEU!$J$16)+1),ROW(2:2))),"")} | N44: {=IFERROR(INDEX(Equipements_STEU!$T$16:$T$72,SMALL(IF(Equipements_STEU!$J$16:$J$72="Pluviomètre",ROW(Equipements_STEU!$J$16:$J$72)-ROW(Equipements_STEU!$J$16)+1),ROW(2:2))),"")}
I45: {=IFERROR(INDEX(Equipements_STEU!$L$16:$L$72,SMALL(IF(Equipements_STEU!$J$16:$J$72="Pluviomètre",ROW(Equipements_STEU!$J$16:$J$72)-ROW(Equipements_STEU!$J$16)+1),ROW(3:3))),"")} | K45: {=IFERROR(INDEX(Equipements_STEU!$P$16:$P$72,SMALL(IF(Equipements_STEU!$J$16:$J$72="Pluviomètre",ROW(Equipements_STEU!$J$16:$J$72)-ROW(Equipements_STEU!$J$16)+1),ROW(3:3))),"")} | N45: {=IFERROR(INDEX(Equipements_STEU!$T$16:$T$72,SMALL(IF(Equipements_STEU!$J$16:$J$72="Pluviomètre",ROW(Equipements_STEU!$J$16:$J$72)-ROW(Equipements_STEU!$J$16)+1),ROW(3:3))),"")}
D48: Commentaire général
C54: DÉTAIL DES CONTRÔLES RÉALISÉS PAR ÉQUIPEMENT D'AUTOSURVEILLANCE
D56: Détails des équipements contrôlés | N56: Score sur 100 | O56: Critères d'évaluation
D57: Libellé | F57: Localisation | G57: Code Point | H57: Type d'équipement | J57: Type de matériel | O57: 1 | P57: 2 | Q57: 3 | R57: 4 | S57: 5 | T57: 6 | U57: 7 | V57: 8 | W57: 9 | X57: 10
D58: =Equipements_STEU!H16 | F58: =Equipements_STEU!I16 | G58: =Equipements_STEU!M16 | H58: =Equipements_STEU!J16 | J58: =Equipements_STEU!K16 | N58: =Equipements_STEU!P16 | O58: =IF(Equipements_STEU!Y16<>"",Equipements_STEU!AK16,"") | P58: =IF(Equipements_STEU!Z16<>"",Equipements_STEU!AL16,"") | Q58: =IF(Equipements_STEU!AA16<>"",Equipements_STEU!AM16,"") | R58: =IF(Equipements_STEU!AB16<>"",Equipements_STEU!AN16,"") | S58: =IF(Equipements_STEU!AC16<>"",Equipements_STEU!AO16,"") | T58: =IF(Equipements_STEU!AD16<>"",Equipements_STEU!AP16,"") | U58: =IF(Equipements_STEU!AE16<>"",Equipements_STEU!AQ16,"") | V58: =IF(Equipements_STEU!AF16<>"",Equipements_STEU!AR16,"") | ... X58: =IF(Equipements_STEU!AH16<>"",Equipements_STEU!AT16,"")
D59: =Equipements_STEU!H17 | F59: =Equipements_STEU!I17 | G59: =Equipements_STEU!M17 | H59: =Equipements_STEU!J17 | J59: =Equipements_STEU!K17 | N59: =Equipements_STEU!P17 | O59: =IF(Equipements_STEU!Y17<>"",Equipements_STEU!AK17,"") | P59: =IF(Equipements_STEU!Z17<>"",Equipements_STEU!AL17,"") | Q59: =IF(Equipements_STEU!AA17<>"",Equipements_STEU!AM17,"") | R59: =IF(Equipements_STEU!AB17<>"",Equipements_STEU!AN17,"") | S59: =IF(Equipements_STEU!AC17<>"",Equipements_STEU!AO17,"") | T59: =IF(Equipements_STEU!AD17<>"",Equipements_STEU!AP17,"") | U59: =IF(Equipements_STEU!AE17<>"",Equipements_STEU!AQ17,"") | V59: =IF(Equipements_STEU!AF17<>"",Equipements_STEU!AR17,"") | ... X59: =IF(Equipements_STEU!AH17<>"",Equipements_STEU!AT17,"")
D60: =Equipements_STEU!H18 | F60: =Equipements_STEU!I18 | G60: =Equipements_STEU!M18 | H60: =Equipements_STEU!J18 | J60: =Equipements_STEU!K18 | N60: =Equipements_STEU!P18 | O60: =IF(Equipements_STEU!Y18<>"",Equipements_STEU!AK18,"") | P60: =IF(Equipements_STEU!Z18<>"",Equipements_STEU!AL18,"") | Q60: =IF(Equipements_STEU!AA18<>"",Equipements_STEU!AM18,"") | R60: =IF(Equipements_STEU!AB18<>"",Equipements_STEU!AN18,"") | S60: =IF(Equipements_STEU!AC18<>"",Equipements_STEU!AO18,"") | T60: =IF(Equipements_STEU!AD18<>"",Equipements_STEU!AP18,"") | U60: =IF(Equipements_STEU!AE18<>"",Equipements_STEU!AQ18,"") | V60: =IF(Equipements_STEU!AF18<>"",Equipements_STEU!AR18,"") | ... X60: =IF(Equipements_STEU!AH18<>"",Equipements_STEU!AT18,"")
D61: =Equipements_STEU!H19 | F61: =Equipements_STEU!I19 | G61: =Equipements_STEU!M19 | H61: =Equipements_STEU!J19 | J61: =Equipements_STEU!K19 | N61: =Equipements_STEU!P19 | O61: =IF(Equipements_STEU!Y19<>"",Equipements_STEU!AK19,"") | P61: =IF(Equipements_STEU!Z19<>"",Equipements_STEU!AL19,"") | Q61: =IF(Equipements_STEU!AA19<>"",Equipements_STEU!AM19,"") | R61: =IF(Equipements_STEU!AB19<>"",Equipements_STEU!AN19,"") | S61: =IF(Equipements_STEU!AC19<>"",Equipements_STEU!AO19,"") | T61: =IF(Equipements_STEU!AD19<>"",Equipements_STEU!AP19,"") | U61: =IF(Equipements_STEU!AE19<>"",Equipements_STEU!AQ19,"") | V61: =IF(Equipements_STEU!AF19<>"",Equipements_STEU!AR19,"") | ... X61: =IF(Equipements_STEU!AH19<>"",Equipements_STEU!AT19,"")
D62: =Equipements_STEU!H20 | F62: =Equipements_STEU!I20 | G62: =Equipements_STEU!M20 | H62: =Equipements_STEU!J20 | J62: =Equipements_STEU!K20 | N62: =Equipements_STEU!P20 | O62: =IF(Equipements_STEU!Y20<>"",Equipements_STEU!AK20,"") | P62: =IF(Equipements_STEU!Z20<>"",Equipements_STEU!AL20,"") | Q62: =IF(Equipements_STEU!AA20<>"",Equipements_STEU!AM20,"") | R62: =IF(Equipements_STEU!AB20<>"",Equipements_STEU!AN20,"") | S62: =IF(Equipements_STEU!AC20<>"",Equipements_STEU!AO20,"") | T62: =IF(Equipements_STEU!AD20<>"",Equipements_STEU!AP20,"") | U62: =IF(Equipements_STEU!AE20<>"",Equipements_STEU!AQ20,"") | V62: =IF(Equipements_STEU!AF20<>"",Equipements_STEU!AR20,"") | ... X62: =IF(Equipements_STEU!AH20<>"",Equipements_STEU!AT20,"")
D63: =Equipements_STEU!H21 | F63: =Equipements_STEU!I21 | G63: =Equipements_STEU!M21 | H63: =Equipements_STEU!J21 | J63: =Equipements_STEU!K21 | N63: =Equipements_STEU!P21 | O63: =IF(Equipements_STEU!Y21<>"",Equipements_STEU!AK21,"") | P63: =IF(Equipements_STEU!Z21<>"",Equipements_STEU!AL21,"") | Q63: =IF(Equipements_STEU!AA21<>"",Equipements_STEU!AM21,"") | R63: =IF(Equipements_STEU!AB21<>"",Equipements_STEU!AN21,"") | S63: =IF(Equipements_STEU!AC21<>"",Equipements_STEU!AO21,"") | T63: =IF(Equipements_STEU!AD21<>"",Equipements_STEU!AP21,"") | U63: =IF(Equipements_STEU!AE21<>"",Equipements_STEU!AQ21,"") | V63: =IF(Equipements_STEU!AF21<>"",Equipements_STEU!AR21,"") | ... X63: =IF(Equipements_STEU!AH21<>"",Equipements_STEU!AT21,"")
D64: =Equipements_STEU!H22 | F64: =Equipements_STEU!I22 | G64: =Equipements_STEU!M22 | H64: =Equipements_STEU!J22 | J64: =Equipements_STEU!K22 | N64: =Equipements_STEU!P22 | O64: =IF(Equipements_STEU!Y22<>"",Equipements_STEU!AK22,"") | P64: =IF(Equipements_STEU!Z22<>"",Equipements_STEU!AL22,"") | Q64: =IF(Equipements_STEU!AA22<>"",Equipements_STEU!AM22,"") | R64: =IF(Equipements_STEU!AB22<>"",Equipements_STEU!AN22,"") | S64: =IF(Equipements_STEU!AC22<>"",Equipements_STEU!AO22,"") | T64: =IF(Equipements_STEU!AD22<>"",Equipements_STEU!AP22,"") | U64: =IF(Equipements_STEU!AE22<>"",Equipements_STEU!AQ22,"") | V64: =IF(Equipements_STEU!AF22<>"",Equipements_STEU!AR22,"") | ... X64: =IF(Equipements_STEU!AH22<>"",Equipements_STEU!AT22,"")
D65: =Equipements_STEU!H23 | F65: =Equipements_STEU!I23 | G65: =Equipements_STEU!M23 | H65: =Equipements_STEU!J23 | J65: =Equipements_STEU!K23 | N65: =Equipements_STEU!P23 | O65: =IF(Equipements_STEU!Y23<>"",Equipements_STEU!AK23,"") | P65: =IF(Equipements_STEU!Z23<>"",Equipements_STEU!AL23,"") | Q65: =IF(Equipements_STEU!AA23<>"",Equipements_STEU!AM23,"") | R65: =IF(Equipements_STEU!AB23<>"",Equipements_STEU!AN23,"") | S65: =IF(Equipements_STEU!AC23<>"",Equipements_STEU!AO23,"") | T65: =IF(Equipements_STEU!AD23<>"",Equipements_STEU!AP23,"") | U65: =IF(Equipements_STEU!AE23<>"",Equipements_STEU!AQ23,"") | V65: =IF(Equipements_STEU!AF23<>"",Equipements_STEU!AR23,"") | ... X65: =IF(Equipements_STEU!AH23<>"",Equipements_STEU!AT23,"")
D66: =Equipements_STEU!H24 | F66: =Equipements_STEU!I24 | G66: =Equipements_STEU!M24 | H66: =Equipements_STEU!J24 | J66: =Equipements_STEU!K24 | N66: =Equipements_STEU!P24 | O66: =IF(Equipements_STEU!Y24<>"",Equipements_STEU!AK24,"") | P66: =IF(Equipements_STEU!Z24<>"",Equipements_STEU!AL24,"") | Q66: =IF(Equipements_STEU!AA24<>"",Equipements_STEU!AM24,"") | R66: =IF(Equipements_STEU!AB24<>"",Equipements_STEU!AN24,"") | S66: =IF(Equipements_STEU!AC24<>"",Equipements_STEU!AO24,"") | T66: =IF(Equipements_STEU!AD24<>"",Equipements_STEU!AP24,"") | U66: =IF(Equipements_STEU!AE24<>"",Equipements_STEU!AQ24,"") | V66: =IF(Equipements_STEU!AF24<>"",Equipements_STEU!AR24,"") | ... X66: =IF(Equipements_STEU!AH24<>"",Equipements_STEU!AT24,"")
D67: =Equipements_STEU!H25 | F67: =Equipements_STEU!I25 | G67: =Equipements_STEU!M25 | H67: =Equipements_STEU!J25 | J67: =Equipements_STEU!K25 | N67: =Equipements_STEU!P25 | O67: =IF(Equipements_STEU!Y25<>"",Equipements_STEU!AK25,"") | P67: =IF(Equipements_STEU!Z25<>"",Equipements_STEU!AL25,"") | Q67: =IF(Equipements_STEU!AA25<>"",Equipements_STEU!AM25,"") | R67: =IF(Equipements_STEU!AB25<>"",Equipements_STEU!AN25,"") | S67: =IF(Equipements_STEU!AC25<>"",Equipements_STEU!AO25,"") | T67: =IF(Equipements_STEU!AD25<>"",Equipements_STEU!AP25,"") | U67: =IF(Equipements_STEU!AE25<>"",Equipements_STEU!AQ25,"") | V67: =IF(Equipements_STEU!AF25<>"",Equipements_STEU!AR25,"") | ... X67: =IF(Equipements_STEU!AH25<>"",Equipements_STEU!AT25,"")
D68: =Equipements_STEU!H26 | F68: =Equipements_STEU!I26 | G68: =Equipements_STEU!M26 | H68: =Equipements_STEU!J26 | J68: =Equipements_STEU!K26 | N68: =Equipements_STEU!P26 | O68: =IF(Equipements_STEU!Y26<>"",Equipements_STEU!AK26,"") | P68: =IF(Equipements_STEU!Z26<>"",Equipements_STEU!AL26,"") | Q68: =IF(Equipements_STEU!AA26<>"",Equipements_STEU!AM26,"") | R68: =IF(Equipements_STEU!AB26<>"",Equipements_STEU!AN26,"") | S68: =IF(Equipements_STEU!AC26<>"",Equipements_STEU!AO26,"") | T68: =IF(Equipements_STEU!AD26<>"",Equipements_STEU!AP26,"") | U68: =IF(Equipements_STEU!AE26<>"",Equipements_STEU!AQ26,"") | V68: =IF(Equipements_STEU!AF26<>"",Equipements_STEU!AR26,"") | ... X68: =IF(Equipements_STEU!AH26<>"",Equipements_STEU!AT26,"")
D69: =Equipements_STEU!H27 | F69: =Equipements_STEU!I27 | G69: =Equipements_STEU!M27 | H69: =Equipements_STEU!J27 | J69: =Equipements_STEU!K27 | N69: =Equipements_STEU!P27 | O69: =IF(Equipements_STEU!Y27<>"",Equipements_STEU!AK27,"") | P69: =IF(Equipements_STEU!Z27<>"",Equipements_STEU!AL27,"") | Q69: =IF(Equipements_STEU!AA27<>"",Equipements_STEU!AM27,"") | R69: =IF(Equipements_STEU!AB27<>"",Equipements_STEU!AN27,"") | S69: =IF(Equipements_STEU!AC27<>"",Equipements_STEU!AO27,"") | T69: =IF(Equipements_STEU!AD27<>"",Equipements_STEU!AP27,"") | U69: =IF(Equipements_STEU!AE27<>"",Equipements_STEU!AQ27,"") | V69: =IF(Equipements_STEU!AF27<>"",Equipements_STEU!AR27,"") | ... X69: =IF(Equipements_STEU!AH27<>"",Equipements_STEU!AT27,"")
... D107: =Equipements_STEU!H65 | F107: =Equipements_STEU!I65 | G107: =Equipements_STEU!M65 | H107: =Equipements_STEU!J65 | J107: =Equipements_STEU!K65 | N107: =Equipements_STEU!P65 | O107: =IF(Equipements_STEU!Y65<>"",Equipements_STEU!AK65,"") | P107: =IF(Equipements_STEU!Z65<>"",Equipements_STEU!AL65,"") | Q107: =IF(Equipements_STEU!AA65<>"",Equipements_STEU!AM65,"") | R107: =IF(Equipements_STEU!AB65<>"",Equipements_STEU!AN65,"") | S107: =IF(Equipements_STEU!AC65<>"",Equipements_STEU!AO65,"") | T107: =IF(Equipements_STEU!AD65<>"",Equipements_STEU!AP65,"") | U107: =IF(Equipements_STEU!AE65<>"",Equipements_STEU!AQ65,"") | V107: =IF(Equipements_STEU!AF65<>"",Equipements_STEU!AR65,"") | ... X107: =IF(Equipements_STEU!AH65<>"",Equipements_STEU!AT65,"")

Sheet Qualité
C2: CONTRÔLE ANNUEL DES DISPOSITIFS D'AUTOSURVEILLANCE DES SYSTÈMES D'ASSAINISSEMENT COLLECTIF
C3: STATION : | E3: =IF(ISBLANK(Descriptif!L3),"",Descriptif!L3) | H3: RÉSEAU : | J3: =IF(ISBLANK(Descriptif!Q3),"",Descriptif!Q3) | M3: ORGANISME DE CONTRÔLE : | P3: =IF(ISBLANK(Descriptif!U3),"",Descriptif!U3)
C4: CODE SANDRE : | E4: =IF(ISBLANK(Descriptif!L4),"",Descriptif!L4) | H4: CODE SANDRE : | J4: =IF(ISBLANK(Descriptif!Q4),"",Descriptif!Q4) | M4: NOM(S) CONTROLEUR(S) : | P4: =IF(ISBLANK(Descriptif!U4),"",Descriptif!U4)
C5: MAITRE D'OUVRAGE : | E5: =IF(ISBLANK(Descriptif!F5),"",Descriptif!F5) | H5: TYPE DE RÉSEAU : | J5: =IF(ISBLANK(Descriptif!Q5),"",Descriptif!Q5) | M5: DATE(S) D'INTERVENTION : | P5: =IF(ISBLANK(Descriptif!U5),"",Descriptif!U5)
C6: EXPLOITANT : | E6: =IF(ISBLANK(Descriptif!L6),"",Descriptif!F6) | H6: EXPLOITANT : | J6: =IF(ISBLANK(Descriptif!Q6),"",Descriptif!Q6) | M6: CONDITION(S) METEO : | P6: =IF(ISBLANK(Descriptif!U6),"",Descriptif!U6)
C8: MANUEL D'AUTOSURVEILLANCE
D10: 1 | E10: Est-ce que le manuel autosurveillance est à jour, validé ou en cours d'expertise ?
D12: COMMENTAIRES :
D15: Le manuel d’autosurveillance n’est pas à jour si : * date du MAS ≤ 2015 ; * changement du maitre d’ouvrage ou de l’exploitant ; * construction d’une nouvelle STEU ou la réhabilitation d’une STEU ; * modification des points du système de collecte, de la station de traitement et des points de déversement au milieu ; * modification du référentiel et du schéma SANDRE (ajout ou suppression d’un point d’autosurveillance ou toute autre modification impactant le calcul du rendement) ; * évolutions techniques ou travaux importants sur le système d'assainissement impactant les points d'autosurveillance ; * modifications réglementaires telles que l’adoption d’un nouvel arrêté si impact sur le référentiel, le schéma SANDRE et le matériel d’autosurveillance ; * modifications significatives du suivi métrologique des dispositifs d'autosurveillance ; *modifications significatives concernant la réalisation des analyses d'autosurveillance.
C19: PROCEDURE DE CONTROLES INTERNES DES MATERIELS D'AUTOSURVEILLANCE
D21: 2 | E21: Est-ce que le contrôle des débimètres est réalisé selon les procédures décrites dans le manuel d'autosurveillance ?
D22: 3 | E22: Est-ce que le contrôle des échantillonneurs est réalisé selon les procédures décrites dans le manuel d'autosurveillance ?
D23: 4 | E23: Est-ce que le contrôle des thermomètres est réalisé selon les procédures décrites dans le manuel d'autosurveillance ?
D24: 5 | E24: Est-ce que le contrôle des pluviomètres est réalisé selon les procédures décrites dans le manuel d'autosurveillance ?
D25: 6 | E25: Est-ce que le contrôle des balances est réalisé selon les procédures décrites dans le manuel d'autosurveillance ?
D26: 7 | E26: Est-ce que le contrôle des chronomètres est réalisé selon les procédures décrites dans le manuel d'autosurveillance ?
D27: 8 | E27: Les contrôles internes sont-ils tous tracés, formalisés et suivis (fiches de vie, cartes de contrôle...) ?
D28: 9 | E28: Des fiches de non-conformité et d'action d'amélioration ont-elles été produites ?
E29: Existe-il un système qualité performant ? | L29: =IF( OR(COUNTIF(L21:L28,"Non")>0,L10="Non"), "Non", IF( AND(COUNTIF(L21:L28,"Oui")>0,L10="Oui"), "Oui", "" ) )
D31: COMMENTAIRES :

Sheet Analytique
U1: Ne rien mettre dans cette colonne | V1: Ne rien mettre dans cette colonne | W1: Ne rien mettre dans cette colonne | X1: Ne rien mettre dans cette colonne | AA1: Ne rien mettre dans cette colonne | AB1: Ne rien mettre dans cette colonne | AC1: Ne rien mettre dans cette colonne | AD1: Ne rien mettre dans cette colonne | AE1: Ne rien mettre dans cette colonne
C2: CONTRÔLE ANNUEL DES DISPOSITIFS D'AUTOSURVEILLANCE DES SYSTÈMES D'ASSAINISSEMENT COLLECTIF | U2: Point | V2: nb ana | W2: nb conforme | X2: Code PREL | Y2: Reg. | Z2: Point | AA2: NB ANALYSE | AB2: NB CONFORME | AC2: Coef | AD2: Score | AE2: Evaluation
C3: STATION : | E3: =IF(ISBLANK(Descriptif!L3),"",Descriptif!L3) | H3: RÉSEAU : | J3: =IF(ISBLANK(Descriptif!Q3),"",Descriptif!Q3) | M3: ORGANISME DE CONTRÔLE : | P3: =IF(ISBLANK(Descriptif!U3),"",Descriptif!U3) | X3: {=IFERROR(INDEX($T$21:$T$1021,SMALL(IF($T$21:$T$1021<>"",ROW($T$21:$T$1021)-ROW($T$21)+1),ROW(1:1))),"")} | Y3: =IF(X3<>"",LEFT(X3,2),"") | Z3: =IF($X3<>"",MID($X3, SEARCH("_", $X3) + 1, SEARCH("_", $X3, SEARCH("_",$X3) + 1) - SEARCH("_", $X3) - 1),"") | AA3: {=IFERROR(INDEX($U$21:$U$1021,SMALL(IF($T$21:$T$1021<>"",ROW($T$21:$T$1021)-ROW($T$21)+1),ROW(1:1))),"")} | AB3: {=IFERROR(INDEX($V$21:$V$1021,SMALL(IF($T$21:$T$1021<>"",ROW($T$21:$T$1021)-ROW($T$21)+1),ROW(1:1))),"")} | AC3: {=IFERROR(INDEX($W$21:$W$1021,SMALL(IF($T$21:$T$1021<>"",ROW($T$21:$T$1021)-ROW($T$21)+1),ROW(1:1))),"")} | AD3: =IF(AND(X3<>"",AC3<>""),(AC3/100 * (1-$N$15)*100),"") | AE3: =IF(X3<>"",IF(AD3<>"",IF(AD3>80,"Validé",IF(AD3<70,"Non Validé","Réserve")),"Non contrôlé"),"")
C4: CODE SANDRE : | E4: =IF(ISBLANK(Descriptif!L4),"",Descriptif!L4) | H4: CODE SANDRE : | J4: =IF(ISBLANK(Descriptif!Q4),"",Descriptif!Q4) | M4: NOM(S) CONTROLEUR(S) : | P4: =IF(ISBLANK(Descriptif!U4),"",Descriptif!U4) | X4: {=IFERROR(INDEX($T$21:$T$1021,SMALL(IF($T$21:$T$1021<>"",ROW($T$21:$T$1021)-ROW($T$21)+1),ROW(2:2))),"")} | Y4: =IF(X4<>"",LEFT(X4,2),"") | Z4: =IF($X4<>"",MID($X4, SEARCH("_", $X4) + 1, SEARCH("_", $X4, SEARCH("_",$X4) + 1) - SEARCH("_", $X4) - 1),"") | AA4: {=IFERROR(INDEX($U$21:$U$1021,SMALL(IF($T$21:$T$1021<>"",ROW($T$21:$T$1021)-ROW($T$21)+1),ROW(2:2))),"")} | AB4: {=IFERROR(INDEX($V$21:$V$1021,SMALL(IF($T$21:$T$1021<>"",ROW($T$21:$T$1021)-ROW($T$21)+1),ROW(2:2))),"")} | AC4: {=IFERROR(INDEX($W$21:$W$1021,SMALL(IF($T$21:$T$1021<>"",ROW($T$21:$T$1021)-ROW($T$21)+1),ROW(2:2))),"")} | AD4: =IF(AND(X4<>"",AC4<>""),(AC4/100 * (1-$N$15)*100),"") | AE4: =IF(X4<>"",IF(AD4<>"",IF(AD4>80,"Validé",IF(AD4<70,"Non Validé","Réserve")),"Non contrôlé"),"")
C5: MAITRE D'OUVRAGE : | E5: =IF(ISBLANK(Descriptif!F5),"",Descriptif!F5) | H5: TYPE DE RÉSEAU : | J5: =IF(ISBLANK(Descriptif!Q5),"",Descriptif!Q5) | M5: DATE(S) D'INTERVENTION : | P5: =IF(ISBLANK(Descriptif!U5),"",Descriptif!U5) | X5: {=IFERROR(INDEX($T$21:$T$1021,SMALL(IF($T$21:$T$1021<>"",ROW($T$21:$T$1021)-ROW($T$21)+1),ROW(3:3))),"")} | Y5: =IF(X5<>"",LEFT(X5,2),"") | Z5: =IF($X5<>"",MID($X5, SEARCH("_", $X5) + 1, SEARCH("_", $X5, SEARCH("_",$X5) + 1) - SEARCH("_", $X5) - 1),"") | AA5: {=IFERROR(INDEX($U$21:$U$1021,SMALL(IF($T$21:$T$1021<>"",ROW($T$21:$T$1021)-ROW($T$21)+1),ROW(3:3))),"")} | AB5: {=IFERROR(INDEX($V$21:$V$1021,SMALL(IF($T$21:$T$1021<>"",ROW($T$21:$T$1021)-ROW($T$21)+1),ROW(3:3))),"")} | AC5: {=IFERROR(INDEX($W$21:$W$1021,SMALL(IF($T$21:$T$1021<>"",ROW($T$21:$T$1021)-ROW($T$21)+1),ROW(3:3))),"")} | AD5: =IF(AND(X5<>"",AC5<>""),(AC5/100 * (1-$N$15)*100),"") | AE5: =IF(X5<>"",IF(AD5<>"",IF(AD5>80,"Validé",IF(AD5<70,"Non Validé","Réserve")),"Non contrôlé"),"")
C6: EXPLOITANT : | E6: =IF(ISBLANK(Descriptif!L6),"",Descriptif!F6) | H6: EXPLOITANT : | J6: =IF(ISBLANK(Descriptif!Q6),"",Descriptif!Q6) | M6: CONDITION(S) METEO : | P6: =IF(ISBLANK(Descriptif!U6),"",Descriptif!U6) | X6: {=IFERROR(INDEX($T$21:$T$1021,SMALL(IF($T$21:$T$1021<>"",ROW($T$21:$T$1021)-ROW($T$21)+1),ROW(4:4))),"")} | Y6: =IF(X6<>"",LEFT(X6,2),"") | Z6: =IF($X6<>"",MID($X6, SEARCH("_", $X6) + 1, SEARCH("_", $X6, SEARCH("_",$X6) + 1) - SEARCH("_", $X6) - 1),"") | AA6: {=IFERROR(INDEX($U$21:$U$1021,SMALL(IF($T$21:$T$1021<>"",ROW($T$21:$T$1021)-ROW($T$21)+1),ROW(4:4))),"")} | AB6: {=IFERROR(INDEX($V$21:$V$1021,SMALL(IF($T$21:$T$1021<>"",ROW($T$21:$T$1021)-ROW($T$21)+1),ROW(4:4))),"")} | AC6: {=IFERROR(INDEX($W$21:$W$1021,SMALL(IF($T$21:$T$1021<>"",ROW($T$21:$T$1021)-ROW($T$21)+1),ROW(4:4))),"")} | AD6: =IF(AND(X6<>"",AC6<>""),(AC6/100 * (1-$N$15)*100),"") | AE6: =IF(X6<>"",IF(AD6<>"",IF(AD6>80,"Validé",IF(AD6<70,"Non Validé","Réserve")),"Non contrôlé"),"")
X7: {=IFERROR(INDEX($T$21:$T$1021,SMALL(IF($T$21:$T$1021<>"",ROW($T$21:$T$1021)-ROW($T$21)+1),ROW(5:5))),"")} | Y7: =IF(X7<>"",LEFT(X7,2),"") | Z7: =IF($X7<>"",MID($X7, SEARCH("_", $X7) + 1, SEARCH("_", $X7, SEARCH("_",$X7) + 1) - SEARCH("_", $X7) - 1),"") | AA7: {=IFERROR(INDEX($U$21:$U$1021,SMALL(IF($T$21:$T$1021<>"",ROW($T$21:$T$1021)-ROW($T$21)+1),ROW(5:5))),"")} | AB7: {=IFERROR(INDEX($V$21:$V$1021,SMALL(IF($T$21:$T$1021<>"",ROW($T$21:$T$1021)-ROW($T$21)+1),ROW(5:5))),"")} | AC7: {=IFERROR(INDEX($W$21:$W$1021,SMALL(IF($T$21:$T$1021<>"",ROW($T$21:$T$1021)-ROW($T$21)+1),ROW(5:5))),"")} | AD7: =IF(AND(X7<>"",AC7<>""),(AC7/100 * (1-$N$15)*100),"") | AE7: =IF(X7<>"",IF(AD7<>"",IF(AD7>80,"Validé",IF(AD7<70,"Non Validé","Réserve")),"Non contrôlé"),"")
C8: FRACTIONNEMENT, TEMPÉRATURE ET DÉLAIS DE TRANSPORT DES ÉCHANTILLONS | X8: {=IFERROR(INDEX($T$21:$T$1021,SMALL(IF($T$21:$T$1021<>"",ROW($T$21:$T$1021)-ROW($T$21)+1),ROW(6:6))),"")} | Y8: =IF(X8<>"",LEFT(X8,2),"") | Z8: =IF($X8<>"",MID($X8, SEARCH("_", $X8) + 1, SEARCH("_", $X8, SEARCH("_",$X8) + 1) - SEARCH("_", $X8) - 1),"") | AA8: {=IFERROR(INDEX($U$21:$U$1021,SMALL(IF($T$21:$T$1021<>"",ROW($T$21:$T$1021)-ROW($T$21)+1),ROW(6:6))),"")} | AB8: {=IFERROR(INDEX($V$21:$V$1021,SMALL(IF($T$21:$T$1021<>"",ROW($T$21:$T$1021)-ROW($T$21)+1),ROW(6:6))),"")} | AC8: {=IFERROR(INDEX($W$21:$W$1021,SMALL(IF($T$21:$T$1021<>"",ROW($T$21:$T$1021)-ROW($T$21)+1),ROW(6:6))),"")} | AD8: =IF(AND(X8<>"",AC8<>""),(AC8/100 * (1-$N$15)*100),"") | AE8: =IF(X8<>"",IF(AD8<>"",IF(AD8>80,"Validé",IF(AD8<70,"Non Validé","Réserve")),"Non contrôlé"),"")
X9: {=IFERROR(INDEX($T$21:$T$1021,SMALL(IF($T$21:$T$1021<>"",ROW($T$21:$T$1021)-ROW($T$21)+1),ROW(7:7))),"")} | Y9: =IF(X9<>"",LEFT(X9,2),"") | Z9: =IF($X9<>"",MID($X9, SEARCH("_", $X9) + 1, SEARCH("_", $X9, SEARCH("_",$X9) + 1) - SEARCH("_", $X9) - 1),"") | AA9: {=IFERROR(INDEX($U$21:$U$1021,SMALL(IF($T$21:$T$1021<>"",ROW($T$21:$T$1021)-ROW($T$21)+1),ROW(7:7))),"")} | AB9: {=IFERROR(INDEX($V$21:$V$1021,SMALL(IF($T$21:$T$1021<>"",ROW($T$21:$T$1021)-ROW($T$21)+1),ROW(7:7))),"")} | AC9: {=IFERROR(INDEX($W$21:$W$1021,SMALL(IF($T$21:$T$1021<>"",ROW($T$21:$T$1021)-ROW($T$21)+1),ROW(7:7))),"")} | AD9: =IF(AND(X9<>"",AC9<>""),(AC9/100 * (1-$N$15)*100),"") | AE9: =IF(X9<>"",IF(AD9<>"",IF(AD9>80,"Validé",IF(AD9<70,"Non Validé","Réserve")),"Non contrôlé"),"")
D10: Les échantillons sont-ils constitués, conservés et mis en analyse, selon les règles de l'art en vigueur ? | N10: Pénalité | X10: {=IFERROR(INDEX($T$21:$T$1021,SMALL(IF($T$21:$T$1021<>"",ROW($T$21:$T$1021)-ROW($T$21)+1),ROW(8:8))),"")} | Y10: =IF(X10<>"",LEFT(X10,2),"") | Z10: =IF($X10<>"",MID($X10, SEARCH("_", $X10) + 1, SEARCH("_", $X10, SEARCH("_",$X10) + 1) - SEARCH("_", $X10) - 1),"") | AA10: {=IFERROR(INDEX($U$21:$U$1021,SMALL(IF($T$21:$T$1021<>"",ROW($T$21:$T$1021)-ROW($T$21)+1),ROW(8:8))),"")} | AB10: {=IFERROR(INDEX($V$21:$V$1021,SMALL(IF($T$21:$T$1021<>"",ROW($T$21:$T$1021)-ROW($T$21)+1),ROW(8:8))),"")} | AC10: {=IFERROR(INDEX($W$21:$W$1021,SMALL(IF($T$21:$T$1021<>"",ROW($T$21:$T$1021)-ROW($T$21)+1),ROW(8:8))),"")} | AD10: =IF(AND(X10<>"",AC10<>""),(AC10/100 * (1-$N$15)*100),"") | AE10: =IF(X10<>"",IF(AD10<>"",IF(AD10>80,"Validé",IF(AD10<70,"Non Validé","Réserve")),"Non contrôlé"),"")
D11: Le guide AQUAREF est-il respecté pour le prélèvement des échantillons SDE ? | N11: =IF(L11="","",IF(L11="Non",0.1,0)) | X11: {=IFERROR(INDEX($T$21:$T$1021,SMALL(IF($T$21:$T$1021<>"",ROW($T$21:$T$1021)-ROW($T$21)+1),ROW(9:9))),"")} | Y11: =IF(X11<>"",LEFT(X11,2),"") | Z11: =IF($X11<>"",MID($X11, SEARCH("_", $X11) + 1, SEARCH("_", $X11, SEARCH("_",$X11) + 1) - SEARCH("_", $X11) - 1),"") | AA11: {=IFERROR(INDEX($U$21:$U$1021,SMALL(IF($T$21:$T$1021<>"",ROW($T$21:$T$1021)-ROW($T$21)+1),ROW(9:9))),"")} | AB11: {=IFERROR(INDEX($V$21:$V$1021,SMALL(IF($T$21:$T$1021<>"",ROW($T$21:$T$1021)-ROW($T$21)+1),ROW(9:9))),"")} | AC11: {=IFERROR(INDEX($W$21:$W$1021,SMALL(IF($T$21:$T$1021<>"",ROW($T$21:$T$1021)-ROW($T$21)+1),ROW(9:9))),"")} | AD11: =IF(AND(X11<>"",AC11<>""),(AC11/100 * (1-$N$15)*100),"") | AE11: =IF(X11<>"",IF(AD11<>"",IF(AD11>80,"Validé",IF(AD11<70,"Non Validé","Réserve")),"Non contrôlé"),"")
D12: Les échantillons sont-ils fractionnés selon la norme FDT 90-523-2 ? | N12: =IF(L12="","",IF(L12="Non",0.1,0)) | X12: {=IFERROR(INDEX($T$21:$T$1021,SMALL(IF($T$21:$T$1021<>"",ROW($T$21:$T$1021)-ROW($T$21)+1),ROW(10:10))),"")} | Y12: =IF(X12<>"",LEFT(X12,2),"") | Z12: =IF($X12<>"",MID($X12, SEARCH("_", $X12) + 1, SEARCH("_", $X12, SEARCH("_",$X12) + 1) - SEARCH("_", $X12) - 1),"") | AA12: {=IFERROR(INDEX($U$21:$U$1021,SMALL(IF($T$21:$T$1021<>"",ROW($T$21:$T$1021)-ROW($T$21)+1),ROW(10:10))),"")} | AB12: {=IFERROR(INDEX($V$21:$V$1021,SMALL(IF($T$21:$T$1021<>"",ROW($T$21:$T$1021)-ROW($T$21)+1),ROW(10:10))),"")} | AC12: {=IFERROR(INDEX($W$21:$W$1021,SMALL(IF($T$21:$T$1021<>"",ROW($T$21:$T$1021)-ROW($T$21)+1),ROW(10:10))),"")} | AD12: =IF(AND(X12<>"",AC12<>""),(AC12/100 * (1-$N$15)*100),"") | AE12: =IF(X12<>"",IF(AD12<>"",IF(AD12>80,"Validé",IF(AD12<70,"Non Validé","Réserve")),"Non contrôlé"),"")
D13: La conservation pendant le transport des échantillons est-elle assurée à 5°C ± 3°C ? | N13: =IF(L13="","",IF(L13="Non",0.1,0)) | X13: {=IFERROR(INDEX($T$21:$T$1021,SMALL(IF($T$21:$T$1021<>"",ROW($T$21:$T$1021)-ROW($T$21)+1),ROW(11:11))),"")} | Y13: =IF(X13<>"",LEFT(X13,2),"") | Z13: =IF($X13<>"",MID($X13, SEARCH("_", $X13) + 1, SEARCH("_", $X13, SEARCH("_",$X13) + 1) - SEARCH("_", $X13) - 1),"") | AA13: {=IFERROR(INDEX($U$21:$U$1021,SMALL(IF($T$21:$T$1021<>"",ROW($T$21:$T$1021)-ROW($T$21)+1),ROW(11:11))),"")} | AB13: {=IFERROR(INDEX($V$21:$V$1021,SMALL(IF($T$21:$T$1021<>"",ROW($T$21:$T$1021)-ROW($T$21)+1),ROW(11:11))),"")} | AC13: {=IFERROR(INDEX($W$21:$W$1021,SMALL(IF($T$21:$T$1021<>"",ROW($T$21:$T$1021)-ROW($T$21)+1),ROW(11:11))),"")} | AD13: =IF(AND(X13<>"",AC13<>""),(AC13/100 * (1-$N$15)*100),"") | AE13: =IF(X13<>"",IF(AD13<>"",IF(AD13>80,"Validé",IF(AD13<70,"Non Validé","Réserve")),"Non contrôlé"),"")
D14: Les conditions de transport permettent-elles l'acheminement et la réception des échantillons dans les 24 h ? | N14: =IF(L14="","",IF(L14="Non",0.1,0)) | X14: {=IFERROR(INDEX($T$21:$T$1021,SMALL(IF($T$21:$T$1021<>"",ROW($T$21:$T$1021)-ROW($T$21)+1),ROW(12:12))),"")} | Y14: =IF(X14<>"",LEFT(X14,2),"") | Z14: =IF($X14<>"",MID($X14, SEARCH("_", $X14) + 1, SEARCH("_", $X14, SEARCH("_",$X14) + 1) - SEARCH("_", $X14) - 1),"") | AA14: {=IFERROR(INDEX($U$21:$U$1021,SMALL(IF($T$21:$T$1021<>"",ROW($T$21:$T$1021)-ROW($T$21)+1),ROW(12:12))),"")} | AB14: {=IFERROR(INDEX($V$21:$V$1021,SMALL(IF($T$21:$T$1021<>"",ROW($T$21:$T$1021)-ROW($T$21)+1),ROW(12:12))),"")} | AC14: {=IFERROR(INDEX($W$21:$W$1021,SMALL(IF($T$21:$T$1021<>"",ROW($T$21:$T$1021)-ROW($T$21)+1),ROW(12:12))),"")} | AD14: =IF(AND(X14<>"",AC14<>""),(AC14/100 * (1-$N$15)*100),"") | AE14: =IF(X14<>"",IF(AD14<>"",IF(AD14>80,"Validé",IF(AD14<70,"Non Validé","Réserve")),"Non contrôlé"),"")
L15: Total pénalité : | N15: =SUM(N11:P14) -> 0 | X15: {=IFERROR(INDEX($T$21:$T$1021,SMALL(IF($T$21:$T$1021<>"",ROW($T$21:$T$1021)-ROW($T$21)+1),ROW(13:13))),"")} | Y15: =IF(X15<>"",LEFT(X15,2),"") | Z15: =IF($X15<>"",MID($X15, SEARCH("_", $X15) + 1, SEARCH("_", $X15, SEARCH("_",$X15) + 1) - SEARCH("_", $X15) - 1),"") | AA15: {=IFERROR(INDEX($U$21:$U$1021,SMALL(IF($T$21:$T$1021<>"",ROW($T$21:$T$1021)-ROW($T$21)+1),ROW(13:13))),"")} | AB15: {=IFERROR(INDEX($V$21:$V$1021,SMALL(IF($T$21:$T$1021<>"",ROW($T$21:$T$1021)-ROW($T$21)+1),ROW(13:13))),"")} | AC15: {=IFERROR(INDEX($W$21:$W$1021,SMALL(IF($T$21:$T$1021<>"",ROW($T$21:$T$1021)-ROW($T$21)+1),ROW(13:13))),"")} | AD15: =IF(AND(X15<>"",AC15<>""),(AC15/100 * (1-$N$15)*100),"") | AE15: =IF(X15<>"",IF(AD15<>"",IF(AD15>80,"Validé",IF(AD15<70,"Non Validé","Réserve")),"Non contrôlé"),"")
D16: COMMENTAIRES : | Y16: =IF(X16<>"",LEFT(X16,2),"") | Z16: =IF($X16<>"",MID($X16, SEARCH("_", $X16) + 1, SEARCH("_", $X16, SEARCH("_",$X16) + 1) - SEARCH("_", $X16) - 1),"") | AD16: =IF(AND(X16<>"",AC16<>""),(AC16/100 * (1-$N$15)*100),"") | AE16: =IF(X16<>"",IF(AD16<>"",IF(AD16>80,"Validé",IF(AD16<70,"Non Validé","Réserve")),"Non contrôlé"),"")
Y17: =IF(X17<>"",LEFT(X17,2),"") | Z17: =IF($X17<>"",MID($X17, SEARCH("_", $X17) + 1, SEARCH("_", $X17, SEARCH("_",$X17) + 1) - SEARCH("_", $X17) - 1),"") | AD17: =IF(AND(X17<>"",AC17<>""),(AC17/100 * (1-$N$15)*100),"") | AE17: =IF(X17<>"",IF(AD17<>"",IF(AD17>80,"Validé",IF(AD17<70,"Non Validé","Réserve")),"Non contrôlé"),"")
Y18: =IF(X18<>"",LEFT(X18,2),"") | Z18: =IF($X18<>"",MID($X18, SEARCH("_", $X18) + 1, SEARCH("_", $X18, SEARCH("_",$X18) + 1) - SEARCH("_", $X18) - 1),"") | AD18: =IF(AND(X18<>"",AC18<>""),(AC18/100 * (1-$N$15)*100),"") | AE18: =IF(X18<>"",IF(AD18<>"",IF(AD18>80,"Validé",IF(AD18<70,"Non Validé","Réserve")),"Non contrôlé"),"")
X19: {=IFERROR(INDEX($T$21:$T$1021,SMALL(IF($T$21:$T$1021<>"",ROW($T$21:$T$1021)-ROW($T$21)+1),ROW(14:14))),"")} | Y19: =IF(X19<>"",LEFT(X19,2),"") | Z19: =IF($X19<>"",MID($X19, SEARCH("_", $X19) + 1, SEARCH("_", $X19, SEARCH("_",$X19) + 1) - SEARCH("_", $X19) - 1),"") | AA19: {=IFERROR(INDEX($U$21:$U$1021,SMALL(IF($T$21:$T$1021<>"",ROW($T$21:$T$1021)-ROW($T$21)+1),ROW(14:14))),"")} | AB19: {=IFERROR(INDEX($V$21:$V$1021,SMALL(IF($T$21:$T$1021<>"",ROW($T$21:$T$1021)-ROW($T$21)+1),ROW(14:14))),"")} | AC19: {=IFERROR(INDEX($W$21:$W$1021,SMALL(IF($T$21:$T$1021<>"",ROW($T$21:$T$1021)-ROW($T$21)+1),ROW(14:14))),"")} | AD19: =IF(AND(X19<>"",AC19<>""),(AC19/100 * (1-$N$15)*100),"") | AE19: =IF(X19<>"",IF(AD19<>"",IF(AD19>80,"Validé",IF(AD19<70,"Non Validé","Réserve")),"Non contrôlé"),"")
X20: {=IFERROR(INDEX($T$21:$T$1021,SMALL(IF($T$21:$T$1021<>"",ROW($T$21:$T$1021)-ROW($T$21)+1),ROW(15:15))),"")} | Y20: =IF(X20<>"",LEFT(X20,2),"") | Z20: =IF($X20<>"",MID($X20, SEARCH("_", $X20) + 1, SEARCH("_", $X20, SEARCH("_",$X20) + 1) - SEARCH("_", $X20) - 1),"") | AA20: {=IFERROR(INDEX($U$21:$U$1021,SMALL(IF($T$21:$T$1021<>"",ROW($T$21:$T$1021)-ROW($T$21)+1),ROW(15:15))),"")} | AB20: {=IFERROR(INDEX($V$21:$V$1021,SMALL(IF($T$21:$T$1021<>"",ROW($T$21:$T$1021)-ROW($T$21)+1),ROW(15:15))),"")} | AC20: {=IFERROR(INDEX($W$21:$W$1021,SMALL(IF($T$21:$T$1021<>"",ROW($T$21:$T$1021)-ROW($T$21)+1),ROW(15:15))),"")} | AD20: =IF(AND(X20<>"",AC20<>""),(AC20/100 * (1-$N$15)*100),"") | AE20: =IF(X20<>"",IF(AD20<>"",IF(AD20>80,"Validé",IF(AD20<70,"Non Validé","Réserve")),"Non contrôlé"),"")
C21: COMPARATIF ANALYTIQUE | K21: (Dupliquer ce bloc en cas de comparatif multiple en utilisant le bouton du bas)
D23: Informations sur le comparatif analytique
D24: Préleveur : | K24: Date du comparatif : | N24: =P5
D25: Le comparatif est-il effectué à partir des prélévements d'une autre station ? | K25: Dans l'affirmative, préciser la station :
D27: Les analyses sont-elles correctement effectuées ?
D28: Nom du(des) laboratoire(s) réalisant les analyses de la matrice eau :
D29: Nom du(des) laboratoire(s) réalisant l'analyse de la siccité des boues et des matières séches :
D30: Le(s) laboratoire(s) est/sont-il(s) agréé(s) au titre du code de l’environnement pour l'ensemble des paramètres de la matrice eau résiduaire ? | J30: Non
D31: A défaut, est ce que le laboratoire réalise un exercice concluant d’intercalibration avec un laboratoire agréé ? | J31: Non
D33: Résultats du comparatif analytique
D34: Paramètres | F34: LQ en mg/l | G34: Laboratoire du Maître d'Ouvrage/exploitant | I34: COFRAC | J34: Laboratoire de contrôle | L34: COFRAC | M34: Nombre d'analyses réalisées | O34: Nombre d'analyses conformes | Q34: Coefficient Analytique
M35: =COUNTA(G37:H46) -> 0 | O35: =COUNTIF(O37:P46,"=Oui") -> 0 | Q35: =IF(OR($J30="Oui",$J31="Oui"),100*(1-N15),IF(M35>0,(O35/M35)*100*(1-N15),0)) -> 0 | T35: =IF(G24<>"",G24,"") | U35: =IF(T35<>"",M35,"") | V35: =IF(T35<>"",O35,"") | W35: =IF(M35>0,100*(O35/M35),"")
M36: Ecart (%) | O36: Conformité | Q36: EMT
D37: DBO5 | F37: =VLOOKUP(D37, 'SeuilsComparaison-EMT'!$C$5:$E$28, 3, FALSE) -> 3 | M37: =IF(OR(J37="",G37=""),"",IF(ISERROR(VLOOKUP(D37,'SeuilsComparaison-EMT'!$C$5:$J$25,4,FALSE)),"-",IF(OR(IF(ISTEXT(J37)=TRUE,SUBSTITUTE(J37,"<","",1)*1,J37)>VLOOKUP(D37,'SeuilsComparaison-EMT'!$C$5:$J$25,4,FALSE),IF(ISTEXT(G37)=TRUE,SUBSTITUTE(G37,"<","",1)*1,G37)>VLOOKUP(D37,'SeuilsComparaison-EMT'!$C$5:$J$25,4,FALSE)=TRUE),(IF(ISTEXT(G37)=TRUE,SUBSTITUTE(G37,"<","",1)*1,G37)-((IF(ISTEXT(G37)=TRUE,SUBSTITUTE(G37,"<","",1)*1,G37)+IF(ISTEXT(J37)=TRUE,SUBSTITUTE(J37,"<","",1)*1,J37))/2))/((IF(ISTEXT(G37)=TRUE,SUBSTITUTE(G37,"<","",1)*1,G37)+IF(ISTEXT(J37)=TRUE,SUBSTITUTE(J37,"<","",1),J37))/2),"-"))) | O37: =IF(OR(G37="",J37=""),"",IF(AND(I37="Oui",L37="Oui"),"Oui",IF(M37="-","Oui",IF(OR(J37>VLOOKUP($D37,'SeuilsComparaison-EMT'!$C$5:$J$27,4,FALSE),G37>VLOOKUP($D37,'SeuilsComparaison-EMT'!$C$5:$J$27,4,FALSE)=TRUE),IF(J37<=VLOOKUP($D37,'SeuilsComparaison-EMT'!$C$5:$J$27,5,FALSE),IF(ABS(M37)<=VLOOKUP($D37,'SeuilsComparaison-EMT'!$C$5:$J$27,6,FALSE),"Oui","Non"),IF(ABS(M37)<=VLOOKUP($D37,'SeuilsComparaison-EMT'!$C$5:$J$27,8,FALSE),"Oui","Non")),"Oui")))) | Q37: =IF(OR(AND(ISNUMBER(G37),G37>VLOOKUP(D37,'SeuilsComparaison-EMT'!$C$5:$J$27,4,FALSE)),AND(ISNUMBER(J37),J37>VLOOKUP(D37,'SeuilsComparaison-EMT'!$C$5:$J$27,4,FALSE))),IF(AVERAGE(G37,J37)<=VLOOKUP(D37,'SeuilsComparaison-EMT'!$C$5:$J$27,5,FALSE),VLOOKUP(D37,'SeuilsComparaison-EMT'!$C$5:$J$27,6,FALSE),VLOOKUP(D37,'SeuilsComparaison-EMT'!$C$5:$J$27,8,FALSE)),"")
D38: DCO | F38: =VLOOKUP(D38, 'SeuilsComparaison-EMT'!$C$5:$E$28, 3, FALSE) -> 30 | M38: =IF(OR(J38="",G38=""),"",IF(ISERROR(VLOOKUP(D38,'SeuilsComparaison-EMT'!$C$5:$J$25,4,FALSE)),"-",IF(OR(IF(ISTEXT(J38)=TRUE,SUBSTITUTE(J38,"<","",1)*1,J38)>VLOOKUP(D38,'SeuilsComparaison-EMT'!$C$5:$J$25,4,FALSE),IF(ISTEXT(G38)=TRUE,SUBSTITUTE(G38,"<","",1)*1,G38)>VLOOKUP(D38,'SeuilsComparaison-EMT'!$C$5:$J$25,4,FALSE)=TRUE),(IF(ISTEXT(G38)=TRUE,SUBSTITUTE(G38,"<","",1)*1,G38)-((IF(ISTEXT(G38)=TRUE,SUBSTITUTE(G38,"<","",1)*1,G38)+IF(ISTEXT(J38)=TRUE,SUBSTITUTE(J38,"<","",1)*1,J38))/2))/((IF(ISTEXT(G38)=TRUE,SUBSTITUTE(G38,"<","",1)*1,G38)+IF(ISTEXT(J38)=TRUE,SUBSTITUTE(J38,"<","",1),J38))/2),"-"))) | O38: =IF(OR(G38="",J38=""),"",IF(AND(I38="Oui",L38="Oui"),"Oui",IF(M38="-","Oui",IF(OR(J38>VLOOKUP($D38,'SeuilsComparaison-EMT'!$C$5:$J$27,4,FALSE),G38>VLOOKUP($D38,'SeuilsComparaison-EMT'!$C$5:$J$27,4,FALSE)=TRUE),IF(J38<=VLOOKUP($D38,'SeuilsComparaison-EMT'!$C$5:$J$27,5,FALSE),IF(ABS(M38)<=VLOOKUP($D38,'SeuilsComparaison-EMT'!$C$5:$J$27,6,FALSE),"Oui","Non"),IF(ABS(M38)<=VLOOKUP($D38,'SeuilsComparaison-EMT'!$C$5:$J$27,8,FALSE),"Oui","Non")),"Oui")))) | Q38: =IF(OR(AND(ISNUMBER(G38),G38>VLOOKUP(D38,'SeuilsComparaison-EMT'!$C$5:$J$27,4,FALSE)),AND(ISNUMBER(J38),J38>VLOOKUP(D38,'SeuilsComparaison-EMT'!$C$5:$J$27,4,FALSE))),IF(AVERAGE(G38,J38)<=VLOOKUP(D38,'SeuilsComparaison-EMT'!$C$5:$J$27,5,FALSE),VLOOKUP(D38,'SeuilsComparaison-EMT'!$C$5:$J$27,6,FALSE),VLOOKUP(D38,'SeuilsComparaison-EMT'!$C$5:$J$27,8,FALSE)),"")
D39: ST DCO | F39: =VLOOKUP(D39, 'SeuilsComparaison-EMT'!$C$5:$E$28, 3, FALSE) -> 10 | M39: =IF(OR(J39="",G39=""),"",IF(ISERROR(VLOOKUP(D39,'SeuilsComparaison-EMT'!$C$5:$J$25,4,FALSE)),"-",IF(OR(IF(ISTEXT(J39)=TRUE,SUBSTITUTE(J39,"<","",1)*1,J39)>VLOOKUP(D39,'SeuilsComparaison-EMT'!$C$5:$J$25,4,FALSE),IF(ISTEXT(G39)=TRUE,SUBSTITUTE(G39,"<","",1)*1,G39)>VLOOKUP(D39,'SeuilsComparaison-EMT'!$C$5:$J$25,4,FALSE)=TRUE),(IF(ISTEXT(G39)=TRUE,SUBSTITUTE(G39,"<","",1)*1,G39)-((IF(ISTEXT(G39)=TRUE,SUBSTITUTE(G39,"<","",1)*1,G39)+IF(ISTEXT(J39)=TRUE,SUBSTITUTE(J39,"<","",1)*1,J39))/2))/((IF(ISTEXT(G39)=TRUE,SUBSTITUTE(G39,"<","",1)*1,G39)+IF(ISTEXT(J39)=TRUE,SUBSTITUTE(J39,"<","",1),J39))/2),"-"))) | O39: =IF(OR(G39="",J39=""),"",IF(AND(I39="Oui",L39="Oui"),"Oui",IF(M39="-","Oui",IF(OR(J39>VLOOKUP($D39,'SeuilsComparaison-EMT'!$C$5:$J$27,4,FALSE),G39>VLOOKUP($D39,'SeuilsComparaison-EMT'!$C$5:$J$27,4,FALSE)=TRUE),IF(J39<=VLOOKUP($D39,'SeuilsComparaison-EMT'!$C$5:$J$27,5,FALSE),IF(ABS(M39)<=VLOOKUP($D39,'SeuilsComparaison-EMT'!$C$5:$J$27,6,FALSE),"Oui","Non"),IF(ABS(M39)<=VLOOKUP($D39,'SeuilsComparaison-EMT'!$C$5:$J$27,8,FALSE),"Oui","Non")),"Oui")))) | Q39: =IF(OR(AND(ISNUMBER(G39),G39>VLOOKUP(D39,'SeuilsComparaison-EMT'!$C$5:$J$27,4,FALSE)),AND(ISNUMBER(J39),J39>VLOOKUP(D39,'SeuilsComparaison-EMT'!$C$5:$J$27,4,FALSE))),IF(AVERAGE(G39,J39)<=VLOOKUP(D39,'SeuilsComparaison-EMT'!$C$5:$J$27,5,FALSE),VLOOKUP(D39,'SeuilsComparaison-EMT'!$C$5:$J$27,6,FALSE),VLOOKUP(D39,'SeuilsComparaison-EMT'!$C$5:$J$27,8,FALSE)),"")
D40: MEST | F40: =VLOOKUP(D40, 'SeuilsComparaison-EMT'!$C$5:$E$28, 3, FALSE) -> 2 | M40: =IF(OR(J40="",G40=""),"",IF(ISERROR(VLOOKUP(D40,'SeuilsComparaison-EMT'!$C$5:$J$25,4,FALSE)),"-",IF(OR(IF(ISTEXT(J40)=TRUE,SUBSTITUTE(J40,"<","",1)*1,J40)>VLOOKUP(D40,'SeuilsComparaison-EMT'!$C$5:$J$25,4,FALSE),IF(ISTEXT(G40)=TRUE,SUBSTITUTE(G40,"<","",1)*1,G40)>VLOOKUP(D40,'SeuilsComparaison-EMT'!$C$5:$J$25,4,FALSE)=TRUE),(IF(ISTEXT(G40)=TRUE,SUBSTITUTE(G40,"<","",1)*1,G40)-((IF(ISTEXT(G40)=TRUE,SUBSTITUTE(G40,"<","",1)*1,G40)+IF(ISTEXT(J40)=TRUE,SUBSTITUTE(J40,"<","",1)*1,J40))/2))/((IF(ISTEXT(G40)=TRUE,SUBSTITUTE(G40,"<","",1)*1,G40)+IF(ISTEXT(J40)=TRUE,SUBSTITUTE(J40,"<","",1),J40))/2),"-"))) | O40: =IF(OR(G40="",J40=""),"",IF(AND(I40="Oui",L40="Oui"),"Oui",IF(M40="-","Oui",IF(OR(J40>VLOOKUP($D40,'SeuilsComparaison-EMT'!$C$5:$J$27,4,FALSE),G40>VLOOKUP($D40,'SeuilsComparaison-EMT'!$C$5:$J$27,4,FALSE)=TRUE),IF(J40<=VLOOKUP($D40,'SeuilsComparaison-EMT'!$C$5:$J$27,5,FALSE),IF(ABS(M40)<=VLOOKUP($D40,'SeuilsComparaison-EMT'!$C$5:$J$27,6,FALSE),"Oui","Non"),IF(ABS(M40)<=VLOOKUP($D40,'SeuilsComparaison-EMT'!$C$5:$J$27,8,FALSE),"Oui","Non")),"Oui")))) | Q40: =IF(OR(AND(ISNUMBER(G40),G40>VLOOKUP(D40,'SeuilsComparaison-EMT'!$C$5:$J$27,4,FALSE)),AND(ISNUMBER(J40),J40>VLOOKUP(D40,'SeuilsComparaison-EMT'!$C$5:$J$27,4,FALSE))),IF(AVERAGE(G40,J40)<=VLOOKUP(D40,'SeuilsComparaison-EMT'!$C$5:$J$27,5,FALSE),VLOOKUP(D40,'SeuilsComparaison-EMT'!$C$5:$J$27,6,FALSE),VLOOKUP(D40,'SeuilsComparaison-EMT'!$C$5:$J$27,8,FALSE)),"")
D41: NKJ (N) | F41: =VLOOKUP(D41, 'SeuilsComparaison-EMT'!$C$5:$E$28, 3, FALSE) -> 0.5 | M41: =IF(OR(J41="",G41=""),"",IF(ISERROR(VLOOKUP(D41,'SeuilsComparaison-EMT'!$C$5:$J$25,4,FALSE)),"-",IF(OR(IF(ISTEXT(J41)=TRUE,SUBSTITUTE(J41,"<","",1)*1,J41)>VLOOKUP(D41,'SeuilsComparaison-EMT'!$C$5:$J$25,4,FALSE),IF(ISTEXT(G41)=TRUE,SUBSTITUTE(G41,"<","",1)*1,G41)>VLOOKUP(D41,'SeuilsComparaison-EMT'!$C$5:$J$25,4,FALSE)=TRUE),(IF(ISTEXT(G41)=TRUE,SUBSTITUTE(G41,"<","",1)*1,G41)-((IF(ISTEXT(G41)=TRUE,SUBSTITUTE(G41,"<","",1)*1,G41)+IF(ISTEXT(J41)=TRUE,SUBSTITUTE(J41,"<","",1)*1,J41))/2))/((IF(ISTEXT(G41)=TRUE,SUBSTITUTE(G41,"<","",1)*1,G41)+IF(ISTEXT(J41)=TRUE,SUBSTITUTE(J41,"<","",1),J41))/2),"-"))) | O41: =IF(OR(G41="",J41=""),"",IF(AND(I41="Oui",L41="Oui"),"Oui",IF(M41="-","Oui",IF(OR(J41>VLOOKUP($D41,'SeuilsComparaison-EMT'!$C$5:$J$27,4,FALSE),G41>VLOOKUP($D41,'SeuilsComparaison-EMT'!$C$5:$J$27,4,FALSE)=TRUE),IF(J41<=VLOOKUP($D41,'SeuilsComparaison-EMT'!$C$5:$J$27,5,FALSE),IF(ABS(M41)<=VLOOKUP($D41,'SeuilsComparaison-EMT'!$C$5:$J$27,6,FALSE),"Oui","Non"),IF(ABS(M41)<=VLOOKUP($D41,'SeuilsComparaison-EMT'!$C$5:$J$27,8,FALSE),"Oui","Non")),"Oui")))) | Q41: =IF(OR(AND(ISNUMBER(G41),G41>VLOOKUP(D41,'SeuilsComparaison-EMT'!$C$5:$J$27,4,FALSE)),AND(ISNUMBER(J41),J41>VLOOKUP(D41,'SeuilsComparaison-EMT'!$C$5:$J$27,4,FALSE))),IF(AVERAGE(G41,J41)<=VLOOKUP(D41,'SeuilsComparaison-EMT'!$C$5:$J$27,5,FALSE),VLOOKUP(D41,'SeuilsComparaison-EMT'!$C$5:$J$27,6,FALSE),VLOOKUP(D41,'SeuilsComparaison-EMT'!$C$5:$J$27,8,FALSE)),"")
D42: NGL | F42: =VLOOKUP(D42, 'SeuilsComparaison-EMT'!$C$5:$E$28, 3, FALSE) -> 1 | M42: =IF(OR(J42="",G42=""),"",IF(ISERROR(VLOOKUP(D42,'SeuilsComparaison-EMT'!$C$5:$J$25,4,FALSE)),"-",IF(OR(IF(ISTEXT(J42)=TRUE,SUBSTITUTE(J42,"<","",1)*1,J42)>VLOOKUP(D42,'SeuilsComparaison-EMT'!$C$5:$J$25,4,FALSE),IF(ISTEXT(G42)=TRUE,SUBSTITUTE(G42,"<","",1)*1,G42)>VLOOKUP(D42,'SeuilsComparaison-EMT'!$C$5:$J$25,4,FALSE)=TRUE),(IF(ISTEXT(G42)=TRUE,SUBSTITUTE(G42,"<","",1)*1,G42)-((IF(ISTEXT(G42)=TRUE,SUBSTITUTE(G42,"<","",1)*1,G42)+IF(ISTEXT(J42)=TRUE,SUBSTITUTE(J42,"<","",1)*1,J42))/2))/((IF(ISTEXT(G42)=TRUE,SUBSTITUTE(G42,"<","",1)*1,G42)+IF(ISTEXT(J42)=TRUE,SUBSTITUTE(J42,"<","",1),J42))/2),"-"))) | O42: =IF(OR(G42="",J42=""),"",IF(AND(I42="Oui",L42="Oui"),"Oui",IF(M42="-","Oui",IF(OR(J42>VLOOKUP($D42,'SeuilsComparaison-EMT'!$C$5:$J$27,4,FALSE),G42>VLOOKUP($D42,'SeuilsComparaison-EMT'!$C$5:$J$27,4,FALSE)=TRUE),IF(J42<=VLOOKUP($D42,'SeuilsComparaison-EMT'!$C$5:$J$27,5,FALSE),IF(ABS(M42)<=VLOOKUP($D42,'SeuilsComparaison-EMT'!$C$5:$J$27,6,FALSE),"Oui","Non"),IF(ABS(M42)<=VLOOKUP($D42,'SeuilsComparaison-EMT'!$C$5:$J$27,8,FALSE),"Oui","Non")),"Oui")))) | Q42: =IF(OR(AND(ISNUMBER(G42),G42>VLOOKUP(D42,'SeuilsComparaison-EMT'!$C$5:$J$27,4,FALSE)),AND(ISNUMBER(J42),J42>VLOOKUP(D42,'SeuilsComparaison-EMT'!$C$5:$J$27,4,FALSE))),IF(AVERAGE(G42,J42)<=VLOOKUP(D42,'SeuilsComparaison-EMT'!$C$5:$J$27,5,FALSE),VLOOKUP(D42,'SeuilsComparaison-EMT'!$C$5:$J$27,6,FALSE),VLOOKUP(D42,'SeuilsComparaison-EMT'!$C$5:$J$27,8,FALSE)),"")
D43: NH4 (NH4) | F43: =VLOOKUP(D43, 'SeuilsComparaison-EMT'!$C$5:$E$28, 3, FALSE) -> 0.5 | M43: =IF(OR(J43="",G43=""),"",IF(ISERROR(VLOOKUP(D43,'SeuilsComparaison-EMT'!$C$5:$J$25,4,FALSE)),"-",IF(OR(IF(ISTEXT(J43)=TRUE,SUBSTITUTE(J43,"<","",1)*1,J43)>VLOOKUP(D43,'SeuilsComparaison-EMT'!$C$5:$J$25,4,FALSE),IF(ISTEXT(G43)=TRUE,SUBSTITUTE(G43,"<","",1)*1,G43)>VLOOKUP(D43,'SeuilsComparaison-EMT'!$C$5:$J$25,4,FALSE)=TRUE),(IF(ISTEXT(G43)=TRUE,SUBSTITUTE(G43,"<","",1)*1,G43)-((IF(ISTEXT(G43)=TRUE,SUBSTITUTE(G43,"<","",1)*1,G43)+IF(ISTEXT(J43)=TRUE,SUBSTITUTE(J43,"<","",1)*1,J43))/2))/((IF(ISTEXT(G43)=TRUE,SUBSTITUTE(G43,"<","",1)*1,G43)+IF(ISTEXT(J43)=TRUE,SUBSTITUTE(J43,"<","",1),J43))/2),"-"))) | O43: =IF(OR(G43="",J43=""),"",IF(AND(I43="Oui",L43="Oui"),"Oui",IF(M43="-","Oui",IF(OR(J43>VLOOKUP($D43,'SeuilsComparaison-EMT'!$C$5:$J$27,4,FALSE),G43>VLOOKUP($D43,'SeuilsComparaison-EMT'!$C$5:$J$27,4,FALSE)=TRUE),IF(J43<=VLOOKUP($D43,'SeuilsComparaison-EMT'!$C$5:$J$27,5,FALSE),IF(ABS(M43)<=VLOOKUP($D43,'SeuilsComparaison-EMT'!$C$5:$J$27,6,FALSE),"Oui","Non"),IF(ABS(M43)<=VLOOKUP($D43,'SeuilsComparaison-EMT'!$C$5:$J$27,8,FALSE),"Oui","Non")),"Oui")))) | Q43: =IF(OR(AND(ISNUMBER(G43),G43>VLOOKUP(D43,'SeuilsComparaison-EMT'!$C$5:$J$27,4,FALSE)),AND(ISNUMBER(J43),J43>VLOOKUP(D43,'SeuilsComparaison-EMT'!$C$5:$J$27,4,FALSE))),IF(AVERAGE(G43,J43)<=VLOOKUP(D43,'SeuilsComparaison-EMT'!$C$5:$J$27,5,FALSE),VLOOKUP(D43,'SeuilsComparaison-EMT'!$C$5:$J$27,6,FALSE),VLOOKUP(D43,'SeuilsComparaison-EMT'!$C$5:$J$27,8,FALSE)),"")
D44: NO2 (NO2) | F44: =VLOOKUP(D44, 'SeuilsComparaison-EMT'!$C$5:$E$28, 3, FALSE) -> 0.05 | M44: =IF(OR(J44="",G44=""),"",IF(ISERROR(VLOOKUP(D44,'SeuilsComparaison-EMT'!$C$5:$J$25,4,FALSE)),"-",IF(OR(IF(ISTEXT(J44)=TRUE,SUBSTITUTE(J44,"<","",1)*1,J44)>VLOOKUP(D44,'SeuilsComparaison-EMT'!$C$5:$J$25,4,FALSE),IF(ISTEXT(G44)=TRUE,SUBSTITUTE(G44,"<","",1)*1,G44)>VLOOKUP(D44,'SeuilsComparaison-EMT'!$C$5:$J$25,4,FALSE)=TRUE),(IF(ISTEXT(G44)=TRUE,SUBSTITUTE(G44,"<","",1)*1,G44)-((IF(ISTEXT(G44)=TRUE,SUBSTITUTE(G44,"<","",1)*1,G44)+IF(ISTEXT(J44)=TRUE,SUBSTITUTE(J44,"<","",1)*1,J44))/2))/((IF(ISTEXT(G44)=TRUE,SUBSTITUTE(G44,"<","",1)*1,G44)+IF(ISTEXT(J44)=TRUE,SUBSTITUTE(J44,"<","",1),J44))/2),"-"))) | O44: =IF(OR(G44="",J44=""),"",IF(AND(I44="Oui",L44="Oui"),"Oui",IF(M44="-","Oui",IF(OR(J44>VLOOKUP($D44,'SeuilsComparaison-EMT'!$C$5:$J$27,4,FALSE),G44>VLOOKUP($D44,'SeuilsComparaison-EMT'!$C$5:$J$27,4,FALSE)=TRUE),IF(J44<=VLOOKUP($D44,'SeuilsComparaison-EMT'!$C$5:$J$27,5,FALSE),IF(ABS(M44)<=VLOOKUP($D44,'SeuilsComparaison-EMT'!$C$5:$J$27,6,FALSE),"Oui","Non"),IF(ABS(M44)<=VLOOKUP($D44,'SeuilsComparaison-EMT'!$C$5:$J$27,8,FALSE),"Oui","Non")),"Oui")))) | Q44: =IF(OR(AND(ISNUMBER(G44),G44>VLOOKUP(D44,'SeuilsComparaison-EMT'!$C$5:$J$27,4,FALSE)),AND(ISNUMBER(J44),J44>VLOOKUP(D44,'SeuilsComparaison-EMT'!$C$5:$J$27,4,FALSE))),IF(AVERAGE(G44,J44)<=VLOOKUP(D44,'SeuilsComparaison-EMT'!$C$5:$J$27,5,FALSE),VLOOKUP(D44,'SeuilsComparaison-EMT'!$C$5:$J$27,6,FALSE),VLOOKUP(D44,'SeuilsComparaison-EMT'!$C$5:$J$27,8,FALSE)),"")
D45: NO3 (NO3) | F45: =VLOOKUP(D45, 'SeuilsComparaison-EMT'!$C$5:$E$28, 3, FALSE) -> 1 | M45: =IF(OR(J45="",G45=""),"",IF(ISERROR(VLOOKUP(D45,'SeuilsComparaison-EMT'!$C$5:$J$25,4,FALSE)),"-",IF(OR(IF(ISTEXT(J45)=TRUE,SUBSTITUTE(J45,"<","",1)*1,J45)>VLOOKUP(D45,'SeuilsComparaison-EMT'!$C$5:$J$25,4,FALSE),IF(ISTEXT(G45)=TRUE,SUBSTITUTE(G45,"<","",1)*1,G45)>VLOOKUP(D45,'SeuilsComparaison-EMT'!$C$5:$J$25,4,FALSE)=TRUE),(IF(ISTEXT(G45)=TRUE,SUBSTITUTE(G45,"<","",1)*1,G45)-((IF(ISTEXT(G45)=TRUE,SUBSTITUTE(G45,"<","",1)*1,G45)+IF(ISTEXT(J45)=TRUE,SUBSTITUTE(J45,"<","",1)*1,J45))/2))/((IF(ISTEXT(G45)=TRUE,SUBSTITUTE(G45,"<","",1)*1,G45)+IF(ISTEXT(J45)=TRUE,SUBSTITUTE(J45,"<","",1),J45))/2),"-"))) | O45: =IF(OR(G45="",J45=""),"",IF(AND(I45="Oui",L45="Oui"),"Oui",IF(M45="-","Oui",IF(OR(J45>VLOOKUP($D45,'SeuilsComparaison-EMT'!$C$5:$J$27,4,FALSE),G45>VLOOKUP($D45,'SeuilsComparaison-EMT'!$C$5:$J$27,4,FALSE)=TRUE),IF(J45<=VLOOKUP($D45,'SeuilsComparaison-EMT'!$C$5:$J$27,5,FALSE),IF(ABS(M45)<=VLOOKUP($D45,'SeuilsComparaison-EMT'!$C$5:$J$27,6,FALSE),"Oui","Non"),IF(ABS(M45)<=VLOOKUP($D45,'SeuilsComparaison-EMT'!$C$5:$J$27,8,FALSE),"Oui","Non")),"Oui")))) | Q45: =IF(OR(AND(ISNUMBER(G45),G45>VLOOKUP(D45,'SeuilsComparaison-EMT'!$C$5:$J$27,4,FALSE)),AND(ISNUMBER(J45),J45>VLOOKUP(D45,'SeuilsComparaison-EMT'!$C$5:$J$27,4,FALSE))),IF(AVERAGE(G45,J45)<=VLOOKUP(D45,'SeuilsComparaison-EMT'!$C$5:$J$27,5,FALSE),VLOOKUP(D45,'SeuilsComparaison-EMT'!$C$5:$J$27,6,FALSE),VLOOKUP(D45,'SeuilsComparaison-EMT'!$C$5:$J$27,8,FALSE)),"")
D46: PT | F46: =VLOOKUP(D46, 'SeuilsComparaison-EMT'!$C$5:$E$28, 3, FALSE) -> 0.05 | M46: =IF(OR(J46="",G46=""),"",IF(ISERROR(VLOOKUP(D46,'SeuilsComparaison-EMT'!$C$5:$J$25,4,FALSE)),"-",IF(OR(IF(ISTEXT(J46)=TRUE,SUBSTITUTE(J46,"<","",1)*1,J46)>VLOOKUP(D46,'SeuilsComparaison-EMT'!$C$5:$J$25,4,FALSE),IF(ISTEXT(G46)=TRUE,SUBSTITUTE(G46,"<","",1)*1,G46)>VLOOKUP(D46,'SeuilsComparaison-EMT'!$C$5:$J$25,4,FALSE)=TRUE),(IF(ISTEXT(G46)=TRUE,SUBSTITUTE(G46,"<","",1)*1,G46)-((IF(ISTEXT(G46)=TRUE,SUBSTITUTE(G46,"<","",1)*1,G46)+IF(ISTEXT(J46)=TRUE,SUBSTITUTE(J46,"<","",1)*1,J46))/2))/((IF(ISTEXT(G46)=TRUE,SUBSTITUTE(G46,"<","",1)*1,G46)+IF(ISTEXT(J46)=TRUE,SUBSTITUTE(J46,"<","",1),J46))/2),"-"))) | O46: =IF(OR(G46="",J46=""),"",IF(AND(I46="Oui",L46="Oui"),"Oui",IF(M46="-","Oui",IF(OR(J46>VLOOKUP($D46,'SeuilsComparaison-EMT'!$C$5:$J$27,4,FALSE),G46>VLOOKUP($D46,'SeuilsComparaison-EMT'!$C$5:$J$27,4,FALSE)=TRUE),IF(J46<=VLOOKUP($D46,'SeuilsComparaison-EMT'!$C$5:$J$27,5,FALSE),IF(ABS(M46)<=VLOOKUP($D46,'SeuilsComparaison-EMT'!$C$5:$J$27,6,FALSE),"Oui","Non"),IF(ABS(M46)<=VLOOKUP($D46,'SeuilsComparaison-EMT'!$C$5:$J$27,8,FALSE),"Oui","Non")),"Oui")))) | Q46: =IF(OR(AND(ISNUMBER(G46),G46>VLOOKUP(D46,'SeuilsComparaison-EMT'!$C$5:$J$27,4,FALSE)),AND(ISNUMBER(J46),J46>VLOOKUP(D46,'SeuilsComparaison-EMT'!$C$5:$J$27,4,FALSE))),IF(AVERAGE(G46,J46)<=VLOOKUP(D46,'SeuilsComparaison-EMT'!$C$5:$J$27,5,FALSE),VLOOKUP(D46,'SeuilsComparaison-EMT'!$C$5:$J$27,6,FALSE),VLOOKUP(D46,'SeuilsComparaison-EMT'!$C$5:$J$27,8,FALSE)),"")
D47: Conductivité | F47: =VLOOKUP(D47, 'SeuilsComparaison-EMT'!$C$5:$E$28, 3, FALSE) -> 0 | M47: =IF(OR(J47="",G47=""),"",IF(ISERROR(VLOOKUP(D47,'SeuilsComparaison-EMT'!$C$5:$J$25,4,FALSE)),"-",IF(OR(IF(ISTEXT(J47)=TRUE,SUBSTITUTE(J47,"<","",1)*1,J47)>VLOOKUP(D47,'SeuilsComparaison-EMT'!$C$5:$J$25,4,FALSE),IF(ISTEXT(G47)=TRUE,SUBSTITUTE(G47,"<","",1)*1,G47)>VLOOKUP(D47,'SeuilsComparaison-EMT'!$C$5:$J$25,4,FALSE)=TRUE),(IF(ISTEXT(G47)=TRUE,SUBSTITUTE(G47,"<","",1)*1,G47)-((IF(ISTEXT(G47)=TRUE,SUBSTITUTE(G47,"<","",1)*1,G47)+IF(ISTEXT(J47)=TRUE,SUBSTITUTE(J47,"<","",1)*1,J47))/2))/((IF(ISTEXT(G47)=TRUE,SUBSTITUTE(G47,"<","",1)*1,G47)+IF(ISTEXT(J47)=TRUE,SUBSTITUTE(J47,"<","",1),J47))/2),"-"))) | O47: =IF(OR(G47="",J47=""),"",IF(AND(I47="Oui",L47="Oui"),"Oui",IF(M47="-","Oui",IF(OR(J47>VLOOKUP($D47,'SeuilsComparaison-EMT'!$C$5:$J$27,4,FALSE),G47>VLOOKUP($D47,'SeuilsComparaison-EMT'!$C$5:$J$27,4,FALSE)=TRUE),IF(J47<=VLOOKUP($D47,'SeuilsComparaison-EMT'!$C$5:$J$27,5,FALSE),IF(ABS(M47)<=VLOOKUP($D47,'SeuilsComparaison-EMT'!$C$5:$J$27,6,FALSE),"Oui","Non"),IF(ABS(M47)<=VLOOKUP($D47,'SeuilsComparaison-EMT'!$C$5:$J$27,8,FALSE),"Oui","Non")),"Oui")))) | Q47: =IF(OR(AND(ISNUMBER(G47),G47>VLOOKUP(D47,'SeuilsComparaison-EMT'!$C$5:$J$27,4,FALSE)),AND(ISNUMBER(J47),J47>VLOOKUP(D47,'SeuilsComparaison-EMT'!$C$5:$J$27,4,FALSE))),IF(AVERAGE(G47,J47)<=VLOOKUP(D47,'SeuilsComparaison-EMT'!$C$5:$J$27,5,FALSE),VLOOKUP(D47,'SeuilsComparaison-EMT'!$C$5:$J$27,6,FALSE),VLOOKUP(D47,'SeuilsComparaison-EMT'!$C$5:$J$27,8,FALSE)),"") | R47: non prise en compte
D48: Cl | F48: =VLOOKUP(D48, 'SeuilsComparaison-EMT'!$C$5:$E$28, 3, FALSE) -> 5 | M48: =IF(OR(J48="",G48=""),"",IF(ISERROR(VLOOKUP(D48,'SeuilsComparaison-EMT'!$C$5:$J$25,4,FALSE)),"-",IF(OR(IF(ISTEXT(J48)=TRUE,SUBSTITUTE(J48,"<","",1)*1,J48)>VLOOKUP(D48,'SeuilsComparaison-EMT'!$C$5:$J$25,4,FALSE),IF(ISTEXT(G48)=TRUE,SUBSTITUTE(G48,"<","",1)*1,G48)>VLOOKUP(D48,'SeuilsComparaison-EMT'!$C$5:$J$25,4,FALSE)=TRUE),(IF(ISTEXT(G48)=TRUE,SUBSTITUTE(G48,"<","",1)*1,G48)-((IF(ISTEXT(G48)=TRUE,SUBSTITUTE(G48,"<","",1)*1,G48)+IF(ISTEXT(J48)=TRUE,SUBSTITUTE(J48,"<","",1)*1,J48))/2))/((IF(ISTEXT(G48)=TRUE,SUBSTITUTE(G48,"<","",1)*1,G48)+IF(ISTEXT(J48)=TRUE,SUBSTITUTE(J48,"<","",1),J48))/2),"-"))) | O48: =IF(OR(G48="",J48=""),"",IF(AND(I48="Oui",L48="Oui"),"Oui",IF(M48="-","Oui",IF(OR(J48>VLOOKUP($D48,'SeuilsComparaison-EMT'!$C$5:$J$27,4,FALSE),G48>VLOOKUP($D48,'SeuilsComparaison-EMT'!$C$5:$J$27,4,FALSE)=TRUE),IF(J48<=VLOOKUP($D48,'SeuilsComparaison-EMT'!$C$5:$J$27,5,FALSE),IF(ABS(M48)<=VLOOKUP($D48,'SeuilsComparaison-EMT'!$C$5:$J$27,6,FALSE),"Oui","Non"),IF(ABS(M48)<=VLOOKUP($D48,'SeuilsComparaison-EMT'!$C$5:$J$27,8,FALSE),"Oui","Non")),"Oui")))) | Q48: =IF(OR(AND(ISNUMBER(G48),G48>VLOOKUP(D48,'SeuilsComparaison-EMT'!$C$5:$J$27,4,FALSE)),AND(ISNUMBER(J48),J48>VLOOKUP(D48,'SeuilsComparaison-EMT'!$C$5:$J$27,4,FALSE))),IF(AVERAGE(G48,J48)<=VLOOKUP(D48,'SeuilsComparaison-EMT'!$C$5:$J$27,5,FALSE),VLOOKUP(D48,'SeuilsComparaison-EMT'!$C$5:$J$27,6,FALSE),VLOOKUP(D48,'SeuilsComparaison-EMT'!$C$5:$J$27,8,FALSE)),"") | R48: non prise en compte
D49: MS | F49: =VLOOKUP(D49, 'SeuilsComparaison-EMT'!$C$5:$E$28, 3, FALSE) -> 0 | M49: =IF(OR(J49="",G49=""),"",IF(ISERROR(VLOOKUP(D49,'SeuilsComparaison-EMT'!$C$5:$J$25,4,FALSE)),"-",IF(OR(IF(ISTEXT(J49)=TRUE,SUBSTITUTE(J49,"<","",1)*1,J49)>VLOOKUP(D49,'SeuilsComparaison-EMT'!$C$5:$J$25,4,FALSE),IF(ISTEXT(G49)=TRUE,SUBSTITUTE(G49,"<","",1)*1,G49)>VLOOKUP(D49,'SeuilsComparaison-EMT'!$C$5:$J$25,4,FALSE)=TRUE),(IF(ISTEXT(G49)=TRUE,SUBSTITUTE(G49,"<","",1)*1,G49)-((IF(ISTEXT(G49)=TRUE,SUBSTITUTE(G49,"<","",1)*1,G49)+IF(ISTEXT(J49)=TRUE,SUBSTITUTE(J49,"<","",1)*1,J49))/2))/((IF(ISTEXT(G49)=TRUE,SUBSTITUTE(G49,"<","",1)*1,G49)+IF(ISTEXT(J49)=TRUE,SUBSTITUTE(J49,"<","",1),J49))/2),"-"))) | O49: =IF(OR(G49="",J49=""),"",IF(AND(I49="Oui",L49="Oui"),"Oui",IF(M49="-","Oui",IF(OR(J49>VLOOKUP($D49,'SeuilsComparaison-EMT'!$C$5:$J$27,4,FALSE),G49>VLOOKUP($D49,'SeuilsComparaison-EMT'!$C$5:$J$27,4,FALSE)=TRUE),IF(J49<=VLOOKUP($D49,'SeuilsComparaison-EMT'!$C$5:$J$27,5,FALSE),IF(ABS(M49)<=VLOOKUP($D49,'SeuilsComparaison-EMT'!$C$5:$J$27,6,FALSE),"Oui","Non"),IF(ABS(M49)<=VLOOKUP($D49,'SeuilsComparaison-EMT'!$C$5:$J$27,8,FALSE),"Oui","Non")),"Oui")))) | Q49: =IF(OR(AND(ISNUMBER(G49),G49>VLOOKUP(D49,'SeuilsComparaison-EMT'!$C$5:$J$27,4,FALSE)),AND(ISNUMBER(J49),J49>VLOOKUP(D49,'SeuilsComparaison-EMT'!$C$5:$J$27,4,FALSE))),IF(AVERAGE(G49,J49)<=VLOOKUP(D49,'SeuilsComparaison-EMT'!$C$5:$J$27,5,FALSE),VLOOKUP(D49,'SeuilsComparaison-EMT'!$C$5:$J$27,6,FALSE),VLOOKUP(D49,'SeuilsComparaison-EMT'!$C$5:$J$27,8,FALSE)),"") | R49: non prise en compte
D51: COMMENTAIRES :
J58: Ajouter un comparatif analytique

Sheet PARAM
A3: Equipement Q | B3: Equipement Prel | C3: Type | D3: Liste des statuts | E3: Code | F3: Code | G3: Liste des statuts | H3: Liste des statuts | I3: Code
A4: Canal Venturi | B4: Préleveur Automatique | C4: Débitmètre en charge | D4: Validé | E4: A2 | F4: A1 | G4: Oui | H4: Agréé | I4: A2
A5: Débitmètre électromagnétique (eau) | B5: Vanne de prélèvement asservie | C5: Débitmètre gravitaire | D5: Non validé | E5: A3 | F5: R1 | G5: Non | H5: Non agréé | I5: A3
A6: Débitmètre électromagnétique (boue/MDV) | B6: Prélèvement ponctuel | C6: Préleveur | D6: Non contrôlé | E6: A4 | F6: R2 | I6: A4
A7: Seuil | C7: Sonde de température | D7: Réserve | E7: A5 | F7: R3 | I7: A5
A8: Caisson | D8: Non validé (absence d'équipement) | E8: A6 | I8: A6
A9: Loi COACHs | D9: Non validé (équipement insuffisant) | E9: A7 | I9: A7
A10: Débitmètre électromagnétique partiellement plein | E10: A8 | I10: A8
A11: Clapet | E11: S1 | I11: S1
A12: Détecteur de surverse | E12: S2 | I12: S2
A13: Modélisation | E13: S3 | I13: S3
A14: Hauteur/Vitesse | E14: S4 | I14: S4
A15: Point non existant | E15: S5 | I15: S5
E16: S12 | I16: S12
E17: S13 | I17: S13
E18: S16 | I18: S16
E19: S19 | I19: S19
A20: LISTE_1 | B20: LISTE_2 | C20: LISTE_3 | D20: LISTE_4 | F20: LISTE_5 | G20: LISTE_6 | H20: LISTE_7
A21: Oui | B21: Validé | C21: Validé | D21: Validé | F21: Validé | G21: Non applicable | H21: Oui
A22: Non | B22: Non validé | C22: Non validé | D22: Non validé | F22: Entre 5 et 10% | H22: Non
A23: Non applicable | B23: Non contrôlé | C23: Non contrôlé | D23: Non contrôlé | F23: Non validé (>10%) | H23: Non contrôlé
B24: Non applicable | C24: Réserve | D24: Réserve | F24: Non contrôlé
C25: Non applicable | D25: Non validé (absence d'équipement) | F25: Non applicable
D26: Non validé (équipement insuffisant)
D27: Non applicable
A28: Type équipement : débimètre
A29: Q en charge | B29: Q Gravitaire | C29: Equipement de contrôle H | D29: Type réseau | E29: Q en charge boues
A30: Débitmètre électromagnétique (eau) | B30: Canal Venturi | C30: Réglet | D30: Mixte | E30: Débitmètre électromagnétique (boue/MDV)
A31: Organe déprimogène (pito...) | B31: Seuil | C31: Sonde | D31: Unitaire
A32: Débitmètre Ultrason | B32: Caisson | C32: Câble | D32: Séparatif
A33: Compteur mécanique | B33: Loi COACHs
B34: Débitmètre électromagnétique partiellement plein
B35: Clapet
B36: Détecteur de surverse
B37: Modélisation
B38: Hauteur/Vitesse
A42: Listes fiches terrain
A43: Asservissement | B43: Conformité | C43: Type_capteur | D43: Satisfaction | E43: Fréquence | F43: Conditions météo | G43: Montage sonde
A44: Au débit | B44: Conforme | C44: Ultrason | D44: Satisfaisant | E44: Journalière | F44: Temps sec | G44: En /
A45: Au temps | B45: Conforme avec réserve | C45: Radar | D45: Non satisfaisant | E45: Hebdomadaire | F45: Temps de pluie | G45: En V
A46: Inconnu | B46: Non conforme | C46: Piezo | D46: Non vérifié | E46: Mensuelle | F46: Inconnues | G46: En W
B47: Non vérifié | C47: Bulle à bulle | E47: Bimensuelle | G47: En N
B48: Non vérifiable | C48: Autre | E48: Trimestrielle
E49: Semestrielle
E50: Annuelle
E51: Autre
A53: Listes méthode contrôle
A54: Méthode | B54: Type de mesure
A55: Simulation d'une hauteur d'eau (leurre) | B55: Ponctuelle
A56: Mesure comparative en parallèle | B56: En continu
A57: Simulation d'une hauteur d'eau et mesure en parallèle

Sheet SeuilsComparaison-EMT
B2: COMPARATIF ANALYTIQUE : DEFINITION DES ECARTS MAXIMUM TOLERES (EMT)
B4: Code SANDRE | C4: Paramètres | D4: Unités | E4: Limites de quantification | F4: Seuil de comparaison | G4: Concentration supérieure au seuil de comparaison et inférieure ou égale à | H4: Ecart Maximum Toléré | I4: Concentration supérieure à | J4: Ecart Maximum Toléré
B5: 1313 | C5: DBO5 | D5: en mg/l de O2 | E5: 3 | F5: 15 | G5: 80 | H5: 0.3 | I5: 80 | J5: 0.2
B6: 1314 | C6: DCO | D6: en mg/l de O2 | E6: 30 | F6: 80 | G6: 250 | H6: 0.2 | I6: 250 | J6: 0.1
B7: 6396 | C7: ST DCO | D7: en mg/l de O2 | E7: 10 | F7: 20 | G7: 150 | H7: 0.2 | I7: 150 | J7: 0.1
B8: 1305 | C8: MEST | D8: en mg/l | E8: 2 | F8: 15 | G8: 60 | H8: 0.3 | I8: 60 | J8: 0.2
B9: 1319 | C9: NKJ (N) | D9: en mg/l de N | E9: 0.5 | F9: 6 | I9: 6 | J9: 0.1
B10: 1551 | C10: NGL | D10: en mg/l de N | E10: 1 | F10: 6 | I10: 6 | J10: 0.2
B11: 1335 | C11: NH4 (NH4) | D11: en mg/l de NH4+ | E11: 0.5 | F11: 6 | I11: 6 | J11: 0.1
B12: 1339 | C12: NO2 (NO2) | D12: en mg/l de NO2 | E12: 0.05 | F12: 1 | I12: 1 | J12: 0.2
B13: 1340 | C13: NO3 (NO3) | D13: en mg/l de NO3 | E13: 1 | F13: 5 | I13: 5 | J13: 0.2
B14: 1350 | C14: PT | D14: en mg/l de P | E14: 0.05 | F14: 1 | I14: 1 | J14: 0.2
B15: 1369 | C15: As | D15: en mg/l | E15: 0.005 | F15: 0.5 | G15: 1 | H15: 0.6 | I15: 1 | J15: 0.3
B16: 1388 | C16: Cd | D16: en mg/l | E16: 0.001 | F16: 0.5 | G16: 1 | H16: 0.6 | I16: 1 | J16: 0.3
B17: 1389 | C17: Cr | D17: en mg/l | E17: 0.005 | F17: 0.5 | G17: 1 | H17: 0.6 | I17: 1 | J17: 0.3
B18: 1392 | C18: Cu | D18: en mg/l | E18: 0.005 | F18: 0.5 | G18: 1 | H18: 0.6 | I18: 1 | J18: 0.3
B19: 1387 | C19: Hg | D19: en mg/l | E19: 0.0002 | F19: 0.005 | G19: 0.01 | H19: 0.6 | I19: 0.01 | J19: 0.3
B20: 1386 | C20: Ni | D20: en mg/l | E20: 0.005 | F20: 0.5 | G20: 1 | H20: 0.6 | I20: 1 | J20: 0.3
B21: 1382 | C21: Pb | D21: en mg/l | E21: 0.002 | F21: 0.5 | G21: 1 | H21: 0.6 | I21: 1 | J21: 0.3
B22: 1383 | C22: Zn | D22: en mg/l | E22: 0.005 | F22: 0.5 | G22: 1 | H22: 0.6 | I22: 1 | J22: 0.3
B23: 1106 | C23: AOX | D23: en mg/l | E23: 0.01 | F23: 0.05 | G23: 0.5 | H23: 0.6 | I23: 0.5 | J23: 0.3
B24: 1841 | C24: COT | D24: en mg/l | E24: 0.3 | F24: 5 | G24: 15 | H24: 0.3 | I24: 15 | J24: 0.1
B25: 1798 | C25: Conductivité
B26: 1337 | C26: Cl | D26: en mg/l | E26: 5
B27: 1799 | C27: MS | D27: en g/l | H27: 0.2 | J27: 0.05
B28: Le cacul des écarts analytiques est effectué si l'un des deux ou les deux résultats sont au dessus du seuil de comparaison. L'écart est calculé par rapport à la moyenne des 2 valeurs.

Sheet Equipements_STEU
A1: Lignes STEU | B1: =Descriptif!$AD$3 -> 34 | C1: =Descriptif!$AF$3 -> 34
A2: Puvio STEU | B2: =Descriptif!$AH$3 -> 43 | C2: =Descriptif!$AI$3 -> 43
A3: Type Equipement | B3: Type
B4: cellule typeE | C4: cellule score global | D4: cellule eval global | E4: cellule commentaire score | F4: cellule commentaire
A5: Pluviomètre | B5: D25 | C5: P33 | D5: N33 | E5: D33 | F5: C37
A6: =PARAM!$C4 -> Débitmètre en charge | B6: D32 | C6: P45 | D6: N45 | E6: D45 | F6: C49
A7: =PARAM!$C5 -> Débitmètre gravitaire | B7: D40 | C7: R53 | D7: P53 | E7: D53 | F7: C57
A8: =PARAM!$C6 -> Préleveur | B8: D37 | C8: P50 | D8: N50 | E8: D50 | F8: C54
A9: =PARAM!$C7 -> Sonde de température | B9: D26 | C9: P33 | D9: N33 | E9: D33 | F9: C37
B12: =$B$2+A42-1 -> 69
A13: Liste équipements
A14: Ligne | C14: Colonnes | H14: Données équipement | N14: TypeE | O14: Score | Q14: Evaluation | S14: Commentaire eval | U14: Commentaire equipement | W14: Evaluations critères | AI14: Scores critères
A15: n° | B15: utilisable | C15: F | D15: I | E15: M | F15: O | G15: J | H15: Feuille | I15: loc | J15: type | K15: typeE | L15: code | M15: point | N15: src | O15: src | P15: val | Q15: src | R15: val | S15: src | T15: val | U15: src | V15: val | W15: col | X15: ligne | Y15: 1 | Z15: 2 | AA15: 3 | AB15: 4 | AC15: 5 | AD15: 6 | AE15: 7 | AF15: 8 | AG15: 9 | AH15: 10 | AI15: col | AJ15: ligne | AK15: 1 | AL15: 2 | AM15: 3 | AN15: 4 | AO15: 5 | AP15: 6 | AQ15: 7 | AR15: 8 | AS15: 9 | AT15: 10
A16: 1 | B16: =IF(OR(AND(($B$1+A16-1)>=$B$1,($B$1+A16-1)<$C$1),AND(($B$1+A16-1)>=$B$2,($B$1+A16-1)<$C$2)),TRUE,FALSE) -> FALSE | C16: =IF( AND( $B16, OR( _xlfn.SINGLE(INDIRECT("Descriptif!$M"&($B$1+$A16-1)))="Préleveur", LEFT(_xlfn.SINGLE(INDIRECT("Descriptif!$M"&($B$1+$A16-1))),5)="Sonde", LEFT(_xlfn.SINGLE(INDIRECT("Descriptif!$M"&($B$1+$A16-1))),10)="Débitmètre", LEFT(_xlfn.SINGLE(INDIRECT("Descriptif!$F"&($B$1+$A16-1))),6)="PLUVIO" ) ), _xlfn.SINGLE(INDIRECT("Descriptif!$"&C$15&($B$1 +$A16 -1))), "" ) | D16: =IF( AND( $B16, OR( _xlfn.SINGLE(INDIRECT("Descriptif!$M"&($B$1+$A16-1)))="Préleveur", LEFT(_xlfn.SINGLE(INDIRECT("Descriptif!$M"&($B$1+$A16-1))),5)="Sonde", LEFT(_xlfn.SINGLE(INDIRECT("Descriptif!$M"&($B$1+$A16-1))),10)="Débitmètre", LEFT(_xlfn.SINGLE(INDIRECT("Descriptif!$F"&($B$1+$A16-1))),6)="PLUVIO" ) ), IF( LEFT(_xlfn.SINGLE(INDIRECT("Descriptif!$F"&($B$1+$A16-1))),11)="PLUVIO_STEU", "A3", IF( LEFT(_xlfn.SINGLE(INDIRECT("Descriptif!$F"&($B$1+$A16-1))),10)="PLUVIO_SCL", "A1", _xlfn.SINGLE(INDIRECT("Descriptif!$"&D$15&($B$1 +$A16 -1)) )) ), "" ) | E16: =IF( AND( $B16, OR( _xlfn.SINGLE(INDIRECT("Descriptif!$M"&($B$1+$A16-1)))="Préleveur", LEFT(_xlfn.SINGLE(INDIRECT("Descriptif!$M"&($B$1+$A16-1))),5)="Sonde", LEFT(_xlfn.SINGLE(INDIRECT("Descriptif!$M"&($B$1+$A16-1))),10)="Débitmètre", LEFT(_xlfn.SINGLE(INDIRECT("Descriptif!$F"&($B$1+$A16-1))),6)="PLUVIO" ) ), IF(LEFT(_xlfn.SINGLE(INDIRECT("Descriptif!$F"&($B$1+$A16-1))),6)="PLUVIO","Pluviomètre",_xlfn.SINGLE(INDIRECT("Descriptif!$"&E$15&($B$1 +$A16 -1)))), "" ) | F16: =IF( AND( $B16, OR( _xlfn.SINGLE(INDIRECT("Descriptif!$M"&($B$1+$A16-1)))="Préleveur", LEFT(_xlfn.SINGLE(INDIRECT("Descriptif!$M"&($B$1+$A16-1))),5)="Sonde", LEFT(_xlfn.SINGLE(INDIRECT("Descriptif!$M"&($B$1+$A16-1))),10)="Débitmètre", LEFT(_xlfn.SINGLE(INDIRECT("Descriptif!$F"&($B$1+$A16-1))),6)="PLUVIO" ) ), IF(LEFT(_xlfn.SINGLE(INDIRECT("Descriptif!$F"&($B$1+$A16-1))),6)="PLUVIO","Pluviomètre",_xlfn.SINGLE(INDIRECT("Descriptif!$"&F$15&($B$1 +$A16 -1)))), "" ) | G16: =IF( AND( $B16, OR( _xlfn.SINGLE(INDIRECT("Descriptif!$M"&($B$1+$A16-1)))="Préleveur", LEFT(_xlfn.SINGLE(INDIRECT("Descriptif!$M"&($B$1+$A16-1))),5)="Sonde", LEFT(_xlfn.SINGLE(INDIRECT("Descriptif!$M"&($B$1+$A16-1))),10)="Débitmètre", LEFT(_xlfn.SINGLE(INDIRECT("Descriptif!$F"&($B$1+$A16-1))),6)="PLUVIO" ) ), IF(LEFT(_xlfn.SINGLE(INDIRECT("Descriptif!$F"&($B$1+$A16-1))),6)="PLUVIO","Pluviomètre",_xlfn.SINGLE(INDIRECT("Descriptif!$"&G$15&($B$1 +$A16 -1)))), "" ) | H16: {=IFERROR(INDEX($C$16:$C$116,SMALL(IF($C$16:$C$116<>"",ROW($C$16:$C$116)-ROW($C$16)+1),ROW(A1))),"")} | I16: {=IFERROR(INDEX($D$16:$D$116,SMALL(IF($D$16:$D$116<>"",ROW($D$16:$D$116)-ROW($D$16)+1),ROW(A1))),"")} | J16: {=IFERROR(INDEX($E$16:$E$116,SMALL(IF($E$16:$E$116<>"",ROW($E$16:$E$116)-ROW($E$16)+1),ROW(A1))),"")} | K16: {=IFERROR(INDEX($F$16:$F$116,SMALL(IF($F$16:$F$116<>"",ROW($F$16:$F$116)-ROW($F$16)+1),ROW(A1))),"")} | L16: =H16 | M16: {=IFERROR(INDEX($G$16:$G$116,SMALL(IF($G$16:$G$116<>"",ROW($G$16:$G$116)-ROW($G$16)+1),ROW(A1))),"")} | N16: =IF($J16<>"",VLOOKUP($J16,$A$5:$F$9,2,FALSE),"") | O16: =IF($J16<>"",VLOOKUP($J16,$A$5:$F$9,3,FALSE),"") | P16: =IF($J16<>"",IF(_xlfn.SINGLE(INDIRECT($H16&"!"&$O16))<>"",_xlfn.SINGLE(INDIRECT($H16&"!"&$O16)),""),"") | Q16: =IF($J16<>"",VLOOKUP($J16,$A$5:$F$9,4,FALSE),"") | R16: =IF($J16<>"",IF(_xlfn.SINGLE(INDIRECT($H16&"!"&$Q16))<>"",_xlfn.SINGLE(INDIRECT($H16&"!"&$Q16)),""),"") | S16: =IF($J16<>"",VLOOKUP($J16,$A$5:$F$9,5,FALSE),"") | T16: =IF($J16<>"",IF(_xlfn.SINGLE(INDIRECT($H16&"!"&$S16))<>"",_xlfn.SINGLE(INDIRECT($H16&"!"&$S16)),""),"") | U16: =IF($J16<>"",VLOOKUP($J16,$A$5:$F$9,6,FALSE),"") | V16: =IF($J16<>"",IF(_xlfn.SINGLE(INDIRECT($H16&"!"&$U16))<>"",_xlfn.SINGLE(INDIRECT($H16&"!"&$U16)),""),"") | W16: =LEFT($Q16,1) | X16: =RIGHT($N16,2) | Y16: =IF($H16<>"",IF(_xlfn.SINGLE(INDIRECT($H16&"!"&$W16&($X16+Y$15+1)))<>"",_xlfn.SINGLE(INDIRECT($H16&"!"&$W16&($X16+Y$15+1))),""),"") | Z16: =IF($H16<>"",IF(_xlfn.SINGLE(INDIRECT($H16&"!"&$W16&($X16+Z$15+1)))<>"",_xlfn.SINGLE(INDIRECT($H16&"!"&$W16&($X16+Z$15+1))),""),"") | AA16: =IF($H16<>"",IF(_xlfn.SINGLE(INDIRECT($H16&"!"&$W16&($X16+AA$15+1)))<>"",_xlfn.SINGLE(INDIRECT($H16&"!"&$W16&($X16+AA$15+1))),""),"") | AB16: =IF($H16<>"",IF(_xlfn.SINGLE(INDIRECT($H16&"!"&$W16&($X16+AB$15+1)))<>"",_xlfn.SINGLE(INDIRECT($H16&"!"&$W16&($X16+AB$15+1))),""),"") | AC16: =IF(LEFT($J16,5)="Sonde","",IF($H16<>"",IF(_xlfn.SINGLE(INDIRECT($H16&"!"&$W16&($X16+AC$15+1)))<>"",_xlfn.SINGLE(INDIRECT($H16&"!"&$W16&($X16+AC$15+1))),""),"")) | AD16: =IF(OR($J16="Pluviomètre",LEFT($J16,5)="Sonde"),"",IF($H16<>"",IF(_xlfn.SINGLE(INDIRECT($H16&"!"&$W16&($X16+AD$15+1)))<>"",_xlfn.SINGLE(INDIRECT($H16&"!"&$W16&($X16+AD$15+1))),""),"")) | AE16: =IF(OR($J16="Pluviomètre",LEFT($J16,5)="Sonde"),"",IF($H16<>"",IF(_xlfn.SINGLE(INDIRECT($H16&"!"&$W16&($X16+AE$15+1)))<>"",_xlfn.SINGLE(INDIRECT($H16&"!"&$W16&($X16+AE$15+1))),""),"")) | AF16: =IF(OR($J16="Pluviomètre",LEFT($J16,5)="Sonde"),"",IF($H16<>"",IF(_xlfn.SINGLE(INDIRECT($H16&"!"&$W16&($X16+AF$15+1)))<>"",_xlfn.SINGLE(INDIRECT($H16&"!"&$W16&($X16+AF$15+1))),""),"")) | AG16: =IF(OR($J16="Pluviomètre",LEFT($J16,5)="Sonde"),"",IF($H16<>"",IF(_xlfn.SINGLE(INDIRECT($H16&"!"&$W16&($X16+AG$15+1)))<>"",_xlfn.SINGLE(INDIRECT($H16&"!"&$W16&($X16+AG$15+1))),""),"")) | AH16: =IF(OR($J16="Pluviomètre",LEFT($J16,5)="Sonde"),"",IF($H16<>"",IF(_xlfn.SINGLE(INDIRECT($H16&"!"&$W16&($X16+AH$15+1)))<>"",_xlfn.SINGLE(INDIRECT($H16&"!"&$W16&($X16+AH$15+1))),""),"")) | AI16: =LEFT($O16,1) | AJ16: =RIGHT($N16,2) | AK16: =IF($H16<>"",IF(_xlfn.SINGLE(INDIRECT($H16&"!"&$AI16&($AJ16+AK$15+1)))<>"",_xlfn.SINGLE(INDIRECT($H16&"!"&$AI16&($AJ16+AK$15+1))),""),"") | AL16: =IF($H16<>"",IF(_xlfn.SINGLE(INDIRECT($H16&"!"&$AI16&($AJ16+AL$15+1)))<>"",_xlfn.SINGLE(INDIRECT($H16&"!"&$AI16&($AJ16+AL$15+1))),""),"") | AM16: =IF($H16<>"",IF(_xlfn.SINGLE(INDIRECT($H16&"!"&$AI16&($AJ16+AM$15+1)))<>"",_xlfn.SINGLE(INDIRECT($H16&"!"&$AI16&($AJ16+AM$15+1))),""),"") | AN16: =IF($H16<>"",IF(_xlfn.SINGLE(INDIRECT($H16&"!"&$AI16&($AJ16+AN$15+1)))<>"",_xlfn.SINGLE(INDIRECT($H16&"!"&$AI16&($AJ16+AN$15+1))),""),"") | AO16: =IF(LEFT($J16,5)="Sonde","",IF($H16<>"",IF(_xlfn.SINGLE(INDIRECT($H16&"!"&$AI16&($AJ16+AO$15+1)))<>"",_xlfn.SINGLE(INDIRECT($H16&"!"&$AI16&($AJ16+AO$15+1))),""),"")) | AP16: =IF(OR($J16="Pluviomètre",LEFT($J16,5)="Sonde"),"",IF($H16<>"",IF(_xlfn.SINGLE(INDIRECT($H16&"!"&$AI16&($AJ16+AP$15+1)))<>"",_xlfn.SINGLE(INDIRECT($H16&"!"&$AI16&($AJ16+AP$15+1))),""),"")) | AQ16: =IF(OR($J16="Pluviomètre",LEFT($J16,5)="Sonde"),"",IF($H16<>"",IF(_xlfn.SINGLE(INDIRECT($H16&"!"&$AI16&($AJ16+AQ$15+1)))<>"",_xlfn.SINGLE(INDIRECT($H16&"!"&$AI16&($AJ16+AQ$15+1))),""),"")) | AR16: =IF(OR($J16="Pluviomètre",LEFT($J16,5)="Sonde"),"",IF($H16<>"",IF(_xlfn.SINGLE(INDIRECT($H16&"!"&$AI16&($AJ16+AR$15+1)))<>"",_xlfn.SINGLE(INDIRECT($H16&"!"&$AI16&($AJ16+AR$15+1))),""),"")) | AS16: =IF(OR($J16="Pluviomètre",LEFT($J16,5)="Sonde"),"",IF($H16<>"",IF(_xlfn.SINGLE(INDIRECT($H16&"!"&$AI16&($AJ16+AS$15+1)))<>"",_xlfn.SINGLE(INDIRECT($H16&"!"&$AI16&($AJ16+AS$15+1))),""),"")) | AT16: =IF(OR($J16="Pluviomètre",LEFT($J16,5)="Sonde"),"",IF($H16<>"",IF(_xlfn.SINGLE(INDIRECT($H16&"!"&$AI16&($AJ16+AT$15+1)))<>"",_xlfn.SINGLE(INDIRECT($H16&"!"&$AI16&($AJ16+AT$15+1))),""),""))
A17: 2 | B17: =IF(OR(AND(($B$1+A17-1)>=$B$1,($B$1+A17-1)<$C$1),AND(($B$1+A17-1)>=$B$2,($B$1+A17-1)<$C$2)),TRUE,FALSE) -> FALSE | C17: =IF( AND( $B17, OR( _xlfn.SINGLE(INDIRECT("Descriptif!$M"&($B$1+$A17-1)))="Préleveur", LEFT(_xlfn.SINGLE(INDIRECT("Descriptif!$M"&($B$1+$A17-1))),5)="Sonde", LEFT(_xlfn.SINGLE(INDIRECT("Descriptif!$M"&($B$1+$A17-1))),10)="Débitmètre", LEFT(_xlfn.SINGLE(INDIRECT("Descriptif!$F"&($B$1+$A17-1))),6)="PLUVIO" ) ), _xlfn.SINGLE(INDIRECT("Descriptif!$"&C$15&($B$1 +$A17 -1))), "" ) | D17: =IF( AND( $B17, OR( _xlfn.SINGLE(INDIRECT("Descriptif!$M"&($B$1+$A17-1)))="Préleveur", LEFT(_xlfn.SINGLE(INDIRECT("Descriptif!$M"&($B$1+$A17-1))),5)="Sonde", LEFT(_xlfn.SINGLE(INDIRECT("Descriptif!$M"&($B$1+$A17-1))),10)="Débitmètre", LEFT(_xlfn.SINGLE(INDIRECT("Descriptif!$F"&($B$1+$A17-1))),6)="PLUVIO" ) ), IF( LEFT(_xlfn.SINGLE(INDIRECT("Descriptif!$F"&($B$1+$A17-1))),11)="PLUVIO_STEU", "A3", IF( LEFT(_xlfn.SINGLE(INDIRECT("Descriptif!$F"&($B$1+$A17-1))),10)="PLUVIO_SCL", "A1", _xlfn.SINGLE(INDIRECT("Descriptif!$"&D$15&($B$1 +$A17 -1)) )) ), "" ) | E17: =IF( AND( $B17, OR( _xlfn.SINGLE(INDIRECT("Descriptif!$M"&($B$1+$A17-1)))="Préleveur", LEFT(_xlfn.SINGLE(INDIRECT("Descriptif!$M"&($B$1+$A17-1))),5)="Sonde", LEFT(_xlfn.SINGLE(INDIRECT("Descriptif!$M"&($B$1+$A17-1))),10)="Débitmètre", LEFT(_xlfn.SINGLE(INDIRECT("Descriptif!$F"&($B$1+$A17-1))),6)="PLUVIO" ) ), IF(LEFT(_xlfn.SINGLE(INDIRECT("Descriptif!$F"&($B$1+$A17-1))),6)="PLUVIO","Pluviomètre",_xlfn.SINGLE(INDIRECT("Descriptif!$"&E$15&($B$1 +$A17 -1)))), "" ) | F17: =IF( AND( $B17, OR( _xlfn.SINGLE(INDIRECT("Descriptif!$M"&($B$1+$A17-1)))="Préleveur", LEFT(_xlfn.SINGLE(INDIRECT("Descriptif!$M"&($B$1+$A17-1))),5)="Sonde", LEFT(_xlfn.SINGLE(INDIRECT("Descriptif!$M"&($B$1+$A17-1))),10)="Débitmètre", LEFT(_xlfn.SINGLE(INDIRECT("Descriptif!$F"&($B$1+$A17-1))),6)="PLUVIO" ) ), IF(LEFT(_xlfn.SINGLE(INDIRECT("Descriptif!$F"&($B$1+$A17-1))),6)="PLUVIO","Pluviomètre",_xlfn.SINGLE(INDIRECT("Descriptif!$"&F$15&($B$1 +$A17 -1)))), "" ) | G17: =IF( AND( $B17, OR( _xlfn.SINGLE(INDIRECT("Descriptif!$M"&($B$1+$A17-1)))="Préleveur", LEFT(_xlfn.SINGLE(INDIRECT("Descriptif!$M"&($B$1+$A17-1))),5)="Sonde", LEFT(_xlfn.SINGLE(INDIRECT("Descriptif!$M"&($B$1+$A17-1))),10)="Débitmètre", LEFT(_xlfn.SINGLE(INDIRECT("Descriptif!$F"&($B$1+$A17-1))),6)="PLUVIO" ) ), IF(LEFT(_xlfn.SINGLE(INDIRECT("Descriptif!$F"&($B$1+$A17-1))),6)="PLUVIO","Pluviomètre",_xlfn.SINGLE(INDIRECT("Descriptif!$"&G$15&($B$1 +$A17 -1)))), "" ) | H17: {=IFERROR(INDEX($C$16:$C$116,SMALL(IF($C$16:$C$116<>"",ROW($C$16:$C$116)-ROW($C$16)+1),ROW(A2))),"")} | I17: {=IFERROR(INDEX($D$16:$D$116,SMALL(IF($D$16:$D$116<>"",ROW($D$16:$D$116)-ROW($D$16)+1),ROW(A2))),"")} | J17: {=IFERROR(INDEX($E$16:$E$116,SMALL(IF($E$16:$E$116<>"",ROW($E$16:$E$116)-ROW($E$16)+1),ROW(A2))),"")} | K17: {=IFERROR(INDEX($F$16:$F$116,SMALL(IF($F$16:$F$116<>"",ROW($F$16:$F$116)-ROW($F$16)+1),ROW(A2))),"")} | L17: =H17 | M17: {=IFERROR(INDEX($G$16:$G$116,SMALL(IF($G$16:$G$116<>"",ROW($G$16:$G$116)-ROW($G$16)+1),ROW(A2))),"")} | N17: =IF($J17<>"",VLOOKUP($J17,$A$5:$F$9,2,FALSE),"") | O17: =IF($J17<>"",VLOOKUP($J17,$A$5:$F$9,3,FALSE),"") | P17: =IF($J17<>"",IF(_xlfn.SINGLE(INDIRECT($H17&"!"&$O17))<>"",_xlfn.SINGLE(INDIRECT($H17&"!"&$O17)),""),"") | Q17: =IF($J17<>"",VLOOKUP($J17,$A$5:$F$9,4,FALSE),"") | R17: =IF($J17<>"",IF(_xlfn.SINGLE(INDIRECT($H17&"!"&$Q17))<>"",_xlfn.SINGLE(INDIRECT($H17&"!"&$Q17)),""),"") | S17: =IF($J17<>"",VLOOKUP($J17,$A$5:$F$9,5,FALSE),"") | T17: =IF($J17<>"",IF(_xlfn.SINGLE(INDIRECT($H17&"!"&$S17))<>"",_xlfn.SINGLE(INDIRECT($H17&"!"&$S17)),""),"") | U17: =IF($J17<>"",VLOOKUP($J17,$A$5:$F$9,6,FALSE),"") | V17: =IF($J17<>"",IF(_xlfn.SINGLE(INDIRECT($H17&"!"&$U17))<>"",_xlfn.SINGLE(INDIRECT($H17&"!"&$U17)),""),"") | W17: =LEFT($Q17,1) | X17: =RIGHT($N17,2) | Y17: =IF($H17<>"",IF(_xlfn.SINGLE(INDIRECT($H17&"!"&$W17&($X17+Y$15+1)))<>"",_xlfn.SINGLE(INDIRECT($H17&"!"&$W17&($X17+Y$15+1))),""),"") | Z17: =IF($H17<>"",IF(_xlfn.SINGLE(INDIRECT($H17&"!"&$W17&($X17+Z$15+1)))<>"",_xlfn.SINGLE(INDIRECT($H17&"!"&$W17&($X17+Z$15+1))),""),"") | AA17: =IF($H17<>"",IF(_xlfn.SINGLE(INDIRECT($H17&"!"&$W17&($X17+AA$15+1)))<>"",_xlfn.SINGLE(INDIRECT($H17&"!"&$W17&($X17+AA$15+1))),""),"") | AB17: =IF($H17<>"",IF(_xlfn.SINGLE(INDIRECT($H17&"!"&$W17&($X17+AB$15+1)))<>"",_xlfn.SINGLE(INDIRECT($H17&"!"&$W17&($X17+AB$15+1))),""),"") | AC17: =IF(LEFT($J17,5)="Sonde","",IF($H17<>"",IF(_xlfn.SINGLE(INDIRECT($H17&"!"&$W17&($X17+AC$15+1)))<>"",_xlfn.SINGLE(INDIRECT($H17&"!"&$W17&($X17+AC$15+1))),""),"")) | AD17: =IF(OR($J17="Pluviomètre",LEFT($J17,5)="Sonde"),"",IF($H17<>"",IF(_xlfn.SINGLE(INDIRECT($H17&"!"&$W17&($X17+AD$15+1)))<>"",_xlfn.SINGLE(INDIRECT($H17&"!"&$W17&($X17+AD$15+1))),""),"")) | AE17: =IF(OR($J17="Pluviomètre",LEFT($J17,5)="Sonde"),"",IF($H17<>"",IF(_xlfn.SINGLE(INDIRECT($H17&"!"&$W17&($X17+AE$15+1)))<>"",_xlfn.SINGLE(INDIRECT($H17&"!"&$W17&($X17+AE$15+1))),""),"")) | AF17: =IF(OR($J17="Pluviomètre",LEFT($J17,5)="Sonde"),"",IF($H17<>"",IF(_xlfn.SINGLE(INDIRECT($H17&"!"&$W17&($X17+AF$15+1)))<>"",_xlfn.SINGLE(INDIRECT($H17&"!"&$W17&($X17+AF$15+1))),""),"")) | AG17: =IF(OR($J17="Pluviomètre",LEFT($J17,5)="Sonde"),"",IF($H17<>"",IF(_xlfn.SINGLE(INDIRECT($H17&"!"&$W17&($X17+AG$15+1)))<>"",_xlfn.SINGLE(INDIRECT($H17&"!"&$W17&($X17+AG$15+1))),""),"")) | AH17: =IF(OR($J17="Pluviomètre",LEFT($J17,5)="Sonde"),"",IF($H17<>"",IF(_xlfn.SINGLE(INDIRECT($H17&"!"&$W17&($X17+AH$15+1)))<>"",_xlfn.SINGLE(INDIRECT($H17&"!"&$W17&($X17+AH$15+1))),""),"")) | AI17: =LEFT($O17,1) | AJ17: =RIGHT($N17,2) | AK17: =IF($H17<>"",IF(_xlfn.SINGLE(INDIRECT($H17&"!"&$AI17&($AJ17+AK$15+1)))<>"",_xlfn.SINGLE(INDIRECT($H17&"!"&$AI17&($AJ17+AK$15+1))),""),"") | AL17: =IF($H17<>"",IF(_xlfn.SINGLE(INDIRECT($H17&"!"&$AI17&($AJ17+AL$15+1)))<>"",_xlfn.SINGLE(INDIRECT($H17&"!"&$AI17&($AJ17+AL$15+1))),""),"") | AM17: =IF($H17<>"",IF(_xlfn.SINGLE(INDIRECT($H17&"!"&$AI17&($AJ17+AM$15+1)))<>"",_xlfn.SINGLE(INDIRECT($H17&"!"&$AI17&($AJ17+AM$15+1))),""),"") | AN17: =IF($H17<>"",IF(_xlfn.SINGLE(INDIRECT($H17&"!"&$AI17&($AJ17+AN$15+1)))<>"",_xlfn.SINGLE(INDIRECT($H17&"!"&$AI17&($AJ17+AN$15+1))),""),"") | AO17: =IF(LEFT($J17,5)="Sonde","",IF($H17<>"",IF(_xlfn.SINGLE(INDIRECT($H17&"!"&$AI17&($AJ17+AO$15+1)))<>"",_xlfn.SINGLE(INDIRECT($H17&"!"&$AI17&($AJ17+AO$15+1))),""),"")) | AP17: =IF(OR($J17="Pluviomètre",LEFT($J17,5)="Sonde"),"",IF($H17<>"",IF(_xlfn.SINGLE(INDIRECT($H17&"!"&$AI17&($AJ17+AP$15+1)))<>"",_xlfn.SINGLE(INDIRECT($H17&"!"&$AI17&($AJ17+AP$15+1))),""),"")) | AQ17: =IF(OR($J17="Pluviomètre",LEFT($J17,5)="Sonde"),"",IF($H17<>"",IF(_xlfn.SINGLE(INDIRECT($H17&"!"&$AI17&($AJ17+AQ$15+1)))<>"",_xlfn.SINGLE(INDIRECT($H17&"!"&$AI17&($AJ17+AQ$15+1))),""),"")) | AR17: =IF(OR($J17="Pluviomètre",LEFT($J17,5)="Sonde"),"",IF($H17<>"",IF(_xlfn.SINGLE(INDIRECT($H17&"!"&$AI17&($AJ17+AR$15+1)))<>"",_xlfn.SINGLE(INDIRECT($H17&"!"&$AI17&($AJ17+AR$15+1))),""),"")) | AS17: =IF(OR($J17="Pluviomètre",LEFT($J17,5)="Sonde"),"",IF($H17<>"",IF(_xlfn.SINGLE(INDIRECT($H17&"!"&$AI17&($AJ17+AS$15+1)))<>"",_xlfn.SINGLE(INDIRECT($H17&"!"&$AI17&($AJ17+AS$15+1))),""),"")) | AT17: =IF(OR($J17="Pluviomètre",LEFT($J17,5)="Sonde"),"",IF($H17<>"",IF(_xlfn.SINGLE(INDIRECT($H17&"!"&$AI17&($AJ17+AT$15+1)))<>"",_xlfn.SINGLE(INDIRECT($H17&"!"&$AI17&($AJ17+AT$15+1))),""),""))
A18: 3 | B18: =IF(OR(AND(($B$1+A18-1)>=$B$1,($B$1+A18-1)<$C$1),AND(($B$1+A18-1)>=$B$2,($B$1+A18-1)<$C$2)),TRUE,FALSE) -> FALSE | C18: =IF( AND( $B18, OR( _xlfn.SINGLE(INDIRECT("Descriptif!$M"&($B$1+$A18-1)))="Préleveur", LEFT(_xlfn.SINGLE(INDIRECT("Descriptif!$M"&($B$1+$A18-1))),5)="Sonde", LEFT(_xlfn.SINGLE(INDIRECT("Descriptif!$M"&($B$1+$A18-1))),10)="Débitmètre", LEFT(_xlfn.SINGLE(INDIRECT("Descriptif!$F"&($B$1+$A18-1))),6)="PLUVIO" ) ), _xlfn.SINGLE(INDIRECT("Descriptif!$"&C$15&($B$1 +$A18 -1))), "" ) | D18: =IF( AND( $B18, OR( _xlfn.SINGLE(INDIRECT("Descriptif!$M"&($B$1+$A18-1)))="Préleveur", LEFT(_xlfn.SINGLE(INDIRECT("Descriptif!$M"&($B$1+$A18-1))),5)="Sonde", LEFT(_xlfn.SINGLE(INDIRECT("Descriptif!$M"&($B$1+$A18-1))),10)="Débitmètre", LEFT(_xlfn.SINGLE(INDIRECT("Descriptif!$F"&($B$1+$A18-1))),6)="PLUVIO" ) ), IF( LEFT(_xlfn.SINGLE(INDIRECT("Descriptif!$F"&($B$1+$A18-1))),11)="PLUVIO_STEU", "A3", IF( LEFT(_xlfn.SINGLE(INDIRECT("Descriptif!$F"&($B$1+$A18-1))),10)="PLUVIO_SCL", "A1", _xlfn.SINGLE(INDIRECT("Descriptif!$"&D$15&($B$1 +$A18 -1)) )) ), "" ) | E18: =IF( AND( $B18, OR( _xlfn.SINGLE(INDIRECT("Descriptif!$M"&($B$1+$A18-1)))="Préleveur", LEFT(_xlfn.SINGLE(INDIRECT("Descriptif!$M"&($B$1+$A18-1))),5)="Sonde", LEFT(_xlfn.SINGLE(INDIRECT("Descriptif!$M"&($B$1+$A18-1))),10)="Débitmètre", LEFT(_xlfn.SINGLE(INDIRECT("Descriptif!$F"&($B$1+$A18-1))),6)="PLUVIO" ) ), IF(LEFT(_xlfn.SINGLE(INDIRECT("Descriptif!$F"&($B$1+$A18-1))),6)="PLUVIO","Pluviomètre",_xlfn.SINGLE(INDIRECT("Descriptif!$"&E$15&($B$1 +$A18 -1)))), "" ) | F18: =IF( AND( $B18, OR( _xlfn.SINGLE(INDIRECT("Descriptif!$M"&($B$1+$A18-1)))="Préleveur", LEFT(_xlfn.SINGLE(INDIRECT("Descriptif!$M"&($B$1+$A18-1))),5)="Sonde", LEFT(_xlfn.SINGLE(INDIRECT("Descriptif!$M"&($B$1+$A18-1))),10)="Débitmètre", LEFT(_xlfn.SINGLE(INDIRECT("Descriptif!$F"&($B$1+$A18-1))),6)="PLUVIO" ) ), IF(LEFT(_xlfn.SINGLE(INDIRECT("Descriptif!$F"&($B$1+$A18-1))),6)="PLUVIO","Pluviomètre",_xlfn.SINGLE(INDIRECT("Descriptif!$"&F$15&($B$1 +$A18 -1)))), "" ) | G18: =IF( AND( $B18, OR( _xlfn.SINGLE(INDIRECT("Descriptif!$M"&($B$1+$A18-1)))="Préleveur", LEFT(_xlfn.SINGLE(INDIRECT("Descriptif!$M"&($B$1+$A18-1))),5)="Sonde", LEFT(_xlfn.SINGLE(INDIRECT("Descriptif!$M"&($B$1+$A18-1))),10)="Débitmètre", LEFT(_xlfn.SINGLE(INDIRECT("Descriptif!$F"&($B$1+$A18-1))),6)="PLUVIO" ) ), IF(LEFT(_xlfn.SINGLE(INDIRECT("Descriptif!$F"&($B$1+$A18-1))),6)="PLUVIO","Pluviomètre",_xlfn.SINGLE(INDIRECT("Descriptif!$"&G$15&($B$1 +$A18 -1)))), "" ) | H18: {=IFERROR(INDEX($C$16:$C$116,SMALL(IF($C$16:$C$116<>"",ROW($C$16:$C$116)-ROW($C$16)+1),ROW(A3))),"")} | I18: {=IFERROR(INDEX($D$16:$D$116,SMALL(IF($D$16:$D$116<>"",ROW($D$16:$D$116)-ROW($D$16)+1),ROW(A3))),"")} | J18: {=IFERROR(INDEX($E$16:$E$116,SMALL(IF($E$16:$E$116<>"",ROW($E$16:$E$116)-ROW($E$16)+1),ROW(A3))),"")} | K18: {=IFERROR(INDEX($F$16:$F$116,SMALL(IF($F$16:$F$116<>"",ROW($F$16:$F$116)-ROW($F$16)+1),ROW(A3))),"")} | L18: =H18 | M18: {=IFERROR(INDEX($G$16:$G$116,SMALL(IF($G$16:$G$116<>"",ROW($G$16:$G$116)-ROW($G$16)+1),ROW(A3))),"")} | N18: =IF($J18<>"",VLOOKUP($J18,$A$5:$F$9,2,FALSE),"") | O18: =IF($J18<>"",VLOOKUP($J18,$A$5:$F$9,3,FALSE),"") | P18: =IF($J18<>"",IF(_xlfn.SINGLE(INDIRECT($H18&"!"&$O18))<>"",_xlfn.SINGLE(INDIRECT($H18&"!"&$O18)),""),"") | Q18: =IF($J18<>"",VLOOKUP($J18,$A$5:$F$9,4,FALSE),"") | R18: =IF($J18<>"",IF(_xlfn.SINGLE(INDIRECT($H18&"!"&$Q18))<>"",_xlfn.SINGLE(INDIRECT($H18&"!"&$Q18)),""),"") | S18: =IF($J18<>"",VLOOKUP($J18,$A$5:$F$9,5,FALSE),"") | T18: =IF($J18<>"",IF(_xlfn.SINGLE(INDIRECT($H18&"!"&$S18))<>"",_xlfn.SINGLE(INDIRECT($H18&"!"&$S18)),""),"") | U18: =IF($J18<>"",VLOOKUP($J18,$A$5:$F$9,6,FALSE),"") | V18: =IF($J18<>"",IF(_xlfn.SINGLE(INDIRECT($H18&"!"&$U18))<>"",_xlfn.SINGLE(INDIRECT($H18&"!"&$U18)),""),"") | W18: =LEFT($Q18,1) | X18: =RIGHT($N18,2) | Y18: =IF($H18<>"",IF(_xlfn.SINGLE(INDIRECT($H18&"!"&$W18&($X18+Y$15+1)))<>"",_xlfn.SINGLE(INDIRECT($H18&"!"&$W18&($X18+Y$15+1))),""),"") | Z18: =IF($H18<>"",IF(_xlfn.SINGLE(INDIRECT($H18&"!"&$W18&($X18+Z$15+1)))<>"",_xlfn.SINGLE(INDIRECT($H18&"!"&$W18&($X18+Z$15+1))),""),"") | AA18: =IF($H18<>"",IF(_xlfn.SINGLE(INDIRECT($H18&"!"&$W18&($X18+AA$15+1)))<>"",_xlfn.SINGLE(INDIRECT($H18&"!"&$W18&($X18+AA$15+1))),""),"") | AB18: =IF($H18<>"",IF(_xlfn.SINGLE(INDIRECT($H18&"!"&$W18&($X18+AB$15+1)))<>"",_xlfn.SINGLE(INDIRECT($H18&"!"&$W18&($X18+AB$15+1))),""),"") | AC18: =IF(LEFT($J18,5)="Sonde","",IF($H18<>"",IF(_xlfn.SINGLE(INDIRECT($H18&"!"&$W18&($X18+AC$15+1)))<>"",_xlfn.SINGLE(INDIRECT($H18&"!"&$W18&($X18+AC$15+1))),""),"")) | AD18: =IF(OR($J18="Pluviomètre",LEFT($J18,5)="Sonde"),"",IF($H18<>"",IF(_xlfn.SINGLE(INDIRECT($H18&"!"&$W18&($X18+AD$15+1)))<>"",_xlfn.SINGLE(INDIRECT($H18&"!"&$W18&($X18+AD$15+1))),""),"")) | AE18: =IF(OR($J18="Pluviomètre",LEFT($J18,5)="Sonde"),"",IF($H18<>"",IF(_xlfn.SINGLE(INDIRECT($H18&"!"&$W18&($X18+AE$15+1)))<>"",_xlfn.SINGLE(INDIRECT($H18&"!"&$W18&($X18+AE$15+1))),""),"")) | AF18: =IF(OR($J18="Pluviomètre",LEFT($J18,5)="Sonde"),"",IF($H18<>"",IF(_xlfn.SINGLE(INDIRECT($H18&"!"&$W18&($X18+AF$15+1)))<>"",_xlfn.SINGLE(INDIRECT($H18&"!"&$W18&($X18+AF$15+1))),""),"")) | AG18: =IF(OR($J18="Pluviomètre",LEFT($J18,5)="Sonde"),"",IF($H18<>"",IF(_xlfn.SINGLE(INDIRECT($H18&"!"&$W18&($X18+AG$15+1)))<>"",_xlfn.SINGLE(INDIRECT($H18&"!"&$W18&($X18+AG$15+1))),""),"")) | AH18: =IF(OR($J18="Pluviomètre",LEFT($J18,5)="Sonde"),"",IF($H18<>"",IF(_xlfn.SINGLE(INDIRECT($H18&"!"&$W18&($X18+AH$15+1)))<>"",_xlfn.SINGLE(INDIRECT($H18&"!"&$W18&($X18+AH$15+1))),""),"")) | AI18: =LEFT($O18,1) | AJ18: =RIGHT($N18,2) | AK18: =IF($H18<>"",IF(_xlfn.SINGLE(INDIRECT($H18&"!"&$AI18&($AJ18+AK$15+1)))<>"",_xlfn.SINGLE(INDIRECT($H18&"!"&$AI18&($AJ18+AK$15+1))),""),"") | AL18: =IF($H18<>"",IF(_xlfn.SINGLE(INDIRECT($H18&"!"&$AI18&($AJ18+AL$15+1)))<>"",_xlfn.SINGLE(INDIRECT($H18&"!"&$AI18&($AJ18+AL$15+1))),""),"") | AM18: =IF($H18<>"",IF(_xlfn.SINGLE(INDIRECT($H18&"!"&$AI18&($AJ18+AM$15+1)))<>"",_xlfn.SINGLE(INDIRECT($H18&"!"&$AI18&($AJ18+AM$15+1))),""),"") | AN18: =IF($H18<>"",IF(_xlfn.SINGLE(INDIRECT($H18&"!"&$AI18&($AJ18+AN$15+1)))<>"",_xlfn.SINGLE(INDIRECT($H18&"!"&$AI18&($AJ18+AN$15+1))),""),"") | AO18: =IF(LEFT($J18,5)="Sonde","",IF($H18<>"",IF(_xlfn.SINGLE(INDIRECT($H18&"!"&$AI18&($AJ18+AO$15+1)))<>"",_xlfn.SINGLE(INDIRECT($H18&"!"&$AI18&($AJ18+AO$15+1))),""),"")) | AP18: =IF(OR($J18="Pluviomètre",LEFT($J18,5)="Sonde"),"",IF($H18<>"",IF(_xlfn.SINGLE(INDIRECT($H18&"!"&$AI18&($AJ18+AP$15+1)))<>"",_xlfn.SINGLE(INDIRECT($H18&"!"&$AI18&($AJ18+AP$15+1))),""),"")) | AQ18: =IF(OR($J18="Pluviomètre",LEFT($J18,5)="Sonde"),"",IF($H18<>"",IF(_xlfn.SINGLE(INDIRECT($H18&"!"&$AI18&($AJ18+AQ$15+1)))<>"",_xlfn.SINGLE(INDIRECT($H18&"!"&$AI18&($AJ18+AQ$15+1))),""),"")) | AR18: =IF(OR($J18="Pluviomètre",LEFT($J18,5)="Sonde"),"",IF($H18<>"",IF(_xlfn.SINGLE(INDIRECT($H18&"!"&$AI18&($AJ18+AR$15+1)))<>"",_xlfn.SINGLE(INDIRECT($H18&"!"&$AI18&($AJ18+AR$15+1))),""),"")) | AS18: =IF(OR($J18="Pluviomètre",LEFT($J18,5)="Sonde"),"",IF($H18<>"",IF(_xlfn.SINGLE(INDIRECT($H18&"!"&$AI18&($AJ18+AS$15+1)))<>"",_xlfn.SINGLE(INDIRECT($H18&"!"&$AI18&($AJ18+AS$15+1))),""),"")) | AT18: =IF(OR($J18="Pluviomètre",LEFT($J18,5)="Sonde"),"",IF($H18<>"",IF(_xlfn.SINGLE(INDIRECT($H18&"!"&$AI18&($AJ18+AT$15+1)))<>"",_xlfn.SINGLE(INDIRECT($H18&"!"&$AI18&($AJ18+AT$15+1))),""),""))
A19: 4 | B19: =IF(OR(AND(($B$1+A19-1)>=$B$1,($B$1+A19-1)<$C$1),AND(($B$1+A19-1)>=$B$2,($B$1+A19-1)<$C$2)),TRUE,FALSE) -> FALSE | C19: =IF( AND( $B19, OR( _xlfn.SINGLE(INDIRECT("Descriptif!$M"&($B$1+$A19-1)))="Préleveur", LEFT(_xlfn.SINGLE(INDIRECT("Descriptif!$M"&($B$1+$A19-1))),5)="Sonde", LEFT(_xlfn.SINGLE(INDIRECT("Descriptif!$M"&($B$1+$A19-1))),10)="Débitmètre", LEFT(_xlfn.SINGLE(INDIRECT("Descriptif!$F"&($B$1+$A19-1))),6)="PLUVIO" ) ), _xlfn.SINGLE(INDIRECT("Descriptif!$"&C$15&($B$1 +$A19 -1))), "" ) | D19: =IF( AND( $B19, OR( _xlfn.SINGLE(INDIRECT("Descriptif!$M"&($B$1+$A19-1)))="Préleveur", LEFT(_xlfn.SINGLE(INDIRECT("Descriptif!$M"&($B$1+$A19-1))),5)="Sonde", LEFT(_xlfn.SINGLE(INDIRECT("Descriptif!$M"&($B$1+$A19-1))),10)="Débitmètre", LEFT(_xlfn.SINGLE(INDIRECT("Descriptif!$F"&($B$1+$A19-1))),6)="PLUVIO" ) ), IF( LEFT(_xlfn.SINGLE(INDIRECT("Descriptif!$F"&($B$1+$A19-1))),11)="PLUVIO_STEU", "A3", IF( LEFT(_xlfn.SINGLE(INDIRECT("Descriptif!$F"&($B$1+$A19-1))),10)="PLUVIO_SCL", "A1", _xlfn.SINGLE(INDIRECT("Descriptif!$"&D$15&($B$1 +$A19 -1)) )) ), "" ) | E19: =IF( AND( $B19, OR( _xlfn.SINGLE(INDIRECT("Descriptif!$M"&($B$1+$A19-1)))="Préleveur", LEFT(_xlfn.SINGLE(INDIRECT("Descriptif!$M"&($B$1+$A19-1))),5)="Sonde", LEFT(_xlfn.SINGLE(INDIRECT("Descriptif!$M"&($B$1+$A19-1))),10)="Débitmètre", LEFT(_xlfn.SINGLE(INDIRECT("Descriptif!$F"&($B$1+$A19-1))),6)="PLUVIO" ) ), IF(LEFT(_xlfn.SINGLE(INDIRECT("Descriptif!$F"&($B$1+$A19-1))),6)="PLUVIO","Pluviomètre",_xlfn.SINGLE(INDIRECT("Descriptif!$"&E$15&($B$1 +$A19 -1)))), "" ) | F19: =IF( AND( $B19, OR( _xlfn.SINGLE(INDIRECT("Descriptif!$M"&($B$1+$A19-1)))="Préleveur", LEFT(_xlfn.SINGLE(INDIRECT("Descriptif!$M"&($B$1+$A19-1))),5)="Sonde", LEFT(_xlfn.SINGLE(INDIRECT("Descriptif!$M"&($B$1+$A19-1))),10)="Débitmètre", LEFT(_xlfn.SINGLE(INDIRECT("Descriptif!$F"&($B$1+$A19-1))),6)="PLUVIO" ) ), IF(LEFT(_xlfn.SINGLE(INDIRECT("Descriptif!$F"&($B$1+$A19-1))),6)="PLUVIO","Pluviomètre",_xlfn.SINGLE(INDIRECT("Descriptif!$"&F$15&($B$1 +$A19 -1)))), "" ) | G19: =IF( AND( $B19, OR( _xlfn.SINGLE(INDIRECT("Descriptif!$M"&($B$1+$A19-1)))="Préleveur", LEFT(_xlfn.SINGLE(INDIRECT("Descriptif!$M"&($B$1+$A19-1))),5)="Sonde", LEFT(_xlfn.SINGLE(INDIRECT("Descriptif!$M"&($B$1+$A19-1))),10)="Débitmètre", LEFT(_xlfn.SINGLE(INDIRECT("Descriptif!$F"&($B$1+$A19-1))),6)="PLUVIO" ) ), IF(LEFT(_xlfn.SINGLE(INDIRECT("Descriptif!$F"&($B$1+$A19-1))),6)="PLUVIO","Pluviomètre",_xlfn.SINGLE(INDIRECT("Descriptif!$"&G$15&($B$1 +$A19 -1)))), "" ) | H19: {=IFERROR(INDEX($C$16:$C$116,SMALL(IF($C$16:$C$116<>"",ROW($C$16:$C$116)-ROW($C$16)+1),ROW(A4))),"")} | I19: {=IFERROR(INDEX($D$16:$D$116,SMALL(IF($D$16:$D$116<>"",ROW($D$16:$D$116)-ROW($D$16)+1),ROW(A4))),"")} | J19: {=IFERROR(INDEX($E$16:$E$116,SMALL(IF($E$16:$E$116<>"",ROW($E$16:$E$116)-ROW($E$16)+1),ROW(A4))),"")} | K19: {=IFERROR(INDEX($F$16:$F$116,SMALL(IF($F$16:$F$116<>"",ROW($F$16:$F$116)-ROW($F$16)+1),ROW(A4))),"")} | L19: =H19 | M19: {=IFERROR(INDEX($G$16:$G$116,SMALL(IF($G$16:$G$116<>"",ROW($G$16:$G$116)-ROW($G$16)+1),ROW(A4))),"")} | N19: =IF($J19<>"",VLOOKUP($J19,$A$5:$F$9,2,FALSE),"") | O19: =IF($J19<>"",VLOOKUP($J19,$A$5:$F$9,3,FALSE),"") | P19: =IF($J19<>"",IF(_xlfn.SINGLE(INDIRECT($H19&"!"&$O19))<>"",_xlfn.SINGLE(INDIRECT($H19&"!"&$O19)),""),"") | Q19: =IF($J19<>"",VLOOKUP($J19,$A$5:$F$9,4,FALSE),"") | R19: =IF($J19<>"",IF(_xlfn.SINGLE(INDIRECT($H19&"!"&$Q19))<>"",_xlfn.SINGLE(INDIRECT($H19&"!"&$Q19)),""),"") | S19: =IF($J19<>"",VLOOKUP($J19,$A$5:$F$9,5,FALSE),"") | T19: =IF($J19<>"",IF(_xlfn.SINGLE(INDIRECT($H19&"!"&$S19))<>"",_xlfn.SINGLE(INDIRECT($H19&"!"&$S19)),""),"") | U19: =IF($J19<>"",VLOOKUP($J19,$A$5:$F$9,6,FALSE),"") | V19: =IF($J19<>"",IF(_xlfn.SINGLE(INDIRECT($H19&"!"&$U19))<>"",_xlfn.SINGLE(INDIRECT($H19&"!"&$U19)),""),"") | W19: =LEFT($Q19,1) | X19: =RIGHT($N19,2) | Y19: =IF($H19<>"",IF(_xlfn.SINGLE(INDIRECT($H19&"!"&$W19&($X19+Y$15+1)))<>"",_xlfn.SINGLE(INDIRECT($H19&"!"&$W19&($X19+Y$15+1))),""),"") | Z19: =IF($H19<>"",IF(_xlfn.SINGLE(INDIRECT($H19&"!"&$W19&($X19+Z$15+1)))<>"",_xlfn.SINGLE(INDIRECT($H19&"!"&$W19&($X19+Z$15+1))),""),"") | AA19: =IF($H19<>"",IF(_xlfn.SINGLE(INDIRECT($H19&"!"&$W19&($X19+AA$15+1)))<>"",_xlfn.SINGLE(INDIRECT($H19&"!"&$W19&($X19+AA$15+1))),""),"") | AB19: =IF($H19<>"",IF(_xlfn.SINGLE(INDIRECT($H19&"!"&$W19&($X19+AB$15+1)))<>"",_xlfn.SINGLE(INDIRECT($H19&"!"&$W19&($X19+AB$15+1))),""),"") | AC19: =IF(LEFT($J19,5)="Sonde","",IF($H19<>"",IF(_xlfn.SINGLE(INDIRECT($H19&"!"&$W19&($X19+AC$15+1)))<>"",_xlfn.SINGLE(INDIRECT($H19&"!"&$W19&($X19+AC$15+1))),""),"")) | AD19: =IF(OR($J19="Pluviomètre",LEFT($J19,5)="Sonde"),"",IF($H19<>"",IF(_xlfn.SINGLE(INDIRECT($H19&"!"&$W19&($X19+AD$15+1)))<>"",_xlfn.SINGLE(INDIRECT($H19&"!"&$W19&($X19+AD$15+1))),""),"")) | AE19: =IF(OR($J19="Pluviomètre",LEFT($J19,5)="Sonde"),"",IF($H19<>"",IF(_xlfn.SINGLE(INDIRECT($H19&"!"&$W19&($X19+AE$15+1)))<>"",_xlfn.SINGLE(INDIRECT($H19&"!"&$W19&($X19+AE$15+1))),""),"")) | AF19: =IF(OR($J19="Pluviomètre",LEFT($J19,5)="Sonde"),"",IF($H19<>"",IF(_xlfn.SINGLE(INDIRECT($H19&"!"&$W19&($X19+AF$15+1)))<>"",_xlfn.SINGLE(INDIRECT($H19&"!"&$W19&($X19+AF$15+1))),""),"")) | AG19: =IF(OR($J19="Pluviomètre",LEFT($J19,5)="Sonde"),"",IF($H19<>"",IF(_xlfn.SINGLE(INDIRECT($H19&"!"&$W19&($X19+AG$15+1)))<>"",_xlfn.SINGLE(INDIRECT($H19&"!"&$W19&($X19+AG$15+1))),""),"")) | AH19: =IF(OR($J19="Pluviomètre",LEFT($J19,5)="Sonde"),"",IF($H19<>"",IF(_xlfn.SINGLE(INDIRECT($H19&"!"&$W19&($X19+AH$15+1)))<>"",_xlfn.SINGLE(INDIRECT($H19&"!"&$W19&($X19+AH$15+1))),""),"")) | AI19: =LEFT($O19,1) | AJ19: =RIGHT($N19,2) | AK19: =IF($H19<>"",IF(_xlfn.SINGLE(INDIRECT($H19&"!"&$AI19&($AJ19+AK$15+1)))<>"",_xlfn.SINGLE(INDIRECT($H19&"!"&$AI19&($AJ19+AK$15+1))),""),"") | AL19: =IF($H19<>"",IF(_xlfn.SINGLE(INDIRECT($H19&"!"&$AI19&($AJ19+AL$15+1)))<>"",_xlfn.SINGLE(INDIRECT($H19&"!"&$AI19&($AJ19+AL$15+1))),""),"") | AM19: =IF($H19<>"",IF(_xlfn.SINGLE(INDIRECT($H19&"!"&$AI19&($AJ19+AM$15+1)))<>"",_xlfn.SINGLE(INDIRECT($H19&"!"&$AI19&($AJ19+AM$15+1))),""),"") | AN19: =IF($H19<>"",IF(_xlfn.SINGLE(INDIRECT($H19&"!"&$AI19&($AJ19+AN$15+1)))<>"",_xlfn.SINGLE(INDIRECT($H19&"!"&$AI19&($AJ19+AN$15+1))),""),"") | AO19: =IF(LEFT($J19,5)="Sonde","",IF($H19<>"",IF(_xlfn.SINGLE(INDIRECT($H19&"!"&$AI19&($AJ19+AO$15+1)))<>"",_xlfn.SINGLE(INDIRECT($H19&"!"&$AI19&($AJ19+AO$15+1))),""),"")) | AP19: =IF(OR($J19="Pluviomètre",LEFT($J19,5)="Sonde"),"",IF($H19<>"",IF(_xlfn.SINGLE(INDIRECT($H19&"!"&$AI19&($AJ19+AP$15+1)))<>"",_xlfn.SINGLE(INDIRECT($H19&"!"&$AI19&($AJ19+AP$15+1))),""),"")) | AQ19: =IF(OR($J19="Pluviomètre",LEFT($J19,5)="Sonde"),"",IF($H19<>"",IF(_xlfn.SINGLE(INDIRECT($H19&"!"&$AI19&($AJ19+AQ$15+1)))<>"",_xlfn.SINGLE(INDIRECT($H19&"!"&$AI19&($AJ19+AQ$15+1))),""),"")) | AR19: =IF(OR($J19="Pluviomètre",LEFT($J19,5)="Sonde"),"",IF($H19<>"",IF(_xlfn.SINGLE(INDIRECT($H19&"!"&$AI19&($AJ19+AR$15+1)))<>"",_xlfn.SINGLE(INDIRECT($H19&"!"&$AI19&($AJ19+AR$15+1))),""),"")) | AS19: =IF(OR($J19="Pluviomètre",LEFT($J19,5)="Sonde"),"",IF($H19<>"",IF(_xlfn.SINGLE(INDIRECT($H19&"!"&$AI19&($AJ19+AS$15+1)))<>"",_xlfn.SINGLE(INDIRECT($H19&"!"&$AI19&($AJ19+AS$15+1))),""),"")) | AT19: =IF(OR($J19="Pluviomètre",LEFT($J19,5)="Sonde"),"",IF($H19<>"",IF(_xlfn.SINGLE(INDIRECT($H19&"!"&$AI19&($AJ19+AT$15+1)))<>"",_xlfn.SINGLE(INDIRECT($H19&"!"&$AI19&($AJ19+AT$15+1))),""),""))
A20: 5 | B20: =IF(OR(AND(($B$1+A20-1)>=$B$1,($B$1+A20-1)<$C$1),AND(($B$1+A20-1)>=$B$2,($B$1+A20-1)<$C$2)),TRUE,FALSE) -> FALSE | C20: =IF( AND( $B20, OR( _xlfn.SINGLE(INDIRECT("Descriptif!$M"&($B$1+$A20-1)))="Préleveur", LEFT(_xlfn.SINGLE(INDIRECT("Descriptif!$M"&($B$1+$A20-1))),5)="Sonde", LEFT(_xlfn.SINGLE(INDIRECT("Descriptif!$M"&($B$1+$A20-1))),10)="Débitmètre", LEFT(_xlfn.SINGLE(INDIRECT("Descriptif!$F"&($B$1+$A20-1))),6)="PLUVIO" ) ), _xlfn.SINGLE(INDIRECT("Descriptif!$"&C$15&($B$1 +$A20 -1))), "" ) | D20: =IF( AND( $B20, OR( _xlfn.SINGLE(INDIRECT("Descriptif!$M"&($B$1+$A20-1)))="Préleveur", LEFT(_xlfn.SINGLE(INDIRECT("Descriptif!$M"&($B$1+$A20-1))),5)="Sonde", LEFT(_xlfn.SINGLE(INDIRECT("Descriptif!$M"&($B$1+$A20-1))),10)="Débitmètre", LEFT(_xlfn.SINGLE(INDIRECT("Descriptif!$F"&($B$1+$A20-1))),6)="PLUVIO" ) ), IF( LEFT(_xlfn.SINGLE(INDIRECT("Descriptif!$F"&($B$1+$A20-1))),11)="PLUVIO_STEU", "A3", IF( LEFT(_xlfn.SINGLE(INDIRECT("Descriptif!$F"&($B$1+$A20-1))),10)="PLUVIO_SCL", "A1", _xlfn.SINGLE(INDIRECT("Descriptif!$"&D$15&($B$1 +$A20 -1)) )) ), "" ) | E20: =IF( AND( $B20, OR( _xlfn.SINGLE(INDIRECT("Descriptif!$M"&($B$1+$A20-1)))="Préleveur", LEFT(_xlfn.SINGLE(INDIRECT("Descriptif!$M"&($B$1+$A20-1))),5)="Sonde", LEFT(_xlfn.SINGLE(INDIRECT("Descriptif!$M"&($B$1+$A20-1))),10)="Débitmètre", LEFT(_xlfn.SINGLE(INDIRECT("Descriptif!$F"&($B$1+$A20-1))),6)="PLUVIO" ) ), IF(LEFT(_xlfn.SINGLE(INDIRECT("Descriptif!$F"&($B$1+$A20-1))),6)="PLUVIO","Pluviomètre",_xlfn.SINGLE(INDIRECT("Descriptif!$"&E$15&($B$1 +$A20 -1)))), "" ) | F20: =IF( AND( $B20, OR( _xlfn.SINGLE(INDIRECT("Descriptif!$M"&($B$1+$A20-1)))="Préleveur", LEFT(_xlfn.SINGLE(INDIRECT("Descriptif!$M"&($B$1+$A20-1))),5)="Sonde", LEFT(_xlfn.SINGLE(INDIRECT("Descriptif!$M"&($B$1+$A20-1))),10)="Débitmètre", LEFT(_xlfn.SINGLE(INDIRECT("Descriptif!$F"&($B$1+$A20-1))),6)="PLUVIO" ) ), IF(LEFT(_xlfn.SINGLE(INDIRECT("Descriptif!$F"&($B$1+$A20-1))),6)="PLUVIO","Pluviomètre",_xlfn.SINGLE(INDIRECT("Descriptif!$"&F$15&($B$1 +$A20 -1)))), "" ) | G20: =IF( AND( $B20, OR( _xlfn.SINGLE(INDIRECT("Descriptif!$M"&($B$1+$A20-1)))="Préleveur", LEFT(_xlfn.SINGLE(INDIRECT("Descriptif!$M"&($B$1+$A20-1))),5)="Sonde", LEFT(_xlfn.SINGLE(INDIRECT("Descriptif!$M"&($B$1+$A20-1))),10)="Débitmètre", LEFT(_xlfn.SINGLE(INDIRECT("Descriptif!$F"&($B$1+$A20-1))),6)="PLUVIO" ) ), IF(LEFT(_xlfn.SINGLE(INDIRECT("Descriptif!$F"&($B$1+$A20-1))),6)="PLUVIO","Pluviomètre",_xlfn.SINGLE(INDIRECT("Descriptif!$"&G$15&($B$1 +$A20 -1)))), "" ) | H20: {=IFERROR(INDEX($C$16:$C$116,SMALL(IF($C$16:$C$116<>"",ROW($C$16:$C$116)-ROW($C$16)+1),ROW(A5))),"")} | I20: {=IFERROR(INDEX($D$16:$D$116,SMALL(IF($D$16:$D$116<>"",ROW($D$16:$D$116)-ROW($D$16)+1),ROW(A5))),"")} | J20: {=IFERROR(INDEX($E$16:$E$116,SMALL(IF($E$16:$E$116<>"",ROW($E$16:$E$116)-ROW($E$16)+1),ROW(A5))),"")} | K20: {=IFERROR(INDEX($F$16:$F$116,SMALL(IF($F$16:$F$116<>"",ROW($F$16:$F$116)-ROW($F$16)+1),ROW(A5))),"")} | L20: =H20 | M20: {=IFERROR(INDEX($G$16:$G$116,SMALL(IF($G$16:$G$116<>"",ROW($G$16:$G$116)-ROW($G$16)+1),ROW(A5))),"")} | N20: =IF($J20<>"",VLOOKUP($J20,$A$5:$F$9,2,FALSE),"") | O20: =IF($J20<>"",VLOOKUP($J20,$A$5:$F$9,3,FALSE),"") | P20: =IF($J20<>"",IF(_xlfn.SINGLE(INDIRECT($H20&"!"&$O20))<>"",_xlfn.SINGLE(INDIRECT($H20&"!"&$O20)),""),"") | Q20: =IF($J20<>"",VLOOKUP($J20,$A$5:$F$9,4,FALSE),"") | R20: =IF($J20<>"",IF(_xlfn.SINGLE(INDIRECT($H20&"!"&$Q20))<>"",_xlfn.SINGLE(INDIRECT($H20&"!"&$Q20)),""),"") | S20: =IF($J20<>"",VLOOKUP($J20,$A$5:$F$9,5,FALSE),"") | T20: =IF($J20<>"",IF(_xlfn.SINGLE(INDIRECT($H20&"!"&$S20))<>"",_xlfn.SINGLE(INDIRECT($H20&"!"&$S20)),""),"") | U20: =IF($J20<>"",VLOOKUP($J20,$A$5:$F$9,6,FALSE),"") | V20: =IF($J20<>"",IF(_xlfn.SINGLE(INDIRECT($H20&"!"&$U20))<>"",_xlfn.SINGLE(INDIRECT($H20&"!"&$U20)),""),"") | W20: =LEFT($Q20,1) | X20: =RIGHT($N20,2) | Y20: =IF($H20<>"",IF(_xlfn.SINGLE(INDIRECT($H20&"!"&$W20&($X20+Y$15+1)))<>"",_xlfn.SINGLE(INDIRECT($H20&"!"&$W20&($X20+Y$15+1))),""),"") | Z20: =IF($H20<>"",IF(_xlfn.SINGLE(INDIRECT($H20&"!"&$W20&($X20+Z$15+1)))<>"",_xlfn.SINGLE(INDIRECT($H20&"!"&$W20&($X20+Z$15+1))),""),"") | AA20: =IF($H20<>"",IF(_xlfn.SINGLE(INDIRECT($H20&"!"&$W20&($X20+AA$15+1)))<>"",_xlfn.SINGLE(INDIRECT($H20&"!"&$W20&($X20+AA$15+1))),""),"") | AB20: =IF($H20<>"",IF(_xlfn.SINGLE(INDIRECT($H20&"!"&$W20&($X20+AB$15+1)))<>"",_xlfn.SINGLE(INDIRECT($H20&"!"&$W20&($X20+AB$15+1))),""),"") | AC20: =IF(LEFT($J20,5)="Sonde","",IF($H20<>"",IF(_xlfn.SINGLE(INDIRECT($H20&"!"&$W20&($X20+AC$15+1)))<>"",_xlfn.SINGLE(INDIRECT($H20&"!"&$W20&($X20+AC$15+1))),""),"")) | AD20: =IF(OR($J20="Pluviomètre",LEFT($J20,5)="Sonde"),"",IF($H20<>"",IF(_xlfn.SINGLE(INDIRECT($H20&"!"&$W20&($X20+AD$15+1)))<>"",_xlfn.SINGLE(INDIRECT($H20&"!"&$W20&($X20+AD$15+1))),""),"")) | AE20: =IF(OR($J20="Pluviomètre",LEFT($J20,5)="Sonde"),"",IF($H20<>"",IF(_xlfn.SINGLE(INDIRECT($H20&"!"&$W20&($X20+AE$15+1)))<>"",_xlfn.SINGLE(INDIRECT($H20&"!"&$W20&($X20+AE$15+1))),""),"")) | AF20: =IF(OR($J20="Pluviomètre",LEFT($J20,5)="Sonde"),"",IF($H20<>"",IF(_xlfn.SINGLE(INDIRECT($H20&"!"&$W20&($X20+AF$15+1)))<>"",_xlfn.SINGLE(INDIRECT($H20&"!"&$W20&($X20+AF$15+1))),""),"")) | AG20: =IF(OR($J20="Pluviomètre",LEFT($J20,5)="Sonde"),"",IF($H20<>"",IF(_xlfn.SINGLE(INDIRECT($H20&"!"&$W20&($X20+AG$15+1)))<>"",_xlfn.SINGLE(INDIRECT($H20&"!"&$W20&($X20+AG$15+1))),""),"")) | AH20: =IF(OR($J20="Pluviomètre",LEFT($J20,5)="Sonde"),"",IF($H20<>"",IF(_xlfn.SINGLE(INDIRECT($H20&"!"&$W20&($X20+AH$15+1)))<>"",_xlfn.SINGLE(INDIRECT($H20&"!"&$W20&($X20+AH$15+1))),""),"")) | AI20: =LEFT($O20,1) | AJ20: =RIGHT($N20,2) | AK20: =IF($H20<>"",IF(_xlfn.SINGLE(INDIRECT($H20&"!"&$AI20&($AJ20+AK$15+1)))<>"",_xlfn.SINGLE(INDIRECT($H20&"!"&$AI20&($AJ20+AK$15+1))),""),"") | AL20: =IF($H20<>"",IF(_xlfn.SINGLE(INDIRECT($H20&"!"&$AI20&($AJ20+AL$15+1)))<>"",_xlfn.SINGLE(INDIRECT($H20&"!"&$AI20&($AJ20+AL$15+1))),""),"") | AM20: =IF($H20<>"",IF(_xlfn.SINGLE(INDIRECT($H20&"!"&$AI20&($AJ20+AM$15+1)))<>"",_xlfn.SINGLE(INDIRECT($H20&"!"&$AI20&($AJ20+AM$15+1))),""),"") | AN20: =IF($H20<>"",IF(_xlfn.SINGLE(INDIRECT($H20&"!"&$AI20&($AJ20+AN$15+1)))<>"",_xlfn.SINGLE(INDIRECT($H20&"!"&$AI20&($AJ20+AN$15+1))),""),"") | AO20: =IF(LEFT($J20,5)="Sonde","",IF($H20<>"",IF(_xlfn.SINGLE(INDIRECT($H20&"!"&$AI20&($AJ20+AO$15+1)))<>"",_xlfn.SINGLE(INDIRECT($H20&"!"&$AI20&($AJ20+AO$15+1))),""),"")) | AP20: =IF(OR($J20="Pluviomètre",LEFT($J20,5)="Sonde"),"",IF($H20<>"",IF(_xlfn.SINGLE(INDIRECT($H20&"!"&$AI20&($AJ20+AP$15+1)))<>"",_xlfn.SINGLE(INDIRECT($H20&"!"&$AI20&($AJ20+AP$15+1))),""),"")) | AQ20: =IF(OR($J20="Pluviomètre",LEFT($J20,5)="Sonde"),"",IF($H20<>"",IF(_xlfn.SINGLE(INDIRECT($H20&"!"&$AI20&($AJ20+AQ$15+1)))<>"",_xlfn.SINGLE(INDIRECT($H20&"!"&$AI20&($AJ20+AQ$15+1))),""),"")) | AR20: =IF(OR($J20="Pluviomètre",LEFT($J20,5)="Sonde"),"",IF($H20<>"",IF(_xlfn.SINGLE(INDIRECT($H20&"!"&$AI20&($AJ20+AR$15+1)))<>"",_xlfn.SINGLE(INDIRECT($H20&"!"&$AI20&($AJ20+AR$15+1))),""),"")) | AS20: =IF(OR($J20="Pluviomètre",LEFT($J20,5)="Sonde"),"",IF($H20<>"",IF(_xlfn.SINGLE(INDIRECT($H20&"!"&$AI20&($AJ20+AS$15+1)))<>"",_xlfn.SINGLE(INDIRECT($H20&"!"&$AI20&($AJ20+AS$15+1))),""),"")) | AT20: =IF(OR($J20="Pluviomètre",LEFT($J20,5)="Sonde"),"",IF($H20<>"",IF(_xlfn.SINGLE(INDIRECT($H20&"!"&$AI20&($AJ20+AT$15+1)))<>"",_xlfn.SINGLE(INDIRECT($H20&"!"&$AI20&($AJ20+AT$15+1))),""),""))
A21: 6 | B21: =IF(OR(AND(($B$1+A21-1)>=$B$1,($B$1+A21-1)<$C$1),AND(($B$1+A21-1)>=$B$2,($B$1+A21-1)<$C$2)),TRUE,FALSE) -> FALSE | C21: =IF( AND( $B21, OR( _xlfn.SINGLE(INDIRECT("Descriptif!$M"&($B$1+$A21-1)))="Préleveur", LEFT(_xlfn.SINGLE(INDIRECT("Descriptif!$M"&($B$1+$A21-1))),5)="Sonde", LEFT(_xlfn.SINGLE(INDIRECT("Descriptif!$M"&($B$1+$A21-1))),10)="Débitmètre", LEFT(_xlfn.SINGLE(INDIRECT("Descriptif!$F"&($B$1+$A21-1))),6)="PLUVIO" ) ), _xlfn.SINGLE(INDIRECT("Descriptif!$"&C$15&($B$1 +$A21 -1))), "" ) | D21: =IF( AND( $B21, OR( _xlfn.SINGLE(INDIRECT("Descriptif!$M"&($B$1+$A21-1)))="Préleveur", LEFT(_xlfn.SINGLE(INDIRECT("Descriptif!$M"&($B$1+$A21-1))),5)="Sonde", LEFT(_xlfn.SINGLE(INDIRECT("Descriptif!$M"&($B$1+$A21-1))),10)="Débitmètre", LEFT(_xlfn.SINGLE(INDIRECT("Descriptif!$F"&($B$1+$A21-1))),6)="PLUVIO" ) ), IF( LEFT(_xlfn.SINGLE(INDIRECT("Descriptif!$F"&($B$1+$A21-1))),11)="PLUVIO_STEU", "A3", IF( LEFT(_xlfn.SINGLE(INDIRECT("Descriptif!$F"&($B$1+$A21-1))),10)="PLUVIO_SCL", "A1", _xlfn.SINGLE(INDIRECT("Descriptif!$"&D$15&($B$1 +$A21 -1)) )) ), "" ) | E21: =IF( AND( $B21, OR( _xlfn.SINGLE(INDIRECT("Descriptif!$M"&($B$1+$A21-1)))="Préleveur", LEFT(_xlfn.SINGLE(INDIRECT("Descriptif!$M"&($B$1+$A21-1))),5)="Sonde", LEFT(_xlfn.SINGLE(INDIRECT("Descriptif!$M"&($B$1+$A21-1))),10)="Débitmètre", LEFT(_xlfn.SINGLE(INDIRECT("Descriptif!$F"&($B$1+$A21-1))),6)="PLUVIO" ) ), IF(LEFT(_xlfn.SINGLE(INDIRECT("Descriptif!$F"&($B$1+$A21-1))),6)="PLUVIO","Pluviomètre",_xlfn.SINGLE(INDIRECT("Descriptif!$"&E$15&($B$1 +$A21 -1)))), "" ) | F21: =IF( AND( $B21, OR( _xlfn.SINGLE(INDIRECT("Descriptif!$M"&($B$1+$A21-1)))="Préleveur", LEFT(_xlfn.SINGLE(INDIRECT("Descriptif!$M"&($B$1+$A21-1))),5)="Sonde", LEFT(_xlfn.SINGLE(INDIRECT("Descriptif!$M"&($B$1+$A21-1))),10)="Débitmètre", LEFT(_xlfn.SINGLE(INDIRECT("Descriptif!$F"&($B$1+$A21-1))),6)="PLUVIO" ) ), IF(LEFT(_xlfn.SINGLE(INDIRECT("Descriptif!$F"&($B$1+$A21-1))),6)="PLUVIO","Pluviomètre",_xlfn.SINGLE(INDIRECT("Descriptif!$"&F$15&($B$1 +$A21 -1)))), "" ) | G21: =IF( AND( $B21, OR( _xlfn.SINGLE(INDIRECT("Descriptif!$M"&($B$1+$A21-1)))="Préleveur", LEFT(_xlfn.SINGLE(INDIRECT("Descriptif!$M"&($B$1+$A21-1))),5)="Sonde", LEFT(_xlfn.SINGLE(INDIRECT("Descriptif!$M"&($B$1+$A21-1))),10)="Débitmètre", LEFT(_xlfn.SINGLE(INDIRECT("Descriptif!$F"&($B$1+$A21-1))),6)="PLUVIO" ) ), IF(LEFT(_xlfn.SINGLE(INDIRECT("Descriptif!$F"&($B$1+$A21-1))),6)="PLUVIO","Pluviomètre",_xlfn.SINGLE(INDIRECT("Descriptif!$"&G$15&($B$1 +$A21 -1)))), "" ) | H21: {=IFERROR(INDEX($C$16:$C$116,SMALL(IF($C$16:$C$116<>"",ROW($C$16:$C$116)-ROW($C$16)+1),ROW(A6))),"")} | I21: {=IFERROR(INDEX($D$16:$D$116,SMALL(IF($D$16:$D$116<>"",ROW($D$16:$D$116)-ROW($D$16)+1),ROW(A6))),"")} | J21: {=IFERROR(INDEX($E$16:$E$116,SMALL(IF($E$16:$E$116<>"",ROW($E$16:$E$116)-ROW($E$16)+1),ROW(A6))),"")} | K21: {=IFERROR(INDEX($F$16:$F$116,SMALL(IF($F$16:$F$116<>"",ROW($F$16:$F$116)-ROW($F$16)+1),ROW(A6))),"")} | L21: =H21 | M21: {=IFERROR(INDEX($G$16:$G$116,SMALL(IF($G$16:$G$116<>"",ROW($G$16:$G$116)-ROW($G$16)+1),ROW(A6))),"")} | N21: =IF($J21<>"",VLOOKUP($J21,$A$5:$F$9,2,FALSE),"") | O21: =IF($J21<>"",VLOOKUP($J21,$A$5:$F$9,3,FALSE),"") | P21: =IF($J21<>"",IF(_xlfn.SINGLE(INDIRECT($H21&"!"&$O21))<>"",_xlfn.SINGLE(INDIRECT($H21&"!"&$O21)),""),"") | Q21: =IF($J21<>"",VLOOKUP($J21,$A$5:$F$9,4,FALSE),"") | R21: =IF($J21<>"",IF(_xlfn.SINGLE(INDIRECT($H21&"!"&$Q21))<>"",_xlfn.SINGLE(INDIRECT($H21&"!"&$Q21)),""),"") | S21: =IF($J21<>"",VLOOKUP($J21,$A$5:$F$9,5,FALSE),"") | T21: =IF($J21<>"",IF(_xlfn.SINGLE(INDIRECT($H21&"!"&$S21))<>"",_xlfn.SINGLE(INDIRECT($H21&"!"&$S21)),""),"") | U21: =IF($J21<>"",VLOOKUP($J21,$A$5:$F$9,6,FALSE),"") | V21: =IF($J21<>"",IF(_xlfn.SINGLE(INDIRECT($H21&"!"&$U21))<>"",_xlfn.SINGLE(INDIRECT($H21&"!"&$U21)),""),"") | W21: =LEFT($Q21,1) | X21: =RIGHT($N21,2) | Y21: =IF($H21<>"",IF(_xlfn.SINGLE(INDIRECT($H21&"!"&$W21&($X21+Y$15+1)))<>"",_xlfn.SINGLE(INDIRECT($H21&"!"&$W21&($X21+Y$15+1))),""),"") | Z21: =IF($H21<>"",IF(_xlfn.SINGLE(INDIRECT($H21&"!"&$W21&($X21+Z$15+1)))<>"",_xlfn.SINGLE(INDIRECT($H21&"!"&$W21&($X21+Z$15+1))),""),"") | AA21: =IF($H21<>"",IF(_xlfn.SINGLE(INDIRECT($H21&"!"&$W21&($X21+AA$15+1)))<>"",_xlfn.SINGLE(INDIRECT($H21&"!"&$W21&($X21+AA$15+1))),""),"") | AB21: =IF($H21<>"",IF(_xlfn.SINGLE(INDIRECT($H21&"!"&$W21&($X21+AB$15+1)))<>"",_xlfn.SINGLE(INDIRECT($H21&"!"&$W21&($X21+AB$15+1))),""),"") | AC21: =IF(LEFT($J21,5)="Sonde","",IF($H21<>"",IF(_xlfn.SINGLE(INDIRECT($H21&"!"&$W21&($X21+AC$15+1)))<>"",_xlfn.SINGLE(INDIRECT($H21&"!"&$W21&($X21+AC$15+1))),""),"")) | AD21: =IF(OR($J21="Pluviomètre",LEFT($J21,5)="Sonde"),"",IF($H21<>"",IF(_xlfn.SINGLE(INDIRECT($H21&"!"&$W21&($X21+AD$15+1)))<>"",_xlfn.SINGLE(INDIRECT($H21&"!"&$W21&($X21+AD$15+1))),""),"")) | AE21: =IF(OR($J21="Pluviomètre",LEFT($J21,5)="Sonde"),"",IF($H21<>"",IF(_xlfn.SINGLE(INDIRECT($H21&"!"&$W21&($X21+AE$15+1)))<>"",_xlfn.SINGLE(INDIRECT($H21&"!"&$W21&($X21+AE$15+1))),""),"")) | AF21: =IF(OR($J21="Pluviomètre",LEFT($J21,5)="Sonde"),"",IF($H21<>"",IF(_xlfn.SINGLE(INDIRECT($H21&"!"&$W21&($X21+AF$15+1)))<>"",_xlfn.SINGLE(INDIRECT($H21&"!"&$W21&($X21+AF$15+1))),""),"")) | AG21: =IF(OR($J21="Pluviomètre",LEFT($J21,5)="Sonde"),"",IF($H21<>"",IF(_xlfn.SINGLE(INDIRECT($H21&"!"&$W21&($X21+AG$15+1)))<>"",_xlfn.SINGLE(INDIRECT($H21&"!"&$W21&($X21+AG$15+1))),""),"")) | AH21: =IF(OR($J21="Pluviomètre",LEFT($J21,5)="Sonde"),"",IF($H21<>"",IF(_xlfn.SINGLE(INDIRECT($H21&"!"&$W21&($X21+AH$15+1)))<>"",_xlfn.SINGLE(INDIRECT($H21&"!"&$W21&($X21+AH$15+1))),""),"")) | AI21: =LEFT($O21,1) | AJ21: =RIGHT($N21,2) | AK21: =IF($H21<>"",IF(_xlfn.SINGLE(INDIRECT($H21&"!"&$AI21&($AJ21+AK$15+1)))<>"",_xlfn.SINGLE(INDIRECT($H21&"!"&$AI21&($AJ21+AK$15+1))),""),"") | AL21: =IF($H21<>"",IF(_xlfn.SINGLE(INDIRECT($H21&"!"&$AI21&($AJ21+AL$15+1)))<>"",_xlfn.SINGLE(INDIRECT($H21&"!"&$AI21&($AJ21+AL$15+1))),""),"") | AM21: =IF($H21<>"",IF(_xlfn.SINGLE(INDIRECT($H21&"!"&$AI21&($AJ21+AM$15+1)))<>"",_xlfn.SINGLE(INDIRECT($H21&"!"&$AI21&($AJ21+AM$15+1))),""),"") | AN21: =IF($H21<>"",IF(_xlfn.SINGLE(INDIRECT($H21&"!"&$AI21&($AJ21+AN$15+1)))<>"",_xlfn.SINGLE(INDIRECT($H21&"!"&$AI21&($AJ21+AN$15+1))),""),"") | AO21: =IF(LEFT($J21,5)="Sonde","",IF($H21<>"",IF(_xlfn.SINGLE(INDIRECT($H21&"!"&$AI21&($AJ21+AO$15+1)))<>"",_xlfn.SINGLE(INDIRECT($H21&"!"&$AI21&($AJ21+AO$15+1))),""),"")) | AP21: =IF(OR($J21="Pluviomètre",LEFT($J21,5)="Sonde"),"",IF($H21<>"",IF(_xlfn.SINGLE(INDIRECT($H21&"!"&$AI21&($AJ21+AP$15+1)))<>"",_xlfn.SINGLE(INDIRECT($H21&"!"&$AI21&($AJ21+AP$15+1))),""),"")) | AQ21: =IF(OR($J21="Pluviomètre",LEFT($J21,5)="Sonde"),"",IF($H21<>"",IF(_xlfn.SINGLE(INDIRECT($H21&"!"&$AI21&($AJ21+AQ$15+1)))<>"",_xlfn.SINGLE(INDIRECT($H21&"!"&$AI21&($AJ21+AQ$15+1))),""),"")) | AR21: =IF(OR($J21="Pluviomètre",LEFT($J21,5)="Sonde"),"",IF($H21<>"",IF(_xlfn.SINGLE(INDIRECT($H21&"!"&$AI21&($AJ21+AR$15+1)))<>"",_xlfn.SINGLE(INDIRECT($H21&"!"&$AI21&($AJ21+AR$15+1))),""),"")) | AS21: =IF(OR($J21="Pluviomètre",LEFT($J21,5)="Sonde"),"",IF($H21<>"",IF(_xlfn.SINGLE(INDIRECT($H21&"!"&$AI21&($AJ21+AS$15+1)))<>"",_xlfn.SINGLE(INDIRECT($H21&"!"&$AI21&($AJ21+AS$15+1))),""),"")) | AT21: =IF(OR($J21="Pluviomètre",LEFT($J21,5)="Sonde"),"",IF($H21<>"",IF(_xlfn.SINGLE(INDIRECT($H21&"!"&$AI21&($AJ21+AT$15+1)))<>"",_xlfn.SINGLE(INDIRECT($H21&"!"&$AI21&($AJ21+AT$15+1))),""),""))
A22: 7 | B22: =IF(OR(AND(($B$1+A22-1)>=$B$1,($B$1+A22-1)<$C$1),AND(($B$1+A22-1)>=$B$2,($B$1+A22-1)<$C$2)),TRUE,FALSE) -> FALSE | C22: =IF( AND( $B22, OR( _xlfn.SINGLE(INDIRECT("Descriptif!$M"&($B$1+$A22-1)))="Préleveur", LEFT(_xlfn.SINGLE(INDIRECT("Descriptif!$M"&($B$1+$A22-1))),5)="Sonde", LEFT(_xlfn.SINGLE(INDIRECT("Descriptif!$M"&($B$1+$A22-1))),10)="Débitmètre", LEFT(_xlfn.SINGLE(INDIRECT("Descriptif!$F"&($B$1+$A22-1))),6)="PLUVIO" ) ), _xlfn.SINGLE(INDIRECT("Descriptif!$"&C$15&($B$1 +$A22 -1))), "" ) | D22: =IF( AND( $B22, OR( _xlfn.SINGLE(INDIRECT("Descriptif!$M"&($B$1+$A22-1)))="Préleveur", LEFT(_xlfn.SINGLE(INDIRECT("Descriptif!$M"&($B$1+$A22-1))),5)="Sonde", LEFT(_xlfn.SINGLE(INDIRECT("Descriptif!$M"&($B$1+$A22-1))),10)="Débitmètre", LEFT(_xlfn.SINGLE(INDIRECT("Descriptif!$F"&($B$1+$A22-1))),6)="PLUVIO" ) ), IF( LEFT(_xlfn.SINGLE(INDIRECT("Descriptif!$F"&($B$1+$A22-1))),11)="PLUVIO_STEU", "A3", IF( LEFT(_xlfn.SINGLE(INDIRECT("Descriptif!$F"&($B$1+$A22-1))),10)="PLUVIO_SCL", "A1", _xlfn.SINGLE(INDIRECT("Descriptif!$"&D$15&($B$1 +$A22 -1)) )) ), "" ) | E22: =IF( AND( $B22, OR( _xlfn.SINGLE(INDIRECT("Descriptif!$M"&($B$1+$A22-1)))="Préleveur", LEFT(_xlfn.SINGLE(INDIRECT("Descriptif!$M"&($B$1+$A22-1))),5)="Sonde", LEFT(_xlfn.SINGLE(INDIRECT("Descriptif!$M"&($B$1+$A22-1))),10)="Débitmètre", LEFT(_xlfn.SINGLE(INDIRECT("Descriptif!$F"&($B$1+$A22-1))),6)="PLUVIO" ) ), IF(LEFT(_xlfn.SINGLE(INDIRECT("Descriptif!$F"&($B$1+$A22-1))),6)="PLUVIO","Pluviomètre",_xlfn.SINGLE(INDIRECT("Descriptif!$"&E$15&($B$1 +$A22 -1)))), "" ) | F22: =IF( AND( $B22, OR( _xlfn.SINGLE(INDIRECT("Descriptif!$M"&($B$1+$A22-1)))="Préleveur", LEFT(_xlfn.SINGLE(INDIRECT("Descriptif!$M"&($B$1+$A22-1))),5)="Sonde", LEFT(_xlfn.SINGLE(INDIRECT("Descriptif!$M"&($B$1+$A22-1))),10)="Débitmètre", LEFT(_xlfn.SINGLE(INDIRECT("Descriptif!$F"&($B$1+$A22-1))),6)="PLUVIO" ) ), IF(LEFT(_xlfn.SINGLE(INDIRECT("Descriptif!$F"&($B$1+$A22-1))),6)="PLUVIO","Pluviomètre",_xlfn.SINGLE(INDIRECT("Descriptif!$"&F$15&($B$1 +$A22 -1)))), "" ) | G22: =IF( AND( $B22, OR( _xlfn.SINGLE(INDIRECT("Descriptif!$M"&($B$1+$A22-1)))="Préleveur", LEFT(_xlfn.SINGLE(INDIRECT("Descriptif!$M"&($B$1+$A22-1))),5)="Sonde", LEFT(_xlfn.SINGLE(INDIRECT("Descriptif!$M"&($B$1+$A22-1))),10)="Débitmètre", LEFT(_xlfn.SINGLE(INDIRECT("Descriptif!$F"&($B$1+$A22-1))),6)="PLUVIO" ) ), IF(LEFT(_xlfn.SINGLE(INDIRECT("Descriptif!$F"&($B$1+$A22-1))),6)="PLUVIO","Pluviomètre",_xlfn.SINGLE(INDIRECT("Descriptif!$"&G$15&($B$1 +$A22 -1)))), "" ) | H22: {=IFERROR(INDEX($C$16:$C$116,SMALL(IF($C$16:$C$116<>"",ROW($C$16:$C$116)-ROW($C$16)+1),ROW(A7))),"")} | I22: {=IFERROR(INDEX($D$16:$D$116,SMALL(IF($D$16:$D$116<>"",ROW($D$16:$D$116)-ROW($D$16)+1),ROW(A7))),"")} | J22: {=IFERROR(INDEX($E$16:$E$116,SMALL(IF($E$16:$E$116<>"",ROW($E$16:$E$116)-ROW($E$16)+1),ROW(A7))),"")} | K22: {=IFERROR(INDEX($F$16:$F$116,SMALL(IF($F$16:$F$116<>"",ROW($F$16:$F$116)-ROW($F$16)+1),ROW(A7))),"")} | L22: =H22 | M22: {=IFERROR(INDEX($G$16:$G$116,SMALL(IF($G$16:$G$116<>"",ROW($G$16:$G$116)-ROW($G$16)+1),ROW(A7))),"")} | N22: =IF($J22<>"",VLOOKUP($J22,$A$5:$F$9,2,FALSE),"") | O22: =IF($J22<>"",VLOOKUP($J22,$A$5:$F$9,3,FALSE),"") | P22: =IF($J22<>"",IF(_xlfn.SINGLE(INDIRECT($H22&"!"&$O22))<>"",_xlfn.SINGLE(INDIRECT($H22&"!"&$O22)),""),"") | Q22: =IF($J22<>"",VLOOKUP($J22,$A$5:$F$9,4,FALSE),"") | R22: =IF($J22<>"",IF(_xlfn.SINGLE(INDIRECT($H22&"!"&$Q22))<>"",_xlfn.SINGLE(INDIRECT($H22&"!"&$Q22)),""),"") | S22: =IF($J22<>"",VLOOKUP($J22,$A$5:$F$9,5,FALSE),"") | T22: =IF($J22<>"",IF(_xlfn.SINGLE(INDIRECT($H22&"!"&$S22))<>"",_xlfn.SINGLE(INDIRECT($H22&"!"&$S22)),""),"") | U22: =IF($J22<>"",VLOOKUP($J22,$A$5:$F$9,6,FALSE),"") | V22: =IF($J22<>"",IF(_xlfn.SINGLE(INDIRECT($H22&"!"&$U22))<>"",_xlfn.SINGLE(INDIRECT($H22&"!"&$U22)),""),"") | W22: =LEFT($Q22,1) | X22: =RIGHT($N22,2) | Y22: =IF($H22<>"",IF(_xlfn.SINGLE(INDIRECT($H22&"!"&$W22&($X22+Y$15+1)))<>"",_xlfn.SINGLE(INDIRECT($H22&"!"&$W22&($X22+Y$15+1))),""),"") | Z22: =IF($H22<>"",IF(_xlfn.SINGLE(INDIRECT($H22&"!"&$W22&($X22+Z$15+1)))<>"",_xlfn.SINGLE(INDIRECT($H22&"!"&$W22&($X22+Z$15+1))),""),"") | AA22: =IF($H22<>"",IF(_xlfn.SINGLE(INDIRECT($H22&"!"&$W22&($X22+AA$15+1)))<>"",_xlfn.SINGLE(INDIRECT($H22&"!"&$W22&($X22+AA$15+1))),""),"") | AB22: =IF($H22<>"",IF(_xlfn.SINGLE(INDIRECT($H22&"!"&$W22&($X22+AB$15+1)))<>"",_xlfn.SINGLE(INDIRECT($H22&"!"&$W22&($X22+AB$15+1))),""),"") | AC22: =IF(LEFT($J22,5)="Sonde","",IF($H22<>"",IF(_xlfn.SINGLE(INDIRECT($H22&"!"&$W22&($X22+AC$15+1)))<>"",_xlfn.SINGLE(INDIRECT($H22&"!"&$W22&($X22+AC$15+1))),""),"")) | AD22: =IF(OR($J22="Pluviomètre",LEFT($J22,5)="Sonde"),"",IF($H22<>"",IF(_xlfn.SINGLE(INDIRECT($H22&"!"&$W22&($X22+AD$15+1)))<>"",_xlfn.SINGLE(INDIRECT($H22&"!"&$W22&($X22+AD$15+1))),""),"")) | AE22: =IF(OR($J22="Pluviomètre",LEFT($J22,5)="Sonde"),"",IF($H22<>"",IF(_xlfn.SINGLE(INDIRECT($H22&"!"&$W22&($X22+AE$15+1)))<>"",_xlfn.SINGLE(INDIRECT($H22&"!"&$W22&($X22+AE$15+1))),""),"")) | AF22: =IF(OR($J22="Pluviomètre",LEFT($J22,5)="Sonde"),"",IF($H22<>"",IF(_xlfn.SINGLE(INDIRECT($H22&"!"&$W22&($X22+AF$15+1)))<>"",_xlfn.SINGLE(INDIRECT($H22&"!"&$W22&($X22+AF$15+1))),""),"")) | AG22: =IF(OR($J22="Pluviomètre",LEFT($J22,5)="Sonde"),"",IF($H22<>"",IF(_xlfn.SINGLE(INDIRECT($H22&"!"&$W22&($X22+AG$15+1)))<>"",_xlfn.SINGLE(INDIRECT($H22&"!"&$W22&($X22+AG$15+1))),""),"")) | AH22: =IF(OR($J22="Pluviomètre",LEFT($J22,5)="Sonde"),"",IF($H22<>"",IF(_xlfn.SINGLE(INDIRECT($H22&"!"&$W22&($X22+AH$15+1)))<>"",_xlfn.SINGLE(INDIRECT($H22&"!"&$W22&($X22+AH$15+1))),""),"")) | AI22: =LEFT($O22,1) | AJ22: =RIGHT($N22,2) | AK22: =IF($H22<>"",IF(_xlfn.SINGLE(INDIRECT($H22&"!"&$AI22&($AJ22+AK$15+1)))<>"",_xlfn.SINGLE(INDIRECT($H22&"!"&$AI22&($AJ22+AK$15+1))),""),"") | AL22: =IF($H22<>"",IF(_xlfn.SINGLE(INDIRECT($H22&"!"&$AI22&($AJ22+AL$15+1)))<>"",_xlfn.SINGLE(INDIRECT($H22&"!"&$AI22&($AJ22+AL$15+1))),""),"") | AM22: =IF($H22<>"",IF(_xlfn.SINGLE(INDIRECT($H22&"!"&$AI22&($AJ22+AM$15+1)))<>"",_xlfn.SINGLE(INDIRECT($H22&"!"&$AI22&($AJ22+AM$15+1))),""),"") | AN22: =IF($H22<>"",IF(_xlfn.SINGLE(INDIRECT($H22&"!"&$AI22&($AJ22+AN$15+1)))<>"",_xlfn.SINGLE(INDIRECT($H22&"!"&$AI22&($AJ22+AN$15+1))),""),"") | AO22: =IF(LEFT($J22,5)="Sonde","",IF($H22<>"",IF(_xlfn.SINGLE(INDIRECT($H22&"!"&$AI22&($AJ22+AO$15+1)))<>"",_xlfn.SINGLE(INDIRECT($H22&"!"&$AI22&($AJ22+AO$15+1))),""),"")) | AP22: =IF(OR($J22="Pluviomètre",LEFT($J22,5)="Sonde"),"",IF($H22<>"",IF(_xlfn.SINGLE(INDIRECT($H22&"!"&$AI22&($AJ22+AP$15+1)))<>"",_xlfn.SINGLE(INDIRECT($H22&"!"&$AI22&($AJ22+AP$15+1))),""),"")) | AQ22: =IF(OR($J22="Pluviomètre",LEFT($J22,5)="Sonde"),"",IF($H22<>"",IF(_xlfn.SINGLE(INDIRECT($H22&"!"&$AI22&($AJ22+AQ$15+1)))<>"",_xlfn.SINGLE(INDIRECT($H22&"!"&$AI22&($AJ22+AQ$15+1))),""),"")) | AR22: =IF(OR($J22="Pluviomètre",LEFT($J22,5)="Sonde"),"",IF($H22<>"",IF(_xlfn.SINGLE(INDIRECT($H22&"!"&$AI22&($AJ22+AR$15+1)))<>"",_xlfn.SINGLE(INDIRECT($H22&"!"&$AI22&($AJ22+AR$15+1))),""),"")) | AS22: =IF(OR($J22="Pluviomètre",LEFT($J22,5)="Sonde"),"",IF($H22<>"",IF(_xlfn.SINGLE(INDIRECT($H22&"!"&$AI22&($AJ22+AS$15+1)))<>"",_xlfn.SINGLE(INDIRECT($H22&"!"&$AI22&($AJ22+AS$15+1))),""),"")) | AT22: =IF(OR($J22="Pluviomètre",LEFT($J22,5)="Sonde"),"",IF($H22<>"",IF(_xlfn.SINGLE(INDIRECT($H22&"!"&$AI22&($AJ22+AT$15+1)))<>"",_xlfn.SINGLE(INDIRECT($H22&"!"&$AI22&($AJ22+AT$15+1))),""),""))
A23: 8 | B23: =IF(OR(AND(($B$1+A23-1)>=$B$1,($B$1+A23-1)<$C$1),AND(($B$1+A23-1)>=$B$2,($B$1+A23-1)<$C$2)),TRUE,FALSE) -> FALSE | C23: =IF( AND( $B23, OR( _xlfn.SINGLE(INDIRECT("Descriptif!$M"&($B$1+$A23-1)))="Préleveur", LEFT(_xlfn.SINGLE(INDIRECT("Descriptif!$M"&($B$1+$A23-1))),5)="Sonde", LEFT(_xlfn.SINGLE(INDIRECT("Descriptif!$M"&($B$1+$A23-1))),10)="Débitmètre", LEFT(_xlfn.SINGLE(INDIRECT("Descriptif!$F"&($B$1+$A23-1))),6)="PLUVIO" ) ), _xlfn.SINGLE(INDIRECT("Descriptif!$"&C$15&($B$1 +$A23 -1))), "" ) | D23: =IF( AND( $B23, OR( _xlfn.SINGLE(INDIRECT("Descriptif!$M"&($B$1+$A23-1)))="Préleveur", LEFT(_xlfn.SINGLE(INDIRECT("Descriptif!$M"&($B$1+$A23-1))),5)="Sonde", LEFT(_xlfn.SINGLE(INDIRECT("Descriptif!$M"&($B$1+$A23-1))),10)="Débitmètre", LEFT(_xlfn.SINGLE(INDIRECT("Descriptif!$F"&($B$1+$A23-1))),6)="PLUVIO" ) ), IF( LEFT(_xlfn.SINGLE(INDIRECT("Descriptif!$F"&($B$1+$A23-1))),11)="PLUVIO_STEU", "A3", IF( LEFT(_xlfn.SINGLE(INDIRECT("Descriptif!$F"&($B$1+$A23-1))),10)="PLUVIO_SCL", "A1", _xlfn.SINGLE(INDIRECT("Descriptif!$"&D$15&($B$1 +$A23 -1)) )) ), "" ) | E23: =IF( AND( $B23, OR( _xlfn.SINGLE(INDIRECT("Descriptif!$M"&($B$1+$A23-1)))="Préleveur", LEFT(_xlfn.SINGLE(INDIRECT("Descriptif!$M"&($B$1+$A23-1))),5)="Sonde", LEFT(_xlfn.SINGLE(INDIRECT("Descriptif!$M"&($B$1+$A23-1))),10)="Débitmètre", LEFT(_xlfn.SINGLE(INDIRECT("Descriptif!$F"&($B$1+$A23-1))),6)="PLUVIO" ) ), IF(LEFT(_xlfn.SINGLE(INDIRECT("Descriptif!$F"&($B$1+$A23-1))),6)="PLUVIO","Pluviomètre",_xlfn.SINGLE(INDIRECT("Descriptif!$"&E$15&($B$1 +$A23 -1)))), "" ) | F23: =IF( AND( $B23, OR( _xlfn.SINGLE(INDIRECT("Descriptif!$M"&($B$1+$A23-1)))="Préleveur", LEFT(_xlfn.SINGLE(INDIRECT("Descriptif!$M"&($B$1+$A23-1))),5)="Sonde", LEFT(_xlfn.SINGLE(INDIRECT("Descriptif!$M"&($B$1+$A23-1))),10)="Débitmètre", LEFT(_xlfn.SINGLE(INDIRECT("Descriptif!$F"&($B$1+$A23-1))),6)="PLUVIO" ) ), IF(LEFT(_xlfn.SINGLE(INDIRECT("Descriptif!$F"&($B$1+$A23-1))),6)="PLUVIO","Pluviomètre",_xlfn.SINGLE(INDIRECT("Descriptif!$"&F$15&($B$1 +$A23 -1)))), "" ) | G23: =IF( AND( $B23, OR( _xlfn.SINGLE(INDIRECT("Descriptif!$M"&($B$1+$A23-1)))="Préleveur", LEFT(_xlfn.SINGLE(INDIRECT("Descriptif!$M"&($B$1+$A23-1))),5)="Sonde", LEFT(_xlfn.SINGLE(INDIRECT("Descriptif!$M"&($B$1+$A23-1))),10)="Débitmètre", LEFT(_xlfn.SINGLE(INDIRECT("Descriptif!$F"&($B$1+$A23-1))),6)="PLUVIO" ) ), IF(LEFT(_xlfn.SINGLE(INDIRECT("Descriptif!$F"&($B$1+$A23-1))),6)="PLUVIO","Pluviomètre",_xlfn.SINGLE(INDIRECT("Descriptif!$"&G$15&($B$1 +$A23 -1)))), "" ) | H23: {=IFERROR(INDEX($C$16:$C$116,SMALL(IF($C$16:$C$116<>"",ROW($C$16:$C$116)-ROW($C$16)+1),ROW(A8))),"")} | I23: {=IFERROR(INDEX($D$16:$D$116,SMALL(IF($D$16:$D$116<>"",ROW($D$16:$D$116)-ROW($D$16)+1),ROW(A8))),"")} | J23: {=IFERROR(INDEX($E$16:$E$116,SMALL(IF($E$16:$E$116<>"",ROW($E$16:$E$116)-ROW($E$16)+1),ROW(A8))),"")} | K23: {=IFERROR(INDEX($F$16:$F$116,SMALL(IF($F$16:$F$116<>"",ROW($F$16:$F$116)-ROW($F$16)+1),ROW(A8))),"")} | L23: =H23 | M23: {=IFERROR(INDEX($G$16:$G$116,SMALL(IF($G$16:$G$116<>"",ROW($G$16:$G$116)-ROW($G$16)+1),ROW(A8))),"")} | N23: =IF($J23<>"",VLOOKUP($J23,$A$5:$F$9,2,FALSE),"") | O23: =IF($J23<>"",VLOOKUP($J23,$A$5:$F$9,3,FALSE),"") | P23: =IF($J23<>"",IF(_xlfn.SINGLE(INDIRECT($H23&"!"&$O23))<>"",_xlfn.SINGLE(INDIRECT($H23&"!"&$O23)),""),"") | Q23: =IF($J23<>"",VLOOKUP($J23,$A$5:$F$9,4,FALSE),"") | R23: =IF($J23<>"",IF(_xlfn.SINGLE(INDIRECT($H23&"!"&$Q23))<>"",_xlfn.SINGLE(INDIRECT($H23&"!"&$Q23)),""),"") | S23: =IF($J23<>"",VLOOKUP($J23,$A$5:$F$9,5,FALSE),"") | T23: =IF($J23<>"",IF(_xlfn.SINGLE(INDIRECT($H23&"!"&$S23))<>"",_xlfn.SINGLE(INDIRECT($H23&"!"&$S23)),""),"") | U23: =IF($J23<>"",VLOOKUP($J23,$A$5:$F$9,6,FALSE),"") | V23: =IF($J23<>"",IF(_xlfn.SINGLE(INDIRECT($H23&"!"&$U23))<>"",_xlfn.SINGLE(INDIRECT($H23&"!"&$U23)),""),"") | W23: =LEFT($Q23,1) | X23: =RIGHT($N23,2) | Y23: =IF($H23<>"",IF(_xlfn.SINGLE(INDIRECT($H23&"!"&$W23&($X23+Y$15+1)))<>"",_xlfn.SINGLE(INDIRECT($H23&"!"&$W23&($X23+Y$15+1))),""),"") | Z23: =IF($H23<>"",IF(_xlfn.SINGLE(INDIRECT($H23&"!"&$W23&($X23+Z$15+1)))<>"",_xlfn.SINGLE(INDIRECT($H23&"!"&$W23&($X23+Z$15+1))),""),"") | AA23: =IF($H23<>"",IF(_xlfn.SINGLE(INDIRECT($H23&"!"&$W23&($X23+AA$15+1)))<>"",_xlfn.SINGLE(INDIRECT($H23&"!"&$W23&($X23+AA$15+1))),""),"") | AB23: =IF($H23<>"",IF(_xlfn.SINGLE(INDIRECT($H23&"!"&$W23&($X23+AB$15+1)))<>"",_xlfn.SINGLE(INDIRECT($H23&"!"&$W23&($X23+AB$15+1))),""),"") | AC23: =IF(LEFT($J23,5)="Sonde","",IF($H23<>"",IF(_xlfn.SINGLE(INDIRECT($H23&"!"&$W23&($X23+AC$15+1)))<>"",_xlfn.SINGLE(INDIRECT($H23&"!"&$W23&($X23+AC$15+1))),""),"")) | AD23: =IF(OR($J23="Pluviomètre",LEFT($J23,5)="Sonde"),"",IF($H23<>"",IF(_xlfn.SINGLE(INDIRECT($H23&"!"&$W23&($X23+AD$15+1)))<>"",_xlfn.SINGLE(INDIRECT($H23&"!"&$W23&($X23+AD$15+1))),""),"")) | AE23: =IF(OR($J23="Pluviomètre",LEFT($J23,5)="Sonde"),"",IF($H23<>"",IF(_xlfn.SINGLE(INDIRECT($H23&"!"&$W23&($X23+AE$15+1)))<>"",_xlfn.SINGLE(INDIRECT($H23&"!"&$W23&($X23+AE$15+1))),""),"")) | AF23: =IF(OR($J23="Pluviomètre",LEFT($J23,5)="Sonde"),"",IF($H23<>"",IF(_xlfn.SINGLE(INDIRECT($H23&"!"&$W23&($X23+AF$15+1)))<>"",_xlfn.SINGLE(INDIRECT($H23&"!"&$W23&($X23+AF$15+1))),""),"")) | AG23: =IF(OR($J23="Pluviomètre",LEFT($J23,5)="Sonde"),"",IF($H23<>"",IF(_xlfn.SINGLE(INDIRECT($H23&"!"&$W23&($X23+AG$15+1)))<>"",_xlfn.SINGLE(INDIRECT($H23&"!"&$W23&($X23+AG$15+1))),""),"")) | AH23: =IF(OR($J23="Pluviomètre",LEFT($J23,5)="Sonde"),"",IF($H23<>"",IF(_xlfn.SINGLE(INDIRECT($H23&"!"&$W23&($X23+AH$15+1)))<>"",_xlfn.SINGLE(INDIRECT($H23&"!"&$W23&($X23+AH$15+1))),""),"")) | AI23: =LEFT($O23,1) | AJ23: =RIGHT($N23,2) | AK23: =IF($H23<>"",IF(_xlfn.SINGLE(INDIRECT($H23&"!"&$AI23&($AJ23+AK$15+1)))<>"",_xlfn.SINGLE(INDIRECT($H23&"!"&$AI23&($AJ23+AK$15+1))),""),"") | AL23: =IF($H23<>"",IF(_xlfn.SINGLE(INDIRECT($H23&"!"&$AI23&($AJ23+AL$15+1)))<>"",_xlfn.SINGLE(INDIRECT($H23&"!"&$AI23&($AJ23+AL$15+1))),""),"") | AM23: =IF($H23<>"",IF(_xlfn.SINGLE(INDIRECT($H23&"!"&$AI23&($AJ23+AM$15+1)))<>"",_xlfn.SINGLE(INDIRECT($H23&"!"&$AI23&($AJ23+AM$15+1))),""),"") | AN23: =IF($H23<>"",IF(_xlfn.SINGLE(INDIRECT($H23&"!"&$AI23&($AJ23+AN$15+1)))<>"",_xlfn.SINGLE(INDIRECT($H23&"!"&$AI23&($AJ23+AN$15+1))),""),"") | AO23: =IF(LEFT($J23,5)="Sonde","",IF($H23<>"",IF(_xlfn.SINGLE(INDIRECT($H23&"!"&$AI23&($AJ23+AO$15+1)))<>"",_xlfn.SINGLE(INDIRECT($H23&"!"&$AI23&($AJ23+AO$15+1))),""),"")) | AP23: =IF(OR($J23="Pluviomètre",LEFT($J23,5)="Sonde"),"",IF($H23<>"",IF(_xlfn.SINGLE(INDIRECT($H23&"!"&$AI23&($AJ23+AP$15+1)))<>"",_xlfn.SINGLE(INDIRECT($H23&"!"&$AI23&($AJ23+AP$15+1))),""),"")) | AQ23: =IF(OR($J23="Pluviomètre",LEFT($J23,5)="Sonde"),"",IF($H23<>"",IF(_xlfn.SINGLE(INDIRECT($H23&"!"&$AI23&($AJ23+AQ$15+1)))<>"",_xlfn.SINGLE(INDIRECT($H23&"!"&$AI23&($AJ23+AQ$15+1))),""),"")) | AR23: =IF(OR($J23="Pluviomètre",LEFT($J23,5)="Sonde"),"",IF($H23<>"",IF(_xlfn.SINGLE(INDIRECT($H23&"!"&$AI23&($AJ23+AR$15+1)))<>"",_xlfn.SINGLE(INDIRECT($H23&"!"&$AI23&($AJ23+AR$15+1))),""),"")) | AS23: =IF(OR($J23="Pluviomètre",LEFT($J23,5)="Sonde"),"",IF($H23<>"",IF(_xlfn.SINGLE(INDIRECT($H23&"!"&$AI23&($AJ23+AS$15+1)))<>"",_xlfn.SINGLE(INDIRECT($H23&"!"&$AI23&($AJ23+AS$15+1))),""),"")) | AT23: =IF(OR($J23="Pluviomètre",LEFT($J23,5)="Sonde"),"",IF($H23<>"",IF(_xlfn.SINGLE(INDIRECT($H23&"!"&$AI23&($AJ23+AT$15+1)))<>"",_xlfn.SINGLE(INDIRECT($H23&"!"&$AI23&($AJ23+AT$15+1))),""),""))
