Workbook
Name Asservissement: PARAM!$A$44:$A$46
Name CODE_SANDRE_3: PARAM!$I$4:$I$19
Name CODE_SANDRE_SCL: PARAM!$F$4:$F$7
Name CODE_SANDRE_STEU: PARAM!$E$4:$E$19
Name conditions_meteo: PARAM!$F$44:$F$46
Name Conformité: PARAM!$B$44:$B$48
Name Conformité: PARAM!$B$44:$B$48
Name Conformité: PARAM!$B$44:$B$48
Name Eq_h_controle: PARAM!$C$30:$C$32
Name Eq_h_controle: PARAM!$C$30:$C$32
Name Eq_h_controle: PARAM!$C$30:$C$32
Name Eq_h_controle: PARAM!$C$30:$C$32
Name EQUIPEMENT_PREL: PARAM!$B$4:$B$6
Name EQUIPEMENT_PREL: PARAM!$B$4:$B$6
Name EQUIPEMENT_PREL: PARAM!$B$4:$B$6
Name EQUIPEMENT_Q: PARAM!$A$4:$A$15
Name Frequence: PARAM!$E$44:$E$51
Name Frequence: PARAM!$E$44:$E$51
Name Frequence: PARAM!$E$44:$E$51
Name Frequence: PARAM!$E$44:$E$51
Name Frequence: PARAM!$E$44:$E$51
Name Frequence: PARAM!$E$44:$E$51
Name LISTE_1: PARAM!$A$21:$A$22
Name LISTE_1: PARAM!$A$21:$A$22
Name LISTE_1: PARAM!$A$21:$A$22
Name LISTE_1: PARAM!$A$21:$A$22
Name LISTE_1: PARAM!$A$21:$A$22
Name LISTE_1: PARAM!$A$21:$A$22
Name LISTE_1: PARAM!$A$21:$A$22
Name LISTE_1: PARAM!$A$21:$A$22
Name LISTE_1: PARAM!$A$21:$A$22
Name LISTE_1: PARAM!$A$21:$A$22
Name LISTE_1: PARAM!$A$21:$A$22
Name LISTE_1: PARAM!$A$21:$A$22
Name LISTE_1: PARAM!$A$21:$A$22
Name LISTE_1_a: '[1]#REF'!#REF!
Name LISTE_1_a: '[1]#REF'!#REF!
Name LISTE_1_a: '[1]#REF'!#REF!
Name LISTE_1_a: '[1]#REF'!#REF!
Name LISTE_1_a: '[1]#REF'!#REF!
Name LISTE_1_a: '[1]#REF'!#REF!
Name LISTE_1_a: '[1]#REF'!#REF!
Name LISTE_1_a: '[1]#REF'!#REF!
Name LISTE_2: PARAM!$B$21:$B$23
Name LISTE_2: PARAM!$B$21:$B$23
Name LISTE_2: PARAM!$B$21:$B$23
Name LISTE_2: PARAM!$B$21:$B$23
Name LISTE_2: PARAM!$B$21:$B$23
Name LISTE_2: PARAM!$B$21:$B$23
Name LISTE_2: PARAM!$B$21:$B$23
Name LISTE_2: PARAM!$B$21:$B$23
Name LISTE_2: PARAM!$B$21:$B$23
Name LISTE_2: PARAM!$B$21:$B$23
Name LISTE_2: PARAM!$B$21:$B$23
Name LISTE_2: PARAM!$B$21:$B$23
Name LISTE_2: PARAM!$B$21:$B$23
Name LISTE_3: PARAM!$C$21:$C$24
Name LISTE_3: PARAM!$C$21:$C$24
Name LISTE_3: PARAM!$C$21:$C$24
Name LISTE_3: PARAM!$C$21:$C$24

Sheet Descriptif
AC1: Ne rien mettre dans cette colonne | AD1: Ne rien mettre dans cette colonne | AE1: Ne rien mettre dans cette colonne | AF1: Ne rien mettre dans cette colonne | AG1: Ne rien mettre dans cette colonne | AH1: Ne rien mettre dans cette colonne | AI1: Ne rien mettre dans cette colonne | AJ1: Ne rien mettre dans cette colonne
C2: CONTRÔLE ANNUEL DES DISPOSITIFS D'AUTOSURVEILLANCE DES SYSTÈMES D'ASSAINISSEMENT COLLECTIF | AC2: début données sys collect | AD2: =ROW(E12)+1 -> 13 | AE2: fin données sys collect | AF2: =ROW(D15)-1 -> 14 | AG2: pluvio SCL | AH2: =ROW(E20)+1 -> 21 | AI2: =ROW(D23)-1 -> 22
C3: NOM DU SYSTÈME D'ASSAINISSEMENT : | G3: BARJAC (30) | K3: NOM SYSTÈME DE TRAITEMENT : | N3: BARJAC (30) | Q3: NOM SYSTÈME DE COLLECTE : | AC3: début données station | AD3: =ROW(E32)+1 -> 33 | AE3: fin données station | AF3: =ROW(D41)-1 -> 40 | AG3: pluvio STEU | AH3: =ROW(E46)+1 -> 47 | AI3: =ROW(D49)-1 -> 48
C4: CODE SANDRE DE L'AGGLOMERATION : | K4: CODE SANDRE DE LA STATION : | N4: 060930290002 | Q4: CODE SANDRE DU RESEAU :
C5: NOM DU MAITRE D'OUVRAGE : | G5: Commune de Barjac | K5: CAPACITE DE LA STATION : | N5: 5 000 EH | Q5: EXPLOITANT DU RESEAU :
C6: ORGANISME DE CONTRÔLE : | G6: CEREG Ingénierie | K6: EXPLOITANT DE LA STATION : | N6: Régie | Q6: ok
C8: SYSTÈME DE COLLECTE
D10: Liste des équipements du système de collecte par point
E12: Actif | F12: Lien vers l'onglet de l'équipement | H12: Point réglementaire | I12: Localisation (cf. MAS) | J12: Code du point (cf MAS) | K12: Libellé du point | M12: Type d'équipement | O12: Type de matériel | Q12: Pluviométre de référence | AC12: Liste préleveurs | AE12: Liste débimètres | AG12: Liste thermo | AI12: Liste pluvio
E13: Oui | F13: A1_DO1_Q_Grav | H13: A1 | I13: =IF(ISBLANK(A1_DO1_Q_Grav!J5), "", A1_DO1_Q_Grav!J5) -> A1 | J13: =IF(ISBLANK(A1_DO1_Q_Grav!J4), "", A1_DO1_Q_Grav!J4) -> DO1 | K13: =IF(ISBLANK(A1_DO1_Q_Grav!J3), "", A1_DO1_Q_Grav!J3) -> DO1 | M13: Débitmètre gravitaire | O13: =IF(ISBLANK(A1_DO1_Q_Grav!D40), "", A1_DO1_Q_Grav!D40) -> Seuil | S13: Gérer l'équipement | AB13: =ROW(A13)- $AD$2 +1 -> 1 | AC13: =IF(AND($E13="Oui",$M13="Préleveur"),$F13,"") | AD13: {=IFERROR(INDEX($AC$13:$AC$94,SMALL(IF($AC$13:$AC$94<>"",ROW($AC$13:$AC$94)-ROW(INDIRECT("$AC$13"))+1),ROW(INDIRECT("A" & AB13 ) ))),"")} -> A3_P102_PREL | AE13: =IF(AND($E13="Oui",LEFT($M13,10) ="Débitmètre"),$F13,"") -> A1_DO1_Q_Grav | AF13: {=IFERROR(INDEX($AE$13:$AE$94,SMALL(IF($AE$13:$AE$94<>"",ROW($AE$13:$AE$94)-ROW(INDIRECT("$AE$13"))+1),ROW(INDIRECT("A" & AB13 ) ))),"")} -> A1_DO1_Q_Grav | AG13: =IF(AND($E13="Oui",LEFT($M13,5) ="Sonde"),$F13,"") | AH13: {=IFERROR(INDEX($AG$13:$AG$94,SMALL(IF($AG$13:$AG$94<>"",ROW($AG$13:$AG$94)-ROW(INDIRECT("$AG$13"))+1),ROW(INDIRECT("A" & AB13 ) ))),"")} -> A4_P103_TEMP | AI13: =IF(AND($E13="Oui", $M13 <> "", $M13 = ""),$F13,"") | AJ13: {=IFERROR(INDEX($AI$13:$AI$94,SMALL(IF($AI$13:$AI$94<>"",ROW($AI$13:$AI$94)-ROW(INDIRECT("$AI$13"))+1),ROW(INDIRECT("A" & AB13 ) ))),"")} -> PLUVIO_SCL_ooo
AB14: =ROW(A14)- $AD$2 +1 -> 2 | AC14: =IF(AND($E14="Oui",$M14="Préleveur"),$F14,"") | AD14: {=IFERROR(INDEX($AC$13:$AC$94,SMALL(IF($AC$13:$AC$94<>"",ROW($AC$13:$AC$94)-ROW(INDIRECT("$AC$13"))+1),ROW(INDIRECT("A" & AB14 ) ))),"")} -> A4_P103_PREL | AE14: =IF(AND($E14="Oui",LEFT($M14,10) ="Débitmètre"),$F14,"") | AF14: {=IFERROR(INDEX($AE$13:$AE$94,SMALL(IF($AE$13:$AE$94<>"",ROW($AE$13:$AE$94)-ROW(INDIRECT("$AE$13"))+1),ROW(INDIRECT("A" & AB14 ) ))),"")} -> A2_P100_Q_Grav | AG14: =IF(AND($E14="Oui",LEFT($M14,5) ="Sonde"),$F14,"") | AH14: {=IFERROR(INDEX($AG$13:$AG$94,SMALL(IF($AG$13:$AG$94<>"",ROW($AG$13:$AG$94)-ROW(INDIRECT("$AG$13"))+1),ROW(INDIRECT("A" & AB14 ) ))),"")} | AI14: =IF(AND($E14="Oui",$F14<>"",$M14=""),$F14,"") | AJ14: {=IFERROR(INDEX($AI$14:$AI$96,SMALL(IF($AI$14:$AI$96<>"",ROW($AI$14:$AI$96)-ROW(INDIRECT("$AI$13"))+1),ROW(INDIRECT("A" & AB14 ) ))),"")} -> PLUVIO_STEU_ee
E15: Ajouter un équipement réseau | AB15: =ROW(A15)- $AD$2 +1 -> 3 | AC15: =IF(AND($E15="Oui",$M15="Préleveur"),$F15,"") | AD15: {=IFERROR(INDEX($AC$13:$AC$94,SMALL(IF($AC$13:$AC$94<>"",ROW($AC$13:$AC$94)-ROW(INDIRECT("$AC$13"))+1),ROW(INDIRECT("A" & AB15 ) ))),"")} | AE15: =IF(AND($E15="Oui",LEFT($M15,10) ="Débitmètre"),$F15,"") | AF15: {=IFERROR(INDEX($AE$13:$AE$94,SMALL(IF($AE$13:$AE$94<>"",ROW($AE$13:$AE$94)-ROW(INDIRECT("$AE$13"))+1),ROW(INDIRECT("A" & AB15 ) ))),"")} -> A3_P102_Q_DEM | AG15: =IF(AND($E15="Oui",LEFT($M15,5) ="Sonde"),$F15,"") | AH15: {=IFERROR(INDEX($AG$13:$AG$94,SMALL(IF($AG$13:$AG$94<>"",ROW($AG$13:$AG$94)-ROW(INDIRECT("$AG$13"))+1),ROW(INDIRECT("A" & AB15 ) ))),"")} | AI15: =IF(AND($E15="Oui",$F15<>"",$M15=""),$F15,"") | AJ15: {=IFERROR(INDEX($AI$14:$AI$96,SMALL(IF($AI$14:$AI$96<>"",ROW($AI$14:$AI$96)-ROW(INDIRECT("$AI$13"))+1),ROW(INDIRECT("A" & AB15 ) ))),"")}
AB16: =ROW(A16)- $AD$2 +1 -> 4 | AC16: =IF(AND($E16="Oui",$M16="Préleveur"),$F16,"") | AD16: {=IFERROR(INDEX($AC$13:$AC$94,SMALL(IF($AC$13:$AC$94<>"",ROW($AC$13:$AC$94)-ROW(INDIRECT("$AC$13"))+1),ROW(INDIRECT("A" & AB16 ) ))),"")} | AE16: =IF(AND($E16="Oui",LEFT($M16,10) ="Débitmètre"),$F16,"") | AF16: {=IFERROR(INDEX($AE$13:$AE$94,SMALL(IF($AE$13:$AE$94<>"",ROW($AE$13:$AE$94)-ROW(INDIRECT("$AE$13"))+1),ROW(INDIRECT("A" & AB16 ) ))),"")} -> A4_P103_Q_Grav | AG16: =IF(AND($E16="Oui",LEFT($M16,5) ="Sonde"),$F16,"") | AH16: {=IFERROR(INDEX($AG$13:$AG$94,SMALL(IF($AG$13:$AG$94<>"",ROW($AG$13:$AG$94)-ROW(INDIRECT("$AG$13"))+1),ROW(INDIRECT("A" & AB16 ) ))),"")} | AI16: =IF(AND($E16="Oui",$F16<>"",$M16=""),$F16,"") | AJ16: {=IFERROR(INDEX($AI$14:$AI$96,SMALL(IF($AI$14:$AI$96<>"",ROW($AI$14:$AI$96)-ROW(INDIRECT("$AI$13"))+1),ROW(INDIRECT("A" & AB16 ) ))),"")}
AB17: =ROW(A17)- $AD$2 +1 -> 5 | AC17: =IF(AND($E17="Oui",$M17="Préleveur"),$F17,"") | AD17: {=IFERROR(INDEX($AC$13:$AC$94,SMALL(IF($AC$13:$AC$94<>"",ROW($AC$13:$AC$94)-ROW(INDIRECT("$AC$13"))+1),ROW(INDIRECT("A" & AB17 ) ))),"")} | AE17: =IF(AND($E17="Oui",LEFT($M17,10) ="Débitmètre"),$F17,"") | AF17: {=IFERROR(INDEX($AE$13:$AE$94,SMALL(IF($AE$13:$AE$94<>"",ROW($AE$13:$AE$94)-ROW(INDIRECT("$AE$13"))+1),ROW(INDIRECT("A" & AB17 ) ))),"")} -> A6_P104_Q_DEM | AG17: =IF(AND($E17="Oui",LEFT($M17,5) ="Sonde"),$F17,"") | AH17: {=IFERROR(INDEX($AG$13:$AG$94,SMALL(IF($AG$13:$AG$94<>"",ROW($AG$13:$AG$94)-ROW(INDIRECT("$AG$13"))+1),ROW(INDIRECT("A" & AB17 ) ))),"")} | AI17: =IF(AND($E17="Oui",$F17<>"",$M17=""),$F17,"") | AJ17: {=IFERROR(INDEX($AI$14:$AI$96,SMALL(IF($AI$14:$AI$96<>"",ROW($AI$14:$AI$96)-ROW(INDIRECT("$AI$13"))+1),ROW(INDIRECT("A" & AB17 ) ))),"")}
D18: Liste des pluviomètres du réseau | AB18: =ROW(A18)- $AD$2 +1 -> 6 | AC18: =IF(AND($E18="Oui",$M18="Préleveur"),$F18,"") | AD18: {=IFERROR(INDEX($AC$13:$AC$94,SMALL(IF($AC$13:$AC$94<>"",ROW($AC$13:$AC$94)-ROW(INDIRECT("$AC$13"))+1),ROW(INDIRECT("A" & AB18 ) ))),"")} | AE18: =IF(AND($E18="Oui",LEFT($M18,10) ="Débitmètre"),$F18,"") | AF18: {=IFERROR(INDEX($AE$14:$AE$96,SMALL(IF($AE$14:$AE$96<>"",ROW($AE$14:$AE$96)-ROW(INDIRECT("$AE$13"))+1),ROW(INDIRECT("A" & AB18 ) ))),"")} | AG18: =IF(AND($E18="Oui",LEFT($M18,5) ="Sonde"),$F18,"") | AH18: {=IFERROR(INDEX($AG$13:$AG$94,SMALL(IF($AG$13:$AG$94<>"",ROW($AG$13:$AG$94)-ROW(INDIRECT("$AG$13"))+1),ROW(INDIRECT("A" & AB18 ) ))),"")} | AI18: =IF(AND($E18="Oui",$F18<>"",$M18=""),$F18,"") | AJ18: {=IFERROR(INDEX($AI$14:$AI$96,SMALL(IF($AI$14:$AI$96<>"",ROW($AI$14:$AI$96)-ROW(INDIRECT("$AI$13"))+1),ROW(INDIRECT("A" & AB18 ) ))),"")}
AB19: =ROW(A19)- $AD$2 +1 -> 7 | AC19: =IF(AND($E19="Oui",$M19="Préleveur"),$F19,"") | AD19: {=IFERROR(INDEX($AC$13:$AC$94,SMALL(IF($AC$13:$AC$94<>"",ROW($AC$13:$AC$94)-ROW(INDIRECT("$AC$13"))+1),ROW(INDIRECT("A" & AB19 ) ))),"")} | AE19: =IF(AND($E19="Oui",LEFT($M19,10) ="Débitmètre"),$F19,"") | AF19: {=IFERROR(INDEX($AE$14:$AE$96,SMALL(IF($AE$14:$AE$96<>"",ROW($AE$14:$AE$96)-ROW(INDIRECT("$AE$13"))+1),ROW(INDIRECT("A" & AB19 ) ))),"")} | AG19: =IF(AND($E19="Oui",LEFT($M19,5) ="Sonde"),$F19,"") | AH19: {=IFERROR(INDEX($AG$13:$AG$94,SMALL(IF($AG$13:$AG$94<>"",ROW($AG$13:$AG$94)-ROW(INDIRECT("$AG$13"))+1),ROW(INDIRECT("A" & AB19 ) ))),"")} | AI19: =IF(AND($E19="Oui",$F19<>"",$M19=""),$F19,"") | AJ19: {=IFERROR(INDEX($AI$14:$AI$96,SMALL(IF($AI$14:$AI$96<>"",ROW($AI$14:$AI$96)-ROW(INDIRECT("$AI$13"))+1),ROW(INDIRECT("A" & AB19 ) ))),"")}
E20: Actif | F20: Lien vers l'onglet de l'équipement | AB20: =ROW(A20)- $AD$2 +1 -> 8 | AC20: =IF(AND($E20="Oui",$M20="Préleveur"),$F20,"") | AD20: {=IFERROR(INDEX($AC$13:$AC$94,SMALL(IF($AC$13:$AC$94<>"",ROW($AC$13:$AC$94)-ROW(INDIRECT("$AC$13"))+1),ROW(INDIRECT("A" & AB20 ) ))),"")} | AE20: =IF(AND($E20="Oui",LEFT($M20,10) ="Débitmètre"),$F20,"") | AF20: {=IFERROR(INDEX($AE$14:$AE$96,SMALL(IF($AE$14:$AE$96<>"",ROW($AE$14:$AE$96)-ROW(INDIRECT("$AE$13"))+1),ROW(INDIRECT("A" & AB20 ) ))),"")} | AG20: =IF(AND($E20="Oui",LEFT($M20,5) ="Sonde"),$F20,"") | AH20: {=IFERROR(INDEX($AG$14:$AG$96,SMALL(IF($AG$14:$AG$96<>"",ROW($AG$14:$AG$96)-ROW(INDIRECT("$AG$13"))+1),ROW(INDIRECT("A" & AB20 ) ))),"")} | AI20: =IF(AND($E20="Oui",$F20<>"",$M20=""),$F20,"") | AJ20: {=IFERROR(INDEX($AI$14:$AI$96,SMALL(IF($AI$14:$AI$96<>"",ROW($AI$14:$AI$96)-ROW(INDIRECT("$AI$13"))+1),ROW(INDIRECT("A" & AB20 ) ))),"")}
E21: Oui | F21: PLUVIO_SCL_ooo | H21: Gérer l'équipement | AB21: =ROW(A21)- $AD$2 +1 -> 9 | AC21: =IF(AND($E21="Oui",$M21="Préleveur"),$F21,"") | AD21: {=IFERROR(INDEX($AC$13:$AC$94,SMALL(IF($AC$13:$AC$94<>"",ROW($AC$13:$AC$94)-ROW(INDIRECT("$AC$13"))+1),ROW(INDIRECT("A" & AB21 ) ))),"")} | AE21: =IF(AND($E21="Oui",LEFT($M21,10) ="Débitmètre"),$F21,"") | AF21: {=IFERROR(INDEX($AE$14:$AE$96,SMALL(IF($AE$14:$AE$96<>"",ROW($AE$14:$AE$96)-ROW(INDIRECT("$AE$13"))+1),ROW(INDIRECT("A" & AB21 ) ))),"")} | AG21: =IF(AND($E21="Oui",LEFT($M21,5) ="Sonde"),$F21,"") | AH21: {=IFERROR(INDEX($AG$14:$AG$96,SMALL(IF($AG$14:$AG$96<>"",ROW($AG$14:$AG$96)-ROW(INDIRECT("$AG$13"))+1),ROW(INDIRECT("A" & AB21 ) ))),"")} | AI21: =IF(AND($E21="Oui",$F21<>"",$M21=""),$F21,"") -> PLUVIO_SCL_ooo | AJ21: {=IFERROR(INDEX($AI$14:$AI$96,SMALL(IF($AI$14:$AI$96<>"",ROW($AI$14:$AI$96)-ROW(INDIRECT("$AI$13"))+1),ROW(INDIRECT("A" & AB21 ) ))),"")}
E23: Ajouter un pluviomètre réseau | K23: Si pas de pluviomètre, veuillez ajouter en commentaire la provenance des données : | AB23: =ROW(A23)- $AD$2 +1 -> 11 | AC23: =IF(AND($E23="Oui",$M23="Préleveur"),$F23,"") | AD23: {=IFERROR(INDEX($AC$13:$AC$94,SMALL(IF($AC$13:$AC$94<>"",ROW($AC$13:$AC$94)-ROW(INDIRECT("$AC$13"))+1),ROW(INDIRECT("A" & AB23 ) ))),"")} | AE23: =IF(AND($E23="Oui",LEFT($M23,10) ="Débitmètre"),$F23,"") | AF23: {=IFERROR(INDEX($AE$14:$AE$96,SMALL(IF($AE$14:$AE$96<>"",ROW($AE$14:$AE$96)-ROW(INDIRECT("$AE$13"))+1),ROW(INDIRECT("A" & AB23 ) ))),"")} | AG23: =IF(AND($E23="Oui",LEFT($M23,5) ="Sonde"),$F23,"") | AH23: {=IFERROR(INDEX($AG$14:$AG$96,SMALL(IF($AG$14:$AG$96<>"",ROW($AG$14:$AG$96)-ROW(INDIRECT("$AG$13"))+1),ROW(INDIRECT("A" & AB23 ) ))),"")} | AI23: =IF(AND($E23="Oui",$F23<>"",$M23=""),$F23,"") | AJ23: {=IFERROR(INDEX($AI$14:$AI$96,SMALL(IF($AI$14:$AI$96<>"",ROW($AI$14:$AI$96)-ROW(INDIRECT("$AI$13"))+1),ROW(INDIRECT("A" & AB23 ) ))),"")}
AB24: =ROW(A24)- $AD$2 +1 -> 12 | AC24: =IF(AND($E24="Oui",$M24="Préleveur"),$F24,"") | AD24: {=IFERROR(INDEX($AC$14:$AC$96,SMALL(IF($AC$14:$AC$96<>"",ROW($AC$14:$AC$96)-ROW(INDIRECT("$AC$13"))+1),ROW(INDIRECT("A" & AB24 ) ))),"")} | AE24: =IF(AND($E24="Oui",LEFT($M24,10) ="Débitmètre"),$F24,"") | AF24: {=IFERROR(INDEX($AE$14:$AE$96,SMALL(IF($AE$14:$AE$96<>"",ROW($AE$14:$AE$96)-ROW(INDIRECT("$AE$13"))+1),ROW(INDIRECT("A" & AB24 ) ))),"")} | AG24: =IF(AND($E24="Oui",LEFT($M24,5) ="Sonde"),$F24,"") | AH24: {=IFERROR(INDEX($AG$14:$AG$96,SMALL(IF($AG$14:$AG$96<>"",ROW($AG$14:$AG$96)-ROW(INDIRECT("$AG$13"))+1),ROW(INDIRECT("A" & AB24 ) ))),"")} | AI24: =IF(AND($E24="Oui",$F24<>"",$M24=""),$F24,"") | AJ24: {=IFERROR(INDEX($AI$14:$AI$96,SMALL(IF($AI$14:$AI$96<>"",ROW($AI$14:$AI$96)-ROW(INDIRECT("$AI$13"))+1),ROW(INDIRECT("A" & AB24 ) ))),"")}
AB25: =ROW(A25)- $AD$2 +1 -> 13 | AC25: =IF(AND($E25="Oui",$M25="Préleveur"),$F25,"") | AD25: {=IFERROR(INDEX($AC$14:$AC$96,SMALL(IF($AC$14:$AC$96<>"",ROW($AC$14:$AC$96)-ROW(INDIRECT("$AC$13"))+1),ROW(INDIRECT("A" & AB25 ) ))),"")} | AE25: =IF(AND($E25="Oui",LEFT($M25,10) ="Débitmètre"),$F25,"") | AF25: {=IFERROR(INDEX($AE$14:$AE$96,SMALL(IF($AE$14:$AE$96<>"",ROW($AE$14:$AE$96)-ROW(INDIRECT("$AE$13"))+1),ROW(INDIRECT("A" & AB25 ) ))),"")} | AG25: =IF(AND($E25="Oui",LEFT($M25,5) ="Sonde"),$F25,"") | AH25: {=IFERROR(INDEX($AG$14:$AG$96,SMALL(IF($AG$14:$AG$96<>"",ROW($AG$14:$AG$96)-ROW(INDIRECT("$AG$13"))+1),ROW(INDIRECT("A" & AB25 ) ))),"")} | AI25: =IF(AND($E25="Oui",$F25<>"",$M25=""),$F25,"") | AJ25: {=IFERROR(INDEX($AI$14:$AI$96,SMALL(IF($AI$14:$AI$96<>"",ROW($AI$14:$AI$96)-ROW(INDIRECT("$AI$13"))+1),ROW(INDIRECT("A" & AB25 ) ))),"")}
AB26: =ROW(A26)- $AD$2 +1 -> 14 | AC26: =IF(AND($E26="Oui",$M26="Préleveur"),$F26,"") | AD26: {=IFERROR(INDEX($AC$14:$AC$96,SMALL(IF($AC$14:$AC$96<>"",ROW($AC$14:$AC$96)-ROW(INDIRECT("$AC$13"))+1),ROW(INDIRECT("A" & AB26 ) ))),"")} | AE26: =IF(AND($E26="Oui",LEFT($M26,10) ="Débitmètre"),$F26,"") | AF26: {=IFERROR(INDEX($AE$14:$AE$96,SMALL(IF($AE$14:$AE$96<>"",ROW($AE$14:$AE$96)-ROW(INDIRECT("$AE$13"))+1),ROW(INDIRECT("A" & AB26 ) ))),"")} | AG26: =IF(AND($E26="Oui",LEFT($M26,5) ="Sonde"),$F26,"") | AH26: {=IFERROR(INDEX($AG$14:$AG$96,SMALL(IF($AG$14:$AG$96<>"",ROW($AG$14:$AG$96)-ROW(INDIRECT("$AG$13"))+1),ROW(INDIRECT("A" & AB26 ) ))),"")} | AI26: =IF(AND($E26="Oui",$F26<>"",$M26=""),$F26,"") | AJ26: {=IFERROR(INDEX($AI$14:$AI$96,SMALL(IF($AI$14:$AI$96<>"",ROW($AI$14:$AI$96)-ROW(INDIRECT("$AI$13"))+1),ROW(INDIRECT("A" & AB26 ) ))),"")}
AB27: =ROW(A27)- $AD$2 +1 -> 15 | AC27: =IF(AND($E27="Oui",$M27="Préleveur"),$F27,"") | AD27: {=IFERROR(INDEX($AC$14:$AC$96,SMALL(IF($AC$14:$AC$96<>"",ROW($AC$14:$AC$96)-ROW(INDIRECT("$AC$13"))+1),ROW(INDIRECT("A" & AB27 ) ))),"")} | AE27: =IF(AND($E27="Oui",LEFT($M27,10) ="Débitmètre"),$F27,"") | AF27: {=IFERROR(INDEX($AE$14:$AE$96,SMALL(IF($AE$14:$AE$96<>"",ROW($AE$14:$AE$96)-ROW(INDIRECT("$AE$13"))+1),ROW(INDIRECT("A" & AB27 ) ))),"")} | AG27: =IF(AND($E27="Oui",LEFT($M27,5) ="Sonde"),$F27,"") | AH27: {=IFERROR(INDEX($AG$14:$AG$96,SMALL(IF($AG$14:$AG$96<>"",ROW($AG$14:$AG$96)-ROW(INDIRECT("$AG$13"))+1),ROW(INDIRECT("A" & AB27 ) ))),"")} | AI27: =IF(AND($E27="Oui",$F27<>"",$M27=""),$F27,"") | AJ27: {=IFERROR(INDEX($AI$14:$AI$96,SMALL(IF($AI$14:$AI$96<>"",ROW($AI$14:$AI$96)-ROW(INDIRECT("$AI$13"))+1),ROW(INDIRECT("A" & AB27 ) ))),"")}
C28: SYSTÈME DE TRAITEMENT | AB28: =ROW(A28)- $AD$2 +1 -> 16 | AC28: =IF(AND($E28="Oui",$M28="Préleveur"),$F28,"") | AD28: {=IFERROR(INDEX($AC$14:$AC$96,SMALL(IF($AC$14:$AC$96<>"",ROW($AC$14:$AC$96)-ROW(INDIRECT("$AC$13"))+1),ROW(INDIRECT("A" & AB28 ) ))),"")} | AE28: =IF(AND($E28="Oui",LEFT($M28,10) ="Débitmètre"),$F28,"") | AF28: {=IFERROR(INDEX($AE$14:$AE$96,SMALL(IF($AE$14:$AE$96<>"",ROW($AE$14:$AE$96)-ROW(INDIRECT("$AE$13"))+1),ROW(INDIRECT("A" & AB28 ) ))),"")} | AG28: =IF(AND($E28="Oui",LEFT($M28,5) ="Sonde"),$F28,"") | AH28: {=IFERROR(INDEX($AG$14:$AG$96,SMALL(IF($AG$14:$AG$96<>"",ROW($AG$14:$AG$96)-ROW(INDIRECT("$AG$13"))+1),ROW(INDIRECT("A" & AB28 ) ))),"")} | AI28: =IF(AND($E28="Oui",$F28<>"",$M28=""),$F28,"") | AJ28: {=IFERROR(INDEX($AI$14:$AI$96,SMALL(IF($AI$14:$AI$96<>"",ROW($AI$14:$AI$96)-ROW(INDIRECT("$AI$13"))+1),ROW(INDIRECT("A" & AB28 ) ))),"")}
AB29: =ROW(A29)- $AD$2 +1 -> 17 | AC29: =IF(AND($E29="Oui",$M29="Préleveur"),$F29,"") | AD29: {=IFERROR(INDEX($AC$14:$AC$96,SMALL(IF($AC$14:$AC$96<>"",ROW($AC$14:$AC$96)-ROW(INDIRECT("$AC$13"))+1),ROW(INDIRECT("A" & AB29 ) ))),"")} | AE29: =IF(AND($E29="Oui",LEFT($M29,10) ="Débitmètre"),$F29,"") | AF29: {=IFERROR(INDEX($AE$14:$AE$96,SMALL(IF($AE$14:$AE$96<>"",ROW($AE$14:$AE$96)-ROW(INDIRECT("$AE$13"))+1),ROW(INDIRECT("A" & AB29 ) ))),"")} | AG29: =IF(AND($E29="Oui",LEFT($M29,5) ="Sonde"),$F29,"") | AH29: {=IFERROR(INDEX($AG$14:$AG$96,SMALL(IF($AG$14:$AG$96<>"",ROW($AG$14:$AG$96)-ROW(INDIRECT("$AG$13"))+1),ROW(INDIRECT("A" & AB29 ) ))),"")} | AI29: =IF(AND($E29="Oui",$F29<>"",$M29=""),$F29,"") | AJ29: {=IFERROR(INDEX($AI$14:$AI$96,SMALL(IF($AI$14:$AI$96<>"",ROW($AI$14:$AI$96)-ROW(INDIRECT("$AI$13"))+1),ROW(INDIRECT("A" & AB29 ) ))),"")}
D30: Liste des équipements du système de traitement | AB30: =ROW(A30)- $AD$2 +1 -> 18 | AC30: =IF(AND($E30="Oui",$M30="Préleveur"),$F30,"") | AD30: {=IFERROR(INDEX($AC$14:$AC$96,SMALL(IF($AC$14:$AC$96<>"",ROW($AC$14:$AC$96)-ROW(INDIRECT("$AC$13"))+1),ROW(INDIRECT("A" & AB30 ) ))),"")} | AE30: =IF(AND($E30="Oui",LEFT($M30,10) ="Débitmètre"),$F30,"") | AF30: {=IFERROR(INDEX($AE$14:$AE$96,SMALL(IF($AE$14:$AE$96<>"",ROW($AE$14:$AE$96)-ROW(INDIRECT("$AE$13"))+1),ROW(INDIRECT("A" & AB30 ) ))),"")} | AG30: =IF(AND($E30="Oui",LEFT($M30,5) ="Sonde"),$F30,"") | AH30: {=IFERROR(INDEX($AG$14:$AG$96,SMALL(IF($AG$14:$AG$96<>"",ROW($AG$14:$AG$96)-ROW(INDIRECT("$AG$13"))+1),ROW(INDIRECT("A" & AB30 ) ))),"")} | AI30: =IF(AND($E30="Oui",$F30<>"",$M30=""),$F30,"") | AJ30: {=IFERROR(INDEX($AI$14:$AI$96,SMALL(IF($AI$14:$AI$96<>"",ROW($AI$14:$AI$96)-ROW(INDIRECT("$AI$13"))+1),ROW(INDIRECT("A" & AB30 ) ))),"")}
K31: mettre plutôt libellé de la localisation | P31: ok | AB31: =ROW(A31)- $AD$2 +1 -> 19 | AC31: =IF(AND($E31="Oui",$M31="Préleveur"),$F31,"") | AD31: {=IFERROR(INDEX($AC$14:$AC$96,SMALL(IF($AC$14:$AC$96<>"",ROW($AC$14:$AC$96)-ROW(INDIRECT("$AC$13"))+1),ROW(INDIRECT("A" & AB31 ) ))),"")} | AE31: =IF(AND($E31="Oui",LEFT($M31,10) ="Débitmètre"),$F31,"") | AF31: {=IFERROR(INDEX($AE$14:$AE$96,SMALL(IF($AE$14:$AE$96<>"",ROW($AE$14:$AE$96)-ROW(INDIRECT("$AE$13"))+1),ROW(INDIRECT("A" & AB31 ) ))),"")} | AG31: =IF(AND($E31="Oui",LEFT($M31,5) ="Sonde"),$F31,"") | AH31: {=IFERROR(INDEX($AG$14:$AG$96,SMALL(IF($AG$14:$AG$96<>"",ROW($AG$14:$AG$96)-ROW(INDIRECT("$AG$13"))+1),ROW(INDIRECT("A" & AB31 ) ))),"")} | AI31: =IF(AND($E31="Oui",$F31<>"",$M31=""),$F31,"") | AJ31: {=IFERROR(INDEX($AI$14:$AI$96,SMALL(IF($AI$14:$AI$96<>"",ROW($AI$14:$AI$96)-ROW(INDIRECT("$AI$13"))+1),ROW(INDIRECT("A" & AB31 ) ))),"")}
E32: Actif | F32: Lien vers l'onglet de l'équipement | H32: Point réglementaire | I32: Localisation (cf. MAS) | J32: Code du point (cf. MAS) | K32: Libellé du point | M32: Type d'équipement | O32: Type de matériel | AB32: =ROW(A32)- $AD$2 +1 -> 20 | AC32: =IF(AND($E32="Oui",$M32="Préleveur"),$F32,"") | AD32: {=IFERROR(INDEX($AC$14:$AC$96,SMALL(IF($AC$14:$AC$96<>"",ROW($AC$14:$AC$96)-ROW(INDIRECT("$AC$13"))+1),ROW(INDIRECT("A" & AB32 ) ))),"")} | AE32: =IF(AND($E32="Oui",LEFT($M32,10) ="Débitmètre"),$F32,"") | AF32: {=IFERROR(INDEX($AE$14:$AE$96,SMALL(IF($AE$14:$AE$96<>"",ROW($AE$14:$AE$96)-ROW(INDIRECT("$AE$13"))+1),ROW(INDIRECT("A" & AB32 ) ))),"")} | AG32: =IF(AND($E32="Oui",LEFT($M32,5) ="Sonde"),$F32,"") | AH32: {=IFERROR(INDEX($AG$14:$AG$96,SMALL(IF($AG$14:$AG$96<>"",ROW($AG$14:$AG$96)-ROW(INDIRECT("$AG$13"))+1),ROW(INDIRECT("A" & AB32 ) ))),"")} | AI32: =IF(AND($E32="Oui",$F32<>"",$M32=""),$F32,"") | AJ32: {=IFERROR(INDEX($AI$14:$AI$96,SMALL(IF($AI$14:$AI$96<>"",ROW($AI$14:$AI$96)-ROW(INDIRECT("$AI$13"))+1),ROW(INDIRECT("A" & AB32 ) ))),"")}
E33: Oui | F33: A2_P100_Q_Grav | H33: A2 | I33: =IF(ISBLANK(A2_P100_Q_Grav!J5), "", A2_P100_Q_Grav!J5) -> A2 | J33: =IF(ISBLANK(A2_P100_Q_Grav!J4), "", A2_P100_Q_Grav!J4) -> P100 | K33: =IF(ISBLANK(A2_P100_Q_Grav!J3), "", A2_P100_Q_Grav!J3) -> test | M33: Débitmètre gravitaire | O33: =IF(ISBLANK(A2_P100_Q_Grav!D40), "", A2_P100_Q_Grav!D40) -> Hauteur/Vitesse | R33: Gérer l'équipement | AB33: =ROW(A33)- $AD$2 +1 -> 21 | AC33: =IF(AND($E33="Oui",$M33="Préleveur"),$F33,"") | AD33: {=IFERROR(INDEX($AC$14:$AC$93,SMALL(IF($AC$14:$AC$93<>"",ROW($AC$14:$AC$93)-ROW(INDIRECT("$AC$13"))+1),ROW(INDIRECT("A" & AB33 ) ))),"")} | AE33: =IF(AND($E33="Oui",LEFT($M33,10) ="Débitmètre"),$F33,"") -> A2_P100_Q_Grav | AF33: {=IFERROR(INDEX($AE$14:$AE$93,SMALL(IF($AE$14:$AE$93<>"",ROW($AE$14:$AE$93)-ROW(INDIRECT("$AE$13"))+1),ROW(INDIRECT("A" & AB33 ) ))),"")} | AG33: =IF(AND($E33="Oui",LEFT($M33,5) ="Sonde"),$F33,"") | AH33: {=IFERROR(INDEX($AG$14:$AG$93,SMALL(IF($AG$14:$AG$93<>"",ROW($AG$14:$AG$93)-ROW(INDIRECT("$AG$13"))+1),ROW(INDIRECT("A" & AB33 ) ))),"")} | AI33: =IF(AND($E33="Oui", $M33 <> "", $M33 = ""),$F33,"") | AJ33: {=IFERROR(INDEX($AI$14:$AI$93,SMALL(IF($AI$14:$AI$93<>"",ROW($AI$14:$AI$93)-ROW(INDIRECT("$AI$13"))+1),ROW(INDIRECT("A" & AB33 ) ))),"")}
E34: Oui | F34: A3_P102_Q_DEM | H34: A3 | I34: =IF(ISBLANK(A3_P102_Q_DEM!J5), "", A3_P102_Q_DEM!J5) -> A3 | J34: =IF(ISBLANK(A3_P102_Q_DEM!J4), "", A3_P102_Q_DEM!J4) -> P102 | K34: =IF(ISBLANK(A3_P102_Q_DEM!J3), "", A3_P102_Q_DEM!J3) -> P102 | M34: Débitmètre en charge | O34: =IF(ISBLANK(A3_P102_Q_DEM!D32), "", A3_P102_Q_DEM!D32) -> Débitmètre électromagnétique (eau) | R34: Gérer l'équipement | AB34: =ROW(A34)- $AD$2 +1 -> 22 | AC34: =IF(AND($E34="Oui",$M34="Préleveur"),$F34,"") | AD34: {=IFERROR(INDEX($AC$14:$AC$95,SMALL(IF($AC$14:$AC$95<>"",ROW($AC$14:$AC$95)-ROW(INDIRECT("$AC$13"))+1),ROW(INDIRECT("A" & AB34 ) ))),"")} | AE34: =IF(AND($E34="Oui",LEFT($M34,10) ="Débitmètre"),$F34,"") -> A3_P102_Q_DEM | AF34: {=IFERROR(INDEX($AE$14:$AE$95,SMALL(IF($AE$14:$AE$95<>"",ROW($AE$14:$AE$95)-ROW(INDIRECT("$AE$13"))+1),ROW(INDIRECT("A" & AB34 ) ))),"")} | AG34: =IF(AND($E34="Oui",LEFT($M34,5) ="Sonde"),$F34,"") | AH34: {=IFERROR(INDEX($AG$14:$AG$95,SMALL(IF($AG$14:$AG$95<>"",ROW($AG$14:$AG$95)-ROW(INDIRECT("$AG$13"))+1),ROW(INDIRECT("A" & AB34 ) ))),"")} | AI34: =IF(AND($E34="Oui", $M34 <> "", $M34 = ""),$F34,"") | AJ34: {=IFERROR(INDEX($AI$14:$AI$95,SMALL(IF($AI$14:$AI$95<>"",ROW($AI$14:$AI$95)-ROW(INDIRECT("$AI$13"))+1),ROW(INDIRECT("A" & AB34 ) ))),"")}
E35: Oui | F35: A3_P102_PREL | H35: A3 | I35: =IF(ISBLANK(A3_P102_PREL!J5), "", A3_P102_PREL!J5) -> A3 | J35: =IF(ISBLANK(A3_P102_PREL!J4), "", A3_P102_PREL!J4) -> P102 | K35: =IF(ISBLANK(A3_P102_PREL!J3), "", A3_P102_PREL!J3) -> P102 | M35: Préleveur | O35: =IF(ISBLANK(A3_P102_PREL!D37), "", A3_P102_PREL!D37) -> Préleveur Automatique | R35: Gérer l'équipement | AB35: =ROW(A35)- $AD$2 +1 -> 23 | AC35: =IF(AND($E35="Oui",$M35="Préleveur"),$F35,"") -> A3_P102_PREL | AD35: {=IFERROR(INDEX($AC$14:$AC$98,SMALL(IF($AC$14:$AC$98<>"",ROW($AC$14:$AC$98)-ROW(INDIRECT("$AC$13"))+1),ROW(INDIRECT("A" & AB35 ) ))),"")} | AE35: =IF(AND($E35="Oui",LEFT($M35,10) ="Débitmètre"),$F35,"") | AF35: {=IFERROR(INDEX($AE$14:$AE$98,SMALL(IF($AE$14:$AE$98<>"",ROW($AE$14:$AE$98)-ROW(INDIRECT("$AE$13"))+1),ROW(INDIRECT("A" & AB35 ) ))),"")} | AG35: =IF(AND($E35="Oui",LEFT($M35,5) ="Sonde"),$F35,"") | AH35: {=IFERROR(INDEX($AG$14:$AG$98,SMALL(IF($AG$14:$AG$98<>"",ROW($AG$14:$AG$98)-ROW(INDIRECT("$AG$13"))+1),ROW(INDIRECT("A" & AB35 ) ))),"")} | AI35: =IF(AND($E35="Oui", $M35 <> "", $M35 = ""),$F35,"") | AJ35: {=IFERROR(INDEX($AI$14:$AI$98,SMALL(IF($AI$14:$AI$98<>"",ROW($AI$14:$AI$98)-ROW(INDIRECT("$AI$13"))+1),ROW(INDIRECT("A" & AB35 ) ))),"")}
E36: Oui | F36: A4_P103_Q_Grav | H36: A4 | I36: =IF(ISBLANK(A4_P103_Q_Grav!J5), "", A4_P103_Q_Grav!J5) -> A4 | J36: =IF(ISBLANK(A4_P103_Q_Grav!J4), "", A4_P103_Q_Grav!J4) -> P103 | K36: =IF(ISBLANK(A4_P103_Q_Grav!J3), "", A4_P103_Q_Grav!J3) -> P103 | M36: Débitmètre gravitaire | O36: =IF(ISBLANK(A4_P103_Q_Grav!D40), "", A4_P103_Q_Grav!D40) -> Canal Venturi | R36: Gérer l'équipement | AB36: =ROW(A36)- $AD$2 +1 -> 24 | AC36: =IF(AND($E36="Oui",$M36="Préleveur"),$F36,"") | AD36: {=IFERROR(INDEX($AC$14:$AC$98,SMALL(IF($AC$14:$AC$98<>"",ROW($AC$14:$AC$98)-ROW(INDIRECT("$AC$13"))+1),ROW(INDIRECT("A" & AB36 ) ))),"")} | AE36: =IF(AND($E36="Oui",LEFT($M36,10) ="Débitmètre"),$F36,"") -> A4_P103_Q_Grav | AF36: {=IFERROR(INDEX($AE$14:$AE$98,SMALL(IF($AE$14:$AE$98<>"",ROW($AE$14:$AE$98)-ROW(INDIRECT("$AE$13"))+1),ROW(INDIRECT("A" & AB36 ) ))),"")} | AG36: =IF(AND($E36="Oui",LEFT($M36,5) ="Sonde"),$F36,"") | AH36: {=IFERROR(INDEX($AG$14:$AG$98,SMALL(IF($AG$14:$AG$98<>"",ROW($AG$14:$AG$98)-ROW(INDIRECT("$AG$13"))+1),ROW(INDIRECT("A" & AB36 ) ))),"")} | AI36: =IF(AND($E36="Oui", $M36 <> "", $M36 = ""),$F36,"") | AJ36: {=IFERROR(INDEX($AI$14:$AI$98,SMALL(IF($AI$14:$AI$98<>"",ROW($AI$14:$AI$98)-ROW(INDIRECT("$AI$13"))+1),ROW(INDIRECT("A" & AB36 ) ))),"")}
E37: Oui | F37: A4_P103_PREL | H37: A4 | I37: =IF(ISBLANK(A4_P103_PREL!J5), "", A4_P103_PREL!J5) -> A4 | J37: =IF(ISBLANK(A4_P103_PREL!J4), "", A4_P103_PREL!J4) -> P103 | K37: =IF(ISBLANK(A4_P103_PREL!J3), "", A4_P103_PREL!J3) -> P103 | M37: Préleveur | O37: =IF(ISBLANK(A4_P103_PREL!D37), "", A4_P103_PREL!D37) -> Préleveur Automatique | R37: Gérer l'équipement | AB37: =ROW(A37)- $AD$2 +1 -> 25 | AC37: =IF(AND($E37="Oui",$M37="Préleveur"),$F37,"") -> A4_P103_PREL | AD37: {=IFERROR(INDEX($AC$14:$AC$97,SMALL(IF($AC$14:$AC$97<>"",ROW($AC$14:$AC$97)-ROW(INDIRECT("$AC$13"))+1),ROW(INDIRECT("A" & AB37 ) ))),"")} | AE37: =IF(AND($E37="Oui",LEFT($M37,10) ="Débitmètre"),$F37,"") | AF37: {=IFERROR(INDEX($AE$14:$AE$97,SMALL(IF($AE$14:$AE$97<>"",ROW($AE$14:$AE$97)-ROW(INDIRECT("$AE$13"))+1),ROW(INDIRECT("A" & AB37 ) ))),"")} | AG37: =IF(AND($E37="Oui",LEFT($M37,5) ="Sonde"),$F37,"") | AH37: {=IFERROR(INDEX($AG$14:$AG$97,SMALL(IF($AG$14:$AG$97<>"",ROW($AG$14:$AG$97)-ROW(INDIRECT("$AG$13"))+1),ROW(INDIRECT("A" & AB37 ) ))),"")} | AI37: =IF(AND($E37="Oui", $M37 <> "", $M37 = ""),$F37,"") | AJ37: {=IFERROR(INDEX($AI$14:$AI$97,SMALL(IF($AI$14:$AI$97<>"",ROW($AI$14:$AI$97)-ROW(INDIRECT("$AI$13"))+1),ROW(INDIRECT("A" & AB37 ) ))),"")}
E38: Oui | F38: A6_P104_Q_DEM | H38: A6 | I38: =IF(ISBLANK(A6_P104_Q_DEM!J5), "", A6_P104_Q_DEM!J5) -> A6 | J38: =IF(ISBLANK(A6_P104_Q_DEM!J4), "", A6_P104_Q_DEM!J4) -> P104 | K38: =IF(ISBLANK(A6_P104_Q_DEM!J3), "", A6_P104_Q_DEM!J3) -> P104 | M38: Débitmètre en charge | O38: =IF(ISBLANK(A6_P104_Q_DEM!D32), "", A6_P104_Q_DEM!D32) -> Débitmètre électromagnétique (boue/MDV) | R38: Gérer l'équipement | AB38: =ROW(A38)- $AD$2 +1 -> 26 | AC38: =IF(AND($E38="Oui",$M38="Préleveur"),$F38,"") | AD38: {=IFERROR(INDEX($AC$14:$AC$96,SMALL(IF($AC$14:$AC$96<>"",ROW($AC$14:$AC$96)-ROW(INDIRECT("$AC$13"))+1),ROW(INDIRECT("A" & AB38 ) ))),"")} | AE38: =IF(AND($E38="Oui",LEFT($M38,10) ="Débitmètre"),$F38,"") -> A6_P104_Q_DEM | AF38: {=IFERROR(INDEX($AE$14:$AE$96,SMALL(IF($AE$14:$AE$96<>"",ROW($AE$14:$AE$96)-ROW(INDIRECT("$AE$13"))+1),ROW(INDIRECT("A" & AB38 ) ))),"")} | AG38: =IF(AND($E38="Oui",LEFT($M38,5) ="Sonde"),$F38,"") | AH38: {=IFERROR(INDEX($AG$14:$AG$96,SMALL(IF($AG$14:$AG$96<>"",ROW($AG$14:$AG$96)-ROW(INDIRECT("$AG$13"))+1),ROW(INDIRECT("A" & AB38 ) ))),"")} | AI38: =IF(AND($E38="Oui", $M38 <> "", $M38 = ""),$F38,"") | AJ38: {=IFERROR(INDEX($AI$14:$AI$96,SMALL(IF($AI$14:$AI$96<>"",ROW($AI$14:$AI$96)-ROW(INDIRECT("$AI$13"))+1),ROW(INDIRECT("A" & AB38 ) ))),"")}
E39: Oui | F39: A4_P103_TEMP | H39: A4 | I39: =IF(ISBLANK(A4_P103_TEMP!J5), "", A4_P103_TEMP!J5) -> A4 | J39: =IF(ISBLANK(A4_P103_TEMP!J4), "", A4_P103_TEMP!J4) -> P103 | K39: =IF(ISBLANK(A4_P103_TEMP!J4), "", A4_P103_TEMP!J4) -> P103 | M39: Sonde de température | R39: Gérer l'équipement | AB39: =ROW(A39)- $AD$2 +1 -> 27 | AC39: =IF(AND($E39="Oui",$M39="Préleveur"),$F39,"") | AD39: {=IFERROR(INDEX($AC$14:$AC$95,SMALL(IF($AC$14:$AC$95<>"",ROW($AC$14:$AC$95)-ROW(INDIRECT("$AC$13"))+1),ROW(INDIRECT("A" & AB39 ) ))),"")} | AE39: =IF(AND($E39="Oui",LEFT($M39,10) ="Débitmètre"),$F39,"") | AF39: {=IFERROR(INDEX($AE$14:$AE$95,SMALL(IF($AE$14:$AE$95<>"",ROW($AE$14:$AE$95)-ROW(INDIRECT("$AE$13"))+1),ROW(INDIRECT("A" & AB39 ) ))),"")} | AG39: =IF(AND($E39="Oui",LEFT($M39,5) ="Sonde"),$F39,"") -> A4_P103_TEMP | AH39: {=IFERROR(INDEX($AG$14:$AG$95,SMALL(IF($AG$14:$AG$95<>"",ROW($AG$14:$AG$95)-ROW(INDIRECT("$AG$13"))+1),ROW(INDIRECT("A" & AB39 ) ))),"")} | AI39: =IF(AND($E39="Oui", $M39 <> "", $M39 = ""),$F39,"") | AJ39: {=IFERROR(INDEX($AI$14:$AI$95,SMALL(IF($AI$14:$AI$95<>"",ROW($AI$14:$AI$95)-ROW(INDIRECT("$AI$13"))+1),ROW(INDIRECT("A" & AB39 ) ))),"")}
J40: ok | L40: ok | AB40: =ROW(A40)- $AD$2 +1 -> 28 | AC40: =IF(AND($E40="Oui",$M40="Préleveur"),$F40,"") | AD40: {=IFERROR(INDEX($AC$14:$AC$96,SMALL(IF($AC$14:$AC$96<>"",ROW($AC$14:$AC$96)-ROW(INDIRECT("$AC$13"))+1),ROW(INDIRECT("A" & AB40 ) ))),"")} | AE40: =IF(AND($E40="Oui",LEFT($M40,10) ="Débitmètre"),$F40,"") | AF40: {=IFERROR(INDEX($AE$14:$AE$96,SMALL(IF($AE$14:$AE$96<>"",ROW($AE$14:$AE$96)-ROW(INDIRECT("$AE$13"))+1),ROW(INDIRECT("A" & AB40 ) ))),"")} | AG40: =IF(AND($E40="Oui",LEFT($M40,5) ="Sonde"),$F40,"") | AH40: {=IFERROR(INDEX($AG$14:$AG$96,SMALL(IF($AG$14:$AG$96<>"",ROW($AG$14:$AG$96)-ROW(INDIRECT("$AG$13"))+1),ROW(INDIRECT("A" & AB40 ) ))),"")} | AI40: =IF(AND($E40="Oui",$F40<>"",$M40=""),$F40,"") | AJ40: {=IFERROR(INDEX($AI$14:$AI$96,SMALL(IF($AI$14:$AI$96<>"",ROW($AI$14:$AI$96)-ROW(INDIRECT("$AI$13"))+1),ROW(INDIRECT("A" & AB40 ) ))),"")}
E41: Ajouter un équipement station | H41: ok | AB41: =ROW(A41)- $AD$2 +1 -> 29 | AC41: =IF(AND($E41="Oui",$M41="Préleveur"),$F41,"") | AD41: {=IFERROR(INDEX($AC$14:$AC$96,SMALL(IF($AC$14:$AC$96<>"",ROW($AC$14:$AC$96)-ROW(INDIRECT("$AC$13"))+1),ROW(INDIRECT("A" & AB41 ) ))),"")} | AE41: =IF(AND($E41="Oui",LEFT($M41,10) ="Débitmètre"),$F41,"") | AF41: {=IFERROR(INDEX($AE$14:$AE$96,SMALL(IF($AE$14:$AE$96<>"",ROW($AE$14:$AE$96)-ROW(INDIRECT("$AE$13"))+1),ROW(INDIRECT("A" & AB41 ) ))),"")} | AG41: =IF(AND($E41="Oui",LEFT($M41,5) ="Sonde"),$F41,"") | AH41: {=IFERROR(INDEX($AG$14:$AG$96,SMALL(IF($AG$14:$AG$96<>"",ROW($AG$14:$AG$96)-ROW(INDIRECT("$AG$13"))+1),ROW(INDIRECT("A" & AB41 ) ))),"")} | AI41: =IF(AND($E41="Oui",$F41<>"",$M41=""),$F41,"") | AJ41: {=IFERROR(INDEX($AI$14:$AI$96,SMALL(IF($AI$14:$AI$96<>"",ROW($AI$14:$AI$96)-ROW(INDIRECT("$AI$13"))+1),ROW(INDIRECT("A" & AB41 ) ))),"")}
AB42: =ROW(A42)- $AD$2 +1 -> 30 | AC42: =IF(AND($E42="Oui",$M42="Préleveur"),$F42,"") | AD42: {=IFERROR(INDEX($AC$14:$AC$96,SMALL(IF($AC$14:$AC$96<>"",ROW($AC$14:$AC$96)-ROW(INDIRECT("$AC$13"))+1),ROW(INDIRECT("A" & AB42 ) ))),"")} | AE42: =IF(AND($E42="Oui",LEFT($M42,10) ="Débitmètre"),$F42,"") | AF42: {=IFERROR(INDEX($AE$14:$AE$96,SMALL(IF($AE$14:$AE$96<>"",ROW($AE$14:$AE$96)-ROW(INDIRECT("$AE$13"))+1),ROW(INDIRECT("A" & AB42 ) ))),"")} | AG42: =IF(AND($E42="Oui",LEFT($M42,5) ="Sonde"),$F42,"") | AH42: {=IFERROR(INDEX($AG$14:$AG$96,SMALL(IF($AG$14:$AG$96<>"",ROW($AG$14:$AG$96)-ROW(INDIRECT("$AG$13"))+1),ROW(INDIRECT("A" & AB42 ) ))),"")} | AI42: =IF(AND($E42="Oui",$F42<>"",$M42=""),$F42,"") | AJ42: {=IFERROR(INDEX($AI$14:$AI$96,SMALL(IF($AI$14:$AI$96<>"",ROW($AI$14:$AI$96)-ROW(INDIRECT("$AI$13"))+1),ROW(INDIRECT("A" & AB42 ) ))),"")}
AB43: =ROW(A43)- $AD$2 +1 -> 31 | AC43: =IF(AND($E43="Oui",$M43="Préleveur"),$F43,"") | AD43: {=IFERROR(INDEX($AC$14:$AC$96,SMALL(IF($AC$14:$AC$96<>"",ROW($AC$14:$AC$96)-ROW(INDIRECT("$AC$13"))+1),ROW(INDIRECT("A" & AB43 ) ))),"")} | AE43: =IF(AND($E43="Oui",LEFT($M43,10) ="Débitmètre"),$F43,"") | AF43: {=IFERROR(INDEX($AE$14:$AE$96,SMALL(IF($AE$14:$AE$96<>"",ROW($AE$14:$AE$96)-ROW(INDIRECT("$AE$13"))+1),ROW(INDIRECT("A" & AB43 ) ))),"")} | AG43: =IF(AND($E43="Oui",LEFT($M43,5) ="Sonde"),$F43,"") | AH43: {=IFERROR(INDEX($AG$14:$AG$96,SMALL(IF($AG$14:$AG$96<>"",ROW($AG$14:$AG$96)-ROW(INDIRECT("$AG$13"))+1),ROW(INDIRECT("A" & AB43 ) ))),"")} | AI43: =IF(AND($E43="Oui",$F43<>"",$M43=""),$F43,"") | AJ43: {=IFERROR(INDEX($AI$14:$AI$96,SMALL(IF($AI$14:$AI$96<>"",ROW($AI$14:$AI$96)-ROW(INDIRECT("$AI$13"))+1),ROW(INDIRECT("A" & AB43 ) ))),"")}
D44: Liste des pluviomètres de la station | AB44: =ROW(A44)- $AD$2 +1 -> 32 | AC44: =IF(AND($E44="Oui",$M44="Préleveur"),$F44,"") | AD44: {=IFERROR(INDEX($AC$14:$AC$96,SMALL(IF($AC$14:$AC$96<>"",ROW($AC$14:$AC$96)-ROW(INDIRECT("$AC$13"))+1),ROW(INDIRECT("A" & AB44 ) ))),"")} | AE44: =IF(AND($E44="Oui",LEFT($M44,10) ="Débitmètre"),$F44,"") | AF44: {=IFERROR(INDEX($AE$14:$AE$96,SMALL(IF($AE$14:$AE$96<>"",ROW($AE$14:$AE$96)-ROW(INDIRECT("$AE$13"))+1),ROW(INDIRECT("A" & AB44 ) ))),"")} | AG44: =IF(AND($E44="Oui",LEFT($M44,5) ="Sonde"),$F44,"") | AH44: {=IFERROR(INDEX($AG$14:$AG$96,SMALL(IF($AG$14:$AG$96<>"",ROW($AG$14:$AG$96)-ROW(INDIRECT("$AG$13"))+1),ROW(INDIRECT("A" & AB44 ) ))),"")} | AI44: =IF(AND($E44="Oui",$F44<>"",$M44=""),$F44,"") | AJ44: {=IFERROR(INDEX($AI$14:$AI$96,SMALL(IF($AI$14:$AI$96<>"",ROW($AI$14:$AI$96)-ROW(INDIRECT("$AI$13"))+1),ROW(INDIRECT("A" & AB44 ) ))),"")}
AB45: =ROW(A45)- $AD$2 +1 -> 33 | AC45: =IF(AND($E45="Oui",$M45="Préleveur"),$F45,"") | AD45: {=IFERROR(INDEX($AC$14:$AC$96,SMALL(IF($AC$14:$AC$96<>"",ROW($AC$14:$AC$96)-ROW(INDIRECT("$AC$13"))+1),ROW(INDIRECT("A" & AB45 ) ))),"")} | AE45: =IF(AND($E45="Oui",LEFT($M45,10) ="Débitmètre"),$F45,"") | AF45: {=IFERROR(INDEX($AE$14:$AE$96,SMALL(IF($AE$14:$AE$96<>"",ROW($AE$14:$AE$96)-ROW(INDIRECT("$AE$13"))+1),ROW(INDIRECT("A" & AB45 ) ))),"")} | AG45: =IF(AND($E45="Oui",LEFT($M45,5) ="Sonde"),$F45,"") | AH45: {=IFERROR(INDEX($AG$14:$AG$96,SMALL(IF($AG$14:$AG$96<>"",ROW($AG$14:$AG$96)-ROW(INDIRECT("$AG$13"))+1),ROW(INDIRECT("A" & AB45 ) ))),"")} | AI45: =IF(AND($E45="Oui",$F45<>"",$M45=""),$F45,"") | AJ45: {=IFERROR(INDEX($AI$14:$AI$96,SMALL(IF($AI$14:$AI$96<>"",ROW($AI$14:$AI$96)-ROW(INDIRECT("$AI$13"))+1),ROW(INDIRECT("A" & AB45 ) ))),"")}
E46: Actif | F46: Lien vers l'onglet de l'équipement | AB46: =ROW(A46)- $AD$2 +1 -> 34 | AC46: =IF(AND($E46="Oui",$M46="Préleveur"),$F46,"") | AD46: {=IFERROR(INDEX($AC$14:$AC$96,SMALL(IF($AC$14:$AC$96<>"",ROW($AC$14:$AC$96)-ROW(INDIRECT("$AC$13"))+1),ROW(INDIRECT("A" & AB46 ) ))),"")} | AE46: =IF(AND($E46="Oui",LEFT($M46,10) ="Débitmètre"),$F46,"") | AF46: {=IFERROR(INDEX($AE$14:$AE$96,SMALL(IF($AE$14:$AE$96<>"",ROW($AE$14:$AE$96)-ROW(INDIRECT("$AE$13"))+1),ROW(INDIRECT("A" & AB46 ) ))),"")} | AG46: =IF(AND($E46="Oui",LEFT($M46,5) ="Sonde"),$F46,"") | AH46: {=IFERROR(INDEX($AG$14:$AG$96,SMALL(IF($AG$14:$AG$96<>"",ROW($AG$14:$AG$96)-ROW(INDIRECT("$AG$13"))+1),ROW(INDIRECT("A" & AB46 ) ))),"")} | AI46: =IF(AND($E46="Oui",$F46<>"",$M46=""),$F46,"") | AJ46: {=IFERROR(INDEX($AI$14:$AI$96,SMALL(IF($AI$14:$AI$96<>"",ROW($AI$14:$AI$96)-ROW(INDIRECT("$AI$13"))+1),ROW(INDIRECT("A" & AB46 ) ))),"")}
E47: Oui | F47: PLUVIO_STEU_P1 | H47: Gérer l'équipement | AB47: =ROW(A47)- $AD$2 +1 -> 35 | AC47: =IF(AND($E47="Oui",$M47="Préleveur"),$F47,"") | AD47: {=IFERROR(INDEX($AC$14:$AC$96,SMALL(IF($AC$14:$AC$96<>"",ROW($AC$14:$AC$96)-ROW(INDIRECT("$AC$13"))+1),ROW(INDIRECT("A" & AB47 ) ))),"")} | AE47: =IF(AND($E47="Oui",LEFT($M47,10) ="Débitmètre"),$F47,"") | AF47: {=IFERROR(INDEX($AE$14:$AE$96,SMALL(IF($AE$14:$AE$96<>"",ROW($AE$14:$AE$96)-ROW(INDIRECT("$AE$13"))+1),ROW(INDIRECT("A" & AB47 ) ))),"")} | AG47: =IF(AND($E47="Oui",LEFT($M47,5) ="Sonde"),$F47,"") | AH47: {=IFERROR(INDEX($AG$14:$AG$96,SMALL(IF($AG$14:$AG$96<>"",ROW($AG$14:$AG$96)-ROW(INDIRECT("$AG$13"))+1),ROW(INDIRECT("A" & AB47 ) ))),"")} | AI47: =IF(AND($E47="Oui",$F47<>"",$M47=""),$F47,"") -> PLUVIO_STEU_P1 | AJ47: {=IFERROR(INDEX($AI$14:$AI$96,SMALL(IF($AI$14:$AI$96<>"",ROW($AI$14:$AI$96)-ROW(INDIRECT("$AI$13"))+1),ROW(INDIRECT("A" & AB47 ) ))),"")}
E48: Oui | F48: PLUVIO_STEU_ee | H48: Gérer l'équipement | AB48: =ROW(A48)- $AD$2 +1 -> 36 | AC48: =IF(AND($E48="Oui",$M48="Préleveur"),$F48,"") | AD48: {=IFERROR(INDEX($AC$14:$AC$96,SMALL(IF($AC$14:$AC$96<>"",ROW($AC$14:$AC$96)-ROW(INDIRECT("$AC$13"))+1),ROW(INDIRECT("A" & AB48 ) ))),"")} | AE48: =IF(AND($E48="Oui",LEFT($M48,10) ="Débitmètre"),$F48,"") | AF48: {=IFERROR(INDEX($AE$14:$AE$96,SMALL(IF($AE$14:$AE$96<>"",ROW($AE$14:$AE$96)-ROW(INDIRECT("$AE$13"))+1),ROW(INDIRECT("A" & AB48 ) ))),"")} | AG48: =IF(AND($E48="Oui",LEFT($M48,5) ="Sonde"),$F48,"") | AH48: {=IFERROR(INDEX($AG$14:$AG$96,SMALL(IF($AG$14:$AG$96<>"",ROW($AG$14:$AG$96)-ROW(INDIRECT("$AG$13"))+1),ROW(INDIRECT("A" & AB48 ) ))),"")} | AI48: =IF(AND($E48="Oui",$F48<>"",$M48=""),$F48,"") -> PLUVIO_STEU_ee | AJ48: {=IFERROR(INDEX($AI$14:$AI$96,SMALL(IF($AI$14:$AI$96<>"",ROW($AI$14:$AI$96)-ROW(INDIRECT("$AI$13"))+1),ROW(INDIRECT("A" & AB48 ) ))),"")}
E49: Ajouter un pluviomètre station | K49: Si pas de pluviomètre, veuillez ajouter en commentaire la provenance des données : | AB49: =ROW(A49)- $AD$2 +1 -> 37 | AC49: =IF(AND($E49="Oui",$M49="Préleveur"),$F49,"") | AD49: {=IFERROR(INDEX($AC$14:$AC$96,SMALL(IF($AC$14:$AC$96<>"",ROW($AC$14:$AC$96)-ROW(INDIRECT("$AC$13"))+1),ROW(INDIRECT("A" & AB49 ) ))),"")} | AE49: =IF(AND($E49="Oui",LEFT($M49,10) ="Débitmètre"),$F49,"") | AF49: {=IFERROR(INDEX($AE$14:$AE$96,SMALL(IF($AE$14:$AE$96<>"",ROW($AE$14:$AE$96)-ROW(INDIRECT("$AE$13"))+1),ROW(INDIRECT("A" & AB49 ) ))),"")} | AG49: =IF(AND($E49="Oui",LEFT($M49,5) ="Sonde"),$F49,"") | AH49: {=IFERROR(INDEX($AG$14:$AG$96,SMALL(IF($AG$14:$AG$96<>"",ROW($AG$14:$AG$96)-ROW(INDIRECT("$AG$13"))+1),ROW(INDIRECT("A" & AB49 ) ))),"")} | AI49: =IF(AND($E49="Oui",$F49<>"",$M49=""),$F49,"") | AJ49: {=IFERROR(INDEX($AI$14:$AI$96,SMALL(IF($AI$14:$AI$96<>"",ROW($AI$14:$AI$96)-ROW(INDIRECT("$AI$13"))+1),ROW(INDIRECT("A" & AB49 ) ))),"")}
AB50: =ROW(A50)- $AD$2 +1 -> 38 | AC50: =IF(AND($E50="Oui",$M50="Préleveur"),$F50,"") | AD50: {=IFERROR(INDEX($AC$14:$AC$96,SMALL(IF($AC$14:$AC$96<>"",ROW($AC$14:$AC$96)-ROW(INDIRECT("$AC$13"))+1),ROW(INDIRECT("A" & AB50 ) ))),"")} | AE50: =IF(AND($E50="Oui",LEFT($M50,10) ="Débitmètre"),$F50,"") | AF50: {=IFERROR(INDEX($AE$14:$AE$96,SMALL(IF($AE$14:$AE$96<>"",ROW($AE$14:$AE$96)-ROW(INDIRECT("$AE$13"))+1),ROW(INDIRECT("A" & AB50 ) ))),"")} | AG50: =IF(AND($E50="Oui",LEFT($M50,5) ="Sonde"),$F50,"") | AH50: {=IFERROR(INDEX($AG$14:$AG$96,SMALL(IF($AG$14:$AG$96<>"",ROW($AG$14:$AG$96)-ROW(INDIRECT("$AG$13"))+1),ROW(INDIRECT("A" & AB50 ) ))),"")} | AI50: =IF(AND($E50="Oui",$F50<>"",$M50=""),$F50,"") | AJ50: {=IFERROR(INDEX($AI$14:$AI$96,SMALL(IF($AI$14:$AI$96<>"",ROW($AI$14:$AI$96)-ROW(INDIRECT("$AI$13"))+1),ROW(INDIRECT("A" & AB50 ) ))),"")}
AB51: =ROW(A51)- $AD$2 +1 -> 39 | AC51: =IF(AND($E51="Oui",$M51="Préleveur"),$F51,"") | AD51: {=IFERROR(INDEX($AC$14:$AC$96,SMALL(IF($AC$14:$AC$96<>"",ROW($AC$14:$AC$96)-ROW(INDIRECT("$AC$13"))+1),ROW(INDIRECT("A" & AB51 ) ))),"")} | AE51: =IF(AND($E51="Oui",LEFT($M51,10) ="Débitmètre"),$F51,"") | AF51: {=IFERROR(INDEX($AE$14:$AE$96,SMALL(IF($AE$14:$AE$96<>"",ROW($AE$14:$AE$96)-ROW(INDIRECT("$AE$13"))+1),ROW(INDIRECT("A" & AB51 ) ))),"")} | AG51: =IF(AND($E51="Oui",LEFT($M51,5) ="Sonde"),$F51,"") | AH51: {=IFERROR(INDEX($AG$14:$AG$96,SMALL(IF($AG$14:$AG$96<>"",ROW($AG$14:$AG$96)-ROW(INDIRECT("$AG$13"))+1),ROW(INDIRECT("A" & AB51 ) ))),"")} | AI51: =IF(AND($E51="Oui",$F51<>"",$M51=""),$F51,"") | AJ51: {=IFERROR(INDEX($AI$14:$AI$96,SMALL(IF($AI$14:$AI$96<>"",ROW($AI$14:$AI$96)-ROW(INDIRECT("$AI$13"))+1),ROW(INDIRECT("A" & AB51 ) ))),"")}
AB52: =ROW(A52)- $AD$2 +1 -> 40 | AC52: =IF(AND($E52="Oui",$M52="Préleveur"),$F52,"") | AD52: {=IFERROR(INDEX($AC$14:$AC$96,SMALL(IF($AC$14:$AC$96<>"",ROW($AC$14:$AC$96)-ROW(INDIRECT("$AC$13"))+1),ROW(INDIRECT("A" & AB52 ) ))),"")} | AE52: =IF(AND($E52="Oui",LEFT($M52,10) ="Débitmètre"),$F52,"") | AF52: {=IFERROR(INDEX($AE$14:$AE$96,SMALL(IF($AE$14:$AE$96<>"",ROW($AE$14:$AE$96)-ROW(INDIRECT("$AE$13"))+1),ROW(INDIRECT("A" & AB52 ) ))),"")} | AG52: =IF(AND($E52="Oui",LEFT($M52,5) ="Sonde"),$F52,"") | AH52: {=IFERROR(INDEX($AG$14:$AG$96,SMALL(IF($AG$14:$AG$96<>"",ROW($AG$14:$AG$96)-ROW(INDIRECT("$AG$13"))+1),ROW(INDIRECT("A" & AB52 ) ))),"")} | AI52: =IF(AND($E52="Oui",$F52<>"",$M52=""),$F52,"") | AJ52: {=IFERROR(INDEX($AI$14:$AI$96,SMALL(IF($AI$14:$AI$96<>"",ROW($AI$14:$AI$96)-ROW(INDIRECT("$AI$13"))+1),ROW(INDIRECT("A" & AB52 ) ))),"")}
AB53: =ROW(A53)- $AD$2 +1 -> 41 | AC53: =IF(AND($E53="Oui",$M53="Préleveur"),$F53,"") | AD53: {=IFERROR(INDEX($AC$14:$AC$96,SMALL(IF($AC$14:$AC$96<>"",ROW($AC$14:$AC$96)-ROW(INDIRECT("$AC$13"))+1),ROW(INDIRECT("A" & AB53 ) ))),"")} | AE53: =IF(AND($E53="Oui",LEFT($M53,10) ="Débitmètre"),$F53,"") | AF53: {=IFERROR(INDEX($AE$14:$AE$96,SMALL(IF($AE$14:$AE$96<>"",ROW($AE$14:$AE$96)-ROW(INDIRECT("$AE$13"))+1),ROW(INDIRECT("A" & AB53 ) ))),"")} | AG53: =IF(AND($E53="Oui",LEFT($M53,5) ="Sonde"),$F53,"") | AH53: {=IFERROR(INDEX($AG$14:$AG$96,SMALL(IF($AG$14:$AG$96<>"",ROW($AG$14:$AG$96)-ROW(INDIRECT("$AG$13"))+1),ROW(INDIRECT("A" & AB53 ) ))),"")} | AI53: =IF(AND($E53="Oui",$F53<>"",$M53=""),$F53,"") | AJ53: {=IFERROR(INDEX($AI$14:$AI$96,SMALL(IF($AI$14:$AI$96<>"",ROW($AI$14:$AI$96)-ROW(INDIRECT("$AI$13"))+1),ROW(INDIRECT("A" & AB53 ) ))),"")}
AB54: =ROW(A54)- $AD$2 +1 -> 42 | AC54: =IF(AND($E54="Oui",$M54="Préleveur"),$F54,"") | AD54: {=IFERROR(INDEX($AC$14:$AC$96,SMALL(IF($AC$14:$AC$96<>"",ROW($AC$14:$AC$96)-ROW(INDIRECT("$AC$13"))+1),ROW(INDIRECT("A" & AB54 ) ))),"")} | AE54: =IF(AND($E54="Oui",LEFT($M54,10) ="Débitmètre"),$F54,"") | AF54: {=IFERROR(INDEX($AE$14:$AE$96,SMALL(IF($AE$14:$AE$96<>"",ROW($AE$14:$AE$96)-ROW(INDIRECT("$AE$13"))+1),ROW(INDIRECT("A" & AB54 ) ))),"")} | AG54: =IF(AND($E54="Oui",LEFT($M54,5) ="Sonde"),$F54,"") | AH54: {=IFERROR(INDEX($AG$14:$AG$96,SMALL(IF($AG$14:$AG$96<>"",ROW($AG$14:$AG$96)-ROW(INDIRECT("$AG$13"))+1),ROW(INDIRECT("A" & AB54 ) ))),"")} | AI54: =IF(AND($E54="Oui",$F54<>"",$M54=""),$F54,"") | AJ54: {=IFERROR(INDEX($AI$14:$AI$96,SMALL(IF($AI$14:$AI$96<>"",ROW($AI$14:$AI$96)-ROW(INDIRECT("$AI$13"))+1),ROW(INDIRECT("A" & AB54 ) ))),"")}
AB55: =ROW(A55)- $AD$2 +1 -> 43 | AC55: =IF(AND($E55="Oui",$M55="Préleveur"),$F55,"") | AD55: {=IFERROR(INDEX($AC$14:$AC$96,SMALL(IF($AC$14:$AC$96<>"",ROW($AC$14:$AC$96)-ROW(INDIRECT("$AC$13"))+1),ROW(INDIRECT("A" & AB55 ) ))),"")} | AE55: =IF(AND($E55="Oui",LEFT($M55,10) ="Débitmètre"),$F55,"") | AF55: {=IFERROR(INDEX($AE$14:$AE$96,SMALL(IF($AE$14:$AE$96<>"",ROW($AE$14:$AE$96)-ROW(INDIRECT("$AE$13"))+1),ROW(INDIRECT("A" & AB55 ) ))),"")} | AG55: =IF(AND($E55="Oui",LEFT($M55,5) ="Sonde"),$F55,"") | AH55: {=IFERROR(INDEX($AG$14:$AG$96,SMALL(IF($AG$14:$AG$96<>"",ROW($AG$14:$AG$96)-ROW(INDIRECT("$AG$13"))+1),ROW(INDIRECT("A" & AB55 ) ))),"")} | AI55: =IF(AND($E55="Oui",$F55<>"",$M55=""),$F55,"") | AJ55: {=IFERROR(INDEX($AI$14:$AI$96,SMALL(IF($AI$14:$AI$96<>"",ROW($AI$14:$AI$96)-ROW(INDIRECT("$AI$13"))+1),ROW(INDIRECT("A" & AB55 ) ))),"")}
AB56: =ROW(A56)- $AD$2 +1 -> 44 | AC56: =IF(AND($E56="Oui",$M56="Préleveur"),$F56,"") | AD56: {=IFERROR(INDEX($AC$14:$AC$96,SMALL(IF($AC$14:$AC$96<>"",ROW($AC$14:$AC$96)-ROW(INDIRECT("$AC$13"))+1),ROW(INDIRECT("A" & AB56 ) ))),"")} | AE56: =IF(AND($E56="Oui",LEFT($M56,10) ="Débitmètre"),$F56,"") | AF56: {=IFERROR(INDEX($AE$14:$AE$96,SMALL(IF($AE$14:$AE$96<>"",ROW($AE$14:$AE$96)-ROW(INDIRECT("$AE$13"))+1),ROW(INDIRECT("A" & AB56 ) ))),"")} | AG56: =IF(AND($E56="Oui",LEFT($M56,5) ="Sonde"),$F56,"") | AH56: {=IFERROR(INDEX($AG$14:$AG$96,SMALL(IF($AG$14:$AG$96<>"",ROW($AG$14:$AG$96)-ROW(INDIRECT("$AG$13"))+1),ROW(INDIRECT("A" & AB56 ) ))),"")} | AI56: =IF(AND($E56="Oui",$F56<>"",$M56=""),$F56,"") | AJ56: {=IFERROR(INDEX($AI$14:$AI$96,SMALL(IF($AI$14:$AI$96<>"",ROW($AI$14:$AI$96)-ROW(INDIRECT("$AI$13"))+1),ROW(INDIRECT("A" & AB56 ) ))),"")}
AB57: =ROW(A57)- $AD$2 +1 -> 45 | AC57: =IF(AND($E57="Oui",$M57="Préleveur"),$F57,"") | AD57: {=IFERROR(INDEX($AC$14:$AC$96,SMALL(IF($AC$14:$AC$96<>"",ROW($AC$14:$AC$96)-ROW(INDIRECT("$AC$13"))+1),ROW(INDIRECT("A" & AB57 ) ))),"")} | AE57: =IF(AND($E57="Oui",LEFT($M57,10) ="Débitmètre"),$F57,"") | AF57: {=IFERROR(INDEX($AE$14:$AE$96,SMALL(IF($AE$14:$AE$96<>"",ROW($AE$14:$AE$96)-ROW(INDIRECT("$AE$13"))+1),ROW(INDIRECT("A" & AB57 ) ))),"")} | AG57: =IF(AND($E57="Oui",LEFT($M57,5) ="Sonde"),$F57,"") | AH57: {=IFERROR(INDEX($AG$14:$AG$96,SMALL(IF($AG$14:$AG$96<>"",ROW($AG$14:$AG$96)-ROW(INDIRECT("$AG$13"))+1),ROW(INDIRECT("A" & AB57 ) ))),"")} | AI57: =IF(AND($E57="Oui",$F57<>"",$M57=""),$F57,"") | AJ57: {=IFERROR(INDEX($AI$14:$AI$96,SMALL(IF($AI$14:$AI$96<>"",ROW($AI$14:$AI$96)-ROW(INDIRECT("$AI$13"))+1),ROW(INDIRECT("A" & AB57 ) ))),"")}
AB58: =ROW(A58)- $AD$2 +1 -> 46 | AC58: =IF(AND($E58="Oui",$M58="Préleveur"),$F58,"") | AD58: {=IFERROR(INDEX($AC$14:$AC$96,SMALL(IF($AC$14:$AC$96<>"",ROW($AC$14:$AC$96)-ROW(INDIRECT("$AC$13"))+1),ROW(INDIRECT("A" & AB58 ) ))),"")} | AE58: =IF(AND($E58="Oui",LEFT($M58,10) ="Débitmètre"),$F58,"") | AF58: {=IFERROR(INDEX($AE$14:$AE$96,SMALL(IF($AE$14:$AE$96<>"",ROW($AE$14:$AE$96)-ROW(INDIRECT("$AE$13"))+1),ROW(INDIRECT("A" & AB58 ) ))),"")} | AG58: =IF(AND($E58="Oui",LEFT($M58,5) ="Sonde"),$F58,"") | AH58: {=IFERROR(INDEX($AG$14:$AG$96,SMALL(IF($AG$14:$AG$96<>"",ROW($AG$14:$AG$96)-ROW(INDIRECT("$AG$13"))+1),ROW(INDIRECT("A" & AB58 ) ))),"")} | AI58: =IF(AND($E58="Oui",$F58<>"",$M58=""),$F58,"") | AJ58: {=IFERROR(INDEX($AI$14:$AI$96,SMALL(IF($AI$14:$AI$96<>"",ROW($AI$14:$AI$96)-ROW(INDIRECT("$AI$13"))+1),ROW(INDIRECT("A" & AB58 ) ))),"")}
AB59: =ROW(A59)- $AD$2 +1 -> 47 | AC59: =IF(AND($E59="Oui",$M59="Préleveur"),$F59,"") | AD59: {=IFERROR(INDEX($AC$14:$AC$96,SMALL(IF($AC$14:$AC$96<>"",ROW($AC$14:$AC$96)-ROW(INDIRECT("$AC$13"))+1),ROW(INDIRECT("A" & AB59 ) ))),"")} | AE59: =IF(AND($E59="Oui",LEFT($M59,10) ="Débitmètre"),$F59,"") | AF59: {=IFERROR(INDEX($AE$14:$AE$96,SMALL(IF($AE$14:$AE$96<>"",ROW($AE$14:$AE$96)-ROW(INDIRECT("$AE$13"))+1),ROW(INDIRECT("A" & AB59 ) ))),"")} | AG59: =IF(AND($E59="Oui",LEFT($M59,5) ="Sonde"),$F59,"") | AH59: {=IFERROR(INDEX($AG$14:$AG$96,SMALL(IF($AG$14:$AG$96<>"",ROW($AG$14:$AG$96)-ROW(INDIRECT("$AG$13"))+1),ROW(INDIRECT("A" & AB59 ) ))),"")} | AI59: =IF(AND($E59="Oui",$F59<>"",$M59=""),$F59,"") | AJ59: {=IFERROR(INDEX($AI$14:$AI$96,SMALL(IF($AI$14:$AI$96<>"",ROW($AI$14:$AI$96)-ROW(INDIRECT("$AI$13"))+1),ROW(INDIRECT("A" & AB59 ) ))),"")}
AB60: =ROW(A60)- $AD$2 +1 -> 48 | AC60: =IF(AND($E60="Oui",$M60="Préleveur"),$F60,"") | AD60: {=IFERROR(INDEX($AC$14:$AC$96,SMALL(IF($AC$14:$AC$96<>"",ROW($AC$14:$AC$96)-ROW(INDIRECT("$AC$13"))+1),ROW(INDIRECT("A" & AB60 ) ))),"")} | AE60: =IF(AND($E60="Oui",LEFT($M60,10) ="Débitmètre"),$F60,"") | AF60: {=IFERROR(INDEX($AE$14:$AE$96,SMALL(IF($AE$14:$AE$96<>"",ROW($AE$14:$AE$96)-ROW(INDIRECT("$AE$13"))+1),ROW(INDIRECT("A" & AB60 ) ))),"")} | AG60: =IF(AND($E60="Oui",LEFT($M60,5) ="Sonde"),$F60,"") | AH60: {=IFERROR(INDEX($AG$14:$AG$96,SMALL(IF($AG$14:$AG$96<>"",ROW($AG$14:$AG$96)-ROW(INDIRECT("$AG$13"))+1),ROW(INDIRECT("A" & AB60 ) ))),"")} | AI60: =IF(AND($E60="Oui",$F60<>"",$M60=""),$F60,"") | AJ60: {=IFERROR(INDEX($AI$14:$AI$96,SMALL(IF($AI$14:$AI$96<>"",ROW($AI$14:$AI$96)-ROW(INDIRECT("$AI$13"))+1),ROW(INDIRECT("A" & AB60 ) ))),"")}
AB61: =ROW(A61)- $AD$2 +1 -> 49 | AC61: =IF(AND($E61="Oui",$M61="Préleveur"),$F61,"") | AD61: {=IFERROR(INDEX($AC$14:$AC$96,SMALL(IF($AC$14:$AC$96<>"",ROW($AC$14:$AC$96)-ROW(INDIRECT("$AC$13"))+1),ROW(INDIRECT("A" & AB61 ) ))),"")} | AE61: =IF(AND($E61="Oui",LEFT($M61,10) ="Débitmètre"),$F61,"") | AF61: {=IFERROR(INDEX($AE$14:$AE$96,SMALL(IF($AE$14:$AE$96<>"",ROW($AE$14:$AE$96)-ROW(INDIRECT("$AE$13"))+1),ROW(INDIRECT("A" & AB61 ) ))),"")} | AG61: =IF(AND($E61="Oui",LEFT($M61,5) ="Sonde"),$F61,"") | AH61: {=IFERROR(INDEX($AG$14:$AG$96,SMALL(IF($AG$14:$AG$96<>"",ROW($AG$14:$AG$96)-ROW(INDIRECT("$AG$13"))+1),ROW(INDIRECT("A" & AB61 ) ))),"")} | AI61: =IF(AND($E61="Oui",$F61<>"",$M61=""),$F61,"") | AJ61: {=IFERROR(INDEX($AI$14:$AI$96,SMALL(IF($AI$14:$AI$96<>"",ROW($AI$14:$AI$96)-ROW(INDIRECT("$AI$13"))+1),ROW(INDIRECT("A" & AB61 ) ))),"")}
... AB96: =ROW(A96)- $AD$2 +1 -> 84 | AC96: =IF(AND($E96="Oui",$M96="Préleveur"),$F96,"") | AD96: {=IFERROR(INDEX($AC$14:$AC$96,SMALL(IF($AC$14:$AC$96<>"",ROW($AC$14:$AC$96)-ROW(INDIRECT("$AC$13"))+1),ROW(INDIRECT("A" & AB96 ) ))),"")} | AE96: =IF(AND($E96="Oui",LEFT($M96,10) ="Débitmètre"),$F96,"") | AF96: {=IFERROR(INDEX($AE$14:$AE$96,SMALL(IF($AE$14:$AE$96<>"",ROW($AE$14:$AE$96)-ROW(INDIRECT("$AE$13"))+1),ROW(INDIRECT("A" & AB96 ) ))),"")} | AG96: =IF(AND($E96="Oui",LEFT($M96,5) ="Sonde"),$F96,"") | AH96: {=IFERROR(INDEX($AG$14:$AG$96,SMALL(IF($AG$14:$AG$96<>"",ROW($AG$14:$AG$96)-ROW(INDIRECT("$AG$13"))+1),ROW(INDIRECT("A" & AB96 ) ))),"")} | AI96: =IF(AND($E96="Oui",$F96<>"",$M96=""),$F96,"") | AJ96: {=IFERROR(INDEX($AI$14:$AI$96,SMALL(IF($AI$14:$AI$96<>"",ROW($AI$14:$AI$96)-ROW(INDIRECT("$AI$13"))+1),ROW(INDIRECT("A" & AB96 ) ))),"")}

Sheet SYNTHESE
C2: CONTRÔLE ANNUEL DES DISPOSITIFS D'AUTOSURVEILLANCE DES SYSTÈMES D'ASSAINISSEMENT COLLECTIF
C3: NOM DU SYSTÈME D'ASSAINISSEMENT : | G3: =IF(ISBLANK(Descriptif!G3),"",Descriptif!G3) -> BARJAC (30) | K3: NOM SYSTÈME DE TRAITEMENT : | N3: =IF(ISBLANK(Descriptif!N3),"",Descriptif!N3) -> BARJAC (30) | T3: NOM SYSTÈME DE COLLECTE : | Y3: =IF(ISBLANK(Descriptif!T3),"",Descriptif!T3)
C4: CODE SANDRE DE L'AGGLOMERATION : | G4: =IF(ISBLANK(Descriptif!G4),"",Descriptif!G4) | K4: CODE SANDRE DE LA STATION : | N4: =IF(ISBLANK(Descriptif!N4),"",Descriptif!N4) -> 060930290002 | T4: CODE SANDRE DU RESEAU : | Y4: =IF(ISBLANK(Descriptif!T4),"",Descriptif!T4)
C5: NOM DU MAITRE D'OUVRAGE : | G5: =IF(ISBLANK(Descriptif!G5),"",Descriptif!G5) -> Commune de Barjac | K5: CAPACITE DE LA STATION : | N5: =IF(ISBLANK(Descriptif!N5),"",Descriptif!N5) -> 5 000 EH | T5: EXPLOITANT DU RESEAU : | Y5: =IF(ISBLANK(Descriptif!T5),"",Descriptif!T5)
C6: ORGANISME DE CONTRÔLE : | G6: =IF(ISBLANK(Descriptif!G6),"",Descriptif!G6) -> CEREG Ingénierie | K6: EXPLOITANT DE LA STATION : | N6: =IF(ISBLANK(Descriptif!N6),"",Descriptif!N6) -> Régie | T6: NOM DU LABORATOIRE : | Y6: =IF(ISBLANK(Analytique!O3),"",Analytique!O3) -> test labo
C8: EVALUATIONS
D10: Evaluation des points règlementaires
G11: ENTREE et SORTIE | J11: Score | L11: DEVERSEMENT STATION | P11: Score | T11: BOUE et Apports extérieurs | Y11: Score
G12: Point A3 | I12: =IF(Recap_equipements!E115<>"",Recap_equipements!E115,"") -> Non validé | J12: =Recap_equipements!E62 -> 78.333333 | L12: Point A2 | N12: =IF(Recap_equipements!E127<>"",Recap_equipements!E127,"") -> Validé avec réserve | P12: =Recap_equipements!E74 -> 80 | T12: Point A6 | X12: =IF(Recap_equipements!E139<>"",Recap_equipements!E139,"") -> Non validé | Y12: =Recap_equipements!E86 -> 40
G13: Débitmètre | I13: =IF(Recap_equipements!F117<>"",Recap_equipements!F117,"") -> Non validé | J13: =IF(Recap_equipements!F64<>"",Recap_equipements!F64,"") -> 60 | L13: Débitmètre | N13: =IF(Recap_equipements!F129<>"",Recap_equipements!F129,"") -> Validé avec réserve | P13: =Recap_equipements!F76 -> 80 | T13: Débitmètre | X13: =IF(Recap_equipements!F141<>"",Recap_equipements!F141,"") -> Non validé | Y13: =Recap_equipements!F88 -> 40
G14: Préleveur | I14: =IF(Recap_equipements!F118<>"",Recap_equipements!F118,"") -> Validé | J14: =IF(Recap_equipements!F65<>"",Recap_equipements!F65,"") -> 85 | L14: Préleveur | N14: =IF(Recap_equipements!F130<>"",Recap_equipements!F130,"") | P14: =Recap_equipements!F77 | T14: Préleveur | X14: =IF(Recap_equipements!F142<>"",Recap_equipements!F142,"") | Y14: =Recap_equipements!F89
G15: Analytique | I15: =IF(Recap_equipements!F119<>"",Recap_equipements!F119,"") -> Validé | J15: =IF(Recap_equipements!F66<>"",Recap_equipements!F66,"") -> 90 | L15: Analytique | N15: =IF(Recap_equipements!F131<>"",Recap_equipements!F131,"") | P15: =Recap_equipements!F78 | T15: Analytique | X15: =IF(Recap_equipements!F143<>"",Recap_equipements!F143,"") | Y15: =Recap_equipements!F90
G16: Point A4 | I16: =IF(Recap_equipements!E121<>"",Recap_equipements!E121,"") -> Non validé | J16: =Recap_equipements!E68 -> 63.333333 | L16: Point A5 | N16: =IF(Recap_equipements!E133<>"",Recap_equipements!E133,"") | P16: =Recap_equipements!E80 | T16: Point A7 | X16: =IF(Recap_equipements!E145<>"",Recap_equipements!E145,"") | Y16: =Recap_equipements!E92
G17: Débitmètre | I17: =IF(Recap_equipements!F123<>"",Recap_equipements!F123,"") -> Non validé | J17: =IF(Recap_equipements!F70<>"",Recap_equipements!F70,"") -> 0 | L17: Débitmètre | N17: =IF(Recap_equipements!F135<>"",Recap_equipements!F135,"") | P17: =Recap_equipements!F82 | T17: Débitmètre | X17: =IF(Recap_equipements!F147<>"",Recap_equipements!F147,"") | Y17: =Recap_equipements!F94
G18: Préleveur | I18: =IF(Recap_equipements!F124<>"",Recap_equipements!F124,"") -> Validé | J18: =IF(Recap_equipements!F71<>"",Recap_equipements!F71,"") -> 100 | L18: Préleveur | N18: =IF(Recap_equipements!F136<>"",Recap_equipements!F136,"") | P18: =Recap_equipements!F83 | T18: Préleveur | X18: =IF(Recap_equipements!F148<>"",Recap_equipements!F148,"") | Y18: =Recap_equipements!F95
G19: Analytique | I19: =IF(Recap_equipements!F125<>"",Recap_equipements!F125,"") -> Validé | J19: =IF(Recap_equipements!F72<>"",Recap_equipements!F72,"") -> 90 | L19: Analytique | N19: =IF(Recap_equipements!F137<>"",Recap_equipements!F137,"") | P19: =Recap_equipements!F84 | T19: Analytique | X19: =IF(Recap_equipements!F149<>"",Recap_equipements!F149,"") | Y19: =Recap_equipements!F96
D22: Evaluation documentaire | O22: Commentaire évaluation :
F23: ok | G23: Manuel d'autosurveillance à jour ou en cours d'expertise | K23: =IF(Qualité!L10<>"",Qualité!L10,"Non contrôlé") -> Validé | M23: Coef Qualité | O23: =IF(Qualité!D29<>"",Qualité!D29,"") -> Le système Qualité mis en œuvre est performant.
G24: Système qualité interne suivi AS | K24: =IF(Qualité!L26<>"",Qualité!L26,"Non contrôlé") -> Validé | M24: =IF(Qualité!L26="Non validé",0.9,1) -> 1
D27: Evaluation des pratiques analytiques | N27: Commentaire évaluation :
G28: EAU | I28: Fractionnement | K28: =Analytique!L12 -> Validé | N28: =IF(Analytique!D31<>"",Analytique!D31,"")
I29: Température | K29: =Analytique!L13 -> Validé
I30: Transport | K30: =Analytique!L14 -> Validé
I31: Analytique | K31: =IF(Analytique!Q27<>"",Analytique!Q27,"") -> Validé
I32: Conclusion | K32: =IF(Analytique!J29<>"",Analytique!J29,"") -> Validé
G33: SDE | I33: Aquaref | K33: =Analytique!L11 -> Non validé
D36: Autres évaluations
G37: Sonde température | I37: {=IFERROR(INDEX(Equipements!$K$16:$K$72,SMALL(IF(Equipements!$I$16:$I$72="Sonde de température",ROW(Equipements!$I$16:$I$72)-ROW(Equipements!$I$16)+1),ROW(1:1))),"")} -> A4_P103_TEMP | K37: {=IFERROR(INDEX(Equipements!$P$16:$P$72,SMALL(IF(Equipements!$I$16:$I$72="Sonde de température",ROW(Equipements!$I$16:$I$72)-ROW(Equipements!$I$16)+1),ROW(1:1))),"")} -> Validé avec réserve | P37: Pluviomètre | T37: {=IFERROR(INDEX(Equipements!$K$16:$K$72,SMALL(IF(Equipements!$I$16:$I$72="Pluviomètre",ROW(Equipements!$I$16:$I$72)-ROW(Equipements!$I$16)+1),ROW(1:1))),"")} -> PLUVIO_SCL_ooo | X37: {=IFERROR(INDEX(Equipements!$P$16:$P$72,SMALL(IF(Equipements!$I$16:$I$72="Pluviomètre",ROW(Equipements!$I$16:$I$72)-ROW(Equipements!$I$16)+1),ROW(1:1))),"")}
I38: {=IFERROR(INDEX(Equipements!$K$16:$K$72,SMALL(IF(Equipements!$I$16:$I$72="Sonde de température",ROW(Equipements!$I$16:$I$72)-ROW(Equipements!$I$16)+1),ROW(2:2))),"")} | K38: {=IFERROR(INDEX(Equipements!$P$16:$P$72,SMALL(IF(Equipements!$I$16:$I$72="Sonde de température",ROW(Equipements!$I$16:$I$72)-ROW(Equipements!$I$16)+1),ROW(2:2))),"")} | M38: Ok | T38: {=IFERROR(INDEX(Equipements!$K$16:$K$72,SMALL(IF(Equipements!$I$16:$I$72="Pluviomètre",ROW(Equipements!$I$16:$I$72)-ROW(Equipements!$I$16)+1),ROW(2:2))),"")} -> PLUVIO_STEU_P1 | X38: {=IFERROR(INDEX(Equipements!$P$16:$P$72,SMALL(IF(Equipements!$I$16:$I$72="Pluviomètre",ROW(Equipements!$I$16:$I$72)-ROW(Equipements!$I$16)+1),ROW(2:2))),"")} -> Validé avec réserve | Z38: Ok
I39: {=IFERROR(INDEX(Equipements!$K$16:$K$72,SMALL(IF(Equipements!$I$16:$I$72="Sonde de température",ROW(Equipements!$I$16:$I$72)-ROW(Equipements!$I$16)+1),ROW(3:3))),"")} | K39: {=IFERROR(INDEX(Equipements!$P$16:$P$72,SMALL(IF(Equipements!$I$16:$I$72="Sonde de température",ROW(Equipements!$I$16:$I$72)-ROW(Equipements!$I$16)+1),ROW(3:3))),"")} | T39: {=IFERROR(INDEX(Equipements!$K$16:$K$72,SMALL(IF(Equipements!$I$16:$I$72="Pluviomètre",ROW(Equipements!$I$16:$I$72)-ROW(Equipements!$I$16)+1),ROW(3:3))),"")} | X39: {=IFERROR(INDEX(Equipements!$P$16:$P$72,SMALL(IF(Equipements!$I$16:$I$72="Pluviomètre",ROW(Equipements!$I$16:$I$72)-ROW(Equipements!$I$16)+1),ROW(3:3))),"")}
G40: Commentaire évaluation :
D45: Commentaire général
C51: SYNTHESE DISPOSITIFS AUTOSURVEILLANCE DE LA STATION D'ÉPURATION
D53: Détails des équipements contrôlés | M53: Score sur 100 | N53: Critères d'évaluation | X53: Commentaires d'évaluation
D54: Libellé | F54: Localisation | G54: Type | I54: Type d'équipement | K54: Evaluation controleur | N54: 1 | O54: 2 | P54: 3 | Q54: 4 | R54: 5 | S54: 6 | T54: 7 | U54: 8 | V54: 9 | W54: 10
D55: =Equipements!G16 -> A1_DO1_Q_Grav | F55: =Equipements!H16 -> A1 | G55: =Equipements!I16 -> Débitmètre gravitaire | I55: =Equipements!J16 -> Seuil | K55: =Equipements!P16 -> Validé | M55: =Equipements!N16 -> 100 | N55: =Equipements!W16 -> Validé | O55: =Equipements!X16 -> Validé | P55: =Equipements!Y16 -> Validé | Q55: =Equipements!Z16 -> Validé | R55: =Equipements!AA16 -> Validé | S55: =Equipements!AB16 -> Validé | T55: =Equipements!AC16 -> Validé | U55: =Equipements!AD16 -> Validé | ... W55: =Equipements!AF16 -> Oui | X55: =IF(Equipements!R16<>"",Equipements!R16,"") -> aaaaaaaa
D56: =Equipements!G17 -> PLUVIO_SCL_ooo | F56: =Equipements!H17 -> A1 | G56: =Equipements!I17 -> Pluviomètre | I56: =Equipements!J17 -> Pluviomètre | K56: =Equipements!P17 | M56: =Equipements!N17 -> 0 | N56: =Equipements!W17 | O56: =Equipements!X17 -> Non contrôlé | P56: =Equipements!Y17 | Q56: =Equipements!Z17 | R56: =Equipements!AA17 -> Non contrôlé | S56: =Equipements!AB17 -> Evaluation finale | T56: =Equipements!AC17 | U56: =Equipements!AD17 | ... W56: =Equipements!AF17 | X56: =IF(Equipements!R17<>"",Equipements!R17,"")
D57: =Equipements!G18 -> A2_P100_Q_Grav | F57: =Equipements!H18 -> A2 | G57: =Equipements!I18 -> Débitmètre gravitaire | I57: =Equipements!J18 -> Hauteur/Vitesse | K57: =Equipements!P18 -> Validé avec réserve | M57: =Equipements!N18 -> 80 | N57: =Equipements!W18 -> Validé | O57: =Equipements!X18 -> Validé | P57: =Equipements!Y18 -> Validé | Q57: =Equipements!Z18 -> Validé | R57: =Equipements!AA18 -> Validé | S57: =Equipements!AB18 -> Validé | T57: =Equipements!AC18 -> Non contrôlé | U57: =Equipements!AD18 -> Non contrôlé | ... W57: =Equipements!AF18 -> Oui | X57: =IF(Equipements!R18<>"",Equipements!R18,"")
D58: =Equipements!G19 -> A3_P102_Q_DEM | F58: =Equipements!H19 -> A3 | G58: =Equipements!I19 -> Débitmètre en charge | I58: =Equipements!J19 -> Débitmètre électromagnétique (eau) | K58: =Equipements!P19 -> Non Validé | M58: =Equipements!N19 -> 60 | N58: =Equipements!W19 -> Validé | O58: =Equipements!X19 -> Validé | P58: =Equipements!Y19 -> Validé | Q58: =Equipements!Z19 -> Non validé (>10%) | R58: =Equipements!AA19 -> Non validé | S58: =Equipements!AB19 -> Non validé | T58: =Equipements!AC19 -> Non validé | U58: =Equipements!AD19 -> Validé | ... W58: =Equipements!AF19 | X58: =IF(Equipements!R19<>"",Equipements!R19,"") -> Le dispositif en place
D59: =Equipements!G20 -> A3_P102_PREL | F59: =Equipements!H20 -> A3 | G59: =Equipements!I20 -> Préleveur | I59: =Equipements!J20 -> Préleveur Automatique | K59: =Equipements!P20 -> Validé | M59: =Equipements!N20 -> 85 | N59: =Equipements!W20 -> Validé | O59: =Equipements!X20 -> Non validé | P59: =Equipements!Y20 -> Validé | Q59: =Equipements!Z20 -> Validé | R59: =Equipements!AA20 -> Validé | S59: =Equipements!AB20 -> Validé | T59: =Equipements!AC20 -> Validé | U59: =Equipements!AD20 -> Validé | ... W59: =Equipements!AF20 -> Validé | X59: =IF(Equipements!R20<>"",Equipements!R20,"") -> Pb de positionnement
D60: =Equipements!G21 -> A4_P103_Q_Grav | F60: =Equipements!H21 -> A4 | G60: =Equipements!I21 -> Débitmètre gravitaire | I60: =Equipements!J21 -> Canal Venturi | K60: =Equipements!P21 -> Non validé | M60: =Equipements!N21 -> 0 | N60: =Equipements!W21 -> Validé | O60: =Equipements!X21 -> Validé | P60: =Equipements!Y21 -> Validé | Q60: =Equipements!Z21 -> Validé | R60: =Equipements!AA21 -> Validé | S60: =Equipements!AB21 -> Non contrôlé | T60: =Equipements!AC21 -> Validé | U60: =Equipements!AD21 -> Non validé | ... W60: =Equipements!AF21 -> Oui | X60: =IF(Equipements!R21<>"",Equipements!R21,"")
D61: =Equipements!G22 -> A4_P103_PREL | F61: =Equipements!H22 -> A4 | G61: =Equipements!I22 -> Préleveur | I61: =Equipements!J22 -> Préleveur Automatique | K61: =Equipements!P22 -> Validé | M61: =Equipements!N22 -> 100 | N61: =Equipements!W22 -> Validé | O61: =Equipements!X22 -> Validé | P61: =Equipements!Y22 -> Validé | Q61: =Equipements!Z22 -> Validé | R61: =Equipements!AA22 -> Validé | S61: =Equipements!AB22 -> Validé | T61: =Equipements!AC22 -> Validé | U61: =Equipements!AD22 -> Validé | ... W61: =Equipements!AF22 -> Validé | X61: =IF(Equipements!R22<>"",Equipements!R22,"")
D62: =Equipements!G23 -> A6_P104_Q_DEM | F62: =Equipements!H23 -> A6 | G62: =Equipements!I23 -> Débitmètre en charge | I62: =Equipements!J23 -> Débitmètre électromagnétique (boue/MDV) | K62: =Equipements!P23 -> Non validé | M62: =Equipements!N23 -> 40 | N62: =Equipements!W23 -> Validé | O62: =Equipements!X23 -> Validé | P62: =Equipements!Y23 -> Validé | Q62: =Equipements!Z23 -> Non validé (>10%) | R62: =Equipements!AA23 | S62: =Equipements!AB23 | T62: =Equipements!AC23 | U62: =Equipements!AD23 -> Validé | ... W62: =Equipements!AF23 | X62: =IF(Equipements!R23<>"",Equipements!R23,"")
D63: =Equipements!G24 -> A4_P103_TEMP | F63: =Equipements!H24 -> A4 | G63: =Equipements!I24 -> Sonde de température | I63: =Equipements!J24 -> 0 | K63: =Equipements!P24 -> Validé avec réserve | M63: =Equipements!N24 -> 100 | N63: =Equipements!W24 -> Validé | O63: =Equipements!X24 -> Validé | P63: =Equipements!Y24 -> Validé | Q63: =Equipements!Z24 -> Validé | R63: =Equipements!AA24 -> Evaluation finale | S63: =Equipements!AB24 -> Validé avec réserve | T63: =Equipements!AC24 | U63: =Equipements!AD24 | ... W63: =Equipements!AF24 | X63: =IF(Equipements!R24<>"",Equipements!R24,"")
D64: =Equipements!G25 -> PLUVIO_STEU_P1 | F64: =Equipements!H25 -> A3 | G64: =Equipements!I25 -> Pluviomètre | I64: =Equipements!J25 -> Pluviomètre | K64: =Equipements!P25 -> Validé avec réserve | M64: =Equipements!N25 -> 70 | N64: =Equipements!W25 -> Validé | O64: =Equipements!X25 -> Validé | P64: =Equipements!Y25 -> Validé | Q64: =Equipements!Z25 -> Validé | R64: =Equipements!AA25 -> Non contrôlé | S64: =Equipements!AB25 -> Evaluation finale | T64: =Equipements!AC25 -> Validé avec réserve | U64: =Equipements!AD25 | ... W64: =Equipements!AF25 | X64: =IF(Equipements!R25<>"",Equipements!R25,"")
D65: =Equipements!G26 | F65: =Equipements!H26 | G65: =Equipements!I26 | I65: =Equipements!J26 | K65: =Equipements!P26 | M65: =Equipements!N26 | N65: =Equipements!W26 | O65: =Equipements!X26 | P65: =Equipements!Y26 | Q65: =Equipements!Z26 | R65: =Equipements!AA26 | S65: =Equipements!AB26 | T65: =Equipements!AC26 | U65: =Equipements!AD26 | ... W65: =Equipements!AF26 | X65: =IF(Equipements!R26<>"",Equipements!R26,"")
D66: =Equipements!G27 | F66: =Equipements!H27 | G66: =Equipements!I27 | I66: =Equipements!J27 | K66: =Equipements!P27 | M66: =Equipements!N27 | N66: =Equipements!W27 | O66: =Equipements!X27 | P66: =Equipements!Y27 | Q66: =Equipements!Z27 | R66: =Equipements!AA27 | S66: =Equipements!AB27 | T66: =Equipements!AC27 | U66: =Equipements!AD27 | ... W66: =Equipements!AF27 | X66: =IF(Equipements!R27<>"",Equipements!R27,"")
D67: =Equipements!G28 | F67: =Equipements!H28 | G67: =Equipements!I28 | I67: =Equipements!J28 | K67: =Equipements!P28 | M67: =Equipements!N28 | N67: =Equipements!W28 | O67: =Equipements!X28 | P67: =Equipements!Y28 | Q67: =Equipements!Z28 | R67: =Equipements!AA28 | S67: =Equipements!AB28 | T67: =Equipements!AC28 | U67: =Equipements!AD28 | ... W67: =Equipements!AF28 | X67: =IF(Equipements!R28<>"",Equipements!R28,"")

Sheet PARAM
A3: Equipement Q | B3: Equipement Prel | C3: Type | D3: Liste des statuts | E3: Code | F3: Code | G3: Liste des statuts | H3: Liste des statuts | I3: Code
A4: Canal Venturi | B4: Préleveur Automatique | C4: Débitmètre en charge | D4: Validé | E4: A2 | F4: A1 | G4: Oui | H4: Agréé | I4: A2
A5: Débitmètre électromagnétique (eau) | B5: Vanne de prélèvement asservie | C5: Débitmètre gravitaire | D5: Non validé | E5: A3 | F5: R1 | G5: Non | H5: Non agréé | I5: A3
A6: Débitmètre électromagnétique (boue/MDV) | B6: Prélèvement ponctuel | C6: Préleveur | D6: Non contrôlé | E6: A4 | F6: R2 | I6: A4
A7: Seuil | C7: Sonde de température | D7: Validé avec réserve | E7: A5 | F7: R3 | I7: A5
A8: Caisson | D8: Non validé (absence d'équipement) | E8: A6 | I8: A6
A9: Loi COACHs | D9: Non validé (équipement insuffisant) | E9: A7 | I9: A7
A10: Débitmètre électromagnétique partiellement plein | E10: A8 | I10: A8
A11: Clapet | E11: S1 | I11: S1
A12: Détecteur de surverse | E12: S2 | I12: S2
A13: Modélisation | E13: S3 | I13: S3
A14: Hauteur/Vitesse | E14: S4 | I14: S4
A15: Point non existant | E15: S5 | I15: S5
E16: S12 | I16: S12
E17: S13 | I17: S13
E18: S16 | I18: S16
E19: S19 | I19: S19
A20: LISTE_1 | B20: LISTE_2 | C20: LISTE_3 | D20: LISTE_4 | F20: LISTE_5
A21: Oui | B21: Validé | C21: Validé | D21: Validé | F21: Validé
A22: Non | B22: Non validé | C22: Non validé | D22: Non validé | F22: Entre 5 et 10%
B23: Non contrôlé | C23: Non contrôlé | D23: Non contrôlé | F23: Non validé (>10%)
C24: Validé avec réserve | D24: Validé avec réserve | F24: Non contrôlé
D25: Non validé (absence d'équipement)
D26: Non validé (équipement insuffisant)
A28: Type équipement : débimètre
A29: Q en charge | B29: Q Gravitaire | C29: Equipement de contrôle H
A30: Débitmètre électromagnétique (eau) | B30: Canal Venturi | C30: Réglet
A31: Débitmètre électromagnétique (boue/MDV) | B31: Seuil | C31: Sonde
A32: Organe deprimogène (pito...) | B32: Caisson | C32: Câble
A33: Débitmètre Ultrason | B33: Loi COACHs
A34: Modélisation | B34: Débitmètre électromagnétique partiellement plein
A35: compteur mécanique | B35: Clapet
A36: Point non existant | B36: Détecteur de surverse
B37: Modélisation
B38: Hauteur/Vitesse
B39: Point non existant
A42: Listes fiches terrain
A43: Asservissement | B43: Conformité | C43: Type_capteur | D43: Satisfaction | E43: Fréquence | F43: Conditions météo | G43: Montage sonde
A44: Au débit | B44: Conforme | C44: Ultrason | D44: Satisfaisant | E44: Journalière | F44: Temps sec | G44: En /
A45: Au temps | B45: Conforme avec réserve | C45: Radar | D45: Non satisfaisant | E45: Hebdomadaire | F45: Temps de pluie | G45: En V
A46: Inconnu | B46: Non conforme | C46: Piezo | D46: Non vérifié | E46: Mensuelle | F46: Inconnues | G46: En W
B47: Non vérifié | C47: Bulle à bulle | E47: Bimensuelle | G47: En N
B48: Non vérifiable | C48: Autre | E48: Trimestrielle
E49: Semestrielle
E50: Annuelle
E51: Autre
A53: Listes méthode contrôle
A54: Méthode | B54: Type de mesure
A55: … | B55: Ponctuelle
A56: Simulation d'une hauteur d'eau (plaque) | B56: En continu
A57: Mesure en parallèle
A58: Simulation d'une hauteur d'eau et mesure en parallèle

Sheet Recap_equipements
B1: Préparation des données pour la feuilles synthèse et pour les exports
B2: Paramètres de localisation des données dans les cellules
B4: Facteur Qualité | D4: Type Equipement | E4: Type
B5: =IF(Qualité!L26="Non validé",0.9,1) -> 1 | E5: cellule typeE | F5: cellule score | G5: cellule eval | H5: cellule commentaire score | I5: cellule commentaire
D6: Pluviomètre | E6: D24 | F6: P32 | G6: N32 | H6: D32 | I6: C36
D7: =PARAM!$C4 -> Débitmètre en charge | E7: D32 | F7: P45 | G7: N45 | H7: D45 | I7: C49
D8: =PARAM!$C5 -> Débitmètre gravitaire | E8: D40 | F8: P53 | G8: N53 | H8: D53 | I8: C57
D9: =PARAM!$C6 -> Préleveur | E9: D37 | F9: P50 | G9: N50 | H9: D50 | I9: C54
D10: =PARAM!$C7 -> Sonde de température | E10: D26 | F10: P33 | G10: N33 | H10: D33 | I10: C37
D12: Type ligne | E12: Ligne
D13: Ligne STEU | E13: =Descriptif!$AD$3 -> 33 | F13: =E13+1 -> 34 | G13: =F13+1 -> 35 | H13: =G13+1 -> 36 | I13: =H13+1 -> 37 | J13: =I13+1 -> 38 | K13: =J13+1 -> 39 | L13: =K13+1 -> 40 | M13: =L13+1 -> 41 | ... S13: =R13+1 -> 47
D14: Ligne SCL | E14: =Descriptif!$AD$2 -> 13 | F14: =E14+1 -> 14 | G14: =F14+1 -> 15 | H14: =G14+1 -> 16 | I14: =H14+1 -> 17 | J14: =I14+1 -> 18 | K14: =J14+1 -> 19 | L14: =K14+1 -> 20 | M14: =L14+1 -> 21 | ... S14: =R14+1 -> 27
B16: Identification des feuilles de données
B18: Reg. | C18: Log. | F18: Point 1 | G18: Point 2 | H18: Point 3 | I18: Point 4 | J18: Point 5 | K18: Point 6 | L18: Point 7 | M18: Point 8 | N18: Point 9 | O18: Point 10 | P18: Point 11 | Q18: Point 12 | R18: Point 13 | S18: Point 14 | T18: Point 15
B19: A3 | C19: S1 | D19: =$D$7 -> Débitmètre en charge | F19: =IF(AND(OR(INDIRECT("Descriptif!I"&E$13)=Recap_equipements!$B19,INDIRECT("Descriptif!I"&E$13)=Recap_equipements!$C19),INDIRECT("Descriptif!M"&E$13)=$D19),INDIRECT("Descriptif!F"&E$13),"") | G19: =IF(AND(OR(INDIRECT("Descriptif!I"&F$13)=Recap_equipements!$B19,INDIRECT("Descriptif!I"&F$13)=Recap_equipements!$C19),INDIRECT("Descriptif!M"&F$13)=$D19),INDIRECT("Descriptif!F"&F$13),"") -> A3_P102_Q_DEM | H19: =IF(AND(OR(INDIRECT("Descriptif!I"&G$13)=Recap_equipements!$B19,INDIRECT("Descriptif!I"&G$13)=Recap_equipements!$C19),INDIRECT("Descriptif!M"&G$13)=$D19),INDIRECT("Descriptif!F"&G$13),"") | I19: =IF(AND(OR(INDIRECT("Descriptif!I"&H$13)=Recap_equipements!$B19,INDIRECT("Descriptif!I"&H$13)=Recap_equipements!$C19),INDIRECT("Descriptif!M"&H$13)=$D19),INDIRECT("Descriptif!F"&H$13),"") | J19: =IF(AND(OR(INDIRECT("Descriptif!I"&I$13)=Recap_equipements!$B19,INDIRECT("Descriptif!I"&I$13)=Recap_equipements!$C19),INDIRECT("Descriptif!M"&I$13)=$D19),INDIRECT("Descriptif!F"&I$13),"") | K19: =IF(AND(OR(INDIRECT("Descriptif!I"&J$13)=Recap_equipements!$B19,INDIRECT("Descriptif!I"&J$13)=Recap_equipements!$C19),INDIRECT("Descriptif!M"&J$13)=$D19),INDIRECT("Descriptif!F"&J$13),"") | L19: =IF(AND(OR(INDIRECT("Descriptif!I"&K$13)=Recap_equipements!$B19,INDIRECT("Descriptif!I"&K$13)=Recap_equipements!$C19),INDIRECT("Descriptif!M"&K$13)=$D19),INDIRECT("Descriptif!F"&K$13),"") | M19: =IF(AND(OR(INDIRECT("Descriptif!I"&L$13)=Recap_equipements!$B19,INDIRECT("Descriptif!I"&L$13)=Recap_equipements!$C19),INDIRECT("Descriptif!M"&L$13)=$D19),INDIRECT("Descriptif!F"&L$13),"") | ... T19: =IF(AND(OR(INDIRECT("Descriptif!I"&S$13)=Recap_equipements!$B19,INDIRECT("Descriptif!I"&S$13)=Recap_equipements!$C19),INDIRECT("Descriptif!M"&S$13)=$D19),INDIRECT("Descriptif!F"&S$13),"")
D20: =$D$8 -> Débitmètre gravitaire | F20: =IF(AND(OR(INDIRECT("Descriptif!I"&E$13)=Recap_equipements!$B19,INDIRECT("Descriptif!I"&E$13)=Recap_equipements!$C19),INDIRECT("Descriptif!M"&E$13)=$D20),INDIRECT("Descriptif!F"&E$13),"") | G20: =IF(AND(OR(INDIRECT("Descriptif!I"&F$13)=Recap_equipements!$B19,INDIRECT("Descriptif!I"&F$13)=Recap_equipements!$C19),INDIRECT("Descriptif!M"&F$13)=$D20),INDIRECT("Descriptif!F"&F$13),"") | H20: =IF(AND(OR(INDIRECT("Descriptif!I"&G$13)=Recap_equipements!$B19,INDIRECT("Descriptif!I"&G$13)=Recap_equipements!$C19),INDIRECT("Descriptif!M"&G$13)=$D20),INDIRECT("Descriptif!F"&G$13),"") | I20: =IF(AND(OR(INDIRECT("Descriptif!I"&H$13)=Recap_equipements!$B19,INDIRECT("Descriptif!I"&H$13)=Recap_equipements!$C19),INDIRECT("Descriptif!M"&H$13)=$D20),INDIRECT("Descriptif!F"&H$13),"") | J20: =IF(AND(OR(INDIRECT("Descriptif!I"&I$13)=Recap_equipements!$B19,INDIRECT("Descriptif!I"&I$13)=Recap_equipements!$C19),INDIRECT("Descriptif!M"&I$13)=$D20),INDIRECT("Descriptif!F"&I$13),"") | K20: =IF(AND(OR(INDIRECT("Descriptif!I"&J$13)=Recap_equipements!$B19,INDIRECT("Descriptif!I"&J$13)=Recap_equipements!$C19),INDIRECT("Descriptif!M"&J$13)=$D20),INDIRECT("Descriptif!F"&J$13),"") | L20: =IF(AND(OR(INDIRECT("Descriptif!I"&K$13)=Recap_equipements!$B19,INDIRECT("Descriptif!I"&K$13)=Recap_equipements!$C19),INDIRECT("Descriptif!M"&K$13)=$D20),INDIRECT("Descriptif!F"&K$13),"") | M20: =IF(AND(OR(INDIRECT("Descriptif!I"&L$13)=Recap_equipements!$B19,INDIRECT("Descriptif!I"&L$13)=Recap_equipements!$C19),INDIRECT("Descriptif!M"&L$13)=$D20),INDIRECT("Descriptif!F"&L$13),"") | ... T20: =IF(AND(OR(INDIRECT("Descriptif!I"&S$13)=Recap_equipements!$B19,INDIRECT("Descriptif!I"&S$13)=Recap_equipements!$C19),INDIRECT("Descriptif!M"&S$13)=$D20),INDIRECT("Descriptif!F"&S$13),"")
D21: =$D$9 -> Préleveur | F21: =IF(AND(OR(INDIRECT("Descriptif!I"&E$13)=Recap_equipements!$B19,INDIRECT("Descriptif!I"&E$13)=Recap_equipements!$C19),INDIRECT("Descriptif!M"&E$13)=$D21),INDIRECT("Descriptif!F"&E$13),"") | G21: =IF(AND(OR(INDIRECT("Descriptif!I"&F$13)=Recap_equipements!$B19,INDIRECT("Descriptif!I"&F$13)=Recap_equipements!$C19),INDIRECT("Descriptif!M"&F$13)=$D21),INDIRECT("Descriptif!F"&F$13),"") | H21: =IF(AND(OR(INDIRECT("Descriptif!I"&G$13)=Recap_equipements!$B19,INDIRECT("Descriptif!I"&G$13)=Recap_equipements!$C19),INDIRECT("Descriptif!M"&G$13)=$D21),INDIRECT("Descriptif!F"&G$13),"") -> A3_P102_PREL | I21: =IF(AND(OR(INDIRECT("Descriptif!I"&H$13)=Recap_equipements!$B19,INDIRECT("Descriptif!I"&H$13)=Recap_equipements!$C19),INDIRECT("Descriptif!M"&H$13)=$D21),INDIRECT("Descriptif!F"&H$13),"") | J21: =IF(AND(OR(INDIRECT("Descriptif!I"&I$13)=Recap_equipements!$B19,INDIRECT("Descriptif!I"&I$13)=Recap_equipements!$C19),INDIRECT("Descriptif!M"&I$13)=$D21),INDIRECT("Descriptif!F"&I$13),"") | K21: =IF(AND(OR(INDIRECT("Descriptif!I"&J$13)=Recap_equipements!$B19,INDIRECT("Descriptif!I"&J$13)=Recap_equipements!$C19),INDIRECT("Descriptif!M"&J$13)=$D21),INDIRECT("Descriptif!F"&J$13),"") | L21: =IF(AND(OR(INDIRECT("Descriptif!I"&K$13)=Recap_equipements!$B19,INDIRECT("Descriptif!I"&K$13)=Recap_equipements!$C19),INDIRECT("Descriptif!M"&K$13)=$D21),INDIRECT("Descriptif!F"&K$13),"") | M21: =IF(AND(OR(INDIRECT("Descriptif!I"&L$13)=Recap_equipements!$B19,INDIRECT("Descriptif!I"&L$13)=Recap_equipements!$C19),INDIRECT("Descriptif!M"&L$13)=$D21),INDIRECT("Descriptif!F"&L$13),"") | ... T21: =IF(AND(OR(INDIRECT("Descriptif!I"&S$13)=Recap_equipements!$B19,INDIRECT("Descriptif!I"&S$13)=Recap_equipements!$C19),INDIRECT("Descriptif!M"&S$13)=$D21),INDIRECT("Descriptif!F"&S$13),"")
D22: Analytique | F22: =IF(F21<>"",VLOOKUP(F21,Analytique!$X$3:$AD$33,1,FALSE),"") | G22: =IF(G21<>"",VLOOKUP(G21,Analytique!$X$3:$AD$33,1,FALSE),"") | H22: =IF(H21<>"",VLOOKUP(H21,Analytique!$X$3:$AD$33,1,FALSE),"") -> A3_P102_PREL | I22: =IF(I21<>"",VLOOKUP(I21,Analytique!$X$3:$AD$33,1,FALSE),"") | J22: =IF(J21<>"",VLOOKUP(J21,Analytique!$X$3:$AD$33,1,FALSE),"") | K22: =IF(K21<>"",VLOOKUP(K21,Analytique!$X$3:$AD$33,1,FALSE),"") | L22: =IF(L21<>"",VLOOKUP(L21,Analytique!$X$3:$AD$33,1,FALSE),"") | M22: =IF(M21<>"",VLOOKUP(M21,Analytique!$X$3:$AD$33,1,FALSE),"") | ... T22: =IF(T21<>"",VLOOKUP(T21,Analytique!$X$3:$AD$33,1,FALSE),"")
D23: =$D$10 -> Sonde de température | F23: =IF(AND(OR(INDIRECT("Descriptif!I"&E$13)=Recap_equipements!$B19,INDIRECT("Descriptif!I"&E$13)=Recap_equipements!$C19),INDIRECT("Descriptif!M"&E$13)=$D23),INDIRECT("Descriptif!F"&E$13),"") | G23: =IF(AND(OR(INDIRECT("Descriptif!I"&F$13)=Recap_equipements!$B19,INDIRECT("Descriptif!I"&F$13)=Recap_equipements!$C19),INDIRECT("Descriptif!M"&F$13)=$D23),INDIRECT("Descriptif!F"&F$13),"") | H23: =IF(AND(OR(INDIRECT("Descriptif!I"&G$13)=Recap_equipements!$B19,INDIRECT("Descriptif!I"&G$13)=Recap_equipements!$C19),INDIRECT("Descriptif!M"&G$13)=$D23),INDIRECT("Descriptif!F"&G$13),"") | I23: =IF(AND(OR(INDIRECT("Descriptif!I"&H$13)=Recap_equipements!$B19,INDIRECT("Descriptif!I"&H$13)=Recap_equipements!$C19),INDIRECT("Descriptif!M"&H$13)=$D23),INDIRECT("Descriptif!F"&H$13),"") | J23: =IF(AND(OR(INDIRECT("Descriptif!I"&I$13)=Recap_equipements!$B19,INDIRECT("Descriptif!I"&I$13)=Recap_equipements!$C19),INDIRECT("Descriptif!M"&I$13)=$D23),INDIRECT("Descriptif!F"&I$13),"") | K23: =IF(AND(OR(INDIRECT("Descriptif!I"&J$13)=Recap_equipements!$B19,INDIRECT("Descriptif!I"&J$13)=Recap_equipements!$C19),INDIRECT("Descriptif!M"&J$13)=$D23),INDIRECT("Descriptif!F"&J$13),"") | L23: =IF(AND(OR(INDIRECT("Descriptif!I"&K$13)=Recap_equipements!$B19,INDIRECT("Descriptif!I"&K$13)=Recap_equipements!$C19),INDIRECT("Descriptif!M"&K$13)=$D23),INDIRECT("Descriptif!F"&K$13),"") | M23: =IF(AND(OR(INDIRECT("Descriptif!I"&L$13)=Recap_equipements!$B19,INDIRECT("Descriptif!I"&L$13)=Recap_equipements!$C19),INDIRECT("Descriptif!M"&L$13)=$D23),INDIRECT("Descriptif!F"&L$13),"") | ... T23: =IF(AND(OR(INDIRECT("Descriptif!I"&S$13)=Recap_equipements!$B19,INDIRECT("Descriptif!I"&S$13)=Recap_equipements!$C19),INDIRECT("Descriptif!M"&S$13)=$D23),INDIRECT("Descriptif!F"&S$13),"")
B24: A4 | C24: S2 | D24: =$D$7 -> Débitmètre en charge | F24: =IF(AND(OR(INDIRECT("Descriptif!I"&E$13)=Recap_equipements!$B24,INDIRECT("Descriptif!I"&E$13)=Recap_equipements!$C24),INDIRECT("Descriptif!M"&E$13)=$D24),INDIRECT("Descriptif!F"&E$13),"") | G24: =IF(AND(OR(INDIRECT("Descriptif!I"&F$13)=Recap_equipements!$B24,INDIRECT("Descriptif!I"&F$13)=Recap_equipements!$C24),INDIRECT("Descriptif!M"&F$13)=$D24),INDIRECT("Descriptif!F"&F$13),"") | H24: =IF(AND(OR(INDIRECT("Descriptif!I"&G$13)=Recap_equipements!$B24,INDIRECT("Descriptif!I"&G$13)=Recap_equipements!$C24),INDIRECT("Descriptif!M"&G$13)=$D24),INDIRECT("Descriptif!F"&G$13),"") | I24: =IF(AND(OR(INDIRECT("Descriptif!I"&H$13)=Recap_equipements!$B24,INDIRECT("Descriptif!I"&H$13)=Recap_equipements!$C24),INDIRECT("Descriptif!M"&H$13)=$D24),INDIRECT("Descriptif!F"&H$13),"") | J24: =IF(AND(OR(INDIRECT("Descriptif!I"&I$13)=Recap_equipements!$B24,INDIRECT("Descriptif!I"&I$13)=Recap_equipements!$C24),INDIRECT("Descriptif!M"&I$13)=$D24),INDIRECT("Descriptif!F"&I$13),"") | K24: =IF(AND(OR(INDIRECT("Descriptif!I"&J$13)=Recap_equipements!$B24,INDIRECT("Descriptif!I"&J$13)=Recap_equipements!$C24),INDIRECT("Descriptif!M"&J$13)=$D24),INDIRECT("Descriptif!F"&J$13),"") | L24: =IF(AND(OR(INDIRECT("Descriptif!I"&K$13)=Recap_equipements!$B24,INDIRECT("Descriptif!I"&K$13)=Recap_equipements!$C24),INDIRECT("Descriptif!M"&K$13)=$D24),INDIRECT("Descriptif!F"&K$13),"") | M24: =IF(AND(OR(INDIRECT("Descriptif!I"&L$13)=Recap_equipements!$B24,INDIRECT("Descriptif!I"&L$13)=Recap_equipements!$C24),INDIRECT("Descriptif!M"&L$13)=$D24),INDIRECT("Descriptif!F"&L$13),"") | ... T24: =IF(AND(OR(INDIRECT("Descriptif!I"&S$13)=Recap_equipements!$B24,INDIRECT("Descriptif!I"&S$13)=Recap_equipements!$C24),INDIRECT("Descriptif!M"&S$13)=$D24),INDIRECT("Descriptif!F"&S$13),"")
D25: =$D$8 -> Débitmètre gravitaire | F25: =IF(AND(OR(INDIRECT("Descriptif!I"&E$13)=Recap_equipements!$B24,INDIRECT("Descriptif!I"&E$13)=Recap_equipements!$C24),INDIRECT("Descriptif!M"&E$13)=$D25),INDIRECT("Descriptif!F"&E$13),"") | G25: =IF(AND(OR(INDIRECT("Descriptif!I"&F$13)=Recap_equipements!$B24,INDIRECT("Descriptif!I"&F$13)=Recap_equipements!$C24),INDIRECT("Descriptif!M"&F$13)=$D25),INDIRECT("Descriptif!F"&F$13),"") | H25: =IF(AND(OR(INDIRECT("Descriptif!I"&G$13)=Recap_equipements!$B24,INDIRECT("Descriptif!I"&G$13)=Recap_equipements!$C24),INDIRECT("Descriptif!M"&G$13)=$D25),INDIRECT("Descriptif!F"&G$13),"") | I25: =IF(AND(OR(INDIRECT("Descriptif!I"&H$13)=Recap_equipements!$B24,INDIRECT("Descriptif!I"&H$13)=Recap_equipements!$C24),INDIRECT("Descriptif!M"&H$13)=$D25),INDIRECT("Descriptif!F"&H$13),"") -> A4_P103_Q_Grav | J25: =IF(AND(OR(INDIRECT("Descriptif!I"&I$13)=Recap_equipements!$B24,INDIRECT("Descriptif!I"&I$13)=Recap_equipements!$C24),INDIRECT("Descriptif!M"&I$13)=$D25),INDIRECT("Descriptif!F"&I$13),"") | K25: =IF(AND(OR(INDIRECT("Descriptif!I"&J$13)=Recap_equipements!$B24,INDIRECT("Descriptif!I"&J$13)=Recap_equipements!$C24),INDIRECT("Descriptif!M"&J$13)=$D25),INDIRECT("Descriptif!F"&J$13),"") | L25: =IF(AND(OR(INDIRECT("Descriptif!I"&K$13)=Recap_equipements!$B24,INDIRECT("Descriptif!I"&K$13)=Recap_equipements!$C24),INDIRECT("Descriptif!M"&K$13)=$D25),INDIRECT("Descriptif!F"&K$13),"") | M25: =IF(AND(OR(INDIRECT("Descriptif!I"&L$13)=Recap_equipements!$B24,INDIRECT("Descriptif!I"&L$13)=Recap_equipements!$C24),INDIRECT("Descriptif!M"&L$13)=$D25),INDIRECT("Descriptif!F"&L$13),"") | ... T25: =IF(AND(OR(INDIRECT("Descriptif!I"&S$13)=Recap_equipements!$B24,INDIRECT("Descriptif!I"&S$13)=Recap_equipements!$C24),INDIRECT("Descriptif!M"&S$13)=$D25),INDIRECT("Descriptif!F"&S$13),"")
D26: =$D$9 -> Préleveur | F26: =IF(AND(OR(INDIRECT("Descriptif!I"&E$13)=Recap_equipements!$B24,INDIRECT("Descriptif!I"&E$13)=Recap_equipements!$C24),INDIRECT("Descriptif!M"&E$13)=$D26),INDIRECT("Descriptif!F"&E$13),"") | G26: =IF(AND(OR(INDIRECT("Descriptif!I"&F$13)=Recap_equipements!$B24,INDIRECT("Descriptif!I"&F$13)=Recap_equipements!$C24),INDIRECT("Descriptif!M"&F$13)=$D26),INDIRECT("Descriptif!F"&F$13),"") | H26: =IF(AND(OR(INDIRECT("Descriptif!I"&G$13)=Recap_equipements!$B24,INDIRECT("Descriptif!I"&G$13)=Recap_equipements!$C24),INDIRECT("Descriptif!M"&G$13)=$D26),INDIRECT("Descriptif!F"&G$13),"") | I26: =IF(AND(OR(INDIRECT("Descriptif!I"&H$13)=Recap_equipements!$B24,INDIRECT("Descriptif!I"&H$13)=Recap_equipements!$C24),INDIRECT("Descriptif!M"&H$13)=$D26),INDIRECT("Descriptif!F"&H$13),"") | J26: =IF(AND(OR(INDIRECT("Descriptif!I"&I$13)=Recap_equipements!$B24,INDIRECT("Descriptif!I"&I$13)=Recap_equipements!$C24),INDIRECT("Descriptif!M"&I$13)=$D26),INDIRECT("Descriptif!F"&I$13),"") -> A4_P103_PREL | K26: =IF(AND(OR(INDIRECT("Descriptif!I"&J$13)=Recap_equipements!$B24,INDIRECT("Descriptif!I"&J$13)=Recap_equipements!$C24),INDIRECT("Descriptif!M"&J$13)=$D26),INDIRECT("Descriptif!F"&J$13),"") | L26: =IF(AND(OR(INDIRECT("Descriptif!I"&K$13)=Recap_equipements!$B24,INDIRECT("Descriptif!I"&K$13)=Recap_equipements!$C24),INDIRECT("Descriptif!M"&K$13)=$D26),INDIRECT("Descriptif!F"&K$13),"") | M26: =IF(AND(OR(INDIRECT("Descriptif!I"&L$13)=Recap_equipements!$B24,INDIRECT("Descriptif!I"&L$13)=Recap_equipements!$C24),INDIRECT("Descriptif!M"&L$13)=$D26),INDIRECT("Descriptif!F"&L$13),"") | ... T26: =IF(AND(OR(INDIRECT("Descriptif!I"&S$13)=Recap_equipements!$B24,INDIRECT("Descriptif!I"&S$13)=Recap_equipements!$C24),INDIRECT("Descriptif!M"&S$13)=$D26),INDIRECT("Descriptif!F"&S$13),"")
D27: Analytique | F27: =IF(F26<>"",VLOOKUP(F26,Analytique!$X$3:$AD$33,1,FALSE),"") | G27: =IF(G26<>"",VLOOKUP(G26,Analytique!$X$3:$AD$33,1,FALSE),"") | H27: =IF(H26<>"",VLOOKUP(H26,Analytique!$X$3:$AD$33,1,FALSE),"") | I27: =IF(I26<>"",VLOOKUP(I26,Analytique!$X$3:$AD$33,1,FALSE),"") | J27: =IF(J26<>"",VLOOKUP(J26,Analytique!$X$3:$AD$33,1,FALSE),"") -> A4_P103_PREL | K27: =IF(K26<>"",VLOOKUP(K26,Analytique!$X$3:$AD$33,1,FALSE),"") | L27: =IF(L26<>"",VLOOKUP(L26,Analytique!$X$3:$AD$33,1,FALSE),"") | M27: =IF(M26<>"",VLOOKUP(M26,Analytique!$X$3:$AD$33,1,FALSE),"") | ... T27: =IF(T26<>"",VLOOKUP(T26,Analytique!$X$3:$AD$33,1,FALSE),"")
D28: =$D$10 -> Sonde de température | F28: =IF(AND(OR(INDIRECT("Descriptif!I"&E$13)=Recap_equipements!$B24,INDIRECT("Descriptif!I"&E$13)=Recap_equipements!$C24),INDIRECT("Descriptif!M"&E$13)=$D28),INDIRECT("Descriptif!F"&E$13),"") | G28: =IF(AND(OR(INDIRECT("Descriptif!I"&F$13)=Recap_equipements!$B24,INDIRECT("Descriptif!I"&F$13)=Recap_equipements!$C24),INDIRECT("Descriptif!M"&F$13)=$D28),INDIRECT("Descriptif!F"&F$13),"") | H28: =IF(AND(OR(INDIRECT("Descriptif!I"&G$13)=Recap_equipements!$B24,INDIRECT("Descriptif!I"&G$13)=Recap_equipements!$C24),INDIRECT("Descriptif!M"&G$13)=$D28),INDIRECT("Descriptif!F"&G$13),"") | I28: =IF(AND(OR(INDIRECT("Descriptif!I"&H$13)=Recap_equipements!$B24,INDIRECT("Descriptif!I"&H$13)=Recap_equipements!$C24),INDIRECT("Descriptif!M"&H$13)=$D28),INDIRECT("Descriptif!F"&H$13),"") | J28: =IF(AND(OR(INDIRECT("Descriptif!I"&I$13)=Recap_equipements!$B24,INDIRECT("Descriptif!I"&I$13)=Recap_equipements!$C24),INDIRECT("Descriptif!M"&I$13)=$D28),INDIRECT("Descriptif!F"&I$13),"") | K28: =IF(AND(OR(INDIRECT("Descriptif!I"&J$13)=Recap_equipements!$B24,INDIRECT("Descriptif!I"&J$13)=Recap_equipements!$C24),INDIRECT("Descriptif!M"&J$13)=$D28),INDIRECT("Descriptif!F"&J$13),"") | L28: =IF(AND(OR(INDIRECT("Descriptif!I"&K$13)=Recap_equipements!$B24,INDIRECT("Descriptif!I"&K$13)=Recap_equipements!$C24),INDIRECT("Descriptif!M"&K$13)=$D28),INDIRECT("Descriptif!F"&K$13),"") -> A4_P103_TEMP | M28: =IF(AND(OR(INDIRECT("Descriptif!I"&L$13)=Recap_equipements!$B24,INDIRECT("Descriptif!I"&L$13)=Recap_equipements!$C24),INDIRECT("Descriptif!M"&L$13)=$D28),INDIRECT("Descriptif!F"&L$13),"") | ... T28: =IF(AND(OR(INDIRECT("Descriptif!I"&S$13)=Recap_equipements!$B24,INDIRECT("Descriptif!I"&S$13)=Recap_equipements!$C24),INDIRECT("Descriptif!M"&S$13)=$D28),INDIRECT("Descriptif!F"&S$13),"")
B29: A2 | C29: S16 | D29: =$D$7 -> Débitmètre en charge | F29: =IF(AND(OR(INDIRECT("Descriptif!I"&E$13)=Recap_equipements!$B29,INDIRECT("Descriptif!I"&E$13)=Recap_equipements!$C29),INDIRECT("Descriptif!M"&E$13)=$D29),INDIRECT("Descriptif!F"&E$13),"") | G29: =IF(AND(OR(INDIRECT("Descriptif!I"&F$13)=Recap_equipements!$B29,INDIRECT("Descriptif!I"&F$13)=Recap_equipements!$C29),INDIRECT("Descriptif!M"&F$13)=$D29),INDIRECT("Descriptif!F"&F$13),"") | H29: =IF(AND(OR(INDIRECT("Descriptif!I"&G$13)=Recap_equipements!$B29,INDIRECT("Descriptif!I"&G$13)=Recap_equipements!$C29),INDIRECT("Descriptif!M"&G$13)=$D29),INDIRECT("Descriptif!F"&G$13),"") | I29: =IF(AND(OR(INDIRECT("Descriptif!I"&H$13)=Recap_equipements!$B29,INDIRECT("Descriptif!I"&H$13)=Recap_equipements!$C29),INDIRECT("Descriptif!M"&H$13)=$D29),INDIRECT("Descriptif!F"&H$13),"") | J29: =IF(AND(OR(INDIRECT("Descriptif!I"&I$13)=Recap_equipements!$B29,INDIRECT("Descriptif!I"&I$13)=Recap_equipements!$C29),INDIRECT("Descriptif!M"&I$13)=$D29),INDIRECT("Descriptif!F"&I$13),"") | K29: =IF(AND(OR(INDIRECT("Descriptif!I"&J$13)=Recap_equipements!$B29,INDIRECT("Descriptif!I"&J$13)=Recap_equipements!$C29),INDIRECT("Descriptif!M"&J$13)=$D29),INDIRECT("Descriptif!F"&J$13),"") | L29: =IF(AND(OR(INDIRECT("Descriptif!I"&K$13)=Recap_equipements!$B29,INDIRECT("Descriptif!I"&K$13)=Recap_equipements!$C29),INDIRECT("Descriptif!M"&K$13)=$D29),INDIRECT("Descriptif!F"&K$13),"") | M29: =IF(AND(OR(INDIRECT("Descriptif!I"&L$13)=Recap_equipements!$B29,INDIRECT("Descriptif!I"&L$13)=Recap_equipements!$C29),INDIRECT("Descriptif!M"&L$13)=$D29),INDIRECT("Descriptif!F"&L$13),"") | ... T29: =IF(AND(OR(INDIRECT("Descriptif!I"&S$13)=Recap_equipements!$B29,INDIRECT("Descriptif!I"&S$13)=Recap_equipements!$C29),INDIRECT("Descriptif!M"&S$13)=$D29),INDIRECT("Descriptif!F"&S$13),"")
D30: =$D$8 -> Débitmètre gravitaire | F30: =IF(AND(OR(INDIRECT("Descriptif!I"&E$13)=Recap_equipements!$B29,INDIRECT("Descriptif!I"&E$13)=Recap_equipements!$C29),INDIRECT("Descriptif!M"&E$13)=$D30),INDIRECT("Descriptif!F"&E$13),"") -> A2_P100_Q_Grav | G30: =IF(AND(OR(INDIRECT("Descriptif!I"&F$13)=Recap_equipements!$B29,INDIRECT("Descriptif!I"&F$13)=Recap_equipements!$C29),INDIRECT("Descriptif!M"&F$13)=$D30),INDIRECT("Descriptif!F"&F$13),"") | H30: =IF(AND(OR(INDIRECT("Descriptif!I"&G$13)=Recap_equipements!$B29,INDIRECT("Descriptif!I"&G$13)=Recap_equipements!$C29),INDIRECT("Descriptif!M"&G$13)=$D30),INDIRECT("Descriptif!F"&G$13),"") | I30: =IF(AND(OR(INDIRECT("Descriptif!I"&H$13)=Recap_equipements!$B29,INDIRECT("Descriptif!I"&H$13)=Recap_equipements!$C29),INDIRECT("Descriptif!M"&H$13)=$D30),INDIRECT("Descriptif!F"&H$13),"") | J30: =IF(AND(OR(INDIRECT("Descriptif!I"&I$13)=Recap_equipements!$B29,INDIRECT("Descriptif!I"&I$13)=Recap_equipements!$C29),INDIRECT("Descriptif!M"&I$13)=$D30),INDIRECT("Descriptif!F"&I$13),"") | K30: =IF(AND(OR(INDIRECT("Descriptif!I"&J$13)=Recap_equipements!$B29,INDIRECT("Descriptif!I"&J$13)=Recap_equipements!$C29),INDIRECT("Descriptif!M"&J$13)=$D30),INDIRECT("Descriptif!F"&J$13),"") | L30: =IF(AND(OR(INDIRECT("Descriptif!I"&K$13)=Recap_equipements!$B29,INDIRECT("Descriptif!I"&K$13)=Recap_equipements!$C29),INDIRECT("Descriptif!M"&K$13)=$D30),INDIRECT("Descriptif!F"&K$13),"") | M30: =IF(AND(OR(INDIRECT("Descriptif!I"&L$13)=Recap_equipements!$B29,INDIRECT("Descriptif!I"&L$13)=Recap_equipements!$C29),INDIRECT("Descriptif!M"&L$13)=$D30),INDIRECT("Descriptif!F"&L$13),"") | ... T30: =IF(AND(OR(INDIRECT("Descriptif!I"&S$13)=Recap_equipements!$B29,INDIRECT("Descriptif!I"&S$13)=Recap_equipements!$C29),INDIRECT("Descriptif!M"&S$13)=$D30),INDIRECT("Descriptif!F"&S$13),"")
D31: =$D$9 -> Préleveur | F31: =IF(AND(OR(INDIRECT("Descriptif!I"&E$13)=Recap_equipements!$B29,INDIRECT("Descriptif!I"&E$13)=Recap_equipements!$C29),INDIRECT("Descriptif!M"&E$13)=$D31),INDIRECT("Descriptif!F"&E$13),"") | G31: =IF(AND(OR(INDIRECT("Descriptif!I"&F$13)=Recap_equipements!$B29,INDIRECT("Descriptif!I"&F$13)=Recap_equipements!$C29),INDIRECT("Descriptif!M"&F$13)=$D31),INDIRECT("Descriptif!F"&F$13),"") | H31: =IF(AND(OR(INDIRECT("Descriptif!I"&G$13)=Recap_equipements!$B29,INDIRECT("Descriptif!I"&G$13)=Recap_equipements!$C29),INDIRECT("Descriptif!M"&G$13)=$D31),INDIRECT("Descriptif!F"&G$13),"") | I31: =IF(AND(OR(INDIRECT("Descriptif!I"&H$13)=Recap_equipements!$B29,INDIRECT("Descriptif!I"&H$13)=Recap_equipements!$C29),INDIRECT("Descriptif!M"&H$13)=$D31),INDIRECT("Descriptif!F"&H$13),"") | J31: =IF(AND(OR(INDIRECT("Descriptif!I"&I$13)=Recap_equipements!$B29,INDIRECT("Descriptif!I"&I$13)=Recap_equipements!$C29),INDIRECT("Descriptif!M"&I$13)=$D31),INDIRECT("Descriptif!F"&I$13),"") | K31: =IF(AND(OR(INDIRECT("Descriptif!I"&J$13)=Recap_equipements!$B29,INDIRECT("Descriptif!I"&J$13)=Recap_equipements!$C29),INDIRECT("Descriptif!M"&J$13)=$D31),INDIRECT("Descriptif!F"&J$13),"") | L31: =IF(AND(OR(INDIRECT("Descriptif!I"&K$13)=Recap_equipements!$B29,INDIRECT("Descriptif!I"&K$13)=Recap_equipements!$C29),INDIRECT("Descriptif!M"&K$13)=$D31),INDIRECT("Descriptif!F"&K$13),"") | M31: =IF(AND(OR(INDIRECT("Descriptif!I"&L$13)=Recap_equipements!$B29,INDIRECT("Descriptif!I"&L$13)=Recap_equipements!$C29),INDIRECT("Descriptif!M"&L$13)=$D31),INDIRECT("Descriptif!F"&L$13),"") | ... T31: =IF(AND(OR(INDIRECT("Descriptif!I"&S$13)=Recap_equipements!$B29,INDIRECT("Descriptif!I"&S$13)=Recap_equipements!$C29),INDIRECT("Descriptif!M"&S$13)=$D31),INDIRECT("Descriptif!F"&S$13),"")
D32: Analytique | F32: =IF(F31<>"",VLOOKUP(F31,Analytique!$X$3:$AD$33,1,FALSE),"") | G32: =IF(G31<>"",VLOOKUP(G31,Analytique!$X$3:$AD$33,1,FALSE),"") | H32: =IF(H31<>"",VLOOKUP(H31,Analytique!$X$3:$AD$33,1,FALSE),"") | I32: =IF(I31<>"",VLOOKUP(I31,Analytique!$X$3:$AD$33,1,FALSE),"") | J32: =IF(J31<>"",VLOOKUP(J31,Analytique!$X$3:$AD$33,1,FALSE),"") | K32: =IF(K31<>"",VLOOKUP(K31,Analytique!$X$3:$AD$33,1,FALSE),"") | L32: =IF(L31<>"",VLOOKUP(L31,Analytique!$X$3:$AD$33,1,FALSE),"") | M32: =IF(M31<>"",VLOOKUP(M31,Analytique!$X$3:$AD$33,1,FALSE),"") | ... T32: =IF(T31<>"",VLOOKUP(T31,Analytique!$X$3:$AD$33,1,FALSE),"")
D33: =$D$10 -> Sonde de température | F33: =IF(AND(OR(INDIRECT("Descriptif!I"&E$13)=Recap_equipements!$B29,INDIRECT("Descriptif!I"&E$13)=Recap_equipements!$C29),INDIRECT("Descriptif!M"&E$13)=$D33),INDIRECT("Descriptif!F"&E$13),"") | G33: =IF(AND(OR(INDIRECT("Descriptif!I"&F$13)=Recap_equipements!$B29,INDIRECT("Descriptif!I"&F$13)=Recap_equipements!$C29),INDIRECT("Descriptif!M"&F$13)=$D33),INDIRECT("Descriptif!F"&F$13),"") | H33: =IF(AND(OR(INDIRECT("Descriptif!I"&G$13)=Recap_equipements!$B29,INDIRECT("Descriptif!I"&G$13)=Recap_equipements!$C29),INDIRECT("Descriptif!M"&G$13)=$D33),INDIRECT("Descriptif!F"&G$13),"") | I33: =IF(AND(OR(INDIRECT("Descriptif!I"&H$13)=Recap_equipements!$B29,INDIRECT("Descriptif!I"&H$13)=Recap_equipements!$C29),INDIRECT("Descriptif!M"&H$13)=$D33),INDIRECT("Descriptif!F"&H$13),"") | J33: =IF(AND(OR(INDIRECT("Descriptif!I"&I$13)=Recap_equipements!$B29,INDIRECT("Descriptif!I"&I$13)=Recap_equipements!$C29),INDIRECT("Descriptif!M"&I$13)=$D33),INDIRECT("Descriptif!F"&I$13),"") | K33: =IF(AND(OR(INDIRECT("Descriptif!I"&J$13)=Recap_equipements!$B29,INDIRECT("Descriptif!I"&J$13)=Recap_equipements!$C29),INDIRECT("Descriptif!M"&J$13)=$D33),INDIRECT("Descriptif!F"&J$13),"") | L33: =IF(AND(OR(INDIRECT("Descriptif!I"&K$13)=Recap_equipements!$B29,INDIRECT("Descriptif!I"&K$13)=Recap_equipements!$C29),INDIRECT("Descriptif!M"&K$13)=$D33),INDIRECT("Descriptif!F"&K$13),"") | M33: =IF(AND(OR(INDIRECT("Descriptif!I"&L$13)=Recap_equipements!$B29,INDIRECT("Descriptif!I"&L$13)=Recap_equipements!$C29),INDIRECT("Descriptif!M"&L$13)=$D33),INDIRECT("Descriptif!F"&L$13),"") | ... T33: =IF(AND(OR(INDIRECT("Descriptif!I"&S$13)=Recap_equipements!$B29,INDIRECT("Descriptif!I"&S$13)=Recap_equipements!$C29),INDIRECT("Descriptif!M"&S$13)=$D33),INDIRECT("Descriptif!F"&S$13),"")
B34: A5 | C34: S3 | D34: =$D$7 -> Débitmètre en charge | F34: =IF(AND(OR(INDIRECT("Descriptif!I"&E$13)=Recap_equipements!$B34,INDIRECT("Descriptif!I"&E$13)=Recap_equipements!$C34),INDIRECT("Descriptif!M"&E$13)=$D34),INDIRECT("Descriptif!F"&E$13),"") | G34: =IF(AND(OR(INDIRECT("Descriptif!I"&F$13)=Recap_equipements!$B34,INDIRECT("Descriptif!I"&F$13)=Recap_equipements!$C34),INDIRECT("Descriptif!M"&F$13)=$D34),INDIRECT("Descriptif!F"&F$13),"") | H34: =IF(AND(OR(INDIRECT("Descriptif!I"&G$13)=Recap_equipements!$B34,INDIRECT("Descriptif!I"&G$13)=Recap_equipements!$C34),INDIRECT("Descriptif!M"&G$13)=$D34),INDIRECT("Descriptif!F"&G$13),"") | I34: =IF(AND(OR(INDIRECT("Descriptif!I"&H$13)=Recap_equipements!$B34,INDIRECT("Descriptif!I"&H$13)=Recap_equipements!$C34),INDIRECT("Descriptif!M"&H$13)=$D34),INDIRECT("Descriptif!F"&H$13),"") | J34: =IF(AND(OR(INDIRECT("Descriptif!I"&I$13)=Recap_equipements!$B34,INDIRECT("Descriptif!I"&I$13)=Recap_equipements!$C34),INDIRECT("Descriptif!M"&I$13)=$D34),INDIRECT("Descriptif!F"&I$13),"") | K34: =IF(AND(OR(INDIRECT("Descriptif!I"&J$13)=Recap_equipements!$B34,INDIRECT("Descriptif!I"&J$13)=Recap_equipements!$C34),INDIRECT("Descriptif!M"&J$13)=$D34),INDIRECT("Descriptif!F"&J$13),"") | L34: =IF(AND(OR(INDIRECT("Descriptif!I"&K$13)=Recap_equipements!$B34,INDIRECT("Descriptif!I"&K$13)=Recap_equipements!$C34),INDIRECT("Descriptif!M"&K$13)=$D34),INDIRECT("Descriptif!F"&K$13),"") | M34: =IF(AND(OR(INDIRECT("Descriptif!I"&L$13)=Recap_equipements!$B34,INDIRECT("Descriptif!I"&L$13)=Recap_equipements!$C34),INDIRECT("Descriptif!M"&L$13)=$D34),INDIRECT("Descriptif!F"&L$13),"") | ... T34: =IF(AND(OR(INDIRECT("Descriptif!I"&S$13)=Recap_equipements!$B34,INDIRECT("Descriptif!I"&S$13)=Recap_equipements!$C34),INDIRECT("Descriptif!M"&S$13)=$D34),INDIRECT("Descriptif!F"&S$13),"")
D35: =$D$8 -> Débitmètre gravitaire | F35: =IF(AND(OR(INDIRECT("Descriptif!I"&E$13)=Recap_equipements!$B34,INDIRECT("Descriptif!I"&E$13)=Recap_equipements!$C34),INDIRECT("Descriptif!M"&E$13)=$D35),INDIRECT("Descriptif!F"&E$13),"") | G35: =IF(AND(OR(INDIRECT("Descriptif!I"&F$13)=Recap_equipements!$B34,INDIRECT("Descriptif!I"&F$13)=Recap_equipements!$C34),INDIRECT("Descriptif!M"&F$13)=$D35),INDIRECT("Descriptif!F"&F$13),"") | H35: =IF(AND(OR(INDIRECT("Descriptif!I"&G$13)=Recap_equipements!$B34,INDIRECT("Descriptif!I"&G$13)=Recap_equipements!$C34),INDIRECT("Descriptif!M"&G$13)=$D35),INDIRECT("Descriptif!F"&G$13),"") | I35: =IF(AND(OR(INDIRECT("Descriptif!I"&H$13)=Recap_equipements!$B34,INDIRECT("Descriptif!I"&H$13)=Recap_equipements!$C34),INDIRECT("Descriptif!M"&H$13)=$D35),INDIRECT("Descriptif!F"&H$13),"") | J35: =IF(AND(OR(INDIRECT("Descriptif!I"&I$13)=Recap_equipements!$B34,INDIRECT("Descriptif!I"&I$13)=Recap_equipements!$C34),INDIRECT("Descriptif!M"&I$13)=$D35),INDIRECT("Descriptif!F"&I$13),"") | K35: =IF(AND(OR(INDIRECT("Descriptif!I"&J$13)=Recap_equipements!$B34,INDIRECT("Descriptif!I"&J$13)=Recap_equipements!$C34),INDIRECT("Descriptif!M"&J$13)=$D35),INDIRECT("Descriptif!F"&J$13),"") | L35: =IF(AND(OR(INDIRECT("Descriptif!I"&K$13)=Recap_equipements!$B34,INDIRECT("Descriptif!I"&K$13)=Recap_equipements!$C34),INDIRECT("Descriptif!M"&K$13)=$D35),INDIRECT("Descriptif!F"&K$13),"") | M35: =IF(AND(OR(INDIRECT("Descriptif!I"&L$13)=Recap_equipements!$B34,INDIRECT("Descriptif!I"&L$13)=Recap_equipements!$C34),INDIRECT("Descriptif!M"&L$13)=$D35),INDIRECT("Descriptif!F"&L$13),"") | ... T35: =IF(AND(OR(INDIRECT("Descriptif!I"&S$13)=Recap_equipements!$B34,INDIRECT("Descriptif!I"&S$13)=Recap_equipements!$C34),INDIRECT("Descriptif!M"&S$13)=$D35),INDIRECT("Descriptif!F"&S$13),"")
D36: =$D$9 -> Préleveur | F36: =IF(AND(OR(INDIRECT("Descriptif!I"&E$13)=Recap_equipements!$B34,INDIRECT("Descriptif!I"&E$13)=Recap_equipements!$C34),INDIRECT("Descriptif!M"&E$13)=$D36),INDIRECT("Descriptif!F"&E$13),"") | G36: =IF(AND(OR(INDIRECT("Descriptif!I"&F$13)=Recap_equipements!$B34,INDIRECT("Descriptif!I"&F$13)=Recap_equipements!$C34),INDIRECT("Descriptif!M"&F$13)=$D36),INDIRECT("Descriptif!F"&F$13),"") | H36: =IF(AND(OR(INDIRECT("Descriptif!I"&G$13)=Recap_equipements!$B34,INDIRECT("Descriptif!I"&G$13)=Recap_equipements!$C34),INDIRECT("Descriptif!M"&G$13)=$D36),INDIRECT("Descriptif!F"&G$13),"") | I36: =IF(AND(OR(INDIRECT("Descriptif!I"&H$13)=Recap_equipements!$B34,INDIRECT("Descriptif!I"&H$13)=Recap_equipements!$C34),INDIRECT("Descriptif!M"&H$13)=$D36),INDIRECT("Descriptif!F"&H$13),"") | J36: =IF(AND(OR(INDIRECT("Descriptif!I"&I$13)=Recap_equipements!$B34,INDIRECT("Descriptif!I"&I$13)=Recap_equipements!$C34),INDIRECT("Descriptif!M"&I$13)=$D36),INDIRECT("Descriptif!F"&I$13),"") | K36: =IF(AND(OR(INDIRECT("Descriptif!I"&J$13)=Recap_equipements!$B34,INDIRECT("Descriptif!I"&J$13)=Recap_equipements!$C34),INDIRECT("Descriptif!M"&J$13)=$D36),INDIRECT("Descriptif!F"&J$13),"") | L36: =IF(AND(OR(INDIRECT("Descriptif!I"&K$13)=Recap_equipements!$B34,INDIRECT("Descriptif!I"&K$13)=Recap_equipements!$C34),INDIRECT("Descriptif!M"&K$13)=$D36),INDIRECT("Descriptif!F"&K$13),"") | M36: =IF(AND(OR(INDIRECT("Descriptif!I"&L$13)=Recap_equipements!$B34,INDIRECT("Descriptif!I"&L$13)=Recap_equipements!$C34),INDIRECT("Descriptif!M"&L$13)=$D36),INDIRECT("Descriptif!F"&L$13),"") | ... T36: =IF(AND(OR(INDIRECT("Descriptif!I"&S$13)=Recap_equipements!$B34,INDIRECT("Descriptif!I"&S$13)=Recap_equipements!$C34),INDIRECT("Descriptif!M"&S$13)=$D36),INDIRECT("Descriptif!F"&S$13),"")
D37: =$D$10 -> Sonde de température | F37: =IF(AND(OR(INDIRECT("Descriptif!I"&E$13)=Recap_equipements!$B34,INDIRECT("Descriptif!I"&E$13)=Recap_equipements!$C34),INDIRECT("Descriptif!M"&E$13)=$D37),INDIRECT("Descriptif!F"&E$13),"") | G37: =IF(AND(OR(INDIRECT("Descriptif!I"&F$13)=Recap_equipements!$B34,INDIRECT("Descriptif!I"&F$13)=Recap_equipements!$C34),INDIRECT("Descriptif!M"&F$13)=$D37),INDIRECT("Descriptif!F"&F$13),"") | H37: =IF(AND(OR(INDIRECT("Descriptif!I"&G$13)=Recap_equipements!$B34,INDIRECT("Descriptif!I"&G$13)=Recap_equipements!$C34),INDIRECT("Descriptif!M"&G$13)=$D37),INDIRECT("Descriptif!F"&G$13),"") | I37: =IF(AND(OR(INDIRECT("Descriptif!I"&H$13)=Recap_equipements!$B34,INDIRECT("Descriptif!I"&H$13)=Recap_equipements!$C34),INDIRECT("Descriptif!M"&H$13)=$D37),INDIRECT("Descriptif!F"&H$13),"") | J37: =IF(AND(OR(INDIRECT("Descriptif!I"&I$13)=Recap_equipements!$B34,INDIRECT("Descriptif!I"&I$13)=Recap_equipements!$C34),INDIRECT("Descriptif!M"&I$13)=$D37),INDIRECT("Descriptif!F"&I$13),"") | K37: =IF(AND(OR(INDIRECT("Descriptif!I"&J$13)=Recap_equipements!$B34,INDIRECT("Descriptif!I"&J$13)=Recap_equipements!$C34),INDIRECT("Descriptif!M"&J$13)=$D37),INDIRECT("Descriptif!F"&J$13),"") | L37: =IF(AND(OR(INDIRECT("Descriptif!I"&K$13)=Recap_equipements!$B34,INDIRECT("Descriptif!I"&K$13)=Recap_equipements!$C34),INDIRECT("Descriptif!M"&K$13)=$D37),INDIRECT("Descriptif!F"&K$13),"") | M37: =IF(AND(OR(INDIRECT("Descriptif!I"&L$13)=Recap_equipements!$B34,INDIRECT("Descriptif!I"&L$13)=Recap_equipements!$C34),INDIRECT("Descriptif!M"&L$13)=$D37),INDIRECT("Descriptif!F"&L$13),"") | ... T37: =IF(AND(OR(INDIRECT("Descriptif!I"&S$13)=Recap_equipements!$B34,INDIRECT("Descriptif!I"&S$13)=Recap_equipements!$C34),INDIRECT("Descriptif!M"&S$13)=$D37),INDIRECT("Descriptif!F"&S$13),"")
B38: A6 | C38: S4 | D38: =$D$7 -> Débitmètre en charge | F38: =IF(AND(OR(INDIRECT("Descriptif!I"&E$13)=Recap_equipements!$B38,INDIRECT("Descriptif!I"&E$13)=Recap_equipements!$C38),INDIRECT("Descriptif!M"&E$13)=$D38),INDIRECT("Descriptif!F"&E$13),"") | G38: =IF(AND(OR(INDIRECT("Descriptif!I"&F$13)=Recap_equipements!$B38,INDIRECT("Descriptif!I"&F$13)=Recap_equipements!$C38),INDIRECT("Descriptif!M"&F$13)=$D38),INDIRECT("Descriptif!F"&F$13),"") | H38: =IF(AND(OR(INDIRECT("Descriptif!I"&G$13)=Recap_equipements!$B38,INDIRECT("Descriptif!I"&G$13)=Recap_equipements!$C38),INDIRECT("Descriptif!M"&G$13)=$D38),INDIRECT("Descriptif!F"&G$13),"") | I38: =IF(AND(OR(INDIRECT("Descriptif!I"&H$13)=Recap_equipements!$B38,INDIRECT("Descriptif!I"&H$13)=Recap_equipements!$C38),INDIRECT("Descriptif!M"&H$13)=$D38),INDIRECT("Descriptif!F"&H$13),"") | J38: =IF(AND(OR(INDIRECT("Descriptif!I"&I$13)=Recap_equipements!$B38,INDIRECT("Descriptif!I"&I$13)=Recap_equipements!$C38),INDIRECT("Descriptif!M"&I$13)=$D38),INDIRECT("Descriptif!F"&I$13),"") | K38: =IF(AND(OR(INDIRECT("Descriptif!I"&J$13)=Recap_equipements!$B38,INDIRECT("Descriptif!I"&J$13)=Recap_equipements!$C38),INDIRECT("Descriptif!M"&J$13)=$D38),INDIRECT("Descriptif!F"&J$13),"") -> A6_P104_Q_DEM | L38: =IF(AND(OR(INDIRECT("Descriptif!I"&K$13)=Recap_equipements!$B38,INDIRECT("Descriptif!I"&K$13)=Recap_equipements!$C38),INDIRECT("Descriptif!M"&K$13)=$D38),INDIRECT("Descriptif!F"&K$13),"") | M38: =IF(AND(OR(INDIRECT("Descriptif!I"&L$13)=Recap_equipements!$B38,INDIRECT("Descriptif!I"&L$13)=Recap_equipements!$C38),INDIRECT("Descriptif!M"&L$13)=$D38),INDIRECT("Descriptif!F"&L$13),"") | ... T38: =IF(AND(OR(INDIRECT("Descriptif!I"&S$13)=Recap_equipements!$B38,INDIRECT("Descriptif!I"&S$13)=Recap_equipements!$C38),INDIRECT("Descriptif!M"&S$13)=$D38),INDIRECT("Descriptif!F"&S$13),"")
D39: =$D$8 -> Débitmètre gravitaire | F39: =IF(AND(OR(INDIRECT("Descriptif!I"&E$13)=Recap_equipements!$B38,INDIRECT("Descriptif!I"&E$13)=Recap_equipements!$C38),INDIRECT("Descriptif!M"&E$13)=$D39),INDIRECT("Descriptif!F"&E$13),"") | G39: =IF(AND(OR(INDIRECT("Descriptif!I"&F$13)=Recap_equipements!$B38,INDIRECT("Descriptif!I"&F$13)=Recap_equipements!$C38),INDIRECT("Descriptif!M"&F$13)=$D39),INDIRECT("Descriptif!F"&F$13),"") | H39: =IF(AND(OR(INDIRECT("Descriptif!I"&G$13)=Recap_equipements!$B38,INDIRECT("Descriptif!I"&G$13)=Recap_equipements!$C38),INDIRECT("Descriptif!M"&G$13)=$D39),INDIRECT("Descriptif!F"&G$13),"") | I39: =IF(AND(OR(INDIRECT("Descriptif!I"&H$13)=Recap_equipements!$B38,INDIRECT("Descriptif!I"&H$13)=Recap_equipements!$C38),INDIRECT("Descriptif!M"&H$13)=$D39),INDIRECT("Descriptif!F"&H$13),"") | J39: =IF(AND(OR(INDIRECT("Descriptif!I"&I$13)=Recap_equipements!$B38,INDIRECT("Descriptif!I"&I$13)=Recap_equipements!$C38),INDIRECT("Descriptif!M"&I$13)=$D39),INDIRECT("Descriptif!F"&I$13),"") | K39: =IF(AND(OR(INDIRECT("Descriptif!I"&J$13)=Recap_equipements!$B38,INDIRECT("Descriptif!I"&J$13)=Recap_equipements!$C38),INDIRECT("Descriptif!M"&J$13)=$D39),INDIRECT("Descriptif!F"&J$13),"") | L39: =IF(AND(OR(INDIRECT("Descriptif!I"&K$13)=Recap_equipements!$B38,INDIRECT("Descriptif!I"&K$13)=Recap_equipements!$C38),INDIRECT("Descriptif!M"&K$13)=$D39),INDIRECT("Descriptif!F"&K$13),"") | M39: =IF(AND(OR(INDIRECT("Descriptif!I"&L$13)=Recap_equipements!$B38,INDIRECT("Descriptif!I"&L$13)=Recap_equipements!$C38),INDIRECT("Descriptif!M"&L$13)=$D39),INDIRECT("Descriptif!F"&L$13),"") | ... T39: =IF(AND(OR(INDIRECT("Descriptif!I"&S$13)=Recap_equipements!$B38,INDIRECT("Descriptif!I"&S$13)=Recap_equipements!$C38),INDIRECT("Descriptif!M"&S$13)=$D39),INDIRECT("Descriptif!F"&S$13),"")
D40: =$D$9 -> Préleveur | F40: =IF(AND(OR(INDIRECT("Descriptif!I"&E$13)=Recap_equipements!$B38,INDIRECT("Descriptif!I"&E$13)=Recap_equipements!$C38),INDIRECT("Descriptif!M"&E$13)=$D40),INDIRECT("Descriptif!F"&E$13),"") | G40: =IF(AND(OR(INDIRECT("Descriptif!I"&F$13)=Recap_equipements!$B38,INDIRECT("Descriptif!I"&F$13)=Recap_equipements!$C38),INDIRECT("Descriptif!M"&F$13)=$D40),INDIRECT("Descriptif!F"&F$13),"") | H40: =IF(AND(OR(INDIRECT("Descriptif!I"&G$13)=Recap_equipements!$B38,INDIRECT("Descriptif!I"&G$13)=Recap_equipements!$C38),INDIRECT("Descriptif!M"&G$13)=$D40),INDIRECT("Descriptif!F"&G$13),"") | I40: =IF(AND(OR(INDIRECT("Descriptif!I"&H$13)=Recap_equipements!$B38,INDIRECT("Descriptif!I"&H$13)=Recap_equipements!$C38),INDIRECT("Descriptif!M"&H$13)=$D40),INDIRECT("Descriptif!F"&H$13),"") | J40: =IF(AND(OR(INDIRECT("Descriptif!I"&I$13)=Recap_equipements!$B38,INDIRECT("Descriptif!I"&I$13)=Recap_equipements!$C38),INDIRECT("Descriptif!M"&I$13)=$D40),INDIRECT("Descriptif!F"&I$13),"") | K40: =IF(AND(OR(INDIRECT("Descriptif!I"&J$13)=Recap_equipements!$B38,INDIRECT("Descriptif!I"&J$13)=Recap_equipements!$C38),INDIRECT("Descriptif!M"&J$13)=$D40),INDIRECT("Descriptif!F"&J$13),"") | L40: =IF(AND(OR(INDIRECT("Descriptif!I"&K$13)=Recap_equipements!$B38,INDIRECT("Descriptif!I"&K$13)=Recap_equipements!$C38),INDIRECT("Descriptif!M"&K$13)=$D40),INDIRECT("Descriptif!F"&K$13),"") | M40: =IF(AND(OR(INDIRECT("Descriptif!I"&L$13)=Recap_equipements!$B38,INDIRECT("Descriptif!I"&L$13)=Recap_equipements!$C38),INDIRECT("Descriptif!M"&L$13)=$D40),INDIRECT("Descriptif!F"&L$13),"") | ... T40: =IF(AND(OR(INDIRECT("Descriptif!I"&S$13)=Recap_equipements!$B38,INDIRECT("Descriptif!I"&S$13)=Recap_equipements!$C38),INDIRECT("Descriptif!M"&S$13)=$D40),INDIRECT("Descriptif!F"&S$13),"")
D41: Analytique | F41: =IF(F40<>"",VLOOKUP(F40,Analytique!$X$3:$AD$33,1,FALSE),"") | G41: =IF(G40<>"",VLOOKUP(G40,Analytique!$X$3:$AD$33,1,FALSE),"") | H41: =IF(H40<>"",VLOOKUP(H40,Analytique!$X$3:$AD$33,1,FALSE),"") | I41: =IF(I40<>"",VLOOKUP(I40,Analytique!$X$3:$AD$33,1,FALSE),"") | J41: =IF(J40<>"",VLOOKUP(J40,Analytique!$X$3:$AD$33,1,FALSE),"") | K41: =IF(K40<>"",VLOOKUP(K40,Analytique!$X$3:$AD$33,1,FALSE),"") | L41: =IF(L40<>"",VLOOKUP(L40,Analytique!$X$3:$AD$33,1,FALSE),"") | M41: =IF(M40<>"",VLOOKUP(M40,Analytique!$X$3:$AD$33,1,FALSE),"") | ... T41: =IF(T40<>"",VLOOKUP(T40,Analytique!$X$3:$AD$33,1,FALSE),"")
D42: =$D$10 -> Sonde de température | F42: =IF(AND(OR(INDIRECT("Descriptif!I"&E$13)=Recap_equipements!$B38,INDIRECT("Descriptif!I"&E$13)=Recap_equipements!$C38),INDIRECT("Descriptif!M"&E$13)=$D42),INDIRECT("Descriptif!F"&E$13),"") | G42: =IF(AND(OR(INDIRECT("Descriptif!I"&F$13)=Recap_equipements!$B38,INDIRECT("Descriptif!I"&F$13)=Recap_equipements!$C38),INDIRECT("Descriptif!M"&F$13)=$D42),INDIRECT("Descriptif!F"&F$13),"") | H42: =IF(AND(OR(INDIRECT("Descriptif!I"&G$13)=Recap_equipements!$B38,INDIRECT("Descriptif!I"&G$13)=Recap_equipements!$C38),INDIRECT("Descriptif!M"&G$13)=$D42),INDIRECT("Descriptif!F"&G$13),"") | I42: =IF(AND(OR(INDIRECT("Descriptif!I"&H$13)=Recap_equipements!$B38,INDIRECT("Descriptif!I"&H$13)=Recap_equipements!$C38),INDIRECT("Descriptif!M"&H$13)=$D42),INDIRECT("Descriptif!F"&H$13),"") | J42: =IF(AND(OR(INDIRECT("Descriptif!I"&I$13)=Recap_equipements!$B38,INDIRECT("Descriptif!I"&I$13)=Recap_equipements!$C38),INDIRECT("Descriptif!M"&I$13)=$D42),INDIRECT("Descriptif!F"&I$13),"") | K42: =IF(AND(OR(INDIRECT("Descriptif!I"&J$13)=Recap_equipements!$B38,INDIRECT("Descriptif!I"&J$13)=Recap_equipements!$C38),INDIRECT("Descriptif!M"&J$13)=$D42),INDIRECT("Descriptif!F"&J$13),"") | L42: =IF(AND(OR(INDIRECT("Descriptif!I"&K$13)=Recap_equipements!$B38,INDIRECT("Descriptif!I"&K$13)=Recap_equipements!$C38),INDIRECT("Descriptif!M"&K$13)=$D42),INDIRECT("Descriptif!F"&K$13),"") | M42: =IF(AND(OR(INDIRECT("Descriptif!I"&L$13)=Recap_equipements!$B38,INDIRECT("Descriptif!I"&L$13)=Recap_equipements!$C38),INDIRECT("Descriptif!M"&L$13)=$D42),INDIRECT("Descriptif!F"&L$13),"") | ... T42: =IF(AND(OR(INDIRECT("Descriptif!I"&S$13)=Recap_equipements!$B38,INDIRECT("Descriptif!I"&S$13)=Recap_equipements!$C38),INDIRECT("Descriptif!M"&S$13)=$D42),INDIRECT("Descriptif!F"&S$13),"")
B43: A7 | C43: S12 | D43: =$D$7 -> Débitmètre en charge | F43: =IF(AND(OR(INDIRECT("Descriptif!I"&E$13)=Recap_equipements!$B43,INDIRECT("Descriptif!I"&E$13)=Recap_equipements!$C43),INDIRECT("Descriptif!M"&E$13)=$D43),INDIRECT("Descriptif!F"&E$13),"") | G43: =IF(AND(OR(INDIRECT("Descriptif!I"&F$13)=Recap_equipements!$B43,INDIRECT("Descriptif!I"&F$13)=Recap_equipements!$C43),INDIRECT("Descriptif!M"&F$13)=$D43),INDIRECT("Descriptif!F"&F$13),"") | H43: =IF(AND(OR(INDIRECT("Descriptif!I"&G$13)=Recap_equipements!$B43,INDIRECT("Descriptif!I"&G$13)=Recap_equipements!$C43),INDIRECT("Descriptif!M"&G$13)=$D43),INDIRECT("Descriptif!F"&G$13),"") | I43: =IF(AND(OR(INDIRECT("Descriptif!I"&H$13)=Recap_equipements!$B43,INDIRECT("Descriptif!I"&H$13)=Recap_equipements!$C43),INDIRECT("Descriptif!M"&H$13)=$D43),INDIRECT("Descriptif!F"&H$13),"") | J43: =IF(AND(OR(INDIRECT("Descriptif!I"&I$13)=Recap_equipements!$B43,INDIRECT("Descriptif!I"&I$13)=Recap_equipements!$C43),INDIRECT("Descriptif!M"&I$13)=$D43),INDIRECT("Descriptif!F"&I$13),"") | K43: =IF(AND(OR(INDIRECT("Descriptif!I"&J$13)=Recap_equipements!$B43,INDIRECT("Descriptif!I"&J$13)=Recap_equipements!$C43),INDIRECT("Descriptif!M"&J$13)=$D43),INDIRECT("Descriptif!F"&J$13),"") | L43: =IF(AND(OR(INDIRECT("Descriptif!I"&K$13)=Recap_equipements!$B43,INDIRECT("Descriptif!I"&K$13)=Recap_equipements!$C43),INDIRECT("Descriptif!M"&K$13)=$D43),INDIRECT("Descriptif!F"&K$13),"") | M43: =IF(AND(OR(INDIRECT("Descriptif!I"&L$13)=Recap_equipements!$B43,INDIRECT("Descriptif!I"&L$13)=Recap_equipements!$C43),INDIRECT("Descriptif!M"&L$13)=$D43),INDIRECT("Descriptif!F"&L$13),"") | ... T43: =IF(AND(OR(INDIRECT("Descriptif!I"&S$13)=Recap_equipements!$B43,INDIRECT("Descriptif!I"&S$13)=Recap_equipements!$C43),INDIRECT("Descriptif!M"&S$13)=$D43),INDIRECT("Descriptif!F"&S$13),"")
D44: =$D$8 -> Débitmètre gravitaire | F44: =IF(AND(OR(INDIRECT("Descriptif!I"&E$13)=Recap_equipements!$B43,INDIRECT("Descriptif!I"&E$13)=Recap_equipements!$C43),INDIRECT("Descriptif!M"&E$13)=$D44),INDIRECT("Descriptif!F"&E$13),"") | G44: =IF(AND(OR(INDIRECT("Descriptif!I"&F$13)=Recap_equipements!$B43,INDIRECT("Descriptif!I"&F$13)=Recap_equipements!$C43),INDIRECT("Descriptif!M"&F$13)=$D44),INDIRECT("Descriptif!F"&F$13),"") | H44: =IF(AND(OR(INDIRECT("Descriptif!I"&G$13)=Recap_equipements!$B43,INDIRECT("Descriptif!I"&G$13)=Recap_equipements!$C43),INDIRECT("Descriptif!M"&G$13)=$D44),INDIRECT("Descriptif!F"&G$13),"") | I44: =IF(AND(OR(INDIRECT("Descriptif!I"&H$13)=Recap_equipements!$B43,INDIRECT("Descriptif!I"&H$13)=Recap_equipements!$C43),INDIRECT("Descriptif!M"&H$13)=$D44),INDIRECT("Descriptif!F"&H$13),"") | J44: =IF(AND(OR(INDIRECT("Descriptif!I"&I$13)=Recap_equipements!$B43,INDIRECT("Descriptif!I"&I$13)=Recap_equipements!$C43),INDIRECT("Descriptif!M"&I$13)=$D44),INDIRECT("Descriptif!F"&I$13),"") | K44: =IF(AND(OR(INDIRECT("Descriptif!I"&J$13)=Recap_equipements!$B43,INDIRECT("Descriptif!I"&J$13)=Recap_equipements!$C43),INDIRECT("Descriptif!M"&J$13)=$D44),INDIRECT("Descriptif!F"&J$13),"") | L44: =IF(AND(OR(INDIRECT("Descriptif!I"&K$13)=Recap_equipements!$B43,INDIRECT("Descriptif!I"&K$13)=Recap_equipements!$C43),INDIRECT("Descriptif!M"&K$13)=$D44),INDIRECT("Descriptif!F"&K$13),"") | M44: =IF(AND(OR(INDIRECT("Descriptif!I"&L$13)=Recap_equipements!$B43,INDIRECT("Descriptif!I"&L$13)=Recap_equipements!$C43),INDIRECT("Descriptif!M"&L$13)=$D44),INDIRECT("Descriptif!F"&L$13),"") | ... T44: =IF(AND(OR(INDIRECT("Descriptif!I"&S$13)=Recap_equipements!$B43,INDIRECT("Descriptif!I"&S$13)=Recap_equipements!$C43),INDIRECT("Descriptif!M"&S$13)=$D44),INDIRECT("Descriptif!F"&S$13),"")
D45: =$D$9 -> Préleveur | F45: =IF(AND(OR(INDIRECT("Descriptif!I"&E$13)=Recap_equipements!$B43,INDIRECT("Descriptif!I"&E$13)=Recap_equipements!$C43),INDIRECT("Descriptif!M"&E$13)=$D45),INDIRECT("Descriptif!F"&E$13),"") | G45: =IF(AND(OR(INDIRECT("Descriptif!I"&F$13)=Recap_equipements!$B43,INDIRECT("Descriptif!I"&F$13)=Recap_equipements!$C43),INDIRECT("Descriptif!M"&F$13)=$D45),INDIRECT("Descriptif!F"&F$13),"") | H45: =IF(AND(OR(INDIRECT("Descriptif!I"&G$13)=Recap_equipements!$B43,INDIRECT("Descriptif!I"&G$13)=Recap_equipements!$C43),INDIRECT("Descriptif!M"&G$13)=$D45),INDIRECT("Descriptif!F"&G$13),"") | I45: =IF(AND(OR(INDIRECT("Descriptif!I"&H$13)=Recap_equipements!$B43,INDIRECT("Descriptif!I"&H$13)=Recap_equipements!$C43),INDIRECT("Descriptif!M"&H$13)=$D45),INDIRECT("Descriptif!F"&H$13),"") | J45: =IF(AND(OR(INDIRECT("Descriptif!I"&I$13)=Recap_equipements!$B43,INDIRECT("Descriptif!I"&I$13)=Recap_equipements!$C43),INDIRECT("Descriptif!M"&I$13)=$D45),INDIRECT("Descriptif!F"&I$13),"") | K45: =IF(AND(OR(INDIRECT("Descriptif!I"&J$13)=Recap_equipements!$B43,INDIRECT("Descriptif!I"&J$13)=Recap_equipements!$C43),INDIRECT("Descriptif!M"&J$13)=$D45),INDIRECT("Descriptif!F"&J$13),"") | L45: =IF(AND(OR(INDIRECT("Descriptif!I"&K$13)=Recap_equipements!$B43,INDIRECT("Descriptif!I"&K$13)=Recap_equipements!$C43),INDIRECT("Descriptif!M"&K$13)=$D45),INDIRECT("Descriptif!F"&K$13),"") | M45: =IF(AND(OR(INDIRECT("Descriptif!I"&L$13)=Recap_equipements!$B43,INDIRECT("Descriptif!I"&L$13)=Recap_equipements!$C43),INDIRECT("Descriptif!M"&L$13)=$D45),INDIRECT("Descriptif!F"&L$13),"") | ... T45: =IF(AND(OR(INDIRECT("Descriptif!I"&S$13)=Recap_equipements!$B43,INDIRECT("Descriptif!I"&S$13)=Recap_equipements!$C43),INDIRECT("Descriptif!M"&S$13)=$D45),INDIRECT("Descriptif!F"&S$13),"")
D46: Analytique | F46: =IF(F45<>"",VLOOKUP(F45,Analytique!$X$3:$AD$33,1,FALSE),"") | G46: =IF(G45<>"",VLOOKUP(G45,Analytique!$X$3:$AD$33,1,FALSE),"") | H46: =IF(H45<>"",VLOOKUP(H45,Analytique!$X$3:$AD$33,1,FALSE),"") | I46: =IF(I45<>"",VLOOKUP(I45,Analytique!$X$3:$AD$33,1,FALSE),"") | J46: =IF(J45<>"",VLOOKUP(J45,Analytique!$X$3:$AD$33,1,FALSE),"") | K46: =IF(K45<>"",VLOOKUP(K45,Analytique!$X$3:$AD$33,1,FALSE),"") | L46: =IF(L45<>"",VLOOKUP(L45,Analytique!$X$3:$AD$33,1,FALSE),"") | M46: =IF(M45<>"",VLOOKUP(M45,Analytique!$X$3:$AD$33,1,FALSE),"") | ... T46: =IF(T45<>"",VLOOKUP(T45,Analytique!$X$3:$AD$33,1,FALSE),"")
D47: =$D$10 -> Sonde de température | F47: =IF(AND(OR(INDIRECT("Descriptif!I"&E$13)=Recap_equipements!$B43,INDIRECT("Descriptif!I"&E$13)=Recap_equipements!$C43),INDIRECT("Descriptif!M"&E$13)=$D47),INDIRECT("Descriptif!F"&E$13),"") | G47: =IF(AND(OR(INDIRECT("Descriptif!I"&F$13)=Recap_equipements!$B43,INDIRECT("Descriptif!I"&F$13)=Recap_equipements!$C43),INDIRECT("Descriptif!M"&F$13)=$D47),INDIRECT("Descriptif!F"&F$13),"") | H47: =IF(AND(OR(INDIRECT("Descriptif!I"&G$13)=Recap_equipements!$B43,INDIRECT("Descriptif!I"&G$13)=Recap_equipements!$C43),INDIRECT("Descriptif!M"&G$13)=$D47),INDIRECT("Descriptif!F"&G$13),"") | I47: =IF(AND(OR(INDIRECT("Descriptif!I"&H$13)=Recap_equipements!$B43,INDIRECT("Descriptif!I"&H$13)=Recap_equipements!$C43),INDIRECT("Descriptif!M"&H$13)=$D47),INDIRECT("Descriptif!F"&H$13),"") | J47: =IF(AND(OR(INDIRECT("Descriptif!I"&I$13)=Recap_equipements!$B43,INDIRECT("Descriptif!I"&I$13)=Recap_equipements!$C43),INDIRECT("Descriptif!M"&I$13)=$D47),INDIRECT("Descriptif!F"&I$13),"") | K47: =IF(AND(OR(INDIRECT("Descriptif!I"&J$13)=Recap_equipements!$B43,INDIRECT("Descriptif!I"&J$13)=Recap_equipements!$C43),INDIRECT("Descriptif!M"&J$13)=$D47),INDIRECT("Descriptif!F"&J$13),"") | L47: =IF(AND(OR(INDIRECT("Descriptif!I"&K$13)=Recap_equipements!$B43,INDIRECT("Descriptif!I"&K$13)=Recap_equipements!$C43),INDIRECT("Descriptif!M"&K$13)=$D47),INDIRECT("Descriptif!F"&K$13),"") | M47: =IF(AND(OR(INDIRECT("Descriptif!I"&L$13)=Recap_equipements!$B43,INDIRECT("Descriptif!I"&L$13)=Recap_equipements!$C43),INDIRECT("Descriptif!M"&L$13)=$D47),INDIRECT("Descriptif!F"&L$13),"") | ... T47: =IF(AND(OR(INDIRECT("Descriptif!I"&S$13)=Recap_equipements!$B43,INDIRECT("Descriptif!I"&S$13)=Recap_equipements!$C43),INDIRECT("Descriptif!M"&S$13)=$D47),INDIRECT("Descriptif!F"&S$13),"")
B48: A1 | C48: R1 | D48: =$D$7 -> Débitmètre en charge | F48: =IF(AND(OR(INDIRECT("Descriptif!I"&E$14)=Recap_equipements!$B48,INDIRECT("Descriptif!I"&E$14)=Recap_equipements!$C48),INDIRECT("Descriptif!M"&E$14)=$D48),INDIRECT("Descriptif!F"&E$14),"") | G48: =IF(AND(OR(INDIRECT("Descriptif!I"&F$14)=Recap_equipements!$B48,INDIRECT("Descriptif!I"&F$14)=Recap_equipements!$C48),INDIRECT("Descriptif!M"&F$14)=$D48),INDIRECT("Descriptif!F"&F$14),"") | H48: =IF(AND(OR(INDIRECT("Descriptif!I"&G$14)=Recap_equipements!$B48,INDIRECT("Descriptif!I"&G$14)=Recap_equipements!$C48),INDIRECT("Descriptif!M"&G$14)=$D48),INDIRECT("Descriptif!F"&G$14),"") | I48: =IF(AND(OR(INDIRECT("Descriptif!I"&H$14)=Recap_equipements!$B48,INDIRECT("Descriptif!I"&H$14)=Recap_equipements!$C48),INDIRECT("Descriptif!M"&H$14)=$D48),INDIRECT("Descriptif!F"&H$14),"") | J48: =IF(AND(OR(INDIRECT("Descriptif!I"&I$14)=Recap_equipements!$B48,INDIRECT("Descriptif!I"&I$14)=Recap_equipements!$C48),INDIRECT("Descriptif!M"&I$14)=$D48),INDIRECT("Descriptif!F"&I$14),"") | K48: =IF(AND(OR(INDIRECT("Descriptif!I"&J$14)=Recap_equipements!$B48,INDIRECT("Descriptif!I"&J$14)=Recap_equipements!$C48),INDIRECT("Descriptif!M"&J$14)=$D48),INDIRECT("Descriptif!F"&J$14),"") | L48: =IF(AND(OR(INDIRECT("Descriptif!I"&K$14)=Recap_equipements!$B48,INDIRECT("Descriptif!I"&K$14)=Recap_equipements!$C48),INDIRECT("Descriptif!M"&K$14)=$D48),INDIRECT("Descriptif!F"&K$14),"") | M48: =IF(AND(OR(INDIRECT("Descriptif!I"&L$14)=Recap_equipements!$B48,INDIRECT("Descriptif!I"&L$14)=Recap_equipements!$C48),INDIRECT("Descriptif!M"&L$14)=$D48),INDIRECT("Descriptif!F"&L$14),"") | ... T48: =IF(AND(OR(INDIRECT("Descriptif!I"&S$14)=Recap_equipements!$B48,INDIRECT("Descriptif!I"&S$14)=Recap_equipements!$C48),INDIRECT("Descriptif!M"&S$14)=$D48),INDIRECT("Descriptif!F"&S$14),"")
D49: =$D$8 -> Débitmètre gravitaire | F49: =IF(AND(OR(INDIRECT("Descriptif!I"&E$14)=Recap_equipements!$B48,INDIRECT("Descriptif!I"&E$14)=Recap_equipements!$C48),INDIRECT("Descriptif!M"&E$14)=$D49),INDIRECT("Descriptif!F"&E$14),"") -> A1_DO1_Q_Grav | G49: =IF(AND(OR(INDIRECT("Descriptif!I"&F$14)=Recap_equipements!$B48,INDIRECT("Descriptif!I"&F$14)=Recap_equipements!$C48),INDIRECT("Descriptif!M"&F$14)=$D49),INDIRECT("Descriptif!F"&F$14),"") | H49: =IF(AND(OR(INDIRECT("Descriptif!I"&G$14)=Recap_equipements!$B48,INDIRECT("Descriptif!I"&G$14)=Recap_equipements!$C48),INDIRECT("Descriptif!M"&G$14)=$D49),INDIRECT("Descriptif!F"&G$14),"") | I49: =IF(AND(OR(INDIRECT("Descriptif!I"&H$14)=Recap_equipements!$B48,INDIRECT("Descriptif!I"&H$14)=Recap_equipements!$C48),INDIRECT("Descriptif!M"&H$14)=$D49),INDIRECT("Descriptif!F"&H$14),"") | J49: =IF(AND(OR(INDIRECT("Descriptif!I"&I$14)=Recap_equipements!$B48,INDIRECT("Descriptif!I"&I$14)=Recap_equipements!$C48),INDIRECT("Descriptif!M"&I$14)=$D49),INDIRECT("Descriptif!F"&I$14),"") | K49: =IF(AND(OR(INDIRECT("Descriptif!I"&J$14)=Recap_equipements!$B48,INDIRECT("Descriptif!I"&J$14)=Recap_equipements!$C48),INDIRECT("Descriptif!M"&J$14)=$D49),INDIRECT("Descriptif!F"&J$14),"") | L49: =IF(AND(OR(INDIRECT("Descriptif!I"&K$14)=Recap_equipements!$B48,INDIRECT("Descriptif!I"&K$14)=Recap_equipements!$C48),INDIRECT("Descriptif!M"&K$14)=$D49),INDIRECT("Descriptif!F"&K$14),"") | M49: =IF(AND(OR(INDIRECT("Descriptif!I"&L$14)=Recap_equipements!$B48,INDIRECT("Descriptif!I"&L$14)=Recap_equipements!$C48),INDIRECT("Descriptif!M"&L$14)=$D49),INDIRECT("Descriptif!F"&L$14),"") | ... T49: =IF(AND(OR(INDIRECT("Descriptif!I"&S$14)=Recap_equipements!$B48,INDIRECT("Descriptif!I"&S$14)=Recap_equipements!$C48),INDIRECT("Descriptif!M"&S$14)=$D49),INDIRECT("Descriptif!F"&S$14),"")
D50: =$D$9 -> Préleveur | F50: =IF(AND(OR(INDIRECT("Descriptif!I"&E$14)=Recap_equipements!$B48,INDIRECT("Descriptif!I"&E$14)=Recap_equipements!$C48),INDIRECT("Descriptif!M"&E$14)=$D50),INDIRECT("Descriptif!F"&E$14),"") | G50: =IF(AND(OR(INDIRECT("Descriptif!I"&F$14)=Recap_equipements!$B48,INDIRECT("Descriptif!I"&F$14)=Recap_equipements!$C48),INDIRECT("Descriptif!M"&F$14)=$D50),INDIRECT("Descriptif!F"&F$14),"") | H50: =IF(AND(OR(INDIRECT("Descriptif!I"&G$14)=Recap_equipements!$B48,INDIRECT("Descriptif!I"&G$14)=Recap_equipements!$C48),INDIRECT("Descriptif!M"&G$14)=$D50),INDIRECT("Descriptif!F"&G$14),"") | I50: =IF(AND(OR(INDIRECT("Descriptif!I"&H$14)=Recap_equipements!$B48,INDIRECT("Descriptif!I"&H$14)=Recap_equipements!$C48),INDIRECT("Descriptif!M"&H$14)=$D50),INDIRECT("Descriptif!F"&H$14),"") | J50: =IF(AND(OR(INDIRECT("Descriptif!I"&I$14)=Recap_equipements!$B48,INDIRECT("Descriptif!I"&I$14)=Recap_equipements!$C48),INDIRECT("Descriptif!M"&I$14)=$D50),INDIRECT("Descriptif!F"&I$14),"") | K50: =IF(AND(OR(INDIRECT("Descriptif!I"&J$14)=Recap_equipements!$B48,INDIRECT("Descriptif!I"&J$14)=Recap_equipements!$C48),INDIRECT("Descriptif!M"&J$14)=$D50),INDIRECT("Descriptif!F"&J$14),"") | L50: =IF(AND(OR(INDIRECT("Descriptif!I"&K$14)=Recap_equipements!$B48,INDIRECT("Descriptif!I"&K$14)=Recap_equipements!$C48),INDIRECT("Descriptif!M"&K$14)=$D50),INDIRECT("Descriptif!F"&K$14),"") | M50: =IF(AND(OR(INDIRECT("Descriptif!I"&L$14)=Recap_equipements!$B48,INDIRECT("Descriptif!I"&L$14)=Recap_equipements!$C48),INDIRECT("Descriptif!M"&L$14)=$D50),INDIRECT("Descriptif!F"&L$14),"") | ... T50: =IF(AND(OR(INDIRECT("Descriptif!I"&S$14)=Recap_equipements!$B48,INDIRECT("Descriptif!I"&S$14)=Recap_equipements!$C48),INDIRECT("Descriptif!M"&S$14)=$D50),INDIRECT("Descriptif!F"&S$14),"")
D51: Analytique | F51: =IF(F50<>"",VLOOKUP(F50,Analytique!$X$3:$AD$33,1,FALSE),"") | G51: =IF(G50<>"",VLOOKUP(G50,Analytique!$X$3:$AD$33,1,FALSE),"") | H51: =IF(H50<>"",VLOOKUP(H50,Analytique!$X$3:$AD$33,1,FALSE),"") | I51: =IF(I50<>"",VLOOKUP(I50,Analytique!$X$3:$AD$33,1,FALSE),"") | J51: =IF(J50<>"",VLOOKUP(J50,Analytique!$X$3:$AD$33,1,FALSE),"") | K51: =IF(K50<>"",VLOOKUP(K50,Analytique!$X$3:$AD$33,1,FALSE),"") | L51: =IF(L50<>"",VLOOKUP(L50,Analytique!$X$3:$AD$33,1,FALSE),"") | M51: =IF(M50<>"",VLOOKUP(M50,Analytique!$X$3:$AD$33,1,FALSE),"") | ... T51: =IF(T50<>"",VLOOKUP(T50,Analytique!$X$3:$AD$33,1,FALSE),"")
D52: =$D$10 -> Sonde de température | F52: =IF(AND(OR(INDIRECT("Descriptif!I"&E$14)=Recap_equipements!$B48,INDIRECT("Descriptif!I"&E$14)=Recap_equipements!$C48),INDIRECT("Descriptif!M"&E$14)=$D52),INDIRECT("Descriptif!F"&E$14),"") | G52: =IF(AND(OR(INDIRECT("Descriptif!I"&F$14)=Recap_equipements!$B48,INDIRECT("Descriptif!I"&F$14)=Recap_equipements!$C48),INDIRECT("Descriptif!M"&F$14)=$D52),INDIRECT("Descriptif!F"&F$14),"") | H52: =IF(AND(OR(INDIRECT("Descriptif!I"&G$14)=Recap_equipements!$B48,INDIRECT("Descriptif!I"&G$14)=Recap_equipements!$C48),INDIRECT("Descriptif!M"&G$14)=$D52),INDIRECT("Descriptif!F"&G$14),"") | I52: =IF(AND(OR(INDIRECT("Descriptif!I"&H$14)=Recap_equipements!$B48,INDIRECT("Descriptif!I"&H$14)=Recap_equipements!$C48),INDIRECT("Descriptif!M"&H$14)=$D52),INDIRECT("Descriptif!F"&H$14),"") | J52: =IF(AND(OR(INDIRECT("Descriptif!I"&I$14)=Recap_equipements!$B48,INDIRECT("Descriptif!I"&I$14)=Recap_equipements!$C48),INDIRECT("Descriptif!M"&I$14)=$D52),INDIRECT("Descriptif!F"&I$14),"") | K52: =IF(AND(OR(INDIRECT("Descriptif!I"&J$14)=Recap_equipements!$B48,INDIRECT("Descriptif!I"&J$14)=Recap_equipements!$C48),INDIRECT("Descriptif!M"&J$14)=$D52),INDIRECT("Descriptif!F"&J$14),"") | L52: =IF(AND(OR(INDIRECT("Descriptif!I"&K$14)=Recap_equipements!$B48,INDIRECT("Descriptif!I"&K$14)=Recap_equipements!$C48),INDIRECT("Descriptif!M"&K$14)=$D52),INDIRECT("Descriptif!F"&K$14),"") | M52: =IF(AND(OR(INDIRECT("Descriptif!I"&L$14)=Recap_equipements!$B48,INDIRECT("Descriptif!I"&L$14)=Recap_equipements!$C48),INDIRECT("Descriptif!M"&L$14)=$D52),INDIRECT("Descriptif!F"&L$14),"") | ... T52: =IF(AND(OR(INDIRECT("Descriptif!I"&S$14)=Recap_equipements!$B48,INDIRECT("Descriptif!I"&S$14)=Recap_equipements!$C48),INDIRECT("Descriptif!M"&S$14)=$D52),INDIRECT("Descriptif!F"&S$14),"")
B53: A8 | C53: S19 | D53: =$D$7 -> Débitmètre en charge | F53: =IF(AND(OR(INDIRECT("Descriptif!I"&E$13)=Recap_equipements!$B53,INDIRECT("Descriptif!I"&E$13)=Recap_equipements!$C53),INDIRECT("Descriptif!M"&E$13)=$D53),INDIRECT("Descriptif!F"&E$13),"") | G53: =IF(AND(OR(INDIRECT("Descriptif!I"&F$13)=Recap_equipements!$B53,INDIRECT("Descriptif!I"&F$13)=Recap_equipements!$C53),INDIRECT("Descriptif!M"&F$13)=$D53),INDIRECT("Descriptif!F"&F$13),"") | H53: =IF(AND(OR(INDIRECT("Descriptif!I"&G$13)=Recap_equipements!$B53,INDIRECT("Descriptif!I"&G$13)=Recap_equipements!$C53),INDIRECT("Descriptif!M"&G$13)=$D53),INDIRECT("Descriptif!F"&G$13),"") | I53: =IF(AND(OR(INDIRECT("Descriptif!I"&H$13)=Recap_equipements!$B53,INDIRECT("Descriptif!I"&H$13)=Recap_equipements!$C53),INDIRECT("Descriptif!M"&H$13)=$D53),INDIRECT("Descriptif!F"&H$13),"") | J53: =IF(AND(OR(INDIRECT("Descriptif!I"&I$13)=Recap_equipements!$B53,INDIRECT("Descriptif!I"&I$13)=Recap_equipements!$C53),INDIRECT("Descriptif!M"&I$13)=$D53),INDIRECT("Descriptif!F"&I$13),"") | K53: =IF(AND(OR(INDIRECT("Descriptif!I"&J$13)=Recap_equipements!$B53,INDIRECT("Descriptif!I"&J$13)=Recap_equipements!$C53),INDIRECT("Descriptif!M"&J$13)=$D53),INDIRECT("Descriptif!F"&J$13),"") | L53: =IF(AND(OR(INDIRECT("Descriptif!I"&K$13)=Recap_equipements!$B53,INDIRECT("Descriptif!I"&K$13)=Recap_equipements!$C53),INDIRECT("Descriptif!M"&K$13)=$D53),INDIRECT("Descriptif!F"&K$13),"") | M53: =IF(AND(OR(INDIRECT("Descriptif!I"&L$13)=Recap_equipements!$B53,INDIRECT("Descriptif!I"&L$13)=Recap_equipements!$C53),INDIRECT("Descriptif!M"&L$13)=$D53),INDIRECT("Descriptif!F"&L$13),"") | ... T53: =IF(AND(OR(INDIRECT("Descriptif!I"&S$13)=Recap_equipements!$B53,INDIRECT("Descriptif!I"&S$13)=Recap_equipements!$C53),INDIRECT("Descriptif!M"&S$13)=$D53),INDIRECT("Descriptif!F"&S$13),"")
D54: =$D$8 -> Débitmètre gravitaire | F54: =IF(AND(OR(INDIRECT("Descriptif!I"&E$13)=Recap_equipements!$B53,INDIRECT("Descriptif!I"&E$13)=Recap_equipements!$C53),INDIRECT("Descriptif!M"&E$13)=$D54),INDIRECT("Descriptif!F"&E$13),"") | G54: =IF(AND(OR(INDIRECT("Descriptif!I"&F$13)=Recap_equipements!$B53,INDIRECT("Descriptif!I"&F$13)=Recap_equipements!$C53),INDIRECT("Descriptif!M"&F$13)=$D54),INDIRECT("Descriptif!F"&F$13),"") | H54: =IF(AND(OR(INDIRECT("Descriptif!I"&G$13)=Recap_equipements!$B53,INDIRECT("Descriptif!I"&G$13)=Recap_equipements!$C53),INDIRECT("Descriptif!M"&G$13)=$D54),INDIRECT("Descriptif!F"&G$13),"") | I54: =IF(AND(OR(INDIRECT("Descriptif!I"&H$13)=Recap_equipements!$B53,INDIRECT("Descriptif!I"&H$13)=Recap_equipements!$C53),INDIRECT("Descriptif!M"&H$13)=$D54),INDIRECT("Descriptif!F"&H$13),"") | J54: =IF(AND(OR(INDIRECT("Descriptif!I"&I$13)=Recap_equipements!$B53,INDIRECT("Descriptif!I"&I$13)=Recap_equipements!$C53),INDIRECT("Descriptif!M"&I$13)=$D54),INDIRECT("Descriptif!F"&I$13),"") | K54: =IF(AND(OR(INDIRECT("Descriptif!I"&J$13)=Recap_equipements!$B53,INDIRECT("Descriptif!I"&J$13)=Recap_equipements!$C53),INDIRECT("Descriptif!M"&J$13)=$D54),INDIRECT("Descriptif!F"&J$13),"") | L54: =IF(AND(OR(INDIRECT("Descriptif!I"&K$13)=Recap_equipements!$B53,INDIRECT("Descriptif!I"&K$13)=Recap_equipements!$C53),INDIRECT("Descriptif!M"&K$13)=$D54),INDIRECT("Descriptif!F"&K$13),"") | M54: =IF(AND(OR(INDIRECT("Descriptif!I"&L$13)=Recap_equipements!$B53,INDIRECT("Descriptif!I"&L$13)=Recap_equipements!$C53),INDIRECT("Descriptif!M"&L$13)=$D54),INDIRECT("Descriptif!F"&L$13),"") | ... T54: =IF(AND(OR(INDIRECT("Descriptif!I"&S$13)=Recap_equipements!$B53,INDIRECT("Descriptif!I"&S$13)=Recap_equipements!$C53),INDIRECT("Descriptif!M"&S$13)=$D54),INDIRECT("Descriptif!F"&S$13),"")
D55: =$D$9 -> Préleveur | F55: =IF(AND(OR(INDIRECT("Descriptif!I"&E$13)=Recap_equipements!$B53,INDIRECT("Descriptif!I"&E$13)=Recap_equipements!$C53),INDIRECT("Descriptif!M"&E$13)=$D55),INDIRECT("Descriptif!F"&E$13),"") | G55: =IF(AND(OR(INDIRECT("Descriptif!I"&F$13)=Recap_equipements!$B53,INDIRECT("Descriptif!I"&F$13)=Recap_equipements!$C53),INDIRECT("Descriptif!M"&F$13)=$D55),INDIRECT("Descriptif!F"&F$13),"") | H55: =IF(AND(OR(INDIRECT("Descriptif!I"&G$13)=Recap_equipements!$B53,INDIRECT("Descriptif!I"&G$13)=Recap_equipements!$C53),INDIRECT("Descriptif!M"&G$13)=$D55),INDIRECT("Descriptif!F"&G$13),"") | I55: =IF(AND(OR(INDIRECT("Descriptif!I"&H$13)=Recap_equipements!$B53,INDIRECT("Descriptif!I"&H$13)=Recap_equipements!$C53),INDIRECT("Descriptif!M"&H$13)=$D55),INDIRECT("Descriptif!F"&H$13),"") | J55: =IF(AND(OR(INDIRECT("Descriptif!I"&I$13)=Recap_equipements!$B53,INDIRECT("Descriptif!I"&I$13)=Recap_equipements!$C53),INDIRECT("Descriptif!M"&I$13)=$D55),INDIRECT("Descriptif!F"&I$13),"") | K55: =IF(AND(OR(INDIRECT("Descriptif!I"&J$13)=Recap_equipements!$B53,INDIRECT("Descriptif!I"&J$13)=Recap_equipements!$C53),INDIRECT("Descriptif!M"&J$13)=$D55),INDIRECT("Descriptif!F"&J$13),"") | L55: =IF(AND(OR(INDIRECT("Descriptif!I"&K$13)=Recap_equipements!$B53,INDIRECT("Descriptif!I"&K$13)=Recap_equipements!$C53),INDIRECT("Descriptif!M"&K$13)=$D55),INDIRECT("Descriptif!F"&K$13),"") | M55: =IF(AND(OR(INDIRECT("Descriptif!I"&L$13)=Recap_equipements!$B53,INDIRECT("Descriptif!I"&L$13)=Recap_equipements!$C53),INDIRECT("Descriptif!M"&L$13)=$D55),INDIRECT("Descriptif!F"&L$13),"") | ... T55: =IF(AND(OR(INDIRECT("Descriptif!I"&S$13)=Recap_equipements!$B53,INDIRECT("Descriptif!I"&S$13)=Recap_equipements!$C53),INDIRECT("Descriptif!M"&S$13)=$D55),INDIRECT("Descriptif!F"&S$13),"")
D56: Analytique | F56: =IF(F55<>"",VLOOKUP(F55,Analytique!$X$3:$AD$33,1,FALSE),"") | G56: =IF(G55<>"",VLOOKUP(G55,Analytique!$X$3:$AD$33,1,FALSE),"") | H56: =IF(H55<>"",VLOOKUP(H55,Analytique!$X$3:$AD$33,1,FALSE),"") | I56: =IF(I55<>"",VLOOKUP(I55,Analytique!$X$3:$AD$33,1,FALSE),"") | J56: =IF(J55<>"",VLOOKUP(J55,Analytique!$X$3:$AD$33,1,FALSE),"") | K56: =IF(K55<>"",VLOOKUP(K55,Analytique!$X$3:$AD$33,1,FALSE),"") | L56: =IF(L55<>"",VLOOKUP(L55,Analytique!$X$3:$AD$33,1,FALSE),"") | M56: =IF(M55<>"",VLOOKUP(M55,Analytique!$X$3:$AD$33,1,FALSE),"") | ... T56: =IF(T55<>"",VLOOKUP(T55,Analytique!$X$3:$AD$33,1,FALSE),"")
D57: =$D$10 -> Sonde de température | F57: =IF(AND(OR(INDIRECT("Descriptif!I"&E$13)=Recap_equipements!$B53,INDIRECT("Descriptif!I"&E$13)=Recap_equipements!$C53),INDIRECT("Descriptif!M"&E$13)=$D57),INDIRECT("Descriptif!F"&E$13),"") | G57: =IF(AND(OR(INDIRECT("Descriptif!I"&F$13)=Recap_equipements!$B53,INDIRECT("Descriptif!I"&F$13)=Recap_equipements!$C53),INDIRECT("Descriptif!M"&F$13)=$D57),INDIRECT("Descriptif!F"&F$13),"") | H57: =IF(AND(OR(INDIRECT("Descriptif!I"&G$13)=Recap_equipements!$B53,INDIRECT("Descriptif!I"&G$13)=Recap_equipements!$C53),INDIRECT("Descriptif!M"&G$13)=$D57),INDIRECT("Descriptif!F"&G$13),"") | I57: =IF(AND(OR(INDIRECT("Descriptif!I"&H$13)=Recap_equipements!$B53,INDIRECT("Descriptif!I"&H$13)=Recap_equipements!$C53),INDIRECT("Descriptif!M"&H$13)=$D57),INDIRECT("Descriptif!F"&H$13),"") | J57: =IF(AND(OR(INDIRECT("Descriptif!I"&I$13)=Recap_equipements!$B53,INDIRECT("Descriptif!I"&I$13)=Recap_equipements!$C53),INDIRECT("Descriptif!M"&I$13)=$D57),INDIRECT("Descriptif!F"&I$13),"") | K57: =IF(AND(OR(INDIRECT("Descriptif!I"&J$13)=Recap_equipements!$B53,INDIRECT("Descriptif!I"&J$13)=Recap_equipements!$C53),INDIRECT("Descriptif!M"&J$13)=$D57),INDIRECT("Descriptif!F"&J$13),"") | L57: =IF(AND(OR(INDIRECT("Descriptif!I"&K$13)=Recap_equipements!$B53,INDIRECT("Descriptif!I"&K$13)=Recap_equipements!$C53),INDIRECT("Descriptif!M"&K$13)=$D57),INDIRECT("Descriptif!F"&K$13),"") | M57: =IF(AND(OR(INDIRECT("Descriptif!I"&L$13)=Recap_equipements!$B53,INDIRECT("Descriptif!I"&L$13)=Recap_equipements!$C53),INDIRECT("Descriptif!M"&L$13)=$D57),INDIRECT("Descriptif!F"&L$13),"") | ... T57: =IF(AND(OR(INDIRECT("Descriptif!I"&S$13)=Recap_equipements!$B53,INDIRECT("Descriptif!I"&S$13)=Recap_equipements!$C53),INDIRECT("Descriptif!M"&S$13)=$D57),INDIRECT("Descriptif!F"&S$13),"")
B59: Scores
B60: Les évaluations des sondes de température ne sont pas prises en compte
B61: Reg. | C61: Log. | E61: Moyennes générales | F61: Moyennes individuelles | G61: Point 1 | H61: Point 2 | I61: Point 3 | J61: Point 4 | K61: Point 5 | L61: Point 6 | M61: Point 7 | N61: Point 8 | O61: Point 9 | P61: Point 10 | Q61: Point 11 | R61: Point 12 | S61: Point 13 | T61: Point 14 | U61: Point 15
B62: A3 | C62: S1 | D62: =$D$7 -> Débitmètre en charge | E62: =IFERROR(AVERAGE(F64:F66)*$B$5,"") -> 78.333333 | F62: =IFERROR(AVERAGE(G62:U62),"") -> 60 | G62: =IF(F19<>"",_xlfn.SINGLE(INDIRECT(F19&"!"&$F$7)),"") | H62: =IF(G19<>"",_xlfn.SINGLE(INDIRECT(G19&"!"&$F$7)),"") -> 60 | I62: =IF(H19<>"",_xlfn.SINGLE(INDIRECT(H19&"!"&$F$7)),"") | J62: =IF(I19<>"",_xlfn.SINGLE(INDIRECT(I19&"!"&$F$7)),"") | K62: =IF(J19<>"",_xlfn.SINGLE(INDIRECT(J19&"!"&$F$7)),"") | L62: =IF(K19<>"",_xlfn.SINGLE(INDIRECT(K19&"!"&$F$7)),"") | M62: =IF(L19<>"",_xlfn.SINGLE(INDIRECT(L19&"!"&$F$7)),"") | N62: =IF(M19<>"",_xlfn.SINGLE(INDIRECT(M19&"!"&$F$7)),"") | ... U62: =IF(T19<>"",_xlfn.SINGLE(INDIRECT(T19&"!"&$F$7)),"")
D63: =$D$8 -> Débitmètre gravitaire | F63: =IFERROR(AVERAGE(G63:U63),"") | G63: =IF(F20<>"",_xlfn.SINGLE(INDIRECT(F20&"!"&$F$8)),"") | H63: =IF(G20<>"",_xlfn.SINGLE(INDIRECT(G20&"!"&$F$8)),"") | I63: =IF(H20<>"",_xlfn.SINGLE(INDIRECT(H20&"!"&$F$8)),"") | J63: =IF(I20<>"",_xlfn.SINGLE(INDIRECT(I20&"!"&$F$8)),"") | K63: =IF(J20<>"",_xlfn.SINGLE(INDIRECT(J20&"!"&$F$8)),"") | L63: =IF(K20<>"",_xlfn.SINGLE(INDIRECT(K20&"!"&$F$8)),"") | M63: =IF(L20<>"",_xlfn.SINGLE(INDIRECT(L20&"!"&$F$8)),"") | N63: =IF(M20<>"",_xlfn.SINGLE(INDIRECT(M20&"!"&$F$8)),"") | ... U63: =IF(T20<>"",_xlfn.SINGLE(INDIRECT(T20&"!"&$F$8)),"")
D64: Débitmètre | F64: =IFERROR(AVERAGE(G64:U64),"") -> 60 | G64: =IF(COUNT(G62:G63)>0,SUM(G62:G63),"") | H64: =IF(COUNT(H62:H63)>0,SUM(H62:H63),"") -> 60 | I64: =IF(COUNT(I62:I63)>0,SUM(I62:I63),"") | J64: =IF(COUNT(J62:J63)>0,SUM(J62:J63),"") | K64: =IF(COUNT(K62:K63)>0,SUM(K62:K63),"") | L64: =IF(COUNT(L62:L63)>0,SUM(L62:L63),"") | M64: =IF(COUNT(M62:M63)>0,SUM(M62:M63),"") | N64: =IF(COUNT(N62:N63)>0,SUM(N62:N63),"") | ... U64: =IF(COUNT(U62:U63)>0,SUM(U62:U63),"")
D65: =$D$9 -> Préleveur | F65: =IFERROR(AVERAGE(G65:U65),"") -> 85 | G65: =IF(F21<>"",_xlfn.SINGLE(INDIRECT(F21&"!"&$F$9)),"") | H65: =IF(G21<>"",_xlfn.SINGLE(INDIRECT(G21&"!"&$F$9)),"") | I65: =IF(H21<>"",_xlfn.SINGLE(INDIRECT(H21&"!"&$F$9)),"") -> 85 | J65: =IF(I21<>"",_xlfn.SINGLE(INDIRECT(I21&"!"&$F$9)),"") | K65: =IF(J21<>"",_xlfn.SINGLE(INDIRECT(J21&"!"&$F$9)),"") | L65: =IF(K21<>"",_xlfn.SINGLE(INDIRECT(K21&"!"&$F$9)),"") | M65: =IF(L21<>"",_xlfn.SINGLE(INDIRECT(L21&"!"&$F$9)),"") | N65: =IF(M21<>"",_xlfn.SINGLE(INDIRECT(M21&"!"&$F$9)),"") | ... U65: =IF(T21<>"",_xlfn.SINGLE(INDIRECT(T21&"!"&$F$9)),"")
D66: Analytique | F66: =IFERROR(AVERAGE(G66:U66),"") -> 90 | G66: =IF(F21<>"",VLOOKUP(F21,Analytique!$X$3:$AD$33,6,FALSE),"") | H66: =IF(G21<>"",VLOOKUP(G21,Analytique!$X$3:$AD$33,6,FALSE),"") | I66: =IF(H21<>"",VLOOKUP(H21,Analytique!$X$3:$AD$33,6,FALSE),"") -> 90 | J66: =IF(I21<>"",VLOOKUP(I21,Analytique!$X$3:$AD$33,6,FALSE),"") | K66: =IF(J21<>"",VLOOKUP(J21,Analytique!$X$3:$AD$33,6,FALSE),"") | L66: =IF(K21<>"",VLOOKUP(K21,Analytique!$X$3:$AD$33,6,FALSE),"") | M66: =IF(L21<>"",VLOOKUP(L21,Analytique!$X$3:$AD$33,6,FALSE),"") | N66: =IF(M21<>"",VLOOKUP(M21,Analytique!$X$3:$AD$33,6,FALSE),"") | ... U66: =IF(T21<>"",VLOOKUP(T21,Analytique!$X$3:$AD$33,6,FALSE),"")
D67: =$D$10 -> Sonde de température | F67: =IFERROR(AVERAGE(G67:U67),"") | G67: =IF(F23<>"",_xlfn.SINGLE(INDIRECT(F23&"!"&$F$10)),"") | H67: =IF(G23<>"",_xlfn.SINGLE(INDIRECT(G23&"!"&$F$10)),"") | I67: =IF(H23<>"",_xlfn.SINGLE(INDIRECT(H23&"!"&$F$10)),"") | J67: =IF(I23<>"",_xlfn.SINGLE(INDIRECT(I23&"!"&$F$10)),"") | K67: =IF(J23<>"",_xlfn.SINGLE(INDIRECT(J23&"!"&$F$10)),"") | L67: =IF(K23<>"",_xlfn.SINGLE(INDIRECT(K23&"!"&$F$10)),"") | M67: =IF(L23<>"",_xlfn.SINGLE(INDIRECT(L23&"!"&$F$10)),"") | N67: =IF(M23<>"",_xlfn.SINGLE(INDIRECT(M23&"!"&$F$10)),"") | ... U67: =IF(T23<>"",_xlfn.SINGLE(INDIRECT(T23&"!"&$F$10)),"")
B68: A4 | C68: S2 | D68: =$D$7 -> Débitmètre en charge | E68: =IFERROR(AVERAGE(F70:F72)*$B$5,"") -> 63.333333 | F68: =IFERROR(AVERAGE(G68:U68),"") | G68: =IF(F24<>"",_xlfn.SINGLE(INDIRECT(F24&"!"&$F$7)),"") | H68: =IF(G24<>"",_xlfn.SINGLE(INDIRECT(G24&"!"&$F$7)),"") | I68: =IF(H24<>"",_xlfn.SINGLE(INDIRECT(H24&"!"&$F$7)),"") | J68: =IF(I24<>"",_xlfn.SINGLE(INDIRECT(I24&"!"&$F$7)),"") | K68: =IF(J24<>"",_xlfn.SINGLE(INDIRECT(J24&"!"&$F$7)),"") | L68: =IF(K24<>"",_xlfn.SINGLE(INDIRECT(K24&"!"&$F$7)),"") | M68: =IF(L24<>"",_xlfn.SINGLE(INDIRECT(L24&"!"&$F$7)),"") | N68: =IF(M24<>"",_xlfn.SINGLE(INDIRECT(M24&"!"&$F$7)),"") | ... U68: =IF(T24<>"",_xlfn.SINGLE(INDIRECT(T24&"!"&$F$7)),"")
D69: =$D$8 -> Débitmètre gravitaire | F69: =IFERROR(AVERAGE(G69:U69),"") -> 0 | G69: =IF(F25<>"",_xlfn.SINGLE(INDIRECT(F25&"!"&$F$8)),"") | H69: =IF(G25<>"",_xlfn.SINGLE(INDIRECT(G25&"!"&$F$8)),"") | I69: =IF(H25<>"",_xlfn.SINGLE(INDIRECT(H25&"!"&$F$8)),"") | J69: =IF(I25<>"",_xlfn.SINGLE(INDIRECT(I25&"!"&$F$8)),"") -> 0 | K69: =IF(J25<>"",_xlfn.SINGLE(INDIRECT(J25&"!"&$F$8)),"") | L69: =IF(K25<>"",_xlfn.SINGLE(INDIRECT(K25&"!"&$F$8)),"") | M69: =IF(L25<>"",_xlfn.SINGLE(INDIRECT(L25&"!"&$F$8)),"") | N69: =IF(M25<>"",_xlfn.SINGLE(INDIRECT(M25&"!"&$F$8)),"") | ... U69: =IF(T25<>"",_xlfn.SINGLE(INDIRECT(T25&"!"&$F$8)),"")
D70: Débitmètre | F70: =IFERROR(AVERAGE(G70:U70),"") -> 0 | G70: =IF(COUNT(G68:G69)>0,SUM(G68:G69),"") | H70: =IF(COUNT(H68:H69)>0,SUM(H68:H69),"") | I70: =IF(COUNT(I68:I69)>0,SUM(I68:I69),"") | J70: =IF(COUNT(J68:J69)>0,SUM(J68:J69),"") -> 0 | K70: =IF(COUNT(K68:K69)>0,SUM(K68:K69),"") | L70: =IF(COUNT(L68:L69)>0,SUM(L68:L69),"") | M70: =IF(COUNT(M68:M69)>0,SUM(M68:M69),"") | N70: =IF(COUNT(N68:N69)>0,SUM(N68:N69),"") | ... U70: =IF(COUNT(U68:U69)>0,SUM(U68:U69),"")
D71: =$D$9 -> Préleveur | F71: =IFERROR(AVERAGE(G71:U71),"") -> 100 | G71: =IF(F26<>"",_xlfn.SINGLE(INDIRECT(F26&"!"&$F$9)),"") | H71: =IF(G26<>"",_xlfn.SINGLE(INDIRECT(G26&"!"&$F$9)),"") | I71: =IF(H26<>"",_xlfn.SINGLE(INDIRECT(H26&"!"&$F$9)),"") | J71: =IF(I26<>"",_xlfn.SINGLE(INDIRECT(I26&"!"&$F$9)),"") | K71: =IF(J26<>"",_xlfn.SINGLE(INDIRECT(J26&"!"&$F$9)),"") -> 100 | L71: =IF(K26<>"",_xlfn.SINGLE(INDIRECT(K26&"!"&$F$9)),"") | M71: =IF(L26<>"",_xlfn.SINGLE(INDIRECT(L26&"!"&$F$9)),"") | N71: =IF(M26<>"",_xlfn.SINGLE(INDIRECT(M26&"!"&$F$9)),"") | ... U71: =IF(T26<>"",_xlfn.SINGLE(INDIRECT(T26&"!"&$F$9)),"")
D72: Analytique | F72: =IFERROR(AVERAGE(G72:U72),"") -> 90 | G72: =IF(F27<>"",VLOOKUP(F27,Analytique!$X$3:$AD$33,6,FALSE),"") | H72: =IF(G27<>"",VLOOKUP(G27,Analytique!$X$3:$AD$33,6,FALSE),"") | I72: =IF(H27<>"",VLOOKUP(H27,Analytique!$X$3:$AD$33,6,FALSE),"") | J72: =IF(I27<>"",VLOOKUP(I27,Analytique!$X$3:$AD$33,6,FALSE),"") | K72: =IF(J27<>"",VLOOKUP(J27,Analytique!$X$3:$AD$33,6,FALSE),"") -> 90 | L72: =IF(K27<>"",VLOOKUP(K27,Analytique!$X$3:$AD$33,6,FALSE),"") | M72: =IF(L27<>"",VLOOKUP(L27,Analytique!$X$3:$AD$33,6,FALSE),"") | N72: =IF(M27<>"",VLOOKUP(M27,Analytique!$X$3:$AD$33,6,FALSE),"") | ... U72: =IF(T27<>"",VLOOKUP(T27,Analytique!$X$3:$AD$33,6,FALSE),"")
D73: =$D$10 -> Sonde de température | F73: =IFERROR(AVERAGE(G73:U73),"") -> 100 | G73: =IF(F28<>"",_xlfn.SINGLE(INDIRECT(F28&"!"&$F$10)),"") | H73: =IF(G28<>"",_xlfn.SINGLE(INDIRECT(G28&"!"&$F$10)),"") | I73: =IF(H28<>"",_xlfn.SINGLE(INDIRECT(H28&"!"&$F$10)),"") | J73: =IF(I28<>"",_xlfn.SINGLE(INDIRECT(I28&"!"&$F$10)),"") | K73: =IF(J28<>"",_xlfn.SINGLE(INDIRECT(J28&"!"&$F$10)),"") | L73: =IF(K28<>"",_xlfn.SINGLE(INDIRECT(K28&"!"&$F$10)),"") | M73: =IF(L28<>"",_xlfn.SINGLE(INDIRECT(L28&"!"&$F$10)),"") -> 100 | N73: =IF(M28<>"",_xlfn.SINGLE(INDIRECT(M28&"!"&$F$10)),"") | ... U73: =IF(T28<>"",_xlfn.SINGLE(INDIRECT(T28&"!"&$F$10)),"")
B74: A2 | C74: S16 | D74: =$D$7 -> Débitmètre en charge | E74: =IFERROR(AVERAGE(F76:F78)*$B$5,"") -> 80 | F74: =IFERROR(AVERAGE(G74:U74),"") | G74: =IF(F29<>"",_xlfn.SINGLE(INDIRECT(F29&"!"&$F$7)),"") | H74: =IF(G29<>"",_xlfn.SINGLE(INDIRECT(G29&"!"&$F$7)),"") | I74: =IF(H29<>"",_xlfn.SINGLE(INDIRECT(H29&"!"&$F$7)),"") | J74: =IF(I29<>"",_xlfn.SINGLE(INDIRECT(I29&"!"&$F$7)),"") | K74: =IF(J29<>"",_xlfn.SINGLE(INDIRECT(J29&"!"&$F$7)),"") | L74: =IF(K29<>"",_xlfn.SINGLE(INDIRECT(K29&"!"&$F$7)),"") | M74: =IF(L29<>"",_xlfn.SINGLE(INDIRECT(L29&"!"&$F$7)),"") | N74: =IF(M29<>"",_xlfn.SINGLE(INDIRECT(M29&"!"&$F$7)),"") | ... U74: =IF(T29<>"",_xlfn.SINGLE(INDIRECT(T29&"!"&$F$7)),"")
D75: =$D$8 -> Débitmètre gravitaire | F75: =IFERROR(AVERAGE(G75:U75),"") -> 80 | G75: =IF(F30<>"",_xlfn.SINGLE(INDIRECT(F30&"!"&$F$8)),"") -> 80 | H75: =IF(G30<>"",_xlfn.SINGLE(INDIRECT(G30&"!"&$F$8)),"") | I75: =IF(H30<>"",_xlfn.SINGLE(INDIRECT(H30&"!"&$F$8)),"") | J75: =IF(I30<>"",_xlfn.SINGLE(INDIRECT(I30&"!"&$F$8)),"") | K75: =IF(J30<>"",_xlfn.SINGLE(INDIRECT(J30&"!"&$F$8)),"") | L75: =IF(K30<>"",_xlfn.SINGLE(INDIRECT(K30&"!"&$F$8)),"") | M75: =IF(L30<>"",_xlfn.SINGLE(INDIRECT(L30&"!"&$F$8)),"") | N75: =IF(M30<>"",_xlfn.SINGLE(INDIRECT(M30&"!"&$F$8)),"") | ... U75: =IF(T30<>"",_xlfn.SINGLE(INDIRECT(T30&"!"&$F$8)),"")
D76: Débitmètre | F76: =IFERROR(AVERAGE(G76:U76),"") -> 80 | G76: =IF(COUNT(G74:G75)>0,SUM(G74:G75),"") -> 80 | H76: =IF(COUNT(H74:H75)>0,SUM(H74:H75),"") | I76: =IF(COUNT(I74:I75)>0,SUM(I74:I75),"") | J76: =IF(COUNT(J74:J75)>0,SUM(J74:J75),"") | K76: =IF(COUNT(K74:K75)>0,SUM(K74:K75),"") | L76: =IF(COUNT(L74:L75)>0,SUM(L74:L75),"") | M76: =IF(COUNT(M74:M75)>0,SUM(M74:M75),"") | N76: =IF(COUNT(N74:N75)>0,SUM(N74:N75),"") | ... U76: =IF(COUNT(U74:U75)>0,SUM(U74:U75),"")
D77: =$D$9 -> Préleveur | F77: =IFERROR(AVERAGE(G77:U77),"") | G77: =IF(F31<>"",_xlfn.SINGLE(INDIRECT(F31&"!"&$F$9)),"") | H77: =IF(G31<>"",_xlfn.SINGLE(INDIRECT(G31&"!"&$F$9)),"") | I77: =IF(H31<>"",_xlfn.SINGLE(INDIRECT(H31&"!"&$F$9)),"") | J77: =IF(I31<>"",_xlfn.SINGLE(INDIRECT(I31&"!"&$F$9)),"") | K77: =IF(J31<>"",_xlfn.SINGLE(INDIRECT(J31&"!"&$F$9)),"") | L77: =IF(K31<>"",_xlfn.SINGLE(INDIRECT(K31&"!"&$F$9)),"") | M77: =IF(L31<>"",_xlfn.SINGLE(INDIRECT(L31&"!"&$F$9)),"") | N77: =IF(M31<>"",_xlfn.SINGLE(INDIRECT(M31&"!"&$F$9)),"") | ... U77: =IF(T31<>"",_xlfn.SINGLE(INDIRECT(T31&"!"&$F$9)),"")
D78: Analytique | F78: =IFERROR(AVERAGE(G78:U78),"") | G78: =IF(F33<>"",VLOOKUP(F33,Analytique!$X$3:$AD$33,6,FALSE),"") | H78: =IF(G33<>"",VLOOKUP(G33,Analytique!$X$3:$AD$33,6,FALSE),"") | I78: =IF(H33<>"",VLOOKUP(H33,Analytique!$X$3:$AD$33,6,FALSE),"") | J78: =IF(I33<>"",VLOOKUP(I33,Analytique!$X$3:$AD$33,6,FALSE),"") | K78: =IF(J33<>"",VLOOKUP(J33,Analytique!$X$3:$AD$33,6,FALSE),"") | L78: =IF(K33<>"",VLOOKUP(K33,Analytique!$X$3:$AD$33,6,FALSE),"") | M78: =IF(L33<>"",VLOOKUP(L33,Analytique!$X$3:$AD$33,6,FALSE),"") | N78: =IF(M33<>"",VLOOKUP(M33,Analytique!$X$3:$AD$33,6,FALSE),"") | ... U78: =IF(T33<>"",VLOOKUP(T33,Analytique!$X$3:$AD$33,6,FALSE),"")
D79: =$D$10 -> Sonde de température | F79: =IFERROR(AVERAGE(G79:U79),"") | G79: =IF(F33<>"",_xlfn.SINGLE(INDIRECT(F33&"!"&$F$10)),"") | H79: =IF(G33<>"",_xlfn.SINGLE(INDIRECT(G33&"!"&$F$10)),"") | I79: =IF(H33<>"",_xlfn.SINGLE(INDIRECT(H33&"!"&$F$10)),"") | J79: =IF(I33<>"",_xlfn.SINGLE(INDIRECT(I33&"!"&$F$10)),"") | K79: =IF(J33<>"",_xlfn.SINGLE(INDIRECT(J33&"!"&$F$10)),"") | L79: =IF(K33<>"",_xlfn.SINGLE(INDIRECT(K33&"!"&$F$10)),"") | M79: =IF(L33<>"",_xlfn.SINGLE(INDIRECT(L33&"!"&$F$10)),"") | N79: =IF(M33<>"",_xlfn.SINGLE(INDIRECT(M33&"!"&$F$10)),"") | ... U79: =IF(T33<>"",_xlfn.SINGLE(INDIRECT(T33&"!"&$F$10)),"")
B80: A5 | C80: S3 | D80: =$D$7 -> Débitmètre en charge | E80: =IFERROR(AVERAGE(F82:F84)*$B$5,"") | F80: =IFERROR(AVERAGE(G80:U80),"") | G80: =IF(F34<>"",_xlfn.SINGLE(INDIRECT(F34&"!"&$F$7)),"") | H80: =IF(G34<>"",_xlfn.SINGLE(INDIRECT(G34&"!"&$F$7)),"") | I80: =IF(H34<>"",_xlfn.SINGLE(INDIRECT(H34&"!"&$F$7)),"") | J80: =IF(I34<>"",_xlfn.SINGLE(INDIRECT(I34&"!"&$F$7)),"") | K80: =IF(J34<>"",_xlfn.SINGLE(INDIRECT(J34&"!"&$F$7)),"") | L80: =IF(K34<>"",_xlfn.SINGLE(INDIRECT(K34&"!"&$F$7)),"") | M80: =IF(L34<>"",_xlfn.SINGLE(INDIRECT(L34&"!"&$F$7)),"") | N80: =IF(M34<>"",_xlfn.SINGLE(INDIRECT(M34&"!"&$F$7)),"") | ... U80: =IF(T34<>"",_xlfn.SINGLE(INDIRECT(T34&"!"&$F$7)),"")
D81: =$D$8 -> Débitmètre gravitaire | F81: =IFERROR(AVERAGE(G81:U81),"") | G81: =IF(F35<>"",_xlfn.SINGLE(INDIRECT(F35&"!"&$F$8)),"") | H81: =IF(G35<>"",_xlfn.SINGLE(INDIRECT(G35&"!"&$F$8)),"") | I81: =IF(H35<>"",_xlfn.SINGLE(INDIRECT(H35&"!"&$F$8)),"") | J81: =IF(I35<>"",_xlfn.SINGLE(INDIRECT(I35&"!"&$F$8)),"") | K81: =IF(J35<>"",_xlfn.SINGLE(INDIRECT(J35&"!"&$F$8)),"") | L81: =IF(K35<>"",_xlfn.SINGLE(INDIRECT(K35&"!"&$F$8)),"") | M81: =IF(L35<>"",_xlfn.SINGLE(INDIRECT(L35&"!"&$F$8)),"") | N81: =IF(M35<>"",_xlfn.SINGLE(INDIRECT(M35&"!"&$F$8)),"") | ... U81: =IF(T35<>"",_xlfn.SINGLE(INDIRECT(T35&"!"&$F$8)),"")
D82: Débitmètre | F82: =IFERROR(AVERAGE(G82:U82),"") | G82: =IF(COUNT(G80:G81)>0,SUM(G80:G81),"") | H82: =IF(COUNT(H80:H81)>0,SUM(H80:H81),"") | I82: =IF(COUNT(I80:I81)>0,SUM(I80:I81),"") | J82: =IF(COUNT(J80:J81)>0,SUM(J80:J81),"") | K82: =IF(COUNT(K80:K81)>0,SUM(K80:K81),"") | L82: =IF(COUNT(L80:L81)>0,SUM(L80:L81),"") | M82: =IF(COUNT(M80:M81)>0,SUM(M80:M81),"") | N82: =IF(COUNT(N80:N81)>0,SUM(N80:N81),"") | ... U82: =IF(COUNT(U80:U81)>0,SUM(U80:U81),"")
D83: =$D$9 -> Préleveur | F83: =IFERROR(AVERAGE(G83:U83),"") | G83: =IF(F36<>"",_xlfn.SINGLE(INDIRECT(F36&"!"&$F$9)),"") | H83: =IF(G36<>"",_xlfn.SINGLE(INDIRECT(G36&"!"&$F$9)),"") | I83: =IF(H36<>"",_xlfn.SINGLE(INDIRECT(H36&"!"&$F$9)),"") | J83: =IF(I36<>"",_xlfn.SINGLE(INDIRECT(I36&"!"&$F$9)),"") | K83: =IF(J36<>"",_xlfn.SINGLE(INDIRECT(J36&"!"&$F$9)),"") | L83: =IF(K36<>"",_xlfn.SINGLE(INDIRECT(K36&"!"&$F$9)),"") | M83: =IF(L36<>"",_xlfn.SINGLE(INDIRECT(L36&"!"&$F$9)),"") | N83: =IF(M36<>"",_xlfn.SINGLE(INDIRECT(M36&"!"&$F$9)),"") | ... U83: =IF(T36<>"",_xlfn.SINGLE(INDIRECT(T36&"!"&$F$9)),"")
D84: Analytique | F84: =IFERROR(AVERAGE(G84:U84),"") | G84: =IF(F39<>"",VLOOKUP(F39,Analytique!$X$3:$AD$33,6,FALSE),"") | H84: =IF(G39<>"",VLOOKUP(G39,Analytique!$X$3:$AD$33,6,FALSE),"") | I84: =IF(H39<>"",VLOOKUP(H39,Analytique!$X$3:$AD$33,6,FALSE),"") | J84: =IF(I39<>"",VLOOKUP(I39,Analytique!$X$3:$AD$33,6,FALSE),"") | K84: =IF(J39<>"",VLOOKUP(J39,Analytique!$X$3:$AD$33,6,FALSE),"") | L84: =IF(K39<>"",VLOOKUP(K39,Analytique!$X$3:$AD$33,6,FALSE),"") | M84: =IF(L39<>"",VLOOKUP(L39,Analytique!$X$3:$AD$33,6,FALSE),"") | N84: =IF(M39<>"",VLOOKUP(M39,Analytique!$X$3:$AD$33,6,FALSE),"") | ... U84: =IF(T39<>"",VLOOKUP(T39,Analytique!$X$3:$AD$33,6,FALSE),"")
D85: =$D$10 -> Sonde de température | F85: =IFERROR(AVERAGE(G85:U85),"") | G85: =IF(F37<>"",_xlfn.SINGLE(INDIRECT(F37&"!"&$F$10)),"") | H85: =IF(G37<>"",_xlfn.SINGLE(INDIRECT(G37&"!"&$F$10)),"") | I85: =IF(H37<>"",_xlfn.SINGLE(INDIRECT(H37&"!"&$F$10)),"") | J85: =IF(I37<>"",_xlfn.SINGLE(INDIRECT(I37&"!"&$F$10)),"") | K85: =IF(J37<>"",_xlfn.SINGLE(INDIRECT(J37&"!"&$F$10)),"") | L85: =IF(K37<>"",_xlfn.SINGLE(INDIRECT(K37&"!"&$F$10)),"") | M85: =IF(L37<>"",_xlfn.SINGLE(INDIRECT(L37&"!"&$F$10)),"") | N85: =IF(M37<>"",_xlfn.SINGLE(INDIRECT(M37&"!"&$F$10)),"") | ... U85: =IF(T37<>"",_xlfn.SINGLE(INDIRECT(T37&"!"&$F$10)),"")
B86: A6 | C86: S4 | D86: =$D$7 -> Débitmètre en charge | E86: =IFERROR(AVERAGE(F88:F90)*$B$5,"") -> 40 | F86: =IFERROR(AVERAGE(G86:U86),"") -> 40 | G86: =IF(F38<>"",_xlfn.SINGLE(INDIRECT(F38&"!"&$F$7)),"") | H86: =IF(G38<>"",_xlfn.SINGLE(INDIRECT(G38&"!"&$F$7)),"") | I86: =IF(H38<>"",_xlfn.SINGLE(INDIRECT(H38&"!"&$F$7)),"") | J86: =IF(I38<>"",_xlfn.SINGLE(INDIRECT(I38&"!"&$F$7)),"") | K86: =IF(J38<>"",_xlfn.SINGLE(INDIRECT(J38&"!"&$F$7)),"") | L86: =IF(K38<>"",_xlfn.SINGLE(INDIRECT(K38&"!"&$F$7)),"") -> 40 | M86: =IF(L38<>"",_xlfn.SINGLE(INDIRECT(L38&"!"&$F$7)),"") | N86: =IF(M38<>"",_xlfn.SINGLE(INDIRECT(M38&"!"&$F$7)),"") | ... U86: =IF(T38<>"",_xlfn.SINGLE(INDIRECT(T38&"!"&$F$7)),"")
D87: =$D$8 -> Débitmètre gravitaire | F87: =IFERROR(AVERAGE(G87:U87),"") | G87: =IF(F39<>"",_xlfn.SINGLE(INDIRECT(F39&"!"&$F$8)),"") | H87: =IF(G39<>"",_xlfn.SINGLE(INDIRECT(G39&"!"&$F$8)),"") | I87: =IF(H39<>"",_xlfn.SINGLE(INDIRECT(H39&"!"&$F$8)),"") | J87: =IF(I39<>"",_xlfn.SINGLE(INDIRECT(I39&"!"&$F$8)),"") | K87: =IF(J39<>"",_xlfn.SINGLE(INDIRECT(J39&"!"&$F$8)),"") | L87: =IF(K39<>"",_xlfn.SINGLE(INDIRECT(K39&"!"&$F$8)),"") | M87: =IF(L39<>"",_xlfn.SINGLE(INDIRECT(L39&"!"&$F$8)),"") | N87: =IF(M39<>"",_xlfn.SINGLE(INDIRECT(M39&"!"&$F$8)),"") | ... U87: =IF(T39<>"",_xlfn.SINGLE(INDIRECT(T39&"!"&$F$8)),"")
D88: Débitmètre | F88: =IFERROR(AVERAGE(G88:U88),"") -> 40 | G88: =IF(COUNT(G86:G87)>0,SUM(G86:G87),"") | H88: =IF(COUNT(H86:H87)>0,SUM(H86:H87),"") | I88: =IF(COUNT(I86:I87)>0,SUM(I86:I87),"") | J88: =IF(COUNT(J86:J87)>0,SUM(J86:J87),"") | K88: =IF(COUNT(K86:K87)>0,SUM(K86:K87),"") | L88: =IF(COUNT(L86:L87)>0,SUM(L86:L87),"") -> 40 | M88: =IF(COUNT(M86:M87)>0,SUM(M86:M87),"") | N88: =IF(COUNT(N86:N87)>0,SUM(N86:N87),"") | ... U88: =IF(COUNT(U86:U87)>0,SUM(U86:U87),"")
D89: =$D$9 -> Préleveur | F89: =IFERROR(AVERAGE(G89:U89),"") | G89: =IF(F40<>"",_xlfn.SINGLE(INDIRECT(F40&"!"&$F$9)),"") | H89: =IF(G40<>"",_xlfn.SINGLE(INDIRECT(G40&"!"&$F$9)),"") | I89: =IF(H40<>"",_xlfn.SINGLE(INDIRECT(H40&"!"&$F$9)),"") | J89: =IF(I40<>"",_xlfn.SINGLE(INDIRECT(I40&"!"&$F$9)),"") | K89: =IF(J40<>"",_xlfn.SINGLE(INDIRECT(J40&"!"&$F$9)),"") | L89: =IF(K40<>"",_xlfn.SINGLE(INDIRECT(K40&"!"&$F$9)),"") | M89: =IF(L40<>"",_xlfn.SINGLE(INDIRECT(L40&"!"&$F$9)),"") | N89: =IF(M40<>"",_xlfn.SINGLE(INDIRECT(M40&"!"&$F$9)),"") | ... U89: =IF(T40<>"",_xlfn.SINGLE(INDIRECT(T40&"!"&$F$9)),"")
D90: Analytique | F90: =IFERROR(AVERAGE(G90:U90),"")
D91: =$D$10 -> Sonde de température | F91: =IFERROR(AVERAGE(G91:U91),"") | G91: =IF(F42<>"",_xlfn.SINGLE(INDIRECT(F42&"!"&$F$10)),"") | H91: =IF(G42<>"",_xlfn.SINGLE(INDIRECT(G42&"!"&$F$10)),"") | I91: =IF(H42<>"",_xlfn.SINGLE(INDIRECT(H42&"!"&$F$10)),"") | J91: =IF(I42<>"",_xlfn.SINGLE(INDIRECT(I42&"!"&$F$10)),"") | K91: =IF(J42<>"",_xlfn.SINGLE(INDIRECT(J42&"!"&$F$10)),"") | L91: =IF(K42<>"",_xlfn.SINGLE(INDIRECT(K42&"!"&$F$10)),"") | M91: =IF(L42<>"",_xlfn.SINGLE(INDIRECT(L42&"!"&$F$10)),"") | N91: =IF(M42<>"",_xlfn.SINGLE(INDIRECT(M42&"!"&$F$10)),"") | ... U91: =IF(T42<>"",_xlfn.SINGLE(INDIRECT(T42&"!"&$F$10)),"")
B92: A7 | C92: S12 | D92: =$D$7 -> Débitmètre en charge | E92: =IFERROR(AVERAGE(F94:F96)*$B$5,"") | F92: =IFERROR(AVERAGE(G92:U92),"") | G92: =IF(F43<>"",_xlfn.SINGLE(INDIRECT(F43&"!"&$F$7)),"") | H92: =IF(G43<>"",_xlfn.SINGLE(INDIRECT(G43&"!"&$F$7)),"") | I92: =IF(H43<>"",_xlfn.SINGLE(INDIRECT(H43&"!"&$F$7)),"") | J92: =IF(I43<>"",_xlfn.SINGLE(INDIRECT(I43&"!"&$F$7)),"") | K92: =IF(J43<>"",_xlfn.SINGLE(INDIRECT(J43&"!"&$F$7)),"") | L92: =IF(K43<>"",_xlfn.SINGLE(INDIRECT(K43&"!"&$F$7)),"") | M92: =IF(L43<>"",_xlfn.SINGLE(INDIRECT(L43&"!"&$F$7)),"") | N92: =IF(M43<>"",_xlfn.SINGLE(INDIRECT(M43&"!"&$F$7)),"") | ... U92: =IF(T43<>"",_xlfn.SINGLE(INDIRECT(T43&"!"&$F$7)),"")
D93: =$D$8 -> Débitmètre gravitaire | F93: =IFERROR(AVERAGE(G93:U93),"") | G93: =IF(F44<>"",_xlfn.SINGLE(INDIRECT(F44&"!"&$F$8)),"") | H93: =IF(G44<>"",_xlfn.SINGLE(INDIRECT(G44&"!"&$F$8)),"") | I93: =IF(H44<>"",_xlfn.SINGLE(INDIRECT(H44&"!"&$F$8)),"") | J93: =IF(I44<>"",_xlfn.SINGLE(INDIRECT(I44&"!"&$F$8)),"") | K93: =IF(J44<>"",_xlfn.SINGLE(INDIRECT(J44&"!"&$F$8)),"") | L93: =IF(K44<>"",_xlfn.SINGLE(INDIRECT(K44&"!"&$F$8)),"") | M93: =IF(L44<>"",_xlfn.SINGLE(INDIRECT(L44&"!"&$F$8)),"") | N93: =IF(M44<>"",_xlfn.SINGLE(INDIRECT(M44&"!"&$F$8)),"") | ... U93: =IF(T44<>"",_xlfn.SINGLE(INDIRECT(T44&"!"&$F$8)),"")
D94: Débitmètre | F94: =IFERROR(AVERAGE(G94:U94),"") | G94: =IF(COUNT(G92:G93)>0,SUM(G92:G93),"") | H94: =IF(COUNT(H92:H93)>0,SUM(H92:H93),"") | I94: =IF(COUNT(I92:I93)>0,SUM(I92:I93),"") | J94: =IF(COUNT(J92:J93)>0,SUM(J92:J93),"") | K94: =IF(COUNT(K92:K93)>0,SUM(K92:K93),"") | L94: =IF(COUNT(L92:L93)>0,SUM(L92:L93),"") | M94: =IF(COUNT(M92:M93)>0,SUM(M92:M93),"") | N94: =IF(COUNT(N92:N93)>0,SUM(N92:N93),"") | ... U94: =IF(COUNT(U92:U93)>0,SUM(U92:U93),"")
D95: =$D$9 -> Préleveur | F95: =IFERROR(AVERAGE(G95:U95),"") | G95: =IF(F45<>"",_xlfn.SINGLE(INDIRECT(F45&"!"&$F$9)),"") | H95: =IF(G45<>"",_xlfn.SINGLE(INDIRECT(G45&"!"&$F$9)),"") | I95: =IF(H45<>"",_xlfn.SINGLE(INDIRECT(H45&"!"&$F$9)),"") | J95: =IF(I45<>"",_xlfn.SINGLE(INDIRECT(I45&"!"&$F$9)),"") | K95: =IF(J45<>"",_xlfn.SINGLE(INDIRECT(J45&"!"&$F$9)),"") | L95: =IF(K45<>"",_xlfn.SINGLE(INDIRECT(K45&"!"&$F$9)),"") | M95: =IF(L45<>"",_xlfn.SINGLE(INDIRECT(L45&"!"&$F$9)),"") | N95: =IF(M45<>"",_xlfn.SINGLE(INDIRECT(M45&"!"&$F$9)),"") | ... U95: =IF(T45<>"",_xlfn.SINGLE(INDIRECT(T45&"!"&$F$9)),"")
D96: Analytique | F96: =IFERROR(AVERAGE(G96:U96),"") | G96: =IF(F51<>"",VLOOKUP(F51,Analytique!$X$3:$AD$33,6,FALSE),"") | H96: =IF(G51<>"",VLOOKUP(G51,Analytique!$X$3:$AD$33,6,FALSE),"") | I96: =IF(H51<>"",VLOOKUP(H51,Analytique!$X$3:$AD$33,6,FALSE),"") | J96: =IF(I51<>"",VLOOKUP(I51,Analytique!$X$3:$AD$33,6,FALSE),"") | K96: =IF(J51<>"",VLOOKUP(J51,Analytique!$X$3:$AD$33,6,FALSE),"") | L96: =IF(K51<>"",VLOOKUP(K51,Analytique!$X$3:$AD$33,6,FALSE),"") | M96: =IF(L51<>"",VLOOKUP(L51,Analytique!$X$3:$AD$33,6,FALSE),"") | N96: =IF(M51<>"",VLOOKUP(M51,Analytique!$X$3:$AD$33,6,FALSE),"") | ... U96: =IF(T51<>"",VLOOKUP(T51,Analytique!$X$3:$AD$33,6,FALSE),"")
D97: =$D$10 -> Sonde de température | F97: =IFERROR(AVERAGE(G97:U97),"") | G97: =IF(F47<>"",_xlfn.SINGLE(INDIRECT(F47&"!"&$F$10)),"") | H97: =IF(G47<>"",_xlfn.SINGLE(INDIRECT(G47&"!"&$F$10)),"") | I97: =IF(H47<>"",_xlfn.SINGLE(INDIRECT(H47&"!"&$F$10)),"") | J97: =IF(I47<>"",_xlfn.SINGLE(INDIRECT(I47&"!"&$F$10)),"") | K97: =IF(J47<>"",_xlfn.SINGLE(INDIRECT(J47&"!"&$F$10)),"") | L97: =IF(K47<>"",_xlfn.SINGLE(INDIRECT(K47&"!"&$F$10)),"") | M97: =IF(L47<>"",_xlfn.SINGLE(INDIRECT(L47&"!"&$F$10)),"") | N97: =IF(M47<>"",_xlfn.SINGLE(INDIRECT(M47&"!"&$F$10)),"") | ... U97: =IF(T47<>"",_xlfn.SINGLE(INDIRECT(T47&"!"&$F$10)),"")
B98: A1 | C98: R1 | D98: =$D$7 -> Débitmètre en charge | E98: =IFERROR(AVERAGE(F100:F102)*$B$5,"") -> 100 | F98: =IFERROR(AVERAGE(G98:U98),"") | G98: =IF(F48<>"",_xlfn.SINGLE(INDIRECT(F48&"!"&$F$7)),"") | H98: =IF(G48<>"",_xlfn.SINGLE(INDIRECT(G48&"!"&$F$7)),"") | I98: =IF(H48<>"",_xlfn.SINGLE(INDIRECT(H48&"!"&$F$7)),"") | J98: =IF(I48<>"",_xlfn.SINGLE(INDIRECT(I48&"!"&$F$7)),"") | K98: =IF(J48<>"",_xlfn.SINGLE(INDIRECT(J48&"!"&$F$7)),"") | L98: =IF(K48<>"",_xlfn.SINGLE(INDIRECT(K48&"!"&$F$7)),"") | M98: =IF(L48<>"",_xlfn.SINGLE(INDIRECT(L48&"!"&$F$7)),"") | N98: =IF(M48<>"",_xlfn.SINGLE(INDIRECT(M48&"!"&$F$7)),"") | ... U98: =IF(T48<>"",_xlfn.SINGLE(INDIRECT(T48&"!"&$F$7)),"")
D99: =$D$8 -> Débitmètre gravitaire | F99: =IFERROR(AVERAGE(G99:U99),"") -> 100 | G99: =IF(F49<>"",_xlfn.SINGLE(INDIRECT(F49&"!"&$F$8)),"") -> 100 | H99: =IF(G49<>"",_xlfn.SINGLE(INDIRECT(G49&"!"&$F$8)),"") | I99: =IF(H49<>"",_xlfn.SINGLE(INDIRECT(H49&"!"&$F$8)),"") | J99: =IF(I49<>"",_xlfn.SINGLE(INDIRECT(I49&"!"&$F$8)),"") | K99: =IF(J49<>"",_xlfn.SINGLE(INDIRECT(J49&"!"&$F$8)),"") | L99: =IF(K49<>"",_xlfn.SINGLE(INDIRECT(K49&"!"&$F$8)),"") | M99: =IF(L49<>"",_xlfn.SINGLE(INDIRECT(L49&"!"&$F$8)),"") | N99: =IF(M49<>"",_xlfn.SINGLE(INDIRECT(M49&"!"&$F$8)),"") | ... U99: =IF(T49<>"",_xlfn.SINGLE(INDIRECT(T49&"!"&$F$8)),"")
D100: Débitmètre | F100: =IFERROR(AVERAGE(G100:U100),"") -> 100 | G100: =IF(COUNT(G98:G99)>0,SUM(G98:G99),"") -> 100 | H100: =IF(COUNT(H98:H99)>0,SUM(H98:H99),"") | I100: =IF(COUNT(I98:I99)>0,SUM(I98:I99),"") | J100: =IF(COUNT(J98:J99)>0,SUM(J98:J99),"") | K100: =IF(COUNT(K98:K99)>0,SUM(K98:K99),"") | L100: =IF(COUNT(L98:L99)>0,SUM(L98:L99),"") | M100: =IF(COUNT(M98:M99)>0,SUM(M98:M99),"") | N100: =IF(COUNT(N98:N99)>0,SUM(N98:N99),"") | ... U100: =IF(COUNT(U98:U99)>0,SUM(U98:U99),"")
D101: =$D$9 -> Préleveur | F101: =IFERROR(AVERAGE(G101:U101),"") | G101: =IF(F50<>"",_xlfn.SINGLE(INDIRECT(F50&"!"&$F$9)),"") | H101: =IF(G50<>"",_xlfn.SINGLE(INDIRECT(G50&"!"&$F$9)),"") | I101: =IF(H50<>"",_xlfn.SINGLE(INDIRECT(H50&"!"&$F$9)),"") | J101: =IF(I50<>"",_xlfn.SINGLE(INDIRECT(I50&"!"&$F$9)),"") | K101: =IF(J50<>"",_xlfn.SINGLE(INDIRECT(J50&"!"&$F$9)),"") | L101: =IF(K50<>"",_xlfn.SINGLE(INDIRECT(K50&"!"&$F$9)),"") | M101: =IF(L50<>"",_xlfn.SINGLE(INDIRECT(L50&"!"&$F$9)),"") | N101: =IF(M50<>"",_xlfn.SINGLE(INDIRECT(M50&"!"&$F$9)),"") | ... U101: =IF(T50<>"",_xlfn.SINGLE(INDIRECT(T50&"!"&$F$9)),"")
D102: Analytique | F102: =IFERROR(AVERAGE(G102:U102),"") | G102: =IF(F57<>"",VLOOKUP(F57,Analytique!$X$3:$AD$33,6,FALSE),"") | H102: =IF(G57<>"",VLOOKUP(G57,Analytique!$X$3:$AD$33,6,FALSE),"") | I102: =IF(H57<>"",VLOOKUP(H57,Analytique!$X$3:$AD$33,6,FALSE),"") | J102: =IF(I57<>"",VLOOKUP(I57,Analytique!$X$3:$AD$33,6,FALSE),"") | K102: =IF(J57<>"",VLOOKUP(J57,Analytique!$X$3:$AD$33,6,FALSE),"") | L102: =IF(K57<>"",VLOOKUP(K57,Analytique!$X$3:$AD$33,6,FALSE),"") | M102: =IF(L57<>"",VLOOKUP(L57,Analytique!$X$3:$AD$33,6,FALSE),"") | N102: =IF(M57<>"",VLOOKUP(M57,Analytique!$X$3:$AD$33,6,FALSE),"") | ... U102: =IF(T57<>"",VLOOKUP(T57,Analytique!$X$3:$AD$33,6,FALSE),"")
D103: =$D$10 -> Sonde de température | F103: =IFERROR(AVERAGE(G103:U103),"") | G103: =IF(F52<>"",_xlfn.SINGLE(INDIRECT(F52&"!"&$F$10)),"") | H103: =IF(G52<>"",_xlfn.SINGLE(INDIRECT(G52&"!"&$F$10)),"") | I103: =IF(H52<>"",_xlfn.SINGLE(INDIRECT(H52&"!"&$F$10)),"") | J103: =IF(I52<>"",_xlfn.SINGLE(INDIRECT(I52&"!"&$F$10)),"") | K103: =IF(J52<>"",_xlfn.SINGLE(INDIRECT(J52&"!"&$F$10)),"") | L103: =IF(K52<>"",_xlfn.SINGLE(INDIRECT(K52&"!"&$F$10)),"") | M103: =IF(L52<>"",_xlfn.SINGLE(INDIRECT(L52&"!"&$F$10)),"") | N103: =IF(M52<>"",_xlfn.SINGLE(INDIRECT(M52&"!"&$F$10)),"") | ... U103: =IF(T52<>"",_xlfn.SINGLE(INDIRECT(T52&"!"&$F$10)),"")
B104: A8 | C104: S19 | D104: =$D$7 -> Débitmètre en charge | E104: =IFERROR(AVERAGE(F106:F108)*$B$5,"") | F104: =IFERROR(AVERAGE(G104:U104),"") | G104: =IF(F53<>"",_xlfn.SINGLE(INDIRECT(F53&"!"&$F$7)),"") | H104: =IF(G53<>"",_xlfn.SINGLE(INDIRECT(G53&"!"&$F$7)),"") | I104: =IF(H53<>"",_xlfn.SINGLE(INDIRECT(H53&"!"&$F$7)),"") | J104: =IF(I53<>"",_xlfn.SINGLE(INDIRECT(I53&"!"&$F$7)),"") | K104: =IF(J53<>"",_xlfn.SINGLE(INDIRECT(J53&"!"&$F$7)),"") | L104: =IF(K53<>"",_xlfn.SINGLE(INDIRECT(K53&"!"&$F$7)),"") | M104: =IF(L53<>"",_xlfn.SINGLE(INDIRECT(L53&"!"&$F$7)),"") | N104: =IF(M53<>"",_xlfn.SINGLE(INDIRECT(M53&"!"&$F$7)),"") | ... U104: =IF(T53<>"",_xlfn.SINGLE(INDIRECT(T53&"!"&$F$7)),"")
D105: =$D$8 -> Débitmètre gravitaire | F105: =IFERROR(AVERAGE(G105:U105),"") | G105: =IF(F54<>"",_xlfn.SINGLE(INDIRECT(F54&"!"&$F$8)),"") | H105: =IF(G54<>"",_xlfn.SINGLE(INDIRECT(G54&"!"&$F$8)),"") | I105: =IF(H54<>"",_xlfn.SINGLE(INDIRECT(H54&"!"&$F$8)),"") | J105: =IF(I54<>"",_xlfn.SINGLE(INDIRECT(I54&"!"&$F$8)),"") | K105: =IF(J54<>"",_xlfn.SINGLE(INDIRECT(J54&"!"&$F$8)),"") | L105: =IF(K54<>"",_xlfn.SINGLE(INDIRECT(K54&"!"&$F$8)),"") | M105: =IF(L54<>"",_xlfn.SINGLE(INDIRECT(L54&"!"&$F$8)),"") | N105: =IF(M54<>"",_xlfn.SINGLE(INDIRECT(M54&"!"&$F$8)),"") | ... U105: =IF(T54<>"",_xlfn.SINGLE(INDIRECT(T54&"!"&$F$8)),"")
...

Sheet Equipements
A1: Lignes SCL | B1: =Descriptif!$AD$2 -> 13 | C1: =Descriptif!$AF$2 -> 14 | D1: Lignes STEU | E1: =Descriptif!$AD$3 -> 33 | F1: =Descriptif!$AF$3 -> 40
A2: Pluvio SCL | B2: =Descriptif!$AH$2 -> 21 | C2: =Descriptif!$AI$2 -> 22 | D2: Puvio STEU | E2: =Descriptif!$AH$3 -> 47 | F2: =Descriptif!$AI$3 -> 48
A3: Type Equipement | B3: Type
B4: cellule typeE | C4: cellule score global | D4: cellule eval global | E4: cellule commentaire score | F4: cellule commentaire
A5: Pluviomètre | B5: D24 | C5: P32 | D5: N32 | E5: D32 | F5: C36
A6: =PARAM!$C4 -> Débitmètre en charge | B6: D32 | C6: P45 | D6: N45 | E6: D45 | F6: C49
A7: =PARAM!$C5 -> Débitmètre gravitaire | B7: D40 | C7: P53 | D7: N53 | E7: D53 | F7: C57
A8: =PARAM!$C6 -> Préleveur | B8: D37 | C8: P50 | D8: N50 | E8: D50 | F8: C54
A9: =PARAM!$C7 -> Sonde de température | B9: D26 | C9: P33 | D9: N33 | E9: D33 | F9: C37
B12: =$B$2+A42-1 -> 47
A13: Liste équipements
A14: Ligne | C14: Colonnes | G14: Données équipement | L14: TypeE | M14: Score | O14: Evaluation | Q14: Commentaire eval | S14: Commentaire equipement | U14: Critères
A15: n° | B15: utilisable | C15: F | D15: I | E15: M | F15: O | G15: Feuille | H15: loc | I15: type | J15: typeE | K15: code | L15: src | M15: src | N15: val | O15: src | P15: val | Q15: src | R15: val | S15: src | T15: val | U15: col | V15: ligne | W15: 1 | X15: 2 | Y15: 3 | Z15: 4 | AA15: 5 | AB15: 6 | AC15: 7 | AD15: 8 | AE15: 9 | AF15: 10
A16: 1 | B16: =IF(OR(AND(($B$1+A16-1)>=$B$1,($B$1+A16-1)<$C$1),AND(($B$1+A16-1)>=$E$1,($B$1+A16-1)<$F$1),AND(($B$1+A16-1)>=$B$2,($B$1+A16-1)<$C$2),AND(($B$1+A16-1)>=$E$2,($B$1+A16-1)<$F$2)),TRUE,FALSE) -> TRUE | C16: =IF( AND( $B16, OR( _xlfn.SINGLE(INDIRECT("Descriptif!$M"&($B$1+$A16-1)))="Préleveur", LEFT(_xlfn.SINGLE(INDIRECT("Descriptif!$M"&($B$1+$A16-1))),5)="Sonde", LEFT(_xlfn.SINGLE(INDIRECT("Descriptif!$M"&($B$1+$A16-1))),10)="Débitmètre", LEFT(_xlfn.SINGLE(INDIRECT("Descriptif!$F"&($B$1+$A16-1))),6)="PLUVIO" ) ), _xlfn.SINGLE(INDIRECT("Descriptif!$"&C$15&($B$1 +$A16 -1))), "" ) -> A1_DO1_Q_Grav | D16: =IF( AND( $B16, OR( _xlfn.SINGLE(INDIRECT("Descriptif!$M"&($B$1+$A16-1)))="Préleveur", LEFT(_xlfn.SINGLE(INDIRECT("Descriptif!$M"&($B$1+$A16-1))),5)="Sonde", LEFT(_xlfn.SINGLE(INDIRECT("Descriptif!$M"&($B$1+$A16-1))),10)="Débitmètre", LEFT(_xlfn.SINGLE(INDIRECT("Descriptif!$F"&($B$1+$A16-1))),6)="PLUVIO" ) ), IF( LEFT(_xlfn.SINGLE(INDIRECT("Descriptif!$F"&($B$1+$A16-1))),11)="PLUVIO_STEU", "A3", IF( LEFT(_xlfn.SINGLE(INDIRECT("Descriptif!$F"&($B$1+$A16-1))),10)="PLUVIO_SCL", "A1", _xlfn.SINGLE(INDIRECT("Descriptif!$"&D$15&($B$1 +$A16 -1)) )) ), "" ) -> A1 | E16: =IF( AND( $B16, OR( _xlfn.SINGLE(INDIRECT("Descriptif!$M"&($B$1+$A16-1)))="Préleveur", LEFT(_xlfn.SINGLE(INDIRECT("Descriptif!$M"&($B$1+$A16-1))),5)="Sonde", LEFT(_xlfn.SINGLE(INDIRECT("Descriptif!$M"&($B$1+$A16-1))),10)="Débitmètre", LEFT(_xlfn.SINGLE(INDIRECT("Descriptif!$F"&($B$1+$A16-1))),6)="PLUVIO" ) ), IF(LEFT(_xlfn.SINGLE(INDIRECT("Descriptif!$F"&($B$1+$A16-1))),6)="PLUVIO","Pluviomètre",_xlfn.SINGLE(INDIRECT("Descriptif!$"&E$15&($B$1 +$A16 -1)))), "" ) -> Débitmètre gravitaire | F16: =IF( AND( $B16, OR( _xlfn.SINGLE(INDIRECT("Descriptif!$M"&($B$1+$A16-1)))="Préleveur", LEFT(_xlfn.SINGLE(INDIRECT("Descriptif!$M"&($B$1+$A16-1))),5)="Sonde", LEFT(_xlfn.SINGLE(INDIRECT("Descriptif!$M"&($B$1+$A16-1))),10)="Débitmètre", LEFT(_xlfn.SINGLE(INDIRECT("Descriptif!$F"&($B$1+$A16-1))),6)="PLUVIO" ) ), IF(LEFT(_xlfn.SINGLE(INDIRECT("Descriptif!$F"&($B$1+$A16-1))),6)="PLUVIO","Pluviomètre",_xlfn.SINGLE(INDIRECT("Descriptif!$"&F$15&($B$1 +$A16 -1)))), "" ) -> Seuil | G16: {=IFERROR(INDEX($C$16:$C$116,SMALL(IF($C$16:$C$116<>"",ROW($C$16:$C$116)-ROW($C$16)+1),ROW(A1))),"")} -> A1_DO1_Q_Grav | H16: {=IFERROR(INDEX($D$16:$D$116,SMALL(IF($D$16:$D$116<>"",ROW($D$16:$D$116)-ROW($D$16)+1),ROW(A1))),"")} -> A1 | I16: {=IFERROR(INDEX($E$16:$E$116,SMALL(IF($E$16:$E$116<>"",ROW($E$16:$E$116)-ROW($E$16)+1),ROW(A1))),"")} -> Débitmètre gravitaire | J16: {=IFERROR(INDEX($F$16:$F$116,SMALL(IF($F$16:$F$116<>"",ROW($F$16:$F$116)-ROW($F$16)+1),ROW(A1))),"")} -> Seuil | K16: =G16 -> A1_DO1_Q_Grav | L16: =IF($I16<>"",VLOOKUP($I16,$A$5:$F$9,2,FALSE),"") -> D40 | M16: =IF($I16<>"",VLOOKUP($I16,$A$5:$F$9,3,FALSE),"") -> P53 | N16: =IF($I16<>"",IF(_xlfn.SINGLE(INDIRECT($G16&"!"&$M16))<>"",_xlfn.SINGLE(INDIRECT($G16&"!"&$M16)),""),"") -> 100 | O16: =IF($I16<>"",VLOOKUP($I16,$A$5:$F$9,4,FALSE),"") -> N53 | P16: =IF($I16<>"",IF(_xlfn.SINGLE(INDIRECT($G16&"!"&$O16))<>"",_xlfn.SINGLE(INDIRECT($G16&"!"&$O16)),""),"") -> Validé | Q16: =IF($I16<>"",VLOOKUP($I16,$A$5:$F$9,5,FALSE),"") -> D53 | R16: =IF($I16<>"",IF(_xlfn.SINGLE(INDIRECT($G16&"!"&$Q16))<>"",_xlfn.SINGLE(INDIRECT($G16&"!"&$Q16)),""),"") -> aaaaaaaa | S16: =IF($I16<>"",VLOOKUP($I16,$A$5:$F$9,6,FALSE),"") -> C57 | T16: =IF($I16<>"",IF(_xlfn.SINGLE(INDIRECT($G16&"!"&$S16))<>"",_xlfn.SINGLE(INDIRECT($G16&"!"&$S16)),""),"") | U16: =LEFT($O16,1) -> N | V16: =RIGHT($L16,2) -> 40 | W16: =IF($G16<>"",IF(_xlfn.SINGLE(INDIRECT($G16&"!"&$U16&($V16+W$15+1)))<>"",_xlfn.SINGLE(INDIRECT($G16&"!"&$U16&($V16+W$15+1))),""),"") -> Validé | X16: =IF($G16<>"",IF(_xlfn.SINGLE(INDIRECT($G16&"!"&$U16&($V16+X$15+1)))<>"",_xlfn.SINGLE(INDIRECT($G16&"!"&$U16&($V16+X$15+1))),""),"") -> Validé | Y16: =IF($G16<>"",IF(_xlfn.SINGLE(INDIRECT($G16&"!"&$U16&($V16+Y$15+1)))<>"",_xlfn.SINGLE(INDIRECT($G16&"!"&$U16&($V16+Y$15+1))),""),"") -> Validé | Z16: =IF($G16<>"",IF(_xlfn.SINGLE(INDIRECT($G16&"!"&$U16&($V16+Z$15+1)))<>"",_xlfn.SINGLE(INDIRECT($G16&"!"&$U16&($V16+Z$15+1))),""),"") -> Validé | AA16: =IF($G16<>"",IF(_xlfn.SINGLE(INDIRECT($G16&"!"&$U16&($V16+AA$15+1)))<>"",_xlfn.SINGLE(INDIRECT($G16&"!"&$U16&($V16+AA$15+1))),""),"") -> Validé | AB16: =IF($G16<>"",IF(_xlfn.SINGLE(INDIRECT($G16&"!"&$U16&($V16+AB$15+1)))<>"",_xlfn.SINGLE(INDIRECT($G16&"!"&$U16&($V16+AB$15+1))),""),"") -> Validé | AC16: =IF($G16<>"",IF(_xlfn.SINGLE(INDIRECT($G16&"!"&$U16&($V16+AC$15+1)))<>"",_xlfn.SINGLE(INDIRECT($G16&"!"&$U16&($V16+AC$15+1))),""),"") -> Validé | AD16: =IF($G16<>"",IF(_xlfn.SINGLE(INDIRECT($G16&"!"&$U16&($V16+AD$15+1)))<>"",_xlfn.SINGLE(INDIRECT($G16&"!"&$U16&($V16+AD$15+1))),""),"") -> Validé | ... AF16: =IF($G16<>"",IF(_xlfn.SINGLE(INDIRECT($G16&"!"&$U16&($V16+AF$15+1)))<>"",_xlfn.SINGLE(INDIRECT($G16&"!"&$U16&($V16+AF$15+1))),""),"") -> Oui
A17: 2 | B17: =IF(OR(AND(($B$1+A17-1)>=$B$1,($B$1+A17-1)<$C$1),AND(($B$1+A17-1)>=$E$1,($B$1+A17-1)<$F$1),AND(($B$1+A17-1)>=$B$2,($B$1+A17-1)<$C$2),AND(($B$1+A17-1)>=$E$2,($B$1+A17-1)<$F$2)),TRUE,FALSE) -> FALSE | C17: =IF( AND( $B17, OR( _xlfn.SINGLE(INDIRECT("Descriptif!$M"&($B$1+$A17-1)))="Préleveur", LEFT(_xlfn.SINGLE(INDIRECT("Descriptif!$M"&($B$1+$A17-1))),5)="Sonde", LEFT(_xlfn.SINGLE(INDIRECT("Descriptif!$M"&($B$1+$A17-1))),10)="Débitmètre", LEFT(_xlfn.SINGLE(INDIRECT("Descriptif!$F"&($B$1+$A17-1))),6)="PLUVIO" ) ), _xlfn.SINGLE(INDIRECT("Descriptif!$"&C$15&($B$1 +$A17 -1))), "" ) | D17: =IF( AND( $B17, OR( _xlfn.SINGLE(INDIRECT("Descriptif!$M"&($B$1+$A17-1)))="Préleveur", LEFT(_xlfn.SINGLE(INDIRECT("Descriptif!$M"&($B$1+$A17-1))),5)="Sonde", LEFT(_xlfn.SINGLE(INDIRECT("Descriptif!$M"&($B$1+$A17-1))),10)="Débitmètre", LEFT(_xlfn.SINGLE(INDIRECT("Descriptif!$F"&($B$1+$A17-1))),6)="PLUVIO" ) ), IF( LEFT(_xlfn.SINGLE(INDIRECT("Descriptif!$F"&($B$1+$A17-1))),11)="PLUVIO_STEU", "A3", IF( LEFT(_xlfn.SINGLE(INDIRECT("Descriptif!$F"&($B$1+$A17-1))),10)="PLUVIO_SCL", "A1", _xlfn.SINGLE(INDIRECT("Descriptif!$"&D$15&($B$1 +$A17 -1)) )) ), "" ) | E17: =IF( AND( $B17, OR( _xlfn.SINGLE(INDIRECT("Descriptif!$M"&($B$1+$A17-1)))="Préleveur", LEFT(_xlfn.SINGLE(INDIRECT("Descriptif!$M"&($B$1+$A17-1))),5)="Sonde", LEFT(_xlfn.SINGLE(INDIRECT("Descriptif!$M"&($B$1+$A17-1))),10)="Débitmètre", LEFT(_xlfn.SINGLE(INDIRECT("Descriptif!$F"&($B$1+$A17-1))),6)="PLUVIO" ) ), IF(LEFT(_xlfn.SINGLE(INDIRECT("Descriptif!$F"&($B$1+$A17-1))),6)="PLUVIO","Pluviomètre",_xlfn.SINGLE(INDIRECT("Descriptif!$"&E$15&($B$1 +$A17 -1)))), "" ) | F17: =IF( AND( $B17, OR( _xlfn.SINGLE(INDIRECT("Descriptif!$M"&($B$1+$A17-1)))="Préleveur", LEFT(_xlfn.SINGLE(INDIRECT("Descriptif!$M"&($B$1+$A17-1))),5)="Sonde", LEFT(_xlfn.SINGLE(INDIRECT("Descriptif!$M"&($B$1+$A17-1))),10)="Débitmètre", LEFT(_xlfn.SINGLE(INDIRECT("Descriptif!$F"&($B$1+$A17-1))),6)="PLUVIO" ) ), IF(LEFT(_xlfn.SINGLE(INDIRECT("Descriptif!$F"&($B$1+$A17-1))),6)="PLUVIO","Pluviomètre",_xlfn.SINGLE(INDIRECT("Descriptif!$"&F$15&($B$1 +$A17 -1)))), "" ) | G17: {=IFERROR(INDEX($C$16:$C$116,SMALL(IF($C$16:$C$116<>"",ROW($C$16:$C$116)-ROW($C$16)+1),ROW(A2))),"")} -> PLUVIO_SCL_ooo | H17: {=IFERROR(INDEX($D$16:$D$116,SMALL(IF($D$16:$D$116<>"",ROW($D$16:$D$116)-ROW($D$16)+1),ROW(A2))),"")} -> A1 | I17: {=IFERROR(INDEX($E$16:$E$116,SMALL(IF($E$16:$E$116<>"",ROW($E$16:$E$116)-ROW($E$16)+1),ROW(A2))),"")} -> Pluviomètre | J17: {=IFERROR(INDEX($F$16:$F$116,SMALL(IF($F$16:$F$116<>"",ROW($F$16:$F$116)-ROW($F$16)+1),ROW(A2))),"")} -> Pluviomètre | K17: =G17 -> PLUVIO_SCL_ooo | L17: =IF($I17<>"",VLOOKUP($I17,$A$5:$F$9,2,FALSE),"") -> D24 | M17: =IF($I17<>"",VLOOKUP($I17,$A$5:$F$9,3,FALSE),"") -> P32 | N17: =IF($I17<>"",IF(_xlfn.SINGLE(INDIRECT($G17&"!"&$M17))<>"",_xlfn.SINGLE(INDIRECT($G17&"!"&$M17)),""),"") -> 0 | O17: =IF($I17<>"",VLOOKUP($I17,$A$5:$F$9,4,FALSE),"") -> N32 | P17: =IF($I17<>"",IF(_xlfn.SINGLE(INDIRECT($G17&"!"&$O17))<>"",_xlfn.SINGLE(INDIRECT($G17&"!"&$O17)),""),"") | Q17: =IF($I17<>"",VLOOKUP($I17,$A$5:$F$9,5,FALSE),"") -> D32 | R17: =IF($I17<>"",IF(_xlfn.SINGLE(INDIRECT($G17&"!"&$Q17))<>"",_xlfn.SINGLE(INDIRECT($G17&"!"&$Q17)),""),"") | S17: =IF($I17<>"",VLOOKUP($I17,$A$5:$F$9,6,FALSE),"") -> C36 | T17: =IF($I17<>"",IF(_xlfn.SINGLE(INDIRECT($G17&"!"&$S17))<>"",_xlfn.SINGLE(INDIRECT($G17&"!"&$S17)),""),"") | U17: =LEFT($O17,1) -> N | V17: =RIGHT($L17,2) -> 24 | W17: =IF($G17<>"",IF(_xlfn.SINGLE(INDIRECT($G17&"!"&$U17&($V17+W$15+1)))<>"",_xlfn.SINGLE(INDIRECT($G17&"!"&$U17&($V17+W$15+1))),""),"") | X17: =IF($G17<>"",IF(_xlfn.SINGLE(INDIRECT($G17&"!"&$U17&($V17+X$15+1)))<>"",_xlfn.SINGLE(INDIRECT($G17&"!"&$U17&($V17+X$15+1))),""),"") -> Non contrôlé | Y17: =IF($G17<>"",IF(_xlfn.SINGLE(INDIRECT($G17&"!"&$U17&($V17+Y$15+1)))<>"",_xlfn.SINGLE(INDIRECT($G17&"!"&$U17&($V17+Y$15+1))),""),"") | Z17: =IF($G17<>"",IF(_xlfn.SINGLE(INDIRECT($G17&"!"&$U17&($V17+Z$15+1)))<>"",_xlfn.SINGLE(INDIRECT($G17&"!"&$U17&($V17+Z$15+1))),""),"") | AA17: =IF($G17<>"",IF(_xlfn.SINGLE(INDIRECT($G17&"!"&$U17&($V17+AA$15+1)))<>"",_xlfn.SINGLE(INDIRECT($G17&"!"&$U17&($V17+AA$15+1))),""),"") -> Non contrôlé | AB17: =IF($G17<>"",IF(_xlfn.SINGLE(INDIRECT($G17&"!"&$U17&($V17+AB$15+1)))<>"",_xlfn.SINGLE(INDIRECT($G17&"!"&$U17&($V17+AB$15+1))),""),"") -> Evaluation finale | AC17: =IF($G17<>"",IF(_xlfn.SINGLE(INDIRECT($G17&"!"&$U17&($V17+AC$15+1)))<>"",_xlfn.SINGLE(INDIRECT($G17&"!"&$U17&($V17+AC$15+1))),""),"") | AD17: =IF($G17<>"",IF(_xlfn.SINGLE(INDIRECT($G17&"!"&$U17&($V17+AD$15+1)))<>"",_xlfn.SINGLE(INDIRECT($G17&"!"&$U17&($V17+AD$15+1))),""),"") | ... AF17: =IF($G17<>"",IF(_xlfn.SINGLE(INDIRECT($G17&"!"&$U17&($V17+AF$15+1)))<>"",_xlfn.SINGLE(INDIRECT($G17&"!"&$U17&($V17+AF$15+1))),""),"")
A18: 3 | B18: =IF(OR(AND(($B$1+A18-1)>=$B$1,($B$1+A18-1)<$C$1),AND(($B$1+A18-1)>=$E$1,($B$1+A18-1)<$F$1),AND(($B$1+A18-1)>=$B$2,($B$1+A18-1)<$C$2),AND(($B$1+A18-1)>=$E$2,($B$1+A18-1)<$F$2)),TRUE,FALSE) -> FALSE | C18: =IF( AND( $B18, OR( _xlfn.SINGLE(INDIRECT("Descriptif!$M"&($B$1+$A18-1)))="Préleveur", LEFT(_xlfn.SINGLE(INDIRECT("Descriptif!$M"&($B$1+$A18-1))),5)="Sonde", LEFT(_xlfn.SINGLE(INDIRECT("Descriptif!$M"&($B$1+$A18-1))),10)="Débitmètre", LEFT(_xlfn.SINGLE(INDIRECT("Descriptif!$F"&($B$1+$A18-1))),6)="PLUVIO" ) ), _xlfn.SINGLE(INDIRECT("Descriptif!$"&C$15&($B$1 +$A18 -1))), "" ) | D18: =IF( AND( $B18, OR( _xlfn.SINGLE(INDIRECT("Descriptif!$M"&($B$1+$A18-1)))="Préleveur", LEFT(_xlfn.SINGLE(INDIRECT("Descriptif!$M"&($B$1+$A18-1))),5)="Sonde", LEFT(_xlfn.SINGLE(INDIRECT("Descriptif!$M"&($B$1+$A18-1))),10)="Débitmètre", LEFT(_xlfn.SINGLE(INDIRECT("Descriptif!$F"&($B$1+$A18-1))),6)="PLUVIO" ) ), IF( LEFT(_xlfn.SINGLE(INDIRECT("Descriptif!$F"&($B$1+$A18-1))),11)="PLUVIO_STEU", "A3", IF( LEFT(_xlfn.SINGLE(INDIRECT("Descriptif!$F"&($B$1+$A18-1))),10)="PLUVIO_SCL", "A1", _xlfn.SINGLE(INDIRECT("Descriptif!$"&D$15&($B$1 +$A18 -1)) )) ), "" ) | E18: =IF( AND( $B18, OR( _xlfn.SINGLE(INDIRECT("Descriptif!$M"&($B$1+$A18-1)))="Préleveur", LEFT(_xlfn.SINGLE(INDIRECT("Descriptif!$M"&($B$1+$A18-1))),5)="Sonde", LEFT(_xlfn.SINGLE(INDIRECT("Descriptif!$M"&($B$1+$A18-1))),10)="Débitmètre", LEFT(_xlfn.SINGLE(INDIRECT("Descriptif!$F"&($B$1+$A18-1))),6)="PLUVIO" ) ), IF(LEFT(_xlfn.SINGLE(INDIRECT("Descriptif!$F"&($B$1+$A18-1))),6)="PLUVIO","Pluviomètre",_xlfn.SINGLE(INDIRECT("Descriptif!$"&E$15&($B$1 +$A18 -1)))), "" ) | F18: =IF( AND( $B18, OR( _xlfn.SINGLE(INDIRECT("Descriptif!$M"&($B$1+$A18-1)))="Préleveur", LEFT(_xlfn.SINGLE(INDIRECT("Descriptif!$M"&($B$1+$A18-1))),5)="Sonde", LEFT(_xlfn.SINGLE(INDIRECT("Descriptif!$M"&($B$1+$A18-1))),10)="Débitmètre", LEFT(_xlfn.SINGLE(INDIRECT("Descriptif!$F"&($B$1+$A18-1))),6)="PLUVIO" ) ), IF(LEFT(_xlfn.SINGLE(INDIRECT("Descriptif!$F"&($B$1+$A18-1))),6)="PLUVIO","Pluviomètre",_xlfn.SINGLE(INDIRECT("Descriptif!$"&F$15&($B$1 +$A18 -1)))), "" ) | G18: {=IFERROR(INDEX($C$16:$C$116,SMALL(IF($C$16:$C$116<>"",ROW($C$16:$C$116)-ROW($C$16)+1),ROW(A3))),"")} -> A2_P100_Q_Grav | H18: {=IFERROR(INDEX($D$16:$D$116,SMALL(IF($D$16:$D$116<>"",ROW($D$16:$D$116)-ROW($D$16)+1),ROW(A3))),"")} -> A2 | I18: {=IFERROR(INDEX($E$16:$E$116,SMALL(IF($E$16:$E$116<>"",ROW($E$16:$E$116)-ROW($E$16)+1),ROW(A3))),"")} -> Débitmètre gravitaire | J18: {=IFERROR(INDEX($F$16:$F$116,SMALL(IF($F$16:$F$116<>"",ROW($F$16:$F$116)-ROW($F$16)+1),ROW(A3))),"")} -> Hauteur/Vitesse | K18: =G18 -> A2_P100_Q_Grav | L18: =IF($I18<>"",VLOOKUP($I18,$A$5:$F$9,2,FALSE),"") -> D40 | M18: =IF($I18<>"",VLOOKUP($I18,$A$5:$F$9,3,FALSE),"") -> P53 | N18: =IF($I18<>"",IF(_xlfn.SINGLE(INDIRECT($G18&"!"&$M18))<>"",_xlfn.SINGLE(INDIRECT($G18&"!"&$M18)),""),"") -> 80 | O18: =IF($I18<>"",VLOOKUP($I18,$A$5:$F$9,4,FALSE),"") -> N53 | P18: =IF($I18<>"",IF(_xlfn.SINGLE(INDIRECT($G18&"!"&$O18))<>"",_xlfn.SINGLE(INDIRECT($G18&"!"&$O18)),""),"") -> Validé avec réserve | Q18: =IF($I18<>"",VLOOKUP($I18,$A$5:$F$9,5,FALSE),"") -> D53 | R18: =IF($I18<>"",IF(_xlfn.SINGLE(INDIRECT($G18&"!"&$Q18))<>"",_xlfn.SINGLE(INDIRECT($G18&"!"&$Q18)),""),"") | S18: =IF($I18<>"",VLOOKUP($I18,$A$5:$F$9,6,FALSE),"") -> C57 | T18: =IF($I18<>"",IF(_xlfn.SINGLE(INDIRECT($G18&"!"&$S18))<>"",_xlfn.SINGLE(INDIRECT($G18&"!"&$S18)),""),"") -> En l'absence | U18: =LEFT($O18,1) -> N | V18: =RIGHT($L18,2) -> 40 | W18: =IF($G18<>"",IF(_xlfn.SINGLE(INDIRECT($G18&"!"&$U18&($V18+W$15+1)))<>"",_xlfn.SINGLE(INDIRECT($G18&"!"&$U18&($V18+W$15+1))),""),"") -> Validé | X18: =IF($G18<>"",IF(_xlfn.SINGLE(INDIRECT($G18&"!"&$U18&($V18+X$15+1)))<>"",_xlfn.SINGLE(INDIRECT($G18&"!"&$U18&($V18+X$15+1))),""),"") -> Validé | Y18: =IF($G18<>"",IF(_xlfn.SINGLE(INDIRECT($G18&"!"&$U18&($V18+Y$15+1)))<>"",_xlfn.SINGLE(INDIRECT($G18&"!"&$U18&($V18+Y$15+1))),""),"") -> Validé | Z18: =IF($G18<>"",IF(_xlfn.SINGLE(INDIRECT($G18&"!"&$U18&($V18+Z$15+1)))<>"",_xlfn.SINGLE(INDIRECT($G18&"!"&$U18&($V18+Z$15+1))),""),"") -> Validé | AA18: =IF($G18<>"",IF(_xlfn.SINGLE(INDIRECT($G18&"!"&$U18&($V18+AA$15+1)))<>"",_xlfn.SINGLE(INDIRECT($G18&"!"&$U18&($V18+AA$15+1))),""),"") -> Validé | AB18: =IF($G18<>"",IF(_xlfn.SINGLE(INDIRECT($G18&"!"&$U18&($V18+AB$15+1)))<>"",_xlfn.SINGLE(INDIRECT($G18&"!"&$U18&($V18+AB$15+1))),""),"") -> Validé | AC18: =IF($G18<>"",IF(_xlfn.SINGLE(INDIRECT($G18&"!"&$U18&($V18+AC$15+1)))<>"",_xlfn.SINGLE(INDIRECT($G18&"!"&$U18&($V18+AC$15+1))),""),"") -> Non contrôlé | AD18: =IF($G18<>"",IF(_xlfn.SINGLE(INDIRECT($G18&"!"&$U18&($V18+AD$15+1)))<>"",_xlfn.SINGLE(INDIRECT($G18&"!"&$U18&($V18+AD$15+1))),""),"") -> Non contrôlé | ... AF18: =IF($G18<>"",IF(_xlfn.SINGLE(INDIRECT($G18&"!"&$U18&($V18+AF$15+1)))<>"",_xlfn.SINGLE(INDIRECT($G18&"!"&$U18&($V18+AF$15+1))),""),"") -> Oui
A19: 4 | B19: =IF(OR(AND(($B$1+A19-1)>=$B$1,($B$1+A19-1)<$C$1),AND(($B$1+A19-1)>=$E$1,($B$1+A19-1)<$F$1),AND(($B$1+A19-1)>=$B$2,($B$1+A19-1)<$C$2),AND(($B$1+A19-1)>=$E$2,($B$1+A19-1)<$F$2)),TRUE,FALSE) -> FALSE | C19: =IF( AND( $B19, OR( _xlfn.SINGLE(INDIRECT("Descriptif!$M"&($B$1+$A19-1)))="Préleveur", LEFT(_xlfn.SINGLE(INDIRECT("Descriptif!$M"&($B$1+$A19-1))),5)="Sonde", LEFT(_xlfn.SINGLE(INDIRECT("Descriptif!$M"&($B$1+$A19-1))),10)="Débitmètre", LEFT(_xlfn.SINGLE(INDIRECT("Descriptif!$F"&($B$1+$A19-1))),6)="PLUVIO" ) ), _xlfn.SINGLE(INDIRECT("Descriptif!$"&C$15&($B$1 +$A19 -1))), "" ) | D19: =IF( AND( $B19, OR( _xlfn.SINGLE(INDIRECT("Descriptif!$M"&($B$1+$A19-1)))="Préleveur", LEFT(_xlfn.SINGLE(INDIRECT("Descriptif!$M"&($B$1+$A19-1))),5)="Sonde", LEFT(_xlfn.SINGLE(INDIRECT("Descriptif!$M"&($B$1+$A19-1))),10)="Débitmètre", LEFT(_xlfn.SINGLE(INDIRECT("Descriptif!$F"&($B$1+$A19-1))),6)="PLUVIO" ) ), IF( LEFT(_xlfn.SINGLE(INDIRECT("Descriptif!$F"&($B$1+$A19-1))),11)="PLUVIO_STEU", "A3", IF( LEFT(_xlfn.SINGLE(INDIRECT("Descriptif!$F"&($B$1+$A19-1))),10)="PLUVIO_SCL", "A1", _xlfn.SINGLE(INDIRECT("Descriptif!$"&D$15&($B$1 +$A19 -1)) )) ), "" ) | E19: =IF( AND( $B19, OR( _xlfn.SINGLE(INDIRECT("Descriptif!$M"&($B$1+$A19-1)))="Préleveur", LEFT(_xlfn.SINGLE(INDIRECT("Descriptif!$M"&($B$1+$A19-1))),5)="Sonde", LEFT(_xlfn.SINGLE(INDIRECT("Descriptif!$M"&($B$1+$A19-1))),10)="Débitmètre", LEFT(_xlfn.SINGLE(INDIRECT("Descriptif!$F"&($B$1+$A19-1))),6)="PLUVIO" ) ), IF(LEFT(_xlfn.SINGLE(INDIRECT("Descriptif!$F"&($B$1+$A19-1))),6)="PLUVIO","Pluviomètre",_xlfn.SINGLE(INDIRECT("Descriptif!$"&E$15&($B$1 +$A19 -1)))), "" ) | F19: =IF( AND( $B19, OR( _xlfn.SINGLE(INDIRECT("Descriptif!$M"&($B$1+$A19-1)))="Préleveur", LEFT(_xlfn.SINGLE(INDIRECT("Descriptif!$M"&($B$1+$A19-1))),5)="Sonde", LEFT(_xlfn.SINGLE(INDIRECT("Descriptif!$M"&($B$1+$A19-1))),10)="Débitmètre", LEFT(_xlfn.SINGLE(INDIRECT("Descriptif!$F"&($B$1+$A19-1))),6)="PLUVIO" ) ), IF(LEFT(_xlfn.SINGLE(INDIRECT("Descriptif!$F"&($B$1+$A19-1))),6)="PLUVIO","Pluviomètre",_xlfn.SINGLE(INDIRECT("Descriptif!$"&F$15&($B$1 +$A19 -1)))), "" ) | G19: {=IFERROR(INDEX($C$16:$C$116,SMALL(IF($C$16:$C$116<>"",ROW($C$16:$C$116)-ROW($C$16)+1),ROW(A4))),"")} -> A3_P102_Q_DEM | H19: {=IFERROR(INDEX($D$16:$D$116,SMALL(IF($D$16:$D$116<>"",ROW($D$16:$D$116)-ROW($D$16)+1),ROW(A4))),"")} -> A3 | I19: {=IFERROR(INDEX($E$16:$E$116,SMALL(IF($E$16:$E$116<>"",ROW($E$16:$E$116)-ROW($E$16)+1),ROW(A4))),"")} -> Débitmètre en charge | J19: {=IFERROR(INDEX($F$16:$F$116,SMALL(IF($F$16:$F$116<>"",ROW($F$16:$F$116)-ROW($F$16)+1),ROW(A4))),"")} -> Débitmètre électromagnétique (eau) | K19: =G19 -> A3_P102_Q_DEM | L19: =IF($I19<>"",VLOOKUP($I19,$A$5:$F$9,2,FALSE),"") -> D32 | M19: =IF($I19<>"",VLOOKUP($I19,$A$5:$F$9,3,FALSE),"") -> P45 | N19: =IF($I19<>"",IF(_xlfn.SINGLE(INDIRECT($G19&"!"&$M19))<>"",_xlfn.SINGLE(INDIRECT($G19&"!"&$M19)),""),"") -> 60 | O19: =IF($I19<>"",VLOOKUP($I19,$A$5:$F$9,4,FALSE),"") -> N45 | P19: =IF($I19<>"",IF(_xlfn.SINGLE(INDIRECT($G19&"!"&$O19))<>"",_xlfn.SINGLE(INDIRECT($G19&"!"&$O19)),""),"") -> Non Validé | Q19: =IF($I19<>"",VLOOKUP($I19,$A$5:$F$9,5,FALSE),"") -> D45 | R19: =IF($I19<>"",IF(_xlfn.SINGLE(INDIRECT($G19&"!"&$Q19))<>"",_xlfn.SINGLE(INDIRECT($G19&"!"&$Q19)),""),"") -> Le dispositif en place | S19: =IF($I19<>"",VLOOKUP($I19,$A$5:$F$9,6,FALSE),"") -> C49 | T19: =IF($I19<>"",IF(_xlfn.SINGLE(INDIRECT($G19&"!"&$S19))<>"",_xlfn.SINGLE(INDIRECT($G19&"!"&$S19)),""),"") | U19: =LEFT($O19,1) -> N | V19: =RIGHT($L19,2) -> 32 | W19: =IF($G19<>"",IF(_xlfn.SINGLE(INDIRECT($G19&"!"&$U19&($V19+W$15+1)))<>"",_xlfn.SINGLE(INDIRECT($G19&"!"&$U19&($V19+W$15+1))),""),"") -> Validé | X19: =IF($G19<>"",IF(_xlfn.SINGLE(INDIRECT($G19&"!"&$U19&($V19+X$15+1)))<>"",_xlfn.SINGLE(INDIRECT($G19&"!"&$U19&($V19+X$15+1))),""),"") -> Validé | Y19: =IF($G19<>"",IF(_xlfn.SINGLE(INDIRECT($G19&"!"&$U19&($V19+Y$15+1)))<>"",_xlfn.SINGLE(INDIRECT($G19&"!"&$U19&($V19+Y$15+1))),""),"") -> Validé | Z19: =IF($G19<>"",IF(_xlfn.SINGLE(INDIRECT($G19&"!"&$U19&($V19+Z$15+1)))<>"",_xlfn.SINGLE(INDIRECT($G19&"!"&$U19&($V19+Z$15+1))),""),"") -> Non validé (>10%) | AA19: =IF($G19<>"",IF(_xlfn.SINGLE(INDIRECT($G19&"!"&$U19&($V19+AA$15+1)))<>"",_xlfn.SINGLE(INDIRECT($G19&"!"&$U19&($V19+AA$15+1))),""),"") -> Non validé | AB19: =IF($G19<>"",IF(_xlfn.SINGLE(INDIRECT($G19&"!"&$U19&($V19+AB$15+1)))<>"",_xlfn.SINGLE(INDIRECT($G19&"!"&$U19&($V19+AB$15+1))),""),"") -> Non validé | AC19: =IF($G19<>"",IF(_xlfn.SINGLE(INDIRECT($G19&"!"&$U19&($V19+AC$15+1)))<>"",_xlfn.SINGLE(INDIRECT($G19&"!"&$U19&($V19+AC$15+1))),""),"") -> Non validé | AD19: =IF($G19<>"",IF(_xlfn.SINGLE(INDIRECT($G19&"!"&$U19&($V19+AD$15+1)))<>"",_xlfn.SINGLE(INDIRECT($G19&"!"&$U19&($V19+AD$15+1))),""),"") -> Validé | ... AF19: =IF($G19<>"",IF(_xlfn.SINGLE(INDIRECT($G19&"!"&$U19&($V19+AF$15+1)))<>"",_xlfn.SINGLE(INDIRECT($G19&"!"&$U19&($V19+AF$15+1))),""),"")
A20: 5 | B20: =IF(OR(AND(($B$1+A20-1)>=$B$1,($B$1+A20-1)<$C$1),AND(($B$1+A20-1)>=$E$1,($B$1+A20-1)<$F$1),AND(($B$1+A20-1)>=$B$2,($B$1+A20-1)<$C$2),AND(($B$1+A20-1)>=$E$2,($B$1+A20-1)<$F$2)),TRUE,FALSE) -> FALSE | C20: =IF( AND( $B20, OR( _xlfn.SINGLE(INDIRECT("Descriptif!$M"&($B$1+$A20-1)))="Préleveur", LEFT(_xlfn.SINGLE(INDIRECT("Descriptif!$M"&($B$1+$A20-1))),5)="Sonde", LEFT(_xlfn.SINGLE(INDIRECT("Descriptif!$M"&($B$1+$A20-1))),10)="Débitmètre", LEFT(_xlfn.SINGLE(INDIRECT("Descriptif!$F"&($B$1+$A20-1))),6)="PLUVIO" ) ), _xlfn.SINGLE(INDIRECT("Descriptif!$"&C$15&($B$1 +$A20 -1))), "" ) | D20: =IF( AND( $B20, OR( _xlfn.SINGLE(INDIRECT("Descriptif!$M"&($B$1+$A20-1)))="Préleveur", LEFT(_xlfn.SINGLE(INDIRECT("Descriptif!$M"&($B$1+$A20-1))),5)="Sonde", LEFT(_xlfn.SINGLE(INDIRECT("Descriptif!$M"&($B$1+$A20-1))),10)="Débitmètre", LEFT(_xlfn.SINGLE(INDIRECT("Descriptif!$F"&($B$1+$A20-1))),6)="PLUVIO" ) ), IF( LEFT(_xlfn.SINGLE(INDIRECT("Descriptif!$F"&($B$1+$A20-1))),11)="PLUVIO_STEU", "A3", IF( LEFT(_xlfn.SINGLE(INDIRECT("Descriptif!$F"&($B$1+$A20-1))),10)="PLUVIO_SCL", "A1", _xlfn.SINGLE(INDIRECT("Descriptif!$"&D$15&($B$1 +$A20 -1)) )) ), "" ) | E20: =IF( AND( $B20, OR( _xlfn.SINGLE(INDIRECT("Descriptif!$M"&($B$1+$A20-1)))="Préleveur", LEFT(_xlfn.SINGLE(INDIRECT("Descriptif!$M"&($B$1+$A20-1))),5)="Sonde", LEFT(_xlfn.SINGLE(INDIRECT("Descriptif!$M"&($B$1+$A20-1))),10)="Débitmètre", LEFT(_xlfn.SINGLE(INDIRECT("Descriptif!$F"&($B$1+$A20-1))),6)="PLUVIO" ) ), IF(LEFT(_xlfn.SINGLE(INDIRECT("Descriptif!$F"&($B$1+$A20-1))),6)="PLUVIO","Pluviomètre",_xlfn.SINGLE(INDIRECT("Descriptif!$"&E$15&($B$1 +$A20 -1)))), "" ) | F20: =IF( AND( $B20, OR( _xlfn.SINGLE(INDIRECT("Descriptif!$M"&($B$1+$A20-1)))="Préleveur", LEFT(_xlfn.SINGLE(INDIRECT("Descriptif!$M"&($B$1+$A20-1))),5)="Sonde", LEFT(_xlfn.SINGLE(INDIRECT("Descriptif!$M"&($B$1+$A20-1))),10)="Débitmètre", LEFT(_xlfn.SINGLE(INDIRECT("Descriptif!$F"&($B$1+$A20-1))),6)="PLUVIO" ) ), IF(LEFT(_xlfn.SINGLE(INDIRECT("Descriptif!$F"&($B$1+$A20-1))),6)="PLUVIO","Pluviomètre",_xlfn.SINGLE(INDIRECT("Descriptif!$"&F$15&($B$1 +$A20 -1)))), "" ) | G20: {=IFERROR(INDEX($C$16:$C$116,SMALL(IF($C$16:$C$116<>"",ROW($C$16:$C$116)-ROW($C$16)+1),ROW(A5))),"")} -> A3_P102_PREL | H20: {=IFERROR(INDEX($D$16:$D$116,SMALL(IF($D$16:$D$116<>"",ROW($D$16:$D$116)-ROW($D$16)+1),ROW(A5))),"")} -> A3 | I20: {=IFERROR(INDEX($E$16:$E$116,SMALL(IF($E$16:$E$116<>"",ROW($E$16:$E$116)-ROW($E$16)+1),ROW(A5))),"")} -> Préleveur | J20: {=IFERROR(INDEX($F$16:$F$116,SMALL(IF($F$16:$F$116<>"",ROW($F$16:$F$116)-ROW($F$16)+1),ROW(A5))),"")} -> Préleveur Automatique | K20: =G20 -> A3_P102_PREL | L20: =IF($I20<>"",VLOOKUP($I20,$A$5:$F$9,2,FALSE),"") -> D37 | M20: =IF($I20<>"",VLOOKUP($I20,$A$5:$F$9,3,FALSE),"") -> P50 | N20: =IF($I20<>"",IF(_xlfn.SINGLE(INDIRECT($G20&"!"&$M20))<>"",_xlfn.SINGLE(INDIRECT($G20&"!"&$M20)),""),"") -> 85 | O20: =IF($I20<>"",VLOOKUP($I20,$A$5:$F$9,4,FALSE),"") -> N50 | P20: =IF($I20<>"",IF(_xlfn.SINGLE(INDIRECT($G20&"!"&$O20))<>"",_xlfn.SINGLE(INDIRECT($G20&"!"&$O20)),""),"") -> Validé | Q20: =IF($I20<>"",VLOOKUP($I20,$A$5:$F$9,5,FALSE),"") -> D50 | R20: =IF($I20<>"",IF(_xlfn.SINGLE(INDIRECT($G20&"!"&$Q20))<>"",_xlfn.SINGLE(INDIRECT($G20&"!"&$Q20)),""),"") -> Pb de positionnement | S20: =IF($I20<>"",VLOOKUP($I20,$A$5:$F$9,6,FALSE),"") -> C54 | T20: =IF($I20<>"",IF(_xlfn.SINGLE(INDIRECT($G20&"!"&$S20))<>"",_xlfn.SINGLE(INDIRECT($G20&"!"&$S20)),""),"") | U20: =LEFT($O20,1) -> N | V20: =RIGHT($L20,2) -> 37 | W20: =IF($G20<>"",IF(_xlfn.SINGLE(INDIRECT($G20&"!"&$U20&($V20+W$15+1)))<>"",_xlfn.SINGLE(INDIRECT($G20&"!"&$U20&($V20+W$15+1))),""),"") -> Validé | X20: =IF($G20<>"",IF(_xlfn.SINGLE(INDIRECT($G20&"!"&$U20&($V20+X$15+1)))<>"",_xlfn.SINGLE(INDIRECT($G20&"!"&$U20&($V20+X$15+1))),""),"") -> Non validé | Y20: =IF($G20<>"",IF(_xlfn.SINGLE(INDIRECT($G20&"!"&$U20&($V20+Y$15+1)))<>"",_xlfn.SINGLE(INDIRECT($G20&"!"&$U20&($V20+Y$15+1))),""),"") -> Validé | Z20: =IF($G20<>"",IF(_xlfn.SINGLE(INDIRECT($G20&"!"&$U20&($V20+Z$15+1)))<>"",_xlfn.SINGLE(INDIRECT($G20&"!"&$U20&($V20+Z$15+1))),""),"") -> Validé | AA20: =IF($G20<>"",IF(_xlfn.SINGLE(INDIRECT($G20&"!"&$U20&($V20+AA$15+1)))<>"",_xlfn.SINGLE(INDIRECT($G20&"!"&$U20&($V20+AA$15+1))),""),"") -> Validé | AB20: =IF($G20<>"",IF(_xlfn.SINGLE(INDIRECT($G20&"!"&$U20&($V20+AB$15+1)))<>"",_xlfn.SINGLE(INDIRECT($G20&"!"&$U20&($V20+AB$15+1))),""),"") -> Validé | AC20: =IF($G20<>"",IF(_xlfn.SINGLE(INDIRECT($G20&"!"&$U20&($V20+AC$15+1)))<>"",_xlfn.SINGLE(INDIRECT($G20&"!"&$U20&($V20+AC$15+1))),""),"") -> Validé | AD20: =IF($G20<>"",IF(_xlfn.SINGLE(INDIRECT($G20&"!"&$U20&($V20+AD$15+1)))<>"",_xlfn.SINGLE(INDIRECT($G20&"!"&$U20&($V20+AD$15+1))),""),"") -> Validé | ... AF20: =IF($G20<>"",IF(_xlfn.SINGLE(INDIRECT($G20&"!"&$U20&($V20+AF$15+1)))<>"",_xlfn.SINGLE(INDIRECT($G20&"!"&$U20&($V20+AF$15+1))),""),"") -> Validé
A21: 6 | B21: =IF(OR(AND(($B$1+A21-1)>=$B$1,($B$1+A21-1)<$C$1),AND(($B$1+A21-1)>=$E$1,($B$1+A21-1)<$F$1),AND(($B$1+A21-1)>=$B$2,($B$1+A21-1)<$C$2),AND(($B$1+A21-1)>=$E$2,($B$1+A21-1)<$F$2)),TRUE,FALSE) -> FALSE | C21: =IF( AND( $B21, OR( _xlfn.SINGLE(INDIRECT("Descriptif!$M"&($B$1+$A21-1)))="Préleveur", LEFT(_xlfn.SINGLE(INDIRECT("Descriptif!$M"&($B$1+$A21-1))),5)="Sonde", LEFT(_xlfn.SINGLE(INDIRECT("Descriptif!$M"&($B$1+$A21-1))),10)="Débitmètre", LEFT(_xlfn.SINGLE(INDIRECT("Descriptif!$F"&($B$1+$A21-1))),6)="PLUVIO" ) ), _xlfn.SINGLE(INDIRECT("Descriptif!$"&C$15&($B$1 +$A21 -1))), "" ) | D21: =IF( AND( $B21, OR( _xlfn.SINGLE(INDIRECT("Descriptif!$M"&($B$1+$A21-1)))="Préleveur", LEFT(_xlfn.SINGLE(INDIRECT("Descriptif!$M"&($B$1+$A21-1))),5)="Sonde", LEFT(_xlfn.SINGLE(INDIRECT("Descriptif!$M"&($B$1+$A21-1))),10)="Débitmètre", LEFT(_xlfn.SINGLE(INDIRECT("Descriptif!$F"&($B$1+$A21-1))),6)="PLUVIO" ) ), IF( LEFT(_xlfn.SINGLE(INDIRECT("Descriptif!$F"&($B$1+$A21-1))),11)="PLUVIO_STEU", "A3", IF( LEFT(_xlfn.SINGLE(INDIRECT("Descriptif!$F"&($B$1+$A21-1))),10)="PLUVIO_SCL", "A1", _xlfn.SINGLE(INDIRECT("Descriptif!$"&D$15&($B$1 +$A21 -1)) )) ), "" ) | E21: =IF( AND( $B21, OR( _xlfn.SINGLE(INDIRECT("Descriptif!$M"&($B$1+$A21-1)))="Préleveur", LEFT(_xlfn.SINGLE(INDIRECT("Descriptif!$M"&($B$1+$A21-1))),5)="Sonde", LEFT(_xlfn.SINGLE(INDIRECT("Descriptif!$M"&($B$1+$A21-1))),10)="Débitmètre", LEFT(_xlfn.SINGLE(INDIRECT("Descriptif!$F"&($B$1+$A21-1))),6)="PLUVIO" ) ), IF(LEFT(_xlfn.SINGLE(INDIRECT("Descriptif!$F"&($B$1+$A21-1))),6)="PLUVIO","Pluviomètre",_xlfn.SINGLE(INDIRECT("Descriptif!$"&E$15&($B$1 +$A21 -1)))), "" ) | F21: =IF( AND( $B21, OR( _xlfn.SINGLE(INDIRECT("Descriptif!$M"&($B$1+$A21-1)))="Préleveur", LEFT(_xlfn.SINGLE(INDIRECT("Descriptif!$M"&($B$1+$A21-1))),5)="Sonde", LEFT(_xlfn.SINGLE(INDIRECT("Descriptif!$M"&($B$1+$A21-1))),10)="Débitmètre", LEFT(_xlfn.SINGLE(INDIRECT("Descriptif!$F"&($B$1+$A21-1))),6)="PLUVIO" ) ), IF(LEFT(_xlfn.SINGLE(INDIRECT("Descriptif!$F"&($B$1+$A21-1))),6)="PLUVIO","Pluviomètre",_xlfn.SINGLE(INDIRECT("Descriptif!$"&F$15&($B$1 +$A21 -1)))), "" ) | G21: {=IFERROR(INDEX($C$16:$C$116,SMALL(IF($C$16:$C$116<>"",ROW($C$16:$C$116)-ROW($C$16)+1),ROW(A6))),"")} -> A4_P103_Q_Grav | H21: {=IFERROR(INDEX($D$16:$D$116,SMALL(IF($D$16:$D$116<>"",ROW($D$16:$D$116)-ROW($D$16)+1),ROW(A6))),"")} -> A4 | I21: {=IFERROR(INDEX($E$16:$E$116,SMALL(IF($E$16:$E$116<>"",ROW($E$16:$E$116)-ROW($E$16)+1),ROW(A6))),"")} -> Débitmètre gravitaire | J21: {=IFERROR(INDEX($F$16:$F$116,SMALL(IF($F$16:$F$116<>"",ROW($F$16:$F$116)-ROW($F$16)+1),ROW(A6))),"")} -> Canal Venturi | K21: =G21 -> A4_P103_Q_Grav | L21: =IF($I21<>"",VLOOKUP($I21,$A$5:$F$9,2,FALSE),"") -> D40 | M21: =IF($I21<>"",VLOOKUP($I21,$A$5:$F$9,3,FALSE),"") -> P53 | N21: =IF($I21<>"",IF(_xlfn.SINGLE(INDIRECT($G21&"!"&$M21))<>"",_xlfn.SINGLE(INDIRECT($G21&"!"&$M21)),""),"") -> 0 | O21: =IF($I21<>"",VLOOKUP($I21,$A$5:$F$9,4,FALSE),"") -> N53 | P21: =IF($I21<>"",IF(_xlfn.SINGLE(INDIRECT($G21&"!"&$O21))<>"",_xlfn.SINGLE(INDIRECT($G21&"!"&$O21)),""),"") -> Non validé | Q21: =IF($I21<>"",VLOOKUP($I21,$A$5:$F$9,5,FALSE),"") -> D53 | R21: =IF($I21<>"",IF(_xlfn.SINGLE(INDIRECT($G21&"!"&$Q21))<>"",_xlfn.SINGLE(INDIRECT($G21&"!"&$Q21)),""),"") | S21: =IF($I21<>"",VLOOKUP($I21,$A$5:$F$9,6,FALSE),"") -> C57 | T21: =IF($I21<>"",IF(_xlfn.SINGLE(INDIRECT($G21&"!"&$S21))<>"",_xlfn.SINGLE(INDIRECT($G21&"!"&$S21)),""),"") | U21: =LEFT($O21,1) -> N | V21: =RIGHT($L21,2) -> 40 | W21: =IF($G21<>"",IF(_xlfn.SINGLE(INDIRECT($G21&"!"&$U21&($V21+W$15+1)))<>"",_xlfn.SINGLE(INDIRECT($G21&"!"&$U21&($V21+W$15+1))),""),"") -> Validé | X21: =IF($G21<>"",IF(_xlfn.SINGLE(INDIRECT($G21&"!"&$U21&($V21+X$15+1)))<>"",_xlfn.SINGLE(INDIRECT($G21&"!"&$U21&($V21+X$15+1))),""),"") -> Validé | Y21: =IF($G21<>"",IF(_xlfn.SINGLE(INDIRECT($G21&"!"&$U21&($V21+Y$15+1)))<>"",_xlfn.SINGLE(INDIRECT($G21&"!"&$U21&($V21+Y$15+1))),""),"") -> Validé | Z21: =IF($G21<>"",IF(_xlfn.SINGLE(INDIRECT($G21&"!"&$U21&($V21+Z$15+1)))<>"",_xlfn.SINGLE(INDIRECT($G21&"!"&$U21&($V21+Z$15+1))),""),"") -> Validé | AA21: =IF($G21<>"",IF(_xlfn.SINGLE(INDIRECT($G21&"!"&$U21&($V21+AA$15+1)))<>"",_xlfn.SINGLE(INDIRECT($G21&"!"&$U21&($V21+AA$15+1))),""),"") -> Validé | AB21: =IF($G21<>"",IF(_xlfn.SINGLE(INDIRECT($G21&"!"&$U21&($V21+AB$15+1)))<>"",_xlfn.SINGLE(INDIRECT($G21&"!"&$U21&($V21+AB$15+1))),""),"") -> Non contrôlé | AC21: =IF($G21<>"",IF(_xlfn.SINGLE(INDIRECT($G21&"!"&$U21&($V21+AC$15+1)))<>"",_xlfn.SINGLE(INDIRECT($G21&"!"&$U21&($V21+AC$15+1))),""),"") -> Validé | AD21: =IF($G21<>"",IF(_xlfn.SINGLE(INDIRECT($G21&"!"&$U21&($V21+AD$15+1)))<>"",_xlfn.SINGLE(INDIRECT($G21&"!"&$U21&($V21+AD$15+1))),""),"") -> Non validé | ... AF21: =IF($G21<>"",IF(_xlfn.SINGLE(INDIRECT($G21&"!"&$U21&($V21+AF$15+1)))<>"",_xlfn.SINGLE(INDIRECT($G21&"!"&$U21&($V21+AF$15+1))),""),"") -> Oui
A22: 7 | B22: =IF(OR(AND(($B$1+A22-1)>=$B$1,($B$1+A22-1)<$C$1),AND(($B$1+A22-1)>=$E$1,($B$1+A22-1)<$F$1),AND(($B$1+A22-1)>=$B$2,($B$1+A22-1)<$C$2),AND(($B$1+A22-1)>=$E$2,($B$1+A22-1)<$F$2)),TRUE,FALSE) -> FALSE | C22: =IF( AND( $B22, OR( _xlfn.SINGLE(INDIRECT("Descriptif!$M"&($B$1+$A22-1)))="Préleveur", LEFT(_xlfn.SINGLE(INDIRECT("Descriptif!$M"&($B$1+$A22-1))),5)="Sonde", LEFT(_xlfn.SINGLE(INDIRECT("Descriptif!$M"&($B$1+$A22-1))),10)="Débitmètre", LEFT(_xlfn.SINGLE(INDIRECT("Descriptif!$F"&($B$1+$A22-1))),6)="PLUVIO" ) ), _xlfn.SINGLE(INDIRECT("Descriptif!$"&C$15&($B$1 +$A22 -1))), "" ) | D22: =IF( AND( $B22, OR( _xlfn.SINGLE(INDIRECT("Descriptif!$M"&($B$1+$A22-1)))="Préleveur", LEFT(_xlfn.SINGLE(INDIRECT("Descriptif!$M"&($B$1+$A22-1))),5)="Sonde", LEFT(_xlfn.SINGLE(INDIRECT("Descriptif!$M"&($B$1+$A22-1))),10)="Débitmètre", LEFT(_xlfn.SINGLE(INDIRECT("Descriptif!$F"&($B$1+$A22-1))),6)="PLUVIO" ) ), IF( LEFT(_xlfn.SINGLE(INDIRECT("Descriptif!$F"&($B$1+$A22-1))),11)="PLUVIO_STEU", "A3", IF( LEFT(_xlfn.SINGLE(INDIRECT("Descriptif!$F"&($B$1+$A22-1))),10)="PLUVIO_SCL", "A1", _xlfn.SINGLE(INDIRECT("Descriptif!$"&D$15&($B$1 +$A22 -1)) )) ), "" ) | E22: =IF( AND( $B22, OR( _xlfn.SINGLE(INDIRECT("Descriptif!$M"&($B$1+$A22-1)))="Préleveur", LEFT(_xlfn.SINGLE(INDIRECT("Descriptif!$M"&($B$1+$A22-1))),5)="Sonde", LEFT(_xlfn.SINGLE(INDIRECT("Descriptif!$M"&($B$1+$A22-1))),10)="Débitmètre", LEFT(_xlfn.SINGLE(INDIRECT("Descriptif!$F"&($B$1+$A22-1))),6)="PLUVIO" ) ), IF(LEFT(_xlfn.SINGLE(INDIRECT("Descriptif!$F"&($B$1+$A22-1))),6)="PLUVIO","Pluviomètre",_xlfn.SINGLE(INDIRECT("Descriptif!$"&E$15&($B$1 +$A22 -1)))), "" ) | F22: =IF( AND( $B22, OR( _xlfn.SINGLE(INDIRECT("Descriptif!$M"&($B$1+$A22-1)))="Préleveur", LEFT(_xlfn.SINGLE(INDIRECT("Descriptif!$M"&($B$1+$A22-1))),5)="Sonde", LEFT(_xlfn.SINGLE(INDIRECT("Descriptif!$M"&($B$1+$A22-1))),10)="Débitmètre", LEFT(_xlfn.SINGLE(INDIRECT("Descriptif!$F"&($B$1+$A22-1))),6)="PLUVIO" ) ), IF(LEFT(_xlfn.SINGLE(INDIRECT("Descriptif!$F"&($B$1+$A22-1))),6)="PLUVIO","Pluviomètre",_xlfn.SINGLE(INDIRECT("Descriptif!$"&F$15&($B$1 +$A22 -1)))), "" ) | G22: {=IFERROR(INDEX($C$16:$C$116,SMALL(IF($C$16:$C$116<>"",ROW($C$16:$C$116)-ROW($C$16)+1),ROW(A7))),"")} -> A4_P103_PREL | H22: {=IFERROR(INDEX($D$16:$D$116,SMALL(IF($D$16:$D$116<>"",ROW($D$16:$D$116)-ROW($D$16)+1),ROW(A7))),"")} -> A4 | I22: {=IFERROR(INDEX($E$16:$E$116,SMALL(IF($E$16:$E$116<>"",ROW($E$16:$E$116)-ROW($E$16)+1),ROW(A7))),"")} -> Préleveur | J22: {=IFERROR(INDEX($F$16:$F$116,SMALL(IF($F$16:$F$116<>"",ROW($F$16:$F$116)-ROW($F$16)+1),ROW(A7))),"")} -> Préleveur Automatique | K22: =G22 -> A4_P103_PREL | L22: =IF($I22<>"",VLOOKUP($I22,$A$5:$F$9,2,FALSE),"") -> D37 | M22: =IF($I22<>"",VLOOKUP($I22,$A$5:$F$9,3,FALSE),"") -> P50 | N22: =IF($I22<>"",IF(_xlfn.SINGLE(INDIRECT($G22&"!"&$M22))<>"",_xlfn.SINGLE(INDIRECT($G22&"!"&$M22)),""),"") -> 100 | O22: =IF($I22<>"",VLOOKUP($I22,$A$5:$F$9,4,FALSE),"") -> N50 | P22: =IF($I22<>"",IF(_xlfn.SINGLE(INDIRECT($G22&"!"&$O22))<>"",_xlfn.SINGLE(INDIRECT($G22&"!"&$O22)),""),"") -> Validé | Q22: =IF($I22<>"",VLOOKUP($I22,$A$5:$F$9,5,FALSE),"") -> D50 | R22: =IF($I22<>"",IF(_xlfn.SINGLE(INDIRECT($G22&"!"&$Q22))<>"",_xlfn.SINGLE(INDIRECT($G22&"!"&$Q22)),""),"") | S22: =IF($I22<>"",VLOOKUP($I22,$A$5:$F$9,6,FALSE),"") -> C54 | T22: =IF($I22<>"",IF(_xlfn.SINGLE(INDIRECT($G22&"!"&$S22))<>"",_xlfn.SINGLE(INDIRECT($G22&"!"&$S22)),""),"") | U22: =LEFT($O22,1) -> N | V22: =RIGHT($L22,2) -> 37 | W22: =IF($G22<>"",IF(_xlfn.SINGLE(INDIRECT($G22&"!"&$U22&($V22+W$15+1)))<>"",_xlfn.SINGLE(INDIRECT($G22&"!"&$U22&($V22+W$15+1))),""),"") -> Validé | X22: =IF($G22<>"",IF(_xlfn.SINGLE(INDIRECT($G22&"!"&$U22&($V22+X$15+1)))<>"",_xlfn.SINGLE(INDIRECT($G22&"!"&$U22&($V22+X$15+1))),""),"") -> Validé | Y22: =IF($G22<>"",IF(_xlfn.SINGLE(INDIRECT($G22&"!"&$U22&($V22+Y$15+1)))<>"",_xlfn.SINGLE(INDIRECT($G22&"!"&$U22&($V22+Y$15+1))),""),"") -> Validé | Z22: =IF($G22<>"",IF(_xlfn.SINGLE(INDIRECT($G22&"!"&$U22&($V22+Z$15+1)))<>"",_xlfn.SINGLE(INDIRECT($G22&"!"&$U22&($V22+Z$15+1))),""),"") -> Validé | AA22: =IF($G22<>"",IF(_xlfn.SINGLE(INDIRECT($G22&"!"&$U22&($V22+AA$15+1)))<>"",_xlfn.SINGLE(INDIRECT($G22&"!"&$U22&($V22+AA$15+1))),""),"") -> Validé | AB22: =IF($G22<>"",IF(_xlfn.SINGLE(INDIRECT($G22&"!"&$U22&($V22+AB$15+1)))<>"",_xlfn.SINGLE(INDIRECT($G22&"!"&$U22&($V22+AB$15+1))),""),"") -> Validé | AC22: =IF($G22<>"",IF(_xlfn.SINGLE(INDIRECT($G22&"!"&$U22&($V22+AC$15+1)))<>"",_xlfn.SINGLE(INDIRECT($G22&"!"&$U22&($V22+AC$15+1))),""),"") -> Validé | AD22: =IF($G22<>"",IF(_xlfn.SINGLE(INDIRECT($G22&"!"&$U22&($V22+AD$15+1)))<>"",_xlfn.SINGLE(INDIRECT($G22&"!"&$U22&($V22+AD$15+1))),""),"") -> Validé | ... AF22: =IF($G22<>"",IF(_xlfn.SINGLE(INDIRECT($G22&"!"&$U22&($V22+AF$15+1)))<>"",_xlfn.SINGLE(INDIRECT($G22&"!"&$U22&($V22+AF$15+1))),""),"") -> Validé
A23: 8 | B23: =IF(OR(AND(($B$1+A23-1)>=$B$1,($B$1+A23-1)<$C$1),AND(($B$1+A23-1)>=$E$1,($B$1+A23-1)<$F$1),AND(($B$1+A23-1)>=$B$2,($B$1+A23-1)<$C$2),AND(($B$1+A23-1)>=$E$2,($B$1+A23-1)<$F$2)),TRUE,FALSE) -> FALSE | C23: =IF( AND( $B23, OR( _xlfn.SINGLE(INDIRECT("Descriptif!$M"&($B$1+$A23-1)))="Préleveur", LEFT(_xlfn.SINGLE(INDIRECT("Descriptif!$M"&($B$1+$A23-1))),5)="Sonde", LEFT(_xlfn.SINGLE(INDIRECT("Descriptif!$M"&($B$1+$A23-1))),10)="Débitmètre", LEFT(_xlfn.SINGLE(INDIRECT("Descriptif!$F"&($B$1+$A23-1))),6)="PLUVIO" ) ), _xlfn.SINGLE(INDIRECT("Descriptif!$"&C$15&($B$1 +$A23 -1))), "" ) | D23: =IF( AND( $B23, OR( _xlfn.SINGLE(INDIRECT("Descriptif!$M"&($B$1+$A23-1)))="Préleveur", LEFT(_xlfn.SINGLE(INDIRECT("Descriptif!$M"&($B$1+$A23-1))),5)="Sonde", LEFT(_xlfn.SINGLE(INDIRECT("Descriptif!$M"&($B$1+$A23-1))),10)="Débitmètre", LEFT(_xlfn.SINGLE(INDIRECT("Descriptif!$F"&($B$1+$A23-1))),6)="PLUVIO" ) ), IF( LEFT(_xlfn.SINGLE(INDIRECT("Descriptif!$F"&($B$1+$A23-1))),11)="PLUVIO_STEU", "A3", IF( LEFT(_xlfn.SINGLE(INDIRECT("Descriptif!$F"&($B$1+$A23-1))),10)="PLUVIO_SCL", "A1", _xlfn.SINGLE(INDIRECT("Descriptif!$"&D$15&($B$1 +$A23 -1)) )) ), "" ) | E23: =IF( AND( $B23, OR( _xlfn.SINGLE(INDIRECT("Descriptif!$M"&($B$1+$A23-1)))="Préleveur", LEFT(_xlfn.SINGLE(INDIRECT("Descriptif!$M"&($B$1+$A23-1))),5)="Sonde", LEFT(_xlfn.SINGLE(INDIRECT("Descriptif!$M"&($B$1+$A23-1))),10)="Débitmètre", LEFT(_xlfn.SINGLE(INDIRECT("Descriptif!$F"&($B$1+$A23-1))),6)="PLUVIO" ) ), IF(LEFT(_xlfn.SINGLE(INDIRECT("Descriptif!$F"&($B$1+$A23-1))),6)="PLUVIO","Pluviomètre",_xlfn.SINGLE(INDIRECT("Descriptif!$"&E$15&($B$1 +$A23 -1)))), "" ) | F23: =IF( AND( $B23, OR( _xlfn.SINGLE(INDIRECT("Descriptif!$M"&($B$1+$A23-1)))="Préleveur", LEFT(_xlfn.SINGLE(INDIRECT("Descriptif!$M"&($B$1+$A23-1))),5)="Sonde", LEFT(_xlfn.SINGLE(INDIRECT("Descriptif!$M"&($B$1+$A23-1))),10)="Débitmètre", LEFT(_xlfn.SINGLE(INDIRECT("Descriptif!$F"&($B$1+$A23-1))),6)="PLUVIO" ) ), IF(LEFT(_xlfn.SINGLE(INDIRECT("Descriptif!$F"&($B$1+$A23-1))),6)="PLUVIO","Pluviomètre",_xlfn.SINGLE(INDIRECT("Descriptif!$"&F$15&($B$1 +$A23 -1)))), "" ) | G23: {=IFERROR(INDEX($C$16:$C$116,SMALL(IF($C$16:$C$116<>"",ROW($C$16:$C$116)-ROW($C$16)+1),ROW(A8))),"")} -> A6_P104_Q_DEM | H23: {=IFERROR(INDEX($D$16:$D$116,SMALL(IF($D$16:$D$116<>"",ROW($D$16:$D$116)-ROW($D$16)+1),ROW(A8))),"")} -> A6 | I23: {=IFERROR(INDEX($E$16:$E$116,SMALL(IF($E$16:$E$116<>"",ROW($E$16:$E$116)-ROW($E$16)+1),ROW(A8))),"")} -> Débitmètre en charge | J23: {=IFERROR(INDEX($F$16:$F$116,SMALL(IF($F$16:$F$116<>"",ROW($F$16:$F$116)-ROW($F$16)+1),ROW(A8))),"")} -> Débitmètre électromagnétique (boue/MDV) | K23: =G23 -> A6_P104_Q_DEM | L23: =IF($I23<>"",VLOOKUP($I23,$A$5:$F$9,2,FALSE),"") -> D32 | M23: =IF($I23<>"",VLOOKUP($I23,$A$5:$F$9,3,FALSE),"") -> P45 | N23: =IF($I23<>"",IF(_xlfn.SINGLE(INDIRECT($G23&"!"&$M23))<>"",_xlfn.SINGLE(INDIRECT($G23&"!"&$M23)),""),"") -> 40 | O23: =IF($I23<>"",VLOOKUP($I23,$A$5:$F$9,4,FALSE),"") -> N45 | P23: =IF($I23<>"",IF(_xlfn.SINGLE(INDIRECT($G23&"!"&$O23))<>"",_xlfn.SINGLE(INDIRECT($G23&"!"&$O23)),""),"") -> Non validé | Q23: =IF($I23<>"",VLOOKUP($I23,$A$5:$F$9,5,FALSE),"") -> D45 | R23: =IF($I23<>"",IF(_xlfn.SINGLE(INDIRECT($G23&"!"&$Q23))<>"",_xlfn.SINGLE(INDIRECT($G23&"!"&$Q23)),""),"") | S23: =IF($I23<>"",VLOOKUP($I23,$A$5:$F$9,6,FALSE),"") -> C49 | T23: =IF($I23<>"",IF(_xlfn.SINGLE(INDIRECT($G23&"!"&$S23))<>"",_xlfn.SINGLE(INDIRECT($G23&"!"&$S23)),""),"") | U23: =LEFT($O23,1) -> N | V23: =RIGHT($L23,2) -> 32 | W23: =IF($G23<>"",IF(_xlfn.SINGLE(INDIRECT($G23&"!"&$U23&($V23+W$15+1)))<>"",_xlfn.SINGLE(INDIRECT($G23&"!"&$U23&($V23+W$15+1))),""),"") -> Validé | X23: =IF($G23<>"",IF(_xlfn.SINGLE(INDIRECT($G23&"!"&$U23&($V23+X$15+1)))<>"",_xlfn.SINGLE(INDIRECT($G23&"!"&$U23&($V23+X$15+1))),""),"") -> Validé | Y23: =IF($G23<>"",IF(_xlfn.SINGLE(INDIRECT($G23&"!"&$U23&($V23+Y$15+1)))<>"",_xlfn.SINGLE(INDIRECT($G23&"!"&$U23&($V23+Y$15+1))),""),"") -> Validé | Z23: =IF($G23<>"",IF(_xlfn.SINGLE(INDIRECT($G23&"!"&$U23&($V23+Z$15+1)))<>"",_xlfn.SINGLE(INDIRECT($G23&"!"&$U23&($V23+Z$15+1))),""),"") -> Non validé (>10%) | AA23: =IF($G23<>"",IF(_xlfn.SINGLE(INDIRECT($G23&"!"&$U23&($V23+AA$15+1)))<>"",_xlfn.SINGLE(INDIRECT($G23&"!"&$U23&($V23+AA$15+1))),""),"") | AB23: =IF($G23<>"",IF(_xlfn.SINGLE(INDIRECT($G23&"!"&$U23&($V23+AB$15+1)))<>"",_xlfn.SINGLE(INDIRECT($G23&"!"&$U23&($V23+AB$15+1))),""),"") | AC23: =IF($G23<>"",IF(_xlfn.SINGLE(INDIRECT($G23&"!"&$U23&($V23+AC$15+1)))<>"",_xlfn.SINGLE(INDIRECT($G23&"!"&$U23&($V23+AC$15+1))),""),"") | AD23: =IF($G23<>"",IF(_xlfn.SINGLE(INDIRECT($G23&"!"&$U23&($V23+AD$15+1)))<>"",_xlfn.SINGLE(INDIRECT($G23&"!"&$U23&($V23+AD$15+1))),""),"") -> Validé | ... AF23: =IF($G23<>"",IF(_xlfn.SINGLE(INDIRECT($G23&"!"&$U23&($V23+AF$15+1)))<>"",_xlfn.SINGLE(INDIRECT($G23&"!"&$U23&($V23+AF$15+1))),""),"")
