Workbook
Name Asservissement: PARAM!$A$44:$A$46
Name CODE_SANDRE_3: PARAM!$I$4:$J$33
Name CODE_SANDRE_SCL: PARAM!$F$4:$F$7
Name CODE_SANDRE_STEU: PARAM!$E$4:$E$19
Name conditions_meteo: PARAM!$F$44:$F$46
Name Conformité: PARAM!$B$44:$B$48
Name diam_debitmetre: 'BD Débitmètres'!$B$11:$B$38
Name Eq_h_controle: PARAM!$C$30:$C$32
Name EQUIPEMENT_PREL: PARAM!$B$4:$B$6
Name EQUIPEMENT_Q: PARAM!$A$4:$A$15
Name Frequence: PARAM!$E$44:$E$51
Name LISTE_1: PARAM!$A$21:$A$23
Name LISTE_2: PARAM!$B$21:$B$24
Name LISTE_3: PARAM!$C$21:$C$25
Name LISTE_4: PARAM!$D$21:$D$25
Name LISTE_5: PARAM!$F$21:$F$25
Name LISTE_6: PARAM!$G$21
Name LISTE_7: PARAM!$H$21:$H$23
Name listeDebimetres: INDIRECT("Descriptif!"&ADDRESS(Descriptif!$AD$2,COLUMN(Descriptif!$AF$1))):INDEX(INDIRECT("Descriptif!AF"&Descriptif!$AD$2&":AF101"),COUNTIF(INDIRECT("Descriptif!AF"&Descriptif!$AD$2&":AF101"),"?*"))
Name listePluviometres: INDIRECT("Descriptif!"&ADDRESS(Descriptif!$AD$2,COLUMN(Descriptif!$AJ$1))):INDEX(INDIRECT("Descriptif!AJ"&Descriptif!$AD$2&":AJ101"),COUNTIF(INDIRECT("Descriptif!AJ"&Descriptif!$AD$2&":AJ101"),"?*"))
Name listePreleveurs: INDIRECT("Descriptif!"&ADDRESS(Descriptif!$AD$2,COLUMN(Descriptif!$AD$1))):INDEX(INDIRECT("Descriptif!AD"&Descriptif!$AD$2&":AD101"),COUNTIF(INDIRECT("Descriptif!AD"&Descriptif!$AD$2&":AD101"),"?*"))
Name listeSondeTemp: INDIRECT("Descriptif!"&ADDRESS(Descriptif!$AD$2,COLUMN(Descriptif!$AH$1))):INDEX(INDIRECT("Descriptif!AH"&Descriptif!$AD$2&":AH101"),COUNTIF(INDIRECT("Descriptif!AH"&Descriptif!$AD$2&":AH101"),"?*"))
Name Méthode: PARAM!$A$55:$A$57
Name Montage_sonde: PARAM!$G$44:$G$47
Name PLUVIO_SCL: Descriptif!$E$24:$E$24
Name Print_Area: LimitequantificationSDE!$A$1:$F$21
Name Print_Area: 'SeuilsComparaison-EMT'!$A$1:$K$29
Name Q_en_charge: PARAM!$A$30:$A$34
Name Q_en_charge_boues: PARAM!$E$30
Name Q_Gravitaire: PARAM!$B$30:$B$38
Name Satisfaction: PARAM!$D$44:$D$46
Name STATUT_EQ: PARAM!$G$4:$G$6
Name Type_capteur: PARAM!$C$44:$C$48
Name Type_equipement: PARAM!$C$4:$C$7
Name Type_reseau: PARAM!$D$30:$D$32
Name TypeDeMesure: PARAM!$B$55:$B$56

Sheet Lisez moi
C2: CONTRÔLE DES DISPOSITIFS D'AUTOSURVEILLANCE DES SYSTÈMES D'ASSAINISSEMENT COLLECTIF | AC2: début données sys collect | AD2: =ROW(E20)+1 -> 21 | AE2: fin données sys collect | AF2: =ROW(D22)-1 -> 21 | AG2: pluvio SCL | AH2: =ROW(#REF!)+1 -> #REF! | AI2: =ROW(#REF!)-1 -> #REF!
C4: Version grille CDA | D4: 1.17.5
C5: Version module | D5: 1.beta
C8: Présentation
C10: Le Contrôle Annuel des dispositifs d’Autosurveillance (CDA) constitue une étape réglementaire majeure dans la gestion des systèmes d'assainissement collectif. Ce diagnostic technique a pour fonction de vérifier la fiabilité et la conformité des données d'autosurveillance produites par les exploitants de Stations de Traitement des Eaux Usées (STEU) et deSystème de Collecte (SCL).
C11: L’autosurveillance repose sur la mesure en continue des débits et la réalisation de prélèvements d'échantillons représentatifs des rejets. Le CDA intervient comme un audit externe visant à : • Valider la métrologie : Vérifier l’étalonnage et la précision des débitmètres et des préleveurs automatiques. • Certifier les données : Garantir que les volumes et les charges polluantes déclarés aux agences de l’eau et aux services de l’État sont exacts. • Assurer la conformité : Vérifier le respect des prescriptions techniques de l’arrêté d'autorisation de l’ouvrage.
C13: Instructions pour la réalisation du CDA
C15: Le contrôle doit être réalisé par un organisme tiers indépendant et compétant (bureaux d’études spécialisés ou services d’assistance technique départementaux : SATESE). Il donne lieu à un rapport technique détaillé (dont une trame est exportable depuis cette feuille Excel) qui consigne les écarts de mesure, l'état de l'instrumentation et la qualité de la chaîne d'acquisition des données des stations de traitement et de leur système de collecte.
C16: Afin de structurer cette collecte et de sécuriser la transmission des informations, le formulaire Excel permet une saisie directe et standardisée des données de contrôle. Cet outil vise à harmoniser les rapports, à réduire les risques d’erreurs de retranscription et à faciliter le suivi des dispositifs d’autosurveillance.
C17: Le formulaire pourra être à terme être pré-généré et déposé sur la plateforme « Port'Aus » mise à disposition par les Agences de l’Eau.
C18: La réalisation du CDA et les modalités de remplissage de la grille conrrespondante doivent respecter les consignes suivantes : • Une grille CDA ne peut au maximum contenir que les inforations pour un système de collecte et une station. Pour les agglomerations disposant de plusieurs système de traitement, il est impératif de générer une grille par système de traitement. • Il est recommandé de faire un CDA distinct pour la partie système de collecte et pour la partie système de traitement. • Dans le cas ou le contrôle s'effectue sur plusieurs jours, une seule grille peut être renseigné les jours sont consécutifs et si les conditions météorologiques sont stables pendant le contrôle. A défaut il faudra fournir plusieurs plusieurs grilles CDA.
C20: Documentation de la grille
C22: Les fichiers sources dans leur dernières version sont disponibles à cette adresse : https://github.com/ndhuygelaere/autosurveillance_steu_excel
C23: L'archive est constituée: • de la grille CDA (fichier GRILLES_CDA_Vxxx.xlsx) • d'un module complémentaire à Excel (fichier autosurveillanceSTEU.xlam) • de fichiers de modèle dans le répertoire "AutosurveillanceTemplates" • de la documentation d'installation Pour chaque mise à jour de la grille, il vous faudra suivre les instructions du manuel d'installation afin de vous assurez d'utiliser la nouvelle version de la grille et du module.
C24: Crédits
... C27: sous la direction du GT Autosurveillance des Agences de l'Eau

Sheet Descriptif
AC1: Ne rien mettre dans cette colonne | AD1: Ne rien mettre dans cette colonne | AE1: Ne rien mettre dans cette colonne | AF1: Ne rien mettre dans cette colonne | AG1: Ne rien mettre dans cette colonne | AH1: Ne rien mettre dans cette colonne | AI1: Ne rien mettre dans cette colonne | AJ1: Ne rien mettre dans cette colonne
C2: CONTRÔLE DES DISPOSITIFS D'AUTOSURVEILLANCE DES SYSTÈMES D'ASSAINISSEMENT COLLECTIF | AC2: début données sys collect | AD2: =ROW(E13)+1 -> 14 | AE2: fin données sys collect | AF2: =ROW(D15)-1 -> 14 | AG2: pluvio SCL | AH2: =ROW(E22)+1 -> 23 | AI2: =ROW(D24)-1 -> 23
C3: NOM DU SYSTÈME D'ASSAINISSEMENT : | I3: NOM DU SYSTÈME DE TRAITEMENT : | N3: NOM DU SYSTÈME DE COLLECTE : | S3: NOM DE L'ORGANISME DE CONTRÔLE : | AC3: début données station | AD3: =ROW(E33)+1 -> 34 | AE3: fin données station | AF3: =ROW(D35)-1 -> 34 | AG3: pluvio STEU | AH3: =ROW(E42)+1 -> 43 | AI3: =ROW(D44)-1 -> 43
C4: CODE SANDRE DE L'AGGLOMÉRATION : | I4: CODE SANDRE DE LA STATION : | N4: CODE SANDRE DU RÉSEAU : | S4: NOM(S) DU(ES) CONTROLEUR(S) :
C5: MAITRE D'OUVRAGE DE LA STATION : | I5: TYPE DE TRAITEMENT : | N5: TYPE DE RÉSEAU : | S5: DATE(S) D'INTERVENTION :
C6: EXPLOITANT DE LA STATION : | I6: CAPACITÉ DE LA STATION : | N6: EXPLOITANT DU RÉSEAU : | S6: CONDITION(S) MÉTÉO :
C8: SYSTÈME DE COLLECTE
D9: Remarques : | E9: Les estimations et les apports par camion ne rentrent pas dans le CDA
D10: Liste des équipements du système de collecte pour chaque point d’autosurveillance
H12: Les informations de codification sont à reprendre du MAS
E13: Statut | F13: Lien vers l'onglet de l'équipement | H13: Point réglementaire | I13: Localisation (cf. MAS) | J13: Code du point (cf MAS) | K13: Libellé de l'équipement | M13: Type d'équipement | O13: Type de matériel | Q13: Pluviomètre de référence | S13: Certaines informations d'un équipement ne sont pas modifiables. Au besoin il est préférable de supprimer et de recréer l'équipement. | AC13: Liste préleveurs | AE13: Liste débimètres | AG13: Liste thermo | AI13: Liste pluvio
AB14: =ROW(A14)- $AD$2 +1 -> 1 | AC14: =IF(AND(OR($E14="Contrôlé",$E14="Non contrôlé"),$M14="Préleveur"),$F14,"") | AD14: {=IFERROR(INDEX($AC$14:$AC$102,SMALL(IF($AC$14:$AC$102<>"",ROW($AC$14:$AC$102)-ROW(INDIRECT("$AC$14"))+1),ROW(INDIRECT("A" & AB14 ) ))),"")} | AE14: =IF(AND(OR($E14="Contrôlé",$E14="Non contrôlé"),LEFT($M14,10) ="Débitmètre"),$F14,"") | AF14: {=IFERROR(INDEX($AE$14:$AE$102,SMALL(IF($AE$14:$AE$102<>"",ROW($AE$14:$AE$102)-ROW(INDIRECT("$AE$14"))+1),ROW(INDIRECT("A" & AB14 ) ))),"")} | AG14: =IF(AND(OR($E14="Contrôlé",$E14="Non contrôlé"),LEFT($M14,5) ="Sonde"),$F14,"") | AH14: {=IFERROR(INDEX($AG$14:$AG$102,SMALL(IF($AG$14:$AG$102<>"",ROW($AG$14:$AG$102)-ROW(INDIRECT("$AG$14"))+1),ROW(INDIRECT("A" & AB14 ) ))),"")} | AI14: =IF(AND(OR($E14="Contrôlé",$E14="Non contrôlé"), $F14 <> "", $M14 = ""),$F14,"") | AJ14: {=IFERROR(INDEX($AI$14:$AI$102,SMALL(IF($AI$14:$AI$102<>"",ROW($AI$14:$AI$102)-ROW(INDIRECT("$AI$14"))+1),ROW(INDIRECT("A" & AB14 ) ))),"")}
E15: Ajouter un équipement réseau | K15: Si certains points ne sont pas équipés, veuillez les indiquer en commentaire : | AB15: =ROW(A15)- $AD$2 +1 -> 2 | AC15: =IF(AND(OR($E15="Contrôlé",$E15="Non contrôlé"),$M15="Préleveur"),$F15,"") | AD15: {=IFERROR(INDEX($AC$14:$AC$102,SMALL(IF($AC$14:$AC$102<>"",ROW($AC$14:$AC$102)-ROW(INDIRECT("$AC$14"))+1),ROW(INDIRECT("A" & AB15 ) ))),"")} | AE15: =IF(AND(OR($E15="Contrôlé",$E15="Non contrôlé"),LEFT($M15,10) ="Débitmètre"),$F15,"") | AF15: {=IFERROR(INDEX($AE$14:$AE$102,SMALL(IF($AE$14:$AE$102<>"",ROW($AE$14:$AE$102)-ROW(INDIRECT("$AE$14"))+1),ROW(INDIRECT("A" & AB15 ) ))),"")} | AG15: =IF(AND(OR($E15="Contrôlé",$E15="Non contrôlé"),LEFT($M15,5) ="Sonde"),$F15,"") | AH15: {=IFERROR(INDEX($AG$14:$AG$102,SMALL(IF($AG$14:$AG$102<>"",ROW($AG$14:$AG$102)-ROW(INDIRECT("$AG$14"))+1),ROW(INDIRECT("A" & AB15 ) ))),"")} | AI15: =IF(AND(OR($E15="Contrôlé",$E15="Non contrôlé"), $F15 <> "", $M15 = ""),$F15,"") | AJ15: {=IFERROR(INDEX($AI$14:$AI$102,SMALL(IF($AI$14:$AI$102<>"",ROW($AI$14:$AI$102)-ROW(INDIRECT("$AI$14"))+1),ROW(INDIRECT("A" & AB15 ) ))),"")}
AB16: =ROW(A16)- $AD$2 +1 -> 3 | AC16: =IF(AND(OR($E16="Contrôlé",$E16="Non contrôlé"),$M16="Préleveur"),$F16,"") | AD16: {=IFERROR(INDEX($AC$14:$AC$102,SMALL(IF($AC$14:$AC$102<>"",ROW($AC$14:$AC$102)-ROW(INDIRECT("$AC$14"))+1),ROW(INDIRECT("A" & AB16 ) ))),"")} | AE16: =IF(AND(OR($E16="Contrôlé",$E16="Non contrôlé"),LEFT($M16,10) ="Débitmètre"),$F16,"") | AF16: {=IFERROR(INDEX($AE$14:$AE$102,SMALL(IF($AE$14:$AE$102<>"",ROW($AE$14:$AE$102)-ROW(INDIRECT("$AE$14"))+1),ROW(INDIRECT("A" & AB16 ) ))),"")} | AG16: =IF(AND(OR($E16="Contrôlé",$E16="Non contrôlé"),LEFT($M16,5) ="Sonde"),$F16,"") | AH16: {=IFERROR(INDEX($AG$14:$AG$102,SMALL(IF($AG$14:$AG$102<>"",ROW($AG$14:$AG$102)-ROW(INDIRECT("$AG$14"))+1),ROW(INDIRECT("A" & AB16 ) ))),"")} | AI16: =IF(AND(OR($E16="Contrôlé",$E16="Non contrôlé"), $F16 <> "", $M16 = ""),$F16,"") | AJ16: {=IFERROR(INDEX($AI$14:$AI$102,SMALL(IF($AI$14:$AI$102<>"",ROW($AI$14:$AI$102)-ROW(INDIRECT("$AI$14"))+1),ROW(INDIRECT("A" & AB16 ) ))),"")}
AB17: =ROW(A17)- $AD$2 +1 -> 4 | AC17: =IF(AND(OR($E17="Contrôlé",$E17="Non contrôlé"),$M17="Préleveur"),$F17,"") | AD17: {=IFERROR(INDEX($AC$14:$AC$102,SMALL(IF($AC$14:$AC$102<>"",ROW($AC$14:$AC$102)-ROW(INDIRECT("$AC$14"))+1),ROW(INDIRECT("A" & AB17 ) ))),"")} | AE17: =IF(AND(OR($E17="Contrôlé",$E17="Non contrôlé"),LEFT($M17,10) ="Débitmètre"),$F17,"") | AF17: {=IFERROR(INDEX($AE$14:$AE$102,SMALL(IF($AE$14:$AE$102<>"",ROW($AE$14:$AE$102)-ROW(INDIRECT("$AE$14"))+1),ROW(INDIRECT("A" & AB17 ) ))),"")} | AG17: =IF(AND(OR($E17="Contrôlé",$E17="Non contrôlé"),LEFT($M17,5) ="Sonde"),$F17,"") | AH17: {=IFERROR(INDEX($AG$14:$AG$102,SMALL(IF($AG$14:$AG$102<>"",ROW($AG$14:$AG$102)-ROW(INDIRECT("$AG$14"))+1),ROW(INDIRECT("A" & AB17 ) ))),"")} | AI17: =IF(AND(OR($E17="Contrôlé",$E17="Non contrôlé"), $F17 <> "", $M17 = ""),$F17,"") | AJ17: {=IFERROR(INDEX($AI$14:$AI$102,SMALL(IF($AI$14:$AI$102<>"",ROW($AI$14:$AI$102)-ROW(INDIRECT("$AI$14"))+1),ROW(INDIRECT("A" & AB17 ) ))),"")}
AB18: =ROW(A18)- $AD$2 +1 -> 5 | AC18: =IF(AND(OR($E18="Contrôlé",$E18="Non contrôlé"),$M18="Préleveur"),$F18,"") | AD18: {=IFERROR(INDEX($AC$14:$AC$102,SMALL(IF($AC$14:$AC$102<>"",ROW($AC$14:$AC$102)-ROW(INDIRECT("$AC$14"))+1),ROW(INDIRECT("A" & AB18 ) ))),"")} | AE18: =IF(AND(OR($E18="Contrôlé",$E18="Non contrôlé"),LEFT($M18,10) ="Débitmètre"),$F18,"") | AF18: {=IFERROR(INDEX($AE$14:$AE$102,SMALL(IF($AE$14:$AE$102<>"",ROW($AE$14:$AE$102)-ROW(INDIRECT("$AE$14"))+1),ROW(INDIRECT("A" & AB18 ) ))),"")} | AG18: =IF(AND(OR($E18="Contrôlé",$E18="Non contrôlé"),LEFT($M18,5) ="Sonde"),$F18,"") | AH18: {=IFERROR(INDEX($AG$14:$AG$102,SMALL(IF($AG$14:$AG$102<>"",ROW($AG$14:$AG$102)-ROW(INDIRECT("$AG$14"))+1),ROW(INDIRECT("A" & AB18 ) ))),"")} | AI18: =IF(AND(OR($E18="Contrôlé",$E18="Non contrôlé"), $F18 <> "", $M18 = ""),$F18,"") | AJ18: {=IFERROR(INDEX($AI$14:$AI$102,SMALL(IF($AI$14:$AI$102<>"",ROW($AI$14:$AI$102)-ROW(INDIRECT("$AI$14"))+1),ROW(INDIRECT("A" & AB18 ) ))),"")}
AB19: =ROW(A19)- $AD$2 +1 -> 6 | AC19: =IF(AND(OR($E19="Contrôlé",$E19="Non contrôlé"),$M19="Préleveur"),$F19,"") | AD19: {=IFERROR(INDEX($AC$14:$AC$102,SMALL(IF($AC$14:$AC$102<>"",ROW($AC$14:$AC$102)-ROW(INDIRECT("$AC$14"))+1),ROW(INDIRECT("A" & AB19 ) ))),"")} | AE19: =IF(AND(OR($E19="Contrôlé",$E19="Non contrôlé"),LEFT($M19,10) ="Débitmètre"),$F19,"") | AF19: {=IFERROR(INDEX($AE$14:$AE$102,SMALL(IF($AE$14:$AE$102<>"",ROW($AE$14:$AE$102)-ROW(INDIRECT("$AE$14"))+1),ROW(INDIRECT("A" & AB19 ) ))),"")} | AG19: =IF(AND(OR($E19="Contrôlé",$E19="Non contrôlé"),LEFT($M19,5) ="Sonde"),$F19,"") | AH19: {=IFERROR(INDEX($AG$14:$AG$102,SMALL(IF($AG$14:$AG$102<>"",ROW($AG$14:$AG$102)-ROW(INDIRECT("$AG$14"))+1),ROW(INDIRECT("A" & AB19 ) ))),"")} | AI19: =IF(AND(OR($E19="Contrôlé",$E19="Non contrôlé"), $F19 <> "", $M19 = ""),$F19,"") | AJ19: {=IFERROR(INDEX($AI$14:$AI$102,SMALL(IF($AI$14:$AI$102<>"",ROW($AI$14:$AI$102)-ROW(INDIRECT("$AI$14"))+1),ROW(INDIRECT("A" & AB19 ) ))),"")}
D20: Liste des pluviomètres de référence du réseau | AB20: =ROW(A20)- $AD$2 +1 -> 7 | AC20: =IF(AND(OR($E20="Contrôlé",$E20="Non contrôlé"),$M20="Préleveur"),$F20,"") | AD20: {=IFERROR(INDEX($AC$14:$AC$102,SMALL(IF($AC$14:$AC$102<>"",ROW($AC$14:$AC$102)-ROW(INDIRECT("$AC$14"))+1),ROW(INDIRECT("A" & AB20 ) ))),"")} | AE20: =IF(AND(OR($E20="Contrôlé",$E20="Non contrôlé"),LEFT($M20,10) ="Débitmètre"),$F20,"") | AF20: {=IFERROR(INDEX($AE$14:$AE$102,SMALL(IF($AE$14:$AE$102<>"",ROW($AE$14:$AE$102)-ROW(INDIRECT("$AE$14"))+1),ROW(INDIRECT("A" & AB20 ) ))),"")} | AG20: =IF(AND(OR($E20="Contrôlé",$E20="Non contrôlé"),LEFT($M20,5) ="Sonde"),$F20,"") | AH20: {=IFERROR(INDEX($AG$14:$AG$102,SMALL(IF($AG$14:$AG$102<>"",ROW($AG$14:$AG$102)-ROW(INDIRECT("$AG$14"))+1),ROW(INDIRECT("A" & AB20 ) ))),"")} | AI20: =IF(AND(OR($E20="Contrôlé",$E20="Non contrôlé"), $F20 <> "", $M20 = ""),$F20,"") | AJ20: {=IFERROR(INDEX($AI$14:$AI$102,SMALL(IF($AI$14:$AI$102<>"",ROW($AI$14:$AI$102)-ROW(INDIRECT("$AI$14"))+1),ROW(INDIRECT("A" & AB20 ) ))),"")}
AB21: =ROW(A21)- $AD$2 +1 -> 8 | AC21: =IF(AND(OR($E21="Contrôlé",$E21="Non contrôlé"),$M21="Préleveur"),$F21,"") | AD21: {=IFERROR(INDEX($AC$14:$AC$102,SMALL(IF($AC$14:$AC$102<>"",ROW($AC$14:$AC$102)-ROW(INDIRECT("$AC$14"))+1),ROW(INDIRECT("A" & AB21 ) ))),"")} | AE21: =IF(AND(OR($E21="Contrôlé",$E21="Non contrôlé"),LEFT($M21,10) ="Débitmètre"),$F21,"") | AF21: {=IFERROR(INDEX($AE$14:$AE$102,SMALL(IF($AE$14:$AE$102<>"",ROW($AE$14:$AE$102)-ROW(INDIRECT("$AE$14"))+1),ROW(INDIRECT("A" & AB21 ) ))),"")} | AG21: =IF(AND(OR($E21="Contrôlé",$E21="Non contrôlé"),LEFT($M21,5) ="Sonde"),$F21,"") | AH21: {=IFERROR(INDEX($AG$14:$AG$102,SMALL(IF($AG$14:$AG$102<>"",ROW($AG$14:$AG$102)-ROW(INDIRECT("$AG$14"))+1),ROW(INDIRECT("A" & AB21 ) ))),"")} | AI21: =IF(AND(OR($E21="Contrôlé",$E21="Non contrôlé"), $F21 <> "", $M21 = ""),$F21,"") | AJ21: {=IFERROR(INDEX($AI$14:$AI$102,SMALL(IF($AI$14:$AI$102<>"",ROW($AI$14:$AI$102)-ROW(INDIRECT("$AI$14"))+1),ROW(INDIRECT("A" & AB21 ) ))),"")}
E22: Statut | F22: Lien vers l'onglet de l'équipement | AB22: =ROW(A22)- $AD$2 +1 -> 9 | AC22: =IF(AND(OR($E22="Contrôlé",$E22="Non contrôlé"),$M22="Préleveur"),$F22,"") | AD22: {=IFERROR(INDEX($AC$14:$AC$102,SMALL(IF($AC$14:$AC$102<>"",ROW($AC$14:$AC$102)-ROW(INDIRECT("$AC$14"))+1),ROW(INDIRECT("A" & AB22 ) ))),"")} | AE22: =IF(AND(OR($E22="Contrôlé",$E22="Non contrôlé"),LEFT($M22,10) ="Débitmètre"),$F22,"") | AF22: {=IFERROR(INDEX($AE$14:$AE$102,SMALL(IF($AE$14:$AE$102<>"",ROW($AE$14:$AE$102)-ROW(INDIRECT("$AE$14"))+1),ROW(INDIRECT("A" & AB22 ) ))),"")} | AG22: =IF(AND(OR($E22="Contrôlé",$E22="Non contrôlé"),LEFT($M22,5) ="Sonde"),$F22,"") | AH22: {=IFERROR(INDEX($AG$14:$AG$102,SMALL(IF($AG$14:$AG$102<>"",ROW($AG$14:$AG$102)-ROW(INDIRECT("$AG$14"))+1),ROW(INDIRECT("A" & AB22 ) ))),"")} | AI22: =IF(AND(OR($E22="Contrôlé",$E22="Non contrôlé"), $F22 <> "", $M22 = ""),$F22,"") | AJ22: {=IFERROR(INDEX($AI$14:$AI$102,SMALL(IF($AI$14:$AI$102<>"",ROW($AI$14:$AI$102)-ROW(INDIRECT("$AI$14"))+1),ROW(INDIRECT("A" & AB22 ) ))),"")}
AB23: =ROW(A23)- $AD$2 +1 -> 10 | AC23: =IF(AND(OR($E23="Contrôlé",$E23="Non contrôlé"),$M23="Préleveur"),$F23,"") | AD23: {=IFERROR(INDEX($AC$14:$AC$102,SMALL(IF($AC$14:$AC$102<>"",ROW($AC$14:$AC$102)-ROW(INDIRECT("$AC$14"))+1),ROW(INDIRECT("A" & AB23 ) ))),"")} | AE23: =IF(AND(OR($E23="Contrôlé",$E23="Non contrôlé"),LEFT($M23,10) ="Débitmètre"),$F23,"") | AF23: {=IFERROR(INDEX($AE$14:$AE$102,SMALL(IF($AE$14:$AE$102<>"",ROW($AE$14:$AE$102)-ROW(INDIRECT("$AE$14"))+1),ROW(INDIRECT("A" & AB23 ) ))),"")} | AG23: =IF(AND(OR($E23="Contrôlé",$E23="Non contrôlé"),LEFT($M23,5) ="Sonde"),$F23,"") | AH23: {=IFERROR(INDEX($AG$14:$AG$102,SMALL(IF($AG$14:$AG$102<>"",ROW($AG$14:$AG$102)-ROW(INDIRECT("$AG$14"))+1),ROW(INDIRECT("A" & AB23 ) ))),"")} | AI23: =IF(AND(OR($E23="Contrôlé",$E23="Non contrôlé"), $F23 <> "", $M23 = ""),$F23,"") | AJ23: {=IFERROR(INDEX($AI$14:$AI$102,SMALL(IF($AI$14:$AI$102<>"",ROW($AI$14:$AI$102)-ROW(INDIRECT("$AI$14"))+1),ROW(INDIRECT("A" & AB23 ) ))),"")}
E24: Ajouter un pluviomètre réseau | K24: Si pas de pluviomètre, veuillez ajouter en commentaire la provenance des données : | AB24: =ROW(A24)- $AD$2 +1 -> 11 | AC24: =IF(AND(OR($E24="Contrôlé",$E24="Non contrôlé"),$M24="Préleveur"),$F24,"") | AD24: {=IFERROR(INDEX($AC$14:$AC$102,SMALL(IF($AC$14:$AC$102<>"",ROW($AC$14:$AC$102)-ROW(INDIRECT("$AC$14"))+1),ROW(INDIRECT("A" & AB24 ) ))),"")} | AE24: =IF(AND(OR($E24="Contrôlé",$E24="Non contrôlé"),LEFT($M24,10) ="Débitmètre"),$F24,"") | AF24: {=IFERROR(INDEX($AE$14:$AE$102,SMALL(IF($AE$14:$AE$102<>"",ROW($AE$14:$AE$102)-ROW(INDIRECT("$AE$14"))+1),ROW(INDIRECT("A" & AB24 ) ))),"")} | AG24: =IF(AND(OR($E24="Contrôlé",$E24="Non contrôlé"),LEFT($M24,5) ="Sonde"),$F24,"") | AH24: {=IFERROR(INDEX($AG$14:$AG$102,SMALL(IF($AG$14:$AG$102<>"",ROW($AG$14:$AG$102)-ROW(INDIRECT("$AG$14"))+1),ROW(INDIRECT("A" & AB24 ) ))),"")} | AI24: =IF(AND(OR($E24="Contrôlé",$E24="Non contrôlé"), $F24 <> "", $M24 = ""),$F24,"") | AJ24: {=IFERROR(INDEX($AI$14:$AI$102,SMALL(IF($AI$14:$AI$102<>"",ROW($AI$14:$AI$102)-ROW(INDIRECT("$AI$14"))+1),ROW(INDIRECT("A" & AB24 ) ))),"")}
AB25: =ROW(A25)- $AD$2 +1 -> 12 | AC25: =IF(AND(OR($E25="Contrôlé",$E25="Non contrôlé"),$M25="Préleveur"),$F25,"") | AD25: {=IFERROR(INDEX($AC$14:$AC$102,SMALL(IF($AC$14:$AC$102<>"",ROW($AC$14:$AC$102)-ROW(INDIRECT("$AC$14"))+1),ROW(INDIRECT("A" & AB25 ) ))),"")} | AE25: =IF(AND(OR($E25="Contrôlé",$E25="Non contrôlé"),LEFT($M25,10) ="Débitmètre"),$F25,"") | AF25: {=IFERROR(INDEX($AE$14:$AE$102,SMALL(IF($AE$14:$AE$102<>"",ROW($AE$14:$AE$102)-ROW(INDIRECT("$AE$14"))+1),ROW(INDIRECT("A" & AB25 ) ))),"")} | AG25: =IF(AND(OR($E25="Contrôlé",$E25="Non contrôlé"),LEFT($M25,5) ="Sonde"),$F25,"") | AH25: {=IFERROR(INDEX($AG$14:$AG$102,SMALL(IF($AG$14:$AG$102<>"",ROW($AG$14:$AG$102)-ROW(INDIRECT("$AG$14"))+1),ROW(INDIRECT("A" & AB25 ) ))),"")} | AI25: =IF(AND(OR($E25="Contrôlé",$E25="Non contrôlé"), $F25 <> "", $M25 = ""),$F25,"") | AJ25: {=IFERROR(INDEX($AI$14:$AI$102,SMALL(IF($AI$14:$AI$102<>"",ROW($AI$14:$AI$102)-ROW(INDIRECT("$AI$14"))+1),ROW(INDIRECT("A" & AB25 ) ))),"")}
AB26: =ROW(A26)- $AD$2 +1 -> 13 | AC26: =IF(AND(OR($E26="Contrôlé",$E26="Non contrôlé"),$M26="Préleveur"),$F26,"") | AD26: {=IFERROR(INDEX($AC$14:$AC$102,SMALL(IF($AC$14:$AC$102<>"",ROW($AC$14:$AC$102)-ROW(INDIRECT("$AC$14"))+1),ROW(INDIRECT("A" & AB26 ) ))),"")} | AE26: =IF(AND(OR($E26="Contrôlé",$E26="Non contrôlé"),LEFT($M26,10) ="Débitmètre"),$F26,"") | AF26: {=IFERROR(INDEX($AE$14:$AE$102,SMALL(IF($AE$14:$AE$102<>"",ROW($AE$14:$AE$102)-ROW(INDIRECT("$AE$14"))+1),ROW(INDIRECT("A" & AB26 ) ))),"")} | AG26: =IF(AND(OR($E26="Contrôlé",$E26="Non contrôlé"),LEFT($M26,5) ="Sonde"),$F26,"") | AH26: {=IFERROR(INDEX($AG$14:$AG$102,SMALL(IF($AG$14:$AG$102<>"",ROW($AG$14:$AG$102)-ROW(INDIRECT("$AG$14"))+1),ROW(INDIRECT("A" & AB26 ) ))),"")} | AI26: =IF(AND(OR($E26="Contrôlé",$E26="Non contrôlé"), $F26 <> "", $M26 = ""),$F26,"") | AJ26: {=IFERROR(INDEX($AI$14:$AI$102,SMALL(IF($AI$14:$AI$102<>"",ROW($AI$14:$AI$102)-ROW(INDIRECT("$AI$14"))+1),ROW(INDIRECT("A" & AB26 ) ))),"")}
AB27: =ROW(A27)- $AD$2 +1 -> 14 | AC27: =IF(AND(OR($E27="Contrôlé",$E27="Non contrôlé"),$M27="Préleveur"),$F27,"") | AD27: {=IFERROR(INDEX($AC$14:$AC$102,SMALL(IF($AC$14:$AC$102<>"",ROW($AC$14:$AC$102)-ROW(INDIRECT("$AC$14"))+1),ROW(INDIRECT("A" & AB27 ) ))),"")} | AE27: =IF(AND(OR($E27="Contrôlé",$E27="Non contrôlé"),LEFT($M27,10) ="Débitmètre"),$F27,"") | AF27: {=IFERROR(INDEX($AE$14:$AE$102,SMALL(IF($AE$14:$AE$102<>"",ROW($AE$14:$AE$102)-ROW(INDIRECT("$AE$14"))+1),ROW(INDIRECT("A" & AB27 ) ))),"")} | AG27: =IF(AND(OR($E27="Contrôlé",$E27="Non contrôlé"),LEFT($M27,5) ="Sonde"),$F27,"") | AH27: {=IFERROR(INDEX($AG$14:$AG$102,SMALL(IF($AG$14:$AG$102<>"",ROW($AG$14:$AG$102)-ROW(INDIRECT("$AG$14"))+1),ROW(INDIRECT("A" & AB27 ) ))),"")} | AI27: =IF(AND(OR($E27="Contrôlé",$E27="Non contrôlé"), $F27 <> "", $M27 = ""),$F27,"") | AJ27: {=IFERROR(INDEX($AI$14:$AI$102,SMALL(IF($AI$14:$AI$102<>"",ROW($AI$14:$AI$102)-ROW(INDIRECT("$AI$14"))+1),ROW(INDIRECT("A" & AB27 ) ))),"")}
AB28: =ROW(A28)- $AD$2 +1 -> 15 | AC28: =IF(AND(OR($E28="Contrôlé",$E28="Non contrôlé"),$M28="Préleveur"),$F28,"") | AD28: {=IFERROR(INDEX($AC$14:$AC$102,SMALL(IF($AC$14:$AC$102<>"",ROW($AC$14:$AC$102)-ROW(INDIRECT("$AC$14"))+1),ROW(INDIRECT("A" & AB28 ) ))),"")} | AE28: =IF(AND(OR($E28="Contrôlé",$E28="Non contrôlé"),LEFT($M28,10) ="Débitmètre"),$F28,"") | AF28: {=IFERROR(INDEX($AE$14:$AE$102,SMALL(IF($AE$14:$AE$102<>"",ROW($AE$14:$AE$102)-ROW(INDIRECT("$AE$14"))+1),ROW(INDIRECT("A" & AB28 ) ))),"")} | AG28: =IF(AND(OR($E28="Contrôlé",$E28="Non contrôlé"),LEFT($M28,5) ="Sonde"),$F28,"") | AH28: {=IFERROR(INDEX($AG$14:$AG$102,SMALL(IF($AG$14:$AG$102<>"",ROW($AG$14:$AG$102)-ROW(INDIRECT("$AG$14"))+1),ROW(INDIRECT("A" & AB28 ) ))),"")} | AI28: =IF(AND(OR($E28="Contrôlé",$E28="Non contrôlé"), $F28 <> "", $M28 = ""),$F28,"") | AJ28: {=IFERROR(INDEX($AI$14:$AI$102,SMALL(IF($AI$14:$AI$102<>"",ROW($AI$14:$AI$102)-ROW(INDIRECT("$AI$14"))+1),ROW(INDIRECT("A" & AB28 ) ))),"")}
C29: SYSTÈME DE TRAITEMENT | AB29: =ROW(A29)- $AD$2 +1 -> 16 | AC29: =IF(AND(OR($E29="Contrôlé",$E29="Non contrôlé"),$M29="Préleveur"),$F29,"") | AD29: {=IFERROR(INDEX($AC$14:$AC$102,SMALL(IF($AC$14:$AC$102<>"",ROW($AC$14:$AC$102)-ROW(INDIRECT("$AC$14"))+1),ROW(INDIRECT("A" & AB29 ) ))),"")} | AE29: =IF(AND(OR($E29="Contrôlé",$E29="Non contrôlé"),LEFT($M29,10) ="Débitmètre"),$F29,"") | AF29: {=IFERROR(INDEX($AE$14:$AE$102,SMALL(IF($AE$14:$AE$102<>"",ROW($AE$14:$AE$102)-ROW(INDIRECT("$AE$14"))+1),ROW(INDIRECT("A" & AB29 ) ))),"")} | AG29: =IF(AND(OR($E29="Contrôlé",$E29="Non contrôlé"),LEFT($M29,5) ="Sonde"),$F29,"") | AH29: {=IFERROR(INDEX($AG$14:$AG$102,SMALL(IF($AG$14:$AG$102<>"",ROW($AG$14:$AG$102)-ROW(INDIRECT("$AG$14"))+1),ROW(INDIRECT("A" & AB29 ) ))),"")} | AI29: =IF(AND(OR($E29="Contrôlé",$E29="Non contrôlé"), $F29 <> "", $M29 = ""),$F29,"") | AJ29: {=IFERROR(INDEX($AI$14:$AI$102,SMALL(IF($AI$14:$AI$102<>"",ROW($AI$14:$AI$102)-ROW(INDIRECT("$AI$14"))+1),ROW(INDIRECT("A" & AB29 ) ))),"")}
D30: Remarques : | E30: Les estimations et les apports par camion ne rentrent pas dans le CDA | AB30: =ROW(A30)- $AD$2 +1 -> 17 | AC30: =IF(AND(OR($E30="Contrôlé",$E30="Non contrôlé"),$M30="Préleveur"),$F30,"") | AD30: {=IFERROR(INDEX($AC$14:$AC$102,SMALL(IF($AC$14:$AC$102<>"",ROW($AC$14:$AC$102)-ROW(INDIRECT("$AC$14"))+1),ROW(INDIRECT("A" & AB30 ) ))),"")} | AE30: =IF(AND(OR($E30="Contrôlé",$E30="Non contrôlé"),LEFT($M30,10) ="Débitmètre"),$F30,"") | AF30: {=IFERROR(INDEX($AE$14:$AE$102,SMALL(IF($AE$14:$AE$102<>"",ROW($AE$14:$AE$102)-ROW(INDIRECT("$AE$14"))+1),ROW(INDIRECT("A" & AB30 ) ))),"")} | AG30: =IF(AND(OR($E30="Contrôlé",$E30="Non contrôlé"),LEFT($M30,5) ="Sonde"),$F30,"") | AH30: {=IFERROR(INDEX($AG$14:$AG$102,SMALL(IF($AG$14:$AG$102<>"",ROW($AG$14:$AG$102)-ROW(INDIRECT("$AG$14"))+1),ROW(INDIRECT("A" & AB30 ) ))),"")} | AI30: =IF(AND(OR($E30="Contrôlé",$E30="Non contrôlé"), $F30 <> "", $M30 = ""),$F30,"") | AJ30: {=IFERROR(INDEX($AI$14:$AI$102,SMALL(IF($AI$14:$AI$102<>"",ROW($AI$14:$AI$102)-ROW(INDIRECT("$AI$14"))+1),ROW(INDIRECT("A" & AB30 ) ))),"")}
D31: Liste des équipements du système de traitement pour chaque point d’autosurveillance | AB31: =ROW(A31)- $AD$2 +1 -> 18 | AC31: =IF(AND(OR($E31="Contrôlé",$E31="Non contrôlé"),$M31="Préleveur"),$F31,"") | AD31: {=IFERROR(INDEX($AC$14:$AC$102,SMALL(IF($AC$14:$AC$102<>"",ROW($AC$14:$AC$102)-ROW(INDIRECT("$AC$14"))+1),ROW(INDIRECT("A" & AB31 ) ))),"")} | AE31: =IF(AND(OR($E31="Contrôlé",$E31="Non contrôlé"),LEFT($M31,10) ="Débitmètre"),$F31,"") | AF31: {=IFERROR(INDEX($AE$14:$AE$102,SMALL(IF($AE$14:$AE$102<>"",ROW($AE$14:$AE$102)-ROW(INDIRECT("$AE$14"))+1),ROW(INDIRECT("A" & AB31 ) ))),"")} | AG31: =IF(AND(OR($E31="Contrôlé",$E31="Non contrôlé"),LEFT($M31,5) ="Sonde"),$F31,"") | AH31: {=IFERROR(INDEX($AG$14:$AG$102,SMALL(IF($AG$14:$AG$102<>"",ROW($AG$14:$AG$102)-ROW(INDIRECT("$AG$14"))+1),ROW(INDIRECT("A" & AB31 ) ))),"")} | AI31: =IF(AND(OR($E31="Contrôlé",$E31="Non contrôlé"), $F31 <> "", $M31 = ""),$F31,"") | AJ31: {=IFERROR(INDEX($AI$14:$AI$102,SMALL(IF($AI$14:$AI$102<>"",ROW($AI$14:$AI$102)-ROW(INDIRECT("$AI$14"))+1),ROW(INDIRECT("A" & AB31 ) ))),"")}
AB32: =ROW(A32)- $AD$2 +1 -> 19 | AC32: =IF(AND(OR($E32="Contrôlé",$E32="Non contrôlé"),$M32="Préleveur"),$F32,"") | AD32: {=IFERROR(INDEX($AC$14:$AC$102,SMALL(IF($AC$14:$AC$102<>"",ROW($AC$14:$AC$102)-ROW(INDIRECT("$AC$14"))+1),ROW(INDIRECT("A" & AB32 ) ))),"")} | AE32: =IF(AND(OR($E32="Contrôlé",$E32="Non contrôlé"),LEFT($M32,10) ="Débitmètre"),$F32,"") | AF32: {=IFERROR(INDEX($AE$14:$AE$102,SMALL(IF($AE$14:$AE$102<>"",ROW($AE$14:$AE$102)-ROW(INDIRECT("$AE$14"))+1),ROW(INDIRECT("A" & AB32 ) ))),"")} | AG32: =IF(AND(OR($E32="Contrôlé",$E32="Non contrôlé"),LEFT($M32,5) ="Sonde"),$F32,"") | AH32: {=IFERROR(INDEX($AG$14:$AG$102,SMALL(IF($AG$14:$AG$102<>"",ROW($AG$14:$AG$102)-ROW(INDIRECT("$AG$14"))+1),ROW(INDIRECT("A" & AB32 ) ))),"")} | AI32: =IF(AND(OR($E32="Contrôlé",$E32="Non contrôlé"), $F32 <> "", $M32 = ""),$F32,"") | AJ32: {=IFERROR(INDEX($AI$14:$AI$102,SMALL(IF($AI$14:$AI$102<>"",ROW($AI$14:$AI$102)-ROW(INDIRECT("$AI$14"))+1),ROW(INDIRECT("A" & AB32 ) ))),"")}
E33: Statut | F33: Lien vers l'onglet de l'équipement | H33: Point réglementaire | I33: Localisation (cf. MAS) | J33: Code du point (cf MAS) | K33: Libellé de l'équipement | M33: Type d'équipement | O33: Type de matériel | R33: Certaines informations d'un équipement ne sont pas modifiables. Au besoin il est préférable de supprimer et de recréer l'équipement. | AB33: =ROW(A33)- $AD$2 +1 -> 20 | AC33: =IF(AND(OR($E33="Contrôlé",$E33="Non contrôlé"),$M33="Préleveur"),$F33,"") | AD33: {=IFERROR(INDEX($AC$14:$AC$102,SMALL(IF($AC$14:$AC$102<>"",ROW($AC$14:$AC$102)-ROW(INDIRECT("$AC$14"))+1),ROW(INDIRECT("A" & AB33 ) ))),"")} | AE33: =IF(AND(OR($E33="Contrôlé",$E33="Non contrôlé"),LEFT($M33,10) ="Débitmètre"),$F33,"") | AF33: {=IFERROR(INDEX($AE$14:$AE$102,SMALL(IF($AE$14:$AE$102<>"",ROW($AE$14:$AE$102)-ROW(INDIRECT("$AE$14"))+1),ROW(INDIRECT("A" & AB33 ) ))),"")} | AG33: =IF(AND(OR($E33="Contrôlé",$E33="Non contrôlé"),LEFT($M33,5) ="Sonde"),$F33,"") | AH33: {=IFERROR(INDEX($AG$14:$AG$102,SMALL(IF($AG$14:$AG$102<>"",ROW($AG$14:$AG$102)-ROW(INDIRECT("$AG$14"))+1),ROW(INDIRECT("A" & AB33 ) ))),"")} | AI33: =IF(AND(OR($E33="Contrôlé",$E33="Non contrôlé"), $F33 <> "", $M33 = ""),$F33,"") | AJ33: {=IFERROR(INDEX($AI$14:$AI$102,SMALL(IF($AI$14:$AI$102<>"",ROW($AI$14:$AI$102)-ROW(INDIRECT("$AI$14"))+1),ROW(INDIRECT("A" & AB33 ) ))),"")}
AB34: =ROW(A34)- $AD$2 +1 -> 21 | AC34: =IF(AND(OR($E34="Contrôlé",$E34="Non contrôlé"),$M34="Préleveur"),$F34,"") | AD34: {=IFERROR(INDEX($AC$14:$AC$102,SMALL(IF($AC$14:$AC$102<>"",ROW($AC$14:$AC$102)-ROW(INDIRECT("$AC$14"))+1),ROW(INDIRECT("A" & AB34 ) ))),"")} | AE34: =IF(AND(OR($E34="Contrôlé",$E34="Non contrôlé"),LEFT($M34,10) ="Débitmètre"),$F34,"") | AF34: {=IFERROR(INDEX($AE$14:$AE$102,SMALL(IF($AE$14:$AE$102<>"",ROW($AE$14:$AE$102)-ROW(INDIRECT("$AE$14"))+1),ROW(INDIRECT("A" & AB34 ) ))),"")} | AG34: =IF(AND(OR($E34="Contrôlé",$E34="Non contrôlé"),LEFT($M34,5) ="Sonde"),$F34,"") | AH34: {=IFERROR(INDEX($AG$14:$AG$102,SMALL(IF($AG$14:$AG$102<>"",ROW($AG$14:$AG$102)-ROW(INDIRECT("$AG$14"))+1),ROW(INDIRECT("A" & AB34 ) ))),"")} | AI34: =IF(AND(OR($E34="Contrôlé",$E34="Non contrôlé"), $F34 <> "", $M34 = ""),$F34,"") | AJ34: {=IFERROR(INDEX($AI$14:$AI$102,SMALL(IF($AI$14:$AI$102<>"",ROW($AI$14:$AI$102)-ROW(INDIRECT("$AI$14"))+1),ROW(INDIRECT("A" & AB34 ) ))),"")}
E35: Ajouter un équipement station | K35: Si certains points ne sont pas équipés, veuillez les indiquer en commentaire : | AB35: =ROW(A35)- $AD$2 +1 -> 22 | AC35: =IF(AND(OR($E35="Contrôlé",$E35="Non contrôlé"),$M35="Préleveur"),$F35,"") | AD35: {=IFERROR(INDEX($AC$14:$AC$102,SMALL(IF($AC$14:$AC$102<>"",ROW($AC$14:$AC$102)-ROW(INDIRECT("$AC$14"))+1),ROW(INDIRECT("A" & AB35 ) ))),"")} | AE35: =IF(AND(OR($E35="Contrôlé",$E35="Non contrôlé"),LEFT($M35,10) ="Débitmètre"),$F35,"") | AF35: {=IFERROR(INDEX($AE$14:$AE$102,SMALL(IF($AE$14:$AE$102<>"",ROW($AE$14:$AE$102)-ROW(INDIRECT("$AE$14"))+1),ROW(INDIRECT("A" & AB35 ) ))),"")} | AG35: =IF(AND(OR($E35="Contrôlé",$E35="Non contrôlé"),LEFT($M35,5) ="Sonde"),$F35,"") | AH35: {=IFERROR(INDEX($AG$14:$AG$102,SMALL(IF($AG$14:$AG$102<>"",ROW($AG$14:$AG$102)-ROW(INDIRECT("$AG$14"))+1),ROW(INDIRECT("A" & AB35 ) ))),"")} | AI35: =IF(AND(OR($E35="Contrôlé",$E35="Non contrôlé"), $F35 <> "", $M35 = ""),$F35,"") | AJ35: {=IFERROR(INDEX($AI$14:$AI$102,SMALL(IF($AI$14:$AI$102<>"",ROW($AI$14:$AI$102)-ROW(INDIRECT("$AI$14"))+1),ROW(INDIRECT("A" & AB35 ) ))),"")}
AB36: =ROW(A36)- $AD$2 +1 -> 23 | AC36: =IF(AND(OR($E36="Contrôlé",$E36="Non contrôlé"),$M36="Préleveur"),$F36,"") | AD36: {=IFERROR(INDEX($AC$14:$AC$102,SMALL(IF($AC$14:$AC$102<>"",ROW($AC$14:$AC$102)-ROW(INDIRECT("$AC$14"))+1),ROW(INDIRECT("A" & AB36 ) ))),"")} | AE36: =IF(AND(OR($E36="Contrôlé",$E36="Non contrôlé"),LEFT($M36,10) ="Débitmètre"),$F36,"") | AF36: {=IFERROR(INDEX($AE$14:$AE$102,SMALL(IF($AE$14:$AE$102<>"",ROW($AE$14:$AE$102)-ROW(INDIRECT("$AE$14"))+1),ROW(INDIRECT("A" & AB36 ) ))),"")} | AG36: =IF(AND(OR($E36="Contrôlé",$E36="Non contrôlé"),LEFT($M36,5) ="Sonde"),$F36,"") | AH36: {=IFERROR(INDEX($AG$14:$AG$102,SMALL(IF($AG$14:$AG$102<>"",ROW($AG$14:$AG$102)-ROW(INDIRECT("$AG$14"))+1),ROW(INDIRECT("A" & AB36 ) ))),"")} | AI36: =IF(AND(OR($E36="Contrôlé",$E36="Non contrôlé"), $F36 <> "", $M36 = ""),$F36,"") | AJ36: {=IFERROR(INDEX($AI$14:$AI$102,SMALL(IF($AI$14:$AI$102<>"",ROW($AI$14:$AI$102)-ROW(INDIRECT("$AI$14"))+1),ROW(INDIRECT("A" & AB36 ) ))),"")}
AB37: =ROW(A37)- $AD$2 +1 -> 24 | AC37: =IF(AND(OR($E37="Contrôlé",$E37="Non contrôlé"),$M37="Préleveur"),$F37,"") | AD37: {=IFERROR(INDEX($AC$14:$AC$102,SMALL(IF($AC$14:$AC$102<>"",ROW($AC$14:$AC$102)-ROW(INDIRECT("$AC$14"))+1),ROW(INDIRECT("A" & AB37 ) ))),"")} | AE37: =IF(AND(OR($E37="Contrôlé",$E37="Non contrôlé"),LEFT($M37,10) ="Débitmètre"),$F37,"") | AF37: {=IFERROR(INDEX($AE$14:$AE$102,SMALL(IF($AE$14:$AE$102<>"",ROW($AE$14:$AE$102)-ROW(INDIRECT("$AE$14"))+1),ROW(INDIRECT("A" & AB37 ) ))),"")} | AG37: =IF(AND(OR($E37="Contrôlé",$E37="Non contrôlé"),LEFT($M37,5) ="Sonde"),$F37,"") | AH37: {=IFERROR(INDEX($AG$14:$AG$102,SMALL(IF($AG$14:$AG$102<>"",ROW($AG$14:$AG$102)-ROW(INDIRECT("$AG$14"))+1),ROW(INDIRECT("A" & AB37 ) ))),"")} | AI37: =IF(AND(OR($E37="Contrôlé",$E37="Non contrôlé"), $F37 <> "", $M37 = ""),$F37,"") | AJ37: {=IFERROR(INDEX($AI$14:$AI$102,SMALL(IF($AI$14:$AI$102<>"",ROW($AI$14:$AI$102)-ROW(INDIRECT("$AI$14"))+1),ROW(INDIRECT("A" & AB37 ) ))),"")}
AB38: =ROW(A38)- $AD$2 +1 -> 25 | AC38: =IF(AND(OR($E38="Contrôlé",$E38="Non contrôlé"),$M38="Préleveur"),$F38,"") | AD38: {=IFERROR(INDEX($AC$14:$AC$102,SMALL(IF($AC$14:$AC$102<>"",ROW($AC$14:$AC$102)-ROW(INDIRECT("$AC$14"))+1),ROW(INDIRECT("A" & AB38 ) ))),"")} | AE38: =IF(AND(OR($E38="Contrôlé",$E38="Non contrôlé"),LEFT($M38,10) ="Débitmètre"),$F38,"") | AF38: {=IFERROR(INDEX($AE$14:$AE$102,SMALL(IF($AE$14:$AE$102<>"",ROW($AE$14:$AE$102)-ROW(INDIRECT("$AE$14"))+1),ROW(INDIRECT("A" & AB38 ) ))),"")} | AG38: =IF(AND(OR($E38="Contrôlé",$E38="Non contrôlé"),LEFT($M38,5) ="Sonde"),$F38,"") | AH38: {=IFERROR(INDEX($AG$14:$AG$102,SMALL(IF($AG$14:$AG$102<>"",ROW($AG$14:$AG$102)-ROW(INDIRECT("$AG$14"))+1),ROW(INDIRECT("A" & AB38 ) ))),"")} | AI38: =IF(AND(OR($E38="Contrôlé",$E38="Non contrôlé"), $F38 <> "", $M38 = ""),$F38,"") | AJ38: {=IFERROR(INDEX($AI$14:$AI$102,SMALL(IF($AI$14:$AI$102<>"",ROW($AI$14:$AI$102)-ROW(INDIRECT("$AI$14"))+1),ROW(INDIRECT("A" & AB38 ) ))),"")}
AB39: =ROW(A39)- $AD$2 +1 -> 26 | AC39: =IF(AND(OR($E39="Contrôlé",$E39="Non contrôlé"),$M39="Préleveur"),$F39,"") | AD39: {=IFERROR(INDEX($AC$14:$AC$102,SMALL(IF($AC$14:$AC$102<>"",ROW($AC$14:$AC$102)-ROW(INDIRECT("$AC$14"))+1),ROW(INDIRECT("A" & AB39 ) ))),"")} | AE39: =IF(AND(OR($E39="Contrôlé",$E39="Non contrôlé"),LEFT($M39,10) ="Débitmètre"),$F39,"") | AF39: {=IFERROR(INDEX($AE$14:$AE$102,SMALL(IF($AE$14:$AE$102<>"",ROW($AE$14:$AE$102)-ROW(INDIRECT("$AE$14"))+1),ROW(INDIRECT("A" & AB39 ) ))),"")} | AG39: =IF(AND(OR($E39="Contrôlé",$E39="Non contrôlé"),LEFT($M39,5) ="Sonde"),$F39,"") | AH39: {=IFERROR(INDEX($AG$14:$AG$102,SMALL(IF($AG$14:$AG$102<>"",ROW($AG$14:$AG$102)-ROW(INDIRECT("$AG$14"))+1),ROW(INDIRECT("A" & AB39 ) ))),"")} | AI39: =IF(AND(OR($E39="Contrôlé",$E39="Non contrôlé"), $F39 <> "", $M39 = ""),$F39,"") | AJ39: {=IFERROR(INDEX($AI$14:$AI$102,SMALL(IF($AI$14:$AI$102<>"",ROW($AI$14:$AI$102)-ROW(INDIRECT("$AI$14"))+1),ROW(INDIRECT("A" & AB39 ) ))),"")}
D40: Liste des pluviomètres de référence de la station | AB40: =ROW(A40)- $AD$2 +1 -> 27 | AC40: =IF(AND(OR($E40="Contrôlé",$E40="Non contrôlé"),$M40="Préleveur"),$F40,"") | AD40: {=IFERROR(INDEX($AC$14:$AC$102,SMALL(IF($AC$14:$AC$102<>"",ROW($AC$14:$AC$102)-ROW(INDIRECT("$AC$14"))+1),ROW(INDIRECT("A" & AB40 ) ))),"")} | AE40: =IF(AND(OR($E40="Contrôlé",$E40="Non contrôlé"),LEFT($M40,10) ="Débitmètre"),$F40,"") | AF40: {=IFERROR(INDEX($AE$14:$AE$102,SMALL(IF($AE$14:$AE$102<>"",ROW($AE$14:$AE$102)-ROW(INDIRECT("$AE$14"))+1),ROW(INDIRECT("A" & AB40 ) ))),"")} | AG40: =IF(AND(OR($E40="Contrôlé",$E40="Non contrôlé"),LEFT($M40,5) ="Sonde"),$F40,"") | AH40: {=IFERROR(INDEX($AG$14:$AG$102,SMALL(IF($AG$14:$AG$102<>"",ROW($AG$14:$AG$102)-ROW(INDIRECT("$AG$14"))+1),ROW(INDIRECT("A" & AB40 ) ))),"")} | AI40: =IF(AND(OR($E40="Contrôlé",$E40="Non contrôlé"), $F40 <> "", $M40 = ""),$F40,"") | AJ40: {=IFERROR(INDEX($AI$14:$AI$102,SMALL(IF($AI$14:$AI$102<>"",ROW($AI$14:$AI$102)-ROW(INDIRECT("$AI$14"))+1),ROW(INDIRECT("A" & AB40 ) ))),"")}
AB41: =ROW(A41)- $AD$2 +1 -> 28 | AC41: =IF(AND(OR($E41="Contrôlé",$E41="Non contrôlé"),$M41="Préleveur"),$F41,"") | AD41: {=IFERROR(INDEX($AC$14:$AC$102,SMALL(IF($AC$14:$AC$102<>"",ROW($AC$14:$AC$102)-ROW(INDIRECT("$AC$14"))+1),ROW(INDIRECT("A" & AB41 ) ))),"")} | AE41: =IF(AND(OR($E41="Contrôlé",$E41="Non contrôlé"),LEFT($M41,10) ="Débitmètre"),$F41,"") | AF41: {=IFERROR(INDEX($AE$14:$AE$102,SMALL(IF($AE$14:$AE$102<>"",ROW($AE$14:$AE$102)-ROW(INDIRECT("$AE$14"))+1),ROW(INDIRECT("A" & AB41 ) ))),"")} | AG41: =IF(AND(OR($E41="Contrôlé",$E41="Non contrôlé"),LEFT($M41,5) ="Sonde"),$F41,"") | AH41: {=IFERROR(INDEX($AG$14:$AG$102,SMALL(IF($AG$14:$AG$102<>"",ROW($AG$14:$AG$102)-ROW(INDIRECT("$AG$14"))+1),ROW(INDIRECT("A" & AB41 ) ))),"")} | AI41: =IF(AND(OR($E41="Contrôlé",$E41="Non contrôlé"), $F41 <> "", $M41 = ""),$F41,"") | AJ41: {=IFERROR(INDEX($AI$14:$AI$102,SMALL(IF($AI$14:$AI$102<>"",ROW($AI$14:$AI$102)-ROW(INDIRECT("$AI$14"))+1),ROW(INDIRECT("A" & AB41 ) ))),"")}
E42: Actif | F42: Lien vers l'onglet de l'équipement | AB42: =ROW(A42)- $AD$2 +1 -> 29 | AC42: =IF(AND(OR($E42="Contrôlé",$E42="Non contrôlé"),$M42="Préleveur"),$F42,"") | AD42: {=IFERROR(INDEX($AC$14:$AC$102,SMALL(IF($AC$14:$AC$102<>"",ROW($AC$14:$AC$102)-ROW(INDIRECT("$AC$14"))+1),ROW(INDIRECT("A" & AB42 ) ))),"")} | AE42: =IF(AND(OR($E42="Contrôlé",$E42="Non contrôlé"),LEFT($M42,10) ="Débitmètre"),$F42,"") | AF42: {=IFERROR(INDEX($AE$14:$AE$102,SMALL(IF($AE$14:$AE$102<>"",ROW($AE$14:$AE$102)-ROW(INDIRECT("$AE$14"))+1),ROW(INDIRECT("A" & AB42 ) ))),"")} | AG42: =IF(AND(OR($E42="Contrôlé",$E42="Non contrôlé"),LEFT($M42,5) ="Sonde"),$F42,"") | AH42: {=IFERROR(INDEX($AG$14:$AG$102,SMALL(IF($AG$14:$AG$102<>"",ROW($AG$14:$AG$102)-ROW(INDIRECT("$AG$14"))+1),ROW(INDIRECT("A" & AB42 ) ))),"")} | AI42: =IF(AND(OR($E42="Contrôlé",$E42="Non contrôlé"), $F42 <> "", $M42 = ""),$F42,"") | AJ42: {=IFERROR(INDEX($AI$14:$AI$102,SMALL(IF($AI$14:$AI$102<>"",ROW($AI$14:$AI$102)-ROW(INDIRECT("$AI$14"))+1),ROW(INDIRECT("A" & AB42 ) ))),"")}
AB43: =ROW(A43)- $AD$2 +1 -> 30 | AC43: =IF(AND(OR($E43="Contrôlé",$E43="Non contrôlé"),$M43="Préleveur"),$F43,"") | AD43: {=IFERROR(INDEX($AC$14:$AC$102,SMALL(IF($AC$14:$AC$102<>"",ROW($AC$14:$AC$102)-ROW(INDIRECT("$AC$14"))+1),ROW(INDIRECT("A" & AB43 ) ))),"")} | AE43: =IF(AND(OR($E43="Contrôlé",$E43="Non contrôlé"),LEFT($M43,10) ="Débitmètre"),$F43,"") | AF43: {=IFERROR(INDEX($AE$14:$AE$102,SMALL(IF($AE$14:$AE$102<>"",ROW($AE$14:$AE$102)-ROW(INDIRECT("$AE$14"))+1),ROW(INDIRECT("A" & AB43 ) ))),"")} | AG43: =IF(AND(OR($E43="Contrôlé",$E43="Non contrôlé"),LEFT($M43,5) ="Sonde"),$F43,"") | AH43: {=IFERROR(INDEX($AG$14:$AG$102,SMALL(IF($AG$14:$AG$102<>"",ROW($AG$14:$AG$102)-ROW(INDIRECT("$AG$14"))+1),ROW(INDIRECT("A" & AB43 ) ))),"")} | AI43: =IF(AND(OR($E43="Contrôlé",$E43="Non contrôlé"), $F43 <> "", $M43 = ""),$F43,"") | AJ43: {=IFERROR(INDEX($AI$14:$AI$102,SMALL(IF($AI$14:$AI$102<>"",ROW($AI$14:$AI$102)-ROW(INDIRECT("$AI$14"))+1),ROW(INDIRECT("A" & AB43 ) ))),"")}
E44: Ajouter un pluviomètre station | K44: Si pas de pluviomètre, veuillez ajouter en commentaire la provenance des données : | AB44: =ROW(A44)- $AD$2 +1 -> 31 | AC44: =IF(AND(OR($E44="Contrôlé",$E44="Non contrôlé"),$M44="Préleveur"),$F44,"") | AD44: {=IFERROR(INDEX($AC$14:$AC$99,SMALL(IF($AC$14:$AC$99<>"",ROW($AC$14:$AC$99)-ROW(INDIRECT("$AC$13"))+1),ROW(INDIRECT("A" & AB44 ) ))),"")} | AE44: =IF(AND(OR($E44="Contrôlé",$E44="Non contrôlé"),LEFT($M44,10) ="Débitmètre"),$F44,"") | AF44: {=IFERROR(INDEX($AE$14:$AE$99,SMALL(IF($AE$14:$AE$99<>"",ROW($AE$14:$AE$99)-ROW(INDIRECT("$AE$13"))+1),ROW(INDIRECT("A" & AB44 ) ))),"")} | AG44: =IF(AND(OR($E44="Contrôlé",$E44="Non contrôlé"),LEFT($M44,5) ="Sonde"),$F44,"") | AH44: {=IFERROR(INDEX($AG$14:$AG$99,SMALL(IF($AG$14:$AG$99<>"",ROW($AG$14:$AG$99)-ROW(INDIRECT("$AG$13"))+1),ROW(INDIRECT("A" & AB44 ) ))),"")} | AI44: =IF(AND(OR($E44="Contrôlé",$E44="Non contrôlé"), $F44 <> "", $M44 = ""),$F44,"") | AJ44: {=IFERROR(INDEX($AI$14:$AI$99,SMALL(IF($AI$14:$AI$99<>"",ROW($AI$14:$AI$99)-ROW(INDIRECT("$AI$13"))+1),ROW(INDIRECT("A" & AB44 ) ))),"")}
AB45: =ROW(A45)- $AD$2 +1 -> 32 | AC45: =IF(AND(OR($E45="Contrôlé",$E45="Non contrôlé"),$M45="Préleveur"),$F45,"") | AD45: {=IFERROR(INDEX($AC$14:$AC$99,SMALL(IF($AC$14:$AC$99<>"",ROW($AC$14:$AC$99)-ROW(INDIRECT("$AC$13"))+1),ROW(INDIRECT("A" & AB45 ) ))),"")} | AE45: =IF(AND(OR($E45="Contrôlé",$E45="Non contrôlé"),LEFT($M45,10) ="Débitmètre"),$F45,"") | AF45: {=IFERROR(INDEX($AE$14:$AE$99,SMALL(IF($AE$14:$AE$99<>"",ROW($AE$14:$AE$99)-ROW(INDIRECT("$AE$13"))+1),ROW(INDIRECT("A" & AB45 ) ))),"")} | AG45: =IF(AND(OR($E45="Contrôlé",$E45="Non contrôlé"),LEFT($M45,5) ="Sonde"),$F45,"") | AH45: {=IFERROR(INDEX($AG$14:$AG$99,SMALL(IF($AG$14:$AG$99<>"",ROW($AG$14:$AG$99)-ROW(INDIRECT("$AG$13"))+1),ROW(INDIRECT("A" & AB45 ) ))),"")} | AI45: =IF(AND(OR($E45="Contrôlé",$E45="Non contrôlé"), $F45 <> "", $M45 = ""),$F45,"") | AJ45: {=IFERROR(INDEX($AI$14:$AI$99,SMALL(IF($AI$14:$AI$99<>"",ROW($AI$14:$AI$99)-ROW(INDIRECT("$AI$13"))+1),ROW(INDIRECT("A" & AB45 ) ))),"")}
AB46: =ROW(A46)- $AD$2 +1 -> 33 | AC46: =IF(AND(OR($E46="Contrôlé",$E46="Non contrôlé"),$M46="Préleveur"),$F46,"") | AD46: {=IFERROR(INDEX($AC$14:$AC$99,SMALL(IF($AC$14:$AC$99<>"",ROW($AC$14:$AC$99)-ROW(INDIRECT("$AC$13"))+1),ROW(INDIRECT("A" & AB46 ) ))),"")} | AE46: =IF(AND(OR($E46="Contrôlé",$E46="Non contrôlé"),LEFT($M46,10) ="Débitmètre"),$F46,"") | AF46: {=IFERROR(INDEX($AE$14:$AE$99,SMALL(IF($AE$14:$AE$99<>"",ROW($AE$14:$AE$99)-ROW(INDIRECT("$AE$13"))+1),ROW(INDIRECT("A" & AB46 ) ))),"")} | AG46: =IF(AND(OR($E46="Contrôlé",$E46="Non contrôlé"),LEFT($M46,5) ="Sonde"),$F46,"") | AH46: {=IFERROR(INDEX($AG$14:$AG$99,SMALL(IF($AG$14:$AG$99<>"",ROW($AG$14:$AG$99)-ROW(INDIRECT("$AG$13"))+1),ROW(INDIRECT("A" & AB46 ) ))),"")} | AI46: =IF(AND(OR($E46="Contrôlé",$E46="Non contrôlé"), $F46 <> "", $M46 = ""),$F46,"") | AJ46: {=IFERROR(INDEX($AI$14:$AI$99,SMALL(IF($AI$14:$AI$99<>"",ROW($AI$14:$AI$99)-ROW(INDIRECT("$AI$13"))+1),ROW(INDIRECT("A" & AB46 ) ))),"")}
AB47: =ROW(A47)- $AD$2 +1 -> 34 | AC47: =IF(AND(OR($E47="Contrôlé",$E47="Non contrôlé"),$M47="Préleveur"),$F47,"") | AD47: {=IFERROR(INDEX($AC$14:$AC$99,SMALL(IF($AC$14:$AC$99<>"",ROW($AC$14:$AC$99)-ROW(INDIRECT("$AC$13"))+1),ROW(INDIRECT("A" & AB47 ) ))),"")} | AE47: =IF(AND(OR($E47="Contrôlé",$E47="Non contrôlé"),LEFT($M47,10) ="Débitmètre"),$F47,"") | AF47: {=IFERROR(INDEX($AE$14:$AE$99,SMALL(IF($AE$14:$AE$99<>"",ROW($AE$14:$AE$99)-ROW(INDIRECT("$AE$13"))+1),ROW(INDIRECT("A" & AB47 ) ))),"")} | AG47: =IF(AND(OR($E47="Contrôlé",$E47="Non contrôlé"),LEFT($M47,5) ="Sonde"),$F47,"") | AH47: {=IFERROR(INDEX($AG$14:$AG$99,SMALL(IF($AG$14:$AG$99<>"",ROW($AG$14:$AG$99)-ROW(INDIRECT("$AG$13"))+1),ROW(INDIRECT("A" & AB47 ) ))),"")} | AI47: =IF(AND(OR($E47="Contrôlé",$E47="Non contrôlé"), $F47 <> "", $M47 = ""),$F47,"") | AJ47: {=IFERROR(INDEX($AI$14:$AI$99,SMALL(IF($AI$14:$AI$99<>"",ROW($AI$14:$AI$99)-ROW(INDIRECT("$AI$13"))+1),ROW(INDIRECT("A" & AB47 ) ))),"")}
AB48: =ROW(A48)- $AD$2 +1 -> 35 | AC48: =IF(AND(OR($E48="Contrôlé",$E48="Non contrôlé"),$M48="Préleveur"),$F48,"") | AD48: {=IFERROR(INDEX($AC$14:$AC$99,SMALL(IF($AC$14:$AC$99<>"",ROW($AC$14:$AC$99)-ROW(INDIRECT("$AC$13"))+1),ROW(INDIRECT("A" & AB48 ) ))),"")} | AE48: =IF(AND(OR($E48="Contrôlé",$E48="Non contrôlé"),LEFT($M48,10) ="Débitmètre"),$F48,"") | AF48: {=IFERROR(INDEX($AE$14:$AE$99,SMALL(IF($AE$14:$AE$99<>"",ROW($AE$14:$AE$99)-ROW(INDIRECT("$AE$13"))+1),ROW(INDIRECT("A" & AB48 ) ))),"")} | AG48: =IF(AND(OR($E48="Contrôlé",$E48="Non contrôlé"),LEFT($M48,5) ="Sonde"),$F48,"") | AH48: {=IFERROR(INDEX($AG$14:$AG$99,SMALL(IF($AG$14:$AG$99<>"",ROW($AG$14:$AG$99)-ROW(INDIRECT("$AG$13"))+1),ROW(INDIRECT("A" & AB48 ) ))),"")} | AI48: =IF(AND(OR($E48="Contrôlé",$E48="Non contrôlé"), $F48 <> "", $M48 = ""),$F48,"") | AJ48: {=IFERROR(INDEX($AI$14:$AI$99,SMALL(IF($AI$14:$AI$99<>"",ROW($AI$14:$AI$99)-ROW(INDIRECT("$AI$13"))+1),ROW(INDIRECT("A" & AB48 ) ))),"")}
AB49: =ROW(A49)- $AD$2 +1 -> 36 | AC49: =IF(AND(OR($E49="Contrôlé",$E49="Non contrôlé"),$M49="Préleveur"),$F49,"") | AD49: {=IFERROR(INDEX($AC$14:$AC$99,SMALL(IF($AC$14:$AC$99<>"",ROW($AC$14:$AC$99)-ROW(INDIRECT("$AC$13"))+1),ROW(INDIRECT("A" & AB49 ) ))),"")} | AE49: =IF(AND(OR($E49="Contrôlé",$E49="Non contrôlé"),LEFT($M49,10) ="Débitmètre"),$F49,"") | AF49: {=IFERROR(INDEX($AE$14:$AE$99,SMALL(IF($AE$14:$AE$99<>"",ROW($AE$14:$AE$99)-ROW(INDIRECT("$AE$13"))+1),ROW(INDIRECT("A" & AB49 ) ))),"")} | AG49: =IF(AND(OR($E49="Contrôlé",$E49="Non contrôlé"),LEFT($M49,5) ="Sonde"),$F49,"") | AH49: {=IFERROR(INDEX($AG$14:$AG$99,SMALL(IF($AG$14:$AG$99<>"",ROW($AG$14:$AG$99)-ROW(INDIRECT("$AG$13"))+1),ROW(INDIRECT("A" & AB49 ) ))),"")} | AI49: =IF(AND(OR($E49="Contrôlé",$E49="Non contrôlé"), $F49 <> "", $M49 = ""),$F49,"") | AJ49: {=IFERROR(INDEX($AI$14:$AI$99,SMALL(IF($AI$14:$AI$99<>"",ROW($AI$14:$AI$99)-ROW(INDIRECT("$AI$13"))+1),ROW(INDIRECT("A" & AB49 ) ))),"")}
AB50: =ROW(A50)- $AD$2 +1 -> 37 | AC50: =IF(AND(OR($E50="Contrôlé",$E50="Non contrôlé"),$M50="Préleveur"),$F50,"") | AD50: {=IFERROR(INDEX($AC$14:$AC$99,SMALL(IF($AC$14:$AC$99<>"",ROW($AC$14:$AC$99)-ROW(INDIRECT("$AC$13"))+1),ROW(INDIRECT("A" & AB50 ) ))),"")} | AE50: =IF(AND(OR($E50="Contrôlé",$E50="Non contrôlé"),LEFT($M50,10) ="Débitmètre"),$F50,"") | AF50: {=IFERROR(INDEX($AE$14:$AE$99,SMALL(IF($AE$14:$AE$99<>"",ROW($AE$14:$AE$99)-ROW(INDIRECT("$AE$13"))+1),ROW(INDIRECT("A" & AB50 ) ))),"")} | AG50: =IF(AND(OR($E50="Contrôlé",$E50="Non contrôlé"),LEFT($M50,5) ="Sonde"),$F50,"") | AH50: {=IFERROR(INDEX($AG$14:$AG$99,SMALL(IF($AG$14:$AG$99<>"",ROW($AG$14:$AG$99)-ROW(INDIRECT("$AG$13"))+1),ROW(INDIRECT("A" & AB50 ) ))),"")} | AI50: =IF(AND(OR($E50="Contrôlé",$E50="Non contrôlé"), $F50 <> "", $M50 = ""),$F50,"") | AJ50: {=IFERROR(INDEX($AI$14:$AI$99,SMALL(IF($AI$14:$AI$99<>"",ROW($AI$14:$AI$99)-ROW(INDIRECT("$AI$13"))+1),ROW(INDIRECT("A" & AB50 ) ))),"")}
AB51: =ROW(A51)- $AD$2 +1 -> 38 | AC51: =IF(AND(OR($E51="Contrôlé",$E51="Non contrôlé"),$M51="Préleveur"),$F51,"") | AD51: {=IFERROR(INDEX($AC$14:$AC$99,SMALL(IF($AC$14:$AC$99<>"",ROW($AC$14:$AC$99)-ROW(INDIRECT("$AC$13"))+1),ROW(INDIRECT("A" & AB51 ) ))),"")} | AE51: =IF(AND(OR($E51="Contrôlé",$E51="Non contrôlé"),LEFT($M51,10) ="Débitmètre"),$F51,"") | AF51: {=IFERROR(INDEX($AE$14:$AE$99,SMALL(IF($AE$14:$AE$99<>"",ROW($AE$14:$AE$99)-ROW(INDIRECT("$AE$13"))+1),ROW(INDIRECT("A" & AB51 ) ))),"")} | AG51: =IF(AND(OR($E51="Contrôlé",$E51="Non contrôlé"),LEFT($M51,5) ="Sonde"),$F51,"") | AH51: {=IFERROR(INDEX($AG$14:$AG$99,SMALL(IF($AG$14:$AG$99<>"",ROW($AG$14:$AG$99)-ROW(INDIRECT("$AG$13"))+1),ROW(INDIRECT("A" & AB51 ) ))),"")} | AI51: =IF(AND(OR($E51="Contrôlé",$E51="Non contrôlé"), $F51 <> "", $M51 = ""),$F51,"") | AJ51: {=IFERROR(INDEX($AI$14:$AI$99,SMALL(IF($AI$14:$AI$99<>"",ROW($AI$14:$AI$99)-ROW(INDIRECT("$AI$13"))+1),ROW(INDIRECT("A" & AB51 ) ))),"")}
AB52: =ROW(A52)- $AD$2 +1 -> 39 | AC52: =IF(AND(OR($E52="Contrôlé",$E52="Non contrôlé"),$M52="Préleveur"),$F52,"") | AD52: {=IFERROR(INDEX($AC$14:$AC$99,SMALL(IF($AC$14:$AC$99<>"",ROW($AC$14:$AC$99)-ROW(INDIRECT("$AC$13"))+1),ROW(INDIRECT("A" & AB52 ) ))),"")} | AE52: =IF(AND(OR($E52="Contrôlé",$E52="Non contrôlé"),LEFT($M52,10) ="Débitmètre"),$F52,"") | AF52: {=IFERROR(INDEX($AE$14:$AE$99,SMALL(IF($AE$14:$AE$99<>"",ROW($AE$14:$AE$99)-ROW(INDIRECT("$AE$13"))+1),ROW(INDIRECT("A" & AB52 ) ))),"")} | AG52: =IF(AND(OR($E52="Contrôlé",$E52="Non contrôlé"),LEFT($M52,5) ="Sonde"),$F52,"") | AH52: {=IFERROR(INDEX($AG$14:$AG$99,SMALL(IF($AG$14:$AG$99<>"",ROW($AG$14:$AG$99)-ROW(INDIRECT("$AG$13"))+1),ROW(INDIRECT("A" & AB52 ) ))),"")} | AI52: =IF(AND(OR($E52="Contrôlé",$E52="Non contrôlé"), $F52 <> "", $M52 = ""),$F52,"") | AJ52: {=IFERROR(INDEX($AI$14:$AI$99,SMALL(IF($AI$14:$AI$99<>"",ROW($AI$14:$AI$99)-ROW(INDIRECT("$AI$13"))+1),ROW(INDIRECT("A" & AB52 ) ))),"")}
AB53: =ROW(A53)- $AD$2 +1 -> 40 | AC53: =IF(AND(OR($E53="Contrôlé",$E53="Non contrôlé"),$M53="Préleveur"),$F53,"") | AD53: {=IFERROR(INDEX($AC$14:$AC$99,SMALL(IF($AC$14:$AC$99<>"",ROW($AC$14:$AC$99)-ROW(INDIRECT("$AC$13"))+1),ROW(INDIRECT("A" & AB53 ) ))),"")} | AE53: =IF(AND(OR($E53="Contrôlé",$E53="Non contrôlé"),LEFT($M53,10) ="Débitmètre"),$F53,"") | AF53: {=IFERROR(INDEX($AE$14:$AE$99,SMALL(IF($AE$14:$AE$99<>"",ROW($AE$14:$AE$99)-ROW(INDIRECT("$AE$13"))+1),ROW(INDIRECT("A" & AB53 ) ))),"")} | AG53: =IF(AND(OR($E53="Contrôlé",$E53="Non contrôlé"),LEFT($M53,5) ="Sonde"),$F53,"") | AH53: {=IFERROR(INDEX($AG$14:$AG$99,SMALL(IF($AG$14:$AG$99<>"",ROW($AG$14:$AG$99)-ROW(INDIRECT("$AG$13"))+1),ROW(INDIRECT("A" & AB53 ) ))),"")} | AI53: =IF(AND(OR($E53="Contrôlé",$E53="Non contrôlé"), $F53 <> "", $M53 = ""),$F53,"") | AJ53: {=IFERROR(INDEX($AI$14:$AI$99,SMALL(IF($AI$14:$AI$99<>"",ROW($AI$14:$AI$99)-ROW(INDIRECT("$AI$13"))+1),ROW(INDIRECT("A" & AB53 ) ))),"")}
AB54: =ROW(A54)- $AD$2 +1 -> 41 | AC54: =IF(AND(OR($E54="Contrôlé",$E54="Non contrôlé"),$M54="Préleveur"),$F54,"") | AD54: {=IFERROR(INDEX($AC$14:$AC$99,SMALL(IF($AC$14:$AC$99<>"",ROW($AC$14:$AC$99)-ROW(INDIRECT("$AC$13"))+1),ROW(INDIRECT("A" & AB54 ) ))),"")} | AE54: =IF(AND(OR($E54="Contrôlé",$E54="Non contrôlé"),LEFT($M54,10) ="Débitmètre"),$F54,"") | AF54: {=IFERROR(INDEX($AE$14:$AE$99,SMALL(IF($AE$14:$AE$99<>"",ROW($AE$14:$AE$99)-ROW(INDIRECT("$AE$13"))+1),ROW(INDIRECT("A" & AB54 ) ))),"")} | AG54: =IF(AND(OR($E54="Contrôlé",$E54="Non contrôlé"),LEFT($M54,5) ="Sonde"),$F54,"") | AH54: {=IFERROR(INDEX($AG$14:$AG$99,SMALL(IF($AG$14:$AG$99<>"",ROW($AG$14:$AG$99)-ROW(INDIRECT("$AG$13"))+1),ROW(INDIRECT("A" & AB54 ) ))),"")} | AI54: =IF(AND(OR($E54="Contrôlé",$E54="Non contrôlé"), $F54 <> "", $M54 = ""),$F54,"") | AJ54: {=IFERROR(INDEX($AI$14:$AI$99,SMALL(IF($AI$14:$AI$99<>"",ROW($AI$14:$AI$99)-ROW(INDIRECT("$AI$13"))+1),ROW(INDIRECT("A" & AB54 ) ))),"")}
AB55: =ROW(A55)- $AD$2 +1 -> 42 | AC55: =IF(AND(OR($E55="Contrôlé",$E55="Non contrôlé"),$M55="Préleveur"),$F55,"") | AD55: {=IFERROR(INDEX($AC$14:$AC$99,SMALL(IF($AC$14:$AC$99<>"",ROW($AC$14:$AC$99)-ROW(INDIRECT("$AC$13"))+1),ROW(INDIRECT("A" & AB55 ) ))),"")} | AE55: =IF(AND(OR($E55="Contrôlé",$E55="Non contrôlé"),LEFT($M55,10) ="Débitmètre"),$F55,"") | AF55: {=IFERROR(INDEX($AE$14:$AE$99,SMALL(IF($AE$14:$AE$99<>"",ROW($AE$14:$AE$99)-ROW(INDIRECT("$AE$13"))+1),ROW(INDIRECT("A" & AB55 ) ))),"")} | AG55: =IF(AND(OR($E55="Contrôlé",$E55="Non contrôlé"),LEFT($M55,5) ="Sonde"),$F55,"") | AH55: {=IFERROR(INDEX($AG$14:$AG$99,SMALL(IF($AG$14:$AG$99<>"",ROW($AG$14:$AG$99)-ROW(INDIRECT("$AG$13"))+1),ROW(INDIRECT("A" & AB55 ) ))),"")} | AI55: =IF(AND(OR($E55="Contrôlé",$E55="Non contrôlé"), $F55 <> "", $M55 = ""),$F55,"") | AJ55: {=IFERROR(INDEX($AI$14:$AI$99,SMALL(IF($AI$14:$AI$99<>"",ROW($AI$14:$AI$99)-ROW(INDIRECT("$AI$13"))+1),ROW(INDIRECT("A" & AB55 ) ))),"")}
AB56: =ROW(A56)- $AD$2 +1 -> 43 | AC56: =IF(AND(OR($E56="Contrôlé",$E56="Non contrôlé"),$M56="Préleveur"),$F56,"") | AD56: {=IFERROR(INDEX($AC$14:$AC$99,SMALL(IF($AC$14:$AC$99<>"",ROW($AC$14:$AC$99)-ROW(INDIRECT("$AC$13"))+1),ROW(INDIRECT("A" & AB56 ) ))),"")} | AE56: =IF(AND(OR($E56="Contrôlé",$E56="Non contrôlé"),LEFT($M56,10) ="Débitmètre"),$F56,"") | AF56: {=IFERROR(INDEX($AE$14:$AE$99,SMALL(IF($AE$14:$AE$99<>"",ROW($AE$14:$AE$99)-ROW(INDIRECT("$AE$13"))+1),ROW(INDIRECT("A" & AB56 ) ))),"")} | AG56: =IF(AND(OR($E56="Contrôlé",$E56="Non contrôlé"),LEFT($M56,5) ="Sonde"),$F56,"") | AH56: {=IFERROR(INDEX($AG$14:$AG$99,SMALL(IF($AG$14:$AG$99<>"",ROW($AG$14:$AG$99)-ROW(INDIRECT("$AG$13"))+1),ROW(INDIRECT("A" & AB56 ) ))),"")} | AI56: =IF(AND(OR($E56="Contrôlé",$E56="Non contrôlé"), $F56 <> "", $M56 = ""),$F56,"") | AJ56: {=IFERROR(INDEX($AI$14:$AI$99,SMALL(IF($AI$14:$AI$99<>"",ROW($AI$14:$AI$99)-ROW(INDIRECT("$AI$13"))+1),ROW(INDIRECT("A" & AB56 ) ))),"")}
... AB91: =ROW(A91)- $AD$2 +1 -> 78 | AC91: =IF(AND(OR($E91="Contrôlé",$E91="Non contrôlé"),$M91="Préleveur"),$F91,"") | AD91: {=IFERROR(INDEX($AC$14:$AC$99,SMALL(IF($AC$14:$AC$99<>"",ROW($AC$14:$AC$99)-ROW(INDIRECT("$AC$13"))+1),ROW(INDIRECT("A" & AB91 ) ))),"")} | AE91: =IF(AND(OR($E91="Contrôlé",$E91="Non contrôlé"),LEFT($M91,10) ="Débitmètre"),$F91,"") | AF91: {=IFERROR(INDEX($AE$14:$AE$99,SMALL(IF($AE$14:$AE$99<>"",ROW($AE$14:$AE$99)-ROW(INDIRECT("$AE$13"))+1),ROW(INDIRECT("A" & AB91 ) ))),"")} | AG91: =IF(AND(OR($E91="Contrôlé",$E91="Non contrôlé"),LEFT($M91,5) ="Sonde"),$F91,"") | AH91: {=IFERROR(INDEX($AG$14:$AG$99,SMALL(IF($AG$14:$AG$99<>"",ROW($AG$14:$AG$99)-ROW(INDIRECT("$AG$13"))+1),ROW(INDIRECT("A" & AB91 ) ))),"")} | AI91: =IF(AND(OR($E91="Contrôlé",$E91="Non contrôlé"), $F91 <> "", $M91 = ""),$F91,"") | AJ91: {=IFERROR(INDEX($AI$14:$AI$99,SMALL(IF($AI$14:$AI$99<>"",ROW($AI$14:$AI$99)-ROW(INDIRECT("$AI$13"))+1),ROW(INDIRECT("A" & AB91 ) ))),"")}
AI92: =IF(AND($E92="Oui", $M92 <> "", $M92 = ""),$F92,"") | AJ92: {=IFERROR(INDEX($AI$14:$AI$99,SMALL(IF($AI$14:$AI$99<>"",ROW($AI$14:$AI$99)-ROW(INDIRECT("$AI$13"))+1),ROW(INDIRECT("A" & AB92 ) ))),"")}

Sheet SYNTHESE_SCL
C2: CONTRÔLE DES DISPOSITIFS D'AUTOSURVEILLANCE DU SYSTÈME DE COLLECTE | Y2: Exporter en Word
C3: NOM DU SYSTÈME D'ASSAINISSEMENT : | G3: =IF(ISBLANK(Descriptif!F3),"",Descriptif!F3) | J3: NOM DU SYSTÈME DE TRAITEMENT : | M3: =IF(ISBLANK(Descriptif!L3),"",Descriptif!L3) | P3: NOM DU SYSTÈME DE COLLECTE : | S3: =IF(ISBLANK(Descriptif!Q3),"",Descriptif!Q3) | V3: NOM DE L'ORGANISME DE CONTRÔLE : | Y3: =IF(ISBLANK(Descriptif!U3),"",Descriptif!U3)
C4: CODE SANDRE DE L'AGGLOMÉRATION : | G4: =IF(ISBLANK(Descriptif!F4),"",Descriptif!F4) | J4: CODE SANDRE DE LA STATION : | M4: =IF(ISBLANK(Descriptif!L4),"",Descriptif!L4) | P4: CODE SANDRE DU RÉSEAU : | S4: =IF(ISBLANK(Descriptif!Q4),"",Descriptif!Q4) | V4: NOM(S) DU(ES) CONTROLEUR(S) : | Y4: =IF(ISBLANK(Descriptif!U4),"",Descriptif!U4)
C5: MAITRE D'OUVRAGE DE LA STATION : | G5: =IF(ISBLANK(Descriptif!F5),"",Descriptif!F5) | J5: TYPE DE TRAITEMENT : | M5: =IF(ISBLANK(Descriptif!L5),"",Descriptif!L5) | P5: TYPE DE RÉSEAU : | S5: =IF(ISBLANK(Descriptif!Q5),"",Descriptif!Q5) | V5: DATE(S) D'INTERVENTION : | Y5: =IF(ISBLANK(Descriptif!U5),"",Descriptif!U5)
C6: EXPLOITANT DE LA STATION : | G6: =IF(ISBLANK(Descriptif!F6),"",Descriptif!F6) | J6: CAPACITÉ DE LA STATION : | M6: =IF(ISBLANK(Descriptif!L6),"",Descriptif!L6) | P6: EXPLOITANT DU RÉSEAU : | S6: =IF(ISBLANK(Descriptif!Q6),"",Descriptif!Q6) | V6: CONDITION(S) MÉTÉO : | Y6: =IF(ISBLANK(Descriptif!U6),"",Descriptif!U6)
C8: SYNTHÈSE DES CONTRÔLES RÉALISÉS SUR LES DISPOSITIFS AUTOSURVEILLANCE
D10: Évaluation documentaire
M11: Coefficient Qualité | N11: Commentaires sur l'évaluation :
G12: Manuel autosurveillance à jour, validé ou en cours d'expertise ? | L12: =IF(Qualité!$L$10<>"",Qualité!$L$10,"Non contrôlé") -> Non contrôlé | N12: =IF(Qualité!$M$10<>"",Qualité!$M$10,"")
G13: Existe-t-il un système Qualité performant ? | L13: =IF(Qualité!$L$29<>"",Qualité!$L$29,"Non contrôlé") -> Non contrôlé | M13: =IF(Qualité!$L$29="Oui",1,0.9) -> 0.9 | N13: =IF(Qualité!$D$32<>"",Qualité!$D$32,"")
D16: Évaluation des pratiques de fractionnement et de transport des échantillons
K17: Penalité | N17: Commentaires sur l'évaluation :
G18: SDE | I18: Aquaref | K18: =IF(Analytique!N11<>"",Analytique!N11,"") | N18: =IF(Analytique!D17<>"",Analytique!D17,"")
G19: Eaux résiduaires | I19: Fractionnement | K19: =IF(Analytique!N12<>"",Analytique!N12,"")
I20: Température | K20: =IF(Analytique!N13<>"",Analytique!N13,"")
I21: Transport | K21: =IF(Analytique!N14<>"",Analytique!N14,"")
D24: Autres évaluations
K25: Score | N25: Commentaires sur l'évaluation :
G26: Sonde température | I26: {=IFERROR(INDEX(Equipements_SCL!$L$16:$L$72,SMALL(IF(Equipements_SCL!$J$16:$J$72="Sonde de température",ROW(Equipements_SCL!$J$16:$J$72)-ROW(Equipements_SCL!$J$16)+1),ROW(1:1))),"")} | K26: {=IFERROR(INDEX(Equipements_SCL!$P$16:$P$72,SMALL(IF(Equipements_SCL!$J$16:$J$72="Sonde de température",ROW(Equipements_SCL!$J$16:$J$72)-ROW(Equipements_SCL!$J$16)+1),ROW(1:1))),"")} | N26: {=IFERROR(INDEX(Equipements_SCL!$T$16:$T$72,SMALL(IF(Equipements_SCL!$J$16:$J$72="Sonde de température",ROW(Equipements_SCL!$J$16:$J$72)-ROW(Equipements_SCL!$J$16)+1),ROW(1:1))),"")}
I27: {=IFERROR(INDEX(Equipements_SCL!$L$16:$L$72,SMALL(IF(Equipements_SCL!$J$16:$J$72="Sonde de température",ROW(Equipements_SCL!$J$16:$J$72)-ROW(Equipements_SCL!$J$16)+1),ROW(2:2))),"")} | K27: {=IFERROR(INDEX(Equipements_SCL!$R$16:$R$72,SMALL(IF(Equipements_SCL!$J$16:$J$72="Sonde de température",ROW(Equipements_SCL!$J$16:$J$72)-ROW(Equipements_SCL!$J$16)+1),ROW(2:2))),"")} | N27: {=IFERROR(INDEX(Equipements_SCL!$T$16:$T$72,SMALL(IF(Equipements_SCL!$J$16:$J$72="Sonde de température",ROW(Equipements_SCL!$J$16:$J$72)-ROW(Equipements_SCL!$J$16)+1),ROW(2:2))),"")}
I28: {=IFERROR(INDEX(Equipements_SCL!$L$16:$L$72,SMALL(IF(Equipements_SCL!$J$16:$J$72="Sonde de température",ROW(Equipements_SCL!$J$16:$J$72)-ROW(Equipements_SCL!$J$16)+1),ROW(3:3))),"")} | K28: {=IFERROR(INDEX(Equipements_SCL!$R$16:$R$72,SMALL(IF(Equipements_SCL!$J$16:$J$72="Sonde de température",ROW(Equipements_SCL!$J$16:$J$72)-ROW(Equipements_SCL!$J$16)+1),ROW(3:3))),"")} | N28: {=IFERROR(INDEX(Equipements_SCL!$T$16:$T$72,SMALL(IF(Equipements_SCL!$J$16:$J$72="Sonde de température",ROW(Equipements_SCL!$J$16:$J$72)-ROW(Equipements_SCL!$J$16)+1),ROW(3:3))),"")}
K30: Score | N30: Commentaires sur l'évaluation :
G31: Pluviomètre | I31: {=IFERROR(INDEX(Equipements_SCL!$L$16:$L$72,SMALL(IF(Equipements_SCL!$J$16:$J$72="Pluviomètre",ROW(Equipements_SCL!$J$16:$J$72)-ROW(Equipements_SCL!$J$16)+1),ROW(1:1))),"")} | K31: {=IFERROR(INDEX(Equipements_SCL!$P$16:$P$72,SMALL(IF(Equipements_SCL!$J$16:$J$72="Pluviomètre",ROW(Equipements_SCL!$J$16:$J$72)-ROW(Equipements_SCL!$J$16)+1),ROW(1:1))),"")} | N31: {=IFERROR(INDEX(Equipements_SCL!$T$16:$T$72,SMALL(IF(Equipements_SCL!$J$16:$J$72="Pluviomètre",ROW(Equipements_SCL!$J$16:$J$72)-ROW(Equipements_SCL!$J$16)+1),ROW(1:1))),"")}
I32: {=IFERROR(INDEX(Equipements_SCL!$L$16:$L$72,SMALL(IF(Equipements_SCL!$J$16:$J$72="Pluviomètre",ROW(Equipements_SCL!$J$16:$J$72)-ROW(Equipements_SCL!$J$16)+1),ROW(2:2))),"")} | K32: {=IFERROR(INDEX(Equipements_SCL!$P$16:$P$72,SMALL(IF(Equipements_SCL!$J$16:$J$72="Pluviomètre",ROW(Equipements_SCL!$J$16:$J$72)-ROW(Equipements_SCL!$J$16)+1),ROW(2:2))),"")} | N32: {=IFERROR(INDEX(Equipements_SCL!$T$16:$T$72,SMALL(IF(Equipements_SCL!$J$16:$J$72="Pluviomètre",ROW(Equipements_SCL!$J$16:$J$72)-ROW(Equipements_SCL!$J$16)+1),ROW(2:2))),"")}
I33: {=IFERROR(INDEX(Equipements_SCL!$L$16:$L$72,SMALL(IF(Equipements_SCL!$J$16:$J$72="Pluviomètre",ROW(Equipements_SCL!$J$16:$J$72)-ROW(Equipements_SCL!$J$16)+1),ROW(3:3))),"")} | K33: {=IFERROR(INDEX(Equipements_SCL!$P$16:$P$72,SMALL(IF(Equipements_SCL!$J$16:$J$72="Pluviomètre",ROW(Equipements_SCL!$J$16:$J$72)-ROW(Equipements_SCL!$J$16)+1),ROW(3:3))),"")} | N33: {=IFERROR(INDEX(Equipements_SCL!$T$16:$T$72,SMALL(IF(Equipements_SCL!$J$16:$J$72="Pluviomètre",ROW(Equipements_SCL!$J$16:$J$72)-ROW(Equipements_SCL!$J$16)+1),ROW(3:3))),"")}
D36: Évaluation des points règlementaires du réseau
G37: Point | H37: Score | I37: Débitmètre | J37: Préleveur | K37: Analytique | AD37: Débitmètre gravitaire | AE37: Débitmètre en charge
G38: {=_xlfn._xlws.SORT(_xlfn.UNIQUE(_xlfn._xlws.FILTER(Equipements_SCL!$M$16:M100, Equipements_SCL!$M$16:M100<>"", "")))} | H38: =IF(AND($G38<>"",OR($I38<>"",$J38<>"",$K38<>"")),AVERAGE($I38,$J38,$K38),"") | I38: =IF(AND($G38<>"",OR($AD38<>"",$AE38<>"")),MAX($AD38,$AE38),"") | J38: =IF($G38="", "", IF(COUNTIFS(Equipements_SCL!$M$16:$M$100, $G38, Equipements_SCL!$J$16:$J$100, J$37)=0, "", IF(SUMIFS(Equipements_SCL!$AV$16:$AV$100, Equipements_SCL!$M$16:$M$100, $G38, Equipements_SCL!$J$16:$J$100, J$37)=-1, "", SUMIFS(Equipements_SCL!$P$16:$P$100, Equipements_SCL!$M$16:$M$100, $G38, Equipements_SCL!$J$16:$J$100, J$37)))) | K38: =IF( $G38="", "", IF( SUMIFS(Analytique!$AD$3:$AD$20, Analytique!$Z$3:$Z$20, $G38, Analytique!$Y$3:$Y$20, "A1")=0, "", SUMIFS(Analytique!$AD$3:$AD$20, Analytique!$Z$3:$Z$20, $G38, Analytique!$Y$3:$Y$20, "A1") ) ) | AD38: =IF($G38="", "", IF(COUNTIFS(Equipements_SCL!$M$16:$M$100, $G38, Equipements_SCL!$J$16:$J$100, AD$37)=0, "", IF(SUMIFS(Equipements_SCL!$AV$16:$AV$100, Equipements_SCL!$M$16:$M$100, $G38, Equipements_SCL!$J$16:$J$100, AD$37)=-1, "", SUMIFS(Equipements_SCL!$P$16:$P$100, Equipements_SCL!$M$16:$M$100, $G38, Equipements_SCL!$J$16:$J$100, AD$37)))) | AE38: =IF($G38="", "", IF(COUNTIFS(Equipements_SCL!$M$16:$M$100, $G38, Equipements_SCL!$J$16:$J$100, AE$37)=0, "", IF(SUMIFS(Equipements_SCL!$AV$16:$AV$100, Equipements_SCL!$M$16:$M$100, $G38, Equipements_SCL!$J$16:$J$100, AE$37)=-1, "", SUMIFS(Equipements_SCL!$P$16:$P$100, Equipements_SCL!$M$16:$M$100, $G38, Equipements_SCL!$J$16:$J$100, AE$37))))
H39: =IF(AND($G39<>"",OR($I39<>"",$J39<>"",$K39<>"")),AVERAGE($I39,$J39,$K39),"") | I39: =IF(AND($G39<>"",OR($AD39<>"",$AE39<>"")),MAX($AD39,$AE39),"") | J39: =IF($G39="", "", IF(COUNTIFS(Equipements_SCL!$M$16:$M$100, $G39, Equipements_SCL!$J$16:$J$100, J$37)=0, "", IF(SUMIFS(Equipements_SCL!$AV$16:$AV$100, Equipements_SCL!$M$16:$M$100, $G39, Equipements_SCL!$J$16:$J$100, J$37)=-1, "", SUMIFS(Equipements_SCL!$P$16:$P$100, Equipements_SCL!$M$16:$M$100, $G39, Equipements_SCL!$J$16:$J$100, J$37)))) | K39: =IF( $G39="", "", IF( SUMIFS(Analytique!$AD$3:$AD$20, Analytique!$Z$3:$Z$20, $G39, Analytique!$Y$3:$Y$20, "A1")=0, "", SUMIFS(Analytique!$AD$3:$AD$20, Analytique!$Z$3:$Z$20, $G39, Analytique!$Y$3:$Y$20, "A1") ) ) | AD39: =IF($G39="", "", IF(COUNTIFS(Equipements_SCL!$M$16:$M$100, $G39, Equipements_SCL!$J$16:$J$100, AD$37)=0, "", IF(SUMIFS(Equipements_SCL!$AV$16:$AV$100, Equipements_SCL!$M$16:$M$100, $G39, Equipements_SCL!$J$16:$J$100, AD$37)=-1, "", SUMIFS(Equipements_SCL!$P$16:$P$100, Equipements_SCL!$M$16:$M$100, $G39, Equipements_SCL!$J$16:$J$100, AD$37)))) | AE39: =IF($G39="", "", IF(COUNTIFS(Equipements_SCL!$M$16:$M$100, $G39, Equipements_SCL!$J$16:$J$100, AE$37)=0, "", IF(SUMIFS(Equipements_SCL!$AV$16:$AV$100, Equipements_SCL!$M$16:$M$100, $G39, Equipements_SCL!$J$16:$J$100, AE$37)=-1, "", SUMIFS(Equipements_SCL!$P$16:$P$100, Equipements_SCL!$M$16:$M$100, $G39, Equipements_SCL!$J$16:$J$100, AE$37))))
H40: =IF(AND($G40<>"",OR($I40<>"",$J40<>"",$K40<>"")),AVERAGE($I40,$J40,$K40),"") | I40: =IF(AND($G40<>"",OR($AD40<>"",$AE40<>"")),MAX($AD40,$AE40),"") | J40: =IF($G40="", "", IF(COUNTIFS(Equipements_SCL!$M$16:$M$100, $G40, Equipements_SCL!$J$16:$J$100, J$37)=0, "", IF(SUMIFS(Equipements_SCL!$AV$16:$AV$100, Equipements_SCL!$M$16:$M$100, $G40, Equipements_SCL!$J$16:$J$100, J$37)=-1, "", SUMIFS(Equipements_SCL!$P$16:$P$100, Equipements_SCL!$M$16:$M$100, $G40, Equipements_SCL!$J$16:$J$100, J$37)))) | K40: =IF( $G40="", "", IF( SUMIFS(Analytique!$AD$3:$AD$20, Analytique!$Z$3:$Z$20, $G40, Analytique!$Y$3:$Y$20, "A1")=0, "", SUMIFS(Analytique!$AD$3:$AD$20, Analytique!$Z$3:$Z$20, $G40, Analytique!$Y$3:$Y$20, "A1") ) ) | AD40: =IF($G40="", "", IF(COUNTIFS(Equipements_SCL!$M$16:$M$100, $G40, Equipements_SCL!$J$16:$J$100, AD$37)=0, "", IF(SUMIFS(Equipements_SCL!$AV$16:$AV$100, Equipements_SCL!$M$16:$M$100, $G40, Equipements_SCL!$J$16:$J$100, AD$37)=-1, "", SUMIFS(Equipements_SCL!$P$16:$P$100, Equipements_SCL!$M$16:$M$100, $G40, Equipements_SCL!$J$16:$J$100, AD$37)))) | AE40: =IF($G40="", "", IF(COUNTIFS(Equipements_SCL!$M$16:$M$100, $G40, Equipements_SCL!$J$16:$J$100, AE$37)=0, "", IF(SUMIFS(Equipements_SCL!$AV$16:$AV$100, Equipements_SCL!$M$16:$M$100, $G40, Equipements_SCL!$J$16:$J$100, AE$37)=-1, "", SUMIFS(Equipements_SCL!$P$16:$P$100, Equipements_SCL!$M$16:$M$100, $G40, Equipements_SCL!$J$16:$J$100, AE$37))))
H41: =IF(AND($G41<>"",OR($I41<>"",$J41<>"",$K41<>"")),AVERAGE($I41,$J41,$K41),"") | I41: =IF(AND($G41<>"",OR($AD41<>"",$AE41<>"")),MAX($AD41,$AE41),"") | J41: =IF($G41="", "", IF(COUNTIFS(Equipements_SCL!$M$16:$M$100, $G41, Equipements_SCL!$J$16:$J$100, J$37)=0, "", IF(SUMIFS(Equipements_SCL!$AV$16:$AV$100, Equipements_SCL!$M$16:$M$100, $G41, Equipements_SCL!$J$16:$J$100, J$37)=-1, "", SUMIFS(Equipements_SCL!$P$16:$P$100, Equipements_SCL!$M$16:$M$100, $G41, Equipements_SCL!$J$16:$J$100, J$37)))) | K41: =IF( $G41="", "", IF( SUMIFS(Analytique!$AD$3:$AD$20, Analytique!$Z$3:$Z$20, $G41, Analytique!$Y$3:$Y$20, "A1")=0, "", SUMIFS(Analytique!$AD$3:$AD$20, Analytique!$Z$3:$Z$20, $G41, Analytique!$Y$3:$Y$20, "A1") ) ) | AD41: =IF($G41="", "", IF(COUNTIFS(Equipements_SCL!$M$16:$M$100, $G41, Equipements_SCL!$J$16:$J$100, AD$37)=0, "", IF(SUMIFS(Equipements_SCL!$AV$16:$AV$100, Equipements_SCL!$M$16:$M$100, $G41, Equipements_SCL!$J$16:$J$100, AD$37)=-1, "", SUMIFS(Equipements_SCL!$P$16:$P$100, Equipements_SCL!$M$16:$M$100, $G41, Equipements_SCL!$J$16:$J$100, AD$37)))) | AE41: =IF($G41="", "", IF(COUNTIFS(Equipements_SCL!$M$16:$M$100, $G41, Equipements_SCL!$J$16:$J$100, AE$37)=0, "", IF(SUMIFS(Equipements_SCL!$AV$16:$AV$100, Equipements_SCL!$M$16:$M$100, $G41, Equipements_SCL!$J$16:$J$100, AE$37)=-1, "", SUMIFS(Equipements_SCL!$P$16:$P$100, Equipements_SCL!$M$16:$M$100, $G41, Equipements_SCL!$J$16:$J$100, AE$37))))
H42: =IF(AND($G42<>"",OR($I42<>"",$J42<>"",$K42<>"")),AVERAGE($I42,$J42,$K42),"") | I42: =IF(AND($G42<>"",OR($AD42<>"",$AE42<>"")),MAX($AD42,$AE42),"") | J42: =IF($G42="", "", IF(COUNTIFS(Equipements_SCL!$M$16:$M$100, $G42, Equipements_SCL!$J$16:$J$100, J$37)=0, "", IF(SUMIFS(Equipements_SCL!$AV$16:$AV$100, Equipements_SCL!$M$16:$M$100, $G42, Equipements_SCL!$J$16:$J$100, J$37)=-1, "", SUMIFS(Equipements_SCL!$P$16:$P$100, Equipements_SCL!$M$16:$M$100, $G42, Equipements_SCL!$J$16:$J$100, J$37)))) | K42: =IF( $G42="", "", IF( SUMIFS(Analytique!$AD$3:$AD$20, Analytique!$Z$3:$Z$20, $G42, Analytique!$Y$3:$Y$20, "A1")=0, "", SUMIFS(Analytique!$AD$3:$AD$20, Analytique!$Z$3:$Z$20, $G42, Analytique!$Y$3:$Y$20, "A1") ) ) | AD42: =IF($G42="", "", IF(COUNTIFS(Equipements_SCL!$M$16:$M$100, $G42, Equipements_SCL!$J$16:$J$100, AD$37)=0, "", IF(SUMIFS(Equipements_SCL!$AV$16:$AV$100, Equipements_SCL!$M$16:$M$100, $G42, Equipements_SCL!$J$16:$J$100, AD$37)=-1, "", SUMIFS(Equipements_SCL!$P$16:$P$100, Equipements_SCL!$M$16:$M$100, $G42, Equipements_SCL!$J$16:$J$100, AD$37)))) | AE42: =IF($G42="", "", IF(COUNTIFS(Equipements_SCL!$M$16:$M$100, $G42, Equipements_SCL!$J$16:$J$100, AE$37)=0, "", IF(SUMIFS(Equipements_SCL!$AV$16:$AV$100, Equipements_SCL!$M$16:$M$100, $G42, Equipements_SCL!$J$16:$J$100, AE$37)=-1, "", SUMIFS(Equipements_SCL!$P$16:$P$100, Equipements_SCL!$M$16:$M$100, $G42, Equipements_SCL!$J$16:$J$100, AE$37))))
H43: =IF(AND($G43<>"",OR($I43<>"",$J43<>"",$K43<>"")),AVERAGE($I43,$J43,$K43),"") | I43: =IF(AND($G43<>"",OR($AD43<>"",$AE43<>"")),MAX($AD43,$AE43),"") | J43: =IF($G43="", "", IF(COUNTIFS(Equipements_SCL!$M$16:$M$100, $G43, Equipements_SCL!$J$16:$J$100, J$37)=0, "", IF(SUMIFS(Equipements_SCL!$AV$16:$AV$100, Equipements_SCL!$M$16:$M$100, $G43, Equipements_SCL!$J$16:$J$100, J$37)=-1, "", SUMIFS(Equipements_SCL!$P$16:$P$100, Equipements_SCL!$M$16:$M$100, $G43, Equipements_SCL!$J$16:$J$100, J$37)))) | K43: =IF( $G43="", "", IF( SUMIFS(Analytique!$AD$3:$AD$20, Analytique!$Z$3:$Z$20, $G43, Analytique!$Y$3:$Y$20, "A1")=0, "", SUMIFS(Analytique!$AD$3:$AD$20, Analytique!$Z$3:$Z$20, $G43, Analytique!$Y$3:$Y$20, "A1") ) ) | AD43: =IF($G43="", "", IF(COUNTIFS(Equipements_SCL!$M$16:$M$100, $G43, Equipements_SCL!$J$16:$J$100, AD$37)=0, "", IF(SUMIFS(Equipements_SCL!$AV$16:$AV$100, Equipements_SCL!$M$16:$M$100, $G43, Equipements_SCL!$J$16:$J$100, AD$37)=-1, "", SUMIFS(Equipements_SCL!$P$16:$P$100, Equipements_SCL!$M$16:$M$100, $G43, Equipements_SCL!$J$16:$J$100, AD$37)))) | AE43: =IF($G43="", "", IF(COUNTIFS(Equipements_SCL!$M$16:$M$100, $G43, Equipements_SCL!$J$16:$J$100, AE$37)=0, "", IF(SUMIFS(Equipements_SCL!$AV$16:$AV$100, Equipements_SCL!$M$16:$M$100, $G43, Equipements_SCL!$J$16:$J$100, AE$37)=-1, "", SUMIFS(Equipements_SCL!$P$16:$P$100, Equipements_SCL!$M$16:$M$100, $G43, Equipements_SCL!$J$16:$J$100, AE$37))))
H44: =IF(AND($G44<>"",OR($I44<>"",$J44<>"",$K44<>"")),AVERAGE($I44,$J44,$K44),"") | I44: =IF(AND($G44<>"",OR($AD44<>"",$AE44<>"")),MAX($AD44,$AE44),"") | J44: =IF($G44="", "", IF(COUNTIFS(Equipements_SCL!$M$16:$M$100, $G44, Equipements_SCL!$J$16:$J$100, J$37)=0, "", IF(SUMIFS(Equipements_SCL!$AV$16:$AV$100, Equipements_SCL!$M$16:$M$100, $G44, Equipements_SCL!$J$16:$J$100, J$37)=-1, "", SUMIFS(Equipements_SCL!$P$16:$P$100, Equipements_SCL!$M$16:$M$100, $G44, Equipements_SCL!$J$16:$J$100, J$37)))) | K44: =IF( $G44="", "", IF( SUMIFS(Analytique!$AD$3:$AD$20, Analytique!$Z$3:$Z$20, $G44, Analytique!$Y$3:$Y$20, "A1")=0, "", SUMIFS(Analytique!$AD$3:$AD$20, Analytique!$Z$3:$Z$20, $G44, Analytique!$Y$3:$Y$20, "A1") ) ) | AD44: =IF($G44="", "", IF(COUNTIFS(Equipements_SCL!$M$16:$M$100, $G44, Equipements_SCL!$J$16:$J$100, AD$37)=0, "", IF(SUMIFS(Equipements_SCL!$AV$16:$AV$100, Equipements_SCL!$M$16:$M$100, $G44, Equipements_SCL!$J$16:$J$100, AD$37)=-1, "", SUMIFS(Equipements_SCL!$P$16:$P$100, Equipements_SCL!$M$16:$M$100, $G44, Equipements_SCL!$J$16:$J$100, AD$37)))) | AE44: =IF($G44="", "", IF(COUNTIFS(Equipements_SCL!$M$16:$M$100, $G44, Equipements_SCL!$J$16:$J$100, AE$37)=0, "", IF(SUMIFS(Equipements_SCL!$AV$16:$AV$100, Equipements_SCL!$M$16:$M$100, $G44, Equipements_SCL!$J$16:$J$100, AE$37)=-1, "", SUMIFS(Equipements_SCL!$P$16:$P$100, Equipements_SCL!$M$16:$M$100, $G44, Equipements_SCL!$J$16:$J$100, AE$37))))
H45: =IF(AND($G45<>"",OR($I45<>"",$J45<>"",$K45<>"")),AVERAGE($I45,$J45,$K45),"") | I45: =IF(AND($G45<>"",OR($AD45<>"",$AE45<>"")),MAX($AD45,$AE45),"") | J45: =IF($G45="", "", IF(COUNTIFS(Equipements_SCL!$M$16:$M$100, $G45, Equipements_SCL!$J$16:$J$100, J$37)=0, "", IF(SUMIFS(Equipements_SCL!$AV$16:$AV$100, Equipements_SCL!$M$16:$M$100, $G45, Equipements_SCL!$J$16:$J$100, J$37)=-1, "", SUMIFS(Equipements_SCL!$P$16:$P$100, Equipements_SCL!$M$16:$M$100, $G45, Equipements_SCL!$J$16:$J$100, J$37)))) | K45: =IF( $G45="", "", IF( SUMIFS(Analytique!$AD$3:$AD$20, Analytique!$Z$3:$Z$20, $G45, Analytique!$Y$3:$Y$20, "A1")=0, "", SUMIFS(Analytique!$AD$3:$AD$20, Analytique!$Z$3:$Z$20, $G45, Analytique!$Y$3:$Y$20, "A1") ) ) | AD45: =IF($G45="", "", IF(COUNTIFS(Equipements_SCL!$M$16:$M$100, $G45, Equipements_SCL!$J$16:$J$100, AD$37)=0, "", IF(SUMIFS(Equipements_SCL!$AV$16:$AV$100, Equipements_SCL!$M$16:$M$100, $G45, Equipements_SCL!$J$16:$J$100, AD$37)=-1, "", SUMIFS(Equipements_SCL!$P$16:$P$100, Equipements_SCL!$M$16:$M$100, $G45, Equipements_SCL!$J$16:$J$100, AD$37)))) | AE45: =IF($G45="", "", IF(COUNTIFS(Equipements_SCL!$M$16:$M$100, $G45, Equipements_SCL!$J$16:$J$100, AE$37)=0, "", IF(SUMIFS(Equipements_SCL!$AV$16:$AV$100, Equipements_SCL!$M$16:$M$100, $G45, Equipements_SCL!$J$16:$J$100, AE$37)=-1, "", SUMIFS(Equipements_SCL!$P$16:$P$100, Equipements_SCL!$M$16:$M$100, $G45, Equipements_SCL!$J$16:$J$100, AE$37))))
H46: =IF(AND($G46<>"",OR($I46<>"",$J46<>"",$K46<>"")),AVERAGE($I46,$J46,$K46),"") | I46: =IF(AND($G46<>"",OR($AD46<>"",$AE46<>"")),MAX($AD46,$AE46),"") | J46: =IF($G46="", "", IF(COUNTIFS(Equipements_SCL!$M$16:$M$100, $G46, Equipements_SCL!$J$16:$J$100, J$37)=0, "", IF(SUMIFS(Equipements_SCL!$AV$16:$AV$100, Equipements_SCL!$M$16:$M$100, $G46, Equipements_SCL!$J$16:$J$100, J$37)=-1, "", SUMIFS(Equipements_SCL!$P$16:$P$100, Equipements_SCL!$M$16:$M$100, $G46, Equipements_SCL!$J$16:$J$100, J$37)))) | K46: =IF( $G46="", "", IF( SUMIFS(Analytique!$AD$3:$AD$20, Analytique!$Z$3:$Z$20, $G46, Analytique!$Y$3:$Y$20, "A1")=0, "", SUMIFS(Analytique!$AD$3:$AD$20, Analytique!$Z$3:$Z$20, $G46, Analytique!$Y$3:$Y$20, "A1") ) ) | AD46: =IF($G46="", "", IF(COUNTIFS(Equipements_SCL!$M$16:$M$100, $G46, Equipements_SCL!$J$16:$J$100, AD$37)=0, "", IF(SUMIFS(Equipements_SCL!$AV$16:$AV$100, Equipements_SCL!$M$16:$M$100, $G46, Equipements_SCL!$J$16:$J$100, AD$37)=-1, "", SUMIFS(Equipements_SCL!$P$16:$P$100, Equipements_SCL!$M$16:$M$100, $G46, Equipements_SCL!$J$16:$J$100, AD$37)))) | AE46: =IF($G46="", "", IF(COUNTIFS(Equipements_SCL!$M$16:$M$100, $G46, Equipements_SCL!$J$16:$J$100, AE$37)=0, "", IF(SUMIFS(Equipements_SCL!$AV$16:$AV$100, Equipements_SCL!$M$16:$M$100, $G46, Equipements_SCL!$J$16:$J$100, AE$37)=-1, "", SUMIFS(Equipements_SCL!$P$16:$P$100, Equipements_SCL!$M$16:$M$100, $G46, Equipements_SCL!$J$16:$J$100, AE$37))))
H47: =IF(AND($G47<>"",OR($I47<>"",$J47<>"",$K47<>"")),AVERAGE($I47,$J47,$K47),"") | I47: =IF(AND($G47<>"",OR($AD47<>"",$AE47<>"")),MAX($AD47,$AE47),"") | J47: =IF($G47="", "", IF(COUNTIFS(Equipements_SCL!$M$16:$M$100, $G47, Equipements_SCL!$J$16:$J$100, J$37)=0, "", IF(SUMIFS(Equipements_SCL!$AV$16:$AV$100, Equipements_SCL!$M$16:$M$100, $G47, Equipements_SCL!$J$16:$J$100, J$37)=-1, "", SUMIFS(Equipements_SCL!$P$16:$P$100, Equipements_SCL!$M$16:$M$100, $G47, Equipements_SCL!$J$16:$J$100, J$37)))) | K47: =IF( $G47="", "", IF( SUMIFS(Analytique!$AD$3:$AD$20, Analytique!$Z$3:$Z$20, $G47, Analytique!$Y$3:$Y$20, "A1")=0, "", SUMIFS(Analytique!$AD$3:$AD$20, Analytique!$Z$3:$Z$20, $G47, Analytique!$Y$3:$Y$20, "A1") ) ) | AD47: =IF($G47="", "", IF(COUNTIFS(Equipements_SCL!$M$16:$M$100, $G47, Equipements_SCL!$J$16:$J$100, AD$37)=0, "", IF(SUMIFS(Equipements_SCL!$AV$16:$AV$100, Equipements_SCL!$M$16:$M$100, $G47, Equipements_SCL!$J$16:$J$100, AD$37)=-1, "", SUMIFS(Equipements_SCL!$P$16:$P$100, Equipements_SCL!$M$16:$M$100, $G47, Equipements_SCL!$J$16:$J$100, AD$37)))) | AE47: =IF($G47="", "", IF(COUNTIFS(Equipements_SCL!$M$16:$M$100, $G47, Equipements_SCL!$J$16:$J$100, AE$37)=0, "", IF(SUMIFS(Equipements_SCL!$AV$16:$AV$100, Equipements_SCL!$M$16:$M$100, $G47, Equipements_SCL!$J$16:$J$100, AE$37)=-1, "", SUMIFS(Equipements_SCL!$P$16:$P$100, Equipements_SCL!$M$16:$M$100, $G47, Equipements_SCL!$J$16:$J$100, AE$37))))
H48: =IF(AND($G48<>"",OR($I48<>"",$J48<>"",$K48<>"")),AVERAGE($I48,$J48,$K48),"") | I48: =IF(AND($G48<>"",OR($AD48<>"",$AE48<>"")),MAX($AD48,$AE48),"") | J48: =IF($G48="", "", IF(COUNTIFS(Equipements_SCL!$M$16:$M$100, $G48, Equipements_SCL!$J$16:$J$100, J$37)=0, "", IF(SUMIFS(Equipements_SCL!$AV$16:$AV$100, Equipements_SCL!$M$16:$M$100, $G48, Equipements_SCL!$J$16:$J$100, J$37)=-1, "", SUMIFS(Equipements_SCL!$P$16:$P$100, Equipements_SCL!$M$16:$M$100, $G48, Equipements_SCL!$J$16:$J$100, J$37)))) | K48: =IF( $G48="", "", IF( SUMIFS(Analytique!$AD$3:$AD$20, Analytique!$Z$3:$Z$20, $G48, Analytique!$Y$3:$Y$20, "A1")=0, "", SUMIFS(Analytique!$AD$3:$AD$20, Analytique!$Z$3:$Z$20, $G48, Analytique!$Y$3:$Y$20, "A1") ) ) | AD48: =IF($G48="", "", IF(COUNTIFS(Equipements_SCL!$M$16:$M$100, $G48, Equipements_SCL!$J$16:$J$100, AD$37)=0, "", IF(SUMIFS(Equipements_SCL!$AV$16:$AV$100, Equipements_SCL!$M$16:$M$100, $G48, Equipements_SCL!$J$16:$J$100, AD$37)=-1, "", SUMIFS(Equipements_SCL!$P$16:$P$100, Equipements_SCL!$M$16:$M$100, $G48, Equipements_SCL!$J$16:$J$100, AD$37)))) | AE48: =IF($G48="", "", IF(COUNTIFS(Equipements_SCL!$M$16:$M$100, $G48, Equipements_SCL!$J$16:$J$100, AE$37)=0, "", IF(SUMIFS(Equipements_SCL!$AV$16:$AV$100, Equipements_SCL!$M$16:$M$100, $G48, Equipements_SCL!$J$16:$J$100, AE$37)=-1, "", SUMIFS(Equipements_SCL!$P$16:$P$100, Equipements_SCL!$M$16:$M$100, $G48, Equipements_SCL!$J$16:$J$100, AE$37))))
H49: =IF(AND($G49<>"",OR($I49<>"",$J49<>"",$K49<>"")),AVERAGE($I49,$J49,$K49),"") | I49: =IF(AND($G49<>"",OR($AD49<>"",$AE49<>"")),MAX($AD49,$AE49),"") | J49: =IF($G49="", "", IF(COUNTIFS(Equipements_SCL!$M$16:$M$100, $G49, Equipements_SCL!$J$16:$J$100, J$37)=0, "", IF(SUMIFS(Equipements_SCL!$AV$16:$AV$100, Equipements_SCL!$M$16:$M$100, $G49, Equipements_SCL!$J$16:$J$100, J$37)=-1, "", SUMIFS(Equipements_SCL!$P$16:$P$100, Equipements_SCL!$M$16:$M$100, $G49, Equipements_SCL!$J$16:$J$100, J$37)))) | K49: =IF( $G49="", "", IF( SUMIFS(Analytique!$AD$3:$AD$20, Analytique!$Z$3:$Z$20, $G49, Analytique!$Y$3:$Y$20, "A1")=0, "", SUMIFS(Analytique!$AD$3:$AD$20, Analytique!$Z$3:$Z$20, $G49, Analytique!$Y$3:$Y$20, "A1") ) ) | AD49: =IF($G49="", "", IF(COUNTIFS(Equipements_SCL!$M$16:$M$100, $G49, Equipements_SCL!$J$16:$J$100, AD$37)=0, "", IF(SUMIFS(Equipements_SCL!$AV$16:$AV$100, Equipements_SCL!$M$16:$M$100, $G49, Equipements_SCL!$J$16:$J$100, AD$37)=-1, "", SUMIFS(Equipements_SCL!$P$16:$P$100, Equipements_SCL!$M$16:$M$100, $G49, Equipements_SCL!$J$16:$J$100, AD$37)))) | AE49: =IF($G49="", "", IF(COUNTIFS(Equipements_SCL!$M$16:$M$100, $G49, Equipements_SCL!$J$16:$J$100, AE$37)=0, "", IF(SUMIFS(Equipements_SCL!$AV$16:$AV$100, Equipements_SCL!$M$16:$M$100, $G49, Equipements_SCL!$J$16:$J$100, AE$37)=-1, "", SUMIFS(Equipements_SCL!$P$16:$P$100, Equipements_SCL!$M$16:$M$100, $G49, Equipements_SCL!$J$16:$J$100, AE$37))))
H50: =IF(AND($G50<>"",OR($I50<>"",$J50<>"",$K50<>"")),AVERAGE($I50,$J50,$K50),"") | I50: =IF(AND($G50<>"",OR($AD50<>"",$AE50<>"")),MAX($AD50,$AE50),"") | J50: =IF($G50="", "", IF(COUNTIFS(Equipements_SCL!$M$16:$M$100, $G50, Equipements_SCL!$J$16:$J$100, J$37)=0, "", IF(SUMIFS(Equipements_SCL!$AV$16:$AV$100, Equipements_SCL!$M$16:$M$100, $G50, Equipements_SCL!$J$16:$J$100, J$37)=-1, "", SUMIFS(Equipements_SCL!$P$16:$P$100, Equipements_SCL!$M$16:$M$100, $G50, Equipements_SCL!$J$16:$J$100, J$37)))) | K50: =IF( $G50="", "", IF( SUMIFS(Analytique!$AD$3:$AD$20, Analytique!$Z$3:$Z$20, $G50, Analytique!$Y$3:$Y$20, "A1")=0, "", SUMIFS(Analytique!$AD$3:$AD$20, Analytique!$Z$3:$Z$20, $G50, Analytique!$Y$3:$Y$20, "A1") ) ) | AD50: =IF($G50="", "", IF(COUNTIFS(Equipements_SCL!$M$16:$M$100, $G50, Equipements_SCL!$J$16:$J$100, AD$37)=0, "", IF(SUMIFS(Equipements_SCL!$AV$16:$AV$100, Equipements_SCL!$M$16:$M$100, $G50, Equipements_SCL!$J$16:$J$100, AD$37)=-1, "", SUMIFS(Equipements_SCL!$P$16:$P$100, Equipements_SCL!$M$16:$M$100, $G50, Equipements_SCL!$J$16:$J$100, AD$37)))) | AE50: =IF($G50="", "", IF(COUNTIFS(Equipements_SCL!$M$16:$M$100, $G50, Equipements_SCL!$J$16:$J$100, AE$37)=0, "", IF(SUMIFS(Equipements_SCL!$AV$16:$AV$100, Equipements_SCL!$M$16:$M$100, $G50, Equipements_SCL!$J$16:$J$100, AE$37)=-1, "", SUMIFS(Equipements_SCL!$P$16:$P$100, Equipements_SCL!$M$16:$M$100, $G50, Equipements_SCL!$J$16:$J$100, AE$37))))
... H92: =IF(AND($G92<>"",OR($I92<>"",$J92<>"",$K92<>"")),AVERAGE($I92,$J92,$K92),"") | I92: =IF(AND($G92<>"",OR($AD92<>"",$AE92<>"")),MAX($AD92,$AE92),"") | J92: =IF($G92="", "", IF(COUNTIFS(Equipements_SCL!$M$16:$M$100, $G92, Equipements_SCL!$J$16:$J$100, J$37)=0, "", IF(SUMIFS(Equipements_SCL!$AV$16:$AV$100, Equipements_SCL!$M$16:$M$100, $G92, Equipements_SCL!$J$16:$J$100, J$37)=-1, "", SUMIFS(Equipements_SCL!$P$16:$P$100, Equipements_SCL!$M$16:$M$100, $G92, Equipements_SCL!$J$16:$J$100, J$37)))) | K92: =IF( $G92="", "", IF( SUMIFS(Analytique!$AD$3:$AD$20, Analytique!$Z$3:$Z$20, $G92, Analytique!$Y$3:$Y$20, "A1")=0, "", SUMIFS(Analytique!$AD$3:$AD$20, Analytique!$Z$3:$Z$20, $G92, Analytique!$Y$3:$Y$20, "A1") ) ) | AD92: =IF($G92="", "", IF(COUNTIFS(Equipements_SCL!$M$16:$M$100, $G92, Equipements_SCL!$J$16:$J$100, AD$37)=0, "", IF(SUMIFS(Equipements_SCL!$AV$16:$AV$100, Equipements_SCL!$M$16:$M$100, $G92, Equipements_SCL!$J$16:$J$100, AD$37)=-1, "", SUMIFS(Equipements_SCL!$P$16:$P$100, Equipements_SCL!$M$16:$M$100, $G92, Equipements_SCL!$J$16:$J$100, AD$37)))) | AE92: =IF($G92="", "", IF(COUNTIFS(Equipements_SCL!$M$16:$M$100, $G92, Equipements_SCL!$J$16:$J$100, AE$37)=0, "", IF(SUMIFS(Equipements_SCL!$AV$16:$AV$100, Equipements_SCL!$M$16:$M$100, $G92, Equipements_SCL!$J$16:$J$100, AE$37)=-1, "", SUMIFS(Equipements_SCL!$P$16:$P$100, Equipements_SCL!$M$16:$M$100, $G92, Equipements_SCL!$J$16:$J$100, AE$37))))
D97: Commentaire général
C103: DÉTAIL DES CONTRÔLES RÉALISÉS PAR ÉQUIPEMENT D'AUTOSURVEILLANCE
D105: Détails des équipements contrôlés | N105: Score sur 100 | O105: Critères d'évaluation
D106: Libellé | F106: Localisation | G106: Code Point | H106: Type d'équipement | J106: Type de matériel | O106: 1 | P106: 2 | Q106: 3 | R106: 4 | S106: 5 | T106: 6 | U106: 7 | V106: 8 | W106: 9 | X106: 10
D107: =Equipements_SCL!H16 | F107: =Equipements_SCL!I16 | G107: =Equipements_SCL!M16 | H107: =Equipements_SCL!J16 | J107: =Equipements_SCL!K16 | N107: =Equipements_SCL!P16 | O107: =IF(Equipements_SCL!Y16<>"",Equipements_SCL!AK16,"") | P107: =IF(Equipements_SCL!Z16<>"",Equipements_SCL!AL16,"") | Q107: =IF(Equipements_SCL!AA16<>"",Equipements_SCL!AM16,"") | R107: =IF(Equipements_SCL!AB16<>"",Equipements_SCL!AN16,"") | S107: =IF(Equipements_SCL!AC16<>"",Equipements_SCL!AO16,"") | T107: =IF(Equipements_SCL!AD16<>"",Equipements_SCL!AP16,"") | U107: =IF(Equipements_SCL!AE16<>"",Equipements_SCL!AQ16,"") | V107: =IF(Equipements_SCL!AF16<>"",Equipements_SCL!AR16,"") | ... X107: =IF(Equipements_SCL!AH16<>"",Equipements_SCL!AT16,"")
D108: =Equipements_SCL!H17 | F108: =Equipements_SCL!I17 | G108: =Equipements_SCL!M17 | H108: =Equipements_SCL!J17 | J108: =Equipements_SCL!K17 | N108: =Equipements_SCL!P17 | O108: =IF(Equipements_SCL!Y17<>"",Equipements_SCL!AK17,"") | P108: =IF(Equipements_SCL!Z17<>"",Equipements_SCL!AL17,"") | Q108: =IF(Equipements_SCL!AA17<>"",Equipements_SCL!AM17,"") | R108: =IF(Equipements_SCL!AB17<>"",Equipements_SCL!AN17,"") | S108: =IF(Equipements_SCL!AC17<>"",Equipements_SCL!AO17,"") | T108: =IF(Equipements_SCL!AD17<>"",Equipements_SCL!AP17,"") | U108: =IF(Equipements_SCL!AE17<>"",Equipements_SCL!AQ17,"") | V108: =IF(Equipements_SCL!AF17<>"",Equipements_SCL!AR17,"") | ... X108: =IF(Equipements_SCL!AH17<>"",Equipements_SCL!AT17,"")
D109: =Equipements_SCL!H18 | F109: =Equipements_SCL!I18 | G109: =Equipements_SCL!M18 | H109: =Equipements_SCL!J18 | J109: =Equipements_SCL!K18 | N109: =Equipements_SCL!P18 | O109: =IF(Equipements_SCL!Y18<>"",Equipements_SCL!AK18,"") | P109: =IF(Equipements_SCL!Z18<>"",Equipements_SCL!AL18,"") | Q109: =IF(Equipements_SCL!AA18<>"",Equipements_SCL!AM18,"") | R109: =IF(Equipements_SCL!AB18<>"",Equipements_SCL!AN18,"") | S109: =IF(Equipements_SCL!AC18<>"",Equipements_SCL!AO18,"") | T109: =IF(Equipements_SCL!AD18<>"",Equipements_SCL!AP18,"") | U109: =IF(Equipements_SCL!AE18<>"",Equipements_SCL!AQ18,"") | V109: =IF(Equipements_SCL!AF18<>"",Equipements_SCL!AR18,"") | ... X109: =IF(Equipements_SCL!AH18<>"",Equipements_SCL!AT18,"")
D110: =Equipements_SCL!H19 | F110: =Equipements_SCL!I19 | G110: =Equipements_SCL!M19 | H110: =Equipements_SCL!J19 | J110: =Equipements_SCL!K19 | N110: =Equipements_SCL!P19 | O110: =IF(Equipements_SCL!Y19<>"",Equipements_SCL!AK19,"") | P110: =IF(Equipements_SCL!Z19<>"",Equipements_SCL!AL19,"") | Q110: =IF(Equipements_SCL!AA19<>"",Equipements_SCL!AM19,"") | R110: =IF(Equipements_SCL!AB19<>"",Equipements_SCL!AN19,"") | S110: =IF(Equipements_SCL!AC19<>"",Equipements_SCL!AO19,"") | T110: =IF(Equipements_SCL!AD19<>"",Equipements_SCL!AP19,"") | U110: =IF(Equipements_SCL!AE19<>"",Equipements_SCL!AQ19,"") | V110: =IF(Equipements_SCL!AF19<>"",Equipements_SCL!AR19,"") | ... X110: =IF(Equipements_SCL!AH19<>"",Equipements_SCL!AT19,"")
D111: =Equipements_SCL!H20 | F111: =Equipements_SCL!I20 | G111: =Equipements_SCL!M20 | H111: =Equipements_SCL!J20 | J111: =Equipements_SCL!K20 | N111: =Equipements_SCL!P20 | O111: =IF(Equipements_SCL!Y20<>"",Equipements_SCL!AK20,"") | P111: =IF(Equipements_SCL!Z20<>"",Equipements_SCL!AL20,"") | Q111: =IF(Equipements_SCL!AA20<>"",Equipements_SCL!AM20,"") | R111: =IF(Equipements_SCL!AB20<>"",Equipements_SCL!AN20,"") | S111: =IF(Equipements_SCL!AC20<>"",Equipements_SCL!AO20,"") | T111: =IF(Equipements_SCL!AD20<>"",Equipements_SCL!AP20,"") | U111: =IF(Equipements_SCL!AE20<>"",Equipements_SCL!AQ20,"") | V111: =IF(Equipements_SCL!AF20<>"",Equipements_SCL!AR20,"") | ... X111: =IF(Equipements_SCL!AH20<>"",Equipements_SCL!AT20,"")
D112: =Equipements_SCL!H21 | F112: =Equipements_SCL!I21 | G112: =Equipements_SCL!M21 | H112: =Equipements_SCL!J21 | J112: =Equipements_SCL!K21 | N112: =Equipements_SCL!P21 | O112: =IF(Equipements_SCL!Y21<>"",Equipements_SCL!AK21,"") | P112: =IF(Equipements_SCL!Z21<>"",Equipements_SCL!AL21,"") | Q112: =IF(Equipements_SCL!AA21<>"",Equipements_SCL!AM21,"") | R112: =IF(Equipements_SCL!AB21<>"",Equipements_SCL!AN21,"") | S112: =IF(Equipements_SCL!AC21<>"",Equipements_SCL!AO21,"") | T112: =IF(Equipements_SCL!AD21<>"",Equipements_SCL!AP21,"") | U112: =IF(Equipements_SCL!AE21<>"",Equipements_SCL!AQ21,"") | V112: =IF(Equipements_SCL!AF21<>"",Equipements_SCL!AR21,"") | ... X112: =IF(Equipements_SCL!AH21<>"",Equipements_SCL!AT21,"")
D113: =Equipements_SCL!H22 | F113: =Equipements_SCL!I22 | G113: =Equipements_SCL!M22 | H113: =Equipements_SCL!J22 | J113: =Equipements_SCL!K22 | N113: =Equipements_SCL!P22 | O113: =IF(Equipements_SCL!Y22<>"",Equipements_SCL!AK22,"") | P113: =IF(Equipements_SCL!Z22<>"",Equipements_SCL!AL22,"") | Q113: =IF(Equipements_SCL!AA22<>"",Equipements_SCL!AM22,"") | R113: =IF(Equipements_SCL!AB22<>"",Equipements_SCL!AN22,"") | S113: =IF(Equipements_SCL!AC22<>"",Equipements_SCL!AO22,"") | T113: =IF(Equipements_SCL!AD22<>"",Equipements_SCL!AP22,"") | U113: =IF(Equipements_SCL!AE22<>"",Equipements_SCL!AQ22,"") | V113: =IF(Equipements_SCL!AF22<>"",Equipements_SCL!AR22,"") | ... X113: =IF(Equipements_SCL!AH22<>"",Equipements_SCL!AT22,"")
D114: =Equipements_SCL!H23 | F114: =Equipements_SCL!I23 | G114: =Equipements_SCL!M23 | H114: =Equipements_SCL!J23 | J114: =Equipements_SCL!K23 | N114: =Equipements_SCL!P23 | O114: =IF(Equipements_SCL!Y23<>"",Equipements_SCL!AK23,"") | P114: =IF(Equipements_SCL!Z23<>"",Equipements_SCL!AL23,"") | Q114: =IF(Equipements_SCL!AA23<>"",Equipements_SCL!AM23,"") | R114: =IF(Equipements_SCL!AB23<>"",Equipements_SCL!AN23,"") | S114: =IF(Equipements_SCL!AC23<>"",Equipements_SCL!AO23,"") | T114: =IF(Equipements_SCL!AD23<>"",Equipements_SCL!AP23,"") | U114: =IF(Equipements_SCL!AE23<>"",Equipements_SCL!AQ23,"") | V114: =IF(Equipements_SCL!AF23<>"",Equipements_SCL!AR23,"") | ... X114: =IF(Equipements_SCL!AH23<>"",Equipements_SCL!AT23,"")
D115: =Equipements_SCL!H24 | F115: =Equipements_SCL!I24 | G115: =Equipements_SCL!M24 | H115: =Equipements_SCL!J24 | J115: =Equipements_SCL!K24 | N115: =Equipements_SCL!P24 | O115: =IF(Equipements_SCL!Y24<>"",Equipements_SCL!AK24,"") | P115: =IF(Equipements_SCL!Z24<>"",Equipements_SCL!AL24,"") | Q115: =IF(Equipements_SCL!AA24<>"",Equipements_SCL!AM24,"") | R115: =IF(Equipements_SCL!AB24<>"",Equipements_SCL!AN24,"") | S115: =IF(Equipements_SCL!AC24<>"",Equipements_SCL!AO24,"") | T115: =IF(Equipements_SCL!AD24<>"",Equipements_SCL!AP24,"") | U115: =IF(Equipements_SCL!AE24<>"",Equipements_SCL!AQ24,"") | V115: =IF(Equipements_SCL!AF24<>"",Equipements_SCL!AR24,"") | ... X115: =IF(Equipements_SCL!AH24<>"",Equipements_SCL!AT24,"")
D116: =Equipements_SCL!H25 | F116: =Equipements_SCL!I25 | G116: =Equipements_SCL!M25 | H116: =Equipements_SCL!J25 | J116: =Equipements_SCL!K25 | N116: =Equipements_SCL!P25 | O116: =IF(Equipements_SCL!Y25<>"",Equipements_SCL!AK25,"") | P116: =IF(Equipements_SCL!Z25<>"",Equipements_SCL!AL25,"") | Q116: =IF(Equipements_SCL!AA25<>"",Equipements_SCL!AM25,"") | R116: =IF(Equipements_SCL!AB25<>"",Equipements_SCL!AN25,"") | S116: =IF(Equipements_SCL!AC25<>"",Equipements_SCL!AO25,"") | T116: =IF(Equipements_SCL!AD25<>"",Equipements_SCL!AP25,"") | U116: =IF(Equipements_SCL!AE25<>"",Equipements_SCL!AQ25,"") | V116: =IF(Equipements_SCL!AF25<>"",Equipements_SCL!AR25,"") | ... X116: =IF(Equipements_SCL!AH25<>"",Equipements_SCL!AT25,"")
D117: =Equipements_SCL!H26 | F117: =Equipements_SCL!I26 | G117: =Equipements_SCL!M26 | H117: =Equipements_SCL!J26 | J117: =Equipements_SCL!K26 | N117: =Equipements_SCL!P26 | O117: =IF(Equipements_SCL!Y26<>"",Equipements_SCL!AK26,"") | P117: =IF(Equipements_SCL!Z26<>"",Equipements_SCL!AL26,"") | Q117: =IF(Equipements_SCL!AA26<>"",Equipements_SCL!AM26,"") | R117: =IF(Equipements_SCL!AB26<>"",Equipements_SCL!AN26,"") | S117: =IF(Equipements_SCL!AC26<>"",Equipements_SCL!AO26,"") | T117: =IF(Equipements_SCL!AD26<>"",Equipements_SCL!AP26,"") | U117: =IF(Equipements_SCL!AE26<>"",Equipements_SCL!AQ26,"") | V117: =IF(Equipements_SCL!AF26<>"",Equipements_SCL!AR26,"") | ... X117: =IF(Equipements_SCL!AH26<>"",Equipements_SCL!AT26,"")
D118: =Equipements_SCL!H27 | F118: =Equipements_SCL!I27 | G118: =Equipements_SCL!M27 | H118: =Equipements_SCL!J27 | J118: =Equipements_SCL!K27 | N118: =Equipements_SCL!P27 | O118: =IF(Equipements_SCL!Y27<>"",Equipements_SCL!AK27,"") | P118: =IF(Equipements_SCL!Z27<>"",Equipements_SCL!AL27,"") | Q118: =IF(Equipements_SCL!AA27<>"",Equipements_SCL!AM27,"") | R118: =IF(Equipements_SCL!AB27<>"",Equipements_SCL!AN27,"") | S118: =IF(Equipements_SCL!AC27<>"",Equipements_SCL!AO27,"") | T118: =IF(Equipements_SCL!AD27<>"",Equipements_SCL!AP27,"") | U118: =IF(Equipements_SCL!AE27<>"",Equipements_SCL!AQ27,"") | V118: =IF(Equipements_SCL!AF27<>"",Equipements_SCL!AR27,"") | ... X118: =IF(Equipements_SCL!AH27<>"",Equipements_SCL!AT27,"")
... D156: =Equipements_SCL!H65 | F156: =Equipements_SCL!I65 | G156: =Equipements_SCL!M65 | H156: =Equipements_SCL!J65 | J156: =Equipements_SCL!K65 | N156: =Equipements_SCL!P65 | O156: =IF(Equipements_SCL!Y65<>"",Equipements_SCL!AK65,"") | P156: =IF(Equipements_SCL!Z65<>"",Equipements_SCL!AL65,"") | Q156: =IF(Equipements_SCL!AA65<>"",Equipements_SCL!AM65,"") | R156: =IF(Equipements_SCL!AB65<>"",Equipements_SCL!AN65,"") | S156: =IF(Equipements_SCL!AC65<>"",Equipements_SCL!AO65,"") | T156: =IF(Equipements_SCL!AD65<>"",Equipements_SCL!AP65,"") | U156: =IF(Equipements_SCL!AE65<>"",Equipements_SCL!AQ65,"") | V156: =IF(Equipements_SCL!AF65<>"",Equipements_SCL!AR65,"") | ... X156: =IF(Equipements_SCL!AH65<>"",Equipements_SCL!AT65,"")

Sheet SYNTHESE_STEU
C2: CONTRÔLE DES DISPOSITIFS D'AUTOSURVEILLANCE DU SYSTÈME DE TRAITEMENT | Y2: Exporter en Word
C3: NOM DU SYSTÈME D'ASSAINISSEMENT : | G3: =IF(ISBLANK(Descriptif!F3),"",Descriptif!F3) | J3: NOM DU SYSTÈME DE TRAITEMENT : | M3: =IF(ISBLANK(Descriptif!L3),"",Descriptif!L3) | P3: NOM DU SYSTÈME DE COLLECTE : | S3: =IF(ISBLANK(Descriptif!Q3),"",Descriptif!Q3) | V3: NOM DE L'ORGANISME DE CONTRÔLE : | Y3: =IF(ISBLANK(Descriptif!U3),"",Descriptif!U3)
C4: CODE SANDRE DE L'AGGLOMÉRATION : | G4: =IF(ISBLANK(Descriptif!F4),"",Descriptif!F4) | J4: CODE SANDRE DE LA STATION : | M4: =IF(ISBLANK(Descriptif!L4),"",Descriptif!L4) | P4: CODE SANDRE DU RÉSEAU : | S4: =IF(ISBLANK(Descriptif!Q4),"",Descriptif!Q4) | V4: NOM(S) DU(ES) CONTROLEUR(S) : | Y4: =IF(ISBLANK(Descriptif!U4),"",Descriptif!U4)
C5: MAITRE D'OUVRAGE DE LA STATION : | G5: =IF(ISBLANK(Descriptif!F5),"",Descriptif!F5) | J5: TYPE DE TRAITEMENT : | M5: =IF(ISBLANK(Descriptif!L5),"",Descriptif!L5) | P5: TYPE DE RÉSEAU : | S5: =IF(ISBLANK(Descriptif!Q5),"",Descriptif!Q5) | V5: DATE(S) D'INTERVENTION : | Y5: =IF(ISBLANK(Descriptif!U5),"",Descriptif!U5)
C6: EXPLOITANT DE LA STATION : | G6: =IF(ISBLANK(Descriptif!F6),"",Descriptif!F6) | J6: CAPACITÉ DE LA STATION : | M6: =IF(ISBLANK(Descriptif!L6),"",Descriptif!L6) | P6: EXPLOITANT DU RÉSEAU : | S6: =IF(ISBLANK(Descriptif!Q6),"",Descriptif!Q6) | V6: CONDITION(S) MÉTÉO : | Y6: =IF(ISBLANK(Descriptif!U6),"",Descriptif!U6)
C8: SYNTHÈSE DES CONTRÔLES RÉALISÉS SUR LES DISPOSITIFS AUTOSURVEILLANCE
D10: Évaluation des points règlementaires
G11: ENTRÉE et SORTIE | J11: Score | L11: DTS ET BY-PASS | O11: Score | Q11: BOUES ET APPORTS EXTÉRIEURS | T11: Score | V11: RÉUTILISATION DES EAUX TRAITÉES | Y11: Score
G12: Point A3 | J12: =Recap_equipements!E63 | L12: Point A2 | O12: =Recap_equipements!E75 | Q12: Point A6 | T12: =Recap_equipements!E87 | V12: Point A8 | Y12: =Recap_equipements!E105
G13: Débitmètre | J13: =IF(Recap_equipements!F65<>"",Recap_equipements!F65,"") | L13: Débitmètre | O13: =IF(Recap_equipements!F77<>"",Recap_equipements!F77,"") | Q13: Débitmètre | T13: =IF(Recap_equipements!F89<>"",Recap_equipements!F89,"") | V13: Débitmètre | Y13: =IF(Recap_equipements!F107<>"",Recap_equipements!F107,"")
G14: Préleveur | J14: =IF(Recap_equipements!F66<>"",Recap_equipements!F66,"") | L14: Préleveur | O14: =IF(Recap_equipements!F78<>"",Recap_equipements!F78,"") | Q14: Préleveur | T14: =IF(Recap_equipements!F90<>"",Recap_equipements!F90,"") | V14: Préleveur | Y14: =IF(Recap_equipements!F108<>"",Recap_equipements!F108,"")
G15: Analytique | J15: =IF(Recap_equipements!F67<>"",Recap_equipements!F67,"") | L15: Analytique | O15: =IF(Recap_equipements!F79<>"",Recap_equipements!F79,"") | Q15: Analytique | T15: =IF(Recap_equipements!F91<>"",Recap_equipements!F91,"") | V15: Analytique | Y15: =IF(Recap_equipements!F109<>"",Recap_equipements!F109,"")
G16: Point A4 | J16: =Recap_equipements!E69 | L16: Point A5 | O16: =Recap_equipements!E81 | Q16: Point A7 | T16: =Recap_equipements!E93
G17: Débitmètre | J17: =IF(Recap_equipements!F71<>"",Recap_equipements!F71,"") | L17: Débitmètre | O17: =IF(Recap_equipements!F83<>"",Recap_equipements!F83,"") | Q17: Débitmètre | T17: =IF(Recap_equipements!F95<>"",Recap_equipements!F95,"") | V17: Validé
G18: Préleveur | J18: =IF(Recap_equipements!F72<>"",Recap_equipements!F72,"") | L18: Préleveur | O18: =IF(Recap_equipements!F84<>"",Recap_equipements!F84,"") | Q18: Préleveur | T18: =IF(Recap_equipements!F96<>"",Recap_equipements!F96,"") | V18: Réserve
G19: Analytique | J19: =IF(Recap_equipements!F73<>"",Recap_equipements!F73,"") | L19: Analytique | O19: =IF(Recap_equipements!F85<>"",Recap_equipements!F85,"") | Q19: Analytique | T19: =IF(Recap_equipements!F97<>"",Recap_equipements!F97,"") | V19: Non validé
D22: Évaluation documentaire
M23: Coefficient Qualité | N23: Commentaires sur l'évaluation :
G24: Manuel autosurveillance à jour, validé ou en cours d'expertise ? | L24: =IF(Qualité!L10<>"",Qualité!$L$10,"Non contrôlé") -> Non contrôlé | N24: =IF(Qualité!M10<>"",Qualité!$M$10,"")
G25: Existe-t-il un système Qualité performant ? | L25: =IF(Qualité!L29<>"",Qualité!$L$29,"Non contrôlé") -> Non contrôlé | M25: =IF(Qualité!$L$29="Oui",1,0.9) -> 0.9 | N25: =IF(Qualité!$D$32<>"",Qualité!$D$32,"")
D28: Évaluation des pratiques de fractionnement et de transport des échantillons
K29: Penalité | N29: Commentaires sur l'évaluation :
G30: SDE | I30: Aquaref | K30: =IF(Analytique!N11<>"",Analytique!N11,"") | N30: =IF(Analytique!D17<>"",Analytique!D17,"")
G31: Eaux résiduaires | I31: Fractionnement | K31: =IF(Analytique!N12<>"",Analytique!N12,"")
I32: Température | K32: =IF(Analytique!N13<>"",Analytique!N13,"")
I33: Transport | K33: =IF(Analytique!N14<>"",Analytique!N14,"")
D36: Autres évaluations
K37: Score | N37: Commentaires sur l'évaluation :
G38: Sonde température | I38: {=IFERROR(INDEX(Equipements_STEU!$L$16:$L$72,SMALL(IF(Equipements_STEU!$J$16:$J$72="Sonde de température",ROW(Equipements_STEU!$J$16:$J$72)-ROW(Equipements_STEU!$J$16)+1),ROW(1:1))),"")} | K38: {=IFERROR(INDEX(Equipements_STEU!$P$16:$P$72,SMALL(IF(Equipements_STEU!$J$16:$J$72="Sonde de température",ROW(Equipements_STEU!$J$16:$J$72)-ROW(Equipements_STEU!$J$16)+1),ROW(1:1))),"")} | N38: {=IFERROR(INDEX(Equipements_STEU!$T$16:$T$72,SMALL(IF(Equipements_STEU!$J$16:$J$72="Sonde de température",ROW(Equipements_STEU!$J$16:$J$72)-ROW(Equipements_STEU!$J$16)+1),ROW(1:1))),"")}
I39: {=IFERROR(INDEX(Equipements_STEU!$L$16:$L$72,SMALL(IF(Equipements_STEU!$J$16:$J$72="Sonde de température",ROW(Equipements_STEU!$J$16:$J$72)-ROW(Equipements_STEU!$J$16)+1),ROW(2:2))),"")} | K39: {=IFERROR(INDEX(Equipements_STEU!$R$16:$R$72,SMALL(IF(Equipements_STEU!$J$16:$J$72="Sonde de température",ROW(Equipements_STEU!$J$16:$J$72)-ROW(Equipements_STEU!$J$16)+1),ROW(2:2))),"")} | N39: {=IFERROR(INDEX(Equipements_STEU!$T$16:$T$72,SMALL(IF(Equipements_STEU!$J$16:$J$72="Sonde de température",ROW(Equipements_STEU!$J$16:$J$72)-ROW(Equipements_STEU!$J$16)+1),ROW(2:2))),"")}
I40: {=IFERROR(INDEX(Equipements_STEU!$L$16:$L$72,SMALL(IF(Equipements_STEU!$J$16:$J$72="Sonde de température",ROW(Equipements_STEU!$J$16:$J$72)-ROW(Equipements_STEU!$J$16)+1),ROW(3:3))),"")} | K40: {=IFERROR(INDEX(Equipements_STEU!$R$16:$R$72,SMALL(IF(Equipements_STEU!$J$16:$J$72="Sonde de température",ROW(Equipements_STEU!$J$16:$J$72)-ROW(Equipements_STEU!$J$16)+1),ROW(3:3))),"")} | N40: {=IFERROR(INDEX(Equipements_STEU!$T$16:$T$72,SMALL(IF(Equipements_STEU!$J$16:$J$72="Sonde de température",ROW(Equipements_STEU!$J$16:$J$72)-ROW(Equipements_STEU!$J$16)+1),ROW(3:3))),"")}
K42: Score | N42: Commentaires sur l'évaluation :
G43: Pluviomètre | I43: {=IFERROR(INDEX(Equipements_STEU!$L$16:$L$72,SMALL(IF(Equipements_STEU!$J$16:$J$72="Pluviomètre",ROW(Equipements_STEU!$J$16:$J$72)-ROW(Equipements_STEU!$J$16)+1),ROW(1:1))),"")} | K43: {=IFERROR(INDEX(Equipements_STEU!$P$16:$P$72,SMALL(IF(Equipements_STEU!$J$16:$J$72="Pluviomètre",ROW(Equipements_STEU!$J$16:$J$72)-ROW(Equipements_STEU!$J$16)+1),ROW(1:1))),"")} | N43: {=IFERROR(INDEX(Equipements_STEU!$T$16:$T$72,SMALL(IF(Equipements_STEU!$J$16:$J$72="Pluviomètre",ROW(Equipements_STEU!$J$16:$J$72)-ROW(Equipements_STEU!$J$16)+1),ROW(1:1))),"")}
I44: {=IFERROR(INDEX(Equipements_STEU!$L$16:$L$72,SMALL(IF(Equipements_STEU!$J$16:$J$72="Pluviomètre",ROW(Equipements_STEU!$J$16:$J$72)-ROW(Equipements_STEU!$J$16)+1),ROW(2:2))),"")} | K44: {=IFERROR(INDEX(Equipements_STEU!$P$16:$P$72,SMALL(IF(Equipements_STEU!$J$16:$J$72="Pluviomètre",ROW(Equipements_STEU!$J$16:$J$72)-ROW(Equipements_STEU!$J$16)+1),ROW(2:2))),"")} | N44: {=IFERROR(INDEX(Equipements_STEU!$T$16:$T$72,SMALL(IF(Equipements_STEU!$J$16:$J$72="Pluviomètre",ROW(Equipements_STEU!$J$16:$J$72)-ROW(Equipements_STEU!$J$16)+1),ROW(2:2))),"")}
I45: {=IFERROR(INDEX(Equipements_STEU!$L$16:$L$72,SMALL(IF(Equipements_STEU!$J$16:$J$72="Pluviomètre",ROW(Equipements_STEU!$J$16:$J$72)-ROW(Equipements_STEU!$J$16)+1),ROW(3:3))),"")} | K45: {=IFERROR(INDEX(Equipements_STEU!$P$16:$P$72,SMALL(IF(Equipements_STEU!$J$16:$J$72="Pluviomètre",ROW(Equipements_STEU!$J$16:$J$72)-ROW(Equipements_STEU!$J$16)+1),ROW(3:3))),"")} | N45: {=IFERROR(INDEX(Equipements_STEU!$T$16:$T$72,SMALL(IF(Equipements_STEU!$J$16:$J$72="Pluviomètre",ROW(Equipements_STEU!$J$16:$J$72)-ROW(Equipements_STEU!$J$16)+1),ROW(3:3))),"")}
D48: Commentaire général
C54: DÉTAIL DES CONTRÔLES RÉALISÉS PAR ÉQUIPEMENT D'AUTOSURVEILLANCE
D56: Détails des équipements contrôlés | N56: Score sur 100 | O56: Critères d'évaluation
D57: Libellé | F57: Localisation | G57: Code Point | H57: Type d'équipement | J57: Type de matériel | O57: 1 | P57: 2 | Q57: 3 | R57: 4 | S57: 5 | T57: 6 | U57: 7 | V57: 8 | W57: 9 | X57: 10
D58: =Equipements_STEU!H16 | F58: =Equipements_STEU!I16 | G58: =Equipements_STEU!M16 | H58: =Equipements_STEU!J16 | J58: =Equipements_STEU!K16 | N58: =Equipements_STEU!P16 | O58: =IF(Equipements_STEU!Y16<>"",Equipements_STEU!AK16,"") | P58: =IF(Equipements_STEU!Z16<>"",Equipements_STEU!AL16,"") | Q58: =IF(Equipements_STEU!AA16<>"",Equipements_STEU!AM16,"") | R58: =IF(Equipements_STEU!AB16<>"",Equipements_STEU!AN16,"") | S58: =IF(Equipements_STEU!AC16<>"",Equipements_STEU!AO16,"") | T58: =IF(Equipements_STEU!AD16<>"",Equipements_STEU!AP16,"") | U58: =IF(Equipements_STEU!AE16<>"",Equipements_STEU!AQ16,"") | V58: =IF(Equipements_STEU!AF16<>"",Equipements_STEU!AR16,"") | ... X58: =IF(Equipements_STEU!AH16<>"",Equipements_STEU!AT16,"")
D59: =Equipements_STEU!H17 | F59: =Equipements_STEU!I17 | G59: =Equipements_STEU!M17 | H59: =Equipements_STEU!J17 | J59: =Equipements_STEU!K17 | N59: =Equipements_STEU!P17 | O59: =IF(Equipements_STEU!Y17<>"",Equipements_STEU!AK17,"") | P59: =IF(Equipements_STEU!Z17<>"",Equipements_STEU!AL17,"") | Q59: =IF(Equipements_STEU!AA17<>"",Equipements_STEU!AM17,"") | R59: =IF(Equipements_STEU!AB17<>"",Equipements_STEU!AN17,"") | S59: =IF(Equipements_STEU!AC17<>"",Equipements_STEU!AO17,"") | T59: =IF(Equipements_STEU!AD17<>"",Equipements_STEU!AP17,"") | U59: =IF(Equipements_STEU!AE17<>"",Equipements_STEU!AQ17,"") | V59: =IF(Equipements_STEU!AF17<>"",Equipements_STEU!AR17,"") | ... X59: =IF(Equipements_STEU!AH17<>"",Equipements_STEU!AT17,"")
D60: =Equipements_STEU!H18 | F60: =Equipements_STEU!I18 | G60: =Equipements_STEU!M18 | H60: =Equipements_STEU!J18 | J60: =Equipements_STEU!K18 | N60: =Equipements_STEU!P18 | O60: =IF(Equipements_STEU!Y18<>"",Equipements_STEU!AK18,"") | P60: =IF(Equipements_STEU!Z18<>"",Equipements_STEU!AL18,"") | Q60: =IF(Equipements_STEU!AA18<>"",Equipements_STEU!AM18,"") | R60: =IF(Equipements_STEU!AB18<>"",Equipements_STEU!AN18,"") | S60: =IF(Equipements_STEU!AC18<>"",Equipements_STEU!AO18,"") | T60: =IF(Equipements_STEU!AD18<>"",Equipements_STEU!AP18,"") | U60: =IF(Equipements_STEU!AE18<>"",Equipements_STEU!AQ18,"") | V60: =IF(Equipements_STEU!AF18<>"",Equipements_STEU!AR18,"") | ... X60: =IF(Equipements_STEU!AH18<>"",Equipements_STEU!AT18,"")
D61: =Equipements_STEU!H19 | F61: =Equipements_STEU!I19 | G61: =Equipements_STEU!M19 | H61: =Equipements_STEU!J19 | J61: =Equipements_STEU!K19 | N61: =Equipements_STEU!P19 | O61: =IF(Equipements_STEU!Y19<>"",Equipements_STEU!AK19,"") | P61: =IF(Equipements_STEU!Z19<>"",Equipements_STEU!AL19,"") | Q61: =IF(Equipements_STEU!AA19<>"",Equipements_STEU!AM19,"") | R61: =IF(Equipements_STEU!AB19<>"",Equipements_STEU!AN19,"") | S61: =IF(Equipements_STEU!AC19<>"",Equipements_STEU!AO19,"") | T61: =IF(Equipements_STEU!AD19<>"",Equipements_STEU!AP19,"") | U61: =IF(Equipements_STEU!AE19<>"",Equipements_STEU!AQ19,"") | V61: =IF(Equipements_STEU!AF19<>"",Equipements_STEU!AR19,"") | ... X61: =IF(Equipements_STEU!AH19<>"",Equipements_STEU!AT19,"")
D62: =Equipements_STEU!H20 | F62: =Equipements_STEU!I20 | G62: =Equipements_STEU!M20 | H62: =Equipements_STEU!J20 | J62: =Equipements_STEU!K20 | N62: =Equipements_STEU!P20 | O62: =IF(Equipements_STEU!Y20<>"",Equipements_STEU!AK20,"") | P62: =IF(Equipements_STEU!Z20<>"",Equipements_STEU!AL20,"") | Q62: =IF(Equipements_STEU!AA20<>"",Equipements_STEU!AM20,"") | R62: =IF(Equipements_STEU!AB20<>"",Equipements_STEU!AN20,"") | S62: =IF(Equipements_STEU!AC20<>"",Equipements_STEU!AO20,"") | T62: =IF(Equipements_STEU!AD20<>"",Equipements_STEU!AP20,"") | U62: =IF(Equipements_STEU!AE20<>"",Equipements_STEU!AQ20,"") | V62: =IF(Equipements_STEU!AF20<>"",Equipements_STEU!AR20,"") | ... X62: =IF(Equipements_STEU!AH20<>"",Equipements_STEU!AT20,"")
D63: =Equipements_STEU!H21 | F63: =Equipements_STEU!I21 | G63: =Equipements_STEU!M21 | H63: =Equipements_STEU!J21 | J63: =Equipements_STEU!K21 | N63: =Equipements_STEU!P21 | O63: =IF(Equipements_STEU!Y21<>"",Equipements_STEU!AK21,"") | P63: =IF(Equipements_STEU!Z21<>"",Equipements_STEU!AL21,"") | Q63: =IF(Equipements_STEU!AA21<>"",Equipements_STEU!AM21,"") | R63: =IF(Equipements_STEU!AB21<>"",Equipements_STEU!AN21,"") | S63: =IF(Equipements_STEU!AC21<>"",Equipements_STEU!AO21,"") | T63: =IF(Equipements_STEU!AD21<>"",Equipements_STEU!AP21,"") | U63: =IF(Equipements_STEU!AE21<>"",Equipements_STEU!AQ21,"") | V63: =IF(Equipements_STEU!AF21<>"",Equipements_STEU!AR21,"") | ... X63: =IF(Equipements_STEU!AH21<>"",Equipements_STEU!AT21,"")
D64: =Equipements_STEU!H22 | F64: =Equipements_STEU!I22 | G64: =Equipements_STEU!M22 | H64: =Equipements_STEU!J22 | J64: =Equipements_STEU!K22 | N64: =Equipements_STEU!P22 | O64: =IF(Equipements_STEU!Y22<>"",Equipements_STEU!AK22,"") | P64: =IF(Equipements_STEU!Z22<>"",Equipements_STEU!AL22,"") | Q64: =IF(Equipements_STEU!AA22<>"",Equipements_STEU!AM22,"") | R64: =IF(Equipements_STEU!AB22<>"",Equipements_STEU!AN22,"") | S64: =IF(Equipements_STEU!AC22<>"",Equipements_STEU!AO22,"") | T64: =IF(Equipements_STEU!AD22<>"",Equipements_STEU!AP22,"") | U64: =IF(Equipements_STEU!AE22<>"",Equipements_STEU!AQ22,"") | V64: =IF(Equipements_STEU!AF22<>"",Equipements_STEU!AR22,"") | ... X64: =IF(Equipements_STEU!AH22<>"",Equipements_STEU!AT22,"")
D65: =Equipements_STEU!H23 | F65: =Equipements_STEU!I23 | G65: =Equipements_STEU!M23 | H65: =Equipements_STEU!J23 | J65: =Equipements_STEU!K23 | N65: =Equipements_STEU!P23 | O65: =IF(Equipements_STEU!Y23<>"",Equipements_STEU!AK23,"") | P65: =IF(Equipements_STEU!Z23<>"",Equipements_STEU!AL23,"") | Q65: =IF(Equipements_STEU!AA23<>"",Equipements_STEU!AM23,"") | R65: =IF(Equipements_STEU!AB23<>"",Equipements_STEU!AN23,"") | S65: =IF(Equipements_STEU!AC23<>"",Equipements_STEU!AO23,"") | T65: =IF(Equipements_STEU!AD23<>"",Equipements_STEU!AP23,"") | U65: =IF(Equipements_STEU!AE23<>"",Equipements_STEU!AQ23,"") | V65: =IF(Equipements_STEU!AF23<>"",Equipements_STEU!AR23,"") | ... X65: =IF(Equipements_STEU!AH23<>"",Equipements_STEU!AT23,"")
D66: =Equipements_STEU!H24 | F66: =Equipements_STEU!I24 | G66: =Equipements_STEU!M24 | H66: =Equipements_STEU!J24 | J66: =Equipements_STEU!K24 | N66: =Equipements_STEU!P24 | O66: =IF(Equipements_STEU!Y24<>"",Equipements_STEU!AK24,"") | P66: =IF(Equipements_STEU!Z24<>"",Equipements_STEU!AL24,"") | Q66: =IF(Equipements_STEU!AA24<>"",Equipements_STEU!AM24,"") | R66: =IF(Equipements_STEU!AB24<>"",Equipements_STEU!AN24,"") | S66: =IF(Equipements_STEU!AC24<>"",Equipements_STEU!AO24,"") | T66: =IF(Equipements_STEU!AD24<>"",Equipements_STEU!AP24,"") | U66: =IF(Equipements_STEU!AE24<>"",Equipements_STEU!AQ24,"") | V66: =IF(Equipements_STEU!AF24<>"",Equipements_STEU!AR24,"") | ... X66: =IF(Equipements_STEU!AH24<>"",Equipements_STEU!AT24,"")
D67: =Equipements_STEU!H25 | F67: =Equipements_STEU!I25 | G67: =Equipements_STEU!M25 | H67: =Equipements_STEU!J25 | J67: =Equipements_STEU!K25 | N67: =Equipements_STEU!P25 | O67: =IF(Equipements_STEU!Y25<>"",Equipements_STEU!AK25,"") | P67: =IF(Equipements_STEU!Z25<>"",Equipements_STEU!AL25,"") | Q67: =IF(Equipements_STEU!AA25<>"",Equipements_STEU!AM25,"") | R67: =IF(Equipements_STEU!AB25<>"",Equipements_STEU!AN25,"") | S67: =IF(Equipements_STEU!AC25<>"",Equipements_STEU!AO25,"") | T67: =IF(Equipements_STEU!AD25<>"",Equipements_STEU!AP25,"") | U67: =IF(Equipements_STEU!AE25<>"",Equipements_STEU!AQ25,"") | V67: =IF(Equipements_STEU!AF25<>"",Equipements_STEU!AR25,"") | ... X67: =IF(Equipements_STEU!AH25<>"",Equipements_STEU!AT25,"")
D68: =Equipements_STEU!H26 | F68: =Equipements_STEU!I26 | G68: =Equipements_STEU!M26 | H68: =Equipements_STEU!J26 | J68: =Equipements_STEU!K26 | N68: =Equipements_STEU!P26 | O68: =IF(Equipements_STEU!Y26<>"",Equipements_STEU!AK26,"") | P68: =IF(Equipements_STEU!Z26<>"",Equipements_STEU!AL26,"") | Q68: =IF(Equipements_STEU!AA26<>"",Equipements_STEU!AM26,"") | R68: =IF(Equipements_STEU!AB26<>"",Equipements_STEU!AN26,"") | S68: =IF(Equipements_STEU!AC26<>"",Equipements_STEU!AO26,"") | T68: =IF(Equipements_STEU!AD26<>"",Equipements_STEU!AP26,"") | U68: =IF(Equipements_STEU!AE26<>"",Equipements_STEU!AQ26,"") | V68: =IF(Equipements_STEU!AF26<>"",Equipements_STEU!AR26,"") | ... X68: =IF(Equipements_STEU!AH26<>"",Equipements_STEU!AT26,"")
D69: =Equipements_STEU!H27 | F69: =Equipements_STEU!I27 | G69: =Equipements_STEU!M27 | H69: =Equipements_STEU!J27 | J69: =Equipements_STEU!K27 | N69: =Equipements_STEU!P27 | O69: =IF(Equipements_STEU!Y27<>"",Equipements_STEU!AK27,"") | P69: =IF(Equipements_STEU!Z27<>"",Equipements_STEU!AL27,"") | Q69: =IF(Equipements_STEU!AA27<>"",Equipements_STEU!AM27,"") | R69: =IF(Equipements_STEU!AB27<>"",Equipements_STEU!AN27,"") | S69: =IF(Equipements_STEU!AC27<>"",Equipements_STEU!AO27,"") | T69: =IF(Equipements_STEU!AD27<>"",Equipements_STEU!AP27,"") | U69: =IF(Equipements_STEU!AE27<>"",Equipements_STEU!AQ27,"") | V69: =IF(Equipements_STEU!AF27<>"",Equipements_STEU!AR27,"") | ... X69: =IF(Equipements_STEU!AH27<>"",Equipements_STEU!AT27,"")
... D107: =Equipements_STEU!H65 | F107: =Equipements_STEU!I65 | G107: =Equipements_STEU!M65 | H107: =Equipements_STEU!J65 | J107: =Equipements_STEU!K65 | N107: =Equipements_STEU!P65 | O107: =IF(Equipements_STEU!Y65<>"",Equipements_STEU!AK65,"") | P107: =IF(Equipements_STEU!Z65<>"",Equipements_STEU!AL65,"") | Q107: =IF(Equipements_STEU!AA65<>"",Equipements_STEU!AM65,"") | R107: =IF(Equipements_STEU!AB65<>"",Equipements_STEU!AN65,"") | S107: =IF(Equipements_STEU!AC65<>"",Equipements_STEU!AO65,"") | T107: =IF(Equipements_STEU!AD65<>"",Equipements_STEU!AP65,"") | U107: =IF(Equipements_STEU!AE65<>"",Equipements_STEU!AQ65,"") | V107: =IF(Equipements_STEU!AF65<>"",Equipements_STEU!AR65,"") | ... X107: =IF(Equipements_STEU!AH65<>"",Equipements_STEU!AT65,"")

Sheet Qualité
C2: CONTRÔLE DES DISPOSITIFS D'AUTOSURVEILLANCE DES SYSTÈMES D'ASSAINISSEMENT COLLECTIF
C3: STATION : | E3: =IF(ISBLANK(Descriptif!L3),"",Descriptif!L3) | H3: RÉSEAU : | J3: =IF(ISBLANK(Descriptif!Q3),"",Descriptif!Q3) | M3: ORGANISME DE CONTRÔLE : | P3: =IF(ISBLANK(Descriptif!U3),"",Descriptif!U3)
C4: CODE SANDRE : | E4: =IF(ISBLANK(Descriptif!L4),"",Descriptif!L4) | H4: CODE SANDRE : | J4: =IF(ISBLANK(Descriptif!Q4),"",Descriptif!Q4) | M4: NOM(S) CONTROLEUR(S) : | P4: =IF(ISBLANK(Descriptif!U4),"",Descriptif!U4)
C5: MAITRE D'OUVRAGE : | E5: =IF(ISBLANK(Descriptif!F5),"",Descriptif!F5) | H5: TYPE DE RÉSEAU : | J5: =IF(ISBLANK(Descriptif!Q5),"",Descriptif!Q5) | M5: DATE(S) D'INTERVENTION : | P5: =IF(ISBLANK(Descriptif!U5),"",Descriptif!U5)
C6: EXPLOITANT : | E6: =IF(ISBLANK(Descriptif!L6),"",Descriptif!F6) | H6: EXPLOITANT : | J6: =IF(ISBLANK(Descriptif!Q6),"",Descriptif!Q6) | M6: CONDITION(S) METEO : | P6: =IF(ISBLANK(Descriptif!U6),"",Descriptif!U6)
C8: MANUEL D'AUTOSURVEILLANCE
D10: 1 | E10: Est-ce que le manuel autosurveillance est à jour, validé ou en cours d'expertise ?
D12: COMMENTAIRES :
D15: Le manuel d’autosurveillance n’est pas à jour si : * date du MAS ≤ 2015 ; * changement du maitre d’ouvrage ou de l’exploitant ; * construction d’une nouvelle STEU ou la réhabilitation d’une STEU ; * modification des points du système de collecte, de la station de traitement et des points de déversement au milieu ; * modification du référentiel et du schéma SANDRE (ajout ou suppression d’un point d’autosurveillance ou toute autre modification impactant le calcul du rendement) ; * évolutions techniques ou travaux importants sur le système d'assainissement impactant les points d'autosurveillance ; * modifications réglementaires telles que l’adoption d’un nouvel arrêté si impact sur le référentiel, le schéma SANDRE et le matériel d’autosurveillance ; * modifications significatives du suivi métrologique des dispositifs d'autosurveillance ; *modifications significatives concernant la réalisation des analyses d'autosurveillance.
C19: PROCÉDURES DE CONTRÔLES INTERNES DES MATÉRIELS D'AUTOSURVEILLANCE
D21: 2 | E21: Est-ce que le contrôle des débitmètres est réalisé selon les procédures décrites dans le manuel d'autosurveillance ?
D22: 3 | E22: Est-ce que le contrôle des échantillonneurs est réalisé selon les procédures décrites dans le manuel d'autosurveillance ?
D23: 4 | E23: Est-ce que le contrôle des thermomètres est réalisé selon les procédures décrites dans le manuel d'autosurveillance ?
D24: 5 | E24: Est-ce que le contrôle des pluviomètres est réalisé selon les procédures décrites dans le manuel d'autosurveillance ?
D25: 6 | E25: Est-ce que le contrôle des balances est réalisé selon les procédures décrites dans le manuel d'autosurveillance ?
D26: 7 | E26: Est-ce que le contrôle des chronomètres est réalisé selon les procédures décrites dans le manuel d'autosurveillance ?
D27: 8 | E27: Les contrôles internes sont-ils tous tracés, formalisés et suivis (fiches de vie, cartes de contrôle...) ?
D28: 9 | E28: Des fiches de non-conformité et d'action d'amélioration ont-elles été produites ?
E29: Existe-il un système qualité performant ?
D31: COMMENTAIRES :

Sheet Analytique
U1: Ne rien mettre dans cette colonne | V1: Ne rien mettre dans cette colonne | W1: Ne rien mettre dans cette colonne | X1: Ne rien mettre dans cette colonne | AA1: Ne rien mettre dans cette colonne | AB1: Ne rien mettre dans cette colonne | AC1: Ne rien mettre dans cette colonne | AD1: Ne rien mettre dans cette colonne | AE1: Ne rien mettre dans cette colonne
C2: CONTRÔLE DES DISPOSITIFS D'AUTOSURVEILLANCE DES SYSTÈMES D'ASSAINISSEMENT COLLECTIF | U2: Point | V2: nb ana | W2: nb conforme | X2: Code PREL | Y2: Reg. | Z2: Point | AA2: NB ANALYSE | AB2: NB CONFORME | AC2: Coef | AD2: Score | AE2: Evaluation
C3: STATION : | E3: =IF(ISBLANK(Descriptif!L3),"",Descriptif!L3) | H3: RÉSEAU : | J3: =IF(ISBLANK(Descriptif!Q3),"",Descriptif!Q3) | M3: ORGANISME DE CONTRÔLE : | P3: =IF(ISBLANK(Descriptif!U3),"",Descriptif!U3) | X3: {=IFERROR(INDEX($T$21:$T$1021,SMALL(IF($T$21:$T$1021<>"",ROW($T$21:$T$1021)-ROW($T$21)+1),ROW(1:1))),"")} | Y3: =IF(X3<>"",LEFT(X3,2),"") | Z3: =IF($X3<>"",MID($X3, SEARCH("_", $X3) + 1, SEARCH("_", $X3, SEARCH("_",$X3) + 1) - SEARCH("_", $X3) - 1),"") | AA3: {=IFERROR(INDEX($U$21:$U$1021,SMALL(IF($T$21:$T$1021<>"",ROW($T$21:$T$1021)-ROW($T$21)+1),ROW(1:1))),"")} | AB3: {=IFERROR(INDEX($V$21:$V$1021,SMALL(IF($T$21:$T$1021<>"",ROW($T$21:$T$1021)-ROW($T$21)+1),ROW(1:1))),"")} | AC3: {=IFERROR(INDEX($W$21:$W$1021,SMALL(IF($T$21:$T$1021<>"",ROW($T$21:$T$1021)-ROW($T$21)+1),ROW(1:1))),"")} | AD3: =IF(AND(X3<>"",AC3<>""),(AC3/100 * (1-$N$15)*100),"") | AE3: =IF(X3<>"",IF(AD3<>"",IF(AD3>80,"Validé",IF(AD3<70,"Non Validé","Réserve")),"Non contrôlé"),"")
C4: CODE SANDRE : | E4: =IF(ISBLANK(Descriptif!L4),"",Descriptif!L4) | H4: CODE SANDRE : | J4: =IF(ISBLANK(Descriptif!Q4),"",Descriptif!Q4) | M4: NOM(S) CONTROLEUR(S) : | P4: =IF(ISBLANK(Descriptif!U4),"",Descriptif!U4) | X4: {=IFERROR(INDEX($T$21:$T$1021,SMALL(IF($T$21:$T$1021<>"",ROW($T$21:$T$1021)-ROW($T$21)+1),ROW(2:2))),"")} | Y4: =IF(X4<>"",LEFT(X4,2),"") | Z4: =IF($X4<>"",MID($X4, SEARCH("_", $X4) + 1, SEARCH("_", $X4, SEARCH("_",$X4) + 1) - SEARCH("_", $X4) - 1),"") | AA4: {=IFERROR(INDEX($U$21:$U$1021,SMALL(IF($T$21:$T$1021<>"",ROW($T$21:$T$1021)-ROW($T$21)+1),ROW(2:2))),"")} | AB4: {=IFERROR(INDEX($V$21:$V$1021,SMALL(IF($T$21:$T$1021<>"",ROW($T$21:$T$1021)-ROW($T$21)+1),ROW(2:2))),"")} | AC4: {=IFERROR(INDEX($W$21:$W$1021,SMALL(IF($T$21:$T$1021<>"",ROW($T$21:$T$1021)-ROW($T$21)+1),ROW(2:2))),"")} | AD4: =IF(AND(X4<>"",AC4<>""),(AC4/100 * (1-$N$15)*100),"") | AE4: =IF(X4<>"",IF(AD4<>"",IF(AD4>80,"Validé",IF(AD4<70,"Non Validé","Réserve")),"Non contrôlé"),"")
C5: MAITRE D'OUVRAGE : | E5: =IF(ISBLANK(Descriptif!F5),"",Descriptif!F5) | H5: TYPE DE RÉSEAU : | J5: =IF(ISBLANK(Descriptif!Q5),"",Descriptif!Q5) | M5: DATE(S) D'INTERVENTION : | P5: =IF(ISBLANK(Descriptif!U5),"",Descriptif!U5) | X5: {=IFERROR(INDEX($T$21:$T$1021,SMALL(IF($T$21:$T$1021<>"",ROW($T$21:$T$1021)-ROW($T$21)+1),ROW(3:3))),"")} | Y5: =IF(X5<>"",LEFT(X5,2),"") | Z5: =IF($X5<>"",MID($X5, SEARCH("_", $X5) + 1, SEARCH("_", $X5, SEARCH("_",$X5) + 1) - SEARCH("_", $X5) - 1),"") | AA5: {=IFERROR(INDEX($U$21:$U$1021,SMALL(IF($T$21:$T$1021<>"",ROW($T$21:$T$1021)-ROW($T$21)+1),ROW(3:3))),"")} | AB5: {=IFERROR(INDEX($V$21:$V$1021,SMALL(IF($T$21:$T$1021<>"",ROW($T$21:$T$1021)-ROW($T$21)+1),ROW(3:3))),"")} | AC5: {=IFERROR(INDEX($W$21:$W$1021,SMALL(IF($T$21:$T$1021<>"",ROW($T$21:$T$1021)-ROW($T$21)+1),ROW(3:3))),"")} | AD5: =IF(AND(X5<>"",AC5<>""),(AC5/100 * (1-$N$15)*100),"") | AE5: =IF(X5<>"",IF(AD5<>"",IF(AD5>80,"Validé",IF(AD5<70,"Non Validé","Réserve")),"Non contrôlé"),"")
C6: EXPLOITANT : | E6: =IF(ISBLANK(Descriptif!L6),"",Descriptif!F6) | H6: EXPLOITANT : | J6: =IF(ISBLANK(Descriptif!Q6),"",Descriptif!Q6) | M6: CONDITION(S) METEO : | P6: =IF(ISBLANK(Descriptif!U6),"",Descriptif!U6) | X6: {=IFERROR(INDEX($T$21:$T$1021,SMALL(IF($T$21:$T$1021<>"",ROW($T$21:$T$1021)-ROW($T$21)+1),ROW(4:4))),"")} | Y6: =IF(X6<>"",LEFT(X6,2),"") | Z6: =IF($X6<>"",MID($X6, SEARCH("_", $X6) + 1, SEARCH("_", $X6, SEARCH("_",$X6) + 1) - SEARCH("_", $X6) - 1),"") | AA6: {=IFERROR(INDEX($U$21:$U$1021,SMALL(IF($T$21:$T$1021<>"",ROW($T$21:$T$1021)-ROW($T$21)+1),ROW(4:4))),"")} | AB6: {=IFERROR(INDEX($V$21:$V$1021,SMALL(IF($T$21:$T$1021<>"",ROW($T$21:$T$1021)-ROW($T$21)+1),ROW(4:4))),"")} | AC6: {=IFERROR(INDEX($W$21:$W$1021,SMALL(IF($T$21:$T$1021<>"",ROW($T$21:$T$1021)-ROW($T$21)+1),ROW(4:4))),"")} | AD6: =IF(AND(X6<>"",AC6<>""),(AC6/100 * (1-$N$15)*100),"") | AE6: =IF(X6<>"",IF(AD6<>"",IF(AD6>80,"Validé",IF(AD6<70,"Non Validé","Réserve")),"Non contrôlé"),"")
X7: {=IFERROR(INDEX($T$21:$T$1021,SMALL(IF($T$21:$T$1021<>"",ROW($T$21:$T$1021)-ROW($T$21)+1),ROW(5:5))),"")} | Y7: =IF(X7<>"",LEFT(X7,2),"") | Z7: =IF($X7<>"",MID($X7, SEARCH("_", $X7) + 1, SEARCH("_", $X7, SEARCH("_",$X7) + 1) - SEARCH("_", $X7) - 1),"") | AA7: {=IFERROR(INDEX($U$21:$U$1021,SMALL(IF($T$21:$T$1021<>"",ROW($T$21:$T$1021)-ROW($T$21)+1),ROW(5:5))),"")} | AB7: {=IFERROR(INDEX($V$21:$V$1021,SMALL(IF($T$21:$T$1021<>"",ROW($T$21:$T$1021)-ROW($T$21)+1),ROW(5:5))),"")} | AC7: {=IFERROR(INDEX($W$21:$W$1021,SMALL(IF($T$21:$T$1021<>"",ROW($T$21:$T$1021)-ROW($T$21)+1),ROW(5:5))),"")} | AD7: =IF(AND(X7<>"",AC7<>""),(AC7/100 * (1-$N$15)*100),"") | AE7: =IF(X7<>"",IF(AD7<>"",IF(AD7>80,"Validé",IF(AD7<70,"Non Validé","Réserve")),"Non contrôlé"),"")
C8: FRACTIONNEMENT, TEMPÉRATURE ET DÉLAIS DE TRANSPORT DES ÉCHANTILLONS | X8: {=IFERROR(INDEX($T$21:$T$1021,SMALL(IF($T$21:$T$1021<>"",ROW($T$21:$T$1021)-ROW($T$21)+1),ROW(6:6))),"")} | Y8: =IF(X8<>"",LEFT(X8,2),"") | Z8: =IF($X8<>"",MID($X8, SEARCH("_", $X8) + 1, SEARCH("_", $X8, SEARCH("_",$X8) + 1) - SEARCH("_", $X8) - 1),"") | AA8: {=IFERROR(INDEX($U$21:$U$1021,SMALL(IF($T$21:$T$1021<>"",ROW($T$21:$T$1021)-ROW($T$21)+1),ROW(6:6))),"")} | AB8: {=IFERROR(INDEX($V$21:$V$1021,SMALL(IF($T$21:$T$1021<>"",ROW($T$21:$T$1021)-ROW($T$21)+1),ROW(6:6))),"")} | AC8: {=IFERROR(INDEX($W$21:$W$1021,SMALL(IF($T$21:$T$1021<>"",ROW($T$21:$T$1021)-ROW($T$21)+1),ROW(6:6))),"")} | AD8: =IF(AND(X8<>"",AC8<>""),(AC8/100 * (1-$N$15)*100),"") | AE8: =IF(X8<>"",IF(AD8<>"",IF(AD8>80,"Validé",IF(AD8<70,"Non Validé","Réserve")),"Non contrôlé"),"")
X9: {=IFERROR(INDEX($T$21:$T$1021,SMALL(IF($T$21:$T$1021<>"",ROW($T$21:$T$1021)-ROW($T$21)+1),ROW(7:7))),"")} | Y9: =IF(X9<>"",LEFT(X9,2),"") | Z9: =IF($X9<>"",MID($X9, SEARCH("_", $X9) + 1, SEARCH("_", $X9, SEARCH("_",$X9) + 1) - SEARCH("_", $X9) - 1),"") | AA9: {=IFERROR(INDEX($U$21:$U$1021,SMALL(IF($T$21:$T$1021<>"",ROW($T$21:$T$1021)-ROW($T$21)+1),ROW(7:7))),"")} | AB9: {=IFERROR(INDEX($V$21:$V$1021,SMALL(IF($T$21:$T$1021<>"",ROW($T$21:$T$1021)-ROW($T$21)+1),ROW(7:7))),"")} | AC9: {=IFERROR(INDEX($W$21:$W$1021,SMALL(IF($T$21:$T$1021<>"",ROW($T$21:$T$1021)-ROW($T$21)+1),ROW(7:7))),"")} | AD9: =IF(AND(X9<>"",AC9<>""),(AC9/100 * (1-$N$15)*100),"") | AE9: =IF(X9<>"",IF(AD9<>"",IF(AD9>80,"Validé",IF(AD9<70,"Non Validé","Réserve")),"Non contrôlé"),"")
D10: Les échantillons sont-ils constitués, conservés et mis en analyse, selon les règles de l'art en vigueur ? | N10: Pénalité | X10: {=IFERROR(INDEX($T$21:$T$1021,SMALL(IF($T$21:$T$1021<>"",ROW($T$21:$T$1021)-ROW($T$21)+1),ROW(8:8))),"")} | Y10: =IF(X10<>"",LEFT(X10,2),"") | Z10: =IF($X10<>"",MID($X10, SEARCH("_", $X10) + 1, SEARCH("_", $X10, SEARCH("_",$X10) + 1) - SEARCH("_", $X10) - 1),"") | AA10: {=IFERROR(INDEX($U$21:$U$1021,SMALL(IF($T$21:$T$1021<>"",ROW($T$21:$T$1021)-ROW($T$21)+1),ROW(8:8))),"")} | AB10: {=IFERROR(INDEX($V$21:$V$1021,SMALL(IF($T$21:$T$1021<>"",ROW($T$21:$T$1021)-ROW($T$21)+1),ROW(8:8))),"")} | AC10: {=IFERROR(INDEX($W$21:$W$1021,SMALL(IF($T$21:$T$1021<>"",ROW($T$21:$T$1021)-ROW($T$21)+1),ROW(8:8))),"")} | AD10: =IF(AND(X10<>"",AC10<>""),(AC10/100 * (1-$N$15)*100),"") | AE10: =IF(X10<>"",IF(AD10<>"",IF(AD10>80,"Validé",IF(AD10<70,"Non Validé","Réserve")),"Non contrôlé"),"")
D11: Le guide AQUAREF est-il respecté pour le prélèvement des échantillons SDE ? | N11: =IF(L11="","",IF(L11="Non",0.1,0)) | X11: {=IFERROR(INDEX($T$21:$T$1021,SMALL(IF($T$21:$T$1021<>"",ROW($T$21:$T$1021)-ROW($T$21)+1),ROW(9:9))),"")} | Y11: =IF(X11<>"",LEFT(X11,2),"") | Z11: =IF($X11<>"",MID($X11, SEARCH("_", $X11) + 1, SEARCH("_", $X11, SEARCH("_",$X11) + 1) - SEARCH("_", $X11) - 1),"") | AA11: {=IFERROR(INDEX($U$21:$U$1021,SMALL(IF($T$21:$T$1021<>"",ROW($T$21:$T$1021)-ROW($T$21)+1),ROW(9:9))),"")} | AB11: {=IFERROR(INDEX($V$21:$V$1021,SMALL(IF($T$21:$T$1021<>"",ROW($T$21:$T$1021)-ROW($T$21)+1),ROW(9:9))),"")} | AC11: {=IFERROR(INDEX($W$21:$W$1021,SMALL(IF($T$21:$T$1021<>"",ROW($T$21:$T$1021)-ROW($T$21)+1),ROW(9:9))),"")} | AD11: =IF(AND(X11<>"",AC11<>""),(AC11/100 * (1-$N$15)*100),"") | AE11: =IF(X11<>"",IF(AD11<>"",IF(AD11>80,"Validé",IF(AD11<70,"Non Validé","Réserve")),"Non contrôlé"),"")
D12: Les échantillons sont-ils fractionnés selon la norme FDT 90-523-2 ? | N12: =IF(L12="","",IF(L12="Non",0.1,0)) | X12: {=IFERROR(INDEX($T$21:$T$1021,SMALL(IF($T$21:$T$1021<>"",ROW($T$21:$T$1021)-ROW($T$21)+1),ROW(10:10))),"")} | Y12: =IF(X12<>"",LEFT(X12,2),"") | Z12: =IF($X12<>"",MID($X12, SEARCH("_", $X12) + 1, SEARCH("_", $X12, SEARCH("_",$X12) + 1) - SEARCH("_", $X12) - 1),"") | AA12: {=IFERROR(INDEX($U$21:$U$1021,SMALL(IF($T$21:$T$1021<>"",ROW($T$21:$T$1021)-ROW($T$21)+1),ROW(10:10))),"")} | AB12: {=IFERROR(INDEX($V$21:$V$1021,SMALL(IF($T$21:$T$1021<>"",ROW($T$21:$T$1021)-ROW($T$21)+1),ROW(10:10))),"")} | AC12: {=IFERROR(INDEX($W$21:$W$1021,SMALL(IF($T$21:$T$1021<>"",ROW($T$21:$T$1021)-ROW($T$21)+1),ROW(10:10))),"")} | AD12: =IF(AND(X12<>"",AC12<>""),(AC12/100 * (1-$N$15)*100),"") | AE12: =IF(X12<>"",IF(AD12<>"",IF(AD12>80,"Validé",IF(AD12<70,"Non Validé","Réserve")),"Non contrôlé"),"")
D13: La conservation pendant le transport des échantillons est-elle assurée à 5°C ± 3°C ? | N13: =IF(L13="","",IF(L13="Non",0.1,0)) | X13: {=IFERROR(INDEX($T$21:$T$1021,SMALL(IF($T$21:$T$1021<>"",ROW($T$21:$T$1021)-ROW($T$21)+1),ROW(11:11))),"")} | Y13: =IF(X13<>"",LEFT(X13,2),"") | Z13: =IF($X13<>"",MID($X13, SEARCH("_", $X13) + 1, SEARCH("_", $X13, SEARCH("_",$X13) + 1) - SEARCH("_", $X13) - 1),"") | AA13: {=IFERROR(INDEX($U$21:$U$1021,SMALL(IF($T$21:$T$1021<>"",ROW($T$21:$T$1021)-ROW($T$21)+1),ROW(11:11))),"")} | AB13: {=IFERROR(INDEX($V$21:$V$1021,SMALL(IF($T$21:$T$1021<>"",ROW($T$21:$T$1021)-ROW($T$21)+1),ROW(11:11))),"")} | AC13: {=IFERROR(INDEX($W$21:$W$1021,SMALL(IF($T$21:$T$1021<>"",ROW($T$21:$T$1021)-ROW($T$21)+1),ROW(11:11))),"")} | AD13: =IF(AND(X13<>"",AC13<>""),(AC13/100 * (1-$N$15)*100),"") | AE13: =IF(X13<>"",IF(AD13<>"",IF(AD13>80,"Validé",IF(AD13<70,"Non Validé","Réserve")),"Non contrôlé"),"")
D14: Les conditions de transport permettent-elles l'acheminement et la réception des échantillons dans les 24 h ? | N14: =IF(L14="","",IF(L14="Non",0.1,0)) | X14: {=IFERROR(INDEX($T$21:$T$1021,SMALL(IF($T$21:$T$1021<>"",ROW($T$21:$T$1021)-ROW($T$21)+1),ROW(12:12))),"")} | Y14: =IF(X14<>"",LEFT(X14,2),"") | Z14: =IF($X14<>"",MID($X14, SEARCH("_", $X14) + 1, SEARCH("_", $X14, SEARCH("_",$X14) + 1) - SEARCH("_", $X14) - 1),"") | AA14: {=IFERROR(INDEX($U$21:$U$1021,SMALL(IF($T$21:$T$1021<>"",ROW($T$21:$T$1021)-ROW($T$21)+1),ROW(12:12))),"")} | AB14: {=IFERROR(INDEX($V$21:$V$1021,SMALL(IF($T$21:$T$1021<>"",ROW($T$21:$T$1021)-ROW($T$21)+1),ROW(12:12))),"")} | AC14: {=IFERROR(INDEX($W$21:$W$1021,SMALL(IF($T$21:$T$1021<>"",ROW($T$21:$T$1021)-ROW($T$21)+1),ROW(12:12))),"")} | AD14: =IF(AND(X14<>"",AC14<>""),(AC14/100 * (1-$N$15)*100),"") | AE14: =IF(X14<>"",IF(AD14<>"",IF(AD14>80,"Validé",IF(AD14<70,"Non Validé","Réserve")),"Non contrôlé"),"")
L15: Total pénalité : | N15: =SUM(N11:P14) -> 0 | X15: {=IFERROR(INDEX($T$21:$T$1021,SMALL(IF($T$21:$T$1021<>"",ROW($T$21:$T$1021)-ROW($T$21)+1),ROW(13:13))),"")} | Y15: =IF(X15<>"",LEFT(X15,2),"") | Z15: =IF($X15<>"",MID($X15, SEARCH("_", $X15) + 1, SEARCH("_", $X15, SEARCH("_",$X15) + 1) - SEARCH("_", $X15) - 1),"") | AA15: {=IFERROR(INDEX($U$21:$U$1021,SMALL(IF($T$21:$T$1021<>"",ROW($T$21:$T$1021)-ROW($T$21)+1),ROW(13:13))),"")} | AB15: {=IFERROR(INDEX($V$21:$V$1021,SMALL(IF($T$21:$T$1021<>"",ROW($T$21:$T$1021)-ROW($T$21)+1),ROW(13:13))),"")} | AC15: {=IFERROR(INDEX($W$21:$W$1021,SMALL(IF($T$21:$T$1021<>"",ROW($T$21:$T$1021)-ROW($T$21)+1),ROW(13:13))),"")} | AD15: =IF(AND(X15<>"",AC15<>""),(AC15/100 * (1-$N$15)*100),"") | AE15: =IF(X15<>"",IF(AD15<>"",IF(AD15>80,"Validé",IF(AD15<70,"Non Validé","Réserve")),"Non contrôlé"),"")
D16: COMMENTAIRES : | Y16: =IF(X16<>"",LEFT(X16,2),"") | Z16: =IF($X16<>"",MID($X16, SEARCH("_", $X16) + 1, SEARCH("_", $X16, SEARCH("_",$X16) + 1) - SEARCH("_", $X16) - 1),"") | AD16: =IF(AND(X16<>"",AC16<>""),(AC16/100 * (1-$N$15)*100),"") | AE16: =IF(X16<>"",IF(AD16<>"",IF(AD16>80,"Validé",IF(AD16<70,"Non Validé","Réserve")),"Non contrôlé"),"")
Y17: =IF(X17<>"",LEFT(X17,2),"") | Z17: =IF($X17<>"",MID($X17, SEARCH("_", $X17) + 1, SEARCH("_", $X17, SEARCH("_",$X17) + 1) - SEARCH("_", $X17) - 1),"") | AD17: =IF(AND(X17<>"",AC17<>""),(AC17/100 * (1-$N$15)*100),"") | AE17: =IF(X17<>"",IF(AD17<>"",IF(AD17>80,"Validé",IF(AD17<70,"Non Validé","Réserve")),"Non contrôlé"),"")
Y18: =IF(X18<>"",LEFT(X18,2),"") | Z18: =IF($X18<>"",MID($X18, SEARCH("_", $X18) + 1, SEARCH("_", $X18, SEARCH("_",$X18) + 1) - SEARCH("_", $X18) - 1),"") | AD18: =IF(AND(X18<>"",AC18<>""),(AC18/100 * (1-$N$15)*100),"") | AE18: =IF(X18<>"",IF(AD18<>"",IF(AD18>80,"Validé",IF(AD18<70,"Non Validé","Réserve")),"Non contrôlé"),"")
X19: {=IFERROR(INDEX($T$21:$T$1021,SMALL(IF($T$21:$T$1021<>"",ROW($T$21:$T$1021)-ROW($T$21)+1),ROW(14:14))),"")} | Y19: =IF(X19<>"",LEFT(X19,2),"") | Z19: =IF($X19<>"",MID($X19, SEARCH("_", $X19) + 1, SEARCH("_", $X19, SEARCH("_",$X19) + 1) - SEARCH("_", $X19) - 1),"") | AA19: {=IFERROR(INDEX($U$21:$U$1021,SMALL(IF($T$21:$T$1021<>"",ROW($T$21:$T$1021)-ROW($T$21)+1),ROW(14:14))),"")} | AB19: {=IFERROR(INDEX($V$21:$V$1021,SMALL(IF($T$21:$T$1021<>"",ROW($T$21:$T$1021)-ROW($T$21)+1),ROW(14:14))),"")} | AC19: {=IFERROR(INDEX($W$21:$W$1021,SMALL(IF($T$21:$T$1021<>"",ROW($T$21:$T$1021)-ROW($T$21)+1),ROW(14:14))),"")} | AD19: =IF(AND(X19<>"",AC19<>""),(AC19/100 * (1-$N$15)*100),"") | AE19: =IF(X19<>"",IF(AD19<>"",IF(AD19>80,"Validé",IF(AD19<70,"Non Validé","Réserve")),"Non contrôlé"),"")
X20: {=IFERROR(INDEX($T$21:$T$1021,SMALL(IF($T$21:$T$1021<>"",ROW($T$21:$T$1021)-ROW($T$21)+1),ROW(15:15))),"")} | Y20: =IF(X20<>"",LEFT(X20,2),"") | Z20: =IF($X20<>"",MID($X20, SEARCH("_", $X20) + 1, SEARCH("_", $X20, SEARCH("_",$X20) + 1) - SEARCH("_", $X20) - 1),"") | AA20: {=IFERROR(INDEX($U$21:$U$1021,SMALL(IF($T$21:$T$1021<>"",ROW($T$21:$T$1021)-ROW($T$21)+1),ROW(15:15))),"")} | AB20: {=IFERROR(INDEX($V$21:$V$1021,SMALL(IF($T$21:$T$1021<>"",ROW($T$21:$T$1021)-ROW($T$21)+1),ROW(15:15))),"")} | AC20: {=IFERROR(INDEX($W$21:$W$1021,SMALL(IF($T$21:$T$1021<>"",ROW($T$21:$T$1021)-ROW($T$21)+1),ROW(15:15))),"")} | AD20: =IF(AND(X20<>"",AC20<>""),(AC20/100 * (1-$N$15)*100),"") | AE20: =IF(X20<>"",IF(AD20<>"",IF(AD20>80,"Validé",IF(AD20<70,"Non Validé","Réserve")),"Non contrôlé"),"")
C21: COMPARATIF ANALYTIQUE | K21: (Dupliquer ce bloc en cas de comparatif multiple en utilisant le bouton du bas)
D23: Informations sur le comparatif analytique
D24: Préleveur : | K24: Date du comparatif :
D25: Le comparatif est-il effectué à partir des prélèvements d'une autre station ? | K25: Dans l'affirmative, préciser la station :
D27: Les analyses sont-elles correctement effectuées ?
D28: Nom du(des) laboratoire(s) réalisant les analyses de la matrice eau :
D29: Nom du(des) laboratoire(s) réalisant l'analyse de la siccité des boues et des matières sèches :
D30: Le(s) laboratoire(s) est/sont-il(s) agréé(s) au titre du code de l’environnement pour l'ensemble des paramètres de la matrice eau résiduaire ?
D31: A défaut, est ce que le laboratoire réalise un exercice concluant d’intercalibration avec un laboratoire agréé ?
D33: Résultats du comparatif analytique
D34: Paramètres | F34: LQ en mg/l | G34: Laboratoire du Maître d'Ouvrage/exploitant | I34: COFRAC | J34: Laboratoire de contrôle | L34: COFRAC | M34: Nombre d'analyses réalisées | O34: Nombre d'analyses conformes | Q34: Coefficient Analytique
M35: =COUNTA(G37:H46) -> 0 | O35: =COUNTIF(O37:P46,"=Oui") -> 0 | Q35: =IF(OR($J30="Oui",$J31="Oui"),100*(1-N15),IF(M35>0,(O35/M35)*100*(1-N15),0)) -> 0 | T35: =IF(G24<>"",G24,"") | U35: =IF(T35<>"",M35,"") | V35: =IF(T35<>"",O35,"") | W35: =IF(Q35<>"",Q35,"") -> 0
M36: Ecart (%) | O36: Conformité | Q36: EMT
D37: DBO5 | F37: =VLOOKUP(D37, 'SeuilsComparaison-EMT'!$C$5:$E$28, 3, FALSE) -> 3 | M37: =IF(OR(J37="",G37=""),"",IF(ISERROR(VLOOKUP(D37,'SeuilsComparaison-EMT'!$C$5:$J$25,4,FALSE)),"-",IF(OR(IF(ISTEXT(J37)=TRUE,SUBSTITUTE(J37,"<","",1)*1,J37)>VLOOKUP(D37,'SeuilsComparaison-EMT'!$C$5:$J$25,4,FALSE),IF(ISTEXT(G37)=TRUE,SUBSTITUTE(G37,"<","",1)*1,G37)>VLOOKUP(D37,'SeuilsComparaison-EMT'!$C$5:$J$25,4,FALSE)=TRUE),(IF(ISTEXT(G37)=TRUE,SUBSTITUTE(G37,"<","",1)*1,G37)-((IF(ISTEXT(G37)=TRUE,SUBSTITUTE(G37,"<","",1)*1,G37)+IF(ISTEXT(J37)=TRUE,SUBSTITUTE(J37,"<","",1)*1,J37))/2))/((IF(ISTEXT(G37)=TRUE,SUBSTITUTE(G37,"<","",1)*1,G37)+IF(ISTEXT(J37)=TRUE,SUBSTITUTE(J37,"<","",1),J37))/2),"-"))) | O37: =IF(OR(G37="",J37=""),"",IF(AND(I37="Oui",L37="Oui"),"Oui",IF(M37="-","Oui",IF(OR(J37>VLOOKUP($D37,'SeuilsComparaison-EMT'!$C$5:$J$27,4,FALSE),G37>VLOOKUP($D37,'SeuilsComparaison-EMT'!$C$5:$J$27,4,FALSE)=TRUE),IF(J37<=VLOOKUP($D37,'SeuilsComparaison-EMT'!$C$5:$J$27,5,FALSE),IF(ABS(M37)<=VLOOKUP($D37,'SeuilsComparaison-EMT'!$C$5:$J$27,6,FALSE),"Oui","Non"),IF(ABS(M37)<=VLOOKUP($D37,'SeuilsComparaison-EMT'!$C$5:$J$27,8,FALSE),"Oui","Non")),"Oui")))) | Q37: =IF(OR(AND(ISNUMBER(G37),G37>VLOOKUP(D37,'SeuilsComparaison-EMT'!$C$5:$J$27,4,FALSE)),AND(ISNUMBER(J37),J37>VLOOKUP(D37,'SeuilsComparaison-EMT'!$C$5:$J$27,4,FALSE))),IF(AVERAGE(G37,J37)<=VLOOKUP(D37,'SeuilsComparaison-EMT'!$C$5:$J$27,5,FALSE),VLOOKUP(D37,'SeuilsComparaison-EMT'!$C$5:$J$27,6,FALSE),VLOOKUP(D37,'SeuilsComparaison-EMT'!$C$5:$J$27,8,FALSE)),"")
D38: DCO | F38: =VLOOKUP(D38, 'SeuilsComparaison-EMT'!$C$5:$E$28, 3, FALSE) -> 30 | M38: =IF(OR(J38="",G38=""),"",IF(ISERROR(VLOOKUP(D38,'SeuilsComparaison-EMT'!$C$5:$J$25,4,FALSE)),"-",IF(OR(IF(ISTEXT(J38)=TRUE,SUBSTITUTE(J38,"<","",1)*1,J38)>VLOOKUP(D38,'SeuilsComparaison-EMT'!$C$5:$J$25,4,FALSE),IF(ISTEXT(G38)=TRUE,SUBSTITUTE(G38,"<","",1)*1,G38)>VLOOKUP(D38,'SeuilsComparaison-EMT'!$C$5:$J$25,4,FALSE)=TRUE),(IF(ISTEXT(G38)=TRUE,SUBSTITUTE(G38,"<","",1)*1,G38)-((IF(ISTEXT(G38)=TRUE,SUBSTITUTE(G38,"<","",1)*1,G38)+IF(ISTEXT(J38)=TRUE,SUBSTITUTE(J38,"<","",1)*1,J38))/2))/((IF(ISTEXT(G38)=TRUE,SUBSTITUTE(G38,"<","",1)*1,G38)+IF(ISTEXT(J38)=TRUE,SUBSTITUTE(J38,"<","",1),J38))/2),"-"))) | O38: =IF(OR(G38="",J38=""),"",IF(AND(I38="Oui",L38="Oui"),"Oui",IF(M38="-","Oui",IF(OR(J38>VLOOKUP($D38,'SeuilsComparaison-EMT'!$C$5:$J$27,4,FALSE),G38>VLOOKUP($D38,'SeuilsComparaison-EMT'!$C$5:$J$27,4,FALSE)=TRUE),IF(J38<=VLOOKUP($D38,'SeuilsComparaison-EMT'!$C$5:$J$27,5,FALSE),IF(ABS(M38)<=VLOOKUP($D38,'SeuilsComparaison-EMT'!$C$5:$J$27,6,FALSE),"Oui","Non"),IF(ABS(M38)<=VLOOKUP($D38,'SeuilsComparaison-EMT'!$C$5:$J$27,8,FALSE),"Oui","Non")),"Oui")))) | Q38: =IF(OR(AND(ISNUMBER(G38),G38>VLOOKUP(D38,'SeuilsComparaison-EMT'!$C$5:$J$27,4,FALSE)),AND(ISNUMBER(J38),J38>VLOOKUP(D38,'SeuilsComparaison-EMT'!$C$5:$J$27,4,FALSE))),IF(AVERAGE(G38,J38)<=VLOOKUP(D38,'SeuilsComparaison-EMT'!$C$5:$J$27,5,FALSE),VLOOKUP(D38,'SeuilsComparaison-EMT'!$C$5:$J$27,6,FALSE),VLOOKUP(D38,'SeuilsComparaison-EMT'!$C$5:$J$27,8,FALSE)),"")
D39: ST DCO | F39: =VLOOKUP(D39, 'SeuilsComparaison-EMT'!$C$5:$E$28, 3, FALSE) -> 10 | M39: =IF(OR(J39="",G39=""),"",IF(ISERROR(VLOOKUP(D39,'SeuilsComparaison-EMT'!$C$5:$J$25,4,FALSE)),"-",IF(OR(IF(ISTEXT(J39)=TRUE,SUBSTITUTE(J39,"<","",1)*1,J39)>VLOOKUP(D39,'SeuilsComparaison-EMT'!$C$5:$J$25,4,FALSE),IF(ISTEXT(G39)=TRUE,SUBSTITUTE(G39,"<","",1)*1,G39)>VLOOKUP(D39,'SeuilsComparaison-EMT'!$C$5:$J$25,4,FALSE)=TRUE),(IF(ISTEXT(G39)=TRUE,SUBSTITUTE(G39,"<","",1)*1,G39)-((IF(ISTEXT(G39)=TRUE,SUBSTITUTE(G39,"<","",1)*1,G39)+IF(ISTEXT(J39)=TRUE,SUBSTITUTE(J39,"<","",1)*1,J39))/2))/((IF(ISTEXT(G39)=TRUE,SUBSTITUTE(G39,"<","",1)*1,G39)+IF(ISTEXT(J39)=TRUE,SUBSTITUTE(J39,"<","",1),J39))/2),"-"))) | O39: =IF(OR(G39="",J39=""),"",IF(AND(I39="Oui",L39="Oui"),"Oui",IF(M39="-","Oui",IF(OR(J39>VLOOKUP($D39,'SeuilsComparaison-EMT'!$C$5:$J$27,4,FALSE),G39>VLOOKUP($D39,'SeuilsComparaison-EMT'!$C$5:$J$27,4,FALSE)=TRUE),IF(J39<=VLOOKUP($D39,'SeuilsComparaison-EMT'!$C$5:$J$27,5,FALSE),IF(ABS(M39)<=VLOOKUP($D39,'SeuilsComparaison-EMT'!$C$5:$J$27,6,FALSE),"Oui","Non"),IF(ABS(M39)<=VLOOKUP($D39,'SeuilsComparaison-EMT'!$C$5:$J$27,8,FALSE),"Oui","Non")),"Oui")))) | Q39: =IF(OR(AND(ISNUMBER(G39),G39>VLOOKUP(D39,'SeuilsComparaison-EMT'!$C$5:$J$27,4,FALSE)),AND(ISNUMBER(J39),J39>VLOOKUP(D39,'SeuilsComparaison-EMT'!$C$5:$J$27,4,FALSE))),IF(AVERAGE(G39,J39)<=VLOOKUP(D39,'SeuilsComparaison-EMT'!$C$5:$J$27,5,FALSE),VLOOKUP(D39,'SeuilsComparaison-EMT'!$C$5:$J$27,6,FALSE),VLOOKUP(D39,'SeuilsComparaison-EMT'!$C$5:$J$27,8,FALSE)),"")
D40: MEST | F40: =VLOOKUP(D40, 'SeuilsComparaison-EMT'!$C$5:$E$28, 3, FALSE) -> 2 | M40: =IF(OR(J40="",G40=""),"",IF(ISERROR(VLOOKUP(D40,'SeuilsComparaison-EMT'!$C$5:$J$25,4,FALSE)),"-",IF(OR(IF(ISTEXT(J40)=TRUE,SUBSTITUTE(J40,"<","",1)*1,J40)>VLOOKUP(D40,'SeuilsComparaison-EMT'!$C$5:$J$25,4,FALSE),IF(ISTEXT(G40)=TRUE,SUBSTITUTE(G40,"<","",1)*1,G40)>VLOOKUP(D40,'SeuilsComparaison-EMT'!$C$5:$J$25,4,FALSE)=TRUE),(IF(ISTEXT(G40)=TRUE,SUBSTITUTE(G40,"<","",1)*1,G40)-((IF(ISTEXT(G40)=TRUE,SUBSTITUTE(G40,"<","",1)*1,G40)+IF(ISTEXT(J40)=TRUE,SUBSTITUTE(J40,"<","",1)*1,J40))/2))/((IF(ISTEXT(G40)=TRUE,SUBSTITUTE(G40,"<","",1)*1,G40)+IF(ISTEXT(J40)=TRUE,SUBSTITUTE(J40,"<","",1),J40))/2),"-"))) | O40: =IF(OR(G40="",J40=""),"",IF(AND(I40="Oui",L40="Oui"),"Oui",IF(M40="-","Oui",IF(OR(J40>VLOOKUP($D40,'SeuilsComparaison-EMT'!$C$5:$J$27,4,FALSE),G40>VLOOKUP($D40,'SeuilsComparaison-EMT'!$C$5:$J$27,4,FALSE)=TRUE),IF(J40<=VLOOKUP($D40,'SeuilsComparaison-EMT'!$C$5:$J$27,5,FALSE),IF(ABS(M40)<=VLOOKUP($D40,'SeuilsComparaison-EMT'!$C$5:$J$27,6,FALSE),"Oui","Non"),IF(ABS(M40)<=VLOOKUP($D40,'SeuilsComparaison-EMT'!$C$5:$J$27,8,FALSE),"Oui","Non")),"Oui")))) | Q40: =IF(OR(AND(ISNUMBER(G40),G40>VLOOKUP(D40,'SeuilsComparaison-EMT'!$C$5:$J$27,4,FALSE)),AND(ISNUMBER(J40),J40>VLOOKUP(D40,'SeuilsComparaison-EMT'!$C$5:$J$27,4,FALSE))),IF(AVERAGE(G40,J40)<=VLOOKUP(D40,'SeuilsComparaison-EMT'!$C$5:$J$27,5,FALSE),VLOOKUP(D40,'SeuilsComparaison-EMT'!$C$5:$J$27,6,FALSE),VLOOKUP(D40,'SeuilsComparaison-EMT'!$C$5:$J$27,8,FALSE)),"")
D41: NKJ (N) | F41: =VLOOKUP(D41, 'SeuilsComparaison-EMT'!$C$5:$E$28, 3, FALSE) -> 0.5 | M41: =IF(OR(J41="",G41=""),"",IF(ISERROR(VLOOKUP(D41,'SeuilsComparaison-EMT'!$C$5:$J$25,4,FALSE)),"-",IF(OR(IF(ISTEXT(J41)=TRUE,SUBSTITUTE(J41,"<","",1)*1,J41)>VLOOKUP(D41,'SeuilsComparaison-EMT'!$C$5:$J$25,4,FALSE),IF(ISTEXT(G41)=TRUE,SUBSTITUTE(G41,"<","",1)*1,G41)>VLOOKUP(D41,'SeuilsComparaison-EMT'!$C$5:$J$25,4,FALSE)=TRUE),(IF(ISTEXT(G41)=TRUE,SUBSTITUTE(G41,"<","",1)*1,G41)-((IF(ISTEXT(G41)=TRUE,SUBSTITUTE(G41,"<","",1)*1,G41)+IF(ISTEXT(J41)=TRUE,SUBSTITUTE(J41,"<","",1)*1,J41))/2))/((IF(ISTEXT(G41)=TRUE,SUBSTITUTE(G41,"<","",1)*1,G41)+IF(ISTEXT(J41)=TRUE,SUBSTITUTE(J41,"<","",1),J41))/2),"-"))) | O41: =IF(OR(G41="",J41=""),"",IF(AND(I41="Oui",L41="Oui"),"Oui",IF(M41="-","Oui",IF(OR(J41>VLOOKUP($D41,'SeuilsComparaison-EMT'!$C$5:$J$27,4,FALSE),G41>VLOOKUP($D41,'SeuilsComparaison-EMT'!$C$5:$J$27,4,FALSE)=TRUE),IF(J41<=VLOOKUP($D41,'SeuilsComparaison-EMT'!$C$5:$J$27,5,FALSE),IF(ABS(M41)<=VLOOKUP($D41,'SeuilsComparaison-EMT'!$C$5:$J$27,6,FALSE),"Oui","Non"),IF(ABS(M41)<=VLOOKUP($D41,'SeuilsComparaison-EMT'!$C$5:$J$27,8,FALSE),"Oui","Non")),"Oui")))) | Q41: =IF(OR(AND(ISNUMBER(G41),G41>VLOOKUP(D41,'SeuilsComparaison-EMT'!$C$5:$J$27,4,FALSE)),AND(ISNUMBER(J41),J41>VLOOKUP(D41,'SeuilsComparaison-EMT'!$C$5:$J$27,4,FALSE))),IF(AVERAGE(G41,J41)<=VLOOKUP(D41,'SeuilsComparaison-EMT'!$C$5:$J$27,5,FALSE),VLOOKUP(D41,'SeuilsComparaison-EMT'!$C$5:$J$27,6,FALSE),VLOOKUP(D41,'SeuilsComparaison-EMT'!$C$5:$J$27,8,FALSE)),"")
D42: NGL | F42: =VLOOKUP(D42, 'SeuilsComparaison-EMT'!$C$5:$E$28, 3, FALSE) -> 1 | M42: =IF(OR(J42="",G42=""),"",IF(ISERROR(VLOOKUP(D42,'SeuilsComparaison-EMT'!$C$5:$J$25,4,FALSE)),"-",IF(OR(IF(ISTEXT(J42)=TRUE,SUBSTITUTE(J42,"<","",1)*1,J42)>VLOOKUP(D42,'SeuilsComparaison-EMT'!$C$5:$J$25,4,FALSE),IF(ISTEXT(G42)=TRUE,SUBSTITUTE(G42,"<","",1)*1,G42)>VLOOKUP(D42,'SeuilsComparaison-EMT'!$C$5:$J$25,4,FALSE)=TRUE),(IF(ISTEXT(G42)=TRUE,SUBSTITUTE(G42,"<","",1)*1,G42)-((IF(ISTEXT(G42)=TRUE,SUBSTITUTE(G42,"<","",1)*1,G42)+IF(ISTEXT(J42)=TRUE,SUBSTITUTE(J42,"<","",1)*1,J42))/2))/((IF(ISTEXT(G42)=TRUE,SUBSTITUTE(G42,"<","",1)*1,G42)+IF(ISTEXT(J42)=TRUE,SUBSTITUTE(J42,"<","",1),J42))/2),"-"))) | O42: =IF(OR(G42="",J42=""),"",IF(AND(I42="Oui",L42="Oui"),"Oui",IF(M42="-","Oui",IF(OR(J42>VLOOKUP($D42,'SeuilsComparaison-EMT'!$C$5:$J$27,4,FALSE),G42>VLOOKUP($D42,'SeuilsComparaison-EMT'!$C$5:$J$27,4,FALSE)=TRUE),IF(J42<=VLOOKUP($D42,'SeuilsComparaison-EMT'!$C$5:$J$27,5,FALSE),IF(ABS(M42)<=VLOOKUP($D42,'SeuilsComparaison-EMT'!$C$5:$J$27,6,FALSE),"Oui","Non"),IF(ABS(M42)<=VLOOKUP($D42,'SeuilsComparaison-EMT'!$C$5:$J$27,8,FALSE),"Oui","Non")),"Oui")))) | Q42: =IF(OR(AND(ISNUMBER(G42),G42>VLOOKUP(D42,'SeuilsComparaison-EMT'!$C$5:$J$27,4,FALSE)),AND(ISNUMBER(J42),J42>VLOOKUP(D42,'SeuilsComparaison-EMT'!$C$5:$J$27,4,FALSE))),IF(AVERAGE(G42,J42)<=VLOOKUP(D42,'SeuilsComparaison-EMT'!$C$5:$J$27,5,FALSE),VLOOKUP(D42,'SeuilsComparaison-EMT'!$C$5:$J$27,6,FALSE),VLOOKUP(D42,'SeuilsComparaison-EMT'!$C$5:$J$27,8,FALSE)),"")
D43: NH4 (NH4) | F43: =VLOOKUP(D43, 'SeuilsComparaison-EMT'!$C$5:$E$28, 3, FALSE) -> 0.5 | M43: =IF(OR(J43="",G43=""),"",IF(ISERROR(VLOOKUP(D43,'SeuilsComparaison-EMT'!$C$5:$J$25,4,FALSE)),"-",IF(OR(IF(ISTEXT(J43)=TRUE,SUBSTITUTE(J43,"<","",1)*1,J43)>VLOOKUP(D43,'SeuilsComparaison-EMT'!$C$5:$J$25,4,FALSE),IF(ISTEXT(G43)=TRUE,SUBSTITUTE(G43,"<","",1)*1,G43)>VLOOKUP(D43,'SeuilsComparaison-EMT'!$C$5:$J$25,4,FALSE)=TRUE),(IF(ISTEXT(G43)=TRUE,SUBSTITUTE(G43,"<","",1)*1,G43)-((IF(ISTEXT(G43)=TRUE,SUBSTITUTE(G43,"<","",1)*1,G43)+IF(ISTEXT(J43)=TRUE,SUBSTITUTE(J43,"<","",1)*1,J43))/2))/((IF(ISTEXT(G43)=TRUE,SUBSTITUTE(G43,"<","",1)*1,G43)+IF(ISTEXT(J43)=TRUE,SUBSTITUTE(J43,"<","",1),J43))/2),"-"))) | O43: =IF(OR(G43="",J43=""),"",IF(AND(I43="Oui",L43="Oui"),"Oui",IF(M43="-","Oui",IF(OR(J43>VLOOKUP($D43,'SeuilsComparaison-EMT'!$C$5:$J$27,4,FALSE),G43>VLOOKUP($D43,'SeuilsComparaison-EMT'!$C$5:$J$27,4,FALSE)=TRUE),IF(J43<=VLOOKUP($D43,'SeuilsComparaison-EMT'!$C$5:$J$27,5,FALSE),IF(ABS(M43)<=VLOOKUP($D43,'SeuilsComparaison-EMT'!$C$5:$J$27,6,FALSE),"Oui","Non"),IF(ABS(M43)<=VLOOKUP($D43,'SeuilsComparaison-EMT'!$C$5:$J$27,8,FALSE),"Oui","Non")),"Oui")))) | Q43: =IF(OR(AND(ISNUMBER(G43),G43>VLOOKUP(D43,'SeuilsComparaison-EMT'!$C$5:$J$27,4,FALSE)),AND(ISNUMBER(J43),J43>VLOOKUP(D43,'SeuilsComparaison-EMT'!$C$5:$J$27,4,FALSE))),IF(AVERAGE(G43,J43)<=VLOOKUP(D43,'SeuilsComparaison-EMT'!$C$5:$J$27,5,FALSE),VLOOKUP(D43,'SeuilsComparaison-EMT'!$C$5:$J$27,6,FALSE),VLOOKUP(D43,'SeuilsComparaison-EMT'!$C$5:$J$27,8,FALSE)),"")
D44: NO2 (NO2) | F44: =VLOOKUP(D44, 'SeuilsComparaison-EMT'!$C$5:$E$28, 3, FALSE) -> 0.05 | M44: =IF(OR(J44="",G44=""),"",IF(ISERROR(VLOOKUP(D44,'SeuilsComparaison-EMT'!$C$5:$J$25,4,FALSE)),"-",IF(OR(IF(ISTEXT(J44)=TRUE,SUBSTITUTE(J44,"<","",1)*1,J44)>VLOOKUP(D44,'SeuilsComparaison-EMT'!$C$5:$J$25,4,FALSE),IF(ISTEXT(G44)=TRUE,SUBSTITUTE(G44,"<","",1)*1,G44)>VLOOKUP(D44,'SeuilsComparaison-EMT'!$C$5:$J$25,4,FALSE)=TRUE),(IF(ISTEXT(G44)=TRUE,SUBSTITUTE(G44,"<","",1)*1,G44)-((IF(ISTEXT(G44)=TRUE,SUBSTITUTE(G44,"<","",1)*1,G44)+IF(ISTEXT(J44)=TRUE,SUBSTITUTE(J44,"<","",1)*1,J44))/2))/((IF(ISTEXT(G44)=TRUE,SUBSTITUTE(G44,"<","",1)*1,G44)+IF(ISTEXT(J44)=TRUE,SUBSTITUTE(J44,"<","",1),J44))/2),"-"))) | O44: =IF(OR(G44="",J44=""),"",IF(AND(I44="Oui",L44="Oui"),"Oui",IF(M44="-","Oui",IF(OR(J44>VLOOKUP($D44,'SeuilsComparaison-EMT'!$C$5:$J$27,4,FALSE),G44>VLOOKUP($D44,'SeuilsComparaison-EMT'!$C$5:$J$27,4,FALSE)=TRUE),IF(J44<=VLOOKUP($D44,'SeuilsComparaison-EMT'!$C$5:$J$27,5,FALSE),IF(ABS(M44)<=VLOOKUP($D44,'SeuilsComparaison-EMT'!$C$5:$J$27,6,FALSE),"Oui","Non"),IF(ABS(M44)<=VLOOKUP($D44,'SeuilsComparaison-EMT'!$C$5:$J$27,8,FALSE),"Oui","Non")),"Oui")))) | Q44: =IF(OR(AND(ISNUMBER(G44),G44>VLOOKUP(D44,'SeuilsComparaison-EMT'!$C$5:$J$27,4,FALSE)),AND(ISNUMBER(J44),J44>VLOOKUP(D44,'SeuilsComparaison-EMT'!$C$5:$J$27,4,FALSE))),IF(AVERAGE(G44,J44)<=VLOOKUP(D44,'SeuilsComparaison-EMT'!$C$5:$J$27,5,FALSE),VLOOKUP(D44,'SeuilsComparaison-EMT'!$C$5:$J$27,6,FALSE),VLOOKUP(D44,'SeuilsComparaison-EMT'!$C$5:$J$27,8,FALSE)),"")
D45: NO3 (NO3) | F45: =VLOOKUP(D45, 'SeuilsComparaison-EMT'!$C$5:$E$28, 3, FALSE) -> 1 | M45: =IF(OR(J45="",G45=""),"",IF(ISERROR(VLOOKUP(D45,'SeuilsComparaison-EMT'!$C$5:$J$25,4,FALSE)),"-",IF(OR(IF(ISTEXT(J45)=TRUE,SUBSTITUTE(J45,"<","",1)*1,J45)>VLOOKUP(D45,'SeuilsComparaison-EMT'!$C$5:$J$25,4,FALSE),IF(ISTEXT(G45)=TRUE,SUBSTITUTE(G45,"<","",1)*1,G45)>VLOOKUP(D45,'SeuilsComparaison-EMT'!$C$5:$J$25,4,FALSE)=TRUE),(IF(ISTEXT(G45)=TRUE,SUBSTITUTE(G45,"<","",1)*1,G45)-((IF(ISTEXT(G45)=TRUE,SUBSTITUTE(G45,"<","",1)*1,G45)+IF(ISTEXT(J45)=TRUE,SUBSTITUTE(J45,"<","",1)*1,J45))/2))/((IF(ISTEXT(G45)=TRUE,SUBSTITUTE(G45,"<","",1)*1,G45)+IF(ISTEXT(J45)=TRUE,SUBSTITUTE(J45,"<","",1),J45))/2),"-"))) | O45: =IF(OR(G45="",J45=""),"",IF(AND(I45="Oui",L45="Oui"),"Oui",IF(M45="-","Oui",IF(OR(J45>VLOOKUP($D45,'SeuilsComparaison-EMT'!$C$5:$J$27,4,FALSE),G45>VLOOKUP($D45,'SeuilsComparaison-EMT'!$C$5:$J$27,4,FALSE)=TRUE),IF(J45<=VLOOKUP($D45,'SeuilsComparaison-EMT'!$C$5:$J$27,5,FALSE),IF(ABS(M45)<=VLOOKUP($D45,'SeuilsComparaison-EMT'!$C$5:$J$27,6,FALSE),"Oui","Non"),IF(ABS(M45)<=VLOOKUP($D45,'SeuilsComparaison-EMT'!$C$5:$J$27,8,FALSE),"Oui","Non")),"Oui")))) | Q45: =IF(OR(AND(ISNUMBER(G45),G45>VLOOKUP(D45,'SeuilsComparaison-EMT'!$C$5:$J$27,4,FALSE)),AND(ISNUMBER(J45),J45>VLOOKUP(D45,'SeuilsComparaison-EMT'!$C$5:$J$27,4,FALSE))),IF(AVERAGE(G45,J45)<=VLOOKUP(D45,'SeuilsComparaison-EMT'!$C$5:$J$27,5,FALSE),VLOOKUP(D45,'SeuilsComparaison-EMT'!$C$5:$J$27,6,FALSE),VLOOKUP(D45,'SeuilsComparaison-EMT'!$C$5:$J$27,8,FALSE)),"")
D46: PT | F46: =VLOOKUP(D46, 'SeuilsComparaison-EMT'!$C$5:$E$28, 3, FALSE) -> 0.05 | M46: =IF(OR(J46="",G46=""),"",IF(ISERROR(VLOOKUP(D46,'SeuilsComparaison-EMT'!$C$5:$J$25,4,FALSE)),"-",IF(OR(IF(ISTEXT(J46)=TRUE,SUBSTITUTE(J46,"<","",1)*1,J46)>VLOOKUP(D46,'SeuilsComparaison-EMT'!$C$5:$J$25,4,FALSE),IF(ISTEXT(G46)=TRUE,SUBSTITUTE(G46,"<","",1)*1,G46)>VLOOKUP(D46,'SeuilsComparaison-EMT'!$C$5:$J$25,4,FALSE)=TRUE),(IF(ISTEXT(G46)=TRUE,SUBSTITUTE(G46,"<","",1)*1,G46)-((IF(ISTEXT(G46)=TRUE,SUBSTITUTE(G46,"<","",1)*1,G46)+IF(ISTEXT(J46)=TRUE,SUBSTITUTE(J46,"<","",1)*1,J46))/2))/((IF(ISTEXT(G46)=TRUE,SUBSTITUTE(G46,"<","",1)*1,G46)+IF(ISTEXT(J46)=TRUE,SUBSTITUTE(J46,"<","",1),J46))/2),"-"))) | O46: =IF(OR(G46="",J46=""),"",IF(AND(I46="Oui",L46="Oui"),"Oui",IF(M46="-","Oui",IF(OR(J46>VLOOKUP($D46,'SeuilsComparaison-EMT'!$C$5:$J$27,4,FALSE),G46>VLOOKUP($D46,'SeuilsComparaison-EMT'!$C$5:$J$27,4,FALSE)=TRUE),IF(J46<=VLOOKUP($D46,'SeuilsComparaison-EMT'!$C$5:$J$27,5,FALSE),IF(ABS(M46)<=VLOOKUP($D46,'SeuilsComparaison-EMT'!$C$5:$J$27,6,FALSE),"Oui","Non"),IF(ABS(M46)<=VLOOKUP($D46,'SeuilsComparaison-EMT'!$C$5:$J$27,8,FALSE),"Oui","Non")),"Oui")))) | Q46: =IF(OR(AND(ISNUMBER(G46),G46>VLOOKUP(D46,'SeuilsComparaison-EMT'!$C$5:$J$27,4,FALSE)),AND(ISNUMBER(J46),J46>VLOOKUP(D46,'SeuilsComparaison-EMT'!$C$5:$J$27,4,FALSE))),IF(AVERAGE(G46,J46)<=VLOOKUP(D46,'SeuilsComparaison-EMT'!$C$5:$J$27,5,FALSE),VLOOKUP(D46,'SeuilsComparaison-EMT'!$C$5:$J$27,6,FALSE),VLOOKUP(D46,'SeuilsComparaison-EMT'!$C$5:$J$27,8,FALSE)),"")
D47: Conductivité | F47: =VLOOKUP(D47, 'SeuilsComparaison-EMT'!$C$5:$E$28, 3, FALSE) -> 0 | M47: =IF(OR(J47="",G47=""),"",IF(ISERROR(VLOOKUP(D47,'SeuilsComparaison-EMT'!$C$5:$J$25,4,FALSE)),"-",IF(OR(IF(ISTEXT(J47)=TRUE,SUBSTITUTE(J47,"<","",1)*1,J47)>VLOOKUP(D47,'SeuilsComparaison-EMT'!$C$5:$J$25,4,FALSE),IF(ISTEXT(G47)=TRUE,SUBSTITUTE(G47,"<","",1)*1,G47)>VLOOKUP(D47,'SeuilsComparaison-EMT'!$C$5:$J$25,4,FALSE)=TRUE),(IF(ISTEXT(G47)=TRUE,SUBSTITUTE(G47,"<","",1)*1,G47)-((IF(ISTEXT(G47)=TRUE,SUBSTITUTE(G47,"<","",1)*1,G47)+IF(ISTEXT(J47)=TRUE,SUBSTITUTE(J47,"<","",1)*1,J47))/2))/((IF(ISTEXT(G47)=TRUE,SUBSTITUTE(G47,"<","",1)*1,G47)+IF(ISTEXT(J47)=TRUE,SUBSTITUTE(J47,"<","",1),J47))/2),"-"))) | O47: =IF(OR(G47="",J47=""),"",IF(AND(I47="Oui",L47="Oui"),"Oui",IF(M47="-","Oui",IF(OR(J47>VLOOKUP($D47,'SeuilsComparaison-EMT'!$C$5:$J$27,4,FALSE),G47>VLOOKUP($D47,'SeuilsComparaison-EMT'!$C$5:$J$27,4,FALSE)=TRUE),IF(J47<=VLOOKUP($D47,'SeuilsComparaison-EMT'!$C$5:$J$27,5,FALSE),IF(ABS(M47)<=VLOOKUP($D47,'SeuilsComparaison-EMT'!$C$5:$J$27,6,FALSE),"Oui","Non"),IF(ABS(M47)<=VLOOKUP($D47,'SeuilsComparaison-EMT'!$C$5:$J$27,8,FALSE),"Oui","Non")),"Oui")))) | Q47: =IF(OR(AND(ISNUMBER(G47),G47>VLOOKUP(D47,'SeuilsComparaison-EMT'!$C$5:$J$27,4,FALSE)),AND(ISNUMBER(J47),J47>VLOOKUP(D47,'SeuilsComparaison-EMT'!$C$5:$J$27,4,FALSE))),IF(AVERAGE(G47,J47)<=VLOOKUP(D47,'SeuilsComparaison-EMT'!$C$5:$J$27,5,FALSE),VLOOKUP(D47,'SeuilsComparaison-EMT'!$C$5:$J$27,6,FALSE),VLOOKUP(D47,'SeuilsComparaison-EMT'!$C$5:$J$27,8,FALSE)),"")
D48: Cl | F48: =VLOOKUP(D48, 'SeuilsComparaison-EMT'!$C$5:$E$28, 3, FALSE) -> 5 | M48: =IF(OR(J48="",G48=""),"",IF(ISERROR(VLOOKUP(D48,'SeuilsComparaison-EMT'!$C$5:$J$25,4,FALSE)),"-",IF(OR(IF(ISTEXT(J48)=TRUE,SUBSTITUTE(J48,"<","",1)*1,J48)>VLOOKUP(D48,'SeuilsComparaison-EMT'!$C$5:$J$25,4,FALSE),IF(ISTEXT(G48)=TRUE,SUBSTITUTE(G48,"<","",1)*1,G48)>VLOOKUP(D48,'SeuilsComparaison-EMT'!$C$5:$J$25,4,FALSE)=TRUE),(IF(ISTEXT(G48)=TRUE,SUBSTITUTE(G48,"<","",1)*1,G48)-((IF(ISTEXT(G48)=TRUE,SUBSTITUTE(G48,"<","",1)*1,G48)+IF(ISTEXT(J48)=TRUE,SUBSTITUTE(J48,"<","",1)*1,J48))/2))/((IF(ISTEXT(G48)=TRUE,SUBSTITUTE(G48,"<","",1)*1,G48)+IF(ISTEXT(J48)=TRUE,SUBSTITUTE(J48,"<","",1),J48))/2),"-"))) | O48: =IF(OR(G48="",J48=""),"",IF(AND(I48="Oui",L48="Oui"),"Oui",IF(M48="-","Oui",IF(OR(J48>VLOOKUP($D48,'SeuilsComparaison-EMT'!$C$5:$J$27,4,FALSE),G48>VLOOKUP($D48,'SeuilsComparaison-EMT'!$C$5:$J$27,4,FALSE)=TRUE),IF(J48<=VLOOKUP($D48,'SeuilsComparaison-EMT'!$C$5:$J$27,5,FALSE),IF(ABS(M48)<=VLOOKUP($D48,'SeuilsComparaison-EMT'!$C$5:$J$27,6,FALSE),"Oui","Non"),IF(ABS(M48)<=VLOOKUP($D48,'SeuilsComparaison-EMT'!$C$5:$J$27,8,FALSE),"Oui","Non")),"Oui")))) | Q48: =IF(OR(AND(ISNUMBER(G48),G48>VLOOKUP(D48,'SeuilsComparaison-EMT'!$C$5:$J$27,4,FALSE)),AND(ISNUMBER(J48),J48>VLOOKUP(D48,'SeuilsComparaison-EMT'!$C$5:$J$27,4,FALSE))),IF(AVERAGE(G48,J48)<=VLOOKUP(D48,'SeuilsComparaison-EMT'!$C$5:$J$27,5,FALSE),VLOOKUP(D48,'SeuilsComparaison-EMT'!$C$5:$J$27,6,FALSE),VLOOKUP(D48,'SeuilsComparaison-EMT'!$C$5:$J$27,8,FALSE)),"")
D49: MS | F49: =VLOOKUP(D49, 'SeuilsComparaison-EMT'!$C$5:$E$28, 3, FALSE) -> 0 | M49: =IF(OR(J49="",G49=""),"",IF(ISERROR(VLOOKUP(D49,'SeuilsComparaison-EMT'!$C$5:$J$25,4,FALSE)),"-",IF(OR(IF(ISTEXT(J49)=TRUE,SUBSTITUTE(J49,"<","",1)*1,J49)>VLOOKUP(D49,'SeuilsComparaison-EMT'!$C$5:$J$25,4,FALSE),IF(ISTEXT(G49)=TRUE,SUBSTITUTE(G49,"<","",1)*1,G49)>VLOOKUP(D49,'SeuilsComparaison-EMT'!$C$5:$J$25,4,FALSE)=TRUE),(IF(ISTEXT(G49)=TRUE,SUBSTITUTE(G49,"<","",1)*1,G49)-((IF(ISTEXT(G49)=TRUE,SUBSTITUTE(G49,"<","",1)*1,G49)+IF(ISTEXT(J49)=TRUE,SUBSTITUTE(J49,"<","",1)*1,J49))/2))/((IF(ISTEXT(G49)=TRUE,SUBSTITUTE(G49,"<","",1)*1,G49)+IF(ISTEXT(J49)=TRUE,SUBSTITUTE(J49,"<","",1),J49))/2),"-"))) | O49: =IF(OR(G49="",J49=""),"",IF(AND(I49="Oui",L49="Oui"),"Oui",IF(M49="-","Oui",IF(OR(J49>VLOOKUP($D49,'SeuilsComparaison-EMT'!$C$5:$J$27,4,FALSE),G49>VLOOKUP($D49,'SeuilsComparaison-EMT'!$C$5:$J$27,4,FALSE)=TRUE),IF(J49<=VLOOKUP($D49,'SeuilsComparaison-EMT'!$C$5:$J$27,5,FALSE),IF(ABS(M49)<=VLOOKUP($D49,'SeuilsComparaison-EMT'!$C$5:$J$27,6,FALSE),"Oui","Non"),IF(ABS(M49)<=VLOOKUP($D49,'SeuilsComparaison-EMT'!$C$5:$J$27,8,FALSE),"Oui","Non")),"Oui")))) | Q49: =IF(OR(AND(ISNUMBER(G49),G49>VLOOKUP(D49,'SeuilsComparaison-EMT'!$C$5:$J$27,4,FALSE)),AND(ISNUMBER(J49),J49>VLOOKUP(D49,'SeuilsComparaison-EMT'!$C$5:$J$27,4,FALSE))),IF(AVERAGE(G49,J49)<=VLOOKUP(D49,'SeuilsComparaison-EMT'!$C$5:$J$27,5,FALSE),VLOOKUP(D49,'SeuilsComparaison-EMT'!$C$5:$J$27,6,FALSE),VLOOKUP(D49,'SeuilsComparaison-EMT'!$C$5:$J$27,8,FALSE)),"")
D51: COMMENTAIRES :
J58: Ajouter un comparatif analytique

Sheet BD Débitmètres
B2: BASE DE DONNÉES SUR LES PLAGES OPTIMALES ET RECOMMANDÉES DES DEBITMÈTRES
B4: Canaux Venturi : | D4: feuilledecontrole_v7.0_locked.xlsx
H5: Base de données sur les plages optimales et recommandées de mesure des débitmètres
B6: Débitmètres en charge :
B8: Diamètre nominal en mm | C8: PLAGES DE MESURE OPTIMALES | K8: PLAGES DE MESURE RECOMMANDÉES
C9: =Critères!$B$3 -> Débitmètre électromagnétique (Eau) | G9: =Critères!$N$3 -> Débitmètre Ultrason | K9: =Critères!$B$3 -> Débitmètre électromagnétique (Eau) | O9: =Critères!$N$3 -> Débitmètre Ultrason
C10: Vitesse mini en m/s | D10: Débit mini en m3/h | E10: Vitesse maxi en m/s | F10: Débit maxi en m3/h | G10: Vitesse mini en m/s | H10: Débit mini en m3/h | I10: Vitesse maxi en m/s | J10: Débit maxi en m3/h | K10: Vitesse mini en m/s | L10: Débit mini en m3/h | M10: Vitesse maxi en m/s | N10: Débit maxi en m3/h | O10: Vitesse mini en m/s | P10: Débit mini en m3/h | Q10: Vitesse maxi en m/s | R10: Débit maxi en m3/h
B11: 20 | C11: 1 | D11: =(PI()*POWER($B11/1000,2)/4)*C11*3600 -> 1.1309734 | E11: 3 | F11: =(PI()*POWER($B11/1000,2)/4)*E11*3600 -> 3.3929201 | G11: 1 | H11: =(PI()*POWER($B11/1000,2)/4)*G11*3600 -> 1.1309734 | I11: 5 | J11: =(PI()*POWER($B11/1000,2)/4)*I11*3600 -> 5.6548668 | K11: 0.3 | L11: =(PI()*POWER($B11/1000,2)/4)*K11*3600 -> 0.33929201 | M11: 10 | N11: =(PI()*POWER($B11/1000,2)/4)*M11*3600 -> 11.309734 | O11: 0.3 | P11: =(PI()*POWER($B11/1000,2)/4)*O11*3600 -> 0.33929201 | Q11: 10 | R11: =(PI()*POWER($B11/1000,2)/4)*Q11*3600 -> 11.309734
B12: 25 | C12: 1 | D12: =(PI()*POWER($B12/1000,2)/4)*C12*3600 -> 1.7671459 | E12: 3 | F12: =(PI()*POWER($B12/1000,2)/4)*E12*3600 -> 5.3014376 | G12: 1 | H12: =(PI()*POWER($B12/1000,2)/4)*G12*3600 -> 1.7671459 | I12: 5 | J12: =(PI()*POWER($B12/1000,2)/4)*I12*3600 -> 8.8357293 | K12: 0.3 | L12: =(PI()*POWER($B12/1000,2)/4)*K12*3600 -> 0.53014376 | M12: 10 | N12: =(PI()*POWER($B12/1000,2)/4)*M12*3600 -> 17.671459 | O12: 0.3 | P12: =(PI()*POWER($B12/1000,2)/4)*O12*3600 -> 0.53014376 | Q12: 10 | R12: =(PI()*POWER($B12/1000,2)/4)*Q12*3600 -> 17.671459
B13: 32 | C13: 1 | D13: =(PI()*POWER($B13/1000,2)/4)*C13*3600 -> 2.8952918 | E13: 3 | F13: =(PI()*POWER($B13/1000,2)/4)*E13*3600 -> 8.6858754 | G13: 1 | H13: =(PI()*POWER($B13/1000,2)/4)*G13*3600 -> 2.8952918 | I13: 5 | J13: =(PI()*POWER($B13/1000,2)/4)*I13*3600 -> 14.476459 | K13: 0.3 | L13: =(PI()*POWER($B13/1000,2)/4)*K13*3600 -> 0.86858754 | M13: 10 | N13: =(PI()*POWER($B13/1000,2)/4)*M13*3600 -> 28.952918 | O13: 0.3 | P13: =(PI()*POWER($B13/1000,2)/4)*O13*3600 -> 0.86858754 | Q13: 10 | R13: =(PI()*POWER($B13/1000,2)/4)*Q13*3600 -> 28.952918
B14: 40 | C14: 1 | D14: =(PI()*POWER($B14/1000,2)/4)*C14*3600 -> 4.5238934 | E14: 3 | F14: =(PI()*POWER($B14/1000,2)/4)*E14*3600 -> 13.57168 | G14: 1 | H14: =(PI()*POWER($B14/1000,2)/4)*G14*3600 -> 4.5238934 | I14: 5 | J14: =(PI()*POWER($B14/1000,2)/4)*I14*3600 -> 22.619467 | K14: 0.3 | L14: =(PI()*POWER($B14/1000,2)/4)*K14*3600 -> 1.357168 | M14: 10 | N14: =(PI()*POWER($B14/1000,2)/4)*M14*3600 -> 45.238934 | O14: 0.3 | P14: =(PI()*POWER($B14/1000,2)/4)*O14*3600 -> 1.357168 | Q14: 10 | R14: =(PI()*POWER($B14/1000,2)/4)*Q14*3600 -> 45.238934
B15: 50 | C15: 1 | D15: =(PI()*POWER($B15/1000,2)/4)*C15*3600 -> 7.0685835 | E15: 3 | F15: =(PI()*POWER($B15/1000,2)/4)*E15*3600 -> 21.20575 | G15: 1 | H15: =(PI()*POWER($B15/1000,2)/4)*G15*3600 -> 7.0685835 | I15: 5 | J15: =(PI()*POWER($B15/1000,2)/4)*I15*3600 -> 35.342917 | K15: 0.3 | L15: =(PI()*POWER($B15/1000,2)/4)*K15*3600 -> 2.120575 | M15: 10 | N15: =(PI()*POWER($B15/1000,2)/4)*M15*3600 -> 70.685835 | O15: 0.3 | P15: =(PI()*POWER($B15/1000,2)/4)*O15*3600 -> 2.120575 | Q15: 10 | R15: =(PI()*POWER($B15/1000,2)/4)*Q15*3600 -> 70.685835
B16: 65 | C16: 1 | D16: =(PI()*POWER($B16/1000,2)/4)*C16*3600 -> 11.945906 | E16: 3 | F16: =(PI()*POWER($B16/1000,2)/4)*E16*3600 -> 35.837718 | G16: 1 | H16: =(PI()*POWER($B16/1000,2)/4)*G16*3600 -> 11.945906 | I16: 5 | J16: =(PI()*POWER($B16/1000,2)/4)*I16*3600 -> 59.72953 | K16: 0.3 | L16: =(PI()*POWER($B16/1000,2)/4)*K16*3600 -> 3.5837718 | M16: 10 | N16: =(PI()*POWER($B16/1000,2)/4)*M16*3600 -> 119.45906 | O16: 0.3 | P16: =(PI()*POWER($B16/1000,2)/4)*O16*3600 -> 3.5837718 | Q16: 10 | R16: =(PI()*POWER($B16/1000,2)/4)*Q16*3600 -> 119.45906
B17: 80 | C17: 1 | D17: =(PI()*POWER($B17/1000,2)/4)*C17*3600 -> 18.095574 | E17: 3 | F17: =(PI()*POWER($B17/1000,2)/4)*E17*3600 -> 54.286721 | G17: 1 | H17: =(PI()*POWER($B17/1000,2)/4)*G17*3600 -> 18.095574 | I17: 5 | J17: =(PI()*POWER($B17/1000,2)/4)*I17*3600 -> 90.477868 | K17: 0.3 | L17: =(PI()*POWER($B17/1000,2)/4)*K17*3600 -> 5.4286721 | M17: 10 | N17: =(PI()*POWER($B17/1000,2)/4)*M17*3600 -> 180.95574 | O17: 0.3 | P17: =(PI()*POWER($B17/1000,2)/4)*O17*3600 -> 5.4286721 | Q17: 10 | R17: =(PI()*POWER($B17/1000,2)/4)*Q17*3600 -> 180.95574
B18: 100 | C18: 1 | D18: =(PI()*POWER($B18/1000,2)/4)*C18*3600 -> 28.274334 | E18: 3 | F18: =(PI()*POWER($B18/1000,2)/4)*E18*3600 -> 84.823002 | G18: 1 | H18: =(PI()*POWER($B18/1000,2)/4)*G18*3600 -> 28.274334 | I18: 5 | J18: =(PI()*POWER($B18/1000,2)/4)*I18*3600 -> 141.37167 | K18: 0.3 | L18: =(PI()*POWER($B18/1000,2)/4)*K18*3600 -> 8.4823002 | M18: 10 | N18: =(PI()*POWER($B18/1000,2)/4)*M18*3600 -> 282.74334 | O18: 0.3 | P18: =(PI()*POWER($B18/1000,2)/4)*O18*3600 -> 8.4823002 | Q18: 10 | R18: =(PI()*POWER($B18/1000,2)/4)*Q18*3600 -> 282.74334
B19: 125 | C19: 1 | D19: =(PI()*POWER($B19/1000,2)/4)*C19*3600 -> 44.178647 | E19: 3 | F19: =(PI()*POWER($B19/1000,2)/4)*E19*3600 -> 132.53594 | G19: 1 | H19: =(PI()*POWER($B19/1000,2)/4)*G19*3600 -> 44.178647 | I19: 5 | J19: =(PI()*POWER($B19/1000,2)/4)*I19*3600 -> 220.89323 | K19: 0.3 | L19: =(PI()*POWER($B19/1000,2)/4)*K19*3600 -> 13.253594 | M19: 10 | N19: =(PI()*POWER($B19/1000,2)/4)*M19*3600 -> 441.78647 | O19: 0.3 | P19: =(PI()*POWER($B19/1000,2)/4)*O19*3600 -> 13.253594 | Q19: 10 | R19: =(PI()*POWER($B19/1000,2)/4)*Q19*3600 -> 441.78647
B20: 150 | C20: 1 | D20: =(PI()*POWER($B20/1000,2)/4)*C20*3600 -> 63.617251 | E20: 3 | F20: =(PI()*POWER($B20/1000,2)/4)*E20*3600 -> 190.85175 | G20: 1 | H20: =(PI()*POWER($B20/1000,2)/4)*G20*3600 -> 63.617251 | I20: 5 | J20: =(PI()*POWER($B20/1000,2)/4)*I20*3600 -> 318.08626 | K20: 0.3 | L20: =(PI()*POWER($B20/1000,2)/4)*K20*3600 -> 19.085175 | M20: 10 | N20: =(PI()*POWER($B20/1000,2)/4)*M20*3600 -> 636.17251 | O20: 0.3 | P20: =(PI()*POWER($B20/1000,2)/4)*O20*3600 -> 19.085175 | Q20: 10 | R20: =(PI()*POWER($B20/1000,2)/4)*Q20*3600 -> 636.17251
B21: 200 | C21: 1 | D21: =(PI()*POWER($B21/1000,2)/4)*C21*3600 -> 113.09734 | E21: 3 | F21: =(PI()*POWER($B21/1000,2)/4)*E21*3600 -> 339.29201 | G21: 1 | H21: =(PI()*POWER($B21/1000,2)/4)*G21*3600 -> 113.09734 | I21: 5 | J21: =(PI()*POWER($B21/1000,2)/4)*I21*3600 -> 565.48668 | K21: 0.3 | L21: =(PI()*POWER($B21/1000,2)/4)*K21*3600 -> 33.929201 | M21: 10 | N21: =(PI()*POWER($B21/1000,2)/4)*M21*3600 -> 1130.9734 | O21: 0.3 | P21: =(PI()*POWER($B21/1000,2)/4)*O21*3600 -> 33.929201 | Q21: 10 | R21: =(PI()*POWER($B21/1000,2)/4)*Q21*3600 -> 1130.9734
B22: 250 | C22: 1 | D22: =(PI()*POWER($B22/1000,2)/4)*C22*3600 -> 176.71459 | E22: 3 | F22: =(PI()*POWER($B22/1000,2)/4)*E22*3600 -> 530.14376 | G22: 1 | H22: =(PI()*POWER($B22/1000,2)/4)*G22*3600 -> 176.71459 | I22: 5 | J22: =(PI()*POWER($B22/1000,2)/4)*I22*3600 -> 883.57293 | K22: 0.3 | L22: =(PI()*POWER($B22/1000,2)/4)*K22*3600 -> 53.014376 | M22: 10 | N22: =(PI()*POWER($B22/1000,2)/4)*M22*3600 -> 1767.1459 | O22: 0.3 | P22: =(PI()*POWER($B22/1000,2)/4)*O22*3600 -> 53.014376 | Q22: 10 | R22: =(PI()*POWER($B22/1000,2)/4)*Q22*3600 -> 1767.1459
... B38: 3000 | C38: 1 | D38: =(PI()*POWER($B38/1000,2)/4)*C38*3600 -> 25446.9 | E38: 3 | F38: =(PI()*POWER($B38/1000,2)/4)*E38*3600 -> 76340.701 | G38: 1 | H38: =(PI()*POWER($B38/1000,2)/4)*G38*3600 -> 25446.9 | I38: 5 | J38: =(PI()*POWER($B38/1000,2)/4)*I38*3600 -> 127234.5 | K38: 0.3 | L38: =(PI()*POWER($B38/1000,2)/4)*K38*3600 -> 7634.0701 | M38: 10 | N38: =(PI()*POWER($B38/1000,2)/4)*M38*3600 -> 254469 | O38: 0.3 | P38: =(PI()*POWER($B38/1000,2)/4)*O38*3600 -> 7634.0701 | Q38: 10 | R38: =(PI()*POWER($B38/1000,2)/4)*Q38*3600 -> 254469

Sheet PARAM
A3: Equipement Q | B3: Equipement Prel | C3: Type | D3: Liste des statuts | E3: CODE_SANDRE_STEU | F3: CODE_SANDRE_SCL | G3: Liste des statuts équipements | H3: Liste des statuts | I3: CODE_SANDRE_3
A4: Canal Venturi | B4: Préleveur Automatique | C4: Débitmètre en charge | D4: Validé | E4: A2 | F4: A1 | G4: Contrôlé | H4: Agréé | I4: A2 | J4: Déversoir en tête de station
A5: Débitmètre électromagnétique (Eau) | B5: Vanne de prélèvement asservie | C5: Débitmètre gravitaire | D5: Non validé | E5: A3 | F5: R1 | G5: Non contrôlé | H5: Non agréé | I5: A3 | J5: Entrée Station
A6: Débitmètre électromagnétique (Boue/MDV) | B6: Prélèvement ponctuel | C6: Préleveur | D6: Non contrôlé | E6: A4 | F6: R2 | G6: Supprimé | I6: A4 | J6: Sortie Station
A7: Seuil | C7: Sonde de température | D7: Réserve | E7: A5 | F7: R3 | I7: A5 | J7: By-pass
A8: Caisson | D8: Non validé (absence d'équipement) | E8: A6 | I8: A6 | J8: Boue produite
A9: Autre loi Hauteur / Débit (COACHs, Manning Strickler, …) | D9: Non validé (équipement insuffisant) | E9: A7 | I9: A7 | J9: Apport extérieur file(s) « eau »
A10: Débitmètre électromagnétique partiellement plein | E10: A8 | I10: A8 | J10: Sortie station pour utilisation des eaux usées traitées
A11: Clapet | E11: S1 | I11: S1 | J11: Entrée station (effluent « eau »)
A12: Détecteur de surverse | E12: S2 | I12: S2 | J12: Sortie Station (effluent « eau »)
A13: Modélisation | E13: S3 | I13: S3 | J13: By-pass
A14: Hauteur/Vitesse | E14: S4 | I14: S4 | J14: Boue extraite de la file « eau » avant traitement
A15: Point non existant | E15: S5 | I15: S5 | J15: Apport extérieur de boue
E16: S12 | I16: S6 | J16: Boue évacuée après traitement
E17: S13 | I17: S7 | J17: Apport extérieur en huiles/graisses
E18: S16 | I18: S8 | J18: Huiles / graisses produites avant traitement
E19: S19 | I19: S9 | J19: Huiles / graisses produites et évacuées sans traitement
A20: LISTE_1 | B20: LISTE_2 | C20: LISTE_3 | D20: LISTE_4 | F20: LISTE_5 | G20: LISTE_6 | H20: LISTE_7 | I20: S10 | J20: Sable évacué
A21: Oui | B21: Validé | C21: Validé | D21: Validé | F21: Validé | G21: Non applicable | H21: Oui | I21: S11 | J21: Refus de dégrillage évacué
A22: Non | B22: Non validé | C22: Non validé | D22: Entre 10 et 20% | F22: Entre 5 et 10% | H22: Non | I22: S12 | J22: Apport extérieur de matières de vidange
A23: Non applicable | B23: Non contrôlé | C23: Non contrôlé | D23: Non validé (>20%) | F23: Non validé (>10%) | H23: Non contrôlé | I23: S13 | J23: Apport extérieur de produits de curage
B24: Non applicable | C24: Réserve | D24: Non contrôlé | F24: Non contrôlé | I24: S14 | J24: Réactifs utilisés (file « eau »)
C25: Non applicable | D25: Non applicable | F25: Non applicable | I25: S15 | J25: Réactifs utilisés (file « boue »)
I26: S16 | J26: Déversoir en tête de station
I27: S17 | J27: Boue évacuée sans traitement
A28: Type équipement : débimètre | I28: S18 | J28: Autre apport extérieur file(s) « eau »
A29: Q en charge | B29: Q Gravitaire | C29: Equipement de contrôle H | D29: Type réseau | E29: Q en charge boues | I29: S19 | J29: Sortie de station pour utilisation des eaux usées traitées
A30: Débitmètre électromagnétique (Eau) | B30: Canal Venturi | C30: Réglet | D30: Mixte | E30: Débitmètre électromagnétique (boue/MDV) | I30: A1 | J30: Déversoir d'orage
A31: Débitmètre électromagnétique (Boue/MDV) | B31: Seuil | C31: Sonde | D31: Unitaire | I31: R1 | J31: Déversoir du système de collecte non soumis à autosurveillance réglementaire
A32: Organe déprimogène (pito...) | B32: Caisson | C32: Câble | D32: Séparatif | I32: R2 | J32: Point caractéristique du système de collecte
A33: Débitmètre Ultrason | B33: Autre loi Hauteur / Débit (COACHs, Manning Strickler, …) | I33: R3 | J33: Effluent non domestique arrivant dans le système de collecte
A34: Compteur mécanique | B34: Débitmètre électromagnétique partiellement plein
B35: Clapet
B36: Détecteur de surverse
B37: Modélisation
B38: Hauteur/Vitesse
A42: Listes fiches terrain
A43: Asservissement | B43: Conformité | C43: Type_capteur | D43: Satisfaction | E43: Fréquence | F43: Conditions météo | G43: Montage sonde
A44: Au débit | B44: Conforme | C44: Ultrason | D44: Satisfaisant | E44: Journalière | F44: Temps sec | G44: En /
A45: Au temps | B45: Conforme avec réserve | C45: Radar | D45: Non satisfaisant | E45: Hebdomadaire | F45: Temps de pluie | G45: En V
A46: Inconnu | B46: Non conforme | C46: Piezo | D46: Non vérifié | E46: Mensuelle | F46: Inconnues | G46: En W
B47: Non vérifié | C47: Bulle à bulle | E47: Bimensuelle | G47: En N
B48: Non vérifiable | C48: Autre | E48: Trimestrielle
E49: Semestrielle
E50: Annuelle
E51: Autre
A53: Listes méthode contrôle
A54: Méthode | B54: Type de mesure
A55: Simulation d'une hauteur d'eau (leurre) | B55: Ponctuelle
A56: Mesure comparative en parallèle | B56: En continu
A57: Simulation d'une hauteur d'eau et mesure en parallèle

Sheet SeuilsComparaison-EMT
B2: COMPARATIF ANALYTIQUE : DÉFINITION DES ÉCARTS MAXIMUM TOLÉRÉS (EMT)
B4: Code SANDRE | C4: Paramètres | D4: Unités | E4: Limites de quantification | F4: Seuil de comparaison | G4: Concentration supérieure au seuil de comparaison et inférieure ou égale à | H4: Ecart Maximum Toléré | I4: Concentration supérieure à | J4: Ecart Maximum Toléré
B5: 1313 | C5: DBO5 | D5: en mg/l de O2 | E5: 3 | F5: 15 | G5: 80 | H5: 0.3 | I5: 80 | J5: 0.2
B6: 1314 | C6: DCO | D6: en mg/l de O2 | E6: 30 | F6: 80 | G6: 250 | H6: 0.2 | I6: 250 | J6: 0.1
B7: 6396 | C7: ST DCO | D7: en mg/l de O2 | E7: 10 | F7: 20 | G7: 150 | H7: 0.2 | I7: 150 | J7: 0.1
B8: 1305 | C8: MEST | D8: en mg/l | E8: 2 | F8: 15 | G8: 60 | H8: 0.3 | I8: 60 | J8: 0.2
B9: 1319 | C9: NKJ (N) | D9: en mg/l de N | E9: 0.5 | F9: 6 | I9: 6 | J9: 0.1
B10: 1551 | C10: NGL | D10: en mg/l de N | E10: 1 | F10: 6 | I10: 6 | J10: 0.2
B11: 1335 | C11: NH4 (NH4) | D11: en mg/l de NH4+ | E11: 0.5 | F11: 6 | I11: 6 | J11: 0.1
B12: 1339 | C12: NO2 (NO2) | D12: en mg/l de NO2 | E12: 0.05 | F12: 1 | I12: 1 | J12: 0.2
B13: 1340 | C13: NO3 (NO3) | D13: en mg/l de NO3 | E13: 1 | F13: 5 | I13: 5 | J13: 0.2
B14: 1350 | C14: PT | D14: en mg/l de P | E14: 0.05 | F14: 1 | I14: 1 | J14: 0.2
B15: 1369 | C15: As | D15: en mg/l | E15: 0.005 | F15: 0.5 | G15: 1 | H15: 0.6 | I15: 1 | J15: 0.3
B16: 1388 | C16: Cd | D16: en mg/l | E16: 0.001 | F16: 0.5 | G16: 1 | H16: 0.6 | I16: 1 | J16: 0.3
B17: 1389 | C17: Cr | D17: en mg/l | E17: 0.005 | F17: 0.5 | G17: 1 | H17: 0.6 | I17: 1 | J17: 0.3
B18: 1392 | C18: Cu | D18: en mg/l | E18: 0.005 | F18: 0.5 | G18: 1 | H18: 0.6 | I18: 1 | J18: 0.3
B19: 1387 | C19: Hg | D19: en mg/l | E19: 0.0002 | F19: 0.005 | G19: 0.01 | H19: 0.6 | I19: 0.01 | J19: 0.3
B20: 1386 | C20: Ni | D20: en mg/l | E20: 0.005 | F20: 0.5 | G20: 1 | H20: 0.6 | I20: 1 | J20: 0.3
B21: 1382 | C21: Pb | D21: en mg/l | E21: 0.002 | F21: 0.5 | G21: 1 | H21: 0.6 | I21: 1 | J21: 0.3
B22: 1383 | C22: Zn | D22: en mg/l | E22: 0.005 | F22: 0.5 | G22: 1 | H22: 0.6 | I22: 1 | J22: 0.3
B23: 1106 | C23: AOX | D23: en mg/l | E23: 0.01 | F23: 0.05 | G23: 0.5 | H23: 0.6 | I23: 0.5 | J23: 0.3
B24: 1841 | C24: COT | D24: en mg/l | E24: 0.3 | F24: 5 | G24: 15 | H24: 0.3 | I24: 15 | J24: 0.1
B25: 1798 | C25: Conductivité
B26: 1337 | C26: Cl | D26: en mg/l | E26: 5
B27: 1799 | C27: MS | D27: en g/l | H27: 0.2 | J27: 0.05
B28: Le cacul des écarts analytiques est effectué si l'un des deux ou les deux résultats sont au dessus du seuil de comparaison. L'écart est calculé par rapport à la moyenne des 2 valeurs.

Sheet Recap_reseau
B1: Préparation des données pour la feuilles synthèse et pour les exports
B2: Paramètres de localisation des données dans les cellules
B4: Facteur Qualité | D4: Type Equipement | E4: Type
B5: =IF(Qualité!L29="Oui",1,0.9) -> 0.9 | E5: cellule typeE | F5: cellule score | G5: cellule eval | H5: cellule commentaire score | I5: cellule commentaire
D6: Pluviomètre | E6: D25 | F6: P33 | G6: N33 | H6: D33 | I6: C37
D7: =PARAM!$C4 -> Débitmètre en charge | E7: D32 | F7: P45 | G7: N45 | H7: D45 | I7: C49
D8: =PARAM!$C5 -> Débitmètre gravitaire | E8: D40 | F8: R53 | G8: P53 | H8: D53 | I8: C57
D9: =PARAM!$C6 -> Préleveur | E9: D37 | F9: P50 | G9: N50 | H9: D50 | I9: C54
D10: =PARAM!$C7 -> Sonde de température | E10: D26 | F10: P33 | G10: N33 | H10: D33 | I10: C37
D12: Type ligne | E12: Ligne
D13: Ligne SCL | E13: =Descriptif!$AD$2 -> 14 | F13: =E13+1 -> 15 | G13: =F13+1 -> 16 | H13: =G13+1 -> 17 | I13: =H13+1 -> 18 | J13: =I13+1 -> 19 | K13: =J13+1 -> 20 | L13: =K13+1 -> 21 | M13: =L13+1 -> 22 | ... S13: =R13+1 -> 28
B15: Identification des feuilles de données
B16: TODO: aller chercher la liste des point Réseau
B17: Reg. | C17: Point | F17: Point 1 | G17: Point 2 | H17: Point 3 | I17: Point 4 | J17: Point 5 | K17: Point 6 | L17: Point 7 | M17: Point 8 | N17: Point 9 | O17: Point 10 | P17: Point 11 | Q17: Point 12 | R17: Point 13 | S17: Point 14 | T17: Point 15
B18: A1 | D18: =$D$7 -> Débitmètre en charge | F18: {=IF(AND(OR(INDIRECT("Descriptif!I"&E$13)=Recap_reseau!$B18,INDIRECT("Descriptif!I"&E$13)=Recap_reseau!$C18),INDIRECT("Descriptif!M"&E$13)=$D18),INDIRECT("Descriptif!F"&E$13),"")} | G18: {=IF(AND(OR(INDIRECT("Descriptif!I"&F$13)=Recap_reseau!$B18,INDIRECT("Descriptif!I"&F$13)=Recap_reseau!$C18),INDIRECT("Descriptif!M"&F$13)=$D18),INDIRECT("Descriptif!F"&F$13),"")} | H18: {=IF(AND(OR(INDIRECT("Descriptif!I"&G$13)=Recap_reseau!$B18,INDIRECT("Descriptif!I"&G$13)=Recap_reseau!$C18),INDIRECT("Descriptif!M"&G$13)=$D18),INDIRECT("Descriptif!F"&G$13),"")} | I18: {=IF(AND(OR(INDIRECT("Descriptif!I"&H$13)=Recap_reseau!$B18,INDIRECT("Descriptif!I"&H$13)=Recap_reseau!$C18),INDIRECT("Descriptif!M"&H$13)=$D18),INDIRECT("Descriptif!F"&H$13),"")} | J18: {=IF(AND(OR(INDIRECT("Descriptif!I"&I$13)=Recap_reseau!$B18,INDIRECT("Descriptif!I"&I$13)=Recap_reseau!$C18),INDIRECT("Descriptif!M"&I$13)=$D18),INDIRECT("Descriptif!F"&I$13),"")} | K18: {=IF(AND(OR(INDIRECT("Descriptif!I"&J$13)=Recap_reseau!$B18,INDIRECT("Descriptif!I"&J$13)=Recap_reseau!$C18),INDIRECT("Descriptif!M"&J$13)=$D18),INDIRECT("Descriptif!F"&J$13),"")} | L18: {=IF(AND(OR(INDIRECT("Descriptif!I"&K$13)=Recap_reseau!$B18,INDIRECT("Descriptif!I"&K$13)=Recap_reseau!$C18),INDIRECT("Descriptif!M"&K$13)=$D18),INDIRECT("Descriptif!F"&K$13),"")} | M18: {=IF(AND(OR(INDIRECT("Descriptif!I"&L$13)=Recap_reseau!$B18,INDIRECT("Descriptif!I"&L$13)=Recap_reseau!$C18),INDIRECT("Descriptif!M"&L$13)=$D18),INDIRECT("Descriptif!F"&L$13),"")} | ... T18: {=IF(AND(OR(INDIRECT("Descriptif!I"&S$13)=Recap_reseau!$B18,INDIRECT("Descriptif!I"&S$13)=Recap_reseau!$C18),INDIRECT("Descriptif!M"&S$13)=$D18),INDIRECT("Descriptif!F"&S$13),"")}
D19: =$D$8 -> Débitmètre gravitaire | F19: {=IF(AND(OR(INDIRECT("Descriptif!I"&E$13)=Recap_reseau!$B18,INDIRECT("Descriptif!I"&E$13)=Recap_reseau!$C18),INDIRECT("Descriptif!M"&E$13)=$D19),INDIRECT("Descriptif!F"&E$13),"")} | G19: {=IF(AND(OR(INDIRECT("Descriptif!I"&F$13)=Recap_reseau!$B18,INDIRECT("Descriptif!I"&F$13)=Recap_reseau!$C18),INDIRECT("Descriptif!M"&F$13)=$D19),INDIRECT("Descriptif!F"&F$13),"")} | H19: {=IF(AND(OR(INDIRECT("Descriptif!I"&G$13)=Recap_reseau!$B18,INDIRECT("Descriptif!I"&G$13)=Recap_reseau!$C18),INDIRECT("Descriptif!M"&G$13)=$D19),INDIRECT("Descriptif!F"&G$13),"")} | I19: {=IF(AND(OR(INDIRECT("Descriptif!I"&H$13)=Recap_reseau!$B18,INDIRECT("Descriptif!I"&H$13)=Recap_reseau!$C18),INDIRECT("Descriptif!M"&H$13)=$D19),INDIRECT("Descriptif!F"&H$13),"")} | J19: {=IF(AND(OR(INDIRECT("Descriptif!I"&I$13)=Recap_reseau!$B18,INDIRECT("Descriptif!I"&I$13)=Recap_reseau!$C18),INDIRECT("Descriptif!M"&I$13)=$D19),INDIRECT("Descriptif!F"&I$13),"")} | K19: {=IF(AND(OR(INDIRECT("Descriptif!I"&J$13)=Recap_reseau!$B18,INDIRECT("Descriptif!I"&J$13)=Recap_reseau!$C18),INDIRECT("Descriptif!M"&J$13)=$D19),INDIRECT("Descriptif!F"&J$13),"")} | L19: {=IF(AND(OR(INDIRECT("Descriptif!I"&K$13)=Recap_reseau!$B18,INDIRECT("Descriptif!I"&K$13)=Recap_reseau!$C18),INDIRECT("Descriptif!M"&K$13)=$D19),INDIRECT("Descriptif!F"&K$13),"")} | M19: {=IF(AND(OR(INDIRECT("Descriptif!I"&L$13)=Recap_reseau!$B18,INDIRECT("Descriptif!I"&L$13)=Recap_reseau!$C18),INDIRECT("Descriptif!M"&L$13)=$D19),INDIRECT("Descriptif!F"&L$13),"")} | ... T19: {=IF(AND(OR(INDIRECT("Descriptif!I"&S$13)=Recap_reseau!$B18,INDIRECT("Descriptif!I"&S$13)=Recap_reseau!$C18),INDIRECT("Descriptif!M"&S$13)=$D19),INDIRECT("Descriptif!F"&S$13),"")}
D20: =$D$9 -> Préleveur | F20: {=IF(AND(OR(INDIRECT("Descriptif!I"&E$13)=Recap_reseau!$B18,INDIRECT("Descriptif!I"&E$13)=Recap_reseau!$C18),INDIRECT("Descriptif!M"&E$13)=$D20),INDIRECT("Descriptif!F"&E$13),"")} | G20: {=IF(AND(OR(INDIRECT("Descriptif!I"&F$13)=Recap_reseau!$B18,INDIRECT("Descriptif!I"&F$13)=Recap_reseau!$C18),INDIRECT("Descriptif!M"&F$13)=$D20),INDIRECT("Descriptif!F"&F$13),"")} | H20: {=IF(AND(OR(INDIRECT("Descriptif!I"&G$13)=Recap_reseau!$B18,INDIRECT("Descriptif!I"&G$13)=Recap_reseau!$C18),INDIRECT("Descriptif!M"&G$13)=$D20),INDIRECT("Descriptif!F"&G$13),"")} | I20: {=IF(AND(OR(INDIRECT("Descriptif!I"&H$13)=Recap_reseau!$B18,INDIRECT("Descriptif!I"&H$13)=Recap_reseau!$C18),INDIRECT("Descriptif!M"&H$13)=$D20),INDIRECT("Descriptif!F"&H$13),"")} | J20: {=IF(AND(OR(INDIRECT("Descriptif!I"&I$13)=Recap_reseau!$B18,INDIRECT("Descriptif!I"&I$13)=Recap_reseau!$C18),INDIRECT("Descriptif!M"&I$13)=$D20),INDIRECT("Descriptif!F"&I$13),"")} | K20: {=IF(AND(OR(INDIRECT("Descriptif!I"&J$13)=Recap_reseau!$B18,INDIRECT("Descriptif!I"&J$13)=Recap_reseau!$C18),INDIRECT("Descriptif!M"&J$13)=$D20),INDIRECT("Descriptif!F"&J$13),"")} | L20: {=IF(AND(OR(INDIRECT("Descriptif!I"&K$13)=Recap_reseau!$B18,INDIRECT("Descriptif!I"&K$13)=Recap_reseau!$C18),INDIRECT("Descriptif!M"&K$13)=$D20),INDIRECT("Descriptif!F"&K$13),"")} | M20: {=IF(AND(OR(INDIRECT("Descriptif!I"&L$13)=Recap_reseau!$B18,INDIRECT("Descriptif!I"&L$13)=Recap_reseau!$C18),INDIRECT("Descriptif!M"&L$13)=$D20),INDIRECT("Descriptif!F"&L$13),"")} | ... T20: {=IF(AND(OR(INDIRECT("Descriptif!I"&S$13)=Recap_reseau!$B18,INDIRECT("Descriptif!I"&S$13)=Recap_reseau!$C18),INDIRECT("Descriptif!M"&S$13)=$D20),INDIRECT("Descriptif!F"&S$13),"")}
D21: Analytique | F21: =IF(F20<>"",VLOOKUP(F20,Analytique!$X$3:$AE$29,1,FALSE),"") | G21: =IF(G20<>"",VLOOKUP(G20,Analytique!$X$3:$AE$29,1,FALSE),"") | H21: =IF(H20<>"",VLOOKUP(H20,Analytique!$X$3:$AE$29,1,FALSE),"") | I21: =IF(I20<>"",VLOOKUP(I20,Analytique!$X$3:$AE$29,1,FALSE),"") | J21: =IF(J20<>"",VLOOKUP(J20,Analytique!$X$3:$AE$29,1,FALSE),"") | K21: =IF(K20<>"",VLOOKUP(K20,Analytique!$X$3:$AE$29,1,FALSE),"") | L21: =IF(L20<>"",VLOOKUP(L20,Analytique!$X$3:$AE$29,1,FALSE),"") | M21: =IF(M20<>"",VLOOKUP(M20,Analytique!$X$3:$AE$29,1,FALSE),"") | ... T21: =IF(T20<>"",VLOOKUP(T20,Analytique!$X$3:$AE$29,1,FALSE),"")
D22: =$D$10 -> Sonde de température | F22: {=IF(AND(OR(INDIRECT("Descriptif!I"&E$13)=Recap_reseau!$B18,INDIRECT("Descriptif!I"&E$13)=Recap_reseau!$C18),INDIRECT("Descriptif!M"&E$13)=$D22),INDIRECT("Descriptif!F"&E$13),"")} | G22: {=IF(AND(OR(INDIRECT("Descriptif!I"&F$13)=Recap_reseau!$B18,INDIRECT("Descriptif!I"&F$13)=Recap_reseau!$C18),INDIRECT("Descriptif!M"&F$13)=$D22),INDIRECT("Descriptif!F"&F$13),"")} | H22: {=IF(AND(OR(INDIRECT("Descriptif!I"&G$13)=Recap_reseau!$B18,INDIRECT("Descriptif!I"&G$13)=Recap_reseau!$C18),INDIRECT("Descriptif!M"&G$13)=$D22),INDIRECT("Descriptif!F"&G$13),"")} | I22: {=IF(AND(OR(INDIRECT("Descriptif!I"&H$13)=Recap_reseau!$B18,INDIRECT("Descriptif!I"&H$13)=Recap_reseau!$C18),INDIRECT("Descriptif!M"&H$13)=$D22),INDIRECT("Descriptif!F"&H$13),"")} | J22: {=IF(AND(OR(INDIRECT("Descriptif!I"&I$13)=Recap_reseau!$B18,INDIRECT("Descriptif!I"&I$13)=Recap_reseau!$C18),INDIRECT("Descriptif!M"&I$13)=$D22),INDIRECT("Descriptif!F"&I$13),"")} | K22: {=IF(AND(OR(INDIRECT("Descriptif!I"&J$13)=Recap_reseau!$B18,INDIRECT("Descriptif!I"&J$13)=Recap_reseau!$C18),INDIRECT("Descriptif!M"&J$13)=$D22),INDIRECT("Descriptif!F"&J$13),"")} | L22: {=IF(AND(OR(INDIRECT("Descriptif!I"&K$13)=Recap_reseau!$B18,INDIRECT("Descriptif!I"&K$13)=Recap_reseau!$C18),INDIRECT("Descriptif!M"&K$13)=$D22),INDIRECT("Descriptif!F"&K$13),"")} | M22: {=IF(AND(OR(INDIRECT("Descriptif!I"&L$13)=Recap_reseau!$B18,INDIRECT("Descriptif!I"&L$13)=Recap_reseau!$C18),INDIRECT("Descriptif!M"&L$13)=$D22),INDIRECT("Descriptif!F"&L$13),"")} | ... T22: {=IF(AND(OR(INDIRECT("Descriptif!I"&S$13)=Recap_reseau!$B18,INDIRECT("Descriptif!I"&S$13)=Recap_reseau!$C18),INDIRECT("Descriptif!M"&S$13)=$D22),INDIRECT("Descriptif!F"&S$13),"")}
B24: Scores
B25: Les évaluations des sondes de température ne sont pas prises en compte
B26: Reg. | C26: Log. | E26: Moyennes générales | F26: Moyennes individuelles | G26: Point 1 | H26: Point 2 | I26: Point 3 | J26: Point 4 | K26: Point 5 | L26: Point 6 | M26: Point 7 | N26: Point 8 | O26: Point 9 | P26: Point 10 | Q26: Point 11 | R26: Point 12 | S26: Point 13 | T26: Point 14 | U26: Point 15
B27: A1 | C27: R1 | D27: =$D$7 -> Débitmètre en charge | E27: =IFERROR(AVERAGE(F29:F31)*$B$5,"") | F27: =IFERROR(AVERAGE(G27:U27),"") | G27: {=IF(F18<>"",INDIRECT(F18&"!"&$F$7),"")} | H27: {=IF(G18<>"",INDIRECT(G18&"!"&$F$7),"")} | I27: {=IF(H18<>"",INDIRECT(H18&"!"&$F$7),"")} | J27: {=IF(I18<>"",INDIRECT(I18&"!"&$F$7),"")} | K27: {=IF(J18<>"",INDIRECT(J18&"!"&$F$7),"")} | L27: {=IF(K18<>"",INDIRECT(K18&"!"&$F$7),"")} | M27: {=IF(L18<>"",INDIRECT(L18&"!"&$F$7),"")} | N27: {=IF(M18<>"",INDIRECT(M18&"!"&$F$7),"")} | ... U27: {=IF(T18<>"",INDIRECT(T18&"!"&$F$7),"")}
D28: =$D$8 -> Débitmètre gravitaire | F28: =IFERROR(AVERAGE(G28:U28),"") | G28: {=IF(F19<>"",INDIRECT(F19&"!"&$F$8),"")} | H28: {=IF(G19<>"",INDIRECT(G19&"!"&$F$8),"")} | I28: {=IF(H19<>"",INDIRECT(H19&"!"&$F$8),"")} | J28: {=IF(I19<>"",INDIRECT(I19&"!"&$F$8),"")} | K28: {=IF(J19<>"",INDIRECT(J19&"!"&$F$8),"")} | L28: {=IF(K19<>"",INDIRECT(K19&"!"&$F$8),"")} | M28: {=IF(L19<>"",INDIRECT(L19&"!"&$F$8),"")} | N28: {=IF(M19<>"",INDIRECT(M19&"!"&$F$8),"")} | ... U28: {=IF(T19<>"",INDIRECT(T19&"!"&$F$8),"")}
D29: Débitmètre | F29: =IFERROR(AVERAGE(G29:U29),"") | G29: =IF(COUNT(G27:G28)>0,SUM(G27:G28),"") | H29: =IF(COUNT(H27:H28)>0,SUM(H27:H28),"") | I29: =IF(COUNT(I27:I28)>0,SUM(I27:I28),"") | J29: =IF(COUNT(J27:J28)>0,SUM(J27:J28),"") | K29: =IF(COUNT(K27:K28)>0,SUM(K27:K28),"") | L29: =IF(COUNT(L27:L28)>0,SUM(L27:L28),"") | M29: =IF(COUNT(M27:M28)>0,SUM(M27:M28),"") | N29: =IF(COUNT(N27:N28)>0,SUM(N27:N28),"") | ... U29: =IF(COUNT(U27:U28)>0,SUM(U27:U28),"")
D30: =$D$9 -> Préleveur | F30: =IFERROR(AVERAGE(G30:U30),"") | G30: {=IF(F20<>"",INDIRECT(F20&"!"&$F$9),"")} | H30: {=IF(G20<>"",INDIRECT(G20&"!"&$F$9),"")} | I30: {=IF(H20<>"",INDIRECT(H20&"!"&$F$9),"")} | J30: {=IF(I20<>"",INDIRECT(I20&"!"&$F$9),"")} | K30: {=IF(J20<>"",INDIRECT(J20&"!"&$F$9),"")} | L30: {=IF(K20<>"",INDIRECT(K20&"!"&$F$9),"")} | M30: {=IF(L20<>"",INDIRECT(L20&"!"&$F$9),"")} | N30: {=IF(M20<>"",INDIRECT(M20&"!"&$F$9),"")} | ... U30: {=IF(T20<>"",INDIRECT(T20&"!"&$F$9),"")}
D31: Analytique | F31: =IFERROR(AVERAGE(G31:U31),"") | G31: =IF(F21<>"",VLOOKUP(F21,Analytique!$X$3:$AE$29,6,FALSE),"") | H31: =IF(G21<>"",VLOOKUP(G21,Analytique!$X$3:$AE$29,6,FALSE),"") | I31: =IF(H21<>"",VLOOKUP(H21,Analytique!$X$3:$AE$29,6,FALSE),"") | J31: =IF(I21<>"",VLOOKUP(I21,Analytique!$X$3:$AE$29,6,FALSE),"") | K31: =IF(J21<>"",VLOOKUP(J21,Analytique!$X$3:$AE$29,6,FALSE),"") | L31: =IF(K21<>"",VLOOKUP(K21,Analytique!$X$3:$AE$29,6,FALSE),"") | M31: =IF(L21<>"",VLOOKUP(L21,Analytique!$X$3:$AE$29,6,FALSE),"") | N31: =IF(M21<>"",VLOOKUP(M21,Analytique!$X$3:$AE$29,6,FALSE),"") | ... U31: =IF(T21<>"",VLOOKUP(T21,Analytique!$X$3:$AE$29,6,FALSE),"")
D32: =$D$10 -> Sonde de température | F32: =IFERROR(AVERAGE(G32:U32),"") | G32: {=IF(F22<>"",INDIRECT(F22&"!"&$F$10),"")} | H32: {=IF(G22<>"",INDIRECT(G22&"!"&$F$10),"")} | I32: {=IF(H22<>"",INDIRECT(H22&"!"&$F$10),"")} | J32: {=IF(I22<>"",INDIRECT(I22&"!"&$F$10),"")} | K32: {=IF(J22<>"",INDIRECT(J22&"!"&$F$10),"")} | L32: {=IF(K22<>"",INDIRECT(K22&"!"&$F$10),"")} | M32: {=IF(L22<>"",INDIRECT(L22&"!"&$F$10),"")} | N32: {=IF(M22<>"",INDIRECT(M22&"!"&$F$10),"")} | ... U32: {=IF(T22<>"",INDIRECT(T22&"!"&$F$10),"")}
B35: Evaluation finale controleur
B36: Les évaluations des sondes de température ne sont pas prises en compte
B37: Reg. | C37: Log. | E37: Evaluation globale | F37: Evaluations individuelles | G37: Point 1 | H37: Point 2 | I37: Point 3 | J37: Point 4 | K37: Point 5 | L37: Point 6 | M37: Point 7 | N37: Point 8 | O37: Point 9 | P37: Point 10 | Q37: Point 11 | R37: Point 12 | S37: Point 13 | T37: Point 14 | U37: Point 15
B38: A1 | C38: R1 | D38: =$D$7 -> Débitmètre en charge | E38: {=IFERROR(LOOKUP(MIN(IF(LEFT(F38:F42,10)="Non validé",1,IF(F38:F42="Validé avec réserve",2,IF(F38:F42="Validé",3)))),{1,2,3},{"Non validé","Validé avec réserve","Validé"}),"")} | F38: {=IFERROR(LOOKUP(MIN(IF(LEFT(G38:U38,10)="Non validé",1,IF(G38:U38="Validé avec réserve",2,IF(G38:U38="Validé",3)))),{1,2,3},{"Non validé","Validé avec réserve","Validé"}),"")} | G38: {=IF(F18<>"",INDIRECT(F18&"!"&$G$7),"")} | H38: {=IF(G18<>"",INDIRECT(G18&"!"&$G$7),"")} | I38: {=IF(H18<>"",INDIRECT(H18&"!"&$G$7),"")} | J38: {=IF(I18<>"",INDIRECT(I18&"!"&$G$7),"")} | K38: {=IF(J18<>"",INDIRECT(J18&"!"&$G$7),"")} | L38: {=IF(K18<>"",INDIRECT(K18&"!"&$G$7),"")} | M38: {=IF(L18<>"",INDIRECT(L18&"!"&$G$7),"")} | N38: {=IF(M18<>"",INDIRECT(M18&"!"&$G$7),"")} | ... U38: {=IF(T18<>"",INDIRECT(T18&"!"&$G$7),"")}
D39: =$D$8 -> Débitmètre gravitaire | F39: {=IFERROR(LOOKUP(MIN(IF(LEFT(G39:U39,10)="Non validé",1,IF(G39:U39="Validé avec réserve",2,IF(G39:U39="Validé",3)))),{1,2,3},{"Non validé","Validé avec réserve","Validé"}),"")} | G39: {=IF(F19<>"",INDIRECT(F19&"!"&$G$8),"")} | H39: {=IF(G19<>"",INDIRECT(G19&"!"&$G$8),"")} | I39: {=IF(H19<>"",INDIRECT(H19&"!"&$G$8),"")} | J39: {=IF(I19<>"",INDIRECT(I19&"!"&$G$8),"")} | K39: {=IF(J19<>"",INDIRECT(J19&"!"&$G$8),"")} | L39: {=IF(K19<>"",INDIRECT(K19&"!"&$G$8),"")} | M39: {=IF(L19<>"",INDIRECT(L19&"!"&$G$8),"")} | N39: {=IF(M19<>"",INDIRECT(M19&"!"&$G$8),"")} | ... U39: {=IF(T19<>"",INDIRECT(T19&"!"&$G$8),"")}
D40: Débitmètre | F40: {=IFERROR(LOOKUP(MIN(IF(LEFT(G40:U40,10)="Non validé",1,IF(G40:U40="Validé avec réserve",2,IF(G40:U40="Validé",3)))),{1,2,3},{"Non validé","Validé avec réserve","Validé"}),"")} | G40: =G38 & G39 | H40: =H38 & H39 | I40: =I38 & I39 | J40: =J38 & J39 | K40: =K38 & K39 | L40: =L38 & L39 | M40: =M38 & M39 | N40: =N38 & N39 | ... U40: =U38 & U39
D41: =$D$9 -> Préleveur | F41: {=IFERROR(LOOKUP(MIN(IF(LEFT(G41:U41,10)="Non validé",1,IF(G41:U41="Validé avec réserve",2,IF(G41:U41="Validé",3)))),{1,2,3},{"Non validé","Validé avec réserve","Validé"}),"")} | G41: {=IF(F20<>"",INDIRECT(F20&"!"&$G$9),"")} | H41: {=IF(G20<>"",INDIRECT(G20&"!"&$G$9),"")} | I41: {=IF(H20<>"",INDIRECT(H20&"!"&$G$9),"")} | J41: {=IF(I20<>"",INDIRECT(I20&"!"&$G$9),"")} | K41: {=IF(J20<>"",INDIRECT(J20&"!"&$G$9),"")} | L41: {=IF(K20<>"",INDIRECT(K20&"!"&$G$9),"")} | M41: {=IF(L20<>"",INDIRECT(L20&"!"&$G$9),"")} | N41: {=IF(M20<>"",INDIRECT(M20&"!"&$G$9),"")} | ... U41: {=IF(T20<>"",INDIRECT(T20&"!"&$G$9),"")}
D42: Analytique | F42: {=IFERROR(LOOKUP(MIN(IF(LEFT(G42:U42,10)="Non validé",1,IF(G42:U42="Validé avec réserve",2,IF(G42:U42="Validé",3)))),{1,2,3},{"Non validé","Validé avec réserve","Validé"}),"")} | G42: =IF(F21<>"",VLOOKUP(F21,Analytique!$X$3:$AE$29,7,FALSE),"") | H42: =IF(G21<>"",VLOOKUP(G21,Analytique!$X$3:$AE$29,7,FALSE),"") | I42: =IF(H21<>"",VLOOKUP(H21,Analytique!$X$3:$AE$29,7,FALSE),"") | J42: =IF(I21<>"",VLOOKUP(I21,Analytique!$X$3:$AE$29,7,FALSE),"") | K42: =IF(J21<>"",VLOOKUP(J21,Analytique!$X$3:$AE$29,7,FALSE),"") | L42: =IF(K21<>"",VLOOKUP(K21,Analytique!$X$3:$AE$29,7,FALSE),"") | M42: =IF(L21<>"",VLOOKUP(L21,Analytique!$X$3:$AE$29,7,FALSE),"") | N42: =IF(M21<>"",VLOOKUP(M21,Analytique!$X$3:$AE$29,7,FALSE),"") | ... U42: =IF(T21<>"",VLOOKUP(T21,Analytique!$X$3:$AE$29,7,FALSE),"")
D43: =$D$10 -> Sonde de température | F43: {=IFERROR(LOOKUP(MIN(IF(LEFT(G43:U43,10)="Non validé",1,IF(G43:U43="Validé avec réserve",2,IF(G43:U43="Validé",3)))),{1,2,3},{"Non validé","Validé avec réserve","Validé"}),"")} | G43: {=IF(F22<>"",INDIRECT(F22&"!"&$G$10),"")} | H43: {=IF(G22<>"",INDIRECT(G22&"!"&$G$10),"")} | I43: {=IF(H22<>"",INDIRECT(H22&"!"&$G$10),"")} | J43: {=IF(I22<>"",INDIRECT(I22&"!"&$G$10),"")} | K43: {=IF(J22<>"",INDIRECT(J22&"!"&$G$10),"")} | L43: {=IF(K22<>"",INDIRECT(K22&"!"&$G$10),"")} | M43: {=IF(L22<>"",INDIRECT(L22&"!"&$G$10),"")} | N43: {=IF(M22<>"",INDIRECT(M22&"!"&$G$10),"")} | ... U43: {=IF(T22<>"",INDIRECT(T22&"!"&$G$10),"")}

Sheet Recap_equipements
B1: Préparation des données pour la feuilles synthèse et pour les exports
B2: Paramètres de localisation des données dans les cellules
B4: Facteur Qualité | D4: Type Equipement | E4: Type
B5: =IF(Qualité!L29="Oui",1,0.9) -> 0.9 | E5: cellule typeE | F5: cellule score | G5: cellule eval | H5: cellule commentaire score | I5: cellule commentaire
D6: Pluviomètre | E6: D25 | F6: P33 | G6: N33 | H6: D33 | I6: C37
D7: =PARAM!$C4 -> Débitmètre en charge | E7: D32 | F7: P45 | G7: N45 | H7: D45 | I7: C49
D8: =PARAM!$C5 -> Débitmètre gravitaire | E8: D40 | F8: R53 | G8: P53 | H8: D53 | I8: C57
D9: =PARAM!$C6 -> Préleveur | E9: D37 | F9: P50 | G9: N50 | H9: D50 | I9: C54
D10: =PARAM!$C7 -> Sonde de température | E10: D26 | F10: P33 | G10: N33 | H10: D33 | I10: C37
D12: Type ligne | E12: Ligne
D13: Ligne STEU | E13: =Descriptif!$AD$3 -> 34 | F13: =E13+1 -> 35 | G13: =F13+1 -> 36 | H13: =G13+1 -> 37 | I13: =H13+1 -> 38 | J13: =I13+1 -> 39 | K13: =J13+1 -> 40 | L13: =K13+1 -> 41 | M13: =L13+1 -> 42 | ... S13: =R13+1 -> 48
D14: Ligne SCL | E14: =Descriptif!$AD$2 -> 14 | F14: =E14+1 -> 15 | G14: =F14+1 -> 16 | H14: =G14+1 -> 17 | I14: =H14+1 -> 18 | J14: =I14+1 -> 19 | K14: =J14+1 -> 20 | L14: =K14+1 -> 21 | M14: =L14+1 -> 22 | ... S14: =R14+1 -> 28
B16: Identification des feuilles de données
B18: Reg. | C18: Log. | F18: Point 1 | G18: Point 2 | H18: Point 3 | I18: Point 4 | J18: Point 5 | K18: Point 6 | L18: Point 7 | M18: Point 8 | N18: Point 9 | O18: Point 10 | P18: Point 11 | Q18: Point 12 | R18: Point 13 | S18: Point 14 | T18: Point 15
B19: A3 | C19: S1 | D19: =$D$7 -> Débitmètre en charge | F19: {=IF(AND(OR(INDIRECT("Descriptif!I"&E$13)=Recap_equipements!$B19,INDIRECT("Descriptif!I"&E$13)=Recap_equipements!$C19),INDIRECT("Descriptif!M"&E$13)=$D19),INDIRECT("Descriptif!F"&E$13),"")} | G19: {=IF(AND(OR(INDIRECT("Descriptif!I"&F$13)=Recap_equipements!$B19,INDIRECT("Descriptif!I"&F$13)=Recap_equipements!$C19),INDIRECT("Descriptif!M"&F$13)=$D19),INDIRECT("Descriptif!F"&F$13),"")} | H19: {=IF(AND(OR(INDIRECT("Descriptif!I"&G$13)=Recap_equipements!$B19,INDIRECT("Descriptif!I"&G$13)=Recap_equipements!$C19),INDIRECT("Descriptif!M"&G$13)=$D19),INDIRECT("Descriptif!F"&G$13),"")} | I19: {=IF(AND(OR(INDIRECT("Descriptif!I"&H$13)=Recap_equipements!$B19,INDIRECT("Descriptif!I"&H$13)=Recap_equipements!$C19),INDIRECT("Descriptif!M"&H$13)=$D19),INDIRECT("Descriptif!F"&H$13),"")} | J19: {=IF(AND(OR(INDIRECT("Descriptif!I"&I$13)=Recap_equipements!$B19,INDIRECT("Descriptif!I"&I$13)=Recap_equipements!$C19),INDIRECT("Descriptif!M"&I$13)=$D19),INDIRECT("Descriptif!F"&I$13),"")} | K19: {=IF(AND(OR(INDIRECT("Descriptif!I"&J$13)=Recap_equipements!$B19,INDIRECT("Descriptif!I"&J$13)=Recap_equipements!$C19),INDIRECT("Descriptif!M"&J$13)=$D19),INDIRECT("Descriptif!F"&J$13),"")} | L19: {=IF(AND(OR(INDIRECT("Descriptif!I"&K$13)=Recap_equipements!$B19,INDIRECT("Descriptif!I"&K$13)=Recap_equipements!$C19),INDIRECT("Descriptif!M"&K$13)=$D19),INDIRECT("Descriptif!F"&K$13),"")} | M19: {=IF(AND(OR(INDIRECT("Descriptif!I"&L$13)=Recap_equipements!$B19,INDIRECT("Descriptif!I"&L$13)=Recap_equipements!$C19),INDIRECT("Descriptif!M"&L$13)=$D19),INDIRECT("Descriptif!F"&L$13),"")} | ... T19: {=IF(AND(OR(INDIRECT("Descriptif!I"&S$13)=Recap_equipements!$B19,INDIRECT("Descriptif!I"&S$13)=Recap_equipements!$C19),INDIRECT("Descriptif!M"&S$13)=$D19),INDIRECT("Descriptif!F"&S$13),"")}
D20: =$D$8 -> Débitmètre gravitaire | F20: {=IF(AND(OR(INDIRECT("Descriptif!I"&E$13)=Recap_equipements!$B19,INDIRECT("Descriptif!I"&E$13)=Recap_equipements!$C19),INDIRECT("Descriptif!M"&E$13)=$D20),INDIRECT("Descriptif!F"&E$13),"")} | G20: {=IF(AND(OR(INDIRECT("Descriptif!I"&F$13)=Recap_equipements!$B19,INDIRECT("Descriptif!I"&F$13)=Recap_equipements!$C19),INDIRECT("Descriptif!M"&F$13)=$D20),INDIRECT("Descriptif!F"&F$13),"")} | H20: {=IF(AND(OR(INDIRECT("Descriptif!I"&G$13)=Recap_equipements!$B19,INDIRECT("Descriptif!I"&G$13)=Recap_equipements!$C19),INDIRECT("Descriptif!M"&G$13)=$D20),INDIRECT("Descriptif!F"&G$13),"")} | I20: {=IF(AND(OR(INDIRECT("Descriptif!I"&H$13)=Recap_equipements!$B19,INDIRECT("Descriptif!I"&H$13)=Recap_equipements!$C19),INDIRECT("Descriptif!M"&H$13)=$D20),INDIRECT("Descriptif!F"&H$13),"")} | J20: {=IF(AND(OR(INDIRECT("Descriptif!I"&I$13)=Recap_equipements!$B19,INDIRECT("Descriptif!I"&I$13)=Recap_equipements!$C19),INDIRECT("Descriptif!M"&I$13)=$D20),INDIRECT("Descriptif!F"&I$13),"")} | K20: {=IF(AND(OR(INDIRECT("Descriptif!I"&J$13)=Recap_equipements!$B19,INDIRECT("Descriptif!I"&J$13)=Recap_equipements!$C19),INDIRECT("Descriptif!M"&J$13)=$D20),INDIRECT("Descriptif!F"&J$13),"")} | L20: {=IF(AND(OR(INDIRECT("Descriptif!I"&K$13)=Recap_equipements!$B19,INDIRECT("Descriptif!I"&K$13)=Recap_equipements!$C19),INDIRECT("Descriptif!M"&K$13)=$D20),INDIRECT("Descriptif!F"&K$13),"")} | M20: {=IF(AND(OR(INDIRECT("Descriptif!I"&L$13)=Recap_equipements!$B19,INDIRECT("Descriptif!I"&L$13)=Recap_equipements!$C19),INDIRECT("Descriptif!M"&L$13)=$D20),INDIRECT("Descriptif!F"&L$13),"")} | ... T20: {=IF(AND(OR(INDIRECT("Descriptif!I"&S$13)=Recap_equipements!$B19,INDIRECT("Descriptif!I"&S$13)=Recap_equipements!$C19),INDIRECT("Descriptif!M"&S$13)=$D20),INDIRECT("Descriptif!F"&S$13),"")}
D21: =$D$9 -> Préleveur | F21: {=IF(AND(OR(INDIRECT("Descriptif!I"&E$13)=Recap_equipements!$B19,INDIRECT("Descriptif!I"&E$13)=Recap_equipements!$C19),INDIRECT("Descriptif!M"&E$13)=$D21),INDIRECT("Descriptif!F"&E$13),"")} | G21: {=IF(AND(OR(INDIRECT("Descriptif!I"&F$13)=Recap_equipements!$B19,INDIRECT("Descriptif!I"&F$13)=Recap_equipements!$C19),INDIRECT("Descriptif!M"&F$13)=$D21),INDIRECT("Descriptif!F"&F$13),"")} | H21: {=IF(AND(OR(INDIRECT("Descriptif!I"&G$13)=Recap_equipements!$B19,INDIRECT("Descriptif!I"&G$13)=Recap_equipements!$C19),INDIRECT("Descriptif!M"&G$13)=$D21),INDIRECT("Descriptif!F"&G$13),"")} | I21: {=IF(AND(OR(INDIRECT("Descriptif!I"&H$13)=Recap_equipements!$B19,INDIRECT("Descriptif!I"&H$13)=Recap_equipements!$C19),INDIRECT("Descriptif!M"&H$13)=$D21),INDIRECT("Descriptif!F"&H$13),"")} | J21: {=IF(AND(OR(INDIRECT("Descriptif!I"&I$13)=Recap_equipements!$B19,INDIRECT("Descriptif!I"&I$13)=Recap_equipements!$C19),INDIRECT("Descriptif!M"&I$13)=$D21),INDIRECT("Descriptif!F"&I$13),"")} | K21: {=IF(AND(OR(INDIRECT("Descriptif!I"&J$13)=Recap_equipements!$B19,INDIRECT("Descriptif!I"&J$13)=Recap_equipements!$C19),INDIRECT("Descriptif!M"&J$13)=$D21),INDIRECT("Descriptif!F"&J$13),"")} | L21: {=IF(AND(OR(INDIRECT("Descriptif!I"&K$13)=Recap_equipements!$B19,INDIRECT("Descriptif!I"&K$13)=Recap_equipements!$C19),INDIRECT("Descriptif!M"&K$13)=$D21),INDIRECT("Descriptif!F"&K$13),"")} | M21: {=IF(AND(OR(INDIRECT("Descriptif!I"&L$13)=Recap_equipements!$B19,INDIRECT("Descriptif!I"&L$13)=Recap_equipements!$C19),INDIRECT("Descriptif!M"&L$13)=$D21),INDIRECT("Descriptif!F"&L$13),"")} | ... T21: {=IF(AND(OR(INDIRECT("Descriptif!I"&S$13)=Recap_equipements!$B19,INDIRECT("Descriptif!I"&S$13)=Recap_equipements!$C19),INDIRECT("Descriptif!M"&S$13)=$D21),INDIRECT("Descriptif!F"&S$13),"")}
D22: Analytique | F22: =IF(F21<>"",VLOOKUP(F21,Analytique!$X$3:$AE$29,1,FALSE),"") | G22: =IF(G21<>"",VLOOKUP(G21,Analytique!$X$3:$AE$29,1,FALSE),"") | H22: =IF(H21<>"",VLOOKUP(H21,Analytique!$X$3:$AE$29,1,FALSE),"") | I22: =IF(I21<>"",VLOOKUP(I21,Analytique!$X$3:$AE$29,1,FALSE),"") | J22: =IF(J21<>"",VLOOKUP(J21,Analytique!$X$3:$AE$29,1,FALSE),"") | K22: =IF(K21<>"",VLOOKUP(K21,Analytique!$X$3:$AE$29,1,FALSE),"") | L22: =IF(L21<>"",VLOOKUP(L21,Analytique!$X$3:$AE$29,1,FALSE),"") | M22: =IF(M21<>"",VLOOKUP(M21,Analytique!$X$3:$AE$29,1,FALSE),"") | ... T22: =IF(T21<>"",VLOOKUP(T21,Analytique!$X$3:$AE$29,1,FALSE),"")
D23: =$D$10 -> Sonde de température | F23: {=IF(AND(OR(INDIRECT("Descriptif!I"&E$13)=Recap_equipements!$B19,INDIRECT("Descriptif!I"&E$13)=Recap_equipements!$C19),INDIRECT("Descriptif!M"&E$13)=$D23),INDIRECT("Descriptif!F"&E$13),"")} | G23: {=IF(AND(OR(INDIRECT("Descriptif!I"&F$13)=Recap_equipements!$B19,INDIRECT("Descriptif!I"&F$13)=Recap_equipements!$C19),INDIRECT("Descriptif!M"&F$13)=$D23),INDIRECT("Descriptif!F"&F$13),"")} | H23: {=IF(AND(OR(INDIRECT("Descriptif!I"&G$13)=Recap_equipements!$B19,INDIRECT("Descriptif!I"&G$13)=Recap_equipements!$C19),INDIRECT("Descriptif!M"&G$13)=$D23),INDIRECT("Descriptif!F"&G$13),"")} | I23: {=IF(AND(OR(INDIRECT("Descriptif!I"&H$13)=Recap_equipements!$B19,INDIRECT("Descriptif!I"&H$13)=Recap_equipements!$C19),INDIRECT("Descriptif!M"&H$13)=$D23),INDIRECT("Descriptif!F"&H$13),"")} | J23: {=IF(AND(OR(INDIRECT("Descriptif!I"&I$13)=Recap_equipements!$B19,INDIRECT("Descriptif!I"&I$13)=Recap_equipements!$C19),INDIRECT("Descriptif!M"&I$13)=$D23),INDIRECT("Descriptif!F"&I$13),"")} | K23: {=IF(AND(OR(INDIRECT("Descriptif!I"&J$13)=Recap_equipements!$B19,INDIRECT("Descriptif!I"&J$13)=Recap_equipements!$C19),INDIRECT("Descriptif!M"&J$13)=$D23),INDIRECT("Descriptif!F"&J$13),"")} | L23: {=IF(AND(OR(INDIRECT("Descriptif!I"&K$13)=Recap_equipements!$B19,INDIRECT("Descriptif!I"&K$13)=Recap_equipements!$C19),INDIRECT("Descriptif!M"&K$13)=$D23),INDIRECT("Descriptif!F"&K$13),"")} | M23: {=IF(AND(OR(INDIRECT("Descriptif!I"&L$13)=Recap_equipements!$B19,INDIRECT("Descriptif!I"&L$13)=Recap_equipements!$C19),INDIRECT("Descriptif!M"&L$13)=$D23),INDIRECT("Descriptif!F"&L$13),"")} | ... T23: {=IF(AND(OR(INDIRECT("Descriptif!I"&S$13)=Recap_equipements!$B19,INDIRECT("Descriptif!I"&S$13)=Recap_equipements!$C19),INDIRECT("Descriptif!M"&S$13)=$D23),INDIRECT("Descriptif!F"&S$13),"")}
B24: A4 | C24: S2 | D24: =$D$7 -> Débitmètre en charge | F24: {=IF(AND(OR(INDIRECT("Descriptif!I"&E$13)=Recap_equipements!$B24,INDIRECT("Descriptif!I"&E$13)=Recap_equipements!$C24),INDIRECT("Descriptif!M"&E$13)=$D24),INDIRECT("Descriptif!F"&E$13),"")} | G24: {=IF(AND(OR(INDIRECT("Descriptif!I"&F$13)=Recap_equipements!$B24,INDIRECT("Descriptif!I"&F$13)=Recap_equipements!$C24),INDIRECT("Descriptif!M"&F$13)=$D24),INDIRECT("Descriptif!F"&F$13),"")} | H24: {=IF(AND(OR(INDIRECT("Descriptif!I"&G$13)=Recap_equipements!$B24,INDIRECT("Descriptif!I"&G$13)=Recap_equipements!$C24),INDIRECT("Descriptif!M"&G$13)=$D24),INDIRECT("Descriptif!F"&G$13),"")} | I24: {=IF(AND(OR(INDIRECT("Descriptif!I"&H$13)=Recap_equipements!$B24,INDIRECT("Descriptif!I"&H$13)=Recap_equipements!$C24),INDIRECT("Descriptif!M"&H$13)=$D24),INDIRECT("Descriptif!F"&H$13),"")} | J24: {=IF(AND(OR(INDIRECT("Descriptif!I"&I$13)=Recap_equipements!$B24,INDIRECT("Descriptif!I"&I$13)=Recap_equipements!$C24),INDIRECT("Descriptif!M"&I$13)=$D24),INDIRECT("Descriptif!F"&I$13),"")} | K24: {=IF(AND(OR(INDIRECT("Descriptif!I"&J$13)=Recap_equipements!$B24,INDIRECT("Descriptif!I"&J$13)=Recap_equipements!$C24),INDIRECT("Descriptif!M"&J$13)=$D24),INDIRECT("Descriptif!F"&J$13),"")} | L24: {=IF(AND(OR(INDIRECT("Descriptif!I"&K$13)=Recap_equipements!$B24,INDIRECT("Descriptif!I"&K$13)=Recap_equipements!$C24),INDIRECT("Descriptif!M"&K$13)=$D24),INDIRECT("Descriptif!F"&K$13),"")} | M24: {=IF(AND(OR(INDIRECT("Descriptif!I"&L$13)=Recap_equipements!$B24,INDIRECT("Descriptif!I"&L$13)=Recap_equipements!$C24),INDIRECT("Descriptif!M"&L$13)=$D24),INDIRECT("Descriptif!F"&L$13),"")} | ... T24: {=IF(AND(OR(INDIRECT("Descriptif!I"&S$13)=Recap_equipements!$B24,INDIRECT("Descriptif!I"&S$13)=Recap_equipements!$C24),INDIRECT("Descriptif!M"&S$13)=$D24),INDIRECT("Descriptif!F"&S$13),"")}
D25: =$D$8 -> Débitmètre gravitaire | F25: {=IF(AND(OR(INDIRECT("Descriptif!I"&E$13)=Recap_equipements!$B24,INDIRECT("Descriptif!I"&E$13)=Recap_equipements!$C24),INDIRECT("Descriptif!M"&E$13)=$D25),INDIRECT("Descriptif!F"&E$13),"")} | G25: {=IF(AND(OR(INDIRECT("Descriptif!I"&F$13)=Recap_equipements!$B24,INDIRECT("Descriptif!I"&F$13)=Recap_equipements!$C24),INDIRECT("Descriptif!M"&F$13)=$D25),INDIRECT("Descriptif!F"&F$13),"")} | H25: {=IF(AND(OR(INDIRECT("Descriptif!I"&G$13)=Recap_equipements!$B24,INDIRECT("Descriptif!I"&G$13)=Recap_equipements!$C24),INDIRECT("Descriptif!M"&G$13)=$D25),INDIRECT("Descriptif!F"&G$13),"")} | I25: {=IF(AND(OR(INDIRECT("Descriptif!I"&H$13)=Recap_equipements!$B24,INDIRECT("Descriptif!I"&H$13)=Recap_equipements!$C24),INDIRECT("Descriptif!M"&H$13)=$D25),INDIRECT("Descriptif!F"&H$13),"")} | J25: {=IF(AND(OR(INDIRECT("Descriptif!I"&I$13)=Recap_equipements!$B24,INDIRECT("Descriptif!I"&I$13)=Recap_equipements!$C24),INDIRECT("Descriptif!M"&I$13)=$D25),INDIRECT("Descriptif!F"&I$13),"")} | K25: {=IF(AND(OR(INDIRECT("Descriptif!I"&J$13)=Recap_equipements!$B24,INDIRECT("Descriptif!I"&J$13)=Recap_equipements!$C24),INDIRECT("Descriptif!M"&J$13)=$D25),INDIRECT("Descriptif!F"&J$13),"")} | L25: {=IF(AND(OR(INDIRECT("Descriptif!I"&K$13)=Recap_equipements!$B24,INDIRECT("Descriptif!I"&K$13)=Recap_equipements!$C24),INDIRECT("Descriptif!M"&K$13)=$D25),INDIRECT("Descriptif!F"&K$13),"")} | M25: {=IF(AND(OR(INDIRECT("Descriptif!I"&L$13)=Recap_equipements!$B24,INDIRECT("Descriptif!I"&L$13)=Recap_equipements!$C24),INDIRECT("Descriptif!M"&L$13)=$D25),INDIRECT("Descriptif!F"&L$13),"")} | ... T25: {=IF(AND(OR(INDIRECT("Descriptif!I"&S$13)=Recap_equipements!$B24,INDIRECT("Descriptif!I"&S$13)=Recap_equipements!$C24),INDIRECT("Descriptif!M"&S$13)=$D25),INDIRECT("Descriptif!F"&S$13),"")}
D26: =$D$9 -> Préleveur | F26: {=IF(AND(OR(INDIRECT("Descriptif!I"&E$13)=Recap_equipements!$B24,INDIRECT("Descriptif!I"&E$13)=Recap_equipements!$C24),INDIRECT("Descriptif!M"&E$13)=$D26),INDIRECT("Descriptif!F"&E$13),"")} | G26: {=IF(AND(OR(INDIRECT("Descriptif!I"&F$13)=Recap_equipements!$B24,INDIRECT("Descriptif!I"&F$13)=Recap_equipements!$C24),INDIRECT("Descriptif!M"&F$13)=$D26),INDIRECT("Descriptif!F"&F$13),"")} | H26: {=IF(AND(OR(INDIRECT("Descriptif!I"&G$13)=Recap_equipements!$B24,INDIRECT("Descriptif!I"&G$13)=Recap_equipements!$C24),INDIRECT("Descriptif!M"&G$13)=$D26),INDIRECT("Descriptif!F"&G$13),"")} | I26: {=IF(AND(OR(INDIRECT("Descriptif!I"&H$13)=Recap_equipements!$B24,INDIRECT("Descriptif!I"&H$13)=Recap_equipements!$C24),INDIRECT("Descriptif!M"&H$13)=$D26),INDIRECT("Descriptif!F"&H$13),"")} | J26: {=IF(AND(OR(INDIRECT("Descriptif!I"&I$13)=Recap_equipements!$B24,INDIRECT("Descriptif!I"&I$13)=Recap_equipements!$C24),INDIRECT("Descriptif!M"&I$13)=$D26),INDIRECT("Descriptif!F"&I$13),"")} | K26: {=IF(AND(OR(INDIRECT("Descriptif!I"&J$13)=Recap_equipements!$B24,INDIRECT("Descriptif!I"&J$13)=Recap_equipements!$C24),INDIRECT("Descriptif!M"&J$13)=$D26),INDIRECT("Descriptif!F"&J$13),"")} | L26: {=IF(AND(OR(INDIRECT("Descriptif!I"&K$13)=Recap_equipements!$B24,INDIRECT("Descriptif!I"&K$13)=Recap_equipements!$C24),INDIRECT("Descriptif!M"&K$13)=$D26),INDIRECT("Descriptif!F"&K$13),"")} | M26: {=IF(AND(OR(INDIRECT("Descriptif!I"&L$13)=Recap_equipements!$B24,INDIRECT("Descriptif!I"&L$13)=Recap_equipements!$C24),INDIRECT("Descriptif!M"&L$13)=$D26),INDIRECT("Descriptif!F"&L$13),"")} | ... T26: {=IF(AND(OR(INDIRECT("Descriptif!I"&S$13)=Recap_equipements!$B24,INDIRECT("Descriptif!I"&S$13)=Recap_equipements!$C24),INDIRECT("Descriptif!M"&S$13)=$D26),INDIRECT("Descriptif!F"&S$13),"")}
D27: Analytique | F27: =IF(F26<>"",VLOOKUP(F26,Analytique!$X$3:$AE$29,1,FALSE),"") | G27: =IF(G26<>"",VLOOKUP(G26,Analytique!$X$3:$AE$29,1,FALSE),"") | H27: =IF(H26<>"",VLOOKUP(H26,Analytique!$X$3:$AE$29,1,FALSE),"") | I27: =IF(I26<>"",VLOOKUP(I26,Analytique!$X$3:$AE$29,1,FALSE),"") | J27: =IF(J26<>"",VLOOKUP(J26,Analytique!$X$3:$AE$29,1,FALSE),"") | K27: =IF(K26<>"",VLOOKUP(K26,Analytique!$X$3:$AE$29,1,FALSE),"") | L27: =IF(L26<>"",VLOOKUP(L26,Analytique!$X$3:$AE$29,1,FALSE),"") | M27: =IF(M26<>"",VLOOKUP(M26,Analytique!$X$3:$AE$29,1,FALSE),"") | ... T27: =IF(T26<>"",VLOOKUP(T26,Analytique!$X$3:$AE$29,1,FALSE),"")
D28: =$D$10 -> Sonde de température | F28: {=IF(AND(OR(INDIRECT("Descriptif!I"&E$13)=Recap_equipements!$B24,INDIRECT("Descriptif!I"&E$13)=Recap_equipements!$C24),INDIRECT("Descriptif!M"&E$13)=$D28),INDIRECT("Descriptif!F"&E$13),"")} | G28: {=IF(AND(OR(INDIRECT("Descriptif!I"&F$13)=Recap_equipements!$B24,INDIRECT("Descriptif!I"&F$13)=Recap_equipements!$C24),INDIRECT("Descriptif!M"&F$13)=$D28),INDIRECT("Descriptif!F"&F$13),"")} | H28: {=IF(AND(OR(INDIRECT("Descriptif!I"&G$13)=Recap_equipements!$B24,INDIRECT("Descriptif!I"&G$13)=Recap_equipements!$C24),INDIRECT("Descriptif!M"&G$13)=$D28),INDIRECT("Descriptif!F"&G$13),"")} | I28: {=IF(AND(OR(INDIRECT("Descriptif!I"&H$13)=Recap_equipements!$B24,INDIRECT("Descriptif!I"&H$13)=Recap_equipements!$C24),INDIRECT("Descriptif!M"&H$13)=$D28),INDIRECT("Descriptif!F"&H$13),"")} | J28: {=IF(AND(OR(INDIRECT("Descriptif!I"&I$13)=Recap_equipements!$B24,INDIRECT("Descriptif!I"&I$13)=Recap_equipements!$C24),INDIRECT("Descriptif!M"&I$13)=$D28),INDIRECT("Descriptif!F"&I$13),"")} | K28: {=IF(AND(OR(INDIRECT("Descriptif!I"&J$13)=Recap_equipements!$B24,INDIRECT("Descriptif!I"&J$13)=Recap_equipements!$C24),INDIRECT("Descriptif!M"&J$13)=$D28),INDIRECT("Descriptif!F"&J$13),"")} | L28: {=IF(AND(OR(INDIRECT("Descriptif!I"&K$13)=Recap_equipements!$B24,INDIRECT("Descriptif!I"&K$13)=Recap_equipements!$C24),INDIRECT("Descriptif!M"&K$13)=$D28),INDIRECT("Descriptif!F"&K$13),"")} | M28: {=IF(AND(OR(INDIRECT("Descriptif!I"&L$13)=Recap_equipements!$B24,INDIRECT("Descriptif!I"&L$13)=Recap_equipements!$C24),INDIRECT("Descriptif!M"&L$13)=$D28),INDIRECT("Descriptif!F"&L$13),"")} | ... T28: {=IF(AND(OR(INDIRECT("Descriptif!I"&S$13)=Recap_equipements!$B24,INDIRECT("Descriptif!I"&S$13)=Recap_equipements!$C24),INDIRECT("Descriptif!M"&S$13)=$D28),INDIRECT("Descriptif!F"&S$13),"")}
B29: A2 | C29: S16 | D29: =$D$7 -> Débitmètre en charge | F29: {=IF(AND(OR(INDIRECT("Descriptif!I"&E$13)=Recap_equipements!$B29,INDIRECT("Descriptif!I"&E$13)=Recap_equipements!$C29),INDIRECT("Descriptif!M"&E$13)=$D29),INDIRECT("Descriptif!F"&E$13),"")} | G29: {=IF(AND(OR(INDIRECT("Descriptif!I"&F$13)=Recap_equipements!$B29,INDIRECT("Descriptif!I"&F$13)=Recap_equipements!$C29),INDIRECT("Descriptif!M"&F$13)=$D29),INDIRECT("Descriptif!F"&F$13),"")} | H29: {=IF(AND(OR(INDIRECT("Descriptif!I"&G$13)=Recap_equipements!$B29,INDIRECT("Descriptif!I"&G$13)=Recap_equipements!$C29),INDIRECT("Descriptif!M"&G$13)=$D29),INDIRECT("Descriptif!F"&G$13),"")} | I29: {=IF(AND(OR(INDIRECT("Descriptif!I"&H$13)=Recap_equipements!$B29,INDIRECT("Descriptif!I"&H$13)=Recap_equipements!$C29),INDIRECT("Descriptif!M"&H$13)=$D29),INDIRECT("Descriptif!F"&H$13),"")} | J29: {=IF(AND(OR(INDIRECT("Descriptif!I"&I$13)=Recap_equipements!$B29,INDIRECT("Descriptif!I"&I$13)=Recap_equipements!$C29),INDIRECT("Descriptif!M"&I$13)=$D29),INDIRECT("Descriptif!F"&I$13),"")} | K29: {=IF(AND(OR(INDIRECT("Descriptif!I"&J$13)=Recap_equipements!$B29,INDIRECT("Descriptif!I"&J$13)=Recap_equipements!$C29),INDIRECT("Descriptif!M"&J$13)=$D29),INDIRECT("Descriptif!F"&J$13),"")} | L29: {=IF(AND(OR(INDIRECT("Descriptif!I"&K$13)=Recap_equipements!$B29,INDIRECT("Descriptif!I"&K$13)=Recap_equipements!$C29),INDIRECT("Descriptif!M"&K$13)=$D29),INDIRECT("Descriptif!F"&K$13),"")} | M29: {=IF(AND(OR(INDIRECT("Descriptif!I"&L$13)=Recap_equipements!$B29,INDIRECT("Descriptif!I"&L$13)=Recap_equipements!$C29),INDIRECT("Descriptif!M"&L$13)=$D29),INDIRECT("Descriptif!F"&L$13),"")} | ... T29: {=IF(AND(OR(INDIRECT("Descriptif!I"&S$13)=Recap_equipements!$B29,INDIRECT("Descriptif!I"&S$13)=Recap_equipements!$C29),INDIRECT("Descriptif!M"&S$13)=$D29),INDIRECT("Descriptif!F"&S$13),"")}
D30: =$D$8 -> Débitmètre gravitaire | F30: {=IF(AND(OR(INDIRECT("Descriptif!I"&E$13)=Recap_equipements!$B29,INDIRECT("Descriptif!I"&E$13)=Recap_equipements!$C29),INDIRECT("Descriptif!M"&E$13)=$D30),INDIRECT("Descriptif!F"&E$13),"")} | G30: {=IF(AND(OR(INDIRECT("Descriptif!I"&F$13)=Recap_equipements!$B29,INDIRECT("Descriptif!I"&F$13)=Recap_equipements!$C29),INDIRECT("Descriptif!M"&F$13)=$D30),INDIRECT("Descriptif!F"&F$13),"")} | H30: {=IF(AND(OR(INDIRECT("Descriptif!I"&G$13)=Recap_equipements!$B29,INDIRECT("Descriptif!I"&G$13)=Recap_equipements!$C29),INDIRECT("Descriptif!M"&G$13)=$D30),INDIRECT("Descriptif!F"&G$13),"")} | I30: {=IF(AND(OR(INDIRECT("Descriptif!I"&H$13)=Recap_equipements!$B29,INDIRECT("Descriptif!I"&H$13)=Recap_equipements!$C29),INDIRECT("Descriptif!M"&H$13)=$D30),INDIRECT("Descriptif!F"&H$13),"")} | J30: {=IF(AND(OR(INDIRECT("Descriptif!I"&I$13)=Recap_equipements!$B29,INDIRECT("Descriptif!I"&I$13)=Recap_equipements!$C29),INDIRECT("Descriptif!M"&I$13)=$D30),INDIRECT("Descriptif!F"&I$13),"")} | K30: {=IF(AND(OR(INDIRECT("Descriptif!I"&J$13)=Recap_equipements!$B29,INDIRECT("Descriptif!I"&J$13)=Recap_equipements!$C29),INDIRECT("Descriptif!M"&J$13)=$D30),INDIRECT("Descriptif!F"&J$13),"")} | L30: {=IF(AND(OR(INDIRECT("Descriptif!I"&K$13)=Recap_equipements!$B29,INDIRECT("Descriptif!I"&K$13)=Recap_equipements!$C29),INDIRECT("Descriptif!M"&K$13)=$D30),INDIRECT("Descriptif!F"&K$13),"")} | M30: {=IF(AND(OR(INDIRECT("Descriptif!I"&L$13)=Recap_equipements!$B29,INDIRECT("Descriptif!I"&L$13)=Recap_equipements!$C29),INDIRECT("Descriptif!M"&L$13)=$D30),INDIRECT("Descriptif!F"&L$13),"")} | ... T30: {=IF(AND(OR(INDIRECT("Descriptif!I"&S$13)=Recap_equipements!$B29,INDIRECT("Descriptif!I"&S$13)=Recap_equipements!$C29),INDIRECT("Descriptif!M"&S$13)=$D30),INDIRECT("Descriptif!F"&S$13),"")}
