Workbook
Name Asservissement: PARAM!$A$44:$A$46
Name CODE_SANDRE_3: PARAM!$I$4:$I$19
Name CODE_SANDRE_SCL: PARAM!$F$4:$F$7
Name CODE_SANDRE_STEU: PARAM!$E$4:$E$19
Name conditions_meteo: PARAM!$F$44:$F$46
Name Conformité: PARAM!$B$44:$B$48
Name Eq_h_controle: PARAM!$C$30:$C$32
Name EQUIPEMENT_PREL: PARAM!$B$4:$B$6
Name EQUIPEMENT_Q: PARAM!$A$4:$A$15
Name Frequence: PARAM!$E$44:$E$51
Name LISTE_1: PARAM!$A$21:$A$22
Name LISTE_1_a: #REF!
Name LISTE_2: PARAM!$B$21:$B$23
Name LISTE_3: PARAM!$C$21:$C$24
Name LISTE_4: PARAM!$D$21:$D$26
Name LISTE_5: PARAM!$F$21:$F$24
Name LISTE_6: PARAM!$G$21:$G$23
Name LISTE_7: PARAM!$H$21:$H$23
Name listeDebimetres: INDIRECT("Descriptif!"&ADDRESS(Descriptif!$AD$2,COLUMN(Descriptif!$AF$1))):INDEX(INDIRECT("Descriptif!AF"&Descriptif!$AD$2&":AF101"),COUNTIF(INDIRECT("Descriptif!AF"&Descriptif!$AD$2&":AF101"),"?*"))
Name listePluviometres: INDIRECT("Descriptif!"&ADDRESS(Descriptif!$AD$2,COLUMN(Descriptif!$AJ$1))):INDEX(INDIRECT("Descriptif!AJ"&Descriptif!$AD$2&":AJ101"),COUNTIF(INDIRECT("Descriptif!AJ"&Descriptif!$AD$2&":AJ101"),"?*"))
Name listePreleveurs: INDIRECT("Descriptif!"&ADDRESS(Descriptif!$AD$2,COLUMN(Descriptif!$AD$1))):INDEX(INDIRECT("Descriptif!AD"&Descriptif!$AD$2&":AD101"),COUNTIF(INDIRECT("Descriptif!AD"&Descriptif!$AD$2&":AD101"),"?*"))
Name listeSondeTemp: INDIRECT("Descriptif!"&ADDRESS(Descriptif!$AD$2,COLUMN(Descriptif!$AH$1))):INDEX(INDIRECT("Descriptif!AH"&Descriptif!$AD$2&":AH101"),COUNTIF(INDIRECT("Descriptif!AH"&Descriptif!$AD$2&":AH101"),"?*"))
Name Méthode: PARAM!$A$55:$A$57
Name Montage_sonde: PARAM!$G$44:$G$47
Name PLUVIO_SCL: Descriptif!$E$24:$E$24
Name Print_Area: LimitequantificationSDE!$A$1:$F$21
Name Print_Area: 'SeuilsComparaison-EMT'!$A$1:$K$29
Name Q_en_charge: PARAM!$A$30:$A$36
Name Q_Gravitaire: PARAM!$B$30:$B$39
Name Satisfaction: PARAM!$D$44:$D$46
Name Type_capteur: PARAM!$C$44:$C$48
Name Type_equipement: PARAM!$C$4:$C$7
Name Type_reseau: PARAM!$D$30:$D$32
Name TypeDeMesure: PARAM!$B$55:$B$56

Sheet Descriptif
AC1: Ne rien mettre dans cette colonne | AD1: Ne rien mettre dans cette colonne | AE1: Ne rien mettre dans cette colonne | AF1: Ne rien mettre dans cette colonne | AG1: Ne rien mettre dans cette colonne | AH1: Ne rien mettre dans cette colonne | AI1: Ne rien mettre dans cette colonne | AJ1: Ne rien mettre dans cette colonne
C2: CONTRÔLE ANNUEL DES DISPOSITIFS D'AUTOSURVEILLANCE DES SYSTÈMES D'ASSAINISSEMENT COLLECTIF | AC2: début données sys collect | AD2: =ROW(E13)+1 -> 14 | AE2: fin données sys collect | AF2: =ROW(D15)-1 -> 14 | AG2: pluvio SCL | AH2: =ROW(E22)+1 -> 23 | AI2: =ROW(D24)-1 -> 23
C3: NOM DU SYSTÈME D'ASSAINISSEMENT : | F3: BARJAC (30) | I3: NOM SYSTÈME DE TRAITEMENT : | L3: BARJAC (30) | N3: NOM SYSTÈME DE COLLECTE : | Q3: sys | S3: ORGANISME DE CONTRÔLE : | U3: CEREG Ingénierie | AC3: début données station | AD3: =ROW(E33)+1 -> 34 | AE3: fin données station | AF3: =ROW(D35)-1 -> 34 | AG3: pluvio STEU | AH3: =ROW(E42)+1 -> 43 | AI3: =ROW(D44)-1 -> 43
C4: CODE SANDRE DE L'AGGLOMERATION : | F4: eee | I4: CODE SANDRE DE LA STATION : | L4: 060930290002 | N4: CODE SANDRE DU RESEAU : | Q4: yyy | S4: NOM(S) CONTROLEUR(S) : | U4: control
C5: NOM DU MAITRE D'OUVRAGE : | F5: Commune de Barjac | I5: TYPE DE TRAITEMENT : | L5: Boues activée faible charge | N5: TYPE DE RESEAU | Q5: Mixte | S5: DATE(S) D'INTERVENTION : | U5: 46006
C6: EXPLOITANT DE LA STATION : | F6: Regie | I6: CAPACITE DE LA STATION : | L6: 5 000 EH | N6: EXPLOITANT DU RESEAU : | Q6: exp r | S6: CONDITION(S) METEO : | U6: pluie
C8: SYSTÈME DE COLLECTE
D10: Liste des équipements du système de collecte pour chaque point d’autosurveillance
H12: Les informations de codification sont à reprendre du MAS
E13: Actif | F13: Lien vers l'onglet de l'équipement | H13: Point réglementaire | I13: Localisation (cf. MAS) | J13: Code du point (cf MAS) | K13: Libellé de l'équipement | M13: Type d'équipement | O13: Type de matériel | Q13: Pluviométre de référence* | S13: Certaines informations d'un équipement ne sont pas modifiables. Au besoin il est préférable de supprimer et de recréer l'équipement. | AC13: Liste préleveurs | AE13: Liste débimètres | AG13: Liste thermo | AI13: Liste pluvio
AB14: =ROW(A14)- $AD$2 +1 -> 1 | AC14: =IF(AND($E14="Oui",$M14="Préleveur"),$F14,"") | AD14: {=IFERROR(INDEX($AC$14:$AC$102,SMALL(IF($AC$14:$AC$102<>"",ROW($AC$14:$AC$102)-ROW(INDIRECT("$AC$14"))+1),ROW(INDIRECT("A" & AB14 ) ))),"")} | AE14: =IF(AND($E14="Oui",LEFT($M14,10) ="Débitmètre"),$F14,"") | AF14: {=IFERROR(INDEX($AE$14:$AE$102,SMALL(IF($AE$14:$AE$102<>"",ROW($AE$14:$AE$102)-ROW(INDIRECT("$AE$14"))+1),ROW(INDIRECT("A" & AB14 ) ))),"")} | AG14: =IF(AND($E14="Oui",LEFT($M14,5) ="Sonde"),$F14,"") | AH14: {=IFERROR(INDEX($AG$14:$AG$102,SMALL(IF($AG$14:$AG$102<>"",ROW($AG$14:$AG$102)-ROW(INDIRECT("$AG$14"))+1),ROW(INDIRECT("A" & AB14 ) ))),"")} | AI14: =IF(AND($E14="Oui", $F14 <> "", $M14 = ""),$F14,"") | AJ14: {=IFERROR(INDEX($AI$14:$AI$102,SMALL(IF($AI$14:$AI$102<>"",ROW($AI$14:$AI$102)-ROW(INDIRECT("$AI$14"))+1),ROW(INDIRECT("A" & AB14 ) ))),"")}
E15: Ajouter un équipement réseau | K15: Si certains points A1 sont non équipés, veuillez les indiquer en commentaire | AB15: =ROW(A15)- $AD$2 +1 -> 2 | AC15: =IF(AND($E15="Oui",$M15="Préleveur"),$F15,"") | AD15: {=IFERROR(INDEX($AC$14:$AC$102,SMALL(IF($AC$14:$AC$102<>"",ROW($AC$14:$AC$102)-ROW(INDIRECT("$AC$14"))+1),ROW(INDIRECT("A" & AB15 ) ))),"")} | AE15: =IF(AND($E15="Oui",LEFT($M15,10) ="Débitmètre"),$F15,"") | AF15: {=IFERROR(INDEX($AE$14:$AE$102,SMALL(IF($AE$14:$AE$102<>"",ROW($AE$14:$AE$102)-ROW(INDIRECT("$AE$14"))+1),ROW(INDIRECT("A" & AB15 ) ))),"")} | AG15: =IF(AND($E15="Oui",LEFT($M15,5) ="Sonde"),$F15,"") | AH15: {=IFERROR(INDEX($AG$14:$AG$102,SMALL(IF($AG$14:$AG$102<>"",ROW($AG$14:$AG$102)-ROW(INDIRECT("$AG$14"))+1),ROW(INDIRECT("A" & AB15 ) ))),"")} | AI15: =IF(AND($E15="Oui", $F15 <> "", $M15 = ""),$F15,"") | AJ15: {=IFERROR(INDEX($AI$14:$AI$102,SMALL(IF($AI$14:$AI$102<>"",ROW($AI$14:$AI$102)-ROW(INDIRECT("$AI$14"))+1),ROW(INDIRECT("A" & AB15 ) ))),"")}
AB16: =ROW(A16)- $AD$2 +1 -> 3 | AC16: =IF(AND($E16="Oui",$M16="Préleveur"),$F16,"") | AD16: {=IFERROR(INDEX($AC$14:$AC$102,SMALL(IF($AC$14:$AC$102<>"",ROW($AC$14:$AC$102)-ROW(INDIRECT("$AC$14"))+1),ROW(INDIRECT("A" & AB16 ) ))),"")} | AE16: =IF(AND($E16="Oui",LEFT($M16,10) ="Débitmètre"),$F16,"") | AF16: {=IFERROR(INDEX($AE$14:$AE$102,SMALL(IF($AE$14:$AE$102<>"",ROW($AE$14:$AE$102)-ROW(INDIRECT("$AE$14"))+1),ROW(INDIRECT("A" & AB16 ) ))),"")} | AG16: =IF(AND($E16="Oui",LEFT($M16,5) ="Sonde"),$F16,"") | AH16: {=IFERROR(INDEX($AG$14:$AG$102,SMALL(IF($AG$14:$AG$102<>"",ROW($AG$14:$AG$102)-ROW(INDIRECT("$AG$14"))+1),ROW(INDIRECT("A" & AB16 ) ))),"")} | AI16: =IF(AND($E16="Oui", $F16 <> "", $M16 = ""),$F16,"") | AJ16: {=IFERROR(INDEX($AI$14:$AI$102,SMALL(IF($AI$14:$AI$102<>"",ROW($AI$14:$AI$102)-ROW(INDIRECT("$AI$14"))+1),ROW(INDIRECT("A" & AB16 ) ))),"")}
AB17: =ROW(A17)- $AD$2 +1 -> 4 | AC17: =IF(AND($E17="Oui",$M17="Préleveur"),$F17,"") | AD17: {=IFERROR(INDEX($AC$14:$AC$102,SMALL(IF($AC$14:$AC$102<>"",ROW($AC$14:$AC$102)-ROW(INDIRECT("$AC$14"))+1),ROW(INDIRECT("A" & AB17 ) ))),"")} | AE17: =IF(AND($E17="Oui",LEFT($M17,10) ="Débitmètre"),$F17,"") | AF17: {=IFERROR(INDEX($AE$14:$AE$102,SMALL(IF($AE$14:$AE$102<>"",ROW($AE$14:$AE$102)-ROW(INDIRECT("$AE$14"))+1),ROW(INDIRECT("A" & AB17 ) ))),"")} | AG17: =IF(AND($E17="Oui",LEFT($M17,5) ="Sonde"),$F17,"") | AH17: {=IFERROR(INDEX($AG$14:$AG$102,SMALL(IF($AG$14:$AG$102<>"",ROW($AG$14:$AG$102)-ROW(INDIRECT("$AG$14"))+1),ROW(INDIRECT("A" & AB17 ) ))),"")} | AI17: =IF(AND($E17="Oui", $F17 <> "", $M17 = ""),$F17,"") | AJ17: {=IFERROR(INDEX($AI$14:$AI$102,SMALL(IF($AI$14:$AI$102<>"",ROW($AI$14:$AI$102)-ROW(INDIRECT("$AI$14"))+1),ROW(INDIRECT("A" & AB17 ) ))),"")}
AB18: =ROW(A18)- $AD$2 +1 -> 5 | AC18: =IF(AND($E18="Oui",$M18="Préleveur"),$F18,"") | AD18: {=IFERROR(INDEX($AC$14:$AC$102,SMALL(IF($AC$14:$AC$102<>"",ROW($AC$14:$AC$102)-ROW(INDIRECT("$AC$14"))+1),ROW(INDIRECT("A" & AB18 ) ))),"")} | AE18: =IF(AND($E18="Oui",LEFT($M18,10) ="Débitmètre"),$F18,"") | AF18: {=IFERROR(INDEX($AE$14:$AE$102,SMALL(IF($AE$14:$AE$102<>"",ROW($AE$14:$AE$102)-ROW(INDIRECT("$AE$14"))+1),ROW(INDIRECT("A" & AB18 ) ))),"")} | AG18: =IF(AND($E18="Oui",LEFT($M18,5) ="Sonde"),$F18,"") | AH18: {=IFERROR(INDEX($AG$14:$AG$102,SMALL(IF($AG$14:$AG$102<>"",ROW($AG$14:$AG$102)-ROW(INDIRECT("$AG$14"))+1),ROW(INDIRECT("A" & AB18 ) ))),"")} | AI18: =IF(AND($E18="Oui", $F18 <> "", $M18 = ""),$F18,"") | AJ18: {=IFERROR(INDEX($AI$14:$AI$102,SMALL(IF($AI$14:$AI$102<>"",ROW($AI$14:$AI$102)-ROW(INDIRECT("$AI$14"))+1),ROW(INDIRECT("A" & AB18 ) ))),"")}
AB19: =ROW(A19)- $AD$2 +1 -> 6 | AC19: =IF(AND($E19="Oui",$M19="Préleveur"),$F19,"") | AD19: {=IFERROR(INDEX($AC$14:$AC$102,SMALL(IF($AC$14:$AC$102<>"",ROW($AC$14:$AC$102)-ROW(INDIRECT("$AC$14"))+1),ROW(INDIRECT("A" & AB19 ) ))),"")} | AE19: =IF(AND($E19="Oui",LEFT($M19,10) ="Débitmètre"),$F19,"") | AF19: {=IFERROR(INDEX($AE$14:$AE$102,SMALL(IF($AE$14:$AE$102<>"",ROW($AE$14:$AE$102)-ROW(INDIRECT("$AE$14"))+1),ROW(INDIRECT("A" & AB19 ) ))),"")} | AG19: =IF(AND($E19="Oui",LEFT($M19,5) ="Sonde"),$F19,"") | AH19: {=IFERROR(INDEX($AG$14:$AG$102,SMALL(IF($AG$14:$AG$102<>"",ROW($AG$14:$AG$102)-ROW(INDIRECT("$AG$14"))+1),ROW(INDIRECT("A" & AB19 ) ))),"")} | AI19: =IF(AND($E19="Oui", $F19 <> "", $M19 = ""),$F19,"") | AJ19: {=IFERROR(INDEX($AI$14:$AI$102,SMALL(IF($AI$14:$AI$102<>"",ROW($AI$14:$AI$102)-ROW(INDIRECT("$AI$14"))+1),ROW(INDIRECT("A" & AB19 ) ))),"")}
D20: Liste des pluviomètres de référence du réseau | AB20: =ROW(A20)- $AD$2 +1 -> 7 | AC20: =IF(AND($E20="Oui",$M20="Préleveur"),$F20,"") | AD20: {=IFERROR(INDEX($AC$14:$AC$102,SMALL(IF($AC$14:$AC$102<>"",ROW($AC$14:$AC$102)-ROW(INDIRECT("$AC$14"))+1),ROW(INDIRECT("A" & AB20 ) ))),"")} | AE20: =IF(AND($E20="Oui",LEFT($M20,10) ="Débitmètre"),$F20,"") | AF20: {=IFERROR(INDEX($AE$14:$AE$102,SMALL(IF($AE$14:$AE$102<>"",ROW($AE$14:$AE$102)-ROW(INDIRECT("$AE$14"))+1),ROW(INDIRECT("A" & AB20 ) ))),"")} | AG20: =IF(AND($E20="Oui",LEFT($M20,5) ="Sonde"),$F20,"") | AH20: {=IFERROR(INDEX($AG$14:$AG$102,SMALL(IF($AG$14:$AG$102<>"",ROW($AG$14:$AG$102)-ROW(INDIRECT("$AG$14"))+1),ROW(INDIRECT("A" & AB20 ) ))),"")} | AI20: =IF(AND($E20="Oui", $F20 <> "", $M20 = ""),$F20,"") | AJ20: {=IFERROR(INDEX($AI$14:$AI$102,SMALL(IF($AI$14:$AI$102<>"",ROW($AI$14:$AI$102)-ROW(INDIRECT("$AI$14"))+1),ROW(INDIRECT("A" & AB20 ) ))),"")}
AB21: =ROW(A21)- $AD$2 +1 -> 8 | AC21: =IF(AND($E21="Oui",$M21="Préleveur"),$F21,"") | AD21: {=IFERROR(INDEX($AC$14:$AC$102,SMALL(IF($AC$14:$AC$102<>"",ROW($AC$14:$AC$102)-ROW(INDIRECT("$AC$14"))+1),ROW(INDIRECT("A" & AB21 ) ))),"")} | AE21: =IF(AND($E21="Oui",LEFT($M21,10) ="Débitmètre"),$F21,"") | AF21: {=IFERROR(INDEX($AE$14:$AE$102,SMALL(IF($AE$14:$AE$102<>"",ROW($AE$14:$AE$102)-ROW(INDIRECT("$AE$14"))+1),ROW(INDIRECT("A" & AB21 ) ))),"")} | AG21: =IF(AND($E21="Oui",LEFT($M21,5) ="Sonde"),$F21,"") | AH21: {=IFERROR(INDEX($AG$14:$AG$102,SMALL(IF($AG$14:$AG$102<>"",ROW($AG$14:$AG$102)-ROW(INDIRECT("$AG$14"))+1),ROW(INDIRECT("A" & AB21 ) ))),"")} | AI21: =IF(AND($E21="Oui", $F21 <> "", $M21 = ""),$F21,"") | AJ21: {=IFERROR(INDEX($AI$14:$AI$102,SMALL(IF($AI$14:$AI$102<>"",ROW($AI$14:$AI$102)-ROW(INDIRECT("$AI$14"))+1),ROW(INDIRECT("A" & AB21 ) ))),"")}
E22: Actif | F22: Lien vers l'onglet de l'équipement | AB22: =ROW(A22)- $AD$2 +1 -> 9 | AC22: =IF(AND($E22="Oui",$M22="Préleveur"),$F22,"") | AD22: {=IFERROR(INDEX($AC$14:$AC$102,SMALL(IF($AC$14:$AC$102<>"",ROW($AC$14:$AC$102)-ROW(INDIRECT("$AC$14"))+1),ROW(INDIRECT("A" & AB22 ) ))),"")} | AE22: =IF(AND($E22="Oui",LEFT($M22,10) ="Débitmètre"),$F22,"") | AF22: {=IFERROR(INDEX($AE$14:$AE$102,SMALL(IF($AE$14:$AE$102<>"",ROW($AE$14:$AE$102)-ROW(INDIRECT("$AE$14"))+1),ROW(INDIRECT("A" & AB22 ) ))),"")} | AG22: =IF(AND($E22="Oui",LEFT($M22,5) ="Sonde"),$F22,"") | AH22: {=IFERROR(INDEX($AG$14:$AG$102,SMALL(IF($AG$14:$AG$102<>"",ROW($AG$14:$AG$102)-ROW(INDIRECT("$AG$14"))+1),ROW(INDIRECT("A" & AB22 ) ))),"")} | AI22: =IF(AND($E22="Oui", $F22 <> "", $M22 = ""),$F22,"") | AJ22: {=IFERROR(INDEX($AI$14:$AI$102,SMALL(IF($AI$14:$AI$102<>"",ROW($AI$14:$AI$102)-ROW(INDIRECT("$AI$14"))+1),ROW(INDIRECT("A" & AB22 ) ))),"")}
AB23: =ROW(A23)- $AD$2 +1 -> 10 | AC23: =IF(AND($E23="Oui",$M23="Préleveur"),$F23,"") | AD23: {=IFERROR(INDEX($AC$14:$AC$102,SMALL(IF($AC$14:$AC$102<>"",ROW($AC$14:$AC$102)-ROW(INDIRECT("$AC$14"))+1),ROW(INDIRECT("A" & AB23 ) ))),"")} | AE23: =IF(AND($E23="Oui",LEFT($M23,10) ="Débitmètre"),$F23,"") | AF23: {=IFERROR(INDEX($AE$14:$AE$102,SMALL(IF($AE$14:$AE$102<>"",ROW($AE$14:$AE$102)-ROW(INDIRECT("$AE$14"))+1),ROW(INDIRECT("A" & AB23 ) ))),"")} | AG23: =IF(AND($E23="Oui",LEFT($M23,5) ="Sonde"),$F23,"") | AH23: {=IFERROR(INDEX($AG$14:$AG$102,SMALL(IF($AG$14:$AG$102<>"",ROW($AG$14:$AG$102)-ROW(INDIRECT("$AG$14"))+1),ROW(INDIRECT("A" & AB23 ) ))),"")} | AI23: =IF(AND($E23="Oui", $F23 <> "", $M23 = ""),$F23,"") | AJ23: {=IFERROR(INDEX($AI$14:$AI$102,SMALL(IF($AI$14:$AI$102<>"",ROW($AI$14:$AI$102)-ROW(INDIRECT("$AI$14"))+1),ROW(INDIRECT("A" & AB23 ) ))),"")}
E24: Ajouter un pluviomètre réseau | K24: Si pas de pluviomètre, veuillez ajouter en commentaire la provenance des données : | AB24: =ROW(A24)- $AD$2 +1 -> 11 | AC24: =IF(AND($E24="Oui",$M24="Préleveur"),$F24,"") | AD24: {=IFERROR(INDEX($AC$14:$AC$102,SMALL(IF($AC$14:$AC$102<>"",ROW($AC$14:$AC$102)-ROW(INDIRECT("$AC$14"))+1),ROW(INDIRECT("A" & AB24 ) ))),"")} | AE24: =IF(AND($E24="Oui",LEFT($M24,10) ="Débitmètre"),$F24,"") | AF24: {=IFERROR(INDEX($AE$14:$AE$102,SMALL(IF($AE$14:$AE$102<>"",ROW($AE$14:$AE$102)-ROW(INDIRECT("$AE$14"))+1),ROW(INDIRECT("A" & AB24 ) ))),"")} | AG24: =IF(AND($E24="Oui",LEFT($M24,5) ="Sonde"),$F24,"") | AH24: {=IFERROR(INDEX($AG$14:$AG$102,SMALL(IF($AG$14:$AG$102<>"",ROW($AG$14:$AG$102)-ROW(INDIRECT("$AG$14"))+1),ROW(INDIRECT("A" & AB24 ) ))),"")} | AI24: =IF(AND($E24="Oui", $F24 <> "", $M24 = ""),$F24,"") | AJ24: {=IFERROR(INDEX($AI$14:$AI$102,SMALL(IF($AI$14:$AI$102<>"",ROW($AI$14:$AI$102)-ROW(INDIRECT("$AI$14"))+1),ROW(INDIRECT("A" & AB24 ) ))),"")}
AB25: =ROW(A25)- $AD$2 +1 -> 12 | AC25: =IF(AND($E25="Oui",$M25="Préleveur"),$F25,"") | AD25: {=IFERROR(INDEX($AC$14:$AC$102,SMALL(IF($AC$14:$AC$102<>"",ROW($AC$14:$AC$102)-ROW(INDIRECT("$AC$14"))+1),ROW(INDIRECT("A" & AB25 ) ))),"")} | AE25: =IF(AND($E25="Oui",LEFT($M25,10) ="Débitmètre"),$F25,"") | AF25: {=IFERROR(INDEX($AE$14:$AE$102,SMALL(IF($AE$14:$AE$102<>"",ROW($AE$14:$AE$102)-ROW(INDIRECT("$AE$14"))+1),ROW(INDIRECT("A" & AB25 ) ))),"")} | AG25: =IF(AND($E25="Oui",LEFT($M25,5) ="Sonde"),$F25,"") | AH25: {=IFERROR(INDEX($AG$14:$AG$102,SMALL(IF($AG$14:$AG$102<>"",ROW($AG$14:$AG$102)-ROW(INDIRECT("$AG$14"))+1),ROW(INDIRECT("A" & AB25 ) ))),"")} | AI25: =IF(AND($E25="Oui", $F25 <> "", $M25 = ""),$F25,"") | AJ25: {=IFERROR(INDEX($AI$14:$AI$102,SMALL(IF($AI$14:$AI$102<>"",ROW($AI$14:$AI$102)-ROW(INDIRECT("$AI$14"))+1),ROW(INDIRECT("A" & AB25 ) ))),"")}
AB26: =ROW(A26)- $AD$2 +1 -> 13 | AC26: =IF(AND($E26="Oui",$M26="Préleveur"),$F26,"") | AD26: {=IFERROR(INDEX($AC$14:$AC$102,SMALL(IF($AC$14:$AC$102<>"",ROW($AC$14:$AC$102)-ROW(INDIRECT("$AC$14"))+1),ROW(INDIRECT("A" & AB26 ) ))),"")} | AE26: =IF(AND($E26="Oui",LEFT($M26,10) ="Débitmètre"),$F26,"") | AF26: {=IFERROR(INDEX($AE$14:$AE$102,SMALL(IF($AE$14:$AE$102<>"",ROW($AE$14:$AE$102)-ROW(INDIRECT("$AE$14"))+1),ROW(INDIRECT("A" & AB26 ) ))),"")} | AG26: =IF(AND($E26="Oui",LEFT($M26,5) ="Sonde"),$F26,"") | AH26: {=IFERROR(INDEX($AG$14:$AG$102,SMALL(IF($AG$14:$AG$102<>"",ROW($AG$14:$AG$102)-ROW(INDIRECT("$AG$14"))+1),ROW(INDIRECT("A" & AB26 ) ))),"")} | AI26: =IF(AND($E26="Oui", $F26 <> "", $M26 = ""),$F26,"") | AJ26: {=IFERROR(INDEX($AI$14:$AI$102,SMALL(IF($AI$14:$AI$102<>"",ROW($AI$14:$AI$102)-ROW(INDIRECT("$AI$14"))+1),ROW(INDIRECT("A" & AB26 ) ))),"")}
AB27: =ROW(A27)- $AD$2 +1 -> 14 | AC27: =IF(AND($E27="Oui",$M27="Préleveur"),$F27,"") | AD27: {=IFERROR(INDEX($AC$14:$AC$102,SMALL(IF($AC$14:$AC$102<>"",ROW($AC$14:$AC$102)-ROW(INDIRECT("$AC$14"))+1),ROW(INDIRECT("A" & AB27 ) ))),"")} | AE27: =IF(AND($E27="Oui",LEFT($M27,10) ="Débitmètre"),$F27,"") | AF27: {=IFERROR(INDEX($AE$14:$AE$102,SMALL(IF($AE$14:$AE$102<>"",ROW($AE$14:$AE$102)-ROW(INDIRECT("$AE$14"))+1),ROW(INDIRECT("A" & AB27 ) ))),"")} | AG27: =IF(AND($E27="Oui",LEFT($M27,5) ="Sonde"),$F27,"") | AH27: {=IFERROR(INDEX($AG$14:$AG$102,SMALL(IF($AG$14:$AG$102<>"",ROW($AG$14:$AG$102)-ROW(INDIRECT("$AG$14"))+1),ROW(INDIRECT("A" & AB27 ) ))),"")} | AI27: =IF(AND($E27="Oui", $F27 <> "", $M27 = ""),$F27,"") | AJ27: {=IFERROR(INDEX($AI$14:$AI$102,SMALL(IF($AI$14:$AI$102<>"",ROW($AI$14:$AI$102)-ROW(INDIRECT("$AI$14"))+1),ROW(INDIRECT("A" & AB27 ) ))),"")}
AB28: =ROW(A28)- $AD$2 +1 -> 15 | AC28: =IF(AND($E28="Oui",$M28="Préleveur"),$F28,"") | AD28: {=IFERROR(INDEX($AC$14:$AC$102,SMALL(IF($AC$14:$AC$102<>"",ROW($AC$14:$AC$102)-ROW(INDIRECT("$AC$14"))+1),ROW(INDIRECT("A" & AB28 ) ))),"")} | AE28: =IF(AND($E28="Oui",LEFT($M28,10) ="Débitmètre"),$F28,"") | AF28: {=IFERROR(INDEX($AE$14:$AE$102,SMALL(IF($AE$14:$AE$102<>"",ROW($AE$14:$AE$102)-ROW(INDIRECT("$AE$14"))+1),ROW(INDIRECT("A" & AB28 ) ))),"")} | AG28: =IF(AND($E28="Oui",LEFT($M28,5) ="Sonde"),$F28,"") | AH28: {=IFERROR(INDEX($AG$14:$AG$102,SMALL(IF($AG$14:$AG$102<>"",ROW($AG$14:$AG$102)-ROW(INDIRECT("$AG$14"))+1),ROW(INDIRECT("A" & AB28 ) ))),"")} | AI28: =IF(AND($E28="Oui", $F28 <> "", $M28 = ""),$F28,"") | AJ28: {=IFERROR(INDEX($AI$14:$AI$102,SMALL(IF($AI$14:$AI$102<>"",ROW($AI$14:$AI$102)-ROW(INDIRECT("$AI$14"))+1),ROW(INDIRECT("A" & AB28 ) ))),"")}
C29: SYSTÈME DE TRAITEMENT | AB29: =ROW(A29)- $AD$2 +1 -> 16 | AC29: =IF(AND($E29="Oui",$M29="Préleveur"),$F29,"") | AD29: {=IFERROR(INDEX($AC$14:$AC$102,SMALL(IF($AC$14:$AC$102<>"",ROW($AC$14:$AC$102)-ROW(INDIRECT("$AC$14"))+1),ROW(INDIRECT("A" & AB29 ) ))),"")} | AE29: =IF(AND($E29="Oui",LEFT($M29,10) ="Débitmètre"),$F29,"") | AF29: {=IFERROR(INDEX($AE$14:$AE$102,SMALL(IF($AE$14:$AE$102<>"",ROW($AE$14:$AE$102)-ROW(INDIRECT("$AE$14"))+1),ROW(INDIRECT("A" & AB29 ) ))),"")} | AG29: =IF(AND($E29="Oui",LEFT($M29,5) ="Sonde"),$F29,"") | AH29: {=IFERROR(INDEX($AG$14:$AG$102,SMALL(IF($AG$14:$AG$102<>"",ROW($AG$14:$AG$102)-ROW(INDIRECT("$AG$14"))+1),ROW(INDIRECT("A" & AB29 ) ))),"")} | AI29: =IF(AND($E29="Oui", $F29 <> "", $M29 = ""),$F29,"") | AJ29: {=IFERROR(INDEX($AI$14:$AI$102,SMALL(IF($AI$14:$AI$102<>"",ROW($AI$14:$AI$102)-ROW(INDIRECT("$AI$14"))+1),ROW(INDIRECT("A" & AB29 ) ))),"")}
AB30: =ROW(A30)- $AD$2 +1 -> 17 | AC30: =IF(AND($E30="Oui",$M30="Préleveur"),$F30,"") | AD30: {=IFERROR(INDEX($AC$14:$AC$102,SMALL(IF($AC$14:$AC$102<>"",ROW($AC$14:$AC$102)-ROW(INDIRECT("$AC$14"))+1),ROW(INDIRECT("A" & AB30 ) ))),"")} | AE30: =IF(AND($E30="Oui",LEFT($M30,10) ="Débitmètre"),$F30,"") | AF30: {=IFERROR(INDEX($AE$14:$AE$102,SMALL(IF($AE$14:$AE$102<>"",ROW($AE$14:$AE$102)-ROW(INDIRECT("$AE$14"))+1),ROW(INDIRECT("A" & AB30 ) ))),"")} | AG30: =IF(AND($E30="Oui",LEFT($M30,5) ="Sonde"),$F30,"") | AH30: {=IFERROR(INDEX($AG$14:$AG$102,SMALL(IF($AG$14:$AG$102<>"",ROW($AG$14:$AG$102)-ROW(INDIRECT("$AG$14"))+1),ROW(INDIRECT("A" & AB30 ) ))),"")} | AI30: =IF(AND($E30="Oui", $F30 <> "", $M30 = ""),$F30,"") | AJ30: {=IFERROR(INDEX($AI$14:$AI$102,SMALL(IF($AI$14:$AI$102<>"",ROW($AI$14:$AI$102)-ROW(INDIRECT("$AI$14"))+1),ROW(INDIRECT("A" & AB30 ) ))),"")}
D31: Liste des équipements du système de traitement pour chaque point d’autosurveillance | AB31: =ROW(A31)- $AD$2 +1 -> 18 | AC31: =IF(AND($E31="Oui",$M31="Préleveur"),$F31,"") | AD31: {=IFERROR(INDEX($AC$14:$AC$102,SMALL(IF($AC$14:$AC$102<>"",ROW($AC$14:$AC$102)-ROW(INDIRECT("$AC$14"))+1),ROW(INDIRECT("A" & AB31 ) ))),"")} | AE31: =IF(AND($E31="Oui",LEFT($M31,10) ="Débitmètre"),$F31,"") | AF31: {=IFERROR(INDEX($AE$14:$AE$102,SMALL(IF($AE$14:$AE$102<>"",ROW($AE$14:$AE$102)-ROW(INDIRECT("$AE$14"))+1),ROW(INDIRECT("A" & AB31 ) ))),"")} | AG31: =IF(AND($E31="Oui",LEFT($M31,5) ="Sonde"),$F31,"") | AH31: {=IFERROR(INDEX($AG$14:$AG$102,SMALL(IF($AG$14:$AG$102<>"",ROW($AG$14:$AG$102)-ROW(INDIRECT("$AG$14"))+1),ROW(INDIRECT("A" & AB31 ) ))),"")} | AI31: =IF(AND($E31="Oui", $F31 <> "", $M31 = ""),$F31,"") | AJ31: {=IFERROR(INDEX($AI$14:$AI$102,SMALL(IF($AI$14:$AI$102<>"",ROW($AI$14:$AI$102)-ROW(INDIRECT("$AI$14"))+1),ROW(INDIRECT("A" & AB31 ) ))),"")}
AB32: =ROW(A32)- $AD$2 +1 -> 19 | AC32: =IF(AND($E32="Oui",$M32="Préleveur"),$F32,"") | AD32: {=IFERROR(INDEX($AC$14:$AC$102,SMALL(IF($AC$14:$AC$102<>"",ROW($AC$14:$AC$102)-ROW(INDIRECT("$AC$14"))+1),ROW(INDIRECT("A" & AB32 ) ))),"")} | AE32: =IF(AND($E32="Oui",LEFT($M32,10) ="Débitmètre"),$F32,"") | AF32: {=IFERROR(INDEX($AE$14:$AE$102,SMALL(IF($AE$14:$AE$102<>"",ROW($AE$14:$AE$102)-ROW(INDIRECT("$AE$14"))+1),ROW(INDIRECT("A" & AB32 ) ))),"")} | AG32: =IF(AND($E32="Oui",LEFT($M32,5) ="Sonde"),$F32,"") | AH32: {=IFERROR(INDEX($AG$14:$AG$102,SMALL(IF($AG$14:$AG$102<>"",ROW($AG$14:$AG$102)-ROW(INDIRECT("$AG$14"))+1),ROW(INDIRECT("A" & AB32 ) ))),"")} | AI32: =IF(AND($E32="Oui", $F32 <> "", $M32 = ""),$F32,"") | AJ32: {=IFERROR(INDEX($AI$14:$AI$102,SMALL(IF($AI$14:$AI$102<>"",ROW($AI$14:$AI$102)-ROW(INDIRECT("$AI$14"))+1),ROW(INDIRECT("A" & AB32 ) ))),"")}
E33: Actif | F33: Lien vers l'onglet de l'équipement | H33: Point réglementaire | I33: Localisation (cf. MAS) | J33: Code du point (cf MAS) | K33: Libellé de l'équipement | M33: Type d'équipement | O33: Type de matériel | R33: Certaines informations d'un équipement ne sont pas modifiables. Au besoin il est préférable de supprimer et de recréer l'équipement. | AB33: =ROW(A33)- $AD$2 +1 -> 20 | AC33: =IF(AND($E33="Oui",$M33="Préleveur"),$F33,"") | AD33: {=IFERROR(INDEX($AC$14:$AC$102,SMALL(IF($AC$14:$AC$102<>"",ROW($AC$14:$AC$102)-ROW(INDIRECT("$AC$14"))+1),ROW(INDIRECT("A" & AB33 ) ))),"")} | AE33: =IF(AND($E33="Oui",LEFT($M33,10) ="Débitmètre"),$F33,"") | AF33: {=IFERROR(INDEX($AE$14:$AE$102,SMALL(IF($AE$14:$AE$102<>"",ROW($AE$14:$AE$102)-ROW(INDIRECT("$AE$14"))+1),ROW(INDIRECT("A" & AB33 ) ))),"")} | AG33: =IF(AND($E33="Oui",LEFT($M33,5) ="Sonde"),$F33,"") | AH33: {=IFERROR(INDEX($AG$14:$AG$102,SMALL(IF($AG$14:$AG$102<>"",ROW($AG$14:$AG$102)-ROW(INDIRECT("$AG$14"))+1),ROW(INDIRECT("A" & AB33 ) ))),"")} | AI33: =IF(AND($E33="Oui", $F33 <> "", $M33 = ""),$F33,"") | AJ33: {=IFERROR(INDEX($AI$14:$AI$102,SMALL(IF($AI$14:$AI$102<>"",ROW($AI$14:$AI$102)-ROW(INDIRECT("$AI$14"))+1),ROW(INDIRECT("A" & AB33 ) ))),"")}
AB34: =ROW(A34)- $AD$2 +1 -> 21 | AC34: =IF(AND($E34="Oui",$M34="Préleveur"),$F34,"") | AD34: {=IFERROR(INDEX($AC$14:$AC$102,SMALL(IF($AC$14:$AC$102<>"",ROW($AC$14:$AC$102)-ROW(INDIRECT("$AC$14"))+1),ROW(INDIRECT("A" & AB34 ) ))),"")} | AE34: =IF(AND($E34="Oui",LEFT($M34,10) ="Débitmètre"),$F34,"") | AF34: {=IFERROR(INDEX($AE$14:$AE$102,SMALL(IF($AE$14:$AE$102<>"",ROW($AE$14:$AE$102)-ROW(INDIRECT("$AE$14"))+1),ROW(INDIRECT("A" & AB34 ) ))),"")} | AG34: =IF(AND($E34="Oui",LEFT($M34,5) ="Sonde"),$F34,"") | AH34: {=IFERROR(INDEX($AG$14:$AG$102,SMALL(IF($AG$14:$AG$102<>"",ROW($AG$14:$AG$102)-ROW(INDIRECT("$AG$14"))+1),ROW(INDIRECT("A" & AB34 ) ))),"")} | AI34: =IF(AND($E34="Oui", $F34 <> "", $M34 = ""),$F34,"") | AJ34: {=IFERROR(INDEX($AI$14:$AI$102,SMALL(IF($AI$14:$AI$102<>"",ROW($AI$14:$AI$102)-ROW(INDIRECT("$AI$14"))+1),ROW(INDIRECT("A" & AB34 ) ))),"")}
E35: Ajouter un équipement station | K35: Si certains points A1 sont non équipés, veuillez les indiquer en commentaire | AB35: =ROW(A35)- $AD$2 +1 -> 22 | AC35: =IF(AND($E35="Oui",$M35="Préleveur"),$F35,"") | AD35: {=IFERROR(INDEX($AC$14:$AC$102,SMALL(IF($AC$14:$AC$102<>"",ROW($AC$14:$AC$102)-ROW(INDIRECT("$AC$14"))+1),ROW(INDIRECT("A" & AB35 ) ))),"")} | AE35: =IF(AND($E35="Oui",LEFT($M35,10) ="Débitmètre"),$F35,"") | AF35: {=IFERROR(INDEX($AE$14:$AE$102,SMALL(IF($AE$14:$AE$102<>"",ROW($AE$14:$AE$102)-ROW(INDIRECT("$AE$14"))+1),ROW(INDIRECT("A" & AB35 ) ))),"")} | AG35: =IF(AND($E35="Oui",LEFT($M35,5) ="Sonde"),$F35,"") | AH35: {=IFERROR(INDEX($AG$14:$AG$102,SMALL(IF($AG$14:$AG$102<>"",ROW($AG$14:$AG$102)-ROW(INDIRECT("$AG$14"))+1),ROW(INDIRECT("A" & AB35 ) ))),"")} | AI35: =IF(AND($E35="Oui", $F35 <> "", $M35 = ""),$F35,"") | AJ35: {=IFERROR(INDEX($AI$14:$AI$102,SMALL(IF($AI$14:$AI$102<>"",ROW($AI$14:$AI$102)-ROW(INDIRECT("$AI$14"))+1),ROW(INDIRECT("A" & AB35 ) ))),"")}
AB36: =ROW(A36)- $AD$2 +1 -> 23 | AC36: =IF(AND($E36="Oui",$M36="Préleveur"),$F36,"") | AD36: {=IFERROR(INDEX($AC$14:$AC$102,SMALL(IF($AC$14:$AC$102<>"",ROW($AC$14:$AC$102)-ROW(INDIRECT("$AC$14"))+1),ROW(INDIRECT("A" & AB36 ) ))),"")} | AE36: =IF(AND($E36="Oui",LEFT($M36,10) ="Débitmètre"),$F36,"") | AF36: {=IFERROR(INDEX($AE$14:$AE$102,SMALL(IF($AE$14:$AE$102<>"",ROW($AE$14:$AE$102)-ROW(INDIRECT("$AE$14"))+1),ROW(INDIRECT("A" & AB36 ) ))),"")} | AG36: =IF(AND($E36="Oui",LEFT($M36,5) ="Sonde"),$F36,"") | AH36: {=IFERROR(INDEX($AG$14:$AG$102,SMALL(IF($AG$14:$AG$102<>"",ROW($AG$14:$AG$102)-ROW(INDIRECT("$AG$14"))+1),ROW(INDIRECT("A" & AB36 ) ))),"")} | AI36: =IF(AND($E36="Oui", $F36 <> "", $M36 = ""),$F36,"") | AJ36: {=IFERROR(INDEX($AI$14:$AI$102,SMALL(IF($AI$14:$AI$102<>"",ROW($AI$14:$AI$102)-ROW(INDIRECT("$AI$14"))+1),ROW(INDIRECT("A" & AB36 ) ))),"")}
AB37: =ROW(A37)- $AD$2 +1 -> 24 | AC37: =IF(AND($E37="Oui",$M37="Préleveur"),$F37,"") | AD37: {=IFERROR(INDEX($AC$14:$AC$102,SMALL(IF($AC$14:$AC$102<>"",ROW($AC$14:$AC$102)-ROW(INDIRECT("$AC$14"))+1),ROW(INDIRECT("A" & AB37 ) ))),"")} | AE37: =IF(AND($E37="Oui",LEFT($M37,10) ="Débitmètre"),$F37,"") | AF37: {=IFERROR(INDEX($AE$14:$AE$102,SMALL(IF($AE$14:$AE$102<>"",ROW($AE$14:$AE$102)-ROW(INDIRECT("$AE$14"))+1),ROW(INDIRECT("A" & AB37 ) ))),"")} | AG37: =IF(AND($E37="Oui",LEFT($M37,5) ="Sonde"),$F37,"") | AH37: {=IFERROR(INDEX($AG$14:$AG$102,SMALL(IF($AG$14:$AG$102<>"",ROW($AG$14:$AG$102)-ROW(INDIRECT("$AG$14"))+1),ROW(INDIRECT("A" & AB37 ) ))),"")} | AI37: =IF(AND($E37="Oui", $F37 <> "", $M37 = ""),$F37,"") | AJ37: {=IFERROR(INDEX($AI$14:$AI$102,SMALL(IF($AI$14:$AI$102<>"",ROW($AI$14:$AI$102)-ROW(INDIRECT("$AI$14"))+1),ROW(INDIRECT("A" & AB37 ) ))),"")}
AB38: =ROW(A38)- $AD$2 +1 -> 25 | AC38: =IF(AND($E38="Oui",$M38="Préleveur"),$F38,"") | AD38: {=IFERROR(INDEX($AC$14:$AC$102,SMALL(IF($AC$14:$AC$102<>"",ROW($AC$14:$AC$102)-ROW(INDIRECT("$AC$14"))+1),ROW(INDIRECT("A" & AB38 ) ))),"")} | AE38: =IF(AND($E38="Oui",LEFT($M38,10) ="Débitmètre"),$F38,"") | AF38: {=IFERROR(INDEX($AE$14:$AE$102,SMALL(IF($AE$14:$AE$102<>"",ROW($AE$14:$AE$102)-ROW(INDIRECT("$AE$14"))+1),ROW(INDIRECT("A" & AB38 ) ))),"")} | AG38: =IF(AND($E38="Oui",LEFT($M38,5) ="Sonde"),$F38,"") | AH38: {=IFERROR(INDEX($AG$14:$AG$102,SMALL(IF($AG$14:$AG$102<>"",ROW($AG$14:$AG$102)-ROW(INDIRECT("$AG$14"))+1),ROW(INDIRECT("A" & AB38 ) ))),"")} | AI38: =IF(AND($E38="Oui", $F38 <> "", $M38 = ""),$F38,"") | AJ38: {=IFERROR(INDEX($AI$14:$AI$102,SMALL(IF($AI$14:$AI$102<>"",ROW($AI$14:$AI$102)-ROW(INDIRECT("$AI$14"))+1),ROW(INDIRECT("A" & AB38 ) ))),"")}
AB39: =ROW(A39)- $AD$2 +1 -> 26 | AC39: =IF(AND($E39="Oui",$M39="Préleveur"),$F39,"") | AD39: {=IFERROR(INDEX($AC$14:$AC$102,SMALL(IF($AC$14:$AC$102<>"",ROW($AC$14:$AC$102)-ROW(INDIRECT("$AC$14"))+1),ROW(INDIRECT("A" & AB39 ) ))),"")} | AE39: =IF(AND($E39="Oui",LEFT($M39,10) ="Débitmètre"),$F39,"") | AF39: {=IFERROR(INDEX($AE$14:$AE$102,SMALL(IF($AE$14:$AE$102<>"",ROW($AE$14:$AE$102)-ROW(INDIRECT("$AE$14"))+1),ROW(INDIRECT("A" & AB39 ) ))),"")} | AG39: =IF(AND($E39="Oui",LEFT($M39,5) ="Sonde"),$F39,"") | AH39: {=IFERROR(INDEX($AG$14:$AG$102,SMALL(IF($AG$14:$AG$102<>"",ROW($AG$14:$AG$102)-ROW(INDIRECT("$AG$14"))+1),ROW(INDIRECT("A" & AB39 ) ))),"")} | AI39: =IF(AND($E39="Oui", $F39 <> "", $M39 = ""),$F39,"") | AJ39: {=IFERROR(INDEX($AI$14:$AI$102,SMALL(IF($AI$14:$AI$102<>"",ROW($AI$14:$AI$102)-ROW(INDIRECT("$AI$14"))+1),ROW(INDIRECT("A" & AB39 ) ))),"")}
D40: Liste des pluviomètres de référence de la station | AB40: =ROW(A40)- $AD$2 +1 -> 27 | AC40: =IF(AND($E40="Oui",$M40="Préleveur"),$F40,"") | AD40: {=IFERROR(INDEX($AC$14:$AC$102,SMALL(IF($AC$14:$AC$102<>"",ROW($AC$14:$AC$102)-ROW(INDIRECT("$AC$14"))+1),ROW(INDIRECT("A" & AB40 ) ))),"")} | AE40: =IF(AND($E40="Oui",LEFT($M40,10) ="Débitmètre"),$F40,"") | AF40: {=IFERROR(INDEX($AE$14:$AE$102,SMALL(IF($AE$14:$AE$102<>"",ROW($AE$14:$AE$102)-ROW(INDIRECT("$AE$14"))+1),ROW(INDIRECT("A" & AB40 ) ))),"")} | AG40: =IF(AND($E40="Oui",LEFT($M40,5) ="Sonde"),$F40,"") | AH40: {=IFERROR(INDEX($AG$14:$AG$102,SMALL(IF($AG$14:$AG$102<>"",ROW($AG$14:$AG$102)-ROW(INDIRECT("$AG$14"))+1),ROW(INDIRECT("A" & AB40 ) ))),"")} | AI40: =IF(AND($E40="Oui", $F40 <> "", $M40 = ""),$F40,"") | AJ40: {=IFERROR(INDEX($AI$14:$AI$102,SMALL(IF($AI$14:$AI$102<>"",ROW($AI$14:$AI$102)-ROW(INDIRECT("$AI$14"))+1),ROW(INDIRECT("A" & AB40 ) ))),"")}
AB41: =ROW(A41)- $AD$2 +1 -> 28 | AC41: =IF(AND($E41="Oui",$M41="Préleveur"),$F41,"") | AD41: {=IFERROR(INDEX($AC$14:$AC$102,SMALL(IF($AC$14:$AC$102<>"",ROW($AC$14:$AC$102)-ROW(INDIRECT("$AC$14"))+1),ROW(INDIRECT("A" & AB41 ) ))),"")} | AE41: =IF(AND($E41="Oui",LEFT($M41,10) ="Débitmètre"),$F41,"") | AF41: {=IFERROR(INDEX($AE$14:$AE$102,SMALL(IF($AE$14:$AE$102<>"",ROW($AE$14:$AE$102)-ROW(INDIRECT("$AE$14"))+1),ROW(INDIRECT("A" & AB41 ) ))),"")} | AG41: =IF(AND($E41="Oui",LEFT($M41,5) ="Sonde"),$F41,"") | AH41: {=IFERROR(INDEX($AG$14:$AG$102,SMALL(IF($AG$14:$AG$102<>"",ROW($AG$14:$AG$102)-ROW(INDIRECT("$AG$14"))+1),ROW(INDIRECT("A" & AB41 ) ))),"")} | AI41: =IF(AND($E41="Oui", $F41 <> "", $M41 = ""),$F41,"") | AJ41: {=IFERROR(INDEX($AI$14:$AI$102,SMALL(IF($AI$14:$AI$102<>"",ROW($AI$14:$AI$102)-ROW(INDIRECT("$AI$14"))+1),ROW(INDIRECT("A" & AB41 ) ))),"")}
E42: Actif | F42: Lien vers l'onglet de l'équipement | AB42: =ROW(A42)- $AD$2 +1 -> 29 | AC42: =IF(AND($E42="Oui",$M42="Préleveur"),$F42,"") | AD42: {=IFERROR(INDEX($AC$14:$AC$102,SMALL(IF($AC$14:$AC$102<>"",ROW($AC$14:$AC$102)-ROW(INDIRECT("$AC$14"))+1),ROW(INDIRECT("A" & AB42 ) ))),"")} | AE42: =IF(AND($E42="Oui",LEFT($M42,10) ="Débitmètre"),$F42,"") | AF42: {=IFERROR(INDEX($AE$14:$AE$102,SMALL(IF($AE$14:$AE$102<>"",ROW($AE$14:$AE$102)-ROW(INDIRECT("$AE$14"))+1),ROW(INDIRECT("A" & AB42 ) ))),"")} | AG42: =IF(AND($E42="Oui",LEFT($M42,5) ="Sonde"),$F42,"") | AH42: {=IFERROR(INDEX($AG$14:$AG$102,SMALL(IF($AG$14:$AG$102<>"",ROW($AG$14:$AG$102)-ROW(INDIRECT("$AG$14"))+1),ROW(INDIRECT("A" & AB42 ) ))),"")} | AI42: =IF(AND($E42="Oui", $F42 <> "", $M42 = ""),$F42,"") | AJ42: {=IFERROR(INDEX($AI$14:$AI$102,SMALL(IF($AI$14:$AI$102<>"",ROW($AI$14:$AI$102)-ROW(INDIRECT("$AI$14"))+1),ROW(INDIRECT("A" & AB42 ) ))),"")}
AB43: =ROW(A43)- $AD$2 +1 -> 30 | AC43: =IF(AND($E43="Oui",$M43="Préleveur"),$F43,"") | AD43: {=IFERROR(INDEX($AC$14:$AC$102,SMALL(IF($AC$14:$AC$102<>"",ROW($AC$14:$AC$102)-ROW(INDIRECT("$AC$14"))+1),ROW(INDIRECT("A" & AB43 ) ))),"")} | AE43: =IF(AND($E43="Oui",LEFT($M43,10) ="Débitmètre"),$F43,"") | AF43: {=IFERROR(INDEX($AE$14:$AE$102,SMALL(IF($AE$14:$AE$102<>"",ROW($AE$14:$AE$102)-ROW(INDIRECT("$AE$14"))+1),ROW(INDIRECT("A" & AB43 ) ))),"")} | AG43: =IF(AND($E43="Oui",LEFT($M43,5) ="Sonde"),$F43,"") | AH43: {=IFERROR(INDEX($AG$14:$AG$102,SMALL(IF($AG$14:$AG$102<>"",ROW($AG$14:$AG$102)-ROW(INDIRECT("$AG$14"))+1),ROW(INDIRECT("A" & AB43 ) ))),"")} | AI43: =IF(AND($E43="Oui", $F43 <> "", $M43 = ""),$F43,"") | AJ43: {=IFERROR(INDEX($AI$14:$AI$102,SMALL(IF($AI$14:$AI$102<>"",ROW($AI$14:$AI$102)-ROW(INDIRECT("$AI$14"))+1),ROW(INDIRECT("A" & AB43 ) ))),"")}
E44: Ajouter un pluviomètre station | K44: Si pas de pluviomètre, veuillez ajouter en commentaire la provenance des données : | AB44: =ROW(A44)- $AD$2 +1 -> 31 | AC44: =IF(AND($E44="Oui",$M44="Préleveur"),$F44,"") | AD44: {=IFERROR(INDEX($AC$14:$AC$99,SMALL(IF($AC$14:$AC$99<>"",ROW($AC$14:$AC$99)-ROW(INDIRECT("$AC$13"))+1),ROW(INDIRECT("A" & AB44 ) ))),"")} | AE44: =IF(AND($E44="Oui",LEFT($M44,10) ="Débitmètre"),$F44,"") | AF44: {=IFERROR(INDEX($AE$14:$AE$99,SMALL(IF($AE$14:$AE$99<>"",ROW($AE$14:$AE$99)-ROW(INDIRECT("$AE$13"))+1),ROW(INDIRECT("A" & AB44 ) ))),"")} | AG44: =IF(AND($E44="Oui",LEFT($M44,5) ="Sonde"),$F44,"") | AH44: {=IFERROR(INDEX($AG$14:$AG$99,SMALL(IF($AG$14:$AG$99<>"",ROW($AG$14:$AG$99)-ROW(INDIRECT("$AG$13"))+1),ROW(INDIRECT("A" & AB44 ) ))),"")} | AI44: =IF(AND($E44="Oui", $F44 <> "", $M44 = ""),$F44,"") | AJ44: {=IFERROR(INDEX($AI$14:$AI$99,SMALL(IF($AI$14:$AI$99<>"",ROW($AI$14:$AI$99)-ROW(INDIRECT("$AI$13"))+1),ROW(INDIRECT("A" & AB44 ) ))),"")}
AB45: =ROW(A45)- $AD$2 +1 -> 32 | AC45: =IF(AND($E45="Oui",$M45="Préleveur"),$F45,"") | AD45: {=IFERROR(INDEX($AC$14:$AC$99,SMALL(IF($AC$14:$AC$99<>"",ROW($AC$14:$AC$99)-ROW(INDIRECT("$AC$13"))+1),ROW(INDIRECT("A" & AB45 ) ))),"")} | AE45: =IF(AND($E45="Oui",LEFT($M45,10) ="Débitmètre"),$F45,"") | AF45: {=IFERROR(INDEX($AE$14:$AE$99,SMALL(IF($AE$14:$AE$99<>"",ROW($AE$14:$AE$99)-ROW(INDIRECT("$AE$13"))+1),ROW(INDIRECT("A" & AB45 ) ))),"")} | AG45: =IF(AND($E45="Oui",LEFT($M45,5) ="Sonde"),$F45,"") | AH45: {=IFERROR(INDEX($AG$14:$AG$99,SMALL(IF($AG$14:$AG$99<>"",ROW($AG$14:$AG$99)-ROW(INDIRECT("$AG$13"))+1),ROW(INDIRECT("A" & AB45 ) ))),"")} | AI45: =IF(AND($E45="Oui", $F45 <> "", $M45 = ""),$F45,"") | AJ45: {=IFERROR(INDEX($AI$14:$AI$99,SMALL(IF($AI$14:$AI$99<>"",ROW($AI$14:$AI$99)-ROW(INDIRECT("$AI$13"))+1),ROW(INDIRECT("A" & AB45 ) ))),"")}
AB46: =ROW(A46)- $AD$2 +1 -> 33 | AC46: =IF(AND($E46="Oui",$M46="Préleveur"),$F46,"") | AD46: {=IFERROR(INDEX($AC$14:$AC$99,SMALL(IF($AC$14:$AC$99<>"",ROW($AC$14:$AC$99)-ROW(INDIRECT("$AC$13"))+1),ROW(INDIRECT("A" & AB46 ) ))),"")} | AE46: =IF(AND($E46="Oui",LEFT($M46,10) ="Débitmètre"),$F46,"") | AF46: {=IFERROR(INDEX($AE$14:$AE$99,SMALL(IF($AE$14:$AE$99<>"",ROW($AE$14:$AE$99)-ROW(INDIRECT("$AE$13"))+1),ROW(INDIRECT("A" & AB46 ) ))),"")} | AG46: =IF(AND($E46="Oui",LEFT($M46,5) ="Sonde"),$F46,"") | AH46: {=IFERROR(INDEX($AG$14:$AG$99,SMALL(IF($AG$14:$AG$99<>"",ROW($AG$14:$AG$99)-ROW(INDIRECT("$AG$13"))+1),ROW(INDIRECT("A" & AB46 ) ))),"")} | AI46: =IF(AND($E46="Oui", $F46 <> "", $M46 = ""),$F46,"") | AJ46: {=IFERROR(INDEX($AI$14:$AI$99,SMALL(IF($AI$14:$AI$99<>"",ROW($AI$14:$AI$99)-ROW(INDIRECT("$AI$13"))+1),ROW(INDIRECT("A" & AB46 ) ))),"")}
AB47: =ROW(A47)- $AD$2 +1 -> 34 | AC47: =IF(AND($E47="Oui",$M47="Préleveur"),$F47,"") | AD47: {=IFERROR(INDEX($AC$14:$AC$99,SMALL(IF($AC$14:$AC$99<>"",ROW($AC$14:$AC$99)-ROW(INDIRECT("$AC$13"))+1),ROW(INDIRECT("A" & AB47 ) ))),"")} | AE47: =IF(AND($E47="Oui",LEFT($M47,10) ="Débitmètre"),$F47,"") | AF47: {=IFERROR(INDEX($AE$14:$AE$99,SMALL(IF($AE$14:$AE$99<>"",ROW($AE$14:$AE$99)-ROW(INDIRECT("$AE$13"))+1),ROW(INDIRECT("A" & AB47 ) ))),"")} | AG47: =IF(AND($E47="Oui",LEFT($M47,5) ="Sonde"),$F47,"") | AH47: {=IFERROR(INDEX($AG$14:$AG$99,SMALL(IF($AG$14:$AG$99<>"",ROW($AG$14:$AG$99)-ROW(INDIRECT("$AG$13"))+1),ROW(INDIRECT("A" & AB47 ) ))),"")} | AI47: =IF(AND($E47="Oui", $F47 <> "", $M47 = ""),$F47,"") | AJ47: {=IFERROR(INDEX($AI$14:$AI$99,SMALL(IF($AI$14:$AI$99<>"",ROW($AI$14:$AI$99)-ROW(INDIRECT("$AI$13"))+1),ROW(INDIRECT("A" & AB47 ) ))),"")}
AB48: =ROW(A48)- $AD$2 +1 -> 35 | AC48: =IF(AND($E48="Oui",$M48="Préleveur"),$F48,"") | AD48: {=IFERROR(INDEX($AC$14:$AC$99,SMALL(IF($AC$14:$AC$99<>"",ROW($AC$14:$AC$99)-ROW(INDIRECT("$AC$13"))+1),ROW(INDIRECT("A" & AB48 ) ))),"")} | AE48: =IF(AND($E48="Oui",LEFT($M48,10) ="Débitmètre"),$F48,"") | AF48: {=IFERROR(INDEX($AE$14:$AE$99,SMALL(IF($AE$14:$AE$99<>"",ROW($AE$14:$AE$99)-ROW(INDIRECT("$AE$13"))+1),ROW(INDIRECT("A" & AB48 ) ))),"")} | AG48: =IF(AND($E48="Oui",LEFT($M48,5) ="Sonde"),$F48,"") | AH48: {=IFERROR(INDEX($AG$14:$AG$99,SMALL(IF($AG$14:$AG$99<>"",ROW($AG$14:$AG$99)-ROW(INDIRECT("$AG$13"))+1),ROW(INDIRECT("A" & AB48 ) ))),"")} | AI48: =IF(AND($E48="Oui", $F48 <> "", $M48 = ""),$F48,"") | AJ48: {=IFERROR(INDEX($AI$14:$AI$99,SMALL(IF($AI$14:$AI$99<>"",ROW($AI$14:$AI$99)-ROW(INDIRECT("$AI$13"))+1),ROW(INDIRECT("A" & AB48 ) ))),"")}
AB49: =ROW(A49)- $AD$2 +1 -> 36 | AC49: =IF(AND($E49="Oui",$M49="Préleveur"),$F49,"") | AD49: {=IFERROR(INDEX($AC$14:$AC$99,SMALL(IF($AC$14:$AC$99<>"",ROW($AC$14:$AC$99)-ROW(INDIRECT("$AC$13"))+1),ROW(INDIRECT("A" & AB49 ) ))),"")} | AE49: =IF(AND($E49="Oui",LEFT($M49,10) ="Débitmètre"),$F49,"") | AF49: {=IFERROR(INDEX($AE$14:$AE$99,SMALL(IF($AE$14:$AE$99<>"",ROW($AE$14:$AE$99)-ROW(INDIRECT("$AE$13"))+1),ROW(INDIRECT("A" & AB49 ) ))),"")} | AG49: =IF(AND($E49="Oui",LEFT($M49,5) ="Sonde"),$F49,"") | AH49: {=IFERROR(INDEX($AG$14:$AG$99,SMALL(IF($AG$14:$AG$99<>"",ROW($AG$14:$AG$99)-ROW(INDIRECT("$AG$13"))+1),ROW(INDIRECT("A" & AB49 ) ))),"")} | AI49: =IF(AND($E49="Oui", $F49 <> "", $M49 = ""),$F49,"") | AJ49: {=IFERROR(INDEX($AI$14:$AI$99,SMALL(IF($AI$14:$AI$99<>"",ROW($AI$14:$AI$99)-ROW(INDIRECT("$AI$13"))+1),ROW(INDIRECT("A" & AB49 ) ))),"")}
AB50: =ROW(A50)- $AD$2 +1 -> 37 | AC50: =IF(AND($E50="Oui",$M50="Préleveur"),$F50,"") | AD50: {=IFERROR(INDEX($AC$14:$AC$99,SMALL(IF($AC$14:$AC$99<>"",ROW($AC$14:$AC$99)-ROW(INDIRECT("$AC$13"))+1),ROW(INDIRECT("A" & AB50 ) ))),"")} | AE50: =IF(AND($E50="Oui",LEFT($M50,10) ="Débitmètre"),$F50,"") | AF50: {=IFERROR(INDEX($AE$14:$AE$99,SMALL(IF($AE$14:$AE$99<>"",ROW($AE$14:$AE$99)-ROW(INDIRECT("$AE$13"))+1),ROW(INDIRECT("A" & AB50 ) ))),"")} | AG50: =IF(AND($E50="Oui",LEFT($M50,5) ="Sonde"),$F50,"") | AH50: {=IFERROR(INDEX($AG$14:$AG$99,SMALL(IF($AG$14:$AG$99<>"",ROW($AG$14:$AG$99)-ROW(INDIRECT("$AG$13"))+1),ROW(INDIRECT("A" & AB50 ) ))),"")} | AI50: =IF(AND($E50="Oui", $F50 <> "", $M50 = ""),$F50,"") | AJ50: {=IFERROR(INDEX($AI$14:$AI$99,SMALL(IF($AI$14:$AI$99<>"",ROW($AI$14:$AI$99)-ROW(INDIRECT("$AI$13"))+1),ROW(INDIRECT("A" & AB50 ) ))),"")}
AB51: =ROW(A51)- $AD$2 +1 -> 38 | AC51: =IF(AND($E51="Oui",$M51="Préleveur"),$F51,"") | AD51: {=IFERROR(INDEX($AC$14:$AC$99,SMALL(IF($AC$14:$AC$99<>"",ROW($AC$14:$AC$99)-ROW(INDIRECT("$AC$13"))+1),ROW(INDIRECT("A" & AB51 ) ))),"")} | AE51: =IF(AND($E51="Oui",LEFT($M51,10) ="Débitmètre"),$F51,"") | AF51: {=IFERROR(INDEX($AE$14:$AE$99,SMALL(IF($AE$14:$AE$99<>"",ROW($AE$14:$AE$99)-ROW(INDIRECT("$AE$13"))+1),ROW(INDIRECT("A" & AB51 ) ))),"")} | AG51: =IF(AND($E51="Oui",LEFT($M51,5) ="Sonde"),$F51,"") | AH51: {=IFERROR(INDEX($AG$14:$AG$99,SMALL(IF($AG$14:$AG$99<>"",ROW($AG$14:$AG$99)-ROW(INDIRECT("$AG$13"))+1),ROW(INDIRECT("A" & AB51 ) ))),"")} | AI51: =IF(AND($E51="Oui", $F51 <> "", $M51 = ""),$F51,"") | AJ51: {=IFERROR(INDEX($AI$14:$AI$99,SMALL(IF($AI$14:$AI$99<>"",ROW($AI$14:$AI$99)-ROW(INDIRECT("$AI$13"))+1),ROW(INDIRECT("A" & AB51 ) ))),"")}
AB52: =ROW(A52)- $AD$2 +1 -> 39 | AC52: =IF(AND($E52="Oui",$M52="Préleveur"),$F52,"") | AD52: {=IFERROR(INDEX($AC$14:$AC$99,SMALL(IF($AC$14:$AC$99<>"",ROW($AC$14:$AC$99)-ROW(INDIRECT("$AC$13"))+1),ROW(INDIRECT("A" & AB52 ) ))),"")} | AE52: =IF(AND($E52="Oui",LEFT($M52,10) ="Débitmètre"),$F52,"") | AF52: {=IFERROR(INDEX($AE$14:$AE$99,SMALL(IF($AE$14:$AE$99<>"",ROW($AE$14:$AE$99)-ROW(INDIRECT("$AE$13"))+1),ROW(INDIRECT("A" & AB52 ) ))),"")} | AG52: =IF(AND($E52="Oui",LEFT($M52,5) ="Sonde"),$F52,"") | AH52: {=IFERROR(INDEX($AG$14:$AG$99,SMALL(IF($AG$14:$AG$99<>"",ROW($AG$14:$AG$99)-ROW(INDIRECT("$AG$13"))+1),ROW(INDIRECT("A" & AB52 ) ))),"")} | AI52: =IF(AND($E52="Oui", $F52 <> "", $M52 = ""),$F52,"") | AJ52: {=IFERROR(INDEX($AI$14:$AI$99,SMALL(IF($AI$14:$AI$99<>"",ROW($AI$14:$AI$99)-ROW(INDIRECT("$AI$13"))+1),ROW(INDIRECT("A" & AB52 ) ))),"")}
AB53: =ROW(A53)- $AD$2 +1 -> 40 | AC53: =IF(AND($E53="Oui",$M53="Préleveur"),$F53,"") | AD53: {=IFERROR(INDEX($AC$14:$AC$99,SMALL(IF($AC$14:$AC$99<>"",ROW($AC$14:$AC$99)-ROW(INDIRECT("$AC$13"))+1),ROW(INDIRECT("A" & AB53 ) ))),"")} | AE53: =IF(AND($E53="Oui",LEFT($M53,10) ="Débitmètre"),$F53,"") | AF53: {=IFERROR(INDEX($AE$14:$AE$99,SMALL(IF($AE$14:$AE$99<>"",ROW($AE$14:$AE$99)-ROW(INDIRECT("$AE$13"))+1),ROW(INDIRECT("A" & AB53 ) ))),"")} | AG53: =IF(AND($E53="Oui",LEFT($M53,5) ="Sonde"),$F53,"") | AH53: {=IFERROR(INDEX($AG$14:$AG$99,SMALL(IF($AG$14:$AG$99<>"",ROW($AG$14:$AG$99)-ROW(INDIRECT("$AG$13"))+1),ROW(INDIRECT("A" & AB53 ) ))),"")} | AI53: =IF(AND($E53="Oui", $F53 <> "", $M53 = ""),$F53,"") | AJ53: {=IFERROR(INDEX($AI$14:$AI$99,SMALL(IF($AI$14:$AI$99<>"",ROW($AI$14:$AI$99)-ROW(INDIRECT("$AI$13"))+1),ROW(INDIRECT("A" & AB53 ) ))),"")}
AB54: =ROW(A54)- $AD$2 +1 -> 41 | AC54: =IF(AND($E54="Oui",$M54="Préleveur"),$F54,"") | AD54: {=IFERROR(INDEX($AC$14:$AC$99,SMALL(IF($AC$14:$AC$99<>"",ROW($AC$14:$AC$99)-ROW(INDIRECT("$AC$13"))+1),ROW(INDIRECT("A" & AB54 ) ))),"")} | AE54: =IF(AND($E54="Oui",LEFT($M54,10) ="Débitmètre"),$F54,"") | AF54: {=IFERROR(INDEX($AE$14:$AE$99,SMALL(IF($AE$14:$AE$99<>"",ROW($AE$14:$AE$99)-ROW(INDIRECT("$AE$13"))+1),ROW(INDIRECT("A" & AB54 ) ))),"")} | AG54: =IF(AND($E54="Oui",LEFT($M54,5) ="Sonde"),$F54,"") | AH54: {=IFERROR(INDEX($AG$14:$AG$99,SMALL(IF($AG$14:$AG$99<>"",ROW($AG$14:$AG$99)-ROW(INDIRECT("$AG$13"))+1),ROW(INDIRECT("A" & AB54 ) ))),"")} | AI54: =IF(AND($E54="Oui", $F54 <> "", $M54 = ""),$F54,"") | AJ54: {=IFERROR(INDEX($AI$14:$AI$99,SMALL(IF($AI$14:$AI$99<>"",ROW($AI$14:$AI$99)-ROW(INDIRECT("$AI$13"))+1),ROW(INDIRECT("A" & AB54 ) ))),"")}
AB55: =ROW(A55)- $AD$2 +1 -> 42 | AC55: =IF(AND($E55="Oui",$M55="Préleveur"),$F55,"") | AD55: {=IFERROR(INDEX($AC$14:$AC$99,SMALL(IF($AC$14:$AC$99<>"",ROW($AC$14:$AC$99)-ROW(INDIRECT("$AC$13"))+1),ROW(INDIRECT("A" & AB55 ) ))),"")} | AE55: =IF(AND($E55="Oui",LEFT($M55,10) ="Débitmètre"),$F55,"") | AF55: {=IFERROR(INDEX($AE$14:$AE$99,SMALL(IF($AE$14:$AE$99<>"",ROW($AE$14:$AE$99)-ROW(INDIRECT("$AE$13"))+1),ROW(INDIRECT("A" & AB55 ) ))),"")} | AG55: =IF(AND($E55="Oui",LEFT($M55,5) ="Sonde"),$F55,"") | AH55: {=IFERROR(INDEX($AG$14:$AG$99,SMALL(IF($AG$14:$AG$99<>"",ROW($AG$14:$AG$99)-ROW(INDIRECT("$AG$13"))+1),ROW(INDIRECT("A" & AB55 ) ))),"")} | AI55: =IF(AND($E55="Oui", $F55 <> "", $M55 = ""),$F55,"") | AJ55: {=IFERROR(INDEX($AI$14:$AI$99,SMALL(IF($AI$14:$AI$99<>"",ROW($AI$14:$AI$99)-ROW(INDIRECT("$AI$13"))+1),ROW(INDIRECT("A" & AB55 ) ))),"")}
AB56: =ROW(A56)- $AD$2 +1 -> 43 | AC56: =IF(AND($E56="Oui",$M56="Préleveur"),$F56,"") | AD56: {=IFERROR(INDEX($AC$14:$AC$99,SMALL(IF($AC$14:$AC$99<>"",ROW($AC$14:$AC$99)-ROW(INDIRECT("$AC$13"))+1),ROW(INDIRECT("A" & AB56 ) ))),"")} | AE56: =IF(AND($E56="Oui",LEFT($M56,10) ="Débitmètre"),$F56,"") | AF56: {=IFERROR(INDEX($AE$14:$AE$99,SMALL(IF($AE$14:$AE$99<>"",ROW($AE$14:$AE$99)-ROW(INDIRECT("$AE$13"))+1),ROW(INDIRECT("A" & AB56 ) ))),"")} | AG56: =IF(AND($E56="Oui",LEFT($M56,5) ="Sonde"),$F56,"") | AH56: {=IFERROR(INDEX($AG$14:$AG$99,SMALL(IF($AG$14:$AG$99<>"",ROW($AG$14:$AG$99)-ROW(INDIRECT("$AG$13"))+1),ROW(INDIRECT("A" & AB56 ) ))),"")} | AI56: =IF(AND($E56="Oui", $F56 <> "", $M56 = ""),$F56,"") | AJ56: {=IFERROR(INDEX($AI$14:$AI$99,SMALL(IF($AI$14:$AI$99<>"",ROW($AI$14:$AI$99)-ROW(INDIRECT("$AI$13"))+1),ROW(INDIRECT("A" & AB56 ) ))),"")}
... AB91: =ROW(A91)- $AD$2 +1 -> 78 | AC91: =IF(AND($E91="Oui",$M91="Préleveur"),$F91,"") | AD91: {=IFERROR(INDEX($AC$14:$AC$99,SMALL(IF($AC$14:$AC$99<>"",ROW($AC$14:$AC$99)-ROW(INDIRECT("$AC$13"))+1),ROW(INDIRECT("A" & AB91 ) ))),"")} | AE91: =IF(AND($E91="Oui",LEFT($M91,10) ="Débitmètre"),$F91,"") | AF91: {=IFERROR(INDEX($AE$14:$AE$99,SMALL(IF($AE$14:$AE$99<>"",ROW($AE$14:$AE$99)-ROW(INDIRECT("$AE$13"))+1),ROW(INDIRECT("A" & AB91 ) ))),"")} | AG91: =IF(AND($E91="Oui",LEFT($M91,5) ="Sonde"),$F91,"") | AH91: {=IFERROR(INDEX($AG$14:$AG$99,SMALL(IF($AG$14:$AG$99<>"",ROW($AG$14:$AG$99)-ROW(INDIRECT("$AG$13"))+1),ROW(INDIRECT("A" & AB91 ) ))),"")} | AI91: =IF(AND($E91="Oui", $F91 <> "", $M91 = ""),$F91,"") | AJ91: {=IFERROR(INDEX($AI$14:$AI$99,SMALL(IF($AI$14:$AI$99<>"",ROW($AI$14:$AI$99)-ROW(INDIRECT("$AI$13"))+1),ROW(INDIRECT("A" & AB91 ) ))),"")}
AI92: =IF(AND($E92="Oui", $M92 <> "", $M92 = ""),$F92,"") | AJ92: {=IFERROR(INDEX($AI$14:$AI$99,SMALL(IF($AI$14:$AI$99<>"",ROW($AI$14:$AI$99)-ROW(INDIRECT("$AI$13"))+1),ROW(INDIRECT("A" & AB92 ) ))),"")}

Sheet SYNTHESE
C2: CONTRÔLE ANNUEL DES DISPOSITIFS D'AUTOSURVEILLANCE DES SYSTÈMES D'ASSAINISSEMENT COLLECTIF
C3: NOM DU SYSTÈME D'ASSAINISSEMENT : | F3: =IF(ISBLANK(Descriptif!F3),"",Descriptif!F3) -> BARJAC (30) | I3: NOM SYSTÈME DE TRAITEMENT : | K3: =IF(ISBLANK(Descriptif!L3),"",Descriptif!L3) -> BARJAC (30) | M3: NOM SYSTÈME DE COLLECTE : | Q3: =IF(ISBLANK(Descriptif!Q3),"",Descriptif!Q3) -> sys | V3: ORGANISME DE CONTRÔLE : | Y3: =IF(ISBLANK(Descriptif!U3),"",Descriptif!U3) -> CEREG Ingénierie
C4: CODE SANDRE DE L'AGGLOMERATION : | F4: =IF(ISBLANK(Descriptif!F4),"",Descriptif!F4) -> eee | I4: CODE SANDRE DE LA STATION : | K4: =IF(ISBLANK(Descriptif!L4),"",Descriptif!L4) -> 060930290002 | M4: CODE SANDRE DU RESEAU : | Q4: =IF(ISBLANK(Descriptif!Q4),"",Descriptif!Q4) -> yyy | V4: NOM(S) CONTROLEUR(S) : | Y4: =IF(ISBLANK(Descriptif!U4),"",Descriptif!U4) -> control
C5: NOM DU MAITRE D'OUVRAGE : | F5: =IF(ISBLANK(Descriptif!F5),"",Descriptif!F5) -> Commune de Barjac | I5: TYPE DE TRAITEMENT : | K5: =IF(ISBLANK(Descriptif!L5),"",Descriptif!L5) -> Boues activée faible charge | M5: TYPE DE RESEAU | Q5: =IF(ISBLANK(Descriptif!Q5),"",Descriptif!Q5) -> Mixte | V5: DATE(S) D'INTERVENTION : | Y5: =IF(ISBLANK(Descriptif!U5),"",Descriptif!U5) -> 46006
C6: EXPLOITANT DE LA STATION : | F6: =IF(ISBLANK(Descriptif!F6),"",Descriptif!F6) -> Regie | I6: CAPACITE DE LA STATION : | K6: =IF(ISBLANK(Descriptif!L6),"",Descriptif!L6) -> 5 000 EH | M6: EXPLOITANT DU RESEAU : | Q6: =IF(ISBLANK(Descriptif!Q6),"",Descriptif!Q6) -> exp r | V6: CONDITION(S) METEO : | Y6: =IF(ISBLANK(Descriptif!U6),"",Descriptif!U6) -> pluie
C8: EVALUATIONS
D10: Evaluation des points règlementaires
G11: ENTREE et SORTIE | J11: Score | L11: DEVERSEMENT STATION | P11: Score | T11: BOUE et Apports extérieurs | Y11: Score
G12: Point A3 | J12: =Recap_equipements!E62 | L12: Point A2 | P12: =Recap_equipements!E74 | T12: Point A6 | Y12: =Recap_equipements!E86
G13: Débitmètre | J13: =IF(Recap_equipements!F64<>"",Recap_equipements!F64,"") | L13: Débitmètre | P13: =Recap_equipements!F76 | T13: Débitmètre | Y13: =Recap_equipements!F88
G14: Préleveur | J14: =IF(Recap_equipements!F65<>"",Recap_equipements!F65,"") | L14: Préleveur | P14: =Recap_equipements!F77 | T14: Préleveur | Y14: =Recap_equipements!F89
G15: Analytique | J15: =IF(Recap_equipements!F66<>"",Recap_equipements!F66,"") | L15: Analytique | P15: =Recap_equipements!F78 | T15: Analytique | Y15: =Recap_equipements!F90
G16: Point A4 | J16: =Recap_equipements!E68 | L16: Point A5 | P16: =Recap_equipements!E80 | T16: Point A7 | Y16: =Recap_equipements!E92
G17: Débitmètre | J17: =IF(Recap_equipements!F70<>"",Recap_equipements!F70,"") | L17: Débitmètre | P17: =Recap_equipements!F82 | T17: Débitmètre | Y17: =Recap_equipements!F94
G18: Préleveur | J18: =IF(Recap_equipements!F71<>"",Recap_equipements!F71,"") | L18: Préleveur | P18: =Recap_equipements!F83 | T18: Préleveur | Y18: =Recap_equipements!F95
G19: Analytique | J19: =IF(Recap_equipements!F72<>"",Recap_equipements!F72,"") | L19: Analytique | P19: =Recap_equipements!F84 | T19: Analytique | Y19: =Recap_equipements!F96
H21: Validé | K21: Validé avec réserve | O21: Non validé
D23: Evaluation documentaire | O23: Commentaire évaluation :
G24: Manuel d'autosurveillance à jour ou en cours d'expertise ? | K24: =IF(Qualité!L10<>"",Qualité!L10,"Non contrôlé") -> Oui | L24: Coef Qualité | O24: =IF(Qualité!M10<>"",Qualité!M10,"")
G25: Existe-t-il un système Qualité performant ? | K25: =IF(Qualité!L29<>"",Qualité!L29,"Non contrôlé") -> Non | L25: =IF(Qualité!L29="Non",0.9,1) -> 0.9 | O25: =IF(Qualité!D32<>"",Qualité!D32,"") -> Le système Qualité mis en œuvre est performant.
D28: Evaluation des pratiques analytiques
K29: Score/Penalité | O29: Commentaire évaluation :
G30: SDE | I30: Aquaref | K30: =IF(Analytique!N11<>"",Analytique!N11,"") -> 0 | O30: =IF(Analytique!D17<>"",Analytique!D17,"")
G31: EAU | I31: Fractionnement | K31: =IF(Analytique!N12<>"",Analytique!N12,"") -> 0
I32: Température | K32: =IF(Analytique!N13<>"",Analytique!N13,"") -> 0
I33: Transport | K33: =IF(Analytique!N14<>"",Analytique!N14,"") -> 0
I34: Score analytique | K34: =IF(Analytique!Q28<>"",Analytique!Q28,"") -> 0 | O34: =IF(Analytique!D34<>"",Analytique!D34,"")
G35: Score total de la chaine analytique | K35: =IF(Analytique!J31<>"",Analytique!J31,"") -> 0
D39: Autres évaluations
K40: Score | M40: Commentaire :
G41: Sonde température | I41: {=IFERROR(INDEX(Equipements!$L$16:$L$72,SMALL(IF(Equipements!$J$16:$J$72="Sonde de température",ROW(Equipements!$J$16:$J$72)-ROW(Equipements!$J$16)+1),ROW(1:1))),"")} | K41: {=IFERROR(INDEX(Equipements!$P$16:$P$72,SMALL(IF(Equipements!$J$16:$J$72="Sonde de température",ROW(Equipements!$J$16:$J$72)-ROW(Equipements!$J$16)+1),ROW(1:1))),"")} | M41: {=IFERROR(INDEX(Equipements!$V$16:$V$72,SMALL(IF(Equipements!$J$16:$J$72="Sonde de température",ROW(Equipements!$J$16:$J$72)-ROW(Equipements!$J$16)+1),ROW(1:1))),"")}
I42: {=IFERROR(INDEX(Equipements!$L$16:$L$72,SMALL(IF(Equipements!$J$16:$J$72="Sonde de température",ROW(Equipements!$J$16:$J$72)-ROW(Equipements!$J$16)+1),ROW(2:2))),"")} | K42: {=IFERROR(INDEX(Equipements!$R$16:$R$72,SMALL(IF(Equipements!$J$16:$J$72="Sonde de température",ROW(Equipements!$J$16:$J$72)-ROW(Equipements!$J$16)+1),ROW(2:2))),"")} | M42: {=IFERROR(INDEX(Equipements!$V$16:$V$72,SMALL(IF(Equipements!$J$16:$J$72="Sonde de température",ROW(Equipements!$J$16:$J$72)-ROW(Equipements!$J$16)+1),ROW(2:2))),"")}
I43: {=IFERROR(INDEX(Equipements!$L$16:$L$72,SMALL(IF(Equipements!$J$16:$J$72="Sonde de température",ROW(Equipements!$J$16:$J$72)-ROW(Equipements!$J$16)+1),ROW(3:3))),"")} | K43: {=IFERROR(INDEX(Equipements!$R$16:$R$72,SMALL(IF(Equipements!$J$16:$J$72="Sonde de température",ROW(Equipements!$J$16:$J$72)-ROW(Equipements!$J$16)+1),ROW(3:3))),"")} | M43: {=IFERROR(INDEX(Equipements!$V$16:$V$72,SMALL(IF(Equipements!$J$16:$J$72="Sonde de température",ROW(Equipements!$J$16:$J$72)-ROW(Equipements!$J$16)+1),ROW(3:3))),"")}
K45: Score | M45: Commentaire :
G46: Pluviomètre | I46: {=IFERROR(INDEX(Equipements!$L$16:$L$72,SMALL(IF(Equipements!$J$16:$J$72="Pluviomètre",ROW(Equipements!$J$16:$J$72)-ROW(Equipements!$J$16)+1),ROW(1:1))),"")} | K46: {=IFERROR(INDEX(Equipements!$P$16:$P$72,SMALL(IF(Equipements!$J$16:$J$72="Pluviomètre",ROW(Equipements!$J$16:$J$72)-ROW(Equipements!$J$16)+1),ROW(1:1))),"")} | M46: {=IFERROR(INDEX(Equipements!$V$16:$V$72,SMALL(IF(Equipements!$J$16:$J$72="Pluviomètre",ROW(Equipements!$J$16:$J$72)-ROW(Equipements!$J$16)+1),ROW(1:1))),"")}
I47: {=IFERROR(INDEX(Equipements!$L$16:$L$72,SMALL(IF(Equipements!$J$16:$J$72="Pluviomètre",ROW(Equipements!$J$16:$J$72)-ROW(Equipements!$J$16)+1),ROW(2:2))),"")} | K47: {=IFERROR(INDEX(Equipements!$P$16:$P$72,SMALL(IF(Equipements!$J$16:$J$72="Pluviomètre",ROW(Equipements!$J$16:$J$72)-ROW(Equipements!$J$16)+1),ROW(2:2))),"")} | M47: {=IFERROR(INDEX(Equipements!$V$16:$V$72,SMALL(IF(Equipements!$J$16:$J$72="Pluviomètre",ROW(Equipements!$J$16:$J$72)-ROW(Equipements!$J$16)+1),ROW(2:2))),"")}
I48: {=IFERROR(INDEX(Equipements!$L$16:$L$72,SMALL(IF(Equipements!$J$16:$J$72="Pluviomètre",ROW(Equipements!$J$16:$J$72)-ROW(Equipements!$J$16)+1),ROW(3:3))),"")} | K48: {=IFERROR(INDEX(Equipements!$P$16:$P$72,SMALL(IF(Equipements!$J$16:$J$72="Pluviomètre",ROW(Equipements!$J$16:$J$72)-ROW(Equipements!$J$16)+1),ROW(3:3))),"")} | M48: {=IFERROR(INDEX(Equipements!$V$16:$V$72,SMALL(IF(Equipements!$J$16:$J$72="Pluviomètre",ROW(Equipements!$J$16:$J$72)-ROW(Equipements!$J$16)+1),ROW(3:3))),"")}
D51: Commentaire général
C57: SYNTHESE DISPOSITIFS AUTOSURVEILLANCE DE LA STATION D'ÉPURATION
D59: Détails des équipements contrôlés | K59: Score sur 100 | L59: Critères d'évaluation
D60: Libellé | F60: Localisation | G60: Code point | H60: Type d'équipement | J60: Type de matériel | L60: 1 | M60: 2 | N60: 3 | O60: 4 | P60: 5 | Q60: 6 | R60: 7 | S60: 8 | T60: 9 | U60: 10
D61: =Equipements!H16 | F61: =Equipements!I16 | G61: =Equipements!M16 | H61: =Equipements!J16 | J61: =Equipements!K16 | K61: =Equipements!P16 | L61: =IF(Equipements!Y16<>"",Equipements!AK16,"") | M61: =IF(Equipements!Z16<>"",Equipements!AL16,"") | N61: =IF(Equipements!AA16<>"",Equipements!AM16,"") | O61: =IF(Equipements!AB16<>"",Equipements!AN16,"") | P61: =IF(Equipements!AC16<>"",Equipements!AO16,"") | Q61: =IF(Equipements!AD16<>"",Equipements!AP16,"") | R61: =IF(Equipements!AE16<>"",Equipements!AQ16,"") | S61: =IF(Equipements!AF16<>"",Equipements!AR16,"") | ... U61: =IF(Equipements!AH16<>"",Equipements!AT16,"")
D62: =Equipements!H17 | F62: =Equipements!I17 | G62: =Equipements!M17 | H62: =Equipements!J17 | J62: =Equipements!K17 | K62: =Equipements!P17 | L62: =IF(Equipements!Y17<>"",Equipements!AK17,"") | M62: =IF(Equipements!Z17<>"",Equipements!AL17,"") | N62: =IF(Equipements!AA17<>"",Equipements!AM17,"") | O62: =IF(Equipements!AB17<>"",Equipements!AN17,"") | P62: =IF(Equipements!AC17<>"",Equipements!AO17,"") | Q62: =IF(Equipements!AD17<>"",Equipements!AP17,"") | R62: =IF(Equipements!AE17<>"",Equipements!AQ17,"") | S62: =IF(Equipements!AF17<>"",Equipements!AR17,"") | ... U62: =IF(Equipements!AH17<>"",Equipements!AT17,"")
D63: =Equipements!H18 | F63: =Equipements!I18 | G63: =Equipements!M18 | H63: =Equipements!J18 | J63: =Equipements!K18 | K63: =Equipements!P18 | L63: =IF(Equipements!Y18<>"",Equipements!AK18,"") | M63: =IF(Equipements!Z18<>"",Equipements!AL18,"") | N63: =IF(Equipements!AA18<>"",Equipements!AM18,"") | O63: =IF(Equipements!AB18<>"",Equipements!AN18,"") | P63: =IF(Equipements!AC18<>"",Equipements!AO18,"") | Q63: =IF(Equipements!AD18<>"",Equipements!AP18,"") | R63: =IF(Equipements!AE18<>"",Equipements!AQ18,"") | S63: =IF(Equipements!AF18<>"",Equipements!AR18,"") | ... U63: =IF(Equipements!AH18<>"",Equipements!AT18,"")
D64: =Equipements!H19 | F64: =Equipements!I19 | G64: =Equipements!M19 | H64: =Equipements!J19 | J64: =Equipements!K19 | K64: =Equipements!P19 | L64: =IF(Equipements!Y19<>"",Equipements!AK19,"") | M64: =IF(Equipements!Z19<>"",Equipements!AL19,"") | N64: =IF(Equipements!AA19<>"",Equipements!AM19,"") | O64: =IF(Equipements!AB19<>"",Equipements!AN19,"") | P64: =IF(Equipements!AC19<>"",Equipements!AO19,"") | Q64: =IF(Equipements!AD19<>"",Equipements!AP19,"") | R64: =IF(Equipements!AE19<>"",Equipements!AQ19,"") | S64: =IF(Equipements!AF19<>"",Equipements!AR19,"") | ... U64: =IF(Equipements!AH19<>"",Equipements!AT19,"")
D65: =Equipements!H20 | F65: =Equipements!I20 | G65: =Equipements!M20 | H65: =Equipements!J20 | J65: =Equipements!K20 | K65: =Equipements!P20 | L65: =IF(Equipements!Y20<>"",Equipements!AK20,"") | M65: =IF(Equipements!Z20<>"",Equipements!AL20,"") | N65: =IF(Equipements!AA20<>"",Equipements!AM20,"") | O65: =IF(Equipements!AB20<>"",Equipements!AN20,"") | P65: =IF(Equipements!AC20<>"",Equipements!AO20,"") | Q65: =IF(Equipements!AD20<>"",Equipements!AP20,"") | R65: =IF(Equipements!AE20<>"",Equipements!AQ20,"") | S65: =IF(Equipements!AF20<>"",Equipements!AR20,"") | ... U65: =IF(Equipements!AH20<>"",Equipements!AT20,"")
D66: =Equipements!H21 | F66: =Equipements!I21 | G66: =Equipements!M21 | H66: =Equipements!J21 | J66: =Equipements!K21 | K66: =Equipements!P21 | L66: =IF(Equipements!Y21<>"",Equipements!AK21,"") | M66: =IF(Equipements!Z21<>"",Equipements!AL21,"") | N66: =IF(Equipements!AA21<>"",Equipements!AM21,"") | O66: =IF(Equipements!AB21<>"",Equipements!AN21,"") | P66: =IF(Equipements!AC21<>"",Equipements!AO21,"") | Q66: =IF(Equipements!AD21<>"",Equipements!AP21,"") | R66: =IF(Equipements!AE21<>"",Equipements!AQ21,"") | S66: =IF(Equipements!AF21<>"",Equipements!AR21,"") | ... U66: =IF(Equipements!AH21<>"",Equipements!AT21,"")
D67: =Equipements!H22 | F67: =Equipements!I22 | G67: =Equipements!M22 | H67: =Equipements!J22 | J67: =Equipements!K22 | K67: =Equipements!P22 | L67: =IF(Equipements!Y22<>"",Equipements!AK22,"") | M67: =IF(Equipements!Z22<>"",Equipements!AL22,"") | N67: =IF(Equipements!AA22<>"",Equipements!AM22,"") | O67: =IF(Equipements!AB22<>"",Equipements!AN22,"") | P67: =IF(Equipements!AC22<>"",Equipements!AO22,"") | Q67: =IF(Equipements!AD22<>"",Equipements!AP22,"") | R67: =IF(Equipements!AE22<>"",Equipements!AQ22,"") | S67: =IF(Equipements!AF22<>"",Equipements!AR22,"") | ... U67: =IF(Equipements!AH22<>"",Equipements!AT22,"")
D68: =Equipements!H23 | F68: =Equipements!I23 | G68: =Equipements!M23 | H68: =Equipements!J23 | J68: =Equipements!K23 | K68: =Equipements!P23 | L68: =IF(Equipements!Y23<>"",Equipements!AK23,"") | M68: =IF(Equipements!Z23<>"",Equipements!AL23,"") | N68: =IF(Equipements!AA23<>"",Equipements!AM23,"") | O68: =IF(Equipements!AB23<>"",Equipements!AN23,"") | P68: =IF(Equipements!AC23<>"",Equipements!AO23,"") | Q68: =IF(Equipements!AD23<>"",Equipements!AP23,"") | R68: =IF(Equipements!AE23<>"",Equipements!AQ23,"") | S68: =IF(Equipements!AF23<>"",Equipements!AR23,"") | ... U68: =IF(Equipements!AH23<>"",Equipements!AT23,"")
D69: =Equipements!H24 | F69: =Equipements!I24 | G69: =Equipements!M24 | H69: =Equipements!J24 | J69: =Equipements!K24 | K69: =Equipements!P24 | L69: =IF(Equipements!Y24<>"",Equipements!AK24,"") | M69: =IF(Equipements!Z24<>"",Equipements!AL24,"") | N69: =IF(Equipements!AA24<>"",Equipements!AM24,"") | O69: =IF(Equipements!AB24<>"",Equipements!AN24,"") | P69: =IF(Equipements!AC24<>"",Equipements!AO24,"") | Q69: =IF(Equipements!AD24<>"",Equipements!AP24,"") | R69: =IF(Equipements!AE24<>"",Equipements!AQ24,"") | S69: =IF(Equipements!AF24<>"",Equipements!AR24,"") | ... U69: =IF(Equipements!AH24<>"",Equipements!AT24,"")
D70: =Equipements!H25 | F70: =Equipements!I25 | G70: =Equipements!M25 | H70: =Equipements!J25 | J70: =Equipements!K25 | K70: =Equipements!P25 | L70: =IF(Equipements!Y25<>"",Equipements!AK25,"") | M70: =IF(Equipements!Z25<>"",Equipements!AL25,"") | N70: =IF(Equipements!AA25<>"",Equipements!AM25,"") | O70: =IF(Equipements!AB25<>"",Equipements!AN25,"") | P70: =IF(Equipements!AC25<>"",Equipements!AO25,"") | Q70: =IF(Equipements!AD25<>"",Equipements!AP25,"") | R70: =IF(Equipements!AE25<>"",Equipements!AQ25,"") | S70: =IF(Equipements!AF25<>"",Equipements!AR25,"") | ... U70: =IF(Equipements!AH25<>"",Equipements!AT25,"")
D71: =Equipements!H26 | F71: =Equipements!I26 | G71: =Equipements!M26 | H71: =Equipements!J26 | J71: =Equipements!K26 | K71: =Equipements!P26 | L71: =IF(Equipements!Y26<>"",Equipements!AK26,"") | M71: =IF(Equipements!Z26<>"",Equipements!AL26,"") | N71: =IF(Equipements!AA26<>"",Equipements!AM26,"") | O71: =IF(Equipements!AB26<>"",Equipements!AN26,"") | P71: =IF(Equipements!AC26<>"",Equipements!AO26,"") | Q71: =IF(Equipements!AD26<>"",Equipements!AP26,"") | R71: =IF(Equipements!AE26<>"",Equipements!AQ26,"") | S71: =IF(Equipements!AF26<>"",Equipements!AR26,"") | ... U71: =IF(Equipements!AH26<>"",Equipements!AT26,"")
D72: =Equipements!H27 | F72: =Equipements!I27 | G72: =Equipements!M27 | H72: =Equipements!J27 | J72: =Equipements!K27 | K72: =Equipements!P27 | L72: =IF(Equipements!Y27<>"",Equipements!AK27,"") | M72: =IF(Equipements!Z27<>"",Equipements!AL27,"") | N72: =IF(Equipements!AA27<>"",Equipements!AM27,"") | O72: =IF(Equipements!AB27<>"",Equipements!AN27,"") | P72: =IF(Equipements!AC27<>"",Equipements!AO27,"") | Q72: =IF(Equipements!AD27<>"",Equipements!AP27,"") | R72: =IF(Equipements!AE27<>"",Equipements!AQ27,"") | S72: =IF(Equipements!AF27<>"",Equipements!AR27,"") | ... U72: =IF(Equipements!AH27<>"",Equipements!AT27,"")
... D75: =Equipements!H30 | F75: =Equipements!I30 | G75: =Equipements!M30 | H75: =Equipements!J30 | J75: =Equipements!K30 | K75: =Equipements!P30 | L75: =IF(Equipements!Y30<>"",Equipements!AK30,"") | M75: =IF(Equipements!Z30<>"",Equipements!AL30,"") | N75: =IF(Equipements!AA30<>"",Equipements!AM30,"") | O75: =IF(Equipements!AB30<>"",Equipements!AN30,"") | P75: =IF(Equipements!AC30<>"",Equipements!AO30,"") | Q75: =IF(Equipements!AD30<>"",Equipements!AP30,"") | R75: =IF(Equipements!AE30<>"",Equipements!AQ30,"") | S75: =IF(Equipements!AF30<>"",Equipements!AR30,"") | ... U75: =IF(Equipements!AH30<>"",Equipements!AT30,"")
D76: =Equipements!H27 | F76: =Equipements!I27 | G76: =Equipements!M27 | H76: =Equipements!J27 | J76: =Equipements!K27 | K76: =Equipements!P27 | L76: =IF(Equipements!Y27<>"",Equipements!AK27,"") | M76: =IF(Equipements!Z27<>"",Equipements!AL27,"") | N76: =IF(Equipements!AA27<>"",Equipements!AM27,"") | O76: =IF(Equipements!AB27<>"",Equipements!AN27,"") | P76: =IF(Equipements!AC27<>"",Equipements!AO27,"") | Q76: =IF(Equipements!AD27<>"",Equipements!AP27,"") | R76: =IF(Equipements!AE27<>"",Equipements!AQ27,"") | S76: =IF(Equipements!AF27<>"",Equipements!AR27,"") | ... U76: =IF(Equipements!AH27<>"",Equipements!AT27,"")
D77: =Equipements!H28 | F77: =Equipements!I28 | G77: =Equipements!M28 | H77: =Equipements!J28 | J77: =Equipements!K28 | K77: =Equipements!P28 | L77: =IF(Equipements!Y28<>"",Equipements!AK28,"") | M77: =IF(Equipements!Z28<>"",Equipements!AL28,"") | N77: =IF(Equipements!AA28<>"",Equipements!AM28,"") | O77: =IF(Equipements!AB28<>"",Equipements!AN28,"") | P77: =IF(Equipements!AC28<>"",Equipements!AO28,"") | Q77: =IF(Equipements!AD28<>"",Equipements!AP28,"") | R77: =IF(Equipements!AE28<>"",Equipements!AQ28,"") | S77: =IF(Equipements!AF28<>"",Equipements!AR28,"") | ... U77: =IF(Equipements!AH28<>"",Equipements!AT28,"")

Sheet Qualité
C2: CONTRÔLE ANNUEL DES DISPOSITIFS D'AUTOSURVEILLANCE DES SYSTÈMES D'ASSAINISSEMENT COLLECTIF
C3: NOM DU SYSTÈME D'ASSAINISSEMENT : | G3: =IF(ISBLANK(Descriptif!F3),"",Descriptif!F3) -> BARJAC (30) | K3: NOM DU SYSTÈME DE COLLECTE : | O3: =IF(ISBLANK(Descriptif!Q3),"",Descriptif!Q3) -> sys
C4: CODE SANDRE DE L'AGGLOMERATION : | G4: =IF(ISBLANK(Descriptif!F4),"",Descriptif!F4) -> eee | K4: CODE SANDRE DU RESEAU : | O4: =IF(ISBLANK(Descriptif!Q4),"",Descriptif!Q4) -> yyy
C5: NOM DU MAITRE D'OUVRAGE : | G5: =IF(ISBLANK(Descriptif!F5),"",Descriptif!F5) -> Commune de Barjac | K5: NOM DE L'EXPLOITANT RESEAU : | O5: =IF(ISBLANK(Descriptif!Q6),"",Descriptif!Q6) -> exp r
C6: NOM DE L'EXPLOITANT STATION : | G6: =IF(ISBLANK(Descriptif!F6),"",Descriptif!F6) -> Regie | K6: ORGANISME DE CONTRÔLE : | O6: =IF(ISBLANK(Descriptif!U3),"",Descriptif!U3) -> CEREG Ingénierie
C8: MANUEL D'AUTOSURVEILLANCE
D10: 1 | E10: Est-ce que le manuel est à jour, validé ou en cours d'expertise? | L10: Oui
D12: COMMENTAIRES :
D13: La fiche descriptive du débitmètre "sortiestation" devra être actualisée afin de tenir compte du renouvellement du dispositif de mesure en mars 2025
D15: Le manuel d’autosurveillance n’est pas à jour si : * date du MAS ≤ 2015 ; * changement du maitre d’ouvrage ou de l’exploitant ; * construction d’une nouvelle STEU ou la réhabilitation d’une STEU ; * modification des points du système de collecte et des points de déversement au milieu ; * modification du référentiel et du schéma SANDRE (ajout ou suppression d’un point d’autosurveillance ou toute autre modification impactant le calcul du rendement) ; * évolutions techniques ou travaux importants sur le système d'assainissement impactant les points d'autosurveillance ; * modifications réglementaires telles que l’adoption d’un nouvel arrêté si impact sur le référentiel, le schéma SANDRE et le matériel d’autosurveillance ; * modifications significatives du suivi métrologique des dispositifs d'autosurveillance ; *modifications significatives concernant la réalisation des analyses d'autosurveillance.
C19: PROCEDURE DE CONTROLES INTERNES DES MATERIELS D'AUTOSURVEILLANCE
D21: 2 | E21: Est-ce que le contrôle des débimètres est réalisé selon les procédures décrites dans le manuel d'autosurveillance ? | L21: Oui
D22: 3 | E22: Est-ce que le contrôle des échantillonneurs est réalisé selon les procédures décrites dans le manuel d'autosurveillance ? | L22: Oui
D23: 4 | E23: Est-ce que le contrôle des thermomètres est réalisé selon les procédures décrites dans le manuel d'autosurveillance ? | L23: Oui
D24: 5 | E24: Est-ce que le contrôle des pluviomètres est réalisé selon les procédures décrites dans le manuel d'autosurveillance ? | L24: Oui
D25: 6 | E25: Est-ce que le contrôle des balances est réalisé selon les procédures décrites dans le manuel d'autosurveillance ? | L25: Oui
D26: 7 | E26: Est-ce que le contrôle des chronomètres est réalisé selon les procédures décrites dans le manuel d'autosurveillance ? | L26: Oui
D27: 8 | E27: Les contrôles internes sont-ils tous tracés, formalisés et suivis (fiches de vie, cartes de contrôle...) ? | L27: Oui
D28: 9 | E28: Des fiches de non-conformité et d'action d'amélioration ont-elles été produites ? | L28: Non
D29: 10 | E29: Existe-il un système qualité performant ? | L29: =IF(COUNTIF(L21:L28,"Non")>0,"Non","Oui") -> Non
D31: COMMENTAIRES :
D32: Le système Qualité mis en œuvre est performant.

Sheet Analytique
U1: Ne rien mettre dans cette colonne | V1: Ne rien mettre dans cette colonne | W1: Ne rien mettre dans cette colonne | X1: Ne rien mettre dans cette colonne | Y1: Ne rien mettre dans cette colonne | Z1: Ne rien mettre dans cette colonne
C2: CONTRÔLE ANNUEL DES DISPOSITIFS D'AUTOSURVEILLANCE DES SYSTÈMES D'ASSAINISSEMENT COLLECTIF | X2: Code PREL | Y2: NB ANALYSE | Z2: NB CONFORME | AA2: Coef | AB2: Coef corrigé | AC2: Score | AD2: Evaluation
C3: NOM DU SYSTÈME D'ASSAINISSEMENT : | G3: =IF(ISBLANK(Descriptif!F3), "", Descriptif!F3) -> BARJAC (30) | K3: NOM DU LABORATOIRE : | O3: Labo | X3: {=IFERROR(INDEX($T$37:$T$1003,SMALL(IF($T$37:$T$1003<>"",ROW($T$37:$T$1003)-ROW($T$37)+1),ROW(1:1))),"")} | Y3: {=IFERROR(INDEX($U$37:$U$1003,SMALL(IF($T$37:$T$1003<>"",ROW($T$37:$T$1003)-ROW($T$37)+1),ROW(1:1))),"")} | Z3: {=IFERROR(INDEX($V$37:$V$1003,SMALL(IF($T$37:$T$1003<>"",ROW($T$37:$T$1003)-ROW($T$37)+1),ROW(1:1))),"")} | AA3: {=IFERROR(INDEX($W$37:$W$1003,SMALL(IF($T$37:$T$1003<>"",ROW($T$37:$T$1003)-ROW($T$37)+1),ROW(1:1))),"")} | AB3: =IF(X3<>"",IF($J$28="Oui",100,AA3),"") | AC3: =IF(X3<>"",(AB3/100 * (1-$P$15)*100),"") | AD3: =IF(X3<>"",IF(AC3<>"",IF(AC3>80,"Validé",IF(AC3<70,"Non Validé","Validé avec réserve")),"Non contrôlé"),"")
C4: CODE SANDRE DE L'AGGLOMERATION : | G4: =IF(ISBLANK(Descriptif!F4), "", Descriptif!F4) -> eee | K4: AGREMENT : | X4: {=IFERROR(INDEX($T$37:$T$1003,SMALL(IF($T$37:$T$1003<>"",ROW($T$37:$T$1003)-ROW($T$37)+1),ROW(2:2))),"")} | Y4: {=IFERROR(INDEX($U$37:$U$1003,SMALL(IF($T$37:$T$1003<>"",ROW($T$37:$T$1003)-ROW($T$37)+1),ROW(2:2))),"")} | Z4: {=IFERROR(INDEX($V$37:$V$1003,SMALL(IF($T$37:$T$1003<>"",ROW($T$37:$T$1003)-ROW($T$37)+1),ROW(2:2))),"")} | AA4: {=IFERROR(INDEX($W$37:$W$1003,SMALL(IF($T$37:$T$1003<>"",ROW($T$37:$T$1003)-ROW($T$37)+1),ROW(2:2))),"")} | AB4: =IF(X4<>"",IF($J$28="Oui",100,AA4),"") | AC4: =IF(X4<>"",(AB4/100 * (1-$P$15)*100),"") | AD4: =IF(X4<>"",IF(AC4<>"",IF(AC4>80,"Validé",IF(AC4<70,"Non Validé","Validé avec réserve")),"Non contrôlé"),"")
C5: MAITRE D'OUVRAGE : | G5: =IF(ISBLANK(Descriptif!F5), "", Descriptif!F5) -> Commune de Barjac | K5: ORGANISME DE CONTRÔLE : | O5: =IF(ISBLANK(Descriptif!U3), "", Descriptif!U3) -> CEREG Ingénierie | X5: {=IFERROR(INDEX($T$37:$T$1003,SMALL(IF($T$37:$T$1003<>"",ROW($T$37:$T$1003)-ROW($T$37)+1),ROW(3:3))),"")} | Y5: {=IFERROR(INDEX($U$37:$U$1003,SMALL(IF($T$37:$T$1003<>"",ROW($T$37:$T$1003)-ROW($T$37)+1),ROW(3:3))),"")} | Z5: {=IFERROR(INDEX($V$37:$V$1003,SMALL(IF($T$37:$T$1003<>"",ROW($T$37:$T$1003)-ROW($T$37)+1),ROW(3:3))),"")} | AA5: {=IFERROR(INDEX($W$37:$W$1003,SMALL(IF($T$37:$T$1003<>"",ROW($T$37:$T$1003)-ROW($T$37)+1),ROW(3:3))),"")} | AB5: =IF(X5<>"",IF($J$28="Oui",100,AA5),"") | AC5: =IF(X5<>"",(AB5/100 * (1-$P$15)*100),"") | AD5: =IF(X5<>"",IF(AC5<>"",IF(AC5>80,"Validé",IF(AC5<70,"Non Validé","Validé avec réserve")),"Non contrôlé"),"")
C6: EXPLOITANT : | G6: =IF(ISBLANK(Descriptif!F6), "", Descriptif!F6) -> Regie | K6: NOM·S CONTROLEUR·SE·S : | O6: =IF(ISBLANK(Descriptif!U4), "", Descriptif!U4) -> control | X6: {=IFERROR(INDEX($T$37:$T$1003,SMALL(IF($T$37:$T$1003<>"",ROW($T$37:$T$1003)-ROW($T$37)+1),ROW(4:4))),"")} | Y6: {=IFERROR(INDEX($U$37:$U$1003,SMALL(IF($T$37:$T$1003<>"",ROW($T$37:$T$1003)-ROW($T$37)+1),ROW(4:4))),"")} | Z6: {=IFERROR(INDEX($V$37:$V$1003,SMALL(IF($T$37:$T$1003<>"",ROW($T$37:$T$1003)-ROW($T$37)+1),ROW(4:4))),"")} | AA6: {=IFERROR(INDEX($W$37:$W$1003,SMALL(IF($T$37:$T$1003<>"",ROW($T$37:$T$1003)-ROW($T$37)+1),ROW(4:4))),"")} | AB6: =IF(X6<>"",IF($J$28="Oui",100,AA6),"") | AC6: =IF(X6<>"",(AB6/100 * (1-$P$15)*100),"") | AD6: =IF(X6<>"",IF(AC6<>"",IF(AC6>80,"Validé",IF(AC6<70,"Non Validé","Validé avec réserve")),"Non contrôlé"),"")
X7: {=IFERROR(INDEX($T$37:$T$1003,SMALL(IF($T$37:$T$1003<>"",ROW($T$37:$T$1003)-ROW($T$37)+1),ROW(5:5))),"")} | Y7: {=IFERROR(INDEX($U$37:$U$1003,SMALL(IF($T$37:$T$1003<>"",ROW($T$37:$T$1003)-ROW($T$37)+1),ROW(5:5))),"")} | Z7: {=IFERROR(INDEX($V$37:$V$1003,SMALL(IF($T$37:$T$1003<>"",ROW($T$37:$T$1003)-ROW($T$37)+1),ROW(5:5))),"")} | AA7: {=IFERROR(INDEX($W$37:$W$1003,SMALL(IF($T$37:$T$1003<>"",ROW($T$37:$T$1003)-ROW($T$37)+1),ROW(5:5))),"")} | AB7: =IF(X7<>"",IF($J$28="Oui",100,AA7),"") | AC7: =IF(X7<>"",(AB7/100 * (1-$P$15)*100),"") | AD7: =IF(X7<>"",IF(AC7<>"",IF(AC7>80,"Validé",IF(AC7<70,"Non Validé","Validé avec réserve")),"Non contrôlé"),"")
C8: ECHANTILLONAGE | X8: {=IFERROR(INDEX($T$37:$T$1003,SMALL(IF($T$37:$T$1003<>"",ROW($T$37:$T$1003)-ROW($T$37)+1),ROW(6:6))),"")} | Y8: {=IFERROR(INDEX($U$37:$U$1003,SMALL(IF($T$37:$T$1003<>"",ROW($T$37:$T$1003)-ROW($T$37)+1),ROW(6:6))),"")} | Z8: {=IFERROR(INDEX($V$37:$V$1003,SMALL(IF($T$37:$T$1003<>"",ROW($T$37:$T$1003)-ROW($T$37)+1),ROW(6:6))),"")} | AA8: {=IFERROR(INDEX($W$37:$W$1003,SMALL(IF($T$37:$T$1003<>"",ROW($T$37:$T$1003)-ROW($T$37)+1),ROW(6:6))),"")} | AB8: =IF(X8<>"",IF($J$28="Oui",100,AA8),"") | AC8: =IF(X8<>"",(AB8/100 * (1-$P$15)*100),"") | AD8: =IF(X8<>"",IF(AC8<>"",IF(AC8>80,"Validé",IF(AC8<70,"Non Validé","Validé avec réserve")),"Non contrôlé"),"")
X9: {=IFERROR(INDEX($T$37:$T$1003,SMALL(IF($T$37:$T$1003<>"",ROW($T$37:$T$1003)-ROW($T$37)+1),ROW(7:7))),"")} | Y9: {=IFERROR(INDEX($U$37:$U$1003,SMALL(IF($T$37:$T$1003<>"",ROW($T$37:$T$1003)-ROW($T$37)+1),ROW(7:7))),"")} | Z9: {=IFERROR(INDEX($V$37:$V$1003,SMALL(IF($T$37:$T$1003<>"",ROW($T$37:$T$1003)-ROW($T$37)+1),ROW(7:7))),"")} | AA9: {=IFERROR(INDEX($W$37:$W$1003,SMALL(IF($T$37:$T$1003<>"",ROW($T$37:$T$1003)-ROW($T$37)+1),ROW(7:7))),"")} | AB9: =IF(X9<>"",IF($J$28="Oui",100,AA9),"") | AC9: =IF(X9<>"",(AB9/100 * (1-$P$15)*100),"") | AD9: =IF(X9<>"",IF(AC9<>"",IF(AC9>80,"Validé",IF(AC9<70,"Non Validé","Validé avec réserve")),"Non contrôlé"),"")
D10: Les échantillons sont-ils constitués, conservés et mis en analyse, selon les règles de l'art en vigueur ? | N10: Pénalité | X10: {=IFERROR(INDEX($T$37:$T$1003,SMALL(IF($T$37:$T$1003<>"",ROW($T$37:$T$1003)-ROW($T$37)+1),ROW(8:8))),"")} | Y10: {=IFERROR(INDEX($U$37:$U$1003,SMALL(IF($T$37:$T$1003<>"",ROW($T$37:$T$1003)-ROW($T$37)+1),ROW(8:8))),"")} | Z10: {=IFERROR(INDEX($V$37:$V$1003,SMALL(IF($T$37:$T$1003<>"",ROW($T$37:$T$1003)-ROW($T$37)+1),ROW(8:8))),"")} | AA10: {=IFERROR(INDEX($W$37:$W$1003,SMALL(IF($T$37:$T$1003<>"",ROW($T$37:$T$1003)-ROW($T$37)+1),ROW(8:8))),"")} | AB10: =IF(X10<>"",IF($J$28="Oui",100,AA10),"") | AC10: =IF(X10<>"",(AB10/100 * (1-$P$15)*100),"") | AD10: =IF(X10<>"",IF(AC10<>"",IF(AC10>80,"Validé",IF(AC10<70,"Non Validé","Validé avec réserve")),"Non contrôlé"),"")
D11: Le guide AQUAREF est-il respecté pour le prélèvement des échantillons SDE ? | L11: Non contrôlé | N11: =IF(L11="","",IF(L11="Non",0.1,0)) -> 0 | X11: {=IFERROR(INDEX($T$37:$T$1003,SMALL(IF($T$37:$T$1003<>"",ROW($T$37:$T$1003)-ROW($T$37)+1),ROW(9:9))),"")} | Y11: {=IFERROR(INDEX($U$37:$U$1003,SMALL(IF($T$37:$T$1003<>"",ROW($T$37:$T$1003)-ROW($T$37)+1),ROW(9:9))),"")} | Z11: {=IFERROR(INDEX($V$37:$V$1003,SMALL(IF($T$37:$T$1003<>"",ROW($T$37:$T$1003)-ROW($T$37)+1),ROW(9:9))),"")} | AA11: {=IFERROR(INDEX($W$37:$W$1003,SMALL(IF($T$37:$T$1003<>"",ROW($T$37:$T$1003)-ROW($T$37)+1),ROW(9:9))),"")} | AB11: =IF(X11<>"",IF($J$28="Oui",100,AA11),"") | AC11: =IF(X11<>"",(AB11/100 * (1-$P$15)*100),"") | AD11: =IF(X11<>"",IF(AC11<>"",IF(AC11>80,"Validé",IF(AC11<70,"Non Validé","Validé avec réserve")),"Non contrôlé"),"")
D12: Les échantillons sont-ils fractionnés selon la norme FDT 90-523-2 ? | L12: Oui | N12: =IF(L12="","",IF(L12="Non",0.1,0)) -> 0 | X12: {=IFERROR(INDEX($T$37:$T$1003,SMALL(IF($T$37:$T$1003<>"",ROW($T$37:$T$1003)-ROW($T$37)+1),ROW(10:10))),"")} | Y12: {=IFERROR(INDEX($U$37:$U$1003,SMALL(IF($T$37:$T$1003<>"",ROW($T$37:$T$1003)-ROW($T$37)+1),ROW(10:10))),"")} | Z12: {=IFERROR(INDEX($V$37:$V$1003,SMALL(IF($T$37:$T$1003<>"",ROW($T$37:$T$1003)-ROW($T$37)+1),ROW(10:10))),"")} | AA12: {=IFERROR(INDEX($W$37:$W$1003,SMALL(IF($T$37:$T$1003<>"",ROW($T$37:$T$1003)-ROW($T$37)+1),ROW(10:10))),"")} | AB12: =IF(X12<>"",IF($J$28="Oui",100,AA12),"") | AC12: =IF(X12<>"",(AB12/100 * (1-$P$15)*100),"") | AD12: =IF(X12<>"",IF(AC12<>"",IF(AC12>80,"Validé",IF(AC12<70,"Non Validé","Validé avec réserve")),"Non contrôlé"),"")
D13: La conservation pendant le transport des échantillons est-elle assurée à 5°C ± 3°C ? | L13: Oui | N13: =IF(L13="","",IF(L13="Non",0.1,0)) -> 0 | X13: {=IFERROR(INDEX($T$37:$T$1003,SMALL(IF($T$37:$T$1003<>"",ROW($T$37:$T$1003)-ROW($T$37)+1),ROW(11:11))),"")} | Y13: {=IFERROR(INDEX($U$37:$U$1003,SMALL(IF($T$37:$T$1003<>"",ROW($T$37:$T$1003)-ROW($T$37)+1),ROW(11:11))),"")} | Z13: {=IFERROR(INDEX($V$37:$V$1003,SMALL(IF($T$37:$T$1003<>"",ROW($T$37:$T$1003)-ROW($T$37)+1),ROW(11:11))),"")} | AA13: {=IFERROR(INDEX($W$37:$W$1003,SMALL(IF($T$37:$T$1003<>"",ROW($T$37:$T$1003)-ROW($T$37)+1),ROW(11:11))),"")} | AB13: =IF(X13<>"",IF($J$28="Oui",100,AA13),"") | AC13: =IF(X13<>"",(AB13/100 * (1-$P$15)*100),"") | AD13: =IF(X13<>"",IF(AC13<>"",IF(AC13>80,"Validé",IF(AC13<70,"Non Validé","Validé avec réserve")),"Non contrôlé"),"")
D14: Les conditions de transport permettent-elles l'acheminement et la réception des échantillons dans les 24 h ? | L14: Oui | N14: =IF(L14="","",IF(L14="Non",0.1,0)) -> 0 | X14: {=IFERROR(INDEX($T$37:$T$1003,SMALL(IF($T$37:$T$1003<>"",ROW($T$37:$T$1003)-ROW($T$37)+1),ROW(12:12))),"")} | Y14: {=IFERROR(INDEX($U$37:$U$1003,SMALL(IF($T$37:$T$1003<>"",ROW($T$37:$T$1003)-ROW($T$37)+1),ROW(12:12))),"")} | Z14: {=IFERROR(INDEX($V$37:$V$1003,SMALL(IF($T$37:$T$1003<>"",ROW($T$37:$T$1003)-ROW($T$37)+1),ROW(12:12))),"")} | AA14: {=IFERROR(INDEX($W$37:$W$1003,SMALL(IF($T$37:$T$1003<>"",ROW($T$37:$T$1003)-ROW($T$37)+1),ROW(12:12))),"")} | AB14: =IF(X14<>"",IF($J$28="Oui",100,AA14),"") | AC14: =IF(X14<>"",(AB14/100 * (1-$P$15)*100),"") | AD14: =IF(X14<>"",IF(AC14<>"",IF(AC14>80,"Validé",IF(AC14<70,"Non Validé","Validé avec réserve")),"Non contrôlé"),"")
N15: Total pénalité : | P15: =SUM(N11:P14) -> 0 | X15: {=IFERROR(INDEX($T$37:$T$1003,SMALL(IF($T$37:$T$1003<>"",ROW($T$37:$T$1003)-ROW($T$37)+1),ROW(13:13))),"")} | Y15: {=IFERROR(INDEX($U$37:$U$1003,SMALL(IF($T$37:$T$1003<>"",ROW($T$37:$T$1003)-ROW($T$37)+1),ROW(13:13))),"")} | Z15: {=IFERROR(INDEX($V$37:$V$1003,SMALL(IF($T$37:$T$1003<>"",ROW($T$37:$T$1003)-ROW($T$37)+1),ROW(13:13))),"")} | AA15: {=IFERROR(INDEX($W$37:$W$1003,SMALL(IF($T$37:$T$1003<>"",ROW($T$37:$T$1003)-ROW($T$37)+1),ROW(13:13))),"")} | AB15: =IF(X15<>"",IF($J$28="Oui",100,AA15),"") | AC15: =IF(X15<>"",(AB15/100 * (1-$P$15)*100),"") | AD15: =IF(X15<>"",IF(AC15<>"",IF(AC15>80,"Validé",IF(AC15<70,"Non Validé","Validé avec réserve")),"Non contrôlé"),"")
D16: COMMENTAIRES :
X19: {=IFERROR(INDEX($T$37:$T$1003,SMALL(IF($T$37:$T$1003<>"",ROW($T$37:$T$1003)-ROW($T$37)+1),ROW(14:14))),"")} | Y19: {=IFERROR(INDEX($U$37:$U$1003,SMALL(IF($T$37:$T$1003<>"",ROW($T$37:$T$1003)-ROW($T$37)+1),ROW(14:14))),"")} | Z19: {=IFERROR(INDEX($V$37:$V$1003,SMALL(IF($T$37:$T$1003<>"",ROW($T$37:$T$1003)-ROW($T$37)+1),ROW(14:14))),"")} | AA19: {=IFERROR(INDEX($W$37:$W$1003,SMALL(IF($T$37:$T$1003<>"",ROW($T$37:$T$1003)-ROW($T$37)+1),ROW(14:14))),"")} | AB19: =IF(X19<>"",IF($J$28="Oui",100,AA19),"") | AC19: =IF(X19<>"",(AB19/100 * (1-$P$15)*100),"") | AD19: =IF(X19<>"",IF(AC19<>"",IF(AC19>80,"Validé",IF(AC19<70,"Non Validé","Validé avec réserve")),"Non contrôlé"),"")
X20: {=IFERROR(INDEX($T$37:$T$1003,SMALL(IF($T$37:$T$1003<>"",ROW($T$37:$T$1003)-ROW($T$37)+1),ROW(15:15))),"")} | Y20: {=IFERROR(INDEX($U$37:$U$1003,SMALL(IF($T$37:$T$1003<>"",ROW($T$37:$T$1003)-ROW($T$37)+1),ROW(15:15))),"")} | Z20: {=IFERROR(INDEX($V$37:$V$1003,SMALL(IF($T$37:$T$1003<>"",ROW($T$37:$T$1003)-ROW($T$37)+1),ROW(15:15))),"")} | AA20: {=IFERROR(INDEX($W$37:$W$1003,SMALL(IF($T$37:$T$1003<>"",ROW($T$37:$T$1003)-ROW($T$37)+1),ROW(15:15))),"")} | AB20: =IF(X20<>"",IF($J$28="Oui",100,AA20),"") | AC20: =IF(X20<>"",(AB20/100 * (1-$P$15)*100),"") | AD20: =IF(X20<>"",IF(AC20<>"",IF(AC20>80,"Validé",IF(AC20<70,"Non Validé","Validé avec réserve")),"Non contrôlé"),"")
C21: ANALYSES | X21: {=IFERROR(INDEX($T$37:$T$1003,SMALL(IF($T$37:$T$1003<>"",ROW($T$37:$T$1003)-ROW($T$37)+1),ROW(19:19))),"")} | Y21: {=IFERROR(INDEX($U$37:$U$1003,SMALL(IF($T$37:$T$1003<>"",ROW($T$37:$T$1003)-ROW($T$37)+1),ROW(19:19))),"")} | Z21: {=IFERROR(INDEX($V$37:$V$1003,SMALL(IF($T$37:$T$1003<>"",ROW($T$37:$T$1003)-ROW($T$37)+1),ROW(19:19))),"")} | AA21: {=IFERROR(INDEX($W$37:$W$1003,SMALL(IF($T$37:$T$1003<>"",ROW($T$37:$T$1003)-ROW($T$37)+1),ROW(19:19))),"")} | AB21: =IF(X21<>"",IF($J$28="Oui",100,AA21),"") | AC21: =IF(X21<>"",(AB21/100 * (1-$P$15)*100),"") | AD21: =IF(X21<>"",IF(AC21<>"",IF(AC21>80,"Validé",IF(AC21<70,"Non Validé","Validé avec réserve")),"Non contrôlé"),"")
X22: {=IFERROR(INDEX($T$37:$T$1003,SMALL(IF($T$37:$T$1003<>"",ROW($T$37:$T$1003)-ROW($T$37)+1),ROW(20:20))),"")} | Y22: {=IFERROR(INDEX($U$37:$U$1003,SMALL(IF($T$37:$T$1003<>"",ROW($T$37:$T$1003)-ROW($T$37)+1),ROW(20:20))),"")} | Z22: {=IFERROR(INDEX($V$37:$V$1003,SMALL(IF($T$37:$T$1003<>"",ROW($T$37:$T$1003)-ROW($T$37)+1),ROW(20:20))),"")} | AA22: {=IFERROR(INDEX($W$37:$W$1003,SMALL(IF($T$37:$T$1003<>"",ROW($T$37:$T$1003)-ROW($T$37)+1),ROW(20:20))),"")} | AB22: =IF(X22<>"",IF($J$28="Oui",100,AA22),"") | AC22: =IF(X22<>"",(AB22/100 * (1-$P$15)*100),"") | AD22: =IF(X22<>"",IF(AC22<>"",IF(AC22>80,"Validé",IF(AC22<70,"Non Validé","Validé avec réserve")),"Non contrôlé"),"")
D23: Les analyses sont-elles correctement effectuées ? | X23: {=IFERROR(INDEX($T$37:$T$1003,SMALL(IF($T$37:$T$1003<>"",ROW($T$37:$T$1003)-ROW($T$37)+1),ROW(21:21))),"")} | Y23: {=IFERROR(INDEX($U$37:$U$1003,SMALL(IF($T$37:$T$1003<>"",ROW($T$37:$T$1003)-ROW($T$37)+1),ROW(21:21))),"")} | Z23: {=IFERROR(INDEX($V$37:$V$1003,SMALL(IF($T$37:$T$1003<>"",ROW($T$37:$T$1003)-ROW($T$37)+1),ROW(21:21))),"")} | AA23: {=IFERROR(INDEX($W$37:$W$1003,SMALL(IF($T$37:$T$1003<>"",ROW($T$37:$T$1003)-ROW($T$37)+1),ROW(21:21))),"")} | AB23: =IF(X23<>"",IF($J$28="Oui",100,AA23),"") | AC23: =IF(X23<>"",(AB23/100 * (1-$P$15)*100),"") | AD23: =IF(X23<>"",IF(AC23<>"",IF(AC23>80,"Validé",IF(AC23<70,"Non Validé","Validé avec réserve")),"Non contrôlé"),"")
D24: Nom du(des) laboratoire(s) réalisant les analyses de la matrice eau | X24: {=IFERROR(INDEX($T$37:$T$1003,SMALL(IF($T$37:$T$1003<>"",ROW($T$37:$T$1003)-ROW($T$37)+1),ROW(22:22))),"")} | Y24: {=IFERROR(INDEX($U$37:$U$1003,SMALL(IF($T$37:$T$1003<>"",ROW($T$37:$T$1003)-ROW($T$37)+1),ROW(22:22))),"")} | Z24: {=IFERROR(INDEX($V$37:$V$1003,SMALL(IF($T$37:$T$1003<>"",ROW($T$37:$T$1003)-ROW($T$37)+1),ROW(22:22))),"")} | AA24: {=IFERROR(INDEX($W$37:$W$1003,SMALL(IF($T$37:$T$1003<>"",ROW($T$37:$T$1003)-ROW($T$37)+1),ROW(22:22))),"")} | AB24: =IF(X24<>"",IF($J$28="Oui",100,AA24),"") | AC24: =IF(X24<>"",(AB24/100 * (1-$P$15)*100),"") | AD24: =IF(X24<>"",IF(AC24<>"",IF(AC24>80,"Validé",IF(AC24<70,"Non Validé","Validé avec réserve")),"Non contrôlé"),"")
D25: Nom du(des) laboratoire(s) réalisant l'analyse de la siccité des boues et des matières séches | X25: {=IFERROR(INDEX($T$37:$T$1003,SMALL(IF($T$37:$T$1003<>"",ROW($T$37:$T$1003)-ROW($T$37)+1),ROW(23:23))),"")} | Y25: {=IFERROR(INDEX($U$37:$U$1003,SMALL(IF($T$37:$T$1003<>"",ROW($T$37:$T$1003)-ROW($T$37)+1),ROW(23:23))),"")} | Z25: {=IFERROR(INDEX($V$37:$V$1003,SMALL(IF($T$37:$T$1003<>"",ROW($T$37:$T$1003)-ROW($T$37)+1),ROW(23:23))),"")} | AA25: {=IFERROR(INDEX($W$37:$W$1003,SMALL(IF($T$37:$T$1003<>"",ROW($T$37:$T$1003)-ROW($T$37)+1),ROW(23:23))),"")} | AB25: =IF(X25<>"",IF($J$28="Oui",100,AA25),"") | AC25: =IF(X25<>"",(AB25/100 * (1-$P$15)*100),"") | AD25: =IF(X25<>"",IF(AC25<>"",IF(AC25>80,"Validé",IF(AC25<70,"Non Validé","Validé avec réserve")),"Non contrôlé"),"")
D26: Le(s) laboratoire(s) est/sont-il(s) agréé(s) au titre du code de l’environnement pour l'ensemble des paramètres de la matrice eau résiduaire? | J26: Non | X26: {=IFERROR(INDEX($T$37:$T$1003,SMALL(IF($T$37:$T$1003<>"",ROW($T$37:$T$1003)-ROW($T$37)+1),ROW(24:24))),"")} | Y26: {=IFERROR(INDEX($U$37:$U$1003,SMALL(IF($T$37:$T$1003<>"",ROW($T$37:$T$1003)-ROW($T$37)+1),ROW(24:24))),"")} | Z26: {=IFERROR(INDEX($V$37:$V$1003,SMALL(IF($T$37:$T$1003<>"",ROW($T$37:$T$1003)-ROW($T$37)+1),ROW(24:24))),"")} | AA26: {=IFERROR(INDEX($W$37:$W$1003,SMALL(IF($T$37:$T$1003<>"",ROW($T$37:$T$1003)-ROW($T$37)+1),ROW(24:24))),"")} | AB26: =IF(X26<>"",IF($J$28="Oui",100,AA26),"") | AC26: =IF(X26<>"",(AB26/100 * (1-$P$15)*100),"") | AD26: =IF(X26<>"",IF(AC26<>"",IF(AC26>80,"Validé",IF(AC26<70,"Non Validé","Validé avec réserve")),"Non contrôlé"),"")
D27: A défaut, est ce que le laboratoire réalise un exercice concluant d’intercalibration avec un laboratoire agréé ? | J27: Non | X27: {=IFERROR(INDEX($T$37:$T$1003,SMALL(IF($T$37:$T$1003<>"",ROW($T$37:$T$1003)-ROW($T$37)+1),ROW(25:25))),"")} | Y27: {=IFERROR(INDEX($U$37:$U$1003,SMALL(IF($T$37:$T$1003<>"",ROW($T$37:$T$1003)-ROW($T$37)+1),ROW(25:25))),"")} | Z27: {=IFERROR(INDEX($V$37:$V$1003,SMALL(IF($T$37:$T$1003<>"",ROW($T$37:$T$1003)-ROW($T$37)+1),ROW(25:25))),"")} | AA27: {=IFERROR(INDEX($W$37:$W$1003,SMALL(IF($T$37:$T$1003<>"",ROW($T$37:$T$1003)-ROW($T$37)+1),ROW(25:25))),"")} | AB27: =IF(X27<>"",IF($J$28="Oui",100,AA27),"") | AC27: =IF(X27<>"",(AB27/100 * (1-$P$15)*100),"") | AD27: =IF(X27<>"",IF(AC27<>"",IF(AC27>80,"Validé",IF(AC27<70,"Non Validé","Validé avec réserve")),"Non contrôlé"),"")
D28: Coefficient fixé à 100 en cas de réalisation de l'ensemble des analyses de la matrice eau résiduaire par un laboratoire agréé au titre du code de l’environnement, ou à défaut procédant annuellement à un exercice concluant d’intercalibration avec un laboratoire agréé : | J28: Non | K28: Nombre d'analyses ayant fait l'objet d'un comparatif analytique : | O28: =SUM(U:U) -> 0 | P28: Coefficient sur les analyses | Q28: =IF(J28="Oui",100,IF(O28>0, (O29 / O28)*100,0)) -> 0 | X28: {=IFERROR(INDEX($T$37:$T$1003,SMALL(IF($T$37:$T$1003<>"",ROW($T$37:$T$1003)-ROW($T$37)+1),ROW(26:26))),"")} | Y28: {=IFERROR(INDEX($U$37:$U$1003,SMALL(IF($T$37:$T$1003<>"",ROW($T$37:$T$1003)-ROW($T$37)+1),ROW(26:26))),"")} | Z28: {=IFERROR(INDEX($V$37:$V$1003,SMALL(IF($T$37:$T$1003<>"",ROW($T$37:$T$1003)-ROW($T$37)+1),ROW(26:26))),"")} | AA28: {=IFERROR(INDEX($W$37:$W$1003,SMALL(IF($T$37:$T$1003<>"",ROW($T$37:$T$1003)-ROW($T$37)+1),ROW(26:26))),"")} | AB28: =IF(X28<>"",IF($J$28="Oui",100,AA28),"") | AC28: =IF(X28<>"",(AB28/100 * (1-$P$15)*100),"") | AD28: =IF(X28<>"",IF(AC28<>"",IF(AC28>80,"Validé",IF(AC28<70,"Non Validé","Validé avec réserve")),"Non contrôlé"),"")
K29: Nombre de résultats analytiques conformes : | O29: =SUM(V:V) -> 0 | X29: {=IFERROR(INDEX($T$37:$T$1003,SMALL(IF($T$37:$T$1003<>"",ROW($T$37:$T$1003)-ROW($T$37)+1),ROW(27:27))),"")} | Y29: {=IFERROR(INDEX($U$37:$U$1003,SMALL(IF($T$37:$T$1003<>"",ROW($T$37:$T$1003)-ROW($T$37)+1),ROW(27:27))),"")} | Z29: {=IFERROR(INDEX($V$37:$V$1003,SMALL(IF($T$37:$T$1003<>"",ROW($T$37:$T$1003)-ROW($T$37)+1),ROW(27:27))),"")} | AA29: {=IFERROR(INDEX($W$37:$W$1003,SMALL(IF($T$37:$T$1003<>"",ROW($T$37:$T$1003)-ROW($T$37)+1),ROW(27:27))),"")} | AB29: =IF(X29<>"",IF($J$28="Oui",100,AA29),"") | AC29: =IF(X29<>"",(AB29/100 * (1-$P$15)*100),"") | AD29: =IF(X29<>"",IF(AC29<>"",IF(AC29>80,"Validé",IF(AC29<70,"Non Validé","Validé avec réserve")),"Non contrôlé"),"")
X30: {=IFERROR(INDEX($T$37:$T$1003,SMALL(IF($T$37:$T$1003<>"",ROW($T$37:$T$1003)-ROW($T$37)+1),ROW(28:28))),"")} | Y30: {=IFERROR(INDEX($U$37:$U$1003,SMALL(IF($T$37:$T$1003<>"",ROW($T$37:$T$1003)-ROW($T$37)+1),ROW(28:28))),"")} | Z30: {=IFERROR(INDEX($V$37:$V$1003,SMALL(IF($T$37:$T$1003<>"",ROW($T$37:$T$1003)-ROW($T$37)+1),ROW(28:28))),"")} | AA30: {=IFERROR(INDEX($W$37:$W$1003,SMALL(IF($T$37:$T$1003<>"",ROW($T$37:$T$1003)-ROW($T$37)+1),ROW(28:28))),"")} | AB30: =IF(X30<>"",IF($J$28="Oui",100,AA30),"") | AC30: =IF(X30<>"",(AB30/100 * (1-$P$15)*100),"") | AD30: =IF(X30<>"",IF(AC30<>"",IF(AC30>80,"Validé",IF(AC30<70,"Non Validé","Validé avec réserve")),"Non contrôlé"),"")
D31: Score total de la chaine analytique (échantillonnage & analyses) : | J31: =(Q28/100 * (1-P15)*100) -> 0 | X31: {=IFERROR(INDEX($T$37:$T$1003,SMALL(IF($T$37:$T$1003<>"",ROW($T$37:$T$1003)-ROW($T$37)+1),ROW(29:29))),"")} | Y31: {=IFERROR(INDEX($U$37:$U$1003,SMALL(IF($T$37:$T$1003<>"",ROW($T$37:$T$1003)-ROW($T$37)+1),ROW(29:29))),"")} | Z31: {=IFERROR(INDEX($V$37:$V$1003,SMALL(IF($T$37:$T$1003<>"",ROW($T$37:$T$1003)-ROW($T$37)+1),ROW(29:29))),"")} | AA31: {=IFERROR(INDEX($W$37:$W$1003,SMALL(IF($T$37:$T$1003<>"",ROW($T$37:$T$1003)-ROW($T$37)+1),ROW(29:29))),"")} | AB31: =IF(X31<>"",IF($J$28="Oui",100,AA31),"") | AC31: =IF(X31<>"",(AB31/100 * (1-$P$15)*100),"") | AD31: =IF(X31<>"",IF(AC31<>"",IF(AC31>80,"Validé",IF(AC31<70,"Non Validé","Validé avec réserve")),"Non contrôlé"),"")
X32: {=IFERROR(INDEX($T$37:$T$1003,SMALL(IF($T$37:$T$1003<>"",ROW($T$37:$T$1003)-ROW($T$37)+1),ROW(30:30))),"")} | Y32: {=IFERROR(INDEX($U$37:$U$1003,SMALL(IF($T$37:$T$1003<>"",ROW($T$37:$T$1003)-ROW($T$37)+1),ROW(30:30))),"")} | Z32: {=IFERROR(INDEX($V$37:$V$1003,SMALL(IF($T$37:$T$1003<>"",ROW($T$37:$T$1003)-ROW($T$37)+1),ROW(30:30))),"")} | AA32: {=IFERROR(INDEX($W$37:$W$1003,SMALL(IF($T$37:$T$1003<>"",ROW($T$37:$T$1003)-ROW($T$37)+1),ROW(30:30))),"")} | AB32: =IF(X32<>"",IF($J$28="Oui",100,AA32),"") | AC32: =IF(X32<>"",(AB32/100 * (1-$P$15)*100),"") | AD32: =IF(X32<>"",IF(AC32<>"",IF(AC32>80,"Validé",IF(AC32<70,"Non Validé","Validé avec réserve")),"Non contrôlé"),"")
D33: COMMENTAIRES : | X33: {=IFERROR(INDEX($T$37:$T$1003,SMALL(IF($T$37:$T$1003<>"",ROW($T$37:$T$1003)-ROW($T$37)+1),ROW(31:31))),"")} | Y33: {=IFERROR(INDEX($U$37:$U$1003,SMALL(IF($T$37:$T$1003<>"",ROW($T$37:$T$1003)-ROW($T$37)+1),ROW(31:31))),"")} | Z33: {=IFERROR(INDEX($V$37:$V$1003,SMALL(IF($T$37:$T$1003<>"",ROW($T$37:$T$1003)-ROW($T$37)+1),ROW(31:31))),"")} | AA33: {=IFERROR(INDEX($W$37:$W$1003,SMALL(IF($T$37:$T$1003<>"",ROW($T$37:$T$1003)-ROW($T$37)+1),ROW(31:31))),"")} | AB33: =IF(X33<>"",IF($J$28="Oui",100,AA33),"") | AC33: =IF(X33<>"",(AB33/100 * (1-$P$15)*100),"") | AD33: =IF(X33<>"",IF(AC33<>"",IF(AC33>80,"Validé",IF(AC33<70,"Non Validé","Validé avec réserve")),"Non contrôlé"),"")
X34: {=IFERROR(INDEX($T$37:$T$1003,SMALL(IF($T$37:$T$1003<>"",ROW($T$37:$T$1003)-ROW($T$37)+1),ROW(32:32))),"")} | Y34: {=IFERROR(INDEX($U$37:$U$1003,SMALL(IF($T$37:$T$1003<>"",ROW($T$37:$T$1003)-ROW($T$37)+1),ROW(32:32))),"")} | Z34: {=IFERROR(INDEX($V$37:$V$1003,SMALL(IF($T$37:$T$1003<>"",ROW($T$37:$T$1003)-ROW($T$37)+1),ROW(32:32))),"")} | AA34: {=IFERROR(INDEX($W$37:$W$1003,SMALL(IF($T$37:$T$1003<>"",ROW($T$37:$T$1003)-ROW($T$37)+1),ROW(32:32))),"")} | AB34: =IF(X34<>"",IF($J$28="Oui",100,AA34),"") | AC34: =IF(X34<>"",(AB34/100 * (1-$P$15)*100),"") | AD34: =IF(X34<>"",IF(AC34<>"",IF(AC34>80,"Validé",IF(AC34<70,"Non Validé","Validé avec réserve")),"Non contrôlé"),"")
X35: {=IFERROR(INDEX($T$37:$T$1003,SMALL(IF($T$37:$T$1003<>"",ROW($T$37:$T$1003)-ROW($T$37)+1),ROW(33:33))),"")} | Y35: {=IFERROR(INDEX($U$37:$U$1003,SMALL(IF($T$37:$T$1003<>"",ROW($T$37:$T$1003)-ROW($T$37)+1),ROW(33:33))),"")} | Z35: {=IFERROR(INDEX($V$37:$V$1003,SMALL(IF($T$37:$T$1003<>"",ROW($T$37:$T$1003)-ROW($T$37)+1),ROW(33:33))),"")} | AA35: {=IFERROR(INDEX($W$37:$W$1003,SMALL(IF($T$37:$T$1003<>"",ROW($T$37:$T$1003)-ROW($T$37)+1),ROW(33:33))),"")} | AB35: =IF(X35<>"",IF($J$28="Oui",100,AA35),"") | AC35: =IF(X35<>"",(AB35/100 * (1-$P$15)*100),"") | AD35: =IF(X35<>"",IF(AC35<>"",IF(AC35>80,"Validé",IF(AC35<70,"Non Validé","Validé avec réserve")),"Non contrôlé"),"")
C37: COMPARATIF ANALYTIQUE | M37: (Dupliquer ce bloc en cas de comparatif multiple)
D38: Veuillez saisir les comparatifs analytiques
D39: Informations sur le comparatif
D40: Préleveur : | K40: Date du comparatif :
D41: Le comparatif est-il effectué à partir des prélévements d'une autre station ? (si oui, précisez la station) | K41: Nom de la station :
K42: Code de la station :
D44: Résultats du comparatif
D45: Paramètres | F45: LQ en mg/l | G45: Laboratoire du MO/exploitant | I45: COFRAC | J45: Laboratoire de contrôle | L45: COFRAC | M45: NB analyses | O45: Nb conformes
M46: =COUNT(G48:H59) -> 0 | O46: =COUNTIF(O48:P59,"=oui") -> 0 | T46: =IF(G40<>"",G40,"") | U46: =IF(T46<>"",M46,"") | V46: =IF(T46<>"",O46,"") | W46: =IF(M46>0,100*(O46/M46),"")
M47: Ecart (%) | O47: Conformité
D48: DBO5 | F48: =VLOOKUP(D48, 'SeuilsComparaison-EMT'!$C$5:$E$28, 3, FALSE) -> 3 | M48: =IF(OR(J48="",G48=""),"",IF(ISERROR(VLOOKUP(D48,'SeuilsComparaison-EMT'!$C$5:$J$25,4,FALSE)),"-",IF(OR(IF(ISTEXT(J48)=TRUE,SUBSTITUTE(J48,"<","",1)*1,J48)>VLOOKUP(D48,'SeuilsComparaison-EMT'!$C$5:$J$25,4,FALSE),IF(ISTEXT(G48)=TRUE,SUBSTITUTE(G48,"<","",1)*1,G48)>VLOOKUP(D48,'SeuilsComparaison-EMT'!$C$5:$J$25,4,FALSE)=TRUE),(IF(ISTEXT(G48)=TRUE,SUBSTITUTE(G48,"<","",1)*1,G48)-((IF(ISTEXT(G48)=TRUE,SUBSTITUTE(G48,"<","",1)*1,G48)+IF(ISTEXT(J48)=TRUE,SUBSTITUTE(J48,"<","",1)*1,J48))/2))/((IF(ISTEXT(G48)=TRUE,SUBSTITUTE(G48,"<","",1)*1,G48)+IF(ISTEXT(J48)=TRUE,SUBSTITUTE(J48,"<","",1),J48))/2),"-"))) | O48: =IF(OR(G48="",J48=""),"",IF(AND(I48="Oui",L48="Oui"),"Oui",IF(M48="-","Oui",IF(OR(J48>VLOOKUP($D48,'SeuilsComparaison-EMT'!$C$5:$J$27,4,FALSE),G48>VLOOKUP($D48,'SeuilsComparaison-EMT'!$C$5:$J$27,4,FALSE)=TRUE),IF(J48<=VLOOKUP($D48,'SeuilsComparaison-EMT'!$C$5:$J$27,5,FALSE),IF(ABS(M48)<=VLOOKUP($D48,'SeuilsComparaison-EMT'!$C$5:$J$27,6,FALSE),"Oui","Non"),IF(ABS(M48)<=VLOOKUP($D48,'SeuilsComparaison-EMT'!$C$5:$J$27,8,FALSE),"Oui","Non")),"Oui"))))
D49: DCO | F49: =VLOOKUP(D49, 'SeuilsComparaison-EMT'!$C$5:$E$28, 3, FALSE) -> 30 | M49: =IF(OR(J49="",G49=""),"",IF(ISERROR(VLOOKUP(D49,'SeuilsComparaison-EMT'!$C$5:$J$25,4,FALSE)),"-",IF(OR(IF(ISTEXT(J49)=TRUE,SUBSTITUTE(J49,"<","",1)*1,J49)>VLOOKUP(D49,'SeuilsComparaison-EMT'!$C$5:$J$25,4,FALSE),IF(ISTEXT(G49)=TRUE,SUBSTITUTE(G49,"<","",1)*1,G49)>VLOOKUP(D49,'SeuilsComparaison-EMT'!$C$5:$J$25,4,FALSE)=TRUE),(IF(ISTEXT(G49)=TRUE,SUBSTITUTE(G49,"<","",1)*1,G49)-((IF(ISTEXT(G49)=TRUE,SUBSTITUTE(G49,"<","",1)*1,G49)+IF(ISTEXT(J49)=TRUE,SUBSTITUTE(J49,"<","",1)*1,J49))/2))/((IF(ISTEXT(G49)=TRUE,SUBSTITUTE(G49,"<","",1)*1,G49)+IF(ISTEXT(J49)=TRUE,SUBSTITUTE(J49,"<","",1),J49))/2),"-"))) | O49: =IF(OR(G49="",J49=""),"",IF(AND(I49="Oui",L49="Oui"),"Oui",IF(M49="-","Oui",IF(OR(J49>VLOOKUP($D49,'SeuilsComparaison-EMT'!$C$5:$J$27,4,FALSE),G49>VLOOKUP($D49,'SeuilsComparaison-EMT'!$C$5:$J$27,4,FALSE)=TRUE),IF(J49<=VLOOKUP($D49,'SeuilsComparaison-EMT'!$C$5:$J$27,5,FALSE),IF(ABS(M49)<=VLOOKUP($D49,'SeuilsComparaison-EMT'!$C$5:$J$27,6,FALSE),"Oui","Non"),IF(ABS(M49)<=VLOOKUP($D49,'SeuilsComparaison-EMT'!$C$5:$J$27,8,FALSE),"Oui","Non")),"Oui"))))
D50: ST DCO | F50: =VLOOKUP(D50, 'SeuilsComparaison-EMT'!$C$5:$E$28, 3, FALSE) -> 10 | M50: =IF(OR(J50="",G50=""),"",IF(ISERROR(VLOOKUP(D50,'SeuilsComparaison-EMT'!$C$5:$J$25,4,FALSE)),"-",IF(OR(IF(ISTEXT(J50)=TRUE,SUBSTITUTE(J50,"<","",1)*1,J50)>VLOOKUP(D50,'SeuilsComparaison-EMT'!$C$5:$J$25,4,FALSE),IF(ISTEXT(G50)=TRUE,SUBSTITUTE(G50,"<","",1)*1,G50)>VLOOKUP(D50,'SeuilsComparaison-EMT'!$C$5:$J$25,4,FALSE)=TRUE),(IF(ISTEXT(G50)=TRUE,SUBSTITUTE(G50,"<","",1)*1,G50)-((IF(ISTEXT(G50)=TRUE,SUBSTITUTE(G50,"<","",1)*1,G50)+IF(ISTEXT(J50)=TRUE,SUBSTITUTE(J50,"<","",1)*1,J50))/2))/((IF(ISTEXT(G50)=TRUE,SUBSTITUTE(G50,"<","",1)*1,G50)+IF(ISTEXT(J50)=TRUE,SUBSTITUTE(J50,"<","",1),J50))/2),"-"))) | O50: =IF(OR(G50="",J50=""),"",IF(AND(I50="Oui",L50="Oui"),"Oui",IF(M50="-","Oui",IF(OR(J50>VLOOKUP($D50,'SeuilsComparaison-EMT'!$C$5:$J$27,4,FALSE),G50>VLOOKUP($D50,'SeuilsComparaison-EMT'!$C$5:$J$27,4,FALSE)=TRUE),IF(J50<=VLOOKUP($D50,'SeuilsComparaison-EMT'!$C$5:$J$27,5,FALSE),IF(ABS(M50)<=VLOOKUP($D50,'SeuilsComparaison-EMT'!$C$5:$J$27,6,FALSE),"Oui","Non"),IF(ABS(M50)<=VLOOKUP($D50,'SeuilsComparaison-EMT'!$C$5:$J$27,8,FALSE),"Oui","Non")),"Oui"))))
D51: MEST | F51: =VLOOKUP(D51, 'SeuilsComparaison-EMT'!$C$5:$E$28, 3, FALSE) -> 2 | M51: =IF(OR(J51="",G51=""),"",IF(ISERROR(VLOOKUP(D51,'SeuilsComparaison-EMT'!$C$5:$J$25,4,FALSE)),"-",IF(OR(IF(ISTEXT(J51)=TRUE,SUBSTITUTE(J51,"<","",1)*1,J51)>VLOOKUP(D51,'SeuilsComparaison-EMT'!$C$5:$J$25,4,FALSE),IF(ISTEXT(G51)=TRUE,SUBSTITUTE(G51,"<","",1)*1,G51)>VLOOKUP(D51,'SeuilsComparaison-EMT'!$C$5:$J$25,4,FALSE)=TRUE),(IF(ISTEXT(G51)=TRUE,SUBSTITUTE(G51,"<","",1)*1,G51)-((IF(ISTEXT(G51)=TRUE,SUBSTITUTE(G51,"<","",1)*1,G51)+IF(ISTEXT(J51)=TRUE,SUBSTITUTE(J51,"<","",1)*1,J51))/2))/((IF(ISTEXT(G51)=TRUE,SUBSTITUTE(G51,"<","",1)*1,G51)+IF(ISTEXT(J51)=TRUE,SUBSTITUTE(J51,"<","",1),J51))/2),"-"))) | O51: =IF(OR(G51="",J51=""),"",IF(AND(I51="Oui",L51="Oui"),"Oui",IF(M51="-","Oui",IF(OR(J51>VLOOKUP($D51,'SeuilsComparaison-EMT'!$C$5:$J$27,4,FALSE),G51>VLOOKUP($D51,'SeuilsComparaison-EMT'!$C$5:$J$27,4,FALSE)=TRUE),IF(J51<=VLOOKUP($D51,'SeuilsComparaison-EMT'!$C$5:$J$27,5,FALSE),IF(ABS(M51)<=VLOOKUP($D51,'SeuilsComparaison-EMT'!$C$5:$J$27,6,FALSE),"Oui","Non"),IF(ABS(M51)<=VLOOKUP($D51,'SeuilsComparaison-EMT'!$C$5:$J$27,8,FALSE),"Oui","Non")),"Oui"))))
D52: NKJ (N) | F52: =VLOOKUP(D52, 'SeuilsComparaison-EMT'!$C$5:$E$28, 3, FALSE) -> 0.5 | M52: =IF(OR(J52="",G52=""),"",IF(ISERROR(VLOOKUP(D52,'SeuilsComparaison-EMT'!$C$5:$J$25,4,FALSE)),"-",IF(OR(IF(ISTEXT(J52)=TRUE,SUBSTITUTE(J52,"<","",1)*1,J52)>VLOOKUP(D52,'SeuilsComparaison-EMT'!$C$5:$J$25,4,FALSE),IF(ISTEXT(G52)=TRUE,SUBSTITUTE(G52,"<","",1)*1,G52)>VLOOKUP(D52,'SeuilsComparaison-EMT'!$C$5:$J$25,4,FALSE)=TRUE),(IF(ISTEXT(G52)=TRUE,SUBSTITUTE(G52,"<","",1)*1,G52)-((IF(ISTEXT(G52)=TRUE,SUBSTITUTE(G52,"<","",1)*1,G52)+IF(ISTEXT(J52)=TRUE,SUBSTITUTE(J52,"<","",1)*1,J52))/2))/((IF(ISTEXT(G52)=TRUE,SUBSTITUTE(G52,"<","",1)*1,G52)+IF(ISTEXT(J52)=TRUE,SUBSTITUTE(J52,"<","",1),J52))/2),"-"))) | O52: =IF(OR(G52="",J52=""),"",IF(AND(I52="Oui",L52="Oui"),"Oui",IF(M52="-","Oui",IF(OR(J52>VLOOKUP($D52,'SeuilsComparaison-EMT'!$C$5:$J$27,4,FALSE),G52>VLOOKUP($D52,'SeuilsComparaison-EMT'!$C$5:$J$27,4,FALSE)=TRUE),IF(J52<=VLOOKUP($D52,'SeuilsComparaison-EMT'!$C$5:$J$27,5,FALSE),IF(ABS(M52)<=VLOOKUP($D52,'SeuilsComparaison-EMT'!$C$5:$J$27,6,FALSE),"Oui","Non"),IF(ABS(M52)<=VLOOKUP($D52,'SeuilsComparaison-EMT'!$C$5:$J$27,8,FALSE),"Oui","Non")),"Oui"))))
D53: NGL | F53: =VLOOKUP(D53, 'SeuilsComparaison-EMT'!$C$5:$E$28, 3, FALSE) -> 1 | M53: =IF(OR(J53="",G53=""),"",IF(ISERROR(VLOOKUP(D53,'SeuilsComparaison-EMT'!$C$5:$J$25,4,FALSE)),"-",IF(OR(IF(ISTEXT(J53)=TRUE,SUBSTITUTE(J53,"<","",1)*1,J53)>VLOOKUP(D53,'SeuilsComparaison-EMT'!$C$5:$J$25,4,FALSE),IF(ISTEXT(G53)=TRUE,SUBSTITUTE(G53,"<","",1)*1,G53)>VLOOKUP(D53,'SeuilsComparaison-EMT'!$C$5:$J$25,4,FALSE)=TRUE),(IF(ISTEXT(G53)=TRUE,SUBSTITUTE(G53,"<","",1)*1,G53)-((IF(ISTEXT(G53)=TRUE,SUBSTITUTE(G53,"<","",1)*1,G53)+IF(ISTEXT(J53)=TRUE,SUBSTITUTE(J53,"<","",1)*1,J53))/2))/((IF(ISTEXT(G53)=TRUE,SUBSTITUTE(G53,"<","",1)*1,G53)+IF(ISTEXT(J53)=TRUE,SUBSTITUTE(J53,"<","",1),J53))/2),"-"))) | O53: =IF(OR(G53="",J53=""),"",IF(AND(I53="Oui",L53="Oui"),"Oui",IF(M53="-","Oui",IF(OR(J53>VLOOKUP($D53,'SeuilsComparaison-EMT'!$C$5:$J$27,4,FALSE),G53>VLOOKUP($D53,'SeuilsComparaison-EMT'!$C$5:$J$27,4,FALSE)=TRUE),IF(J53<=VLOOKUP($D53,'SeuilsComparaison-EMT'!$C$5:$J$27,5,FALSE),IF(ABS(M53)<=VLOOKUP($D53,'SeuilsComparaison-EMT'!$C$5:$J$27,6,FALSE),"Oui","Non"),IF(ABS(M53)<=VLOOKUP($D53,'SeuilsComparaison-EMT'!$C$5:$J$27,8,FALSE),"Oui","Non")),"Oui"))))
D54: NH4 (NH4) | F54: =VLOOKUP(D54, 'SeuilsComparaison-EMT'!$C$5:$E$28, 3, FALSE) -> 0.5 | M54: =IF(OR(J54="",G54=""),"",IF(ISERROR(VLOOKUP(D54,'SeuilsComparaison-EMT'!$C$5:$J$25,4,FALSE)),"-",IF(OR(IF(ISTEXT(J54)=TRUE,SUBSTITUTE(J54,"<","",1)*1,J54)>VLOOKUP(D54,'SeuilsComparaison-EMT'!$C$5:$J$25,4,FALSE),IF(ISTEXT(G54)=TRUE,SUBSTITUTE(G54,"<","",1)*1,G54)>VLOOKUP(D54,'SeuilsComparaison-EMT'!$C$5:$J$25,4,FALSE)=TRUE),(IF(ISTEXT(G54)=TRUE,SUBSTITUTE(G54,"<","",1)*1,G54)-((IF(ISTEXT(G54)=TRUE,SUBSTITUTE(G54,"<","",1)*1,G54)+IF(ISTEXT(J54)=TRUE,SUBSTITUTE(J54,"<","",1)*1,J54))/2))/((IF(ISTEXT(G54)=TRUE,SUBSTITUTE(G54,"<","",1)*1,G54)+IF(ISTEXT(J54)=TRUE,SUBSTITUTE(J54,"<","",1),J54))/2),"-"))) | O54: =IF(OR(G54="",J54=""),"",IF(AND(I54="Oui",L54="Oui"),"Oui",IF(M54="-","Oui",IF(OR(J54>VLOOKUP($D54,'SeuilsComparaison-EMT'!$C$5:$J$27,4,FALSE),G54>VLOOKUP($D54,'SeuilsComparaison-EMT'!$C$5:$J$27,4,FALSE)=TRUE),IF(J54<=VLOOKUP($D54,'SeuilsComparaison-EMT'!$C$5:$J$27,5,FALSE),IF(ABS(M54)<=VLOOKUP($D54,'SeuilsComparaison-EMT'!$C$5:$J$27,6,FALSE),"Oui","Non"),IF(ABS(M54)<=VLOOKUP($D54,'SeuilsComparaison-EMT'!$C$5:$J$27,8,FALSE),"Oui","Non")),"Oui"))))
D55: NO2 (NO2) | F55: =VLOOKUP(D55, 'SeuilsComparaison-EMT'!$C$5:$E$28, 3, FALSE) -> 0.05 | M55: =IF(OR(J55="",G55=""),"",IF(ISERROR(VLOOKUP(D55,'SeuilsComparaison-EMT'!$C$5:$J$25,4,FALSE)),"-",IF(OR(IF(ISTEXT(J55)=TRUE,SUBSTITUTE(J55,"<","",1)*1,J55)>VLOOKUP(D55,'SeuilsComparaison-EMT'!$C$5:$J$25,4,FALSE),IF(ISTEXT(G55)=TRUE,SUBSTITUTE(G55,"<","",1)*1,G55)>VLOOKUP(D55,'SeuilsComparaison-EMT'!$C$5:$J$25,4,FALSE)=TRUE),(IF(ISTEXT(G55)=TRUE,SUBSTITUTE(G55,"<","",1)*1,G55)-((IF(ISTEXT(G55)=TRUE,SUBSTITUTE(G55,"<","",1)*1,G55)+IF(ISTEXT(J55)=TRUE,SUBSTITUTE(J55,"<","",1)*1,J55))/2))/((IF(ISTEXT(G55)=TRUE,SUBSTITUTE(G55,"<","",1)*1,G55)+IF(ISTEXT(J55)=TRUE,SUBSTITUTE(J55,"<","",1),J55))/2),"-"))) | O55: =IF(OR(G55="",J55=""),"",IF(AND(I55="Oui",L55="Oui"),"Oui",IF(M55="-","Oui",IF(OR(J55>VLOOKUP($D55,'SeuilsComparaison-EMT'!$C$5:$J$27,4,FALSE),G55>VLOOKUP($D55,'SeuilsComparaison-EMT'!$C$5:$J$27,4,FALSE)=TRUE),IF(J55<=VLOOKUP($D55,'SeuilsComparaison-EMT'!$C$5:$J$27,5,FALSE),IF(ABS(M55)<=VLOOKUP($D55,'SeuilsComparaison-EMT'!$C$5:$J$27,6,FALSE),"Oui","Non"),IF(ABS(M55)<=VLOOKUP($D55,'SeuilsComparaison-EMT'!$C$5:$J$27,8,FALSE),"Oui","Non")),"Oui"))))
D56: NO3 (NO3) | F56: =VLOOKUP(D56, 'SeuilsComparaison-EMT'!$C$5:$E$28, 3, FALSE) -> 1 | M56: =IF(OR(J56="",G56=""),"",IF(ISERROR(VLOOKUP(D56,'SeuilsComparaison-EMT'!$C$5:$J$25,4,FALSE)),"-",IF(OR(IF(ISTEXT(J56)=TRUE,SUBSTITUTE(J56,"<","",1)*1,J56)>VLOOKUP(D56,'SeuilsComparaison-EMT'!$C$5:$J$25,4,FALSE),IF(ISTEXT(G56)=TRUE,SUBSTITUTE(G56,"<","",1)*1,G56)>VLOOKUP(D56,'SeuilsComparaison-EMT'!$C$5:$J$25,4,FALSE)=TRUE),(IF(ISTEXT(G56)=TRUE,SUBSTITUTE(G56,"<","",1)*1,G56)-((IF(ISTEXT(G56)=TRUE,SUBSTITUTE(G56,"<","",1)*1,G56)+IF(ISTEXT(J56)=TRUE,SUBSTITUTE(J56,"<","",1)*1,J56))/2))/((IF(ISTEXT(G56)=TRUE,SUBSTITUTE(G56,"<","",1)*1,G56)+IF(ISTEXT(J56)=TRUE,SUBSTITUTE(J56,"<","",1),J56))/2),"-"))) | O56: =IF(OR(G56="",J56=""),"",IF(AND(I56="Oui",L56="Oui"),"Oui",IF(M56="-","Oui",IF(OR(J56>VLOOKUP($D56,'SeuilsComparaison-EMT'!$C$5:$J$27,4,FALSE),G56>VLOOKUP($D56,'SeuilsComparaison-EMT'!$C$5:$J$27,4,FALSE)=TRUE),IF(J56<=VLOOKUP($D56,'SeuilsComparaison-EMT'!$C$5:$J$27,5,FALSE),IF(ABS(M56)<=VLOOKUP($D56,'SeuilsComparaison-EMT'!$C$5:$J$27,6,FALSE),"Oui","Non"),IF(ABS(M56)<=VLOOKUP($D56,'SeuilsComparaison-EMT'!$C$5:$J$27,8,FALSE),"Oui","Non")),"Oui"))))
D57: PT | F57: =VLOOKUP(D57, 'SeuilsComparaison-EMT'!$C$5:$E$28, 3, FALSE) -> 0.05 | M57: =IF(OR(J57="",G57=""),"",IF(ISERROR(VLOOKUP(D57,'SeuilsComparaison-EMT'!$C$5:$J$25,4,FALSE)),"-",IF(OR(IF(ISTEXT(J57)=TRUE,SUBSTITUTE(J57,"<","",1)*1,J57)>VLOOKUP(D57,'SeuilsComparaison-EMT'!$C$5:$J$25,4,FALSE),IF(ISTEXT(G57)=TRUE,SUBSTITUTE(G57,"<","",1)*1,G57)>VLOOKUP(D57,'SeuilsComparaison-EMT'!$C$5:$J$25,4,FALSE)=TRUE),(IF(ISTEXT(G57)=TRUE,SUBSTITUTE(G57,"<","",1)*1,G57)-((IF(ISTEXT(G57)=TRUE,SUBSTITUTE(G57,"<","",1)*1,G57)+IF(ISTEXT(J57)=TRUE,SUBSTITUTE(J57,"<","",1)*1,J57))/2))/((IF(ISTEXT(G57)=TRUE,SUBSTITUTE(G57,"<","",1)*1,G57)+IF(ISTEXT(J57)=TRUE,SUBSTITUTE(J57,"<","",1),J57))/2),"-"))) | O57: =IF(OR(G57="",J57=""),"",IF(AND(I57="Oui",L57="Oui"),"Oui",IF(M57="-","Oui",IF(OR(J57>VLOOKUP($D57,'SeuilsComparaison-EMT'!$C$5:$J$27,4,FALSE),G57>VLOOKUP($D57,'SeuilsComparaison-EMT'!$C$5:$J$27,4,FALSE)=TRUE),IF(J57<=VLOOKUP($D57,'SeuilsComparaison-EMT'!$C$5:$J$27,5,FALSE),IF(ABS(M57)<=VLOOKUP($D57,'SeuilsComparaison-EMT'!$C$5:$J$27,6,FALSE),"Oui","Non"),IF(ABS(M57)<=VLOOKUP($D57,'SeuilsComparaison-EMT'!$C$5:$J$27,8,FALSE),"Oui","Non")),"Oui"))))
D58: Conductivité | F58: =VLOOKUP(D58, 'SeuilsComparaison-EMT'!$C$5:$E$28, 3, FALSE) -> 0 | M58: =IF(OR(J58="",G58=""),"",IF(ISERROR(VLOOKUP(D58,'SeuilsComparaison-EMT'!$C$5:$J$25,4,FALSE)),"-",IF(OR(IF(ISTEXT(J58)=TRUE,SUBSTITUTE(J58,"<","",1)*1,J58)>VLOOKUP(D58,'SeuilsComparaison-EMT'!$C$5:$J$25,4,FALSE),IF(ISTEXT(G58)=TRUE,SUBSTITUTE(G58,"<","",1)*1,G58)>VLOOKUP(D58,'SeuilsComparaison-EMT'!$C$5:$J$25,4,FALSE)=TRUE),(IF(ISTEXT(G58)=TRUE,SUBSTITUTE(G58,"<","",1)*1,G58)-((IF(ISTEXT(G58)=TRUE,SUBSTITUTE(G58,"<","",1)*1,G58)+IF(ISTEXT(J58)=TRUE,SUBSTITUTE(J58,"<","",1)*1,J58))/2))/((IF(ISTEXT(G58)=TRUE,SUBSTITUTE(G58,"<","",1)*1,G58)+IF(ISTEXT(J58)=TRUE,SUBSTITUTE(J58,"<","",1),J58))/2),"-"))) | O58: =IF(OR(G58="",J58=""),"",IF(AND(I58="Oui",L58="Oui"),"Oui",IF(M58="-","Oui",IF(OR(J58>VLOOKUP($D58,'SeuilsComparaison-EMT'!$C$5:$J$27,4,FALSE),G58>VLOOKUP($D58,'SeuilsComparaison-EMT'!$C$5:$J$27,4,FALSE)=TRUE),IF(J58<=VLOOKUP($D58,'SeuilsComparaison-EMT'!$C$5:$J$27,5,FALSE),IF(ABS(M58)<=VLOOKUP($D58,'SeuilsComparaison-EMT'!$C$5:$J$27,6,FALSE),"Oui","Non"),IF(ABS(M58)<=VLOOKUP($D58,'SeuilsComparaison-EMT'!$C$5:$J$27,8,FALSE),"Oui","Non")),"Oui"))))
D59: Cl | F59: =VLOOKUP(D59, 'SeuilsComparaison-EMT'!$C$5:$E$28, 3, FALSE) -> 5 | M59: =IF(OR(J59="",G59=""),"",IF(ISERROR(VLOOKUP(D59,'SeuilsComparaison-EMT'!$C$5:$J$25,4,FALSE)),"-",IF(OR(IF(ISTEXT(J59)=TRUE,SUBSTITUTE(J59,"<","",1)*1,J59)>VLOOKUP(D59,'SeuilsComparaison-EMT'!$C$5:$J$25,4,FALSE),IF(ISTEXT(G59)=TRUE,SUBSTITUTE(G59,"<","",1)*1,G59)>VLOOKUP(D59,'SeuilsComparaison-EMT'!$C$5:$J$25,4,FALSE)=TRUE),(IF(ISTEXT(G59)=TRUE,SUBSTITUTE(G59,"<","",1)*1,G59)-((IF(ISTEXT(G59)=TRUE,SUBSTITUTE(G59,"<","",1)*1,G59)+IF(ISTEXT(J59)=TRUE,SUBSTITUTE(J59,"<","",1)*1,J59))/2))/((IF(ISTEXT(G59)=TRUE,SUBSTITUTE(G59,"<","",1)*1,G59)+IF(ISTEXT(J59)=TRUE,SUBSTITUTE(J59,"<","",1),J59))/2),"-"))) | O59: =IF(OR(G59="",J59=""),"",IF(AND(I59="Oui",L59="Oui"),"Oui",IF(M59="-","Oui",IF(OR(J59>VLOOKUP($D59,'SeuilsComparaison-EMT'!$C$5:$J$27,4,FALSE),G59>VLOOKUP($D59,'SeuilsComparaison-EMT'!$C$5:$J$27,4,FALSE)=TRUE),IF(J59<=VLOOKUP($D59,'SeuilsComparaison-EMT'!$C$5:$J$27,5,FALSE),IF(ABS(M59)<=VLOOKUP($D59,'SeuilsComparaison-EMT'!$C$5:$J$27,6,FALSE),"Oui","Non"),IF(ABS(M59)<=VLOOKUP($D59,'SeuilsComparaison-EMT'!$C$5:$J$27,8,FALSE),"Oui","Non")),"Oui"))))
D60: MS | F60: =VLOOKUP(D60, 'SeuilsComparaison-EMT'!$C$5:$E$28, 3, FALSE) -> 0 | M60: =IF(OR(J60="",G60=""),"",IF(ISERROR(VLOOKUP(D60,'SeuilsComparaison-EMT'!$C$5:$J$25,4,FALSE)),"-",IF(OR(IF(ISTEXT(J60)=TRUE,SUBSTITUTE(J60,"<","",1)*1,J60)>VLOOKUP(D60,'SeuilsComparaison-EMT'!$C$5:$J$25,4,FALSE),IF(ISTEXT(G60)=TRUE,SUBSTITUTE(G60,"<","",1)*1,G60)>VLOOKUP(D60,'SeuilsComparaison-EMT'!$C$5:$J$25,4,FALSE)=TRUE),(IF(ISTEXT(G60)=TRUE,SUBSTITUTE(G60,"<","",1)*1,G60)-((IF(ISTEXT(G60)=TRUE,SUBSTITUTE(G60,"<","",1)*1,G60)+IF(ISTEXT(J60)=TRUE,SUBSTITUTE(J60,"<","",1)*1,J60))/2))/((IF(ISTEXT(G60)=TRUE,SUBSTITUTE(G60,"<","",1)*1,G60)+IF(ISTEXT(J60)=TRUE,SUBSTITUTE(J60,"<","",1),J60))/2),"-"))) | O60: =IF(OR(G60="",J60=""),"",IF(AND(I60="Oui",L60="Oui"),"Oui",IF(M60="-","Oui",IF(OR(J60>VLOOKUP($D60,'SeuilsComparaison-EMT'!$C$5:$J$27,4,FALSE),G60>VLOOKUP($D60,'SeuilsComparaison-EMT'!$C$5:$J$27,4,FALSE)=TRUE),IF(J60<=VLOOKUP($D60,'SeuilsComparaison-EMT'!$C$5:$J$27,5,FALSE),IF(ABS(M60)<=VLOOKUP($D60,'SeuilsComparaison-EMT'!$C$5:$J$27,6,FALSE),"Oui","Non"),IF(ABS(M60)<=VLOOKUP($D60,'SeuilsComparaison-EMT'!$C$5:$J$27,8,FALSE),"Oui","Non")),"Oui"))))
D62: COMMENTAIRES :
J68: Ajouter un comparatif analytique

Sheet PARAM
A3: Equipement Q | B3: Equipement Prel | C3: Type | D3: Liste des statuts | E3: Code | F3: Code | G3: Liste des statuts | H3: Liste des statuts | I3: Code
A4: Canal Venturi | B4: Préleveur Automatique | C4: Débitmètre en charge | D4: Validé | E4: A2 | F4: A1 | G4: Oui | H4: Agréé | I4: A2
A5: Débitmètre électromagnétique (eau) | B5: Vanne de prélèvement asservie | C5: Débitmètre gravitaire | D5: Non validé | E5: A3 | F5: R1 | G5: Non | H5: Non agréé | I5: A3
A6: Débitmètre électromagnétique (boue/MDV) | B6: Prélèvement ponctuel | C6: Préleveur | D6: Non contrôlé | E6: A4 | F6: R2 | I6: A4
A7: Seuil | C7: Sonde de température | D7: Validé avec réserve | E7: A5 | F7: R3 | I7: A5
A8: Caisson | D8: Non validé (absence d'équipement) | E8: A6 | I8: A6
A9: Loi COACHs | D9: Non validé (équipement insuffisant) | E9: A7 | I9: A7
A10: Débitmètre électromagnétique partiellement plein | E10: A8 | I10: A8
A11: Clapet | E11: S1 | I11: S1
A12: Détecteur de surverse | E12: S2 | I12: S2
A13: Modélisation | E13: S3 | I13: S3
A14: Hauteur/Vitesse | E14: S4 | I14: S4
A15: Point non existant | E15: S5 | I15: S5
E16: S12 | I16: S12
E17: S13 | I17: S13
E18: S16 | I18: S16
E19: S19 | I19: S19
A20: LISTE_1 | B20: LISTE_2 | C20: LISTE_3 | D20: LISTE_4 | F20: LISTE_5 | G20: LISTE_6 | H20: LISTE_7
A21: Oui | B21: Validé | C21: Validé | D21: Validé | F21: Validé | G21: Oui | H21: Oui
A22: Non | B22: Non validé | C22: Non validé | D22: Non validé | F22: Entre 5 et 10% | G22: Non | H22: Non
B23: Non contrôlé | C23: Non contrôlé | D23: Non contrôlé | F23: Non validé (>10%) | G23: Non concerné | H23: Non contrôlé
C24: Validé avec réserve | D24: Validé avec réserve | F24: Non contrôlé
D25: Non validé (absence d'équipement)
D26: Non validé (équipement insuffisant)
A28: Type équipement : débimètre
A29: Q en charge | B29: Q Gravitaire | C29: Equipement de contrôle H | D29: Type réseau
A30: Débitmètre électromagnétique (eau) | B30: Canal Venturi | C30: Réglet | D30: Mixte
A31: Débitmètre électromagnétique (boue/MDV) | B31: Seuil | C31: Sonde | D31: Unitaire
A32: Organe deprimogène (pito...) | B32: Caisson | C32: Câble | D32: Séparatif
A33: Débitmètre Ultrason | B33: Loi COACHs
A34: Modélisation | B34: Débitmètre électromagnétique partiellement plein
A35: compteur mécanique | B35: Clapet
A36: Point non existant | B36: Détecteur de surverse
B37: Modélisation
B38: Hauteur/Vitesse
B39: Point non existant
A42: Listes fiches terrain
A43: Asservissement | B43: Conformité | C43: Type_capteur | D43: Satisfaction | E43: Fréquence | F43: Conditions météo | G43: Montage sonde
A44: Au débit | B44: Conforme | C44: Ultrason | D44: Satisfaisant | E44: Journalière | F44: Temps sec | G44: En /
A45: Au temps | B45: Conforme avec réserve | C45: Radar | D45: Non satisfaisant | E45: Hebdomadaire | F45: Temps de pluie | G45: En V
A46: Inconnu | B46: Non conforme | C46: Piezo | D46: Non vérifié | E46: Mensuelle | F46: Inconnues | G46: En W
B47: Non vérifié | C47: Bulle à bulle | E47: Bimensuelle | G47: En N
B48: Non vérifiable | C48: Autre | E48: Trimestrielle
E49: Semestrielle
E50: Annuelle
E51: Autre
A53: Listes méthode contrôle
A54: Méthode | B54: Type de mesure
A55: Simulation d'une hauteur d'eau (leurre) | B55: Ponctuelle
A56: Mesure en parallèle | B56: En continu
A57: Simulation d'une hauteur d'eau et mesure en parallèle

Sheet SeuilsComparaison-EMT
B2: COMPARATIF ANALYTIQUE : DEFINITION DES ECARTS MAXIMUM TOLERES (EMT)
B4: Code SANDRE | C4: Paramètres | D4: Unités | E4: Limites de quantification | F4: Seuil de comparaison | G4: Concentration supérieure au seuil de comparaison et inférieure ou égale à | H4: Ecart Maximum Toléré | I4: Concentration supérieure à | J4: Ecart Maximum Toléré
B5: 1313 | C5: DBO5 | D5: en mg/l de O2 | E5: 3 | F5: 15 | G5: 80 | H5: 0.3 | I5: 80 | J5: 0.2
B6: 1314 | C6: DCO | D6: en mg/l de O2 | E6: 30 | F6: 80 | G6: 250 | H6: 0.2 | I6: 250 | J6: 0.1
B7: 6396 | C7: ST DCO | D7: en mg/l de O2 | E7: 10 | F7: 20 | G7: 150 | H7: 0.2 | I7: 150 | J7: 0.1
B8: 1305 | C8: MEST | D8: en mg/l | E8: 2 | F8: 15 | G8: 60 | H8: 0.3 | I8: 60 | J8: 0.2
B9: 1319 | C9: NKJ (N) | D9: en mg/l de N | E9: 0.5 | F9: 6 | I9: 6 | J9: 0.1
B10: 1551 | C10: NGL | D10: en mg/l de N | E10: 1 | F10: 6 | I10: 6 | J10: 0.2
B11: 1335 | C11: NH4 (NH4) | D11: en mg/l de NH4+ | E11: 0.5 | F11: 6 | I11: 6 | J11: 0.1
B12: 1339 | C12: NO2 (NO2) | D12: en mg/l de NO2 | E12: 0.05 | F12: 1 | I12: 1 | J12: 0.2
B13: 1340 | C13: NO3 (NO3) | D13: en mg/l de NO3 | E13: 1 | F13: 5 | I13: 5 | J13: 0.2
B14: 1350 | C14: PT | D14: en mg/l de P | E14: 0.05 | F14: 1 | I14: 1 | J14: 0.2
B15: 1369 | C15: As | D15: en mg/l | E15: 0.005 | F15: 0.5 | G15: 1 | H15: 0.6 | I15: 1 | J15: 0.3
B16: 1388 | C16: Cd | D16: en mg/l | E16: 0.001 | F16: 0.5 | G16: 1 | H16: 0.6 | I16: 1 | J16: 0.3
B17: 1389 | C17: Cr | D17: en mg/l | E17: 0.005 | F17: 0.5 | G17: 1 | H17: 0.6 | I17: 1 | J17: 0.3
B18: 1392 | C18: Cu | D18: en mg/l | E18: 0.005 | F18: 0.5 | G18: 1 | H18: 0.6 | I18: 1 | J18: 0.3
B19: 1387 | C19: Hg | D19: en mg/l | E19: 0.0002 | F19: 0.005 | G19: 0.01 | H19: 0.6 | I19: 0.01 | J19: 0.3
B20: 1386 | C20: Ni | D20: en mg/l | E20: 0.005 | F20: 0.5 | G20: 1 | H20: 0.6 | I20: 1 | J20: 0.3
B21: 1382 | C21: Pb | D21: en mg/l | E21: 0.002 | F21: 0.5 | G21: 1 | H21: 0.6 | I21: 1 | J21: 0.3
B22: 1383 | C22: Zn | D22: en mg/l | E22: 0.005 | F22: 0.5 | G22: 1 | H22: 0.6 | I22: 1 | J22: 0.3
B23: 1106 | C23: AOX | D23: en mg/l | E23: 0.01 | F23: 0.05 | G23: 0.5 | H23: 0.6 | I23: 0.5 | J23: 0.3
B24: 1841 | C24: COT | D24: en mg/l | E24: 0.3 | F24: 5 | G24: 15 | H24: 0.3 | I24: 15 | J24: 0.1
B25: 1798 | C25: Conductivité
B26: 1337 | C26: Cl | D26: en mg/l | E26: 5
B27: 1799 | C27: MS | D27: en g/l | H27: 0.2 | J27: 0.05 | K27: si S4
B28: Le cacul des écarts analytiques est effectué si l'un des deux ou les deux résultats sont au dessus du seuil de comparaison. L'écart est calculé par rapport à la moyenne des 2 valeurs.

Sheet Recap_equipements
B1: Préparation des données pour la feuilles synthèse et pour les exports
B2: Paramètres de localisation des données dans les cellules
B4: Facteur Qualité | D4: Type Equipement | E4: Type
B5: =IF(Qualité!L29="Non",0.9,1) -> 0.9 | E5: cellule typeE | F5: cellule score | G5: cellule eval | H5: cellule commentaire score | I5: cellule commentaire
D6: Pluviomètre | E6: D24 | F6: P32 | G6: N32 | H6: D32 | I6: C36
D7: =PARAM!$C4 -> Débitmètre en charge | E7: D32 | F7: P45 | G7: N45 | H7: D45 | I7: C49
D8: =PARAM!$C5 -> Débitmètre gravitaire | E8: D40 | F8: P53 | G8: N53 | H8: D53 | I8: C57
D9: =PARAM!$C6 -> Préleveur | E9: D37 | F9: P50 | G9: N50 | H9: D50 | I9: C54
D10: =PARAM!$C7 -> Sonde de température | E10: D26 | F10: P33 | G10: N33 | H10: D33 | I10: C37
D12: Type ligne | E12: Ligne
D13: Ligne STEU | E13: =Descriptif!$AD$3 -> 34 | F13: =E13+1 -> 35 | G13: =F13+1 -> 36 | H13: =G13+1 -> 37 | I13: =H13+1 -> 38 | J13: =I13+1 -> 39 | K13: =J13+1 -> 40 | L13: =K13+1 -> 41 | M13: =L13+1 -> 42 | ... S13: =R13+1 -> 48
D14: Ligne SCL | E14: =Descriptif!$AD$2 -> 14 | F14: =E14+1 -> 15 | G14: =F14+1 -> 16 | H14: =G14+1 -> 17 | I14: =H14+1 -> 18 | J14: =I14+1 -> 19 | K14: =J14+1 -> 20 | L14: =K14+1 -> 21 | M14: =L14+1 -> 22 | ... S14: =R14+1 -> 28
B16: Identification des feuilles de données
B18: Reg. | C18: Log. | F18: Point 1 | G18: Point 2 | H18: Point 3 | I18: Point 4 | J18: Point 5 | K18: Point 6 | L18: Point 7 | M18: Point 8 | N18: Point 9 | O18: Point 10 | P18: Point 11 | Q18: Point 12 | R18: Point 13 | S18: Point 14 | T18: Point 15
B19: A3 | C19: S1 | D19: =$D$7 -> Débitmètre en charge | F19: =IF(AND(OR(INDIRECT("Descriptif!I"&E$13)=Recap_equipements!$B19,INDIRECT("Descriptif!I"&E$13)=Recap_equipements!$C19),INDIRECT("Descriptif!M"&E$13)=$D19),INDIRECT("Descriptif!F"&E$13),"") | G19: =IF(AND(OR(INDIRECT("Descriptif!I"&F$13)=Recap_equipements!$B19,INDIRECT("Descriptif!I"&F$13)=Recap_equipements!$C19),INDIRECT("Descriptif!M"&F$13)=$D19),INDIRECT("Descriptif!F"&F$13),"") | H19: =IF(AND(OR(INDIRECT("Descriptif!I"&G$13)=Recap_equipements!$B19,INDIRECT("Descriptif!I"&G$13)=Recap_equipements!$C19),INDIRECT("Descriptif!M"&G$13)=$D19),INDIRECT("Descriptif!F"&G$13),"") | I19: =IF(AND(OR(INDIRECT("Descriptif!I"&H$13)=Recap_equipements!$B19,INDIRECT("Descriptif!I"&H$13)=Recap_equipements!$C19),INDIRECT("Descriptif!M"&H$13)=$D19),INDIRECT("Descriptif!F"&H$13),"") | J19: =IF(AND(OR(INDIRECT("Descriptif!I"&I$13)=Recap_equipements!$B19,INDIRECT("Descriptif!I"&I$13)=Recap_equipements!$C19),INDIRECT("Descriptif!M"&I$13)=$D19),INDIRECT("Descriptif!F"&I$13),"") | K19: =IF(AND(OR(INDIRECT("Descriptif!I"&J$13)=Recap_equipements!$B19,INDIRECT("Descriptif!I"&J$13)=Recap_equipements!$C19),INDIRECT("Descriptif!M"&J$13)=$D19),INDIRECT("Descriptif!F"&J$13),"") | L19: =IF(AND(OR(INDIRECT("Descriptif!I"&K$13)=Recap_equipements!$B19,INDIRECT("Descriptif!I"&K$13)=Recap_equipements!$C19),INDIRECT("Descriptif!M"&K$13)=$D19),INDIRECT("Descriptif!F"&K$13),"") | M19: =IF(AND(OR(INDIRECT("Descriptif!I"&L$13)=Recap_equipements!$B19,INDIRECT("Descriptif!I"&L$13)=Recap_equipements!$C19),INDIRECT("Descriptif!M"&L$13)=$D19),INDIRECT("Descriptif!F"&L$13),"") | ... T19: =IF(AND(OR(INDIRECT("Descriptif!I"&S$13)=Recap_equipements!$B19,INDIRECT("Descriptif!I"&S$13)=Recap_equipements!$C19),INDIRECT("Descriptif!M"&S$13)=$D19),INDIRECT("Descriptif!F"&S$13),"")
D20: =$D$8 -> Débitmètre gravitaire | F20: =IF(AND(OR(INDIRECT("Descriptif!I"&E$13)=Recap_equipements!$B19,INDIRECT("Descriptif!I"&E$13)=Recap_equipements!$C19),INDIRECT("Descriptif!M"&E$13)=$D20),INDIRECT("Descriptif!F"&E$13),"") | G20: =IF(AND(OR(INDIRECT("Descriptif!I"&F$13)=Recap_equipements!$B19,INDIRECT("Descriptif!I"&F$13)=Recap_equipements!$C19),INDIRECT("Descriptif!M"&F$13)=$D20),INDIRECT("Descriptif!F"&F$13),"") | H20: =IF(AND(OR(INDIRECT("Descriptif!I"&G$13)=Recap_equipements!$B19,INDIRECT("Descriptif!I"&G$13)=Recap_equipements!$C19),INDIRECT("Descriptif!M"&G$13)=$D20),INDIRECT("Descriptif!F"&G$13),"") | I20: =IF(AND(OR(INDIRECT("Descriptif!I"&H$13)=Recap_equipements!$B19,INDIRECT("Descriptif!I"&H$13)=Recap_equipements!$C19),INDIRECT("Descriptif!M"&H$13)=$D20),INDIRECT("Descriptif!F"&H$13),"") | J20: =IF(AND(OR(INDIRECT("Descriptif!I"&I$13)=Recap_equipements!$B19,INDIRECT("Descriptif!I"&I$13)=Recap_equipements!$C19),INDIRECT("Descriptif!M"&I$13)=$D20),INDIRECT("Descriptif!F"&I$13),"") | K20: =IF(AND(OR(INDIRECT("Descriptif!I"&J$13)=Recap_equipements!$B19,INDIRECT("Descriptif!I"&J$13)=Recap_equipements!$C19),INDIRECT("Descriptif!M"&J$13)=$D20),INDIRECT("Descriptif!F"&J$13),"") | L20: =IF(AND(OR(INDIRECT("Descriptif!I"&K$13)=Recap_equipements!$B19,INDIRECT("Descriptif!I"&K$13)=Recap_equipements!$C19),INDIRECT("Descriptif!M"&K$13)=$D20),INDIRECT("Descriptif!F"&K$13),"") | M20: =IF(AND(OR(INDIRECT("Descriptif!I"&L$13)=Recap_equipements!$B19,INDIRECT("Descriptif!I"&L$13)=Recap_equipements!$C19),INDIRECT("Descriptif!M"&L$13)=$D20),INDIRECT("Descriptif!F"&L$13),"") | ... T20: =IF(AND(OR(INDIRECT("Descriptif!I"&S$13)=Recap_equipements!$B19,INDIRECT("Descriptif!I"&S$13)=Recap_equipements!$C19),INDIRECT("Descriptif!M"&S$13)=$D20),INDIRECT("Descriptif!F"&S$13),"")
D21: =$D$9 -> Préleveur | F21: =IF(AND(OR(INDIRECT("Descriptif!I"&E$13)=Recap_equipements!$B19,INDIRECT("Descriptif!I"&E$13)=Recap_equipements!$C19),INDIRECT("Descriptif!M"&E$13)=$D21),INDIRECT("Descriptif!F"&E$13),"") | G21: =IF(AND(OR(INDIRECT("Descriptif!I"&F$13)=Recap_equipements!$B19,INDIRECT("Descriptif!I"&F$13)=Recap_equipements!$C19),INDIRECT("Descriptif!M"&F$13)=$D21),INDIRECT("Descriptif!F"&F$13),"") | H21: =IF(AND(OR(INDIRECT("Descriptif!I"&G$13)=Recap_equipements!$B19,INDIRECT("Descriptif!I"&G$13)=Recap_equipements!$C19),INDIRECT("Descriptif!M"&G$13)=$D21),INDIRECT("Descriptif!F"&G$13),"") | I21: =IF(AND(OR(INDIRECT("Descriptif!I"&H$13)=Recap_equipements!$B19,INDIRECT("Descriptif!I"&H$13)=Recap_equipements!$C19),INDIRECT("Descriptif!M"&H$13)=$D21),INDIRECT("Descriptif!F"&H$13),"") | J21: =IF(AND(OR(INDIRECT("Descriptif!I"&I$13)=Recap_equipements!$B19,INDIRECT("Descriptif!I"&I$13)=Recap_equipements!$C19),INDIRECT("Descriptif!M"&I$13)=$D21),INDIRECT("Descriptif!F"&I$13),"") | K21: =IF(AND(OR(INDIRECT("Descriptif!I"&J$13)=Recap_equipements!$B19,INDIRECT("Descriptif!I"&J$13)=Recap_equipements!$C19),INDIRECT("Descriptif!M"&J$13)=$D21),INDIRECT("Descriptif!F"&J$13),"") | L21: =IF(AND(OR(INDIRECT("Descriptif!I"&K$13)=Recap_equipements!$B19,INDIRECT("Descriptif!I"&K$13)=Recap_equipements!$C19),INDIRECT("Descriptif!M"&K$13)=$D21),INDIRECT("Descriptif!F"&K$13),"") | M21: =IF(AND(OR(INDIRECT("Descriptif!I"&L$13)=Recap_equipements!$B19,INDIRECT("Descriptif!I"&L$13)=Recap_equipements!$C19),INDIRECT("Descriptif!M"&L$13)=$D21),INDIRECT("Descriptif!F"&L$13),"") | ... T21: =IF(AND(OR(INDIRECT("Descriptif!I"&S$13)=Recap_equipements!$B19,INDIRECT("Descriptif!I"&S$13)=Recap_equipements!$C19),INDIRECT("Descriptif!M"&S$13)=$D21),INDIRECT("Descriptif!F"&S$13),"")
D22: Analytique | F22: =IF(F21<>"",VLOOKUP(F21,Analytique!$X$3:$AD$36,1,FALSE),"") | G22: =IF(G21<>"",VLOOKUP(G21,Analytique!$X$3:$AD$36,1,FALSE),"") | H22: =IF(H21<>"",VLOOKUP(H21,Analytique!$X$3:$AD$36,1,FALSE),"") | I22: =IF(I21<>"",VLOOKUP(I21,Analytique!$X$3:$AD$36,1,FALSE),"") | J22: =IF(J21<>"",VLOOKUP(J21,Analytique!$X$3:$AD$36,1,FALSE),"") | K22: =IF(K21<>"",VLOOKUP(K21,Analytique!$X$3:$AD$36,1,FALSE),"") | L22: =IF(L21<>"",VLOOKUP(L21,Analytique!$X$3:$AD$36,1,FALSE),"") | M22: =IF(M21<>"",VLOOKUP(M21,Analytique!$X$3:$AD$36,1,FALSE),"") | ... T22: =IF(T21<>"",VLOOKUP(T21,Analytique!$X$3:$AD$36,1,FALSE),"")
D23: =$D$10 -> Sonde de température | F23: =IF(AND(OR(INDIRECT("Descriptif!I"&E$13)=Recap_equipements!$B19,INDIRECT("Descriptif!I"&E$13)=Recap_equipements!$C19),INDIRECT("Descriptif!M"&E$13)=$D23),INDIRECT("Descriptif!F"&E$13),"") | G23: =IF(AND(OR(INDIRECT("Descriptif!I"&F$13)=Recap_equipements!$B19,INDIRECT("Descriptif!I"&F$13)=Recap_equipements!$C19),INDIRECT("Descriptif!M"&F$13)=$D23),INDIRECT("Descriptif!F"&F$13),"") | H23: =IF(AND(OR(INDIRECT("Descriptif!I"&G$13)=Recap_equipements!$B19,INDIRECT("Descriptif!I"&G$13)=Recap_equipements!$C19),INDIRECT("Descriptif!M"&G$13)=$D23),INDIRECT("Descriptif!F"&G$13),"") | I23: =IF(AND(OR(INDIRECT("Descriptif!I"&H$13)=Recap_equipements!$B19,INDIRECT("Descriptif!I"&H$13)=Recap_equipements!$C19),INDIRECT("Descriptif!M"&H$13)=$D23),INDIRECT("Descriptif!F"&H$13),"") | J23: =IF(AND(OR(INDIRECT("Descriptif!I"&I$13)=Recap_equipements!$B19,INDIRECT("Descriptif!I"&I$13)=Recap_equipements!$C19),INDIRECT("Descriptif!M"&I$13)=$D23),INDIRECT("Descriptif!F"&I$13),"") | K23: =IF(AND(OR(INDIRECT("Descriptif!I"&J$13)=Recap_equipements!$B19,INDIRECT("Descriptif!I"&J$13)=Recap_equipements!$C19),INDIRECT("Descriptif!M"&J$13)=$D23),INDIRECT("Descriptif!F"&J$13),"") | L23: =IF(AND(OR(INDIRECT("Descriptif!I"&K$13)=Recap_equipements!$B19,INDIRECT("Descriptif!I"&K$13)=Recap_equipements!$C19),INDIRECT("Descriptif!M"&K$13)=$D23),INDIRECT("Descriptif!F"&K$13),"") | M23: =IF(AND(OR(INDIRECT("Descriptif!I"&L$13)=Recap_equipements!$B19,INDIRECT("Descriptif!I"&L$13)=Recap_equipements!$C19),INDIRECT("Descriptif!M"&L$13)=$D23),INDIRECT("Descriptif!F"&L$13),"") | ... T23: =IF(AND(OR(INDIRECT("Descriptif!I"&S$13)=Recap_equipements!$B19,INDIRECT("Descriptif!I"&S$13)=Recap_equipements!$C19),INDIRECT("Descriptif!M"&S$13)=$D23),INDIRECT("Descriptif!F"&S$13),"")
B24: A4 | C24: S2 | D24: =$D$7 -> Débitmètre en charge | F24: =IF(AND(OR(INDIRECT("Descriptif!I"&E$13)=Recap_equipements!$B24,INDIRECT("Descriptif!I"&E$13)=Recap_equipements!$C24),INDIRECT("Descriptif!M"&E$13)=$D24),INDIRECT("Descriptif!F"&E$13),"") | G24: =IF(AND(OR(INDIRECT("Descriptif!I"&F$13)=Recap_equipements!$B24,INDIRECT("Descriptif!I"&F$13)=Recap_equipements!$C24),INDIRECT("Descriptif!M"&F$13)=$D24),INDIRECT("Descriptif!F"&F$13),"") | H24: =IF(AND(OR(INDIRECT("Descriptif!I"&G$13)=Recap_equipements!$B24,INDIRECT("Descriptif!I"&G$13)=Recap_equipements!$C24),INDIRECT("Descriptif!M"&G$13)=$D24),INDIRECT("Descriptif!F"&G$13),"") | I24: =IF(AND(OR(INDIRECT("Descriptif!I"&H$13)=Recap_equipements!$B24,INDIRECT("Descriptif!I"&H$13)=Recap_equipements!$C24),INDIRECT("Descriptif!M"&H$13)=$D24),INDIRECT("Descriptif!F"&H$13),"") | J24: =IF(AND(OR(INDIRECT("Descriptif!I"&I$13)=Recap_equipements!$B24,INDIRECT("Descriptif!I"&I$13)=Recap_equipements!$C24),INDIRECT("Descriptif!M"&I$13)=$D24),INDIRECT("Descriptif!F"&I$13),"") | K24: =IF(AND(OR(INDIRECT("Descriptif!I"&J$13)=Recap_equipements!$B24,INDIRECT("Descriptif!I"&J$13)=Recap_equipements!$C24),INDIRECT("Descriptif!M"&J$13)=$D24),INDIRECT("Descriptif!F"&J$13),"") | L24: =IF(AND(OR(INDIRECT("Descriptif!I"&K$13)=Recap_equipements!$B24,INDIRECT("Descriptif!I"&K$13)=Recap_equipements!$C24),INDIRECT("Descriptif!M"&K$13)=$D24),INDIRECT("Descriptif!F"&K$13),"") | M24: =IF(AND(OR(INDIRECT("Descriptif!I"&L$13)=Recap_equipements!$B24,INDIRECT("Descriptif!I"&L$13)=Recap_equipements!$C24),INDIRECT("Descriptif!M"&L$13)=$D24),INDIRECT("Descriptif!F"&L$13),"") | ... T24: =IF(AND(OR(INDIRECT("Descriptif!I"&S$13)=Recap_equipements!$B24,INDIRECT("Descriptif!I"&S$13)=Recap_equipements!$C24),INDIRECT("Descriptif!M"&S$13)=$D24),INDIRECT("Descriptif!F"&S$13),"")
D25: =$D$8 -> Débitmètre gravitaire | F25: =IF(AND(OR(INDIRECT("Descriptif!I"&E$13)=Recap_equipements!$B24,INDIRECT("Descriptif!I"&E$13)=Recap_equipements!$C24),INDIRECT("Descriptif!M"&E$13)=$D25),INDIRECT("Descriptif!F"&E$13),"") | G25: =IF(AND(OR(INDIRECT("Descriptif!I"&F$13)=Recap_equipements!$B24,INDIRECT("Descriptif!I"&F$13)=Recap_equipements!$C24),INDIRECT("Descriptif!M"&F$13)=$D25),INDIRECT("Descriptif!F"&F$13),"") | H25: =IF(AND(OR(INDIRECT("Descriptif!I"&G$13)=Recap_equipements!$B24,INDIRECT("Descriptif!I"&G$13)=Recap_equipements!$C24),INDIRECT("Descriptif!M"&G$13)=$D25),INDIRECT("Descriptif!F"&G$13),"") | I25: =IF(AND(OR(INDIRECT("Descriptif!I"&H$13)=Recap_equipements!$B24,INDIRECT("Descriptif!I"&H$13)=Recap_equipements!$C24),INDIRECT("Descriptif!M"&H$13)=$D25),INDIRECT("Descriptif!F"&H$13),"") | J25: =IF(AND(OR(INDIRECT("Descriptif!I"&I$13)=Recap_equipements!$B24,INDIRECT("Descriptif!I"&I$13)=Recap_equipements!$C24),INDIRECT("Descriptif!M"&I$13)=$D25),INDIRECT("Descriptif!F"&I$13),"") | K25: =IF(AND(OR(INDIRECT("Descriptif!I"&J$13)=Recap_equipements!$B24,INDIRECT("Descriptif!I"&J$13)=Recap_equipements!$C24),INDIRECT("Descriptif!M"&J$13)=$D25),INDIRECT("Descriptif!F"&J$13),"") | L25: =IF(AND(OR(INDIRECT("Descriptif!I"&K$13)=Recap_equipements!$B24,INDIRECT("Descriptif!I"&K$13)=Recap_equipements!$C24),INDIRECT("Descriptif!M"&K$13)=$D25),INDIRECT("Descriptif!F"&K$13),"") | M25: =IF(AND(OR(INDIRECT("Descriptif!I"&L$13)=Recap_equipements!$B24,INDIRECT("Descriptif!I"&L$13)=Recap_equipements!$C24),INDIRECT("Descriptif!M"&L$13)=$D25),INDIRECT("Descriptif!F"&L$13),"") | ... T25: =IF(AND(OR(INDIRECT("Descriptif!I"&S$13)=Recap_equipements!$B24,INDIRECT("Descriptif!I"&S$13)=Recap_equipements!$C24),INDIRECT("Descriptif!M"&S$13)=$D25),INDIRECT("Descriptif!F"&S$13),"")
D26: =$D$9 -> Préleveur | F26: =IF(AND(OR(INDIRECT("Descriptif!I"&E$13)=Recap_equipements!$B24,INDIRECT("Descriptif!I"&E$13)=Recap_equipements!$C24),INDIRECT("Descriptif!M"&E$13)=$D26),INDIRECT("Descriptif!F"&E$13),"") | G26: =IF(AND(OR(INDIRECT("Descriptif!I"&F$13)=Recap_equipements!$B24,INDIRECT("Descriptif!I"&F$13)=Recap_equipements!$C24),INDIRECT("Descriptif!M"&F$13)=$D26),INDIRECT("Descriptif!F"&F$13),"") | H26: =IF(AND(OR(INDIRECT("Descriptif!I"&G$13)=Recap_equipements!$B24,INDIRECT("Descriptif!I"&G$13)=Recap_equipements!$C24),INDIRECT("Descriptif!M"&G$13)=$D26),INDIRECT("Descriptif!F"&G$13),"") | I26: =IF(AND(OR(INDIRECT("Descriptif!I"&H$13)=Recap_equipements!$B24,INDIRECT("Descriptif!I"&H$13)=Recap_equipements!$C24),INDIRECT("Descriptif!M"&H$13)=$D26),INDIRECT("Descriptif!F"&H$13),"") | J26: =IF(AND(OR(INDIRECT("Descriptif!I"&I$13)=Recap_equipements!$B24,INDIRECT("Descriptif!I"&I$13)=Recap_equipements!$C24),INDIRECT("Descriptif!M"&I$13)=$D26),INDIRECT("Descriptif!F"&I$13),"") | K26: =IF(AND(OR(INDIRECT("Descriptif!I"&J$13)=Recap_equipements!$B24,INDIRECT("Descriptif!I"&J$13)=Recap_equipements!$C24),INDIRECT("Descriptif!M"&J$13)=$D26),INDIRECT("Descriptif!F"&J$13),"") | L26: =IF(AND(OR(INDIRECT("Descriptif!I"&K$13)=Recap_equipements!$B24,INDIRECT("Descriptif!I"&K$13)=Recap_equipements!$C24),INDIRECT("Descriptif!M"&K$13)=$D26),INDIRECT("Descriptif!F"&K$13),"") | M26: =IF(AND(OR(INDIRECT("Descriptif!I"&L$13)=Recap_equipements!$B24,INDIRECT("Descriptif!I"&L$13)=Recap_equipements!$C24),INDIRECT("Descriptif!M"&L$13)=$D26),INDIRECT("Descriptif!F"&L$13),"") | ... T26: =IF(AND(OR(INDIRECT("Descriptif!I"&S$13)=Recap_equipements!$B24,INDIRECT("Descriptif!I"&S$13)=Recap_equipements!$C24),INDIRECT("Descriptif!M"&S$13)=$D26),INDIRECT("Descriptif!F"&S$13),"")
D27: Analytique | F27: =IF(F26<>"",VLOOKUP(F26,Analytique!$X$3:$AD$36,1,FALSE),"") | G27: =IF(G26<>"",VLOOKUP(G26,Analytique!$X$3:$AD$36,1,FALSE),"") | H27: =IF(H26<>"",VLOOKUP(H26,Analytique!$X$3:$AD$36,1,FALSE),"") | I27: =IF(I26<>"",VLOOKUP(I26,Analytique!$X$3:$AD$36,1,FALSE),"") | J27: =IF(J26<>"",VLOOKUP(J26,Analytique!$X$3:$AD$36,1,FALSE),"") | K27: =IF(K26<>"",VLOOKUP(K26,Analytique!$X$3:$AD$36,1,FALSE),"") | L27: =IF(L26<>"",VLOOKUP(L26,Analytique!$X$3:$AD$36,1,FALSE),"") | M27: =IF(M26<>"",VLOOKUP(M26,Analytique!$X$3:$AD$36,1,FALSE),"") | ... T27: =IF(T26<>"",VLOOKUP(T26,Analytique!$X$3:$AD$36,1,FALSE),"")
D28: =$D$10 -> Sonde de température | F28: =IF(AND(OR(INDIRECT("Descriptif!I"&E$13)=Recap_equipements!$B24,INDIRECT("Descriptif!I"&E$13)=Recap_equipements!$C24),INDIRECT("Descriptif!M"&E$13)=$D28),INDIRECT("Descriptif!F"&E$13),"") | G28: =IF(AND(OR(INDIRECT("Descriptif!I"&F$13)=Recap_equipements!$B24,INDIRECT("Descriptif!I"&F$13)=Recap_equipements!$C24),INDIRECT("Descriptif!M"&F$13)=$D28),INDIRECT("Descriptif!F"&F$13),"") | H28: =IF(AND(OR(INDIRECT("Descriptif!I"&G$13)=Recap_equipements!$B24,INDIRECT("Descriptif!I"&G$13)=Recap_equipements!$C24),INDIRECT("Descriptif!M"&G$13)=$D28),INDIRECT("Descriptif!F"&G$13),"") | I28: =IF(AND(OR(INDIRECT("Descriptif!I"&H$13)=Recap_equipements!$B24,INDIRECT("Descriptif!I"&H$13)=Recap_equipements!$C24),INDIRECT("Descriptif!M"&H$13)=$D28),INDIRECT("Descriptif!F"&H$13),"") | J28: =IF(AND(OR(INDIRECT("Descriptif!I"&I$13)=Recap_equipements!$B24,INDIRECT("Descriptif!I"&I$13)=Recap_equipements!$C24),INDIRECT("Descriptif!M"&I$13)=$D28),INDIRECT("Descriptif!F"&I$13),"") | K28: =IF(AND(OR(INDIRECT("Descriptif!I"&J$13)=Recap_equipements!$B24,INDIRECT("Descriptif!I"&J$13)=Recap_equipements!$C24),INDIRECT("Descriptif!M"&J$13)=$D28),INDIRECT("Descriptif!F"&J$13),"") | L28: =IF(AND(OR(INDIRECT("Descriptif!I"&K$13)=Recap_equipements!$B24,INDIRECT("Descriptif!I"&K$13)=Recap_equipements!$C24),INDIRECT("Descriptif!M"&K$13)=$D28),INDIRECT("Descriptif!F"&K$13),"") | M28: =IF(AND(OR(INDIRECT("Descriptif!I"&L$13)=Recap_equipements!$B24,INDIRECT("Descriptif!I"&L$13)=Recap_equipements!$C24),INDIRECT("Descriptif!M"&L$13)=$D28),INDIRECT("Descriptif!F"&L$13),"") | ... T28: =IF(AND(OR(INDIRECT("Descriptif!I"&S$13)=Recap_equipements!$B24,INDIRECT("Descriptif!I"&S$13)=Recap_equipements!$C24),INDIRECT("Descriptif!M"&S$13)=$D28),INDIRECT("Descriptif!F"&S$13),"")
B29: A2 | C29: S16 | D29: =$D$7 -> Débitmètre en charge | F29: =IF(AND(OR(INDIRECT("Descriptif!I"&E$13)=Recap_equipements!$B29,INDIRECT("Descriptif!I"&E$13)=Recap_equipements!$C29),INDIRECT("Descriptif!M"&E$13)=$D29),INDIRECT("Descriptif!F"&E$13),"") | G29: =IF(AND(OR(INDIRECT("Descriptif!I"&F$13)=Recap_equipements!$B29,INDIRECT("Descriptif!I"&F$13)=Recap_equipements!$C29),INDIRECT("Descriptif!M"&F$13)=$D29),INDIRECT("Descriptif!F"&F$13),"") | H29: =IF(AND(OR(INDIRECT("Descriptif!I"&G$13)=Recap_equipements!$B29,INDIRECT("Descriptif!I"&G$13)=Recap_equipements!$C29),INDIRECT("Descriptif!M"&G$13)=$D29),INDIRECT("Descriptif!F"&G$13),"") | I29: =IF(AND(OR(INDIRECT("Descriptif!I"&H$13)=Recap_equipements!$B29,INDIRECT("Descriptif!I"&H$13)=Recap_equipements!$C29),INDIRECT("Descriptif!M"&H$13)=$D29),INDIRECT("Descriptif!F"&H$13),"") | J29: =IF(AND(OR(INDIRECT("Descriptif!I"&I$13)=Recap_equipements!$B29,INDIRECT("Descriptif!I"&I$13)=Recap_equipements!$C29),INDIRECT("Descriptif!M"&I$13)=$D29),INDIRECT("Descriptif!F"&I$13),"") | K29: =IF(AND(OR(INDIRECT("Descriptif!I"&J$13)=Recap_equipements!$B29,INDIRECT("Descriptif!I"&J$13)=Recap_equipements!$C29),INDIRECT("Descriptif!M"&J$13)=$D29),INDIRECT("Descriptif!F"&J$13),"") | L29: =IF(AND(OR(INDIRECT("Descriptif!I"&K$13)=Recap_equipements!$B29,INDIRECT("Descriptif!I"&K$13)=Recap_equipements!$C29),INDIRECT("Descriptif!M"&K$13)=$D29),INDIRECT("Descriptif!F"&K$13),"") | M29: =IF(AND(OR(INDIRECT("Descriptif!I"&L$13)=Recap_equipements!$B29,INDIRECT("Descriptif!I"&L$13)=Recap_equipements!$C29),INDIRECT("Descriptif!M"&L$13)=$D29),INDIRECT("Descriptif!F"&L$13),"") | ... T29: =IF(AND(OR(INDIRECT("Descriptif!I"&S$13)=Recap_equipements!$B29,INDIRECT("Descriptif!I"&S$13)=Recap_equipements!$C29),INDIRECT("Descriptif!M"&S$13)=$D29),INDIRECT("Descriptif!F"&S$13),"")
D30: =$D$8 -> Débitmètre gravitaire | F30: =IF(AND(OR(INDIRECT("Descriptif!I"&E$13)=Recap_equipements!$B29,INDIRECT("Descriptif!I"&E$13)=Recap_equipements!$C29),INDIRECT("Descriptif!M"&E$13)=$D30),INDIRECT("Descriptif!F"&E$13),"") | G30: =IF(AND(OR(INDIRECT("Descriptif!I"&F$13)=Recap_equipements!$B29,INDIRECT("Descriptif!I"&F$13)=Recap_equipements!$C29),INDIRECT("Descriptif!M"&F$13)=$D30),INDIRECT("Descriptif!F"&F$13),"") | H30: =IF(AND(OR(INDIRECT("Descriptif!I"&G$13)=Recap_equipements!$B29,INDIRECT("Descriptif!I"&G$13)=Recap_equipements!$C29),INDIRECT("Descriptif!M"&G$13)=$D30),INDIRECT("Descriptif!F"&G$13),"") | I30: =IF(AND(OR(INDIRECT("Descriptif!I"&H$13)=Recap_equipements!$B29,INDIRECT("Descriptif!I"&H$13)=Recap_equipements!$C29),INDIRECT("Descriptif!M"&H$13)=$D30),INDIRECT("Descriptif!F"&H$13),"") | J30: =IF(AND(OR(INDIRECT("Descriptif!I"&I$13)=Recap_equipements!$B29,INDIRECT("Descriptif!I"&I$13)=Recap_equipements!$C29),INDIRECT("Descriptif!M"&I$13)=$D30),INDIRECT("Descriptif!F"&I$13),"") | K30: =IF(AND(OR(INDIRECT("Descriptif!I"&J$13)=Recap_equipements!$B29,INDIRECT("Descriptif!I"&J$13)=Recap_equipements!$C29),INDIRECT("Descriptif!M"&J$13)=$D30),INDIRECT("Descriptif!F"&J$13),"") | L30: =IF(AND(OR(INDIRECT("Descriptif!I"&K$13)=Recap_equipements!$B29,INDIRECT("Descriptif!I"&K$13)=Recap_equipements!$C29),INDIRECT("Descriptif!M"&K$13)=$D30),INDIRECT("Descriptif!F"&K$13),"") | M30: =IF(AND(OR(INDIRECT("Descriptif!I"&L$13)=Recap_equipements!$B29,INDIRECT("Descriptif!I"&L$13)=Recap_equipements!$C29),INDIRECT("Descriptif!M"&L$13)=$D30),INDIRECT("Descriptif!F"&L$13),"") | ... T30: =IF(AND(OR(INDIRECT("Descriptif!I"&S$13)=Recap_equipements!$B29,INDIRECT("Descriptif!I"&S$13)=Recap_equipements!$C29),INDIRECT("Descriptif!M"&S$13)=$D30),INDIRECT("Descriptif!F"&S$13),"")
D31: =$D$9 -> Préleveur | F31: =IF(AND(OR(INDIRECT("Descriptif!I"&E$13)=Recap_equipements!$B29,INDIRECT("Descriptif!I"&E$13)=Recap_equipements!$C29),INDIRECT("Descriptif!M"&E$13)=$D31),INDIRECT("Descriptif!F"&E$13),"") | G31: =IF(AND(OR(INDIRECT("Descriptif!I"&F$13)=Recap_equipements!$B29,INDIRECT("Descriptif!I"&F$13)=Recap_equipements!$C29),INDIRECT("Descriptif!M"&F$13)=$D31),INDIRECT("Descriptif!F"&F$13),"") | H31: =IF(AND(OR(INDIRECT("Descriptif!I"&G$13)=Recap_equipements!$B29,INDIRECT("Descriptif!I"&G$13)=Recap_equipements!$C29),INDIRECT("Descriptif!M"&G$13)=$D31),INDIRECT("Descriptif!F"&G$13),"") | I31: =IF(AND(OR(INDIRECT("Descriptif!I"&H$13)=Recap_equipements!$B29,INDIRECT("Descriptif!I"&H$13)=Recap_equipements!$C29),INDIRECT("Descriptif!M"&H$13)=$D31),INDIRECT("Descriptif!F"&H$13),"") | J31: =IF(AND(OR(INDIRECT("Descriptif!I"&I$13)=Recap_equipements!$B29,INDIRECT("Descriptif!I"&I$13)=Recap_equipements!$C29),INDIRECT("Descriptif!M"&I$13)=$D31),INDIRECT("Descriptif!F"&I$13),"") | K31: =IF(AND(OR(INDIRECT("Descriptif!I"&J$13)=Recap_equipements!$B29,INDIRECT("Descriptif!I"&J$13)=Recap_equipements!$C29),INDIRECT("Descriptif!M"&J$13)=$D31),INDIRECT("Descriptif!F"&J$13),"") | L31: =IF(AND(OR(INDIRECT("Descriptif!I"&K$13)=Recap_equipements!$B29,INDIRECT("Descriptif!I"&K$13)=Recap_equipements!$C29),INDIRECT("Descriptif!M"&K$13)=$D31),INDIRECT("Descriptif!F"&K$13),"") | M31: =IF(AND(OR(INDIRECT("Descriptif!I"&L$13)=Recap_equipements!$B29,INDIRECT("Descriptif!I"&L$13)=Recap_equipements!$C29),INDIRECT("Descriptif!M"&L$13)=$D31),INDIRECT("Descriptif!F"&L$13),"") | ... T31: =IF(AND(OR(INDIRECT("Descriptif!I"&S$13)=Recap_equipements!$B29,INDIRECT("Descriptif!I"&S$13)=Recap_equipements!$C29),INDIRECT("Descriptif!M"&S$13)=$D31),INDIRECT("Descriptif!F"&S$13),"")
D32: Analytique | F32: =IF(F31<>"",VLOOKUP(F31,Analytique!$X$3:$AD$36,1,FALSE),"") | G32: =IF(G31<>"",VLOOKUP(G31,Analytique!$X$3:$AD$36,1,FALSE),"") | H32: =IF(H31<>"",VLOOKUP(H31,Analytique!$X$3:$AD$36,1,FALSE),"") | I32: =IF(I31<>"",VLOOKUP(I31,Analytique!$X$3:$AD$36,1,FALSE),"") | J32: =IF(J31<>"",VLOOKUP(J31,Analytique!$X$3:$AD$36,1,FALSE),"") | K32: =IF(K31<>"",VLOOKUP(K31,Analytique!$X$3:$AD$36,1,FALSE),"") | L32: =IF(L31<>"",VLOOKUP(L31,Analytique!$X$3:$AD$36,1,FALSE),"") | M32: =IF(M31<>"",VLOOKUP(M31,Analytique!$X$3:$AD$36,1,FALSE),"") | ... T32: =IF(T31<>"",VLOOKUP(T31,Analytique!$X$3:$AD$36,1,FALSE),"")
D33: =$D$10 -> Sonde de température | F33: =IF(AND(OR(INDIRECT("Descriptif!I"&E$13)=Recap_equipements!$B29,INDIRECT("Descriptif!I"&E$13)=Recap_equipements!$C29),INDIRECT("Descriptif!M"&E$13)=$D33),INDIRECT("Descriptif!F"&E$13),"") | G33: =IF(AND(OR(INDIRECT("Descriptif!I"&F$13)=Recap_equipements!$B29,INDIRECT("Descriptif!I"&F$13)=Recap_equipements!$C29),INDIRECT("Descriptif!M"&F$13)=$D33),INDIRECT("Descriptif!F"&F$13),"") | H33: =IF(AND(OR(INDIRECT("Descriptif!I"&G$13)=Recap_equipements!$B29,INDIRECT("Descriptif!I"&G$13)=Recap_equipements!$C29),INDIRECT("Descriptif!M"&G$13)=$D33),INDIRECT("Descriptif!F"&G$13),"") | I33: =IF(AND(OR(INDIRECT("Descriptif!I"&H$13)=Recap_equipements!$B29,INDIRECT("Descriptif!I"&H$13)=Recap_equipements!$C29),INDIRECT("Descriptif!M"&H$13)=$D33),INDIRECT("Descriptif!F"&H$13),"") | J33: =IF(AND(OR(INDIRECT("Descriptif!I"&I$13)=Recap_equipements!$B29,INDIRECT("Descriptif!I"&I$13)=Recap_equipements!$C29),INDIRECT("Descriptif!M"&I$13)=$D33),INDIRECT("Descriptif!F"&I$13),"") | K33: =IF(AND(OR(INDIRECT("Descriptif!I"&J$13)=Recap_equipements!$B29,INDIRECT("Descriptif!I"&J$13)=Recap_equipements!$C29),INDIRECT("Descriptif!M"&J$13)=$D33),INDIRECT("Descriptif!F"&J$13),"") | L33: =IF(AND(OR(INDIRECT("Descriptif!I"&K$13)=Recap_equipements!$B29,INDIRECT("Descriptif!I"&K$13)=Recap_equipements!$C29),INDIRECT("Descriptif!M"&K$13)=$D33),INDIRECT("Descriptif!F"&K$13),"") | M33: =IF(AND(OR(INDIRECT("Descriptif!I"&L$13)=Recap_equipements!$B29,INDIRECT("Descriptif!I"&L$13)=Recap_equipements!$C29),INDIRECT("Descriptif!M"&L$13)=$D33),INDIRECT("Descriptif!F"&L$13),"") | ... T33: =IF(AND(OR(INDIRECT("Descriptif!I"&S$13)=Recap_equipements!$B29,INDIRECT("Descriptif!I"&S$13)=Recap_equipements!$C29),INDIRECT("Descriptif!M"&S$13)=$D33),INDIRECT("Descriptif!F"&S$13),"")
B34: A5 | C34: S3 | D34: =$D$7 -> Débitmètre en charge | F34: =IF(AND(OR(INDIRECT("Descriptif!I"&E$13)=Recap_equipements!$B34,INDIRECT("Descriptif!I"&E$13)=Recap_equipements!$C34),INDIRECT("Descriptif!M"&E$13)=$D34),INDIRECT("Descriptif!F"&E$13),"") | G34: =IF(AND(OR(INDIRECT("Descriptif!I"&F$13)=Recap_equipements!$B34,INDIRECT("Descriptif!I"&F$13)=Recap_equipements!$C34),INDIRECT("Descriptif!M"&F$13)=$D34),INDIRECT("Descriptif!F"&F$13),"") | H34: =IF(AND(OR(INDIRECT("Descriptif!I"&G$13)=Recap_equipements!$B34,INDIRECT("Descriptif!I"&G$13)=Recap_equipements!$C34),INDIRECT("Descriptif!M"&G$13)=$D34),INDIRECT("Descriptif!F"&G$13),"") | I34: =IF(AND(OR(INDIRECT("Descriptif!I"&H$13)=Recap_equipements!$B34,INDIRECT("Descriptif!I"&H$13)=Recap_equipements!$C34),INDIRECT("Descriptif!M"&H$13)=$D34),INDIRECT("Descriptif!F"&H$13),"") | J34: =IF(AND(OR(INDIRECT("Descriptif!I"&I$13)=Recap_equipements!$B34,INDIRECT("Descriptif!I"&I$13)=Recap_equipements!$C34),INDIRECT("Descriptif!M"&I$13)=$D34),INDIRECT("Descriptif!F"&I$13),"") | K34: =IF(AND(OR(INDIRECT("Descriptif!I"&J$13)=Recap_equipements!$B34,INDIRECT("Descriptif!I"&J$13)=Recap_equipements!$C34),INDIRECT("Descriptif!M"&J$13)=$D34),INDIRECT("Descriptif!F"&J$13),"") | L34: =IF(AND(OR(INDIRECT("Descriptif!I"&K$13)=Recap_equipements!$B34,INDIRECT("Descriptif!I"&K$13)=Recap_equipements!$C34),INDIRECT("Descriptif!M"&K$13)=$D34),INDIRECT("Descriptif!F"&K$13),"") | M34: =IF(AND(OR(INDIRECT("Descriptif!I"&L$13)=Recap_equipements!$B34,INDIRECT("Descriptif!I"&L$13)=Recap_equipements!$C34),INDIRECT("Descriptif!M"&L$13)=$D34),INDIRECT("Descriptif!F"&L$13),"") | ... T34: =IF(AND(OR(INDIRECT("Descriptif!I"&S$13)=Recap_equipements!$B34,INDIRECT("Descriptif!I"&S$13)=Recap_equipements!$C34),INDIRECT("Descriptif!M"&S$13)=$D34),INDIRECT("Descriptif!F"&S$13),"")
D35: =$D$8 -> Débitmètre gravitaire | F35: =IF(AND(OR(INDIRECT("Descriptif!I"&E$13)=Recap_equipements!$B34,INDIRECT("Descriptif!I"&E$13)=Recap_equipements!$C34),INDIRECT("Descriptif!M"&E$13)=$D35),INDIRECT("Descriptif!F"&E$13),"") | G35: =IF(AND(OR(INDIRECT("Descriptif!I"&F$13)=Recap_equipements!$B34,INDIRECT("Descriptif!I"&F$13)=Recap_equipements!$C34),INDIRECT("Descriptif!M"&F$13)=$D35),INDIRECT("Descriptif!F"&F$13),"") | H35: =IF(AND(OR(INDIRECT("Descriptif!I"&G$13)=Recap_equipements!$B34,INDIRECT("Descriptif!I"&G$13)=Recap_equipements!$C34),INDIRECT("Descriptif!M"&G$13)=$D35),INDIRECT("Descriptif!F"&G$13),"") | I35: =IF(AND(OR(INDIRECT("Descriptif!I"&H$13)=Recap_equipements!$B34,INDIRECT("Descriptif!I"&H$13)=Recap_equipements!$C34),INDIRECT("Descriptif!M"&H$13)=$D35),INDIRECT("Descriptif!F"&H$13),"") | J35: =IF(AND(OR(INDIRECT("Descriptif!I"&I$13)=Recap_equipements!$B34,INDIRECT("Descriptif!I"&I$13)=Recap_equipements!$C34),INDIRECT("Descriptif!M"&I$13)=$D35),INDIRECT("Descriptif!F"&I$13),"") | K35: =IF(AND(OR(INDIRECT("Descriptif!I"&J$13)=Recap_equipements!$B34,INDIRECT("Descriptif!I"&J$13)=Recap_equipements!$C34),INDIRECT("Descriptif!M"&J$13)=$D35),INDIRECT("Descriptif!F"&J$13),"") | L35: =IF(AND(OR(INDIRECT("Descriptif!I"&K$13)=Recap_equipements!$B34,INDIRECT("Descriptif!I"&K$13)=Recap_equipements!$C34),INDIRECT("Descriptif!M"&K$13)=$D35),INDIRECT("Descriptif!F"&K$13),"") | M35: =IF(AND(OR(INDIRECT("Descriptif!I"&L$13)=Recap_equipements!$B34,INDIRECT("Descriptif!I"&L$13)=Recap_equipements!$C34),INDIRECT("Descriptif!M"&L$13)=$D35),INDIRECT("Descriptif!F"&L$13),"") | ... T35: =IF(AND(OR(INDIRECT("Descriptif!I"&S$13)=Recap_equipements!$B34,INDIRECT("Descriptif!I"&S$13)=Recap_equipements!$C34),INDIRECT("Descriptif!M"&S$13)=$D35),INDIRECT("Descriptif!F"&S$13),"")
D36: =$D$9 -> Préleveur | F36: =IF(AND(OR(INDIRECT("Descriptif!I"&E$13)=Recap_equipements!$B34,INDIRECT("Descriptif!I"&E$13)=Recap_equipements!$C34),INDIRECT("Descriptif!M"&E$13)=$D36),INDIRECT("Descriptif!F"&E$13),"") | G36: =IF(AND(OR(INDIRECT("Descriptif!I"&F$13)=Recap_equipements!$B34,INDIRECT("Descriptif!I"&F$13)=Recap_equipements!$C34),INDIRECT("Descriptif!M"&F$13)=$D36),INDIRECT("Descriptif!F"&F$13),"") | H36: =IF(AND(OR(INDIRECT("Descriptif!I"&G$13)=Recap_equipements!$B34,INDIRECT("Descriptif!I"&G$13)=Recap_equipements!$C34),INDIRECT("Descriptif!M"&G$13)=$D36),INDIRECT("Descriptif!F"&G$13),"") | I36: =IF(AND(OR(INDIRECT("Descriptif!I"&H$13)=Recap_equipements!$B34,INDIRECT("Descriptif!I"&H$13)=Recap_equipements!$C34),INDIRECT("Descriptif!M"&H$13)=$D36),INDIRECT("Descriptif!F"&H$13),"") | J36: =IF(AND(OR(INDIRECT("Descriptif!I"&I$13)=Recap_equipements!$B34,INDIRECT("Descriptif!I"&I$13)=Recap_equipements!$C34),INDIRECT("Descriptif!M"&I$13)=$D36),INDIRECT("Descriptif!F"&I$13),"") | K36: =IF(AND(OR(INDIRECT("Descriptif!I"&J$13)=Recap_equipements!$B34,INDIRECT("Descriptif!I"&J$13)=Recap_equipements!$C34),INDIRECT("Descriptif!M"&J$13)=$D36),INDIRECT("Descriptif!F"&J$13),"") | L36: =IF(AND(OR(INDIRECT("Descriptif!I"&K$13)=Recap_equipements!$B34,INDIRECT("Descriptif!I"&K$13)=Recap_equipements!$C34),INDIRECT("Descriptif!M"&K$13)=$D36),INDIRECT("Descriptif!F"&K$13),"") | M36: =IF(AND(OR(INDIRECT("Descriptif!I"&L$13)=Recap_equipements!$B34,INDIRECT("Descriptif!I"&L$13)=Recap_equipements!$C34),INDIRECT("Descriptif!M"&L$13)=$D36),INDIRECT("Descriptif!F"&L$13),"") | ... T36: =IF(AND(OR(INDIRECT("Descriptif!I"&S$13)=Recap_equipements!$B34,INDIRECT("Descriptif!I"&S$13)=Recap_equipements!$C34),INDIRECT("Descriptif!M"&S$13)=$D36),INDIRECT("Descriptif!F"&S$13),"")
D37: =$D$10 -> Sonde de température | F37: =IF(AND(OR(INDIRECT("Descriptif!I"&E$13)=Recap_equipements!$B34,INDIRECT("Descriptif!I"&E$13)=Recap_equipements!$C34),INDIRECT("Descriptif!M"&E$13)=$D37),INDIRECT("Descriptif!F"&E$13),"") | G37: =IF(AND(OR(INDIRECT("Descriptif!I"&F$13)=Recap_equipements!$B34,INDIRECT("Descriptif!I"&F$13)=Recap_equipements!$C34),INDIRECT("Descriptif!M"&F$13)=$D37),INDIRECT("Descriptif!F"&F$13),"") | H37: =IF(AND(OR(INDIRECT("Descriptif!I"&G$13)=Recap_equipements!$B34,INDIRECT("Descriptif!I"&G$13)=Recap_equipements!$C34),INDIRECT("Descriptif!M"&G$13)=$D37),INDIRECT("Descriptif!F"&G$13),"") | I37: =IF(AND(OR(INDIRECT("Descriptif!I"&H$13)=Recap_equipements!$B34,INDIRECT("Descriptif!I"&H$13)=Recap_equipements!$C34),INDIRECT("Descriptif!M"&H$13)=$D37),INDIRECT("Descriptif!F"&H$13),"") | J37: =IF(AND(OR(INDIRECT("Descriptif!I"&I$13)=Recap_equipements!$B34,INDIRECT("Descriptif!I"&I$13)=Recap_equipements!$C34),INDIRECT("Descriptif!M"&I$13)=$D37),INDIRECT("Descriptif!F"&I$13),"") | K37: =IF(AND(OR(INDIRECT("Descriptif!I"&J$13)=Recap_equipements!$B34,INDIRECT("Descriptif!I"&J$13)=Recap_equipements!$C34),INDIRECT("Descriptif!M"&J$13)=$D37),INDIRECT("Descriptif!F"&J$13),"") | L37: =IF(AND(OR(INDIRECT("Descriptif!I"&K$13)=Recap_equipements!$B34,INDIRECT("Descriptif!I"&K$13)=Recap_equipements!$C34),INDIRECT("Descriptif!M"&K$13)=$D37),INDIRECT("Descriptif!F"&K$13),"") | M37: =IF(AND(OR(INDIRECT("Descriptif!I"&L$13)=Recap_equipements!$B34,INDIRECT("Descriptif!I"&L$13)=Recap_equipements!$C34),INDIRECT("Descriptif!M"&L$13)=$D37),INDIRECT("Descriptif!F"&L$13),"") | ... T37: =IF(AND(OR(INDIRECT("Descriptif!I"&S$13)=Recap_equipements!$B34,INDIRECT("Descriptif!I"&S$13)=Recap_equipements!$C34),INDIRECT("Descriptif!M"&S$13)=$D37),INDIRECT("Descriptif!F"&S$13),"")
B38: A6 | C38: S4 | D38: =$D$7 -> Débitmètre en charge | F38: =IF(AND(OR(INDIRECT("Descriptif!I"&E$13)=Recap_equipements!$B38,INDIRECT("Descriptif!I"&E$13)=Recap_equipements!$C38),INDIRECT("Descriptif!M"&E$13)=$D38),INDIRECT("Descriptif!F"&E$13),"") | G38: =IF(AND(OR(INDIRECT("Descriptif!I"&F$13)=Recap_equipements!$B38,INDIRECT("Descriptif!I"&F$13)=Recap_equipements!$C38),INDIRECT("Descriptif!M"&F$13)=$D38),INDIRECT("Descriptif!F"&F$13),"") | H38: =IF(AND(OR(INDIRECT("Descriptif!I"&G$13)=Recap_equipements!$B38,INDIRECT("Descriptif!I"&G$13)=Recap_equipements!$C38),INDIRECT("Descriptif!M"&G$13)=$D38),INDIRECT("Descriptif!F"&G$13),"") | I38: =IF(AND(OR(INDIRECT("Descriptif!I"&H$13)=Recap_equipements!$B38,INDIRECT("Descriptif!I"&H$13)=Recap_equipements!$C38),INDIRECT("Descriptif!M"&H$13)=$D38),INDIRECT("Descriptif!F"&H$13),"") | J38: =IF(AND(OR(INDIRECT("Descriptif!I"&I$13)=Recap_equipements!$B38,INDIRECT("Descriptif!I"&I$13)=Recap_equipements!$C38),INDIRECT("Descriptif!M"&I$13)=$D38),INDIRECT("Descriptif!F"&I$13),"") | K38: =IF(AND(OR(INDIRECT("Descriptif!I"&J$13)=Recap_equipements!$B38,INDIRECT("Descriptif!I"&J$13)=Recap_equipements!$C38),INDIRECT("Descriptif!M"&J$13)=$D38),INDIRECT("Descriptif!F"&J$13),"") | L38: =IF(AND(OR(INDIRECT("Descriptif!I"&K$13)=Recap_equipements!$B38,INDIRECT("Descriptif!I"&K$13)=Recap_equipements!$C38),INDIRECT("Descriptif!M"&K$13)=$D38),INDIRECT("Descriptif!F"&K$13),"") | M38: =IF(AND(OR(INDIRECT("Descriptif!I"&L$13)=Recap_equipements!$B38,INDIRECT("Descriptif!I"&L$13)=Recap_equipements!$C38),INDIRECT("Descriptif!M"&L$13)=$D38),INDIRECT("Descriptif!F"&L$13),"") | ... T38: =IF(AND(OR(INDIRECT("Descriptif!I"&S$13)=Recap_equipements!$B38,INDIRECT("Descriptif!I"&S$13)=Recap_equipements!$C38),INDIRECT("Descriptif!M"&S$13)=$D38),INDIRECT("Descriptif!F"&S$13),"")
D39: =$D$8 -> Débitmètre gravitaire | F39: =IF(AND(OR(INDIRECT("Descriptif!I"&E$13)=Recap_equipements!$B38,INDIRECT("Descriptif!I"&E$13)=Recap_equipements!$C38),INDIRECT("Descriptif!M"&E$13)=$D39),INDIRECT("Descriptif!F"&E$13),"") | G39: =IF(AND(OR(INDIRECT("Descriptif!I"&F$13)=Recap_equipements!$B38,INDIRECT("Descriptif!I"&F$13)=Recap_equipements!$C38),INDIRECT("Descriptif!M"&F$13)=$D39),INDIRECT("Descriptif!F"&F$13),"") | H39: =IF(AND(OR(INDIRECT("Descriptif!I"&G$13)=Recap_equipements!$B38,INDIRECT("Descriptif!I"&G$13)=Recap_equipements!$C38),INDIRECT("Descriptif!M"&G$13)=$D39),INDIRECT("Descriptif!F"&G$13),"") | I39: =IF(AND(OR(INDIRECT("Descriptif!I"&H$13)=Recap_equipements!$B38,INDIRECT("Descriptif!I"&H$13)=Recap_equipements!$C38),INDIRECT("Descriptif!M"&H$13)=$D39),INDIRECT("Descriptif!F"&H$13),"") | J39: =IF(AND(OR(INDIRECT("Descriptif!I"&I$13)=Recap_equipements!$B38,INDIRECT("Descriptif!I"&I$13)=Recap_equipements!$C38),INDIRECT("Descriptif!M"&I$13)=$D39),INDIRECT("Descriptif!F"&I$13),"") | K39: =IF(AND(OR(INDIRECT("Descriptif!I"&J$13)=Recap_equipements!$B38,INDIRECT("Descriptif!I"&J$13)=Recap_equipements!$C38),INDIRECT("Descriptif!M"&J$13)=$D39),INDIRECT("Descriptif!F"&J$13),"") | L39: =IF(AND(OR(INDIRECT("Descriptif!I"&K$13)=Recap_equipements!$B38,INDIRECT("Descriptif!I"&K$13)=Recap_equipements!$C38),INDIRECT("Descriptif!M"&K$13)=$D39),INDIRECT("Descriptif!F"&K$13),"") | M39: =IF(AND(OR(INDIRECT("Descriptif!I"&L$13)=Recap_equipements!$B38,INDIRECT("Descriptif!I"&L$13)=Recap_equipements!$C38),INDIRECT("Descriptif!M"&L$13)=$D39),INDIRECT("Descriptif!F"&L$13),"") | ... T39: =IF(AND(OR(INDIRECT("Descriptif!I"&S$13)=Recap_equipements!$B38,INDIRECT("Descriptif!I"&S$13)=Recap_equipements!$C38),INDIRECT("Descriptif!M"&S$13)=$D39),INDIRECT("Descriptif!F"&S$13),"")
D40: =$D$9 -> Préleveur | F40: =IF(AND(OR(INDIRECT("Descriptif!I"&E$13)=Recap_equipements!$B38,INDIRECT("Descriptif!I"&E$13)=Recap_equipements!$C38),INDIRECT("Descriptif!M"&E$13)=$D40),INDIRECT("Descriptif!F"&E$13),"") | G40: =IF(AND(OR(INDIRECT("Descriptif!I"&F$13)=Recap_equipements!$B38,INDIRECT("Descriptif!I"&F$13)=Recap_equipements!$C38),INDIRECT("Descriptif!M"&F$13)=$D40),INDIRECT("Descriptif!F"&F$13),"") | H40: =IF(AND(OR(INDIRECT("Descriptif!I"&G$13)=Recap_equipements!$B38,INDIRECT("Descriptif!I"&G$13)=Recap_equipements!$C38),INDIRECT("Descriptif!M"&G$13)=$D40),INDIRECT("Descriptif!F"&G$13),"") | I40: =IF(AND(OR(INDIRECT("Descriptif!I"&H$13)=Recap_equipements!$B38,INDIRECT("Descriptif!I"&H$13)=Recap_equipements!$C38),INDIRECT("Descriptif!M"&H$13)=$D40),INDIRECT("Descriptif!F"&H$13),"") | J40: =IF(AND(OR(INDIRECT("Descriptif!I"&I$13)=Recap_equipements!$B38,INDIRECT("Descriptif!I"&I$13)=Recap_equipements!$C38),INDIRECT("Descriptif!M"&I$13)=$D40),INDIRECT("Descriptif!F"&I$13),"") | K40: =IF(AND(OR(INDIRECT("Descriptif!I"&J$13)=Recap_equipements!$B38,INDIRECT("Descriptif!I"&J$13)=Recap_equipements!$C38),INDIRECT("Descriptif!M"&J$13)=$D40),INDIRECT("Descriptif!F"&J$13),"") | L40: =IF(AND(OR(INDIRECT("Descriptif!I"&K$13)=Recap_equipements!$B38,INDIRECT("Descriptif!I"&K$13)=Recap_equipements!$C38),INDIRECT("Descriptif!M"&K$13)=$D40),INDIRECT("Descriptif!F"&K$13),"") | M40: =IF(AND(OR(INDIRECT("Descriptif!I"&L$13)=Recap_equipements!$B38,INDIRECT("Descriptif!I"&L$13)=Recap_equipements!$C38),INDIRECT("Descriptif!M"&L$13)=$D40),INDIRECT("Descriptif!F"&L$13),"") | ... T40: =IF(AND(OR(INDIRECT("Descriptif!I"&S$13)=Recap_equipements!$B38,INDIRECT("Descriptif!I"&S$13)=Recap_equipements!$C38),INDIRECT("Descriptif!M"&S$13)=$D40),INDIRECT("Descriptif!F"&S$13),"")
D41: Analytique | F41: =IF(F40<>"",VLOOKUP(F40,Analytique!$X$3:$AD$36,1,FALSE),"") | G41: =IF(G40<>"",VLOOKUP(G40,Analytique!$X$3:$AD$36,1,FALSE),"") | H41: =IF(H40<>"",VLOOKUP(H40,Analytique!$X$3:$AD$36,1,FALSE),"") | I41: =IF(I40<>"",VLOOKUP(I40,Analytique!$X$3:$AD$36,1,FALSE),"") | J41: =IF(J40<>"",VLOOKUP(J40,Analytique!$X$3:$AD$36,1,FALSE),"") | K41: =IF(K40<>"",VLOOKUP(K40,Analytique!$X$3:$AD$36,1,FALSE),"") | L41: =IF(L40<>"",VLOOKUP(L40,Analytique!$X$3:$AD$36,1,FALSE),"") | M41: =IF(M40<>"",VLOOKUP(M40,Analytique!$X$3:$AD$36,1,FALSE),"") | ... T41: =IF(T40<>"",VLOOKUP(T40,Analytique!$X$3:$AD$36,1,FALSE),"")
D42: =$D$10 -> Sonde de température | F42: =IF(AND(OR(INDIRECT("Descriptif!I"&E$13)=Recap_equipements!$B38,INDIRECT("Descriptif!I"&E$13)=Recap_equipements!$C38),INDIRECT("Descriptif!M"&E$13)=$D42),INDIRECT("Descriptif!F"&E$13),"") | G42: =IF(AND(OR(INDIRECT("Descriptif!I"&F$13)=Recap_equipements!$B38,INDIRECT("Descriptif!I"&F$13)=Recap_equipements!$C38),INDIRECT("Descriptif!M"&F$13)=$D42),INDIRECT("Descriptif!F"&F$13),"") | H42: =IF(AND(OR(INDIRECT("Descriptif!I"&G$13)=Recap_equipements!$B38,INDIRECT("Descriptif!I"&G$13)=Recap_equipements!$C38),INDIRECT("Descriptif!M"&G$13)=$D42),INDIRECT("Descriptif!F"&G$13),"") | I42: =IF(AND(OR(INDIRECT("Descriptif!I"&H$13)=Recap_equipements!$B38,INDIRECT("Descriptif!I"&H$13)=Recap_equipements!$C38),INDIRECT("Descriptif!M"&H$13)=$D42),INDIRECT("Descriptif!F"&H$13),"") | J42: =IF(AND(OR(INDIRECT("Descriptif!I"&I$13)=Recap_equipements!$B38,INDIRECT("Descriptif!I"&I$13)=Recap_equipements!$C38),INDIRECT("Descriptif!M"&I$13)=$D42),INDIRECT("Descriptif!F"&I$13),"") | K42: =IF(AND(OR(INDIRECT("Descriptif!I"&J$13)=Recap_equipements!$B38,INDIRECT("Descriptif!I"&J$13)=Recap_equipements!$C38),INDIRECT("Descriptif!M"&J$13)=$D42),INDIRECT("Descriptif!F"&J$13),"") | L42: =IF(AND(OR(INDIRECT("Descriptif!I"&K$13)=Recap_equipements!$B38,INDIRECT("Descriptif!I"&K$13)=Recap_equipements!$C38),INDIRECT("Descriptif!M"&K$13)=$D42),INDIRECT("Descriptif!F"&K$13),"") | M42: =IF(AND(OR(INDIRECT("Descriptif!I"&L$13)=Recap_equipements!$B38,INDIRECT("Descriptif!I"&L$13)=Recap_equipements!$C38),INDIRECT("Descriptif!M"&L$13)=$D42),INDIRECT("Descriptif!F"&L$13),"") | ... T42: =IF(AND(OR(INDIRECT("Descriptif!I"&S$13)=Recap_equipements!$B38,INDIRECT("Descriptif!I"&S$13)=Recap_equipements!$C38),INDIRECT("Descriptif!M"&S$13)=$D42),INDIRECT("Descriptif!F"&S$13),"")
B43: A7 | C43: S12 | D43: =$D$7 -> Débitmètre en charge | F43: =IF(AND(OR(INDIRECT("Descriptif!I"&E$13)=Recap_equipements!$B43,INDIRECT("Descriptif!I"&E$13)=Recap_equipements!$C43),INDIRECT("Descriptif!M"&E$13)=$D43),INDIRECT("Descriptif!F"&E$13),"") | G43: =IF(AND(OR(INDIRECT("Descriptif!I"&F$13)=Recap_equipements!$B43,INDIRECT("Descriptif!I"&F$13)=Recap_equipements!$C43),INDIRECT("Descriptif!M"&F$13)=$D43),INDIRECT("Descriptif!F"&F$13),"") | H43: =IF(AND(OR(INDIRECT("Descriptif!I"&G$13)=Recap_equipements!$B43,INDIRECT("Descriptif!I"&G$13)=Recap_equipements!$C43),INDIRECT("Descriptif!M"&G$13)=$D43),INDIRECT("Descriptif!F"&G$13),"") | I43: =IF(AND(OR(INDIRECT("Descriptif!I"&H$13)=Recap_equipements!$B43,INDIRECT("Descriptif!I"&H$13)=Recap_equipements!$C43),INDIRECT("Descriptif!M"&H$13)=$D43),INDIRECT("Descriptif!F"&H$13),"") | J43: =IF(AND(OR(INDIRECT("Descriptif!I"&I$13)=Recap_equipements!$B43,INDIRECT("Descriptif!I"&I$13)=Recap_equipements!$C43),INDIRECT("Descriptif!M"&I$13)=$D43),INDIRECT("Descriptif!F"&I$13),"") | K43: =IF(AND(OR(INDIRECT("Descriptif!I"&J$13)=Recap_equipements!$B43,INDIRECT("Descriptif!I"&J$13)=Recap_equipements!$C43),INDIRECT("Descriptif!M"&J$13)=$D43),INDIRECT("Descriptif!F"&J$13),"") | L43: =IF(AND(OR(INDIRECT("Descriptif!I"&K$13)=Recap_equipements!$B43,INDIRECT("Descriptif!I"&K$13)=Recap_equipements!$C43),INDIRECT("Descriptif!M"&K$13)=$D43),INDIRECT("Descriptif!F"&K$13),"") | M43: =IF(AND(OR(INDIRECT("Descriptif!I"&L$13)=Recap_equipements!$B43,INDIRECT("Descriptif!I"&L$13)=Recap_equipements!$C43),INDIRECT("Descriptif!M"&L$13)=$D43),INDIRECT("Descriptif!F"&L$13),"") | ... T43: =IF(AND(OR(INDIRECT("Descriptif!I"&S$13)=Recap_equipements!$B43,INDIRECT("Descriptif!I"&S$13)=Recap_equipements!$C43),INDIRECT("Descriptif!M"&S$13)=$D43),INDIRECT("Descriptif!F"&S$13),"")
D44: =$D$8 -> Débitmètre gravitaire | F44: =IF(AND(OR(INDIRECT("Descriptif!I"&E$13)=Recap_equipements!$B43,INDIRECT("Descriptif!I"&E$13)=Recap_equipements!$C43),INDIRECT("Descriptif!M"&E$13)=$D44),INDIRECT("Descriptif!F"&E$13),"") | G44: =IF(AND(OR(INDIRECT("Descriptif!I"&F$13)=Recap_equipements!$B43,INDIRECT("Descriptif!I"&F$13)=Recap_equipements!$C43),INDIRECT("Descriptif!M"&F$13)=$D44),INDIRECT("Descriptif!F"&F$13),"") | H44: =IF(AND(OR(INDIRECT("Descriptif!I"&G$13)=Recap_equipements!$B43,INDIRECT("Descriptif!I"&G$13)=Recap_equipements!$C43),INDIRECT("Descriptif!M"&G$13)=$D44),INDIRECT("Descriptif!F"&G$13),"") | I44: =IF(AND(OR(INDIRECT("Descriptif!I"&H$13)=Recap_equipements!$B43,INDIRECT("Descriptif!I"&H$13)=Recap_equipements!$C43),INDIRECT("Descriptif!M"&H$13)=$D44),INDIRECT("Descriptif!F"&H$13),"") | J44: =IF(AND(OR(INDIRECT("Descriptif!I"&I$13)=Recap_equipements!$B43,INDIRECT("Descriptif!I"&I$13)=Recap_equipements!$C43),INDIRECT("Descriptif!M"&I$13)=$D44),INDIRECT("Descriptif!F"&I$13),"") | K44: =IF(AND(OR(INDIRECT("Descriptif!I"&J$13)=Recap_equipements!$B43,INDIRECT("Descriptif!I"&J$13)=Recap_equipements!$C43),INDIRECT("Descriptif!M"&J$13)=$D44),INDIRECT("Descriptif!F"&J$13),"") | L44: =IF(AND(OR(INDIRECT("Descriptif!I"&K$13)=Recap_equipements!$B43,INDIRECT("Descriptif!I"&K$13)=Recap_equipements!$C43),INDIRECT("Descriptif!M"&K$13)=$D44),INDIRECT("Descriptif!F"&K$13),"") | M44: =IF(AND(OR(INDIRECT("Descriptif!I"&L$13)=Recap_equipements!$B43,INDIRECT("Descriptif!I"&L$13)=Recap_equipements!$C43),INDIRECT("Descriptif!M"&L$13)=$D44),INDIRECT("Descriptif!F"&L$13),"") | ... T44: =IF(AND(OR(INDIRECT("Descriptif!I"&S$13)=Recap_equipements!$B43,INDIRECT("Descriptif!I"&S$13)=Recap_equipements!$C43),INDIRECT("Descriptif!M"&S$13)=$D44),INDIRECT("Descriptif!F"&S$13),"")
D45: =$D$9 -> Préleveur | F45: =IF(AND(OR(INDIRECT("Descriptif!I"&E$13)=Recap_equipements!$B43,INDIRECT("Descriptif!I"&E$13)=Recap_equipements!$C43),INDIRECT("Descriptif!M"&E$13)=$D45),INDIRECT("Descriptif!F"&E$13),"") | G45: =IF(AND(OR(INDIRECT("Descriptif!I"&F$13)=Recap_equipements!$B43,INDIRECT("Descriptif!I"&F$13)=Recap_equipements!$C43),INDIRECT("Descriptif!M"&F$13)=$D45),INDIRECT("Descriptif!F"&F$13),"") | H45: =IF(AND(OR(INDIRECT("Descriptif!I"&G$13)=Recap_equipements!$B43,INDIRECT("Descriptif!I"&G$13)=Recap_equipements!$C43),INDIRECT("Descriptif!M"&G$13)=$D45),INDIRECT("Descriptif!F"&G$13),"") | I45: =IF(AND(OR(INDIRECT("Descriptif!I"&H$13)=Recap_equipements!$B43,INDIRECT("Descriptif!I"&H$13)=Recap_equipements!$C43),INDIRECT("Descriptif!M"&H$13)=$D45),INDIRECT("Descriptif!F"&H$13),"") | J45: =IF(AND(OR(INDIRECT("Descriptif!I"&I$13)=Recap_equipements!$B43,INDIRECT("Descriptif!I"&I$13)=Recap_equipements!$C43),INDIRECT("Descriptif!M"&I$13)=$D45),INDIRECT("Descriptif!F"&I$13),"") | K45: =IF(AND(OR(INDIRECT("Descriptif!I"&J$13)=Recap_equipements!$B43,INDIRECT("Descriptif!I"&J$13)=Recap_equipements!$C43),INDIRECT("Descriptif!M"&J$13)=$D45),INDIRECT("Descriptif!F"&J$13),"") | L45: =IF(AND(OR(INDIRECT("Descriptif!I"&K$13)=Recap_equipements!$B43,INDIRECT("Descriptif!I"&K$13)=Recap_equipements!$C43),INDIRECT("Descriptif!M"&K$13)=$D45),INDIRECT("Descriptif!F"&K$13),"") | M45: =IF(AND(OR(INDIRECT("Descriptif!I"&L$13)=Recap_equipements!$B43,INDIRECT("Descriptif!I"&L$13)=Recap_equipements!$C43),INDIRECT("Descriptif!M"&L$13)=$D45),INDIRECT("Descriptif!F"&L$13),"") | ... T45: =IF(AND(OR(INDIRECT("Descriptif!I"&S$13)=Recap_equipements!$B43,INDIRECT("Descriptif!I"&S$13)=Recap_equipements!$C43),INDIRECT("Descriptif!M"&S$13)=$D45),INDIRECT("Descriptif!F"&S$13),"")
D46: Analytique | F46: =IF(F45<>"",VLOOKUP(F45,Analytique!$X$3:$AD$36,1,FALSE),"") | G46: =IF(G45<>"",VLOOKUP(G45,Analytique!$X$3:$AD$36,1,FALSE),"") | H46: =IF(H45<>"",VLOOKUP(H45,Analytique!$X$3:$AD$36,1,FALSE),"") | I46: =IF(I45<>"",VLOOKUP(I45,Analytique!$X$3:$AD$36,1,FALSE),"") | J46: =IF(J45<>"",VLOOKUP(J45,Analytique!$X$3:$AD$36,1,FALSE),"") | K46: =IF(K45<>"",VLOOKUP(K45,Analytique!$X$3:$AD$36,1,FALSE),"") | L46: =IF(L45<>"",VLOOKUP(L45,Analytique!$X$3:$AD$36,1,FALSE),"") | M46: =IF(M45<>"",VLOOKUP(M45,Analytique!$X$3:$AD$36,1,FALSE),"") | ... T46: =IF(T45<>"",VLOOKUP(T45,Analytique!$X$3:$AD$36,1,FALSE),"")
D47: =$D$10 -> Sonde de température | F47: =IF(AND(OR(INDIRECT("Descriptif!I"&E$13)=Recap_equipements!$B43,INDIRECT("Descriptif!I"&E$13)=Recap_equipements!$C43),INDIRECT("Descriptif!M"&E$13)=$D47),INDIRECT("Descriptif!F"&E$13),"") | G47: =IF(AND(OR(INDIRECT("Descriptif!I"&F$13)=Recap_equipements!$B43,INDIRECT("Descriptif!I"&F$13)=Recap_equipements!$C43),INDIRECT("Descriptif!M"&F$13)=$D47),INDIRECT("Descriptif!F"&F$13),"") | H47: =IF(AND(OR(INDIRECT("Descriptif!I"&G$13)=Recap_equipements!$B43,INDIRECT("Descriptif!I"&G$13)=Recap_equipements!$C43),INDIRECT("Descriptif!M"&G$13)=$D47),INDIRECT("Descriptif!F"&G$13),"") | I47: =IF(AND(OR(INDIRECT("Descriptif!I"&H$13)=Recap_equipements!$B43,INDIRECT("Descriptif!I"&H$13)=Recap_equipements!$C43),INDIRECT("Descriptif!M"&H$13)=$D47),INDIRECT("Descriptif!F"&H$13),"") | J47: =IF(AND(OR(INDIRECT("Descriptif!I"&I$13)=Recap_equipements!$B43,INDIRECT("Descriptif!I"&I$13)=Recap_equipements!$C43),INDIRECT("Descriptif!M"&I$13)=$D47),INDIRECT("Descriptif!F"&I$13),"") | K47: =IF(AND(OR(INDIRECT("Descriptif!I"&J$13)=Recap_equipements!$B43,INDIRECT("Descriptif!I"&J$13)=Recap_equipements!$C43),INDIRECT("Descriptif!M"&J$13)=$D47),INDIRECT("Descriptif!F"&J$13),"") | L47: =IF(AND(OR(INDIRECT("Descriptif!I"&K$13)=Recap_equipements!$B43,INDIRECT("Descriptif!I"&K$13)=Recap_equipements!$C43),INDIRECT("Descriptif!M"&K$13)=$D47),INDIRECT("Descriptif!F"&K$13),"") | M47: =IF(AND(OR(INDIRECT("Descriptif!I"&L$13)=Recap_equipements!$B43,INDIRECT("Descriptif!I"&L$13)=Recap_equipements!$C43),INDIRECT("Descriptif!M"&L$13)=$D47),INDIRECT("Descriptif!F"&L$13),"") | ... T47: =IF(AND(OR(INDIRECT("Descriptif!I"&S$13)=Recap_equipements!$B43,INDIRECT("Descriptif!I"&S$13)=Recap_equipements!$C43),INDIRECT("Descriptif!M"&S$13)=$D47),INDIRECT("Descriptif!F"&S$13),"")
B48: A1 | C48: R1 | D48: =$D$7 -> Débitmètre en charge | F48: =IF(AND(OR(INDIRECT("Descriptif!I"&E$14)=Recap_equipements!$B48,INDIRECT("Descriptif!I"&E$14)=Recap_equipements!$C48),INDIRECT("Descriptif!M"&E$14)=$D48),INDIRECT("Descriptif!F"&E$14),"") | G48: =IF(AND(OR(INDIRECT("Descriptif!I"&F$14)=Recap_equipements!$B48,INDIRECT("Descriptif!I"&F$14)=Recap_equipements!$C48),INDIRECT("Descriptif!M"&F$14)=$D48),INDIRECT("Descriptif!F"&F$14),"") | H48: =IF(AND(OR(INDIRECT("Descriptif!I"&G$14)=Recap_equipements!$B48,INDIRECT("Descriptif!I"&G$14)=Recap_equipements!$C48),INDIRECT("Descriptif!M"&G$14)=$D48),INDIRECT("Descriptif!F"&G$14),"") | I48: =IF(AND(OR(INDIRECT("Descriptif!I"&H$14)=Recap_equipements!$B48,INDIRECT("Descriptif!I"&H$14)=Recap_equipements!$C48),INDIRECT("Descriptif!M"&H$14)=$D48),INDIRECT("Descriptif!F"&H$14),"") | J48: =IF(AND(OR(INDIRECT("Descriptif!I"&I$14)=Recap_equipements!$B48,INDIRECT("Descriptif!I"&I$14)=Recap_equipements!$C48),INDIRECT("Descriptif!M"&I$14)=$D48),INDIRECT("Descriptif!F"&I$14),"") | K48: =IF(AND(OR(INDIRECT("Descriptif!I"&J$14)=Recap_equipements!$B48,INDIRECT("Descriptif!I"&J$14)=Recap_equipements!$C48),INDIRECT("Descriptif!M"&J$14)=$D48),INDIRECT("Descriptif!F"&J$14),"") | L48: =IF(AND(OR(INDIRECT("Descriptif!I"&K$14)=Recap_equipements!$B48,INDIRECT("Descriptif!I"&K$14)=Recap_equipements!$C48),INDIRECT("Descriptif!M"&K$14)=$D48),INDIRECT("Descriptif!F"&K$14),"") | M48: =IF(AND(OR(INDIRECT("Descriptif!I"&L$14)=Recap_equipements!$B48,INDIRECT("Descriptif!I"&L$14)=Recap_equipements!$C48),INDIRECT("Descriptif!M"&L$14)=$D48),INDIRECT("Descriptif!F"&L$14),"") | ... T48: =IF(AND(OR(INDIRECT("Descriptif!I"&S$14)=Recap_equipements!$B48,INDIRECT("Descriptif!I"&S$14)=Recap_equipements!$C48),INDIRECT("Descriptif!M"&S$14)=$D48),INDIRECT("Descriptif!F"&S$14),"")
D49: =$D$8 -> Débitmètre gravitaire | F49: =IF(AND(OR(INDIRECT("Descriptif!I"&E$14)=Recap_equipements!$B48,INDIRECT("Descriptif!I"&E$14)=Recap_equipements!$C48),INDIRECT("Descriptif!M"&E$14)=$D49),INDIRECT("Descriptif!F"&E$14),"") | G49: =IF(AND(OR(INDIRECT("Descriptif!I"&F$14)=Recap_equipements!$B48,INDIRECT("Descriptif!I"&F$14)=Recap_equipements!$C48),INDIRECT("Descriptif!M"&F$14)=$D49),INDIRECT("Descriptif!F"&F$14),"") | H49: =IF(AND(OR(INDIRECT("Descriptif!I"&G$14)=Recap_equipements!$B48,INDIRECT("Descriptif!I"&G$14)=Recap_equipements!$C48),INDIRECT("Descriptif!M"&G$14)=$D49),INDIRECT("Descriptif!F"&G$14),"") | I49: =IF(AND(OR(INDIRECT("Descriptif!I"&H$14)=Recap_equipements!$B48,INDIRECT("Descriptif!I"&H$14)=Recap_equipements!$C48),INDIRECT("Descriptif!M"&H$14)=$D49),INDIRECT("Descriptif!F"&H$14),"") | J49: =IF(AND(OR(INDIRECT("Descriptif!I"&I$14)=Recap_equipements!$B48,INDIRECT("Descriptif!I"&I$14)=Recap_equipements!$C48),INDIRECT("Descriptif!M"&I$14)=$D49),INDIRECT("Descriptif!F"&I$14),"") | K49: =IF(AND(OR(INDIRECT("Descriptif!I"&J$14)=Recap_equipements!$B48,INDIRECT("Descriptif!I"&J$14)=Recap_equipements!$C48),INDIRECT("Descriptif!M"&J$14)=$D49),INDIRECT("Descriptif!F"&J$14),"") | L49: =IF(AND(OR(INDIRECT("Descriptif!I"&K$14)=Recap_equipements!$B48,INDIRECT("Descriptif!I"&K$14)=Recap_equipements!$C48),INDIRECT("Descriptif!M"&K$14)=$D49),INDIRECT("Descriptif!F"&K$14),"") | M49: =IF(AND(OR(INDIRECT("Descriptif!I"&L$14)=Recap_equipements!$B48,INDIRECT("Descriptif!I"&L$14)=Recap_equipements!$C48),INDIRECT("Descriptif!M"&L$14)=$D49),INDIRECT("Descriptif!F"&L$14),"") | ... T49: =IF(AND(OR(INDIRECT("Descriptif!I"&S$14)=Recap_equipements!$B48,INDIRECT("Descriptif!I"&S$14)=Recap_equipements!$C48),INDIRECT("Descriptif!M"&S$14)=$D49),INDIRECT("Descriptif!F"&S$14),"")
D50: =$D$9 -> Préleveur | F50: =IF(AND(OR(INDIRECT("Descriptif!I"&E$14)=Recap_equipements!$B48,INDIRECT("Descriptif!I"&E$14)=Recap_equipements!$C48),INDIRECT("Descriptif!M"&E$14)=$D50),INDIRECT("Descriptif!F"&E$14),"") | G50: =IF(AND(OR(INDIRECT("Descriptif!I"&F$14)=Recap_equipements!$B48,INDIRECT("Descriptif!I"&F$14)=Recap_equipements!$C48),INDIRECT("Descriptif!M"&F$14)=$D50),INDIRECT("Descriptif!F"&F$14),"") | H50: =IF(AND(OR(INDIRECT("Descriptif!I"&G$14)=Recap_equipements!$B48,INDIRECT("Descriptif!I"&G$14)=Recap_equipements!$C48),INDIRECT("Descriptif!M"&G$14)=$D50),INDIRECT("Descriptif!F"&G$14),"") | I50: =IF(AND(OR(INDIRECT("Descriptif!I"&H$14)=Recap_equipements!$B48,INDIRECT("Descriptif!I"&H$14)=Recap_equipements!$C48),INDIRECT("Descriptif!M"&H$14)=$D50),INDIRECT("Descriptif!F"&H$14),"") | J50: =IF(AND(OR(INDIRECT("Descriptif!I"&I$14)=Recap_equipements!$B48,INDIRECT("Descriptif!I"&I$14)=Recap_equipements!$C48),INDIRECT("Descriptif!M"&I$14)=$D50),INDIRECT("Descriptif!F"&I$14),"") | K50: =IF(AND(OR(INDIRECT("Descriptif!I"&J$14)=Recap_equipements!$B48,INDIRECT("Descriptif!I"&J$14)=Recap_equipements!$C48),INDIRECT("Descriptif!M"&J$14)=$D50),INDIRECT("Descriptif!F"&J$14),"") | L50: =IF(AND(OR(INDIRECT("Descriptif!I"&K$14)=Recap_equipements!$B48,INDIRECT("Descriptif!I"&K$14)=Recap_equipements!$C48),INDIRECT("Descriptif!M"&K$14)=$D50),INDIRECT("Descriptif!F"&K$14),"") | M50: =IF(AND(OR(INDIRECT("Descriptif!I"&L$14)=Recap_equipements!$B48,INDIRECT("Descriptif!I"&L$14)=Recap_equipements!$C48),INDIRECT("Descriptif!M"&L$14)=$D50),INDIRECT("Descriptif!F"&L$14),"") | ... T50: =IF(AND(OR(INDIRECT("Descriptif!I"&S$14)=Recap_equipements!$B48,INDIRECT("Descriptif!I"&S$14)=Recap_equipements!$C48),INDIRECT("Descriptif!M"&S$14)=$D50),INDIRECT("Descriptif!F"&S$14),"")
D51: Analytique | F51: =IF(F50<>"",VLOOKUP(F50,Analytique!$X$3:$AD$36,1,FALSE),"") | G51: =IF(G50<>"",VLOOKUP(G50,Analytique!$X$3:$AD$36,1,FALSE),"") | H51: =IF(H50<>"",VLOOKUP(H50,Analytique!$X$3:$AD$36,1,FALSE),"") | I51: =IF(I50<>"",VLOOKUP(I50,Analytique!$X$3:$AD$36,1,FALSE),"") | J51: =IF(J50<>"",VLOOKUP(J50,Analytique!$X$3:$AD$36,1,FALSE),"") | K51: =IF(K50<>"",VLOOKUP(K50,Analytique!$X$3:$AD$36,1,FALSE),"") | L51: =IF(L50<>"",VLOOKUP(L50,Analytique!$X$3:$AD$36,1,FALSE),"") | M51: =IF(M50<>"",VLOOKUP(M50,Analytique!$X$3:$AD$36,1,FALSE),"") | ... T51: =IF(T50<>"",VLOOKUP(T50,Analytique!$X$3:$AD$36,1,FALSE),"")
D52: =$D$10 -> Sonde de température | F52: =IF(AND(OR(INDIRECT("Descriptif!I"&E$14)=Recap_equipements!$B48,INDIRECT("Descriptif!I"&E$14)=Recap_equipements!$C48),INDIRECT("Descriptif!M"&E$14)=$D52),INDIRECT("Descriptif!F"&E$14),"") | G52: =IF(AND(OR(INDIRECT("Descriptif!I"&F$14)=Recap_equipements!$B48,INDIRECT("Descriptif!I"&F$14)=Recap_equipements!$C48),INDIRECT("Descriptif!M"&F$14)=$D52),INDIRECT("Descriptif!F"&F$14),"") | H52: =IF(AND(OR(INDIRECT("Descriptif!I"&G$14)=Recap_equipements!$B48,INDIRECT("Descriptif!I"&G$14)=Recap_equipements!$C48),INDIRECT("Descriptif!M"&G$14)=$D52),INDIRECT("Descriptif!F"&G$14),"") | I52: =IF(AND(OR(INDIRECT("Descriptif!I"&H$14)=Recap_equipements!$B48,INDIRECT("Descriptif!I"&H$14)=Recap_equipements!$C48),INDIRECT("Descriptif!M"&H$14)=$D52),INDIRECT("Descriptif!F"&H$14),"") | J52: =IF(AND(OR(INDIRECT("Descriptif!I"&I$14)=Recap_equipements!$B48,INDIRECT("Descriptif!I"&I$14)=Recap_equipements!$C48),INDIRECT("Descriptif!M"&I$14)=$D52),INDIRECT("Descriptif!F"&I$14),"") | K52: =IF(AND(OR(INDIRECT("Descriptif!I"&J$14)=Recap_equipements!$B48,INDIRECT("Descriptif!I"&J$14)=Recap_equipements!$C48),INDIRECT("Descriptif!M"&J$14)=$D52),INDIRECT("Descriptif!F"&J$14),"") | L52: =IF(AND(OR(INDIRECT("Descriptif!I"&K$14)=Recap_equipements!$B48,INDIRECT("Descriptif!I"&K$14)=Recap_equipements!$C48),INDIRECT("Descriptif!M"&K$14)=$D52),INDIRECT("Descriptif!F"&K$14),"") | M52: =IF(AND(OR(INDIRECT("Descriptif!I"&L$14)=Recap_equipements!$B48,INDIRECT("Descriptif!I"&L$14)=Recap_equipements!$C48),INDIRECT("Descriptif!M"&L$14)=$D52),INDIRECT("Descriptif!F"&L$14),"") | ... T52: =IF(AND(OR(INDIRECT("Descriptif!I"&S$14)=Recap_equipements!$B48,INDIRECT("Descriptif!I"&S$14)=Recap_equipements!$C48),INDIRECT("Descriptif!M"&S$14)=$D52),INDIRECT("Descriptif!F"&S$14),"")
B53: A8 | C53: S19 | D53: =$D$7 -> Débitmètre en charge | F53: =IF(AND(OR(INDIRECT("Descriptif!I"&E$13)=Recap_equipements!$B53,INDIRECT("Descriptif!I"&E$13)=Recap_equipements!$C53),INDIRECT("Descriptif!M"&E$13)=$D53),INDIRECT("Descriptif!F"&E$13),"") | G53: =IF(AND(OR(INDIRECT("Descriptif!I"&F$13)=Recap_equipements!$B53,INDIRECT("Descriptif!I"&F$13)=Recap_equipements!$C53),INDIRECT("Descriptif!M"&F$13)=$D53),INDIRECT("Descriptif!F"&F$13),"") | H53: =IF(AND(OR(INDIRECT("Descriptif!I"&G$13)=Recap_equipements!$B53,INDIRECT("Descriptif!I"&G$13)=Recap_equipements!$C53),INDIRECT("Descriptif!M"&G$13)=$D53),INDIRECT("Descriptif!F"&G$13),"") | I53: =IF(AND(OR(INDIRECT("Descriptif!I"&H$13)=Recap_equipements!$B53,INDIRECT("Descriptif!I"&H$13)=Recap_equipements!$C53),INDIRECT("Descriptif!M"&H$13)=$D53),INDIRECT("Descriptif!F"&H$13),"") | J53: =IF(AND(OR(INDIRECT("Descriptif!I"&I$13)=Recap_equipements!$B53,INDIRECT("Descriptif!I"&I$13)=Recap_equipements!$C53),INDIRECT("Descriptif!M"&I$13)=$D53),INDIRECT("Descriptif!F"&I$13),"") | K53: =IF(AND(OR(INDIRECT("Descriptif!I"&J$13)=Recap_equipements!$B53,INDIRECT("Descriptif!I"&J$13)=Recap_equipements!$C53),INDIRECT("Descriptif!M"&J$13)=$D53),INDIRECT("Descriptif!F"&J$13),"") | L53: =IF(AND(OR(INDIRECT("Descriptif!I"&K$13)=Recap_equipements!$B53,INDIRECT("Descriptif!I"&K$13)=Recap_equipements!$C53),INDIRECT("Descriptif!M"&K$13)=$D53),INDIRECT("Descriptif!F"&K$13),"") | M53: =IF(AND(OR(INDIRECT("Descriptif!I"&L$13)=Recap_equipements!$B53,INDIRECT("Descriptif!I"&L$13)=Recap_equipements!$C53),INDIRECT("Descriptif!M"&L$13)=$D53),INDIRECT("Descriptif!F"&L$13),"") | ... T53: =IF(AND(OR(INDIRECT("Descriptif!I"&S$13)=Recap_equipements!$B53,INDIRECT("Descriptif!I"&S$13)=Recap_equipements!$C53),INDIRECT("Descriptif!M"&S$13)=$D53),INDIRECT("Descriptif!F"&S$13),"")
D54: =$D$8 -> Débitmètre gravitaire | F54: =IF(AND(OR(INDIRECT("Descriptif!I"&E$13)=Recap_equipements!$B53,INDIRECT("Descriptif!I"&E$13)=Recap_equipements!$C53),INDIRECT("Descriptif!M"&E$13)=$D54),INDIRECT("Descriptif!F"&E$13),"") | G54: =IF(AND(OR(INDIRECT("Descriptif!I"&F$13)=Recap_equipements!$B53,INDIRECT("Descriptif!I"&F$13)=Recap_equipements!$C53),INDIRECT("Descriptif!M"&F$13)=$D54),INDIRECT("Descriptif!F"&F$13),"") | H54: =IF(AND(OR(INDIRECT("Descriptif!I"&G$13)=Recap_equipements!$B53,INDIRECT("Descriptif!I"&G$13)=Recap_equipements!$C53),INDIRECT("Descriptif!M"&G$13)=$D54),INDIRECT("Descriptif!F"&G$13),"") | I54: =IF(AND(OR(INDIRECT("Descriptif!I"&H$13)=Recap_equipements!$B53,INDIRECT("Descriptif!I"&H$13)=Recap_equipements!$C53),INDIRECT("Descriptif!M"&H$13)=$D54),INDIRECT("Descriptif!F"&H$13),"") | J54: =IF(AND(OR(INDIRECT("Descriptif!I"&I$13)=Recap_equipements!$B53,INDIRECT("Descriptif!I"&I$13)=Recap_equipements!$C53),INDIRECT("Descriptif!M"&I$13)=$D54),INDIRECT("Descriptif!F"&I$13),"") | K54: =IF(AND(OR(INDIRECT("Descriptif!I"&J$13)=Recap_equipements!$B53,INDIRECT("Descriptif!I"&J$13)=Recap_equipements!$C53),INDIRECT("Descriptif!M"&J$13)=$D54),INDIRECT("Descriptif!F"&J$13),"") | L54: =IF(AND(OR(INDIRECT("Descriptif!I"&K$13)=Recap_equipements!$B53,INDIRECT("Descriptif!I"&K$13)=Recap_equipements!$C53),INDIRECT("Descriptif!M"&K$13)=$D54),INDIRECT("Descriptif!F"&K$13),"") | M54: =IF(AND(OR(INDIRECT("Descriptif!I"&L$13)=Recap_equipements!$B53,INDIRECT("Descriptif!I"&L$13)=Recap_equipements!$C53),INDIRECT("Descriptif!M"&L$13)=$D54),INDIRECT("Descriptif!F"&L$13),"") | ... T54: =IF(AND(OR(INDIRECT("Descriptif!I"&S$13)=Recap_equipements!$B53,INDIRECT("Descriptif!I"&S$13)=Recap_equipements!$C53),INDIRECT("Descriptif!M"&S$13)=$D54),INDIRECT("Descriptif!F"&S$13),"")
D55: =$D$9 -> Préleveur | F55: =IF(AND(OR(INDIRECT("Descriptif!I"&E$13)=Recap_equipements!$B53,INDIRECT("Descriptif!I"&E$13)=Recap_equipements!$C53),INDIRECT("Descriptif!M"&E$13)=$D55),INDIRECT("Descriptif!F"&E$13),"") | G55: =IF(AND(OR(INDIRECT("Descriptif!I"&F$13)=Recap_equipements!$B53,INDIRECT("Descriptif!I"&F$13)=Recap_equipements!$C53),INDIRECT("Descriptif!M"&F$13)=$D55),INDIRECT("Descriptif!F"&F$13),"") | H55: =IF(AND(OR(INDIRECT("Descriptif!I"&G$13)=Recap_equipements!$B53,INDIRECT("Descriptif!I"&G$13)=Recap_equipements!$C53),INDIRECT("Descriptif!M"&G$13)=$D55),INDIRECT("Descriptif!F"&G$13),"") | I55: =IF(AND(OR(INDIRECT("Descriptif!I"&H$13)=Recap_equipements!$B53,INDIRECT("Descriptif!I"&H$13)=Recap_equipements!$C53),INDIRECT("Descriptif!M"&H$13)=$D55),INDIRECT("Descriptif!F"&H$13),"") | J55: =IF(AND(OR(INDIRECT("Descriptif!I"&I$13)=Recap_equipements!$B53,INDIRECT("Descriptif!I"&I$13)=Recap_equipements!$C53),INDIRECT("Descriptif!M"&I$13)=$D55),INDIRECT("Descriptif!F"&I$13),"") | K55: =IF(AND(OR(INDIRECT("Descriptif!I"&J$13)=Recap_equipements!$B53,INDIRECT("Descriptif!I"&J$13)=Recap_equipements!$C53),INDIRECT("Descriptif!M"&J$13)=$D55),INDIRECT("Descriptif!F"&J$13),"") | L55: =IF(AND(OR(INDIRECT("Descriptif!I"&K$13)=Recap_equipements!$B53,INDIRECT("Descriptif!I"&K$13)=Recap_equipements!$C53),INDIRECT("Descriptif!M"&K$13)=$D55),INDIRECT("Descriptif!F"&K$13),"") | M55: =IF(AND(OR(INDIRECT("Descriptif!I"&L$13)=Recap_equipements!$B53,INDIRECT("Descriptif!I"&L$13)=Recap_equipements!$C53),INDIRECT("Descriptif!M"&L$13)=$D55),INDIRECT("Descriptif!F"&L$13),"") | ... T55: =IF(AND(OR(INDIRECT("Descriptif!I"&S$13)=Recap_equipements!$B53,INDIRECT("Descriptif!I"&S$13)=Recap_equipements!$C53),INDIRECT("Descriptif!M"&S$13)=$D55),INDIRECT("Descriptif!F"&S$13),"")
D56: Analytique | F56: =IF(F55<>"",VLOOKUP(F55,Analytique!$X$3:$AD$36,1,FALSE),"") | G56: =IF(G55<>"",VLOOKUP(G55,Analytique!$X$3:$AD$36,1,FALSE),"") | H56: =IF(H55<>"",VLOOKUP(H55,Analytique!$X$3:$AD$36,1,FALSE),"") | I56: =IF(I55<>"",VLOOKUP(I55,Analytique!$X$3:$AD$36,1,FALSE),"") | J56: =IF(J55<>"",VLOOKUP(J55,Analytique!$X$3:$AD$36,1,FALSE),"") | K56: =IF(K55<>"",VLOOKUP(K55,Analytique!$X$3:$AD$36,1,FALSE),"") | L56: =IF(L55<>"",VLOOKUP(L55,Analytique!$X$3:$AD$36,1,FALSE),"") | M56: =IF(M55<>"",VLOOKUP(M55,Analytique!$X$3:$AD$36,1,FALSE),"") | ... T56: =IF(T55<>"",VLOOKUP(T55,Analytique!$X$3:$AD$36,1,FALSE),"")
D57: =$D$10 -> Sonde de température | F57: =IF(AND(OR(INDIRECT("Descriptif!I"&E$13)=Recap_equipements!$B53,INDIRECT("Descriptif!I"&E$13)=Recap_equipements!$C53),INDIRECT("Descriptif!M"&E$13)=$D57),INDIRECT("Descriptif!F"&E$13),"") | G57: =IF(AND(OR(INDIRECT("Descriptif!I"&F$13)=Recap_equipements!$B53,INDIRECT("Descriptif!I"&F$13)=Recap_equipements!$C53),INDIRECT("Descriptif!M"&F$13)=$D57),INDIRECT("Descriptif!F"&F$13),"") | H57: =IF(AND(OR(INDIRECT("Descriptif!I"&G$13)=Recap_equipements!$B53,INDIRECT("Descriptif!I"&G$13)=Recap_equipements!$C53),INDIRECT("Descriptif!M"&G$13)=$D57),INDIRECT("Descriptif!F"&G$13),"") | I57: =IF(AND(OR(INDIRECT("Descriptif!I"&H$13)=Recap_equipements!$B53,INDIRECT("Descriptif!I"&H$13)=Recap_equipements!$C53),INDIRECT("Descriptif!M"&H$13)=$D57),INDIRECT("Descriptif!F"&H$13),"") | J57: =IF(AND(OR(INDIRECT("Descriptif!I"&I$13)=Recap_equipements!$B53,INDIRECT("Descriptif!I"&I$13)=Recap_equipements!$C53),INDIRECT("Descriptif!M"&I$13)=$D57),INDIRECT("Descriptif!F"&I$13),"") | K57: =IF(AND(OR(INDIRECT("Descriptif!I"&J$13)=Recap_equipements!$B53,INDIRECT("Descriptif!I"&J$13)=Recap_equipements!$C53),INDIRECT("Descriptif!M"&J$13)=$D57),INDIRECT("Descriptif!F"&J$13),"") | L57: =IF(AND(OR(INDIRECT("Descriptif!I"&K$13)=Recap_equipements!$B53,INDIRECT("Descriptif!I"&K$13)=Recap_equipements!$C53),INDIRECT("Descriptif!M"&K$13)=$D57),INDIRECT("Descriptif!F"&K$13),"") | M57: =IF(AND(OR(INDIRECT("Descriptif!I"&L$13)=Recap_equipements!$B53,INDIRECT("Descriptif!I"&L$13)=Recap_equipements!$C53),INDIRECT("Descriptif!M"&L$13)=$D57),INDIRECT("Descriptif!F"&L$13),"") | ... T57: =IF(AND(OR(INDIRECT("Descriptif!I"&S$13)=Recap_equipements!$B53,INDIRECT("Descriptif!I"&S$13)=Recap_equipements!$C53),INDIRECT("Descriptif!M"&S$13)=$D57),INDIRECT("Descriptif!F"&S$13),"")
B59: Scores
B60: Les évaluations des sondes de température ne sont pas prises en compte
B61: Reg. | C61: Log. | E61: Moyennes générales | F61: Moyennes individuelles | G61: Point 1 | H61: Point 2 | I61: Point 3 | J61: Point 4 | K61: Point 5 | L61: Point 6 | M61: Point 7 | N61: Point 8 | O61: Point 9 | P61: Point 10 | Q61: Point 11 | R61: Point 12 | S61: Point 13 | T61: Point 14 | U61: Point 15
B62: A3 | C62: S1 | D62: =$D$7 -> Débitmètre en charge | E62: =IFERROR(AVERAGE(F64:F66)*$B$5,"") | F62: =IFERROR(AVERAGE(G62:U62),"") | G62: =IF(F19<>"",_xlfn.SINGLE(INDIRECT(F19&"!"&$F$7)),"") | H62: =IF(G19<>"",_xlfn.SINGLE(INDIRECT(G19&"!"&$F$7)),"") | I62: =IF(H19<>"",_xlfn.SINGLE(INDIRECT(H19&"!"&$F$7)),"") | J62: =IF(I19<>"",_xlfn.SINGLE(INDIRECT(I19&"!"&$F$7)),"") | K62: =IF(J19<>"",_xlfn.SINGLE(INDIRECT(J19&"!"&$F$7)),"") | L62: =IF(K19<>"",_xlfn.SINGLE(INDIRECT(K19&"!"&$F$7)),"") | M62: =IF(L19<>"",_xlfn.SINGLE(INDIRECT(L19&"!"&$F$7)),"") | N62: =IF(M19<>"",_xlfn.SINGLE(INDIRECT(M19&"!"&$F$7)),"") | ... U62: =IF(T19<>"",_xlfn.SINGLE(INDIRECT(T19&"!"&$F$7)),"")
D63: =$D$8 -> Débitmètre gravitaire | F63: =IFERROR(AVERAGE(G63:U63),"") | G63: =IF(F20<>"",_xlfn.SINGLE(INDIRECT(F20&"!"&$F$8)),"") | H63: =IF(G20<>"",_xlfn.SINGLE(INDIRECT(G20&"!"&$F$8)),"") | I63: =IF(H20<>"",_xlfn.SINGLE(INDIRECT(H20&"!"&$F$8)),"") | J63: =IF(I20<>"",_xlfn.SINGLE(INDIRECT(I20&"!"&$F$8)),"") | K63: =IF(J20<>"",_xlfn.SINGLE(INDIRECT(J20&"!"&$F$8)),"") | L63: =IF(K20<>"",_xlfn.SINGLE(INDIRECT(K20&"!"&$F$8)),"") | M63: =IF(L20<>"",_xlfn.SINGLE(INDIRECT(L20&"!"&$F$8)),"") | N63: =IF(M20<>"",_xlfn.SINGLE(INDIRECT(M20&"!"&$F$8)),"") | ... U63: =IF(T20<>"",_xlfn.SINGLE(INDIRECT(T20&"!"&$F$8)),"")
D64: Débitmètre | F64: =IFERROR(AVERAGE(G64:U64),"") | G64: =IF(COUNT(G62:G63)>0,SUM(G62:G63),"") | H64: =IF(COUNT(H62:H63)>0,SUM(H62:H63),"") | I64: =IF(COUNT(I62:I63)>0,SUM(I62:I63),"") | J64: =IF(COUNT(J62:J63)>0,SUM(J62:J63),"") | K64: =IF(COUNT(K62:K63)>0,SUM(K62:K63),"") | L64: =IF(COUNT(L62:L63)>0,SUM(L62:L63),"") | M64: =IF(COUNT(M62:M63)>0,SUM(M62:M63),"") | N64: =IF(COUNT(N62:N63)>0,SUM(N62:N63),"") | ... U64: =IF(COUNT(U62:U63)>0,SUM(U62:U63),"")
D65: =$D$9 -> Préleveur | F65: =IFERROR(AVERAGE(G65:U65),"") | G65: =IF(F21<>"",_xlfn.SINGLE(INDIRECT(F21&"!"&$F$9)),"") | H65: =IF(G21<>"",_xlfn.SINGLE(INDIRECT(G21&"!"&$F$9)),"") | I65: =IF(H21<>"",_xlfn.SINGLE(INDIRECT(H21&"!"&$F$9)),"") | J65: =IF(I21<>"",_xlfn.SINGLE(INDIRECT(I21&"!"&$F$9)),"") | K65: =IF(J21<>"",_xlfn.SINGLE(INDIRECT(J21&"!"&$F$9)),"") | L65: =IF(K21<>"",_xlfn.SINGLE(INDIRECT(K21&"!"&$F$9)),"") | M65: =IF(L21<>"",_xlfn.SINGLE(INDIRECT(L21&"!"&$F$9)),"") | N65: =IF(M21<>"",_xlfn.SINGLE(INDIRECT(M21&"!"&$F$9)),"") | ... U65: =IF(T21<>"",_xlfn.SINGLE(INDIRECT(T21&"!"&$F$9)),"")
D66: Analytique | F66: =IFERROR(AVERAGE(G66:U66),"") | G66: =IF(F21<>"",VLOOKUP(F21,Analytique!$X$3:$AD$36,6,FALSE),"") | H66: =IF(G21<>"",VLOOKUP(G21,Analytique!$X$3:$AD$36,6,FALSE),"") | I66: =IF(H21<>"",VLOOKUP(H21,Analytique!$X$3:$AD$36,6,FALSE),"") | J66: =IF(I21<>"",VLOOKUP(I21,Analytique!$X$3:$AD$36,6,FALSE),"") | K66: =IF(J21<>"",VLOOKUP(J21,Analytique!$X$3:$AD$36,6,FALSE),"") | L66: =IF(K21<>"",VLOOKUP(K21,Analytique!$X$3:$AD$36,6,FALSE),"") | M66: =IF(L21<>"",VLOOKUP(L21,Analytique!$X$3:$AD$36,6,FALSE),"") | N66: =IF(M21<>"",VLOOKUP(M21,Analytique!$X$3:$AD$36,6,FALSE),"") | ... U66: =IF(T21<>"",VLOOKUP(T21,Analytique!$X$3:$AD$36,6,FALSE),"")
D67: =$D$10 -> Sonde de température | F67: =IFERROR(AVERAGE(G67:U67),"") | G67: =IF(F23<>"",_xlfn.SINGLE(INDIRECT(F23&"!"&$F$10)),"") | H67: =IF(G23<>"",_xlfn.SINGLE(INDIRECT(G23&"!"&$F$10)),"") | I67: =IF(H23<>"",_xlfn.SINGLE(INDIRECT(H23&"!"&$F$10)),"") | J67: =IF(I23<>"",_xlfn.SINGLE(INDIRECT(I23&"!"&$F$10)),"") | K67: =IF(J23<>"",_xlfn.SINGLE(INDIRECT(J23&"!"&$F$10)),"") | L67: =IF(K23<>"",_xlfn.SINGLE(INDIRECT(K23&"!"&$F$10)),"") | M67: =IF(L23<>"",_xlfn.SINGLE(INDIRECT(L23&"!"&$F$10)),"") | N67: =IF(M23<>"",_xlfn.SINGLE(INDIRECT(M23&"!"&$F$10)),"") | ... U67: =IF(T23<>"",_xlfn.SINGLE(INDIRECT(T23&"!"&$F$10)),"")
B68: A4 | C68: S2 | D68: =$D$7 -> Débitmètre en charge | E68: =IFERROR(AVERAGE(F70:F72)*$B$5,"") | F68: =IFERROR(AVERAGE(G68:U68),"") | G68: =IF(F24<>"",_xlfn.SINGLE(INDIRECT(F24&"!"&$F$7)),"") | H68: =IF(G24<>"",_xlfn.SINGLE(INDIRECT(G24&"!"&$F$7)),"") | I68: =IF(H24<>"",_xlfn.SINGLE(INDIRECT(H24&"!"&$F$7)),"") | J68: =IF(I24<>"",_xlfn.SINGLE(INDIRECT(I24&"!"&$F$7)),"") | K68: =IF(J24<>"",_xlfn.SINGLE(INDIRECT(J24&"!"&$F$7)),"") | L68: =IF(K24<>"",_xlfn.SINGLE(INDIRECT(K24&"!"&$F$7)),"") | M68: =IF(L24<>"",_xlfn.SINGLE(INDIRECT(L24&"!"&$F$7)),"") | N68: =IF(M24<>"",_xlfn.SINGLE(INDIRECT(M24&"!"&$F$7)),"") | ... U68: =IF(T24<>"",_xlfn.SINGLE(INDIRECT(T24&"!"&$F$7)),"")
D69: =$D$8 -> Débitmètre gravitaire | F69: =IFERROR(AVERAGE(G69:U69),"") | G69: =IF(F25<>"",_xlfn.SINGLE(INDIRECT(F25&"!"&$F$8)),"") | H69: =IF(G25<>"",_xlfn.SINGLE(INDIRECT(G25&"!"&$F$8)),"") | I69: =IF(H25<>"",_xlfn.SINGLE(INDIRECT(H25&"!"&$F$8)),"") | J69: =IF(I25<>"",_xlfn.SINGLE(INDIRECT(I25&"!"&$F$8)),"") | K69: =IF(J25<>"",_xlfn.SINGLE(INDIRECT(J25&"!"&$F$8)),"") | L69: =IF(K25<>"",_xlfn.SINGLE(INDIRECT(K25&"!"&$F$8)),"") | M69: =IF(L25<>"",_xlfn.SINGLE(INDIRECT(L25&"!"&$F$8)),"") | N69: =IF(M25<>"",_xlfn.SINGLE(INDIRECT(M25&"!"&$F$8)),"") | ... U69: =IF(T25<>"",_xlfn.SINGLE(INDIRECT(T25&"!"&$F$8)),"")
D70: Débitmètre | F70: =IFERROR(AVERAGE(G70:U70),"") | G70: =IF(COUNT(G68:G69)>0,SUM(G68:G69),"") | H70: =IF(COUNT(H68:H69)>0,SUM(H68:H69),"") | I70: =IF(COUNT(I68:I69)>0,SUM(I68:I69),"") | J70: =IF(COUNT(J68:J69)>0,SUM(J68:J69),"") | K70: =IF(COUNT(K68:K69)>0,SUM(K68:K69),"") | L70: =IF(COUNT(L68:L69)>0,SUM(L68:L69),"") | M70: =IF(COUNT(M68:M69)>0,SUM(M68:M69),"") | N70: =IF(COUNT(N68:N69)>0,SUM(N68:N69),"") | ... U70: =IF(COUNT(U68:U69)>0,SUM(U68:U69),"")
D71: =$D$9 -> Préleveur | F71: =IFERROR(AVERAGE(G71:U71),"") | G71: =IF(F26<>"",_xlfn.SINGLE(INDIRECT(F26&"!"&$F$9)),"") | H71: =IF(G26<>"",_xlfn.SINGLE(INDIRECT(G26&"!"&$F$9)),"") | I71: =IF(H26<>"",_xlfn.SINGLE(INDIRECT(H26&"!"&$F$9)),"") | J71: =IF(I26<>"",_xlfn.SINGLE(INDIRECT(I26&"!"&$F$9)),"") | K71: =IF(J26<>"",_xlfn.SINGLE(INDIRECT(J26&"!"&$F$9)),"") | L71: =IF(K26<>"",_xlfn.SINGLE(INDIRECT(K26&"!"&$F$9)),"") | M71: =IF(L26<>"",_xlfn.SINGLE(INDIRECT(L26&"!"&$F$9)),"") | N71: =IF(M26<>"",_xlfn.SINGLE(INDIRECT(M26&"!"&$F$9)),"") | ... U71: =IF(T26<>"",_xlfn.SINGLE(INDIRECT(T26&"!"&$F$9)),"")
D72: Analytique | F72: =IFERROR(AVERAGE(G72:U72),"") | G72: =IF(F27<>"",VLOOKUP(F27,Analytique!$X$3:$AD$36,6,FALSE),"") | H72: =IF(G27<>"",VLOOKUP(G27,Analytique!$X$3:$AD$36,6,FALSE),"") | I72: =IF(H27<>"",VLOOKUP(H27,Analytique!$X$3:$AD$36,6,FALSE),"") | J72: =IF(I27<>"",VLOOKUP(I27,Analytique!$X$3:$AD$36,6,FALSE),"") | K72: =IF(J27<>"",VLOOKUP(J27,Analytique!$X$3:$AD$36,6,FALSE),"") | L72: =IF(K27<>"",VLOOKUP(K27,Analytique!$X$3:$AD$36,6,FALSE),"") | M72: =IF(L27<>"",VLOOKUP(L27,Analytique!$X$3:$AD$36,6,FALSE),"") | N72: =IF(M27<>"",VLOOKUP(M27,Analytique!$X$3:$AD$36,6,FALSE),"") | ... U72: =IF(T27<>"",VLOOKUP(T27,Analytique!$X$3:$AD$36,6,FALSE),"")
D73: =$D$10 -> Sonde de température | F73: =IFERROR(AVERAGE(G73:U73),"") | G73: =IF(F28<>"",_xlfn.SINGLE(INDIRECT(F28&"!"&$F$10)),"") | H73: =IF(G28<>"",_xlfn.SINGLE(INDIRECT(G28&"!"&$F$10)),"") | I73: =IF(H28<>"",_xlfn.SINGLE(INDIRECT(H28&"!"&$F$10)),"") | J73: =IF(I28<>"",_xlfn.SINGLE(INDIRECT(I28&"!"&$F$10)),"") | K73: =IF(J28<>"",_xlfn.SINGLE(INDIRECT(J28&"!"&$F$10)),"") | L73: =IF(K28<>"",_xlfn.SINGLE(INDIRECT(K28&"!"&$F$10)),"") | M73: =IF(L28<>"",_xlfn.SINGLE(INDIRECT(L28&"!"&$F$10)),"") | N73: =IF(M28<>"",_xlfn.SINGLE(INDIRECT(M28&"!"&$F$10)),"") | ... U73: =IF(T28<>"",_xlfn.SINGLE(INDIRECT(T28&"!"&$F$10)),"")
B74: A2 | C74: S16 | D74: =$D$7 -> Débitmètre en charge | E74: =IFERROR(AVERAGE(F76:F78)*$B$5,"") | F74: =IFERROR(AVERAGE(G74:U74),"") | G74: =IF(F29<>"",_xlfn.SINGLE(INDIRECT(F29&"!"&$F$7)),"") | H74: =IF(G29<>"",_xlfn.SINGLE(INDIRECT(G29&"!"&$F$7)),"") | I74: =IF(H29<>"",_xlfn.SINGLE(INDIRECT(H29&"!"&$F$7)),"") | J74: =IF(I29<>"",_xlfn.SINGLE(INDIRECT(I29&"!"&$F$7)),"") | K74: =IF(J29<>"",_xlfn.SINGLE(INDIRECT(J29&"!"&$F$7)),"") | L74: =IF(K29<>"",_xlfn.SINGLE(INDIRECT(K29&"!"&$F$7)),"") | M74: =IF(L29<>"",_xlfn.SINGLE(INDIRECT(L29&"!"&$F$7)),"") | N74: =IF(M29<>"",_xlfn.SINGLE(INDIRECT(M29&"!"&$F$7)),"") | ... U74: =IF(T29<>"",_xlfn.SINGLE(INDIRECT(T29&"!"&$F$7)),"")
D75: =$D$8 -> Débitmètre gravitaire | F75: =IFERROR(AVERAGE(G75:U75),"") | G75: =IF(F30<>"",_xlfn.SINGLE(INDIRECT(F30&"!"&$F$8)),"") | H75: =IF(G30<>"",_xlfn.SINGLE(INDIRECT(G30&"!"&$F$8)),"") | I75: =IF(H30<>"",_xlfn.SINGLE(INDIRECT(H30&"!"&$F$8)),"") | J75: =IF(I30<>"",_xlfn.SINGLE(INDIRECT(I30&"!"&$F$8)),"") | K75: =IF(J30<>"",_xlfn.SINGLE(INDIRECT(J30&"!"&$F$8)),"") | L75: =IF(K30<>"",_xlfn.SINGLE(INDIRECT(K30&"!"&$F$8)),"") | M75: =IF(L30<>"",_xlfn.SINGLE(INDIRECT(L30&"!"&$F$8)),"") | N75: =IF(M30<>"",_xlfn.SINGLE(INDIRECT(M30&"!"&$F$8)),"") | ... U75: =IF(T30<>"",_xlfn.SINGLE(INDIRECT(T30&"!"&$F$8)),"")
D76: Débitmètre | F76: =IFERROR(AVERAGE(G76:U76),"") | G76: =IF(COUNT(G74:G75)>0,SUM(G74:G75),"") | H76: =IF(COUNT(H74:H75)>0,SUM(H74:H75),"") | I76: =IF(COUNT(I74:I75)>0,SUM(I74:I75),"") | J76: =IF(COUNT(J74:J75)>0,SUM(J74:J75),"") | K76: =IF(COUNT(K74:K75)>0,SUM(K74:K75),"") | L76: =IF(COUNT(L74:L75)>0,SUM(L74:L75),"") | M76: =IF(COUNT(M74:M75)>0,SUM(M74:M75),"") | N76: =IF(COUNT(N74:N75)>0,SUM(N74:N75),"") | ... U76: =IF(COUNT(U74:U75)>0,SUM(U74:U75),"")
D77: =$D$9 -> Préleveur | F77: =IFERROR(AVERAGE(G77:U77),"") | G77: =IF(F31<>"",_xlfn.SINGLE(INDIRECT(F31&"!"&$F$9)),"") | H77: =IF(G31<>"",_xlfn.SINGLE(INDIRECT(G31&"!"&$F$9)),"") | I77: =IF(H31<>"",_xlfn.SINGLE(INDIRECT(H31&"!"&$F$9)),"") | J77: =IF(I31<>"",_xlfn.SINGLE(INDIRECT(I31&"!"&$F$9)),"") | K77: =IF(J31<>"",_xlfn.SINGLE(INDIRECT(J31&"!"&$F$9)),"") | L77: =IF(K31<>"",_xlfn.SINGLE(INDIRECT(K31&"!"&$F$9)),"") | M77: =IF(L31<>"",_xlfn.SINGLE(INDIRECT(L31&"!"&$F$9)),"") | N77: =IF(M31<>"",_xlfn.SINGLE(INDIRECT(M31&"!"&$F$9)),"") | ... U77: =IF(T31<>"",_xlfn.SINGLE(INDIRECT(T31&"!"&$F$9)),"")
D78: Analytique | F78: =IFERROR(AVERAGE(G78:U78),"") | G78: =IF(F33<>"",VLOOKUP(F33,Analytique!$X$3:$AD$36,6,FALSE),"") | H78: =IF(G33<>"",VLOOKUP(G33,Analytique!$X$3:$AD$36,6,FALSE),"") | I78: =IF(H33<>"",VLOOKUP(H33,Analytique!$X$3:$AD$36,6,FALSE),"") | J78: =IF(I33<>"",VLOOKUP(I33,Analytique!$X$3:$AD$36,6,FALSE),"") | K78: =IF(J33<>"",VLOOKUP(J33,Analytique!$X$3:$AD$36,6,FALSE),"") | L78: =IF(K33<>"",VLOOKUP(K33,Analytique!$X$3:$AD$36,6,FALSE),"") | M78: =IF(L33<>"",VLOOKUP(L33,Analytique!$X$3:$AD$36,6,FALSE),"") | N78: =IF(M33<>"",VLOOKUP(M33,Analytique!$X$3:$AD$36,6,FALSE),"") | ... U78: =IF(T33<>"",VLOOKUP(T33,Analytique!$X$3:$AD$36,6,FALSE),"")
D79: =$D$10 -> Sonde de température | F79: =IFERROR(AVERAGE(G79:U79),"") | G79: =IF(F33<>"",_xlfn.SINGLE(INDIRECT(F33&"!"&$F$10)),"") | H79: =IF(G33<>"",_xlfn.SINGLE(INDIRECT(G33&"!"&$F$10)),"") | I79: =IF(H33<>"",_xlfn.SINGLE(INDIRECT(H33&"!"&$F$10)),"") | J79: =IF(I33<>"",_xlfn.SINGLE(INDIRECT(I33&"!"&$F$10)),"") | K79: =IF(J33<>"",_xlfn.SINGLE(INDIRECT(J33&"!"&$F$10)),"") | L79: =IF(K33<>"",_xlfn.SINGLE(INDIRECT(K33&"!"&$F$10)),"") | M79: =IF(L33<>"",_xlfn.SINGLE(INDIRECT(L33&"!"&$F$10)),"") | N79: =IF(M33<>"",_xlfn.SINGLE(INDIRECT(M33&"!"&$F$10)),"") | ... U79: =IF(T33<>"",_xlfn.SINGLE(INDIRECT(T33&"!"&$F$10)),"")
B80: A5 | C80: S3 | D80: =$D$7 -> Débitmètre en charge | E80: =IFERROR(AVERAGE(F82:F84)*$B$5,"") | F80: =IFERROR(AVERAGE(G80:U80),"") | G80: =IF(F34<>"",_xlfn.SINGLE(INDIRECT(F34&"!"&$F$7)),"") | H80: =IF(G34<>"",_xlfn.SINGLE(INDIRECT(G34&"!"&$F$7)),"") | I80: =IF(H34<>"",_xlfn.SINGLE(INDIRECT(H34&"!"&$F$7)),"") | J80: =IF(I34<>"",_xlfn.SINGLE(INDIRECT(I34&"!"&$F$7)),"") | K80: =IF(J34<>"",_xlfn.SINGLE(INDIRECT(J34&"!"&$F$7)),"") | L80: =IF(K34<>"",_xlfn.SINGLE(INDIRECT(K34&"!"&$F$7)),"") | M80: =IF(L34<>"",_xlfn.SINGLE(INDIRECT(L34&"!"&$F$7)),"") | N80: =IF(M34<>"",_xlfn.SINGLE(INDIRECT(M34&"!"&$F$7)),"") | ... U80: =IF(T34<>"",_xlfn.SINGLE(INDIRECT(T34&"!"&$F$7)),"")
D81: =$D$8 -> Débitmètre gravitaire | F81: =IFERROR(AVERAGE(G81:U81),"") | G81: =IF(F35<>"",_xlfn.SINGLE(INDIRECT(F35&"!"&$F$8)),"") | H81: =IF(G35<>"",_xlfn.SINGLE(INDIRECT(G35&"!"&$F$8)),"") | I81: =IF(H35<>"",_xlfn.SINGLE(INDIRECT(H35&"!"&$F$8)),"") | J81: =IF(I35<>"",_xlfn.SINGLE(INDIRECT(I35&"!"&$F$8)),"") | K81: =IF(J35<>"",_xlfn.SINGLE(INDIRECT(J35&"!"&$F$8)),"") | L81: =IF(K35<>"",_xlfn.SINGLE(INDIRECT(K35&"!"&$F$8)),"") | M81: =IF(L35<>"",_xlfn.SINGLE(INDIRECT(L35&"!"&$F$8)),"") | N81: =IF(M35<>"",_xlfn.SINGLE(INDIRECT(M35&"!"&$F$8)),"") | ... U81: =IF(T35<>"",_xlfn.SINGLE(INDIRECT(T35&"!"&$F$8)),"")
D82: Débitmètre | F82: =IFERROR(AVERAGE(G82:U82),"") | G82: =IF(COUNT(G80:G81)>0,SUM(G80:G81),"") | H82: =IF(COUNT(H80:H81)>0,SUM(H80:H81),"") | I82: =IF(COUNT(I80:I81)>0,SUM(I80:I81),"") | J82: =IF(COUNT(J80:J81)>0,SUM(J80:J81),"") | K82: =IF(COUNT(K80:K81)>0,SUM(K80:K81),"") | L82: =IF(COUNT(L80:L81)>0,SUM(L80:L81),"") | M82: =IF(COUNT(M80:M81)>0,SUM(M80:M81),"") | N82: =IF(COUNT(N80:N81)>0,SUM(N80:N81),"") | ... U82: =IF(COUNT(U80:U81)>0,SUM(U80:U81),"")
D83: =$D$9 -> Préleveur | F83: =IFERROR(AVERAGE(G83:U83),"") | G83: =IF(F36<>"",_xlfn.SINGLE(INDIRECT(F36&"!"&$F$9)),"") | H83: =IF(G36<>"",_xlfn.SINGLE(INDIRECT(G36&"!"&$F$9)),"") | I83: =IF(H36<>"",_xlfn.SINGLE(INDIRECT(H36&"!"&$F$9)),"") | J83: =IF(I36<>"",_xlfn.SINGLE(INDIRECT(I36&"!"&$F$9)),"") | K83: =IF(J36<>"",_xlfn.SINGLE(INDIRECT(J36&"!"&$F$9)),"") | L83: =IF(K36<>"",_xlfn.SINGLE(INDIRECT(K36&"!"&$F$9)),"") | M83: =IF(L36<>"",_xlfn.SINGLE(INDIRECT(L36&"!"&$F$9)),"") | N83: =IF(M36<>"",_xlfn.SINGLE(INDIRECT(M36&"!"&$F$9)),"") | ... U83: =IF(T36<>"",_xlfn.SINGLE(INDIRECT(T36&"!"&$F$9)),"")
D84: Analytique | F84: =IFERROR(AVERAGE(G84:U84),"") | G84: =IF(F39<>"",VLOOKUP(F39,Analytique!$X$3:$AD$36,6,FALSE),"") | H84: =IF(G39<>"",VLOOKUP(G39,Analytique!$X$3:$AD$36,6,FALSE),"") | I84: =IF(H39<>"",VLOOKUP(H39,Analytique!$X$3:$AD$36,6,FALSE),"") | J84: =IF(I39<>"",VLOOKUP(I39,Analytique!$X$3:$AD$36,6,FALSE),"") | K84: =IF(J39<>"",VLOOKUP(J39,Analytique!$X$3:$AD$36,6,FALSE),"") | L84: =IF(K39<>"",VLOOKUP(K39,Analytique!$X$3:$AD$36,6,FALSE),"") | M84: =IF(L39<>"",VLOOKUP(L39,Analytique!$X$3:$AD$36,6,FALSE),"") | N84: =IF(M39<>"",VLOOKUP(M39,Analytique!$X$3:$AD$36,6,FALSE),"") | ... U84: =IF(T39<>"",VLOOKUP(T39,Analytique!$X$3:$AD$36,6,FALSE),"")
D85: =$D$10 -> Sonde de température | F85: =IFERROR(AVERAGE(G85:U85),"") | G85: =IF(F37<>"",_xlfn.SINGLE(INDIRECT(F37&"!"&$F$10)),"") | H85: =IF(G37<>"",_xlfn.SINGLE(INDIRECT(G37&"!"&$F$10)),"") | I85: =IF(H37<>"",_xlfn.SINGLE(INDIRECT(H37&"!"&$F$10)),"") | J85: =IF(I37<>"",_xlfn.SINGLE(INDIRECT(I37&"!"&$F$10)),"") | K85: =IF(J37<>"",_xlfn.SINGLE(INDIRECT(J37&"!"&$F$10)),"") | L85: =IF(K37<>"",_xlfn.SINGLE(INDIRECT(K37&"!"&$F$10)),"") | M85: =IF(L37<>"",_xlfn.SINGLE(INDIRECT(L37&"!"&$F$10)),"") | N85: =IF(M37<>"",_xlfn.SINGLE(INDIRECT(M37&"!"&$F$10)),"") | ... U85: =IF(T37<>"",_xlfn.SINGLE(INDIRECT(T37&"!"&$F$10)),"")
B86: A6 | C86: S4 | D86: =$D$7 -> Débitmètre en charge | E86: =IFERROR(AVERAGE(F88:F90)*$B$5,"") | F86: =IFERROR(AVERAGE(G86:U86),"") | G86: =IF(F38<>"",_xlfn.SINGLE(INDIRECT(F38&"!"&$F$7)),"") | H86: =IF(G38<>"",_xlfn.SINGLE(INDIRECT(G38&"!"&$F$7)),"") | I86: =IF(H38<>"",_xlfn.SINGLE(INDIRECT(H38&"!"&$F$7)),"") | J86: =IF(I38<>"",_xlfn.SINGLE(INDIRECT(I38&"!"&$F$7)),"") | K86: =IF(J38<>"",_xlfn.SINGLE(INDIRECT(J38&"!"&$F$7)),"") | L86: =IF(K38<>"",_xlfn.SINGLE(INDIRECT(K38&"!"&$F$7)),"") | M86: =IF(L38<>"",_xlfn.SINGLE(INDIRECT(L38&"!"&$F$7)),"") | N86: =IF(M38<>"",_xlfn.SINGLE(INDIRECT(M38&"!"&$F$7)),"") | ... U86: =IF(T38<>"",_xlfn.SINGLE(INDIRECT(T38&"!"&$F$7)),"")
D87: =$D$8 -> Débitmètre gravitaire | F87: =IFERROR(AVERAGE(G87:U87),"") | G87: =IF(F39<>"",_xlfn.SINGLE(INDIRECT(F39&"!"&$F$8)),"") | H87: =IF(G39<>"",_xlfn.SINGLE(INDIRECT(G39&"!"&$F$8)),"") | I87: =IF(H39<>"",_xlfn.SINGLE(INDIRECT(H39&"!"&$F$8)),"") | J87: =IF(I39<>"",_xlfn.SINGLE(INDIRECT(I39&"!"&$F$8)),"") | K87: =IF(J39<>"",_xlfn.SINGLE(INDIRECT(J39&"!"&$F$8)),"") | L87: =IF(K39<>"",_xlfn.SINGLE(INDIRECT(K39&"!"&$F$8)),"") | M87: =IF(L39<>"",_xlfn.SINGLE(INDIRECT(L39&"!"&$F$8)),"") | N87: =IF(M39<>"",_xlfn.SINGLE(INDIRECT(M39&"!"&$F$8)),"") | ... U87: =IF(T39<>"",_xlfn.SINGLE(INDIRECT(T39&"!"&$F$8)),"")
D88: Débitmètre | F88: =IFERROR(AVERAGE(G88:U88),"") | G88: =IF(COUNT(G86:G87)>0,SUM(G86:G87),"") | H88: =IF(COUNT(H86:H87)>0,SUM(H86:H87),"") | I88: =IF(COUNT(I86:I87)>0,SUM(I86:I87),"") | J88: =IF(COUNT(J86:J87)>0,SUM(J86:J87),"") | K88: =IF(COUNT(K86:K87)>0,SUM(K86:K87),"") | L88: =IF(COUNT(L86:L87)>0,SUM(L86:L87),"") | M88: =IF(COUNT(M86:M87)>0,SUM(M86:M87),"") | N88: =IF(COUNT(N86:N87)>0,SUM(N86:N87),"") | ... U88: =IF(COUNT(U86:U87)>0,SUM(U86:U87),"")
D89: =$D$9 -> Préleveur | F89: =IFERROR(AVERAGE(G89:U89),"") | G89: =IF(F40<>"",_xlfn.SINGLE(INDIRECT(F40&"!"&$F$9)),"") | H89: =IF(G40<>"",_xlfn.SINGLE(INDIRECT(G40&"!"&$F$9)),"") | I89: =IF(H40<>"",_xlfn.SINGLE(INDIRECT(H40&"!"&$F$9)),"") | J89: =IF(I40<>"",_xlfn.SINGLE(INDIRECT(I40&"!"&$F$9)),"") | K89: =IF(J40<>"",_xlfn.SINGLE(INDIRECT(J40&"!"&$F$9)),"") | L89: =IF(K40<>"",_xlfn.SINGLE(INDIRECT(K40&"!"&$F$9)),"") | M89: =IF(L40<>"",_xlfn.SINGLE(INDIRECT(L40&"!"&$F$9)),"") | N89: =IF(M40<>"",_xlfn.SINGLE(INDIRECT(M40&"!"&$F$9)),"") | ... U89: =IF(T40<>"",_xlfn.SINGLE(INDIRECT(T40&"!"&$F$9)),"")
D90: Analytique | F90: =IFERROR(AVERAGE(G90:U90),"")
D91: =$D$10 -> Sonde de température | F91: =IFERROR(AVERAGE(G91:U91),"") | G91: =IF(F42<>"",_xlfn.SINGLE(INDIRECT(F42&"!"&$F$10)),"") | H91: =IF(G42<>"",_xlfn.SINGLE(INDIRECT(G42&"!"&$F$10)),"") | I91: =IF(H42<>"",_xlfn.SINGLE(INDIRECT(H42&"!"&$F$10)),"") | J91: =IF(I42<>"",_xlfn.SINGLE(INDIRECT(I42&"!"&$F$10)),"") | K91: =IF(J42<>"",_xlfn.SINGLE(INDIRECT(J42&"!"&$F$10)),"") | L91: =IF(K42<>"",_xlfn.SINGLE(INDIRECT(K42&"!"&$F$10)),"") | M91: =IF(L42<>"",_xlfn.SINGLE(INDIRECT(L42&"!"&$F$10)),"") | N91: =IF(M42<>"",_xlfn.SINGLE(INDIRECT(M42&"!"&$F$10)),"") | ... U91: =IF(T42<>"",_xlfn.SINGLE(INDIRECT(T42&"!"&$F$10)),"")
B92: A7 | C92: S12 | D92: =$D$7 -> Débitmètre en charge | E92: =IFERROR(AVERAGE(F94:F96)*$B$5,"") | F92: =IFERROR(AVERAGE(G92:U92),"") | G92: =IF(F43<>"",_xlfn.SINGLE(INDIRECT(F43&"!"&$F$7)),"") | H92: =IF(G43<>"",_xlfn.SINGLE(INDIRECT(G43&"!"&$F$7)),"") | I92: =IF(H43<>"",_xlfn.SINGLE(INDIRECT(H43&"!"&$F$7)),"") | J92: =IF(I43<>"",_xlfn.SINGLE(INDIRECT(I43&"!"&$F$7)),"") | K92: =IF(J43<>"",_xlfn.SINGLE(INDIRECT(J43&"!"&$F$7)),"") | L92: =IF(K43<>"",_xlfn.SINGLE(INDIRECT(K43&"!"&$F$7)),"") | M92: =IF(L43<>"",_xlfn.SINGLE(INDIRECT(L43&"!"&$F$7)),"") | N92: =IF(M43<>"",_xlfn.SINGLE(INDIRECT(M43&"!"&$F$7)),"") | ... U92: =IF(T43<>"",_xlfn.SINGLE(INDIRECT(T43&"!"&$F$7)),"")
D93: =$D$8 -> Débitmètre gravitaire | F93: =IFERROR(AVERAGE(G93:U93),"") | G93: =IF(F44<>"",_xlfn.SINGLE(INDIRECT(F44&"!"&$F$8)),"") | H93: =IF(G44<>"",_xlfn.SINGLE(INDIRECT(G44&"!"&$F$8)),"") | I93: =IF(H44<>"",_xlfn.SINGLE(INDIRECT(H44&"!"&$F$8)),"") | J93: =IF(I44<>"",_xlfn.SINGLE(INDIRECT(I44&"!"&$F$8)),"") | K93: =IF(J44<>"",_xlfn.SINGLE(INDIRECT(J44&"!"&$F$8)),"") | L93: =IF(K44<>"",_xlfn.SINGLE(INDIRECT(K44&"!"&$F$8)),"") | M93: =IF(L44<>"",_xlfn.SINGLE(INDIRECT(L44&"!"&$F$8)),"") | N93: =IF(M44<>"",_xlfn.SINGLE(INDIRECT(M44&"!"&$F$8)),"") | ... U93: =IF(T44<>"",_xlfn.SINGLE(INDIRECT(T44&"!"&$F$8)),"")
D94: Débitmètre | F94: =IFERROR(AVERAGE(G94:U94),"") | G94: =IF(COUNT(G92:G93)>0,SUM(G92:G93),"") | H94: =IF(COUNT(H92:H93)>0,SUM(H92:H93),"") | I94: =IF(COUNT(I92:I93)>0,SUM(I92:I93),"") | J94: =IF(COUNT(J92:J93)>0,SUM(J92:J93),"") | K94: =IF(COUNT(K92:K93)>0,SUM(K92:K93),"") | L94: =IF(COUNT(L92:L93)>0,SUM(L92:L93),"") | M94: =IF(COUNT(M92:M93)>0,SUM(M92:M93),"") | N94: =IF(COUNT(N92:N93)>0,SUM(N92:N93),"") | ... U94: =IF(COUNT(U92:U93)>0,SUM(U92:U93),"")
D95: =$D$9 -> Préleveur | F95: =IFERROR(AVERAGE(G95:U95),"") | G95: =IF(F45<>"",_xlfn.SINGLE(INDIRECT(F45&"!"&$F$9)),"") | H95: =IF(G45<>"",_xlfn.SINGLE(INDIRECT(G45&"!"&$F$9)),"") | I95: =IF(H45<>"",_xlfn.SINGLE(INDIRECT(H45&"!"&$F$9)),"") | J95: =IF(I45<>"",_xlfn.SINGLE(INDIRECT(I45&"!"&$F$9)),"") | K95: =IF(J45<>"",_xlfn.SINGLE(INDIRECT(J45&"!"&$F$9)),"") | L95: =IF(K45<>"",_xlfn.SINGLE(INDIRECT(K45&"!"&$F$9)),"") | M95: =IF(L45<>"",_xlfn.SINGLE(INDIRECT(L45&"!"&$F$9)),"") | N95: =IF(M45<>"",_xlfn.SINGLE(INDIRECT(M45&"!"&$F$9)),"") | ... U95: =IF(T45<>"",_xlfn.SINGLE(INDIRECT(T45&"!"&$F$9)),"")
D96: Analytique | F96: =IFERROR(AVERAGE(G96:U96),"") | G96: =IF(F51<>"",VLOOKUP(F51,Analytique!$X$3:$AD$36,6,FALSE),"") | H96: =IF(G51<>"",VLOOKUP(G51,Analytique!$X$3:$AD$36,6,FALSE),"") | I96: =IF(H51<>"",VLOOKUP(H51,Analytique!$X$3:$AD$36,6,FALSE),"") | J96: =IF(I51<>"",VLOOKUP(I51,Analytique!$X$3:$AD$36,6,FALSE),"") | K96: =IF(J51<>"",VLOOKUP(J51,Analytique!$X$3:$AD$36,6,FALSE),"") | L96: =IF(K51<>"",VLOOKUP(K51,Analytique!$X$3:$AD$36,6,FALSE),"") | M96: =IF(L51<>"",VLOOKUP(L51,Analytique!$X$3:$AD$36,6,FALSE),"") | N96: =IF(M51<>"",VLOOKUP(M51,Analytique!$X$3:$AD$36,6,FALSE),"") | ... U96: =IF(T51<>"",VLOOKUP(T51,Analytique!$X$3:$AD$36,6,FALSE),"")
D97: =$D$10 -> Sonde de température | F97: =IFERROR(AVERAGE(G97:U97),"") | G97: =IF(F47<>"",_xlfn.SINGLE(INDIRECT(F47&"!"&$F$10)),"") | H97: =IF(G47<>"",_xlfn.SINGLE(INDIRECT(G47&"!"&$F$10)),"") | I97: =IF(H47<>"",_xlfn.SINGLE(INDIRECT(H47&"!"&$F$10)),"") | J97: =IF(I47<>"",_xlfn.SINGLE(INDIRECT(I47&"!"&$F$10)),"") | K97: =IF(J47<>"",_xlfn.SINGLE(INDIRECT(J47&"!"&$F$10)),"") | L97: =IF(K47<>"",_xlfn.SINGLE(INDIRECT(K47&"!"&$F$10)),"") | M97: =IF(L47<>"",_xlfn.SINGLE(INDIRECT(L47&"!"&$F$10)),"") | N97: =IF(M47<>"",_xlfn.SINGLE(INDIRECT(M47&"!"&$F$10)),"") | ... U97: =IF(T47<>"",_xlfn.SINGLE(INDIRECT(T47&"!"&$F$10)),"")
B98: A1 | C98: R1 | D98: =$D$7 -> Débitmètre en charge | E98: =IFERROR(AVERAGE(F100:F102)*$B$5,"") | F98: =IFERROR(AVERAGE(G98:U98),"") | G98: =IF(F48<>"",_xlfn.SINGLE(INDIRECT(F48&"!"&$F$7)),"") | H98: =IF(G48<>"",_xlfn.SINGLE(INDIRECT(G48&"!"&$F$7)),"") | I98: =IF(H48<>"",_xlfn.SINGLE(INDIRECT(H48&"!"&$F$7)),"") | J98: =IF(I48<>"",_xlfn.SINGLE(INDIRECT(I48&"!"&$F$7)),"") | K98: =IF(J48<>"",_xlfn.SINGLE(INDIRECT(J48&"!"&$F$7)),"") | L98: =IF(K48<>"",_xlfn.SINGLE(INDIRECT(K48&"!"&$F$7)),"") | M98: =IF(L48<>"",_xlfn.SINGLE(INDIRECT(L48&"!"&$F$7)),"") | N98: =IF(M48<>"",_xlfn.SINGLE(INDIRECT(M48&"!"&$F$7)),"") | ... U98: =IF(T48<>"",_xlfn.SINGLE(INDIRECT(T48&"!"&$F$7)),"")
D99: =$D$8 -> Débitmètre gravitaire | F99: =IFERROR(AVERAGE(G99:U99),"") | G99: =IF(F49<>"",_xlfn.SINGLE(INDIRECT(F49&"!"&$F$8)),"") | H99: =IF(G49<>"",_xlfn.SINGLE(INDIRECT(G49&"!"&$F$8)),"") | I99: =IF(H49<>"",_xlfn.SINGLE(INDIRECT(H49&"!"&$F$8)),"") | J99: =IF(I49<>"",_xlfn.SINGLE(INDIRECT(I49&"!"&$F$8)),"") | K99: =IF(J49<>"",_xlfn.SINGLE(INDIRECT(J49&"!"&$F$8)),"") | L99: =IF(K49<>"",_xlfn.SINGLE(INDIRECT(K49&"!"&$F$8)),"") | M99: =IF(L49<>"",_xlfn.SINGLE(INDIRECT(L49&"!"&$F$8)),"") | N99: =IF(M49<>"",_xlfn.SINGLE(INDIRECT(M49&"!"&$F$8)),"") | ... U99: =IF(T49<>"",_xlfn.SINGLE(INDIRECT(T49&"!"&$F$8)),"")
D100: Débitmètre | F100: =IFERROR(AVERAGE(G100:U100),"") | G100: =IF(COUNT(G98:G99)>0,SUM(G98:G99),"") | H100: =IF(COUNT(H98:H99)>0,SUM(H98:H99),"") | I100: =IF(COUNT(I98:I99)>0,SUM(I98:I99),"") | J100: =IF(COUNT(J98:J99)>0,SUM(J98:J99),"") | K100: =IF(COUNT(K98:K99)>0,SUM(K98:K99),"") | L100: =IF(COUNT(L98:L99)>0,SUM(L98:L99),"") | M100: =IF(COUNT(M98:M99)>0,SUM(M98:M99),"") | N100: =IF(COUNT(N98:N99)>0,SUM(N98:N99),"") | ... U100: =IF(COUNT(U98:U99)>0,SUM(U98:U99),"")
D101: =$D$9 -> Préleveur | F101: =IFERROR(AVERAGE(G101:U101),"") | G101: =IF(F50<>"",_xlfn.SINGLE(INDIRECT(F50&"!"&$F$9)),"") | H101: =IF(G50<>"",_xlfn.SINGLE(INDIRECT(G50&"!"&$F$9)),"") | I101: =IF(H50<>"",_xlfn.SINGLE(INDIRECT(H50&"!"&$F$9)),"") | J101: =IF(I50<>"",_xlfn.SINGLE(INDIRECT(I50&"!"&$F$9)),"") | K101: =IF(J50<>"",_xlfn.SINGLE(INDIRECT(J50&"!"&$F$9)),"") | L101: =IF(K50<>"",_xlfn.SINGLE(INDIRECT(K50&"!"&$F$9)),"") | M101: =IF(L50<>"",_xlfn.SINGLE(INDIRECT(L50&"!"&$F$9)),"") | N101: =IF(M50<>"",_xlfn.SINGLE(INDIRECT(M50&"!"&$F$9)),"") | ... U101: =IF(T50<>"",_xlfn.SINGLE(INDIRECT(T50&"!"&$F$9)),"")
D102: Analytique | F102: =IFERROR(AVERAGE(G102:U102),"") | G102: =IF(F57<>"",VLOOKUP(F57,Analytique!$X$3:$AD$36,6,FALSE),"") | H102: =IF(G57<>"",VLOOKUP(G57,Analytique!$X$3:$AD$36,6,FALSE),"") | I102: =IF(H57<>"",VLOOKUP(H57,Analytique!$X$3:$AD$36,6,FALSE),"") | J102: =IF(I57<>"",VLOOKUP(I57,Analytique!$X$3:$AD$36,6,FALSE),"") | K102: =IF(J57<>"",VLOOKUP(J57,Analytique!$X$3:$AD$36,6,FALSE),"") | L102: =IF(K57<>"",VLOOKUP(K57,Analytique!$X$3:$AD$36,6,FALSE),"") | M102: =IF(L57<>"",VLOOKUP(L57,Analytique!$X$3:$AD$36,6,FALSE),"") | N102: =IF(M57<>"",VLOOKUP(M57,Analytique!$X$3:$AD$36,6,FALSE),"") | ... U102: =IF(T57<>"",VLOOKUP(T57,Analytique!$X$3:$AD$36,6,FALSE),"")
D103: =$D$10 -> Sonde de température | F103: =IFERROR(AVERAGE(G103:U103),"") | G103: =IF(F52<>"",_xlfn.SINGLE(INDIRECT(F52&"!"&$F$10)),"") | H103: =IF(G52<>"",_xlfn.SINGLE(INDIRECT(G52&"!"&$F$10)),"") | I103: =IF(H52<>"",_xlfn.SINGLE(INDIRECT(H52&"!"&$F$10)),"") | J103: =IF(I52<>"",_xlfn.SINGLE(INDIRECT(I52&"!"&$F$10)),"") | K103: =IF(J52<>"",_xlfn.SINGLE(INDIRECT(J52&"!"&$F$10)),"") | L103: =IF(K52<>"",_xlfn.SINGLE(INDIRECT(K52&"!"&$F$10)),"") | M103: =IF(L52<>"",_xlfn.SINGLE(INDIRECT(L52&"!"&$F$10)),"") | N103: =IF(M52<>"",_xlfn.SINGLE(INDIRECT(M52&"!"&$F$10)),"") | ... U103: =IF(T52<>"",_xlfn.SINGLE(INDIRECT(T52&"!"&$F$10)),"")
B104: A8 | C104: S19 | D104: =$D$7 -> Débitmètre en charge | E104: =IFERROR(AVERAGE(F106:F108)*$B$5,"") | F104: =IFERROR(AVERAGE(G104:U104),"") | G104: =IF(F53<>"",_xlfn.SINGLE(INDIRECT(F53&"!"&$F$7)),"") | H104: =IF(G53<>"",_xlfn.SINGLE(INDIRECT(G53&"!"&$F$7)),"") | I104: =IF(H53<>"",_xlfn.SINGLE(INDIRECT(H53&"!"&$F$7)),"") | J104: =IF(I53<>"",_xlfn.SINGLE(INDIRECT(I53&"!"&$F$7)),"") | K104: =IF(J53<>"",_xlfn.SINGLE(INDIRECT(J53&"!"&$F$7)),"") | L104: =IF(K53<>"",_xlfn.SINGLE(INDIRECT(K53&"!"&$F$7)),"") | M104: =IF(L53<>"",_xlfn.SINGLE(INDIRECT(L53&"!"&$F$7)),"") | N104: =IF(M53<>"",_xlfn.SINGLE(INDIRECT(M53&"!"&$F$7)),"") | ... U104: =IF(T53<>"",_xlfn.SINGLE(INDIRECT(T53&"!"&$F$7)),"")
D105: =$D$8 -> Débitmètre gravitaire | F105: =IFERROR(AVERAGE(G105:U105),"") | G105: =IF(F54<>"",_xlfn.SINGLE(INDIRECT(F54&"!"&$F$8)),"") | H105: =IF(G54<>"",_xlfn.SINGLE(INDIRECT(G54&"!"&$F$8)),"") | I105: =IF(H54<>"",_xlfn.SINGLE(INDIRECT(H54&"!"&$F$8)),"") | J105: =IF(I54<>"",_xlfn.SINGLE(INDIRECT(I54&"!"&$F$8)),"") | K105: =IF(J54<>"",_xlfn.SINGLE(INDIRECT(J54&"!"&$F$8)),"") | L105: =IF(K54<>"",_xlfn.SINGLE(INDIRECT(K54&"!"&$F$8)),"") | M105: =IF(L54<>"",_xlfn.SINGLE(INDIRECT(L54&"!"&$F$8)),"") | N105: =IF(M54<>"",_xlfn.SINGLE(INDIRECT(M54&"!"&$F$8)),"") | ... U105: =IF(T54<>"",_xlfn.SINGLE(INDIRECT(T54&"!"&$F$8)),"")
...

Sheet Equipements
A1: Lignes SCL | B1: =Descriptif!$AD$2 -> 14 | C1: =Descriptif!$AF$2 -> 14 | D1: Lignes STEU | E1: =Descriptif!$AD$3 -> 34 | F1: =Descriptif!$AF$3 -> 34
A2: Pluvio SCL | B2: =Descriptif!$AH$2 -> 23 | C2: =Descriptif!$AI$2 -> 23 | D2: Puvio STEU | E2: =Descriptif!$AH$3 -> 43 | F2: =Descriptif!$AI$3 -> 43
A3: Type Equipement | B3: Type
B4: cellule typeE | C4: cellule score global | D4: cellule eval global | E4: cellule commentaire score | F4: cellule commentaire
